Workbook
Name Rev.: 表紙!$U$22
Name Ver.: 表紙!$AE$26
Name ご確認者: 表紙!$AG$40
Name ご確認日: 表紙!$AG$42
Name サブシステム名: 表紙!$U$28
Name システム名: 表紙!$U$26
Name プロジェクト名: 表紙!$U$18
Name 開発区分: 表紙!$U$36
Name 機能ＩＤ: 表紙!$U$32
Name 機能区分: 表紙!$U$34
Name 機能名称: 表紙!$U$30
Name 顧客名: 表紙!$U$16
Name 最終更新者: 表紙!$AB$40
Name 最終更新日: 表紙!$AB$42
Name 作成者: 表紙!$W$40
Name 作成日: 表紙!$W$42
Name 章: 表紙!$M$10
Name 文書名: 表紙!$M$10

Sheet 目次
A1: アドオン設計書作成ガイド
C3: ■アドオン設計と成果物について
D4: ・システム設計フェーズとソフトウェア設計フェーズでアドオンの処理仕様を定義する
D5: ・システム設計フェーズとソフトウェア設計フェーズの成果物がアドオン設計書であり、ソフトウェア製作フェーズのインプットとなる
C7: ■各設計フェーズ毎のアドオン設計書作成範囲
D8: ・システム設計フェーズ：他機能との関連を定義するとともに、画面や帳票、ファイル入出力を中心とした外部入出力の設計を行う
D9: ・ソフトウェア設計フェーズ：内部処理を中心とした設計を行う
U11: ◎ | W11: … | X11: システム設計フェーズで作成
U12: ○ | W12: … | X12: システム設計フェーズで基本仕様を定義して、ソフトウェア設計フェーズで詳細化する
U13: △ | W13: … | X13: 必要に応じて（例えば標準仕様から変更がない場合は不要）
U14: ‐ | W14: … | X14: 不要
W15: … | X15: ソフトウェア設計フェーズで作成
D17: 各設計書と作成対象シートのマトリックス | S17: ※カスタマイズ：標準機能に機能を追加する アドオン：新規で機能を開発する
D18: EXCELシート | N18: 画面設計書 | W18: バッチ設計書 | AF18: 帳票設計書 | AO18: ＢＩ設計書 | AT18: .Net設計書 | BB18: EXCELシート | BL18: WebDB設計書 | BR18: 帳票設計書 | BX18: 汎用申請設計書
N19: カスタマイズ | S19: アドオン | W19: カスタマイズ | AB19: アドオン | AF19: カスタマイズ | AK19: アドオン | AO19: アドオン | AT19: アドオン | BL19: アドオン | BR19: アドオン | BX19: アドオン
D20: 概要 | N20: ◎ | O20: ※1 | S20: ◎ | W20: ◎ | X20: ※1 | AB20: ◎ | AF20: ◎ | AG20: ※1 | AK20: ◎ | AO20: ◎ | AT20: ◎ | BB20: 機能概要 | BL20: ◎ | BR20: ◎ | BX20: ◎
D21: レイアウト | N21: ◎ | O21: ※2 | S21: ◎ | W21: ‐ | AB21: ‐ | AF21: ◎ | AG21: ※2 | AK21: ◎ | AO21: ◎ | AT21: ◎ | BB21: アプリケーションフロー | BL21: ◎ | BR21: ー | BX21: ◎
D22: 項目説明 | N22: △ | S22: ○ | W22: ‐ | AB22: ‐ | AF22: △ | AK22: ○ | AO22: ○ | AT22: ○ | BB22: データベース設定 | BL22: ◎ | BR22: ー | BX22: ◎
D23: 引数説明 | N23: ‐ | S23: ‐ | W23: △ | AB23: ◎ | AF23: ‐ | AK23: ‐ | AO23: ‐ | AT23: ◎ | BB23: フィールド設定 | BL23: ◎ | BR23: ー | BX23: ◎
D24: 処理概要 | N24: ◎ | S24: ◎ | W24: ◎ | AB24: ◎ | AF24: ◎ | AK24: ◎ | AO24: ◎ | AT24: ◎ | BB24: 一覧表示画面設定 | BL24: ◎ | BR24: ー | BX24: ◎
D25: 処理詳細 | BB25: 表示編集画面設定 | BL25: ◎ | BR25: ー | BX25: ◎
D26: 処理・サービス関連図 | N26: △ | S26: ◎ | W26: △ | AB26: ◎ | AF26: ‐ | AK26: ‐ | AO26: ‐ | AT26: ◎ | BB26: 明細画面設定 | BL26: △ | BN26: ※3 | BR26: ー | BX26: △ | BZ26: ※3
D27: 検索入出力仕様 | N27: △ | S27: ○ | W27: △ | AB27: ○ | AF27: ‐ | AK27: ‐ | AO27: ‐ | AT27: ○ | BB27: 集計表示設定 | BL27: △ | BN27: ※4 | BR27: ー | BX27: △ | BZ27: ※4
D28: 更新入出力仕様 | N28: △ | S28: ○ | W28: △ | AB28: ○ | AF28: ‐ | AK28: ‐ | AO28: ‐ | AT28: ○ | BB28: 絞り込み条件設定 | BL28: △ | BN28: ※5 | BR28: ー | BX28: △ | BZ28: ※5
D29: ファイル入出力仕様 | N29: △ | S29: △ | W29: ‐ | AB29: ‐ | AF29: ‐ | AK29: ‐ | AO29: ‐ | AT29: △ | BB29: その他設定 | BR29: ー
D30: 画面遷移 | N30: △ | S30: ◎ | W30: ‐ | AB30: ‐ | AF30: ‐ | AK30: ‐ | AO30: ‐ | AT30: ◎ | BB30: 帳票イメージ | BL30: ー | BR30: ◎ | BX30: ー
D31: メッセージ一覧 | N31: △ | S31: △ | W31: △ | AB31: △ | AF31: ‐ | AK31: ‐ | AO31: ‐ | AT31: △ | BB31: 項目設計 | BL31: ー | BR31: ◎ | BX31: ー
D32: 補足説明 | N32: △ | S32: △ | W32: △ | AB32: △ | AF32: △ | AK32: △ | AO32: △ | AT32: △ | BB32: 補足説明 | BL32: △ | BR32: △ | BX32: △
D33: サービス呼出編集仕様 | N33: - | S33: - | W33: - | AB33: - | AF33: - | AK33: - | AO33: - | AT33: - | BB33: 補足説明(詳細)
D35: ※1 | G35: 別シートでカスタマイズ内容を記載する | BB35: ※3 | BE35: 単票画面は記載しない
D36: ※2 | G36: 吹き出しでカスタマイズ内容を記載する | BB36: ※4 | BE36: 集計・グラフ機能を使用する場合に記載する
BB37: ※5 | BE37: 共通設定のみ記載する(個別設定は、記載しない)

Sheet 表紙
AW2: サブモジュール
AW3: MA_マスタ管理
AW4: MB_業務共通
AW5: MG_原価管理
AW6: MSBA_需給管理
M7: 基本設計 | AW7: MSBB_販売管理
AW8: MSBC_生産管理
AW9: MSBD_購買管理
M10: アドオン設計書 | AW10: MSBE_在庫物流管理
AW11: MSBF_品質管理
AW12: MSBG_債権管理
AW13: MSBH_債務管理
AW14: MSBI_締処理
AW15: MSUA_リスト・入力補助
M16: 顧客 | U16: 株式会社クラウン・パッケージ | AW16: PF_ESBアダプタ
M18: プロジェクト名 | U18: 基幹システム刷新PJ | AW18: 機能区分
AW19: 画面
M20: 文書番号 | AW20: 帳票
AW21: バッチ
M22: Ｒｅｖ． | U22: {=MAX(_xlfn.NUMBERVALUE(改訂!A7:E48))} -> 1 | AW22: マスタ
M24: 機密性区分 | U24: 取扱注意（Ｃ） | AW24: 開発区分
AW25: カスタマイズ
M26: システム名 | U26: mcframe7 | AC26: Ver. | AE26: 7.0.2 | AW26: アドオン
AW27: －
M28: サブモジュール | U28: MSBB_販売管理
M30: 機能名 | U30: =M50 -> 取引先マスタ連携
M32: 機能ID | U32: =G50 -> MSBBBA020
M34: 機能区分 | U34: バッチ
M36: 開発区分 | U36: アドオン
W39: 作成 | AB39: 最終更新 | AG39: ご確認
W40: MDSOL
W42: 44824
A48: 文書番号 | G48: 画面ID | M48: 画面名 | V48: Version | AB48: Revision
A50: M7-US-1140 | G50: MSBBBA020 | M50: 取引先マスタ連携 | V50: 1.0.0 | AB50: r01.00
A53: 共通（元データ）
A54: Webシステム・mcframe7 | K54: 文書名 | U54: モジュールID | Z54: MS | AE54: モジュール名 | AJ54: Webシステム | AS54: 文書番号 | AZ54: Version | BF54: Rev.
K55: 画面説明書 | U55: ｻﾌﾞﾓｼﾞｭｰﾙID | Z55: MSBB | AE55: ｻﾌﾞﾓｼﾞｭｰﾙ名 | AJ55: 販売Webシステム | AS55: M7-US-1140 | AZ55: 1.0.0 | BF55: r00.00
K56: 表紙 | U56: 表題 | Z56: MSBBBA020 | AE56: 取引先マスタ連携
A57: 共通（リンク用）
A58: =A54 -> Webシステム・mcframe7 | K58: 文書名 | U58: モジュールID | Z58: =Z54 -> MS | AE58: モジュール名 | AJ58: =AJ54 -> Webシステム | AS58: 文書番号 | AZ58: Version | BF58: Rev.
K59: =文書名 -> アドオン設計書 | U59: ｻﾌﾞﾓｼﾞｭｰﾙID | Z59: =Z55 -> MSBB | AE59: ｻﾌﾞﾓｼﾞｭｰﾙ名 | AJ59: =AJ55 -> 販売Webシステム | AS59: =AS55 -> M7-US-1140 | AZ59: =AZ55 -> 1.0.0 | BF59: =BF55 -> r00.00
K60: =RIGHT(CELL("filename",$A$1),LEN(CELL("filename",$A$1))-FIND("]",CELL("filename",$A$1))) -> 表紙 | U60: 表題 | Z60: =Z56 -> MSBBBA020 | AE60: =AE56 -> 取引先マスタ連携
A62: 概要シート用
A63: =A58 -> Webシステム・mcframe7 | O63: 文書名 | AC63: モジュールID | AJ63: =Z58 -> MS | AQ63: モジュール名 | AX63: =AJ58 -> Webシステム | BL63: 文書番号 | BU63: Version | CB63: Rev.
O64: =K59 -> アドオン設計書 | AC64: サブモジュールID | AJ64: =Z59 -> MSBB | AQ64: サブモジュール名 | AX64: =AJ59 -> 販売Webシステム | BL64: =AS59 -> M7-US-1140 | BU64: 7.0.2 | CB64: {=MAX(_xlfn.NUMBERVALUE(改訂!A7:E48))} -> 1
O65: =RIGHT(CELL("filename",$A$1),LEN(CELL("filename",$A$1))-FIND("]",CELL("filename",$A$1))) -> 表紙 | AC65: 表題 | AJ65: =Z60 -> MSBBBA020 | AQ65: =AE60 -> 取引先マスタ連携

Sheet 改訂
A1: 第7章 | K1: 改訂 | AU1: 作成者 | AZ1: MDSOL | BE1: 作成日 | BJ1: =表紙!W42 -> 44824 | BP1: Rev.
AU2: 修正者 | BE2: 改訂日 | BP2: =表紙!CB64 -> 1
A5: Rev. | F5: 改定内容 | BC5: 頁 | BM5: 変更日 変更者 | BR5: 確認日 確認者
A7: 1 | F7: 新規作成

Sheet 概要
A1: =表紙!A54 -> Webシステム・mcframe7 | O1: 文書名 | AC1: モジュールID | AJ1: =表紙!AJ63 -> MS | AQ1: モジュール名 | AX1: =表紙!AX63 -> Webシステム | BL1: 文書番号 | BU1: Version | CB1: Rev.
O2: =表紙!O64 -> アドオン設計書 | AC2: サブモジュールID | AJ2: =表紙!AJ64 -> MSBB | AQ2: サブモジュール名 | AX2: =表紙!AX64 -> 販売Webシステム | BL2: =表紙!BL64 -> M7-US-1140 | BU2: =表紙!BU64 -> 7.0.2 | CB2: =表紙!CB64 -> 1
O3: =RIGHT(CELL("filename",$A$1),LEN(CELL("filename",$A$1))-FIND("]",CELL("filename",$A$1))) -> 概要 | AC3: 表題 | AJ3: =表紙!AJ65 -> MSBBBA020 | AQ3: =表紙!AQ65 -> 取引先マスタ連携
AO5: 概要
B7: 【業務要件】
C8: カスタマイズ | G8: 内容
C9: No.
C10: 4 | G10: 見積Webシステムを構築する
H11: 主要機能
H12: ⑦得意先マスタ | M12: ・・・＞ | O12: システム設計フェーズ変更点：得意先→取引先
C14: 35 | G14: 消込条件追加
H15: ①取引先の口座を管理する(得意先マスタ項目追加:得意先マスタのアドオンに含む)
C17: 75 | G17: 取引先マスタのmcframeへの連携
H18: Webにて取引先マスタ(得意先マスタ)を実装する
C20: 40 | G20: 発注一覧登録、発注登録 共通帳票印刷共通ロジック
H21: 発注先のFSC認証番号(取引先マスタ 発注先タブのメモ３)の取得、出力 | AD21: ・・・＞mcframe7 メモ3に連携する
B24: 【機能概要】
C25: Web取引先の情報をmcframe7取引先マスタへ転送する
C26: web取引先マスタから取引先マスタ、得意先担当マスタ、口座マスタへデータ転送する
B28: 【前提条件】
C29: 1. | D29: ジョブスケジューラにより実行する
C30: 2. | D30: 与信限度額マスタへの連携は実施しない
D31: →mcframe7の機能にて登録する
C32: 3. | D32: 削除連携は、論理削除の連携とする
B34: 【説明】
C35: Web取引先マスタ情報をmcframe7の取引先マスタに連携する。
C36: ※得意先→取引先(買い側)含めた連携となった
C40: 新規時
C54: 更新時
C64: 削除時
B74: 【目的】
C75: Web取引先マスタ情報をmcframe7の取引先マスタに連携する
B77: 【処理関連図/サービス関連図】
C78: ※処理・サービス関連図シートに詳細記載
B80: 【自由記述】
C81: なし

Sheet IF概要
A1: =表紙!A54 -> Webシステム・mcframe7 | K1: 文書名 | U1: モジュールID | Z1: =表紙!$AJ$63 -> MS | AE1: モジュール名 | AJ1: =表紙!$AX$63 -> Webシステム | AS1: 文書番号 | AZ1: Version | BF1: Rev.
K2: =表紙!O64 -> アドオン設計書 | U2: ｻﾌﾞﾓｼﾞｭｰﾙID | Z2: =表紙!$AJ$64 -> MSBB | AE2: ｻﾌﾞﾓｼﾞｭｰﾙ名 | AJ2: =表紙!$AX$64 -> 販売Webシステム | AS2: =表紙!$BL$64 -> M7-US-1140 | AZ2: =表紙!$BU$64 -> 7.0.2 | BF2: =表紙!$CB$64 -> 1
K3: =RIGHT(CELL("filename",$A$1),LEN(CELL("filename",$A$1))-FIND("]",CELL("filename",$A$1))) -> IF概要 | U3: 表題 | Z3: =表紙!$AJ$65 -> MSBBBA020 | AE3: =表紙!$AQ$65 -> 取引先マスタ連携

Sheet 処理・サービス関連図
A1: =表紙!A54 -> Webシステム・mcframe7 | K1: 文書名 | U1: モジュールID | Z1: =表紙!$AJ$63 -> MS | AE1: モジュール名 | AJ1: =表紙!$AX$63 -> Webシステム | AS1: 文書番号 | AZ1: Version | BF1: Rev.
K2: =表紙!O64 -> アドオン設計書 | U2: ｻﾌﾞﾓｼﾞｭｰﾙID | Z2: =表紙!$AJ$64 -> MSBB | AE2: ｻﾌﾞﾓｼﾞｭｰﾙ名 | AJ2: =表紙!$AX$64 -> 販売Webシステム | AS2: =表紙!$BL$64 -> M7-US-1140 | AZ2: =表紙!$BU$64 -> 7.0.2 | BF2: =表紙!$CB$64 -> 1
K3: =RIGHT(CELL("filename",$A$1),LEN(CELL("filename",$A$1))-FIND("]",CELL("filename",$A$1))) -> 処理・サービス関連図 | U3: 表題 | Z3: =表紙!$AJ$65 -> MSBBBA020 | AE3: =表紙!$AQ$65 -> 取引先マスタ連携
C7: 検索処理
C21: 登録・更新処理

Sheet 処理概要
A1: =表紙!A54 -> Webシステム・mcframe7 | K1: 文書名 | U1: モジュールID | Z1: =表紙!$AJ$63 -> MS | AE1: モジュール名 | AJ1: =表紙!$AX$63 -> Webシステム | AS1: 文書番号 | AZ1: Version | BF1: Rev.
K2: =表紙!O64 -> アドオン設計書 | U2: ｻﾌﾞﾓｼﾞｭｰﾙID | Z2: =表紙!$AJ$64 -> MSBB | AE2: ｻﾌﾞﾓｼﾞｭｰﾙ名 | AJ2: =表紙!$AX$64 -> 販売Webシステム | AS2: =表紙!$BL$64 -> M7-US-1140 | AZ2: =表紙!$BU$64 -> 7.0.2 | BF2: =表紙!$CB$64 -> 1
K3: =RIGHT(CELL("filename",$A$1),LEN(CELL("filename",$A$1))-FIND("]",CELL("filename",$A$1))) -> 処理概要 | U3: 表題 | Z3: =表紙!$AJ$65 -> MSBBBA020 | AE3: =表紙!$AQ$65 -> 取引先マスタ連携
A5: No | B5: 入力 | J5: 処理（取引先マスタ連携） | AZ5: 出力
A6: 1 | B6: 初期処理
K8: １．処理開始メッセージをログに出力する。 | AZ8: サーバログ
K9: ２．WEB取引先マスタのmcframe7転送FLG=0 ANDのデータを抽出する。 | AZ9: 内部ワーク
A12: 2 | B12: データ出力
K14: １．取引先出力定義.txtを読込み、転送定義を取得する
K15: ２．初期処理で抽出したWEB取引先マスタから各マスタへデータを転送する | AZ15: 取引先マスタ入出力仕様.NO1
M16: 取引先マスタ、得意先担当マスタ、口座マスタ | AZ16: 得意先担当マスタ入出力仕様.NO1
AZ17: 口座マスタ入出力仕様.NO1
L19: 取引先マスタ連携は、固定値の転送項目があるため、取引先出力定義.txtを用意し、固定値を設定できるようにする
M20: →DB項目と固定値項目に関して：取引先出力定義.txtを読込み設定する
AB22: 例：マスタ入力定義 住所１、通貨項目
AC23: 取引先出力定義テキストに下記のように定義しDB項目、固定値を取得する
AC24: 取引先出力定義.txt
AD25: # 転送項目
AD26: 通貨=JPY | AL26: …固定値の場合
AD27: 住所１=@都道府県@ | AL27: …DB項目の場合
AD28: 固定値は、値を記述、DB項目は、@[DB名]@で指定する
A48: 2 | B48: テーブル更新
K50: １．初期処理で抽出したデータのmcframe7転送FLG、mcframe7転送日時を更新する | AZ50: 更新入出力仕様.NO1
K51: (抽出したWEB取引先マスタの取引先CDをキーに更新する)
A53: 3 | B53: 終了処理
K55: １．出力したデータ件数をログに出力する。 | AZ55: サーバログ
M56: 取引先IFデータ出力件数：nnn件
K58: ２．処理終了メッセージをログに出力する。 | AZ58: サーバログ

Sheet 引数説明
A1: =表紙!A54 -> Webシステム・mcframe7 | K1: 文書名 | U1: モジュールID | Z1: =表紙!$AJ$63 -> MS | AE1: モジュール名 | AJ1: =表紙!$AX$63 -> Webシステム | AS1: 文書番号 | AZ1: Version | BF1: Rev.
K2: =表紙!O64 -> アドオン設計書 | U2: ｻﾌﾞﾓｼﾞｭｰﾙID | Z2: =表紙!$AJ$64 -> MSBB | AE2: ｻﾌﾞﾓｼﾞｭｰﾙ名 | AJ2: =表紙!$AX$64 -> 販売Webシステム | AS2: =表紙!$BL$64 -> M7-US-1140 | AZ2: =表紙!$BU$64 -> 7.0.2 | BF2: =表紙!$CB$64 -> 1
K3: =RIGHT(CELL("filename",$A$1),LEN(CELL("filename",$A$1))-FIND("]",CELL("filename",$A$1))) -> 引数説明 | U3: 表題 | Z3: =表紙!$AJ$65 -> MSBBBA020 | AE3: =表紙!$AQ$65 -> 取引先マスタ連携
B5: オペレーションＩＤ/名称：取引先マスタ連携/取込
A6: 必 | B6: 項目名 | N6: 説明 | AS6: 未設定時の振る舞い
C7: 引数無し

Sheet 取引先マスタ入出力仕様
A1: =表紙!A54 -> Webシステム・mcframe7 | K1: 文書名 | U1: モジュールID | Z1: =表紙!$AJ$63 -> MS | AE1: モジュール名 | AJ1: =表紙!$AX$63 -> Webシステム | AS1: 文書番号 | AZ1: Version | BF1: Rev.
K2: =表紙!O64 -> アドオン設計書 | U2: ｻﾌﾞﾓｼﾞｭｰﾙID | Z2: =表紙!$AJ$64 -> MSBB | AE2: ｻﾌﾞﾓｼﾞｭｰﾙ名 | AJ2: =表紙!$AX$64 -> 販売Webシステム | AS2: =表紙!$BL$64 -> M7-US-1140 | AZ2: =表紙!$BU$64 -> 7.0.2 | BF2: =表紙!$CB$64 -> 1
K3: =RIGHT(CELL("filename",$A$1),LEN(CELL("filename",$A$1))-FIND("]",CELL("filename",$A$1))) -> 取引先マスタ入出力仕様 | U3: 表題 | Z3: =表紙!$AJ$65 -> MSBBBA020 | AE3: =表紙!$AQ$65 -> 取引先マスタ連携
A5: No | G5: 1 | S5: ロジック名称 | AH5: 備考 | BM5: CP指摘 2022/11/1 本多 新シート単価適用基準（0：受注日 1：納入日）を項目追加 願います。 | BX5: MDSOL回答 2022/11/04 MCF側からの参照は、VIEW参照となります。(MCFには項目追加せずに、VIEW参照する) | DG5: 2022/11/07 落合 問題なし。当該機能には不要と認識しました。
A6: 処理分類 | E6: 更新 | BM6: 説明 1：納入日基準の場合、日次処理日にて新単価適用日に該当した場合、特値扱いされていない、かつ売上確定していない、受注データ、出荷データの単価を新単価へ更新する。 | BX6: WEB取引先マスタには、項目追加しました。
A7: No | C7: 転送先 | V7: 転送元 | AQ7: 備考
C8: 種 | D8: オブジェクト | K8: 項目名 | V8: 種 | W8: オブジェクト | AF8: 項目名 | BM8: 説明 | BN8: 値の制限 | BO8: 設定仕様 | BP8: 未設定時の振る舞い | BR8: 区
A9: 1 | C9: T | D9: 取引先マスタ（共通） | K9: 取引先ＣＤ | V9: T | W9: WEB取引先マスタ | AF9: 取引先ＣＤ | BM9: 取引先を表すＣＤ
A10: 2 | C10: T | D10: 取引先マスタ（共通） | K10: 取引先名 | V10: T | W10: WEB取引先マスタ | AF10: 取引先略称 | BM10: 取引先に対する名称
A11: 3 | C11: T | D11: 取引先マスタ（共通） | K11: 取引先別名１ | V11: T | W11: WEB取引先マスタ | AF11: 取引先名 | BM11: 取引先に対する別名 標準機能ではマスタに登録できるだけで、設定した値が使用される機能はない ※会計Link機能によっては会計システムに連携される
A12: 4 | C12: T | D12: 取引先マスタ（共通） | K12: 取引先別名２ | V12: T | W12: WEB取引先マスタ | AF12: 取引先別名２ | AQ12: 使用しない | BM12: 取引先に対する別名 標準機能ではマスタに登録できるだけで、設定した値が使用される機能はない ※会計Link機能によっては会計システムに連携される
A13: 5 | C13: T | D13: 取引先マスタ（共通） | K13: 取引先別名３ | V13: T | W13: WEB取引先マスタ | AF13: 取引先別名３ | AQ13: 使用しない | BM13: 取引先に対する別名 標準機能ではマスタに登録できるだけで、設定した値が使用される機能はない ※会計Link機能によっては会計システムに連携される
A14: 6 | C14: T | D14: 取引先マスタ（共通） | K14: 取引先別名４ | V14: T | W14: WEB取引先マスタ | AF14: 取引先別名４ | AQ14: 使用しない | BM14: 取引先に対する別名 標準機能ではマスタに登録できるだけで、設定した値が使用される機能はない ※会計Link機能によっては会計システムに連携される
A15: 7 | C15: T | D15: 取引先マスタ（共通） | K15: 郵便番号 | V15: T | W15: WEB取引先マスタ | AF15: 郵便番号 | AQ15: 画面 | AS15: 郵便番号 | BM15: 取引先に対する郵便番号 帳票に表示する値を設定する | BN15: 半角大文字アルファベット、半角数字、半角スペース、「-」から成り立つ文字列
A16: 8 | C16: T | D16: 取引先マスタ（共通） | K16: 住所１ | V16: T | W16: WEB取引先マスタ | AF16: 都道府県 | AQ16: 画面 | AS16: 都道府県 | BM16: 取引先に対する住所 帳票に表示する値を設定する
A17: 9 | C17: T | D17: 取引先マスタ（共通） | K17: 住所２ | V17: T | W17: WEB取引先マスタ | AF17: 市区町村 | AQ17: 画面 | AS17: 市区町村 | BM17: 取引先に対する住所 帳票に表示する値を設定する
A18: 10 | C18: T | D18: 取引先マスタ（共通） | K18: 住所３ | V18: T | W18: WEB取引先マスタ | AF18: 町域・番地 | AQ18: 画面 | AS18: 町域・番地 | BM18: 取引先に対する住所 帳票に表示する値を設定する
A19: 11 | C19: T | D19: 取引先マスタ（共通） | K19: 住所４ | V19: T | W19: WEB取引先マスタ | AF19: 建物など | AQ19: 画面 | AS19: 建物など | BM19: 取引先に対する住所 帳票に表示する値を設定する
A20: 12 | C20: T | D20: 取引先マスタ（共通） | K20: ＴＥＬ | V20: T | W20: WEB取引先マスタ | AF20: ＴＥＬ | AQ20: 画面 | AS20: ＴＥＬ | BM20: 取引先に対する電話番号 帳票に表示する値を設定する | BN20: 「+」、「-」、半角スペース、「(」、「)」、半角数字から成り立つ文字列
A21: 13 | C21: T | D21: 取引先マスタ（共通） | K21: ＦＡＸ | V21: T | W21: WEB取引先マスタ | AF21: ＦＡＸ | AQ21: 画面 | AS21: ＦＡＸ | BM21: 取引先に対するＦＡＸ番号 帳票に表示する値を設定する | BN21: 「+」、「-」、半角スペース、「(」、「)」、半角数字から成り立つ文字列
A22: 14 | C22: T | D22: 取引先マスタ（共通） | K22: 法人番号 | V22: T | W22: WEB取引先マスタ | AF22: 法人番号 | AQ22: 画面 | AS22: 法人番号 | BM22: 取引先に対する法人番号
A23: 15 | C23: T | D23: 取引先マスタ（共通） | K23: 標準企業コード | V23: T | W23: WEB取引先マスタ | AF23: 標準企業コード | AQ23: 画面 | AS23: 標準企業コード | BM23: 各種業界における統一された企業コード 納品書など社外帳票に出力する際に使用することを想定している
A24: 16 | C24: T | D24: 取引先マスタ（共通） | K24: 国ＣＤ | AF24: 固定：JP | AQ24: ※国内取引 | BM24: 取引先に対する国ＣＤ | BN24: 国マスタに登録されている国ＣＤ
A25: 17 | C25: T | D25: 取引先マスタ（共通） | K25: 地域ＣＤ | V25: T | W25: WEB取引先マスタ | AF25: 地域ＣＤ | AQ25: 画面 | AS25: 地域ＣＤ | BM25: 取引先に対する地域ＣＤ 集計処理や検索条件として使用される | BN25: 地域マスタに登録されている地域ＣＤ
A26: 18 | C26: T | D26: 取引先マスタ（共通） | K26: 通貨ＣＤ | AF26: 固定：JPY | AQ26: ※国内取引 | BM26: 取引先に対する基準通貨ＣＤ | BN26: 通貨マスタに登録されている通貨ＣＤ
A27: 19 | C27: T | D27: 取引先マスタ（共通） | K27: 帳票出力ロケールＣＤ | AF27: 固定：ja_jp | BM27: 注文書や見積書など社外帳票を出力する際に使用するロケールＣＤ ※ロケールＣＤに対する名称が表示される ※指定しない場合はトリガで会社基本マスタ（FrameManager)の標準ロケールＣ Ｄが設定される | BN27: MCConfigのロケールエントリーに存在するロケールＣＤ
A28: 20 | C28: T | D28: 取引先マスタ（共通） | K28: 取引先分類ＣＤ１ | V28: T | W28: WEB取引先マスタ | AF28: 取引先分類ＣＤ１ | AQ28: 画面 | AS28: 取引先分類ＣＤ１ | BM28: 取引先対する取引先分類ＣＤ１ | BN28: 取引先分類マスタに取引先分類区分が1で登録されている取引先分類ＣＤ
A29: 21 | C29: T | D29: 取引先マスタ（共通） | K29: 取引先分類ＣＤ２ | V29: T | W29: WEB取引先マスタ | AF29: 取引先分類ＣＤ２ | AQ29: 画面 | AS29: 取引先分類ＣＤ２ | BM29: 取引先対する取引先分類ＣＤ２ | BN29: 取引先分類マスタに取引先分類区分が2で登録されている取引先分類ＣＤ
A30: 22 | C30: T | D30: 取引先マスタ（共通） | K30: 取引先分類ＣＤ３ | V30: T | W30: WEB取引先マスタ | AF30: 取引先分類ＣＤ３ | AQ30: 画面 | AS30: 取引先分類ＣＤ３ | BM30: 取引先対する取引先分類ＣＤ３ | BN30: 取引先分類マスタに取引先分類区分が3で登録されている取引先分類ＣＤ
A31: 23 | C31: T | D31: 取引先マスタ（共通） | K31: 取引先分類ＣＤ４ | V31: T | W31: WEB取引先マスタ | AF31: 取引先分類ＣＤ４ | AQ31: 画面 | AS31: 取引先分類ＣＤ４ | BM31: 取引先対する取引先分類ＣＤ４ | BN31: 取引先分類マスタに取引先分類区分が4で登録されている取引先分類ＣＤ
A32: 24 | C32: T | D32: 取引先マスタ（共通） | K32: 取引先分類ＣＤ５ | V32: T | W32: WEB取引先マスタ | AF32: 取引先分類ＣＤ５ | AQ32: 画面 | AS32: 取引先分類ＣＤ５ | BM32: 取引先対する取引先分類ＣＤ５ | BN32: 取引先分類マスタに取引先分類区分が5で登録されている取引先分類ＣＤ
A33: 25 | C33: T | D33: 取引先マスタ（共通） | K33: 取引先分類ＣＤ６ | V33: T | W33: WEB取引先マスタ | AF33: 取引先分類ＣＤ６ | AQ33: 画面 | AS33: 取引先分類ＣＤ６ | BM33: 取引先対する取引先分類ＣＤ６ | BN33: 取引先分類マスタに取引先分類区分が6で登録されている取引先分類ＣＤ
A34: 26 | C34: T | D34: 取引先マスタ（共通） | K34: 取引先分類ＣＤ７ | V34: T | W34: WEB取引先マスタ | AF34: 取引先分類ＣＤ７ | AQ34: 画面 | AS34: 取引先分類ＣＤ７ | BM34: 取引先対する取引先分類ＣＤ７ | BN34: 取引先分類マスタに取引先分類区分が7で登録されている取引先分類ＣＤ
A35: 27 | C35: T | D35: 取引先マスタ（共通） | K35: 取引先分類ＣＤ８ | V35: T | W35: WEB取引先マスタ | AF35: 取引先分類ＣＤ８ | AQ35: 画面 | AS35: 取引先分類ＣＤ８ | BM35: 取引先対する取引先分類ＣＤ８ | BN35: 取引先分類マスタに取引先分類区分が8で登録されている取引先分類ＣＤ
A36: 28 | C36: T | D36: 取引先マスタ（共通） | K36: 取引先分類ＣＤ９ | V36: T | W36: WEB取引先マスタ | AF36: 取引先分類ＣＤ９ | AQ36: 画面 | AS36: 取引先分類ＣＤ９ | BM36: 取引先対する取引先分類ＣＤ９ | BN36: 取引先分類マスタに取引先分類区分が9で登録されている取引先分類ＣＤ
A37: 29 | C37: T | D37: 取引先マスタ（共通） | K37: 取引先分類ＣＤ１０ | V37: T | W37: WEB取引先マスタ | AF37: 取引先分類ＣＤ１０ | AQ37: 画面 | AS37: 取引先分類ＣＤ１０ | BM37: 取引先対する取引先分類ＣＤ１０ | BN37: 取引先分類マスタに取引先分類区分が10で登録されている取引先分類ＣＤ
A38: 30 | C38: T | D38: 取引先マスタ（共通） | K38: 取引先配賦グループ | AF38: NULL | BM38: 取引先に対する配賦グループ | BO38: 原価管理で取引先別に費用情報が登録される場合に使用される 取引先１及び取引先２の費用は数量配賦、取引先３の費用は金額配賦など、取引先別に配賦方法（配賦パタン）が異なる場合に、取引先ごとに異なる値を設定する ※同じ配賦方法（配賦パタン）となる取引先に対しては同じ値を設定する ※上記では取引先１と取引先２に同じ値を設定する | BP38: 取引先ごとに配賦パタンを決定しない
A39: 31 | C39: T | D39: 取引先マスタ（共通） | K39: 得意先ＦＬＧ | V39: T | W39: WEB取引先マスタ | AF39: 得意先ＦＬＧ
A40: 32 | C40: T | D40: 取引先マスタ（共通） | K40: 売掛先ＦＬＧ | V40: T | W40: WEB取引先マスタ | AF40: 売掛先ＦＬＧ
A41: 33 | C41: T | D41: 取引先マスタ（共通） | K41: 請求先ＦＬＧ | V41: T | W41: WEB取引先マスタ | AF41: 請求先ＦＬＧ
A42: 34 | C42: T | D42: 取引先マスタ（共通） | K42: 入金先ＦＬＧ | V42: T | W42: WEB取引先マスタ | AF42: 入金先ＦＬＧ
A43: 35 | C43: T | D43: 取引先マスタ（共通） | K43: 発注先ＦＬＧ | V43: T | W43: WEB取引先マスタ | AF43: 発注先ＦＬＧ | BN43: 配送先ＦＬＧが設定されている場合は入力不可（常に０）
A44: 36 | C44: T | D44: 取引先マスタ（共通） | K44: 買掛先ＦＬＧ | V44: T | W44: WEB取引先マスタ | AF44: 買掛先ＦＬＧ
A45: 37 | C45: T | D45: 取引先マスタ（共通） | K45: 支払予定管理先ＦＬＧ | V45: T | W45: WEB取引先マスタ | AF45: 支払予定管理先ＦＬＧ
A46: 38 | C46: T | D46: 取引先マスタ（共通） | K46: 支払先ＦＬＧ | V46: T | W46: WEB取引先マスタ | AF46: 支払先ＦＬＧ
A47: 39 | C47: T | D47: 取引先マスタ（共通） | K47: 与信管理先ＦＬＧ | V47: T | W47: WEB取引先マスタ | AF47: 与信管理先ＦＬＧ
A48: 40 | C48: T | D48: 取引先マスタ（共通） | K48: 納品先ＦＬＧ | V48: T | W48: WEB取引先マスタ | AF48: 納品先ＦＬＧ
A49: 41 | C49: T | D49: 取引先マスタ（共通） | K49: メーカＦＬＧ | V49: T | W49: WEB取引先マスタ | AF49: メーカＦＬＧ
A50: 42 | C50: T | D50: 取引先マスタ（共通） | K50: 仕向先ＦＬＧ
A51: 43 | C51: T | D51: 取引先マスタ（共通） | K51: 全社ＦＬＧ | W51: システム設定 | BM51: 取引先マスタを会社共通で利用する場合に全社で利用可能かどうかを制御する フラグ | BP51: 全社で使用可能とする場合に1を設定する 個社単位で制御する場合は取引先会社マスタを設定する
A52: 44 | C52: T | D52: 取引先マスタ（共通） | K52: 売掛先ＣＤ | V52: T | W52: WEB取引先マスタ | AF52: 売掛先ＣＤ | AQ52: 画面 | AS52: 売掛先ＣＤ | BM52: 得意先に対する売掛先 | BN52: 取引先マスタで売掛先ＦＬＧが設定されている取引先ＣＤ | BO52: 得意先項目（必須） | BR52: 得
A53: 45 | C53: T | D53: 取引先マスタ（共通） | K53: 債権部門区分 | AF53: 固定：1（1：売上部門） | BM53: 債権（売掛金）を管理する部門を制御する区分 | BN53: 定数：債権部門区分 1：売上部門 2：債権部門 | BO53: 得意先項目（必須） 売上部門を債権部門として引き継ぐ場合は1を設定する 得意先に対して設定する債権部門とする場合は2を設定する | BR53: 得
A54: 46 | C54: T | D54: 取引先マスタ（共通） | K54: 債権部門ＣＤ | AF54: NULL | BM54: 債権（売掛金）を管理する部門ＣＤ | BN54: 部門マスタで債権ＦＬＧが設定されている部門ＣＤ 請求部門区分に2を設定した場合に入力可（必須） 上記以外は入力不可（常にNULL） | BO54: 得意先項目（任意） | BR54: 得
A55: 47 | C55: T | D55: 取引先マスタ（共通） | K55: 得意先部署 | V55: T | W55: WEB取引先マスタ | AF55: 得意先部署 | AQ55: 画面 | AS55: 得意先部署 | BM55: 得意先に対する部署名 帳票に得意先の情報を出力する際に使用される | BO55: 得意先項目（任意） | BP55: 得意先部署を出力しない | BR55: 得
A56: 48 | C56: T | D56: 取引先マスタ（共通） | K56: 得意先担当者 | V56: T | W56: WEB取引先マスタ | AF56: 得意先担当者 | AQ56: 画面 | AS56: 得意先担当者 | BM56: 得意先に対する担当者名 帳票に得意先の情報を出力する際に使用される | BO56: 得意先項目（任意） | BP56: 得意先担当者を出力しない | BR56: 得
A57: 49 | C57: T | D57: 取引先マスタ（共通） | K57: 得意先担当者敬称 | V57: T | W57: WEB取引先マスタ | AF57: 得意先担当者敬称 | AQ57: 画面 | AS57: 得意先担当者敬称 | BM57: 得意先に対する担当者敬称 帳票に得意先の情報を出力する際に使用される | BO57: 得意先項目（任意） | BP57: 得意先担当者敬称を出力しない | BR57: 得
A58: 50 | C58: T | D58: 取引先マスタ（共通） | K58: 得意先諸口ＦＬＧ | AF58: 固定：FALSE | BM58: 案件登録、見積登録で諸口（＊）の得意先ＣＤとして扱うことを制御するフラ グ （＊）案件登録、見積登録で得意先名を任意の値に変更できる 得意先諸口が設定されている場合は受注登録や出荷・売上登録ができない ※案件登録、見積登録でのみ使用可能 | BO58: 得意先項目 | BR58: 得
A59: 51 | C59: T | D59: 取引先マスタ（共通） | K59: 販売単価取得区分 | AF59: NULL | BM59: 販売単価を取得する際の基準日を制御する区分 | BN59: 定数：販売単価取得区分 1: 受注日 2: 希望納期 3: 売上予定日 | BO59: 得意先項目（任意） 受注日を基準として販売単価を取得する場合は1を設定する 希望納期を基準として販売単価を取得する場合は2を設定する 売上予定日を基準として販売単価を取得する場合は3を設定する | BP59: 会社マスタに登録されている販売単価取得区分を取得する | BR59: 得
A60: 52 | C60: T | D60: 取引先マスタ（共通） | K60: 販売単価変更許可ＦＬＧ | AF60: 固定：TRUE | BM60: 受注時の単価及び仮単価フラグを変更可能にするかどうかを制御するフラグ 対象機能 ・受注登録 ・構成仕様登録 ・輸出インボイス登録 ・売上登録（受注なし売上） ※見積登録時は設定によらず常に変更可 | BO60: 得意先項目 ある得意先・品目の受注に対して取引先マスタの販売単価変更許可ＦＬＧ、品目マスタの販売単価変更許可ＦＬＧのどちらも設定されていない場合は、受注時の販売単価は変更不可となる ※上記の場合はマスタが必須となり、マスタから単価情報が取得できない場合は受注登録できない | BR60: 得
A61: 53 | C61: T | D61: 取引先マスタ（共通） | K61: 販売単価端数処理区分 | AF61: 固定：3 | BM61: 販売単価（単価×掛率）を計算する際の端数処理方法 | BN61: 定数：端数処理区分 1: 切り上げ 2: 切り捨て 3: 四捨五入 | BO61: 得意先項目（必須） | BR61: 得
A62: 54 | C62: T | D62: 取引先マスタ（共通） | K62: 売上金額端数処理区分 | AF62: 固定：3 | BM62: 売上金額（単価×数量）を計算する際の端数処理方法 | BN62: 定数：端数処理区分 1: 切り上げ 2: 切り捨て 3: 四捨五入 | BO62: 得意先項目（必須） | BR62: 得
A63: 55 | C63: T | D63: 取引先マスタ（共通） | K63: 売上税計算区分 | AF63: 固定：2 | BM63: 売上伝票に対する税計算を行う単位を制御する区分 ※請求締処理で請求書単位で税を再計算する場合は請求先に対する請求書単位 税計算フラグを設定する | BN63: 定数：税計算区分 1：行単位 2：伝票単位 | BO63: 得意先項目（必須） | BR63: 得
A64: 56 | C64: T | D64: 取引先マスタ（共通） | K64: 売上税額端数処理区分 | AF64: 固定：3 | BM64: 売上金額に対する税額を計算する際の端数処理方法 | BN64: 定数：端数処理区分 1: 切り上げ 2: 切り捨て 3: 四捨五入 | BO64: 得意先項目（必須） | BR64: 得
A65: 57 | C65: T | D65: 取引先マスタ（共通） | K65: 売上計上区分 | AF65: NULL | AQ65: ※会社マスタ設定 | BM65: 売上計上を行うタイミングを制御する区分 | BN65: 定数：売上計上区分 1：出荷基準 2：検収基準 3：着荷基準 | BO65: 得意先項目（任意） | BP65: 会社マスタに登録されている売上計上区分を参照する | BR65: 得
A66: 58 | C66: T | D66: 取引先マスタ（共通） | K66: 請求起算区分 | AF66: NULL | AQ66: ※会社マスタ設定 | BM66: 売上計上区分が出荷基準の際に請求締日を決定する際に使用される項目を制御 する区分 ※どの項目の日付をもとに請求締日と比較するかを制御する | BN66: 定数：請求起算区分 1：売上基準 2：納品基準 売上計上区分に「1：出荷基準」が設定されている場合は必須 売上計上区分に「2：検収基準」が設定されている場合は入力不可（1固定） 売上計上区分に「3：着荷基準」が設定されている場合は入力不可（2固定） 上記以外（売上計上区分が設定されていない場合）は入力不可（常にＮＵＬＬ） | BO66: 得意先項目（任意） 出荷基準の際に出荷計上日（売上計上日）をもとに請求締日を求める場合は1、納品予定日をもとに請求締日を求まる場合は2を設定する | BP66: 会社マスタに登録されている請求起算区分を参照する | BR66: 得
A67: 59 | C67: T | D67: 取引先マスタ（共通） | K67: 出荷予定分割区分 | AF67: NULL | AQ67: ※会社マスタ設定 | BM67: 出荷数を満たす在庫が引当できない場合に、引当済みの出荷予定と未引当の出 荷予定に分割するかどうかを制御する区分 | BN67: 定数：出荷予定分割区分 1：分割しない 2：分割する | BO67: 得意先項目（任意） 出荷数を満たす在庫引当ができない場合に未引当の出荷予定を作成しない場合は1、作成する場合は2を設定する ※作成しない場合は一部引当として管理され、引当済み分も出荷できない状態になる 全数引当されるまで出荷しない場合に1を設定する | BP67: 会社マスタに登録されている出荷予定分割区分を参照する | BR67: 得
A68: 60 | C68: T | D68: 取引先マスタ（共通） | K68: 請求繰越回数 | AF68: 固定：0 | BM68: 売上データが請求締の対象として含まれるまでに請求締処理が行われる回数 | BN68: 「0」～「99」 | BO68: 得意先項目（必須） 請求締日が10日、15日、20日、25日と設定されており、５日売上を20日請求締の対象とする場合は請求繰越回数に2を設定する 品目マスタに請求繰越回数が指定されている場合は、品目マスタの請求繰越回数が優先される | BR68: 得
A69: 61 | C69: T | D69: 取引先マスタ（共通） | K69: ロット逆転禁止区分 | AF69: 固定：1 | BM69: 出荷ロットに対する逆転チェック（ロットに指定された有効期限の逆転チェッ ク）を制御する区分 チェック対象の品目は品目マスタで出荷ロット逆転禁止フラグを指定する ※出荷ロット逆転禁止フラグが設定されていない品目はチェックされない | BN69: 定数：ロット逆転禁止区分 1：逆転可 2：逆転禁止（得意先） 3：逆転禁止（納品先） | BO69: 得意先項目（必須） 得意先に対する出荷ロットでチェックする場合は2、得意先・納品先に対する出荷ロットでチェックする場合は3を設定する | BR69: 得
A70: 62 | C70: T | D70: 取引先マスタ（共通） | K70: ロット明細分割区分 | AF70: 固定：1 | BM70: １受注明細に対して複数のロットＮＯ・サブロットＮＯを出荷する場合に、納 品書発行処理でロットＮＯ・サブロットＮＯごとに納品書明細を作成するかど うかを制御する区分 ※納品書明細の単位で売上実績が計上される ※売上金額（単価×数量）は売上実績の単位で計算される ※売上返品は対象外 | BN70: 定数：ロット明細分割区分 1：分割しない 2：ロットＮＯごと 3：ロットＮＯ・サブロットＮＯごと | BO70: 得意先項目（必須） 複数のロットＮＯ・サブロットＮＯを出荷する場合に、納品書明細を出力する方法を設定する 1：ロットＮＯ・サブロットＮＯごとに納品書明細を分割しない ※ロットＮＯ・サブロットＮＯを表示しない 2：ロットＮＯごとに納品書明細を作成する ※ロットＮＯを表示する、サブロットＮＯは表示しない 3：ロットＮＯ・サブロットＮＯごとに納品書明細を作成する | BR70: 得
A71: 63 | C71: T | D71: 取引先マスタ（共通） | K71: 得意先納品書ＣＤ | AF71: NULL | BM71: 得意先に対する納品書のフォームを示す伝票帳票ＣＤ | BN71: 伝票帳票マスタに登録されている伝票帳票ＣＤ 納品書として使用できる帳票ＩＤが指定されている伝票帳票ＣＤを指定する ※カスタマイズで帳票が追加されることもあるので、値の制限は行なっていない | BO71: 得意先項目（任意） 得意先ごとに納品書のフォーム・行数を変更したい場合に設定する | BP71: 取引マスタに登録されている伝票帳票ＣＤを参照する | BR71: 得
A72: 64 | C72: T | D72: 取引先マスタ（共通） | K72: 現品票発行ＦＬＧ | AF72: NULL | BM72: 得意先からの受注に対する納品物に現品票を付与するかどうかを制御する ※出荷指示時に現品票を発行可能となる | BO72: 得意先項目 | BR72: 得
A73: 65 | C73: T | D73: 取引先マスタ（共通） | K73: 現品票ＣＤ | AF73: NULL | BM73: 得意先からの受注に対する納品物に付与する現品票のフォームを示す伝票帳票 ＣＤ | BN73: 伝票帳票マスタに登録されている伝票帳票ＣＤ 現品票発行ＦＬＧが設定されている場合は必須 それ以外は入力不可 現品票して使用できる帳票ＩＤが指定されている伝票帳票ＣＤを指定する ※カスタマイズで帳票が追加されることもあるので、値の制限は行なっていない | BO73: 得意先項目（任意） | BR73: 得
A74: 66 | C74: T | D74: 取引先マスタ（共通） | K74: 売上税ＣＤ | AF74: NULL | BM74: 売上関連の取引で使用される税ＣＤ 売上税ＣＤを取得する際の優先順位 取引先の売上税優先ＦＬＧがオフ： 品目⇒取引先⇒会社 取引先の売上税優先ＦＬＧがオン： 取引先⇒品目⇒会社 | BN74: 税マスタで売上ＦＬＧが設定されている税ＣＤ | BO74: 得意先項目（任意） | BP74: 取引先マスタの売上税優先ＦＬＧがオフ： 会社補助マスタの売上税ＣＤを参照する 取引先マスタの売上税優先ＦＬＧがオン： 品目マスタ（品目補助マスタ）の売上税ＣＤを参照する | BR74: 得
A75: 67 | C75: T | D75: 取引先マスタ（共通） | K75: 売上税優先ＦＬＧ | AF75: NULL | BM75: 売上税ＣＤの取得を品目より優先することを制御するフラグ | BO75: 得意先項目 得意先に対する売上税ＣＤと品目マスタの売上税ＣＤが登録されている場合に得意先の売上税ＣＤを優先させる場合は1を設定する | BR75: 得
A76: 68 | C76: T | D76: 取引先マスタ（共通） | K76: 案件別債権管理ＦＬＧ | AF76: NULL | BM76: 債権管理（売掛／請求／入金管理）を案件別に行うかを制御するフラグ フラグを設定した場合は案件情報の債権管理フラグによらず、案件ごとに債権 管理を行う フラグを設定しない場合は案件情報の債権管理フラグに従って債権管理を行う | BO76: 得意先項目 | BR76: 得
A77: 69 | C77: T | D77: 取引先マスタ（共通） | K77: 得意先インボイス取引ＦＬＧ | AF77: NULL | BM77: 得意先に対して売上取引時にインボイスを用いた取引が必要になるかを制御す るフラグ | BO77: 得意先項目 インボイスを用いた取引とする場合に設定する | BR77: 得
A78: 70 | C78: T | D78: 取引先マスタ（共通） | K78: 出荷ＬＴ（需要情報用） | AF78: NULL | BM78: 需要情報作成処理で使用される。 顧客期間内示の納期や販売計画の日付から指定してリードタイムをもとに需要 期間が計算される。 ※顧客期間内示で得意先及び納品先から物流制御マスタが取得できる場合は、 物流制御マスタの設定（＊）が優先される。 （＊）移動ＬＴ、需要情報ＬＴを考慮しないＦＬＧ | BN78: 「0」以上の整数 | BO78: 得意先項目（任意） | BR78: 得
A79: 71 | C79: T | D79: 取引先マスタ（共通） | K79: 得意先取引条件ＣＤ１ | AF79: NULL | BM79: 得意先に対する取引条件ＣＤ | BN79: 取引条件マスタで取引条件区分に1が設定されている取引条件ＣＤ | BO79: 得意先項目（任意） | BR79: 得
A80: 72 | C80: T | D80: 取引先マスタ（共通） | K80: 得意先取引条件ＣＤ２ | AF80: NULL | BM80: 得意先に対する取引条件ＣＤ | BN80: 取引条件マスタで取引条件区分に2が設定されている取引条件ＣＤ | BO80: 得意先項目（任意） | BR80: 得
A81: 73 | C81: T | D81: 取引先マスタ（共通） | K81: 得意先取引条件ＣＤ３ | AF81: NULL | BM81: 得意先に対する取引条件ＣＤ | BN81: 取引条件マスタで取引条件区分に3が設定されている取引条件ＣＤ | BO81: 得意先項目（任意） | BR81: 得
A82: 74 | C82: T | D82: 取引先マスタ（共通） | K82: 販売分析ＣＤ１ | V82: T | W82: WEB取引先マスタ | AF82: 販売分析ＣＤ１ | AQ82: 画面 | AS82: 販売分析ＣＤ１ | BM82: 得意先に対する販売分析ＣＤ１ | BN82: 販売分析マスタに販売分析区分が1で登録されている取引先分類ＣＤ | BO82: 得意先項目（任意） | BR82: 得
A83: 75 | C83: T | D83: 取引先マスタ（共通） | K83: 販売分析ＣＤ２ | V83: T | W83: WEB取引先マスタ | AF83: 販売分析ＣＤ２ | AQ83: 画面 | AS83: 販売分析ＣＤ２ | BM83: 得意先に対する販売分析ＣＤ２ | BN83: 販売分析マスタに販売分析区分が2で登録されている取引先分類ＣＤ | BO83: 得意先項目（任意） | BR83: 得
A84: 76 | C84: T | D84: 取引先マスタ（共通） | K84: 販売分析ＣＤ３ | V84: T | W84: WEB取引先マスタ | AF84: 販売分析ＣＤ３ | AQ84: 画面 | AS84: 販売分析ＣＤ３ | BM84: 得意先に対する販売分析ＣＤ３ | BN84: 販売分析マスタに販売分析区分が3で登録されている取引先分類ＣＤ | BO84: 得意先項目（任意） | BR84: 得
A85: 77 | C85: T | D85: 取引先マスタ（共通） | K85: 請求先ＣＤ | V85: T | W85: WEB取引先マスタ | AF85: 請求先ＣＤ | AQ85: 画面 | AS85: 請求先ＣＤ | BM85: 売掛先に対する請求先 | BN85: 取引先マスタで請求先ＦＬＧが設定されている取引先ＣＤ 会社マスタの債権不使用ＦＬＧが設定されていない場合は必須とし、債権不使用ＦＬＧが設定されている場合は任意とする | BO85: 売掛先項目（必須） | BR85: 売
A86: 78 | C86: T | D86: 取引先マスタ（共通） | K86: 入金先ＣＤ | V86: T | W86: WEB取引先マスタ | AF86: 入金先ＣＤ | AQ86: 画面 | AS86: 入金先ＣＤ | BM86: 請求先に対する入金先 | BN86: 取引先マスタで入金先ＦＬＧが設定されている取引先ＣＤ | BO86: 請求先項目（必須） | BR86: 請
A87: 79 | C87: T | D87: 取引先マスタ（共通） | K87: 債権与信管理先ＣＤ | V87: T | W87: WEB取引先マスタ | AF87: 債権与信管理先ＣＤ | AQ87: 画面 | AS87: 債権与信管理先ＣＤ | BM87: 請求先に対する与信管理先 | BN87: 取引先マスタで与信管理先ＦＬＧが設定されている取引先ＣＤ | BO87: 請求先項目（任意） | BP87: 債権に対する与信管理情報を更新しない | BR87: 請
A88: 80 | C88: T | D88: 取引先マスタ（共通） | K88: 請求部門区分 | AF88: 固定：1 | BM88: 請求先を担当する部門を制御する区分 | BN88: 定数：請求部門 1：売上部門 2：債権部門 3：請求部門 | BO88: 請求先項目（必須） 売上部門を請求部門として引き継ぐ場合は1を設定する 債権部門（売掛部門）を請求部門として引き継ぐ場合は2を設定する 請求先に対して設定する請求部門とする場合は3を設定する | BR88: 請
A89: 81 | C89: T | D89: 取引先マスタ（共通） | K89: 請求先担当部門ＣＤ | AF89: NULL | BM89: 請求先を担当する部門ＣＤ | BN89: 部門マスタで債権ＦＬＧが設定されている部門ＣＤ 請求部門区分に3を設定した場合に入力可（必須） 上記以外は入力不可（常にNULL） | BO89: 請求先項目（任意） | BR89: 請
A90: 82 | C90: T | D90: 取引先マスタ（共通） | K90: 請求締処理区分 | AF90: 固定：1 | BM90: 請求先に対する請求締方法を制御する項目 | BN90: 定数：請求締処理区分 1：バッチ締日請求 2：マニュアル締日請求 3：マニュアル選択請求 4：売上都度請求 | BO90: 請求先項目（必須） | BR90: 請
A91: 83 | C91: T | D91: 取引先マスタ（共通） | K91: 請求締日１ | V91: T | W91: WEB取引先マスタ | AF91: 請求締日１ | AQ91: 画面 | AS91: 請求締日１ | BM91: バッチ締日請求やマニュアル締日請求で使用する最初の請求締日 | BN91: 「1」～「31」、「99」 請求締処理区分が「1:バッチ締日請求」「2:マニュアル締日請求」の場合は必須 「1:バッチ締日請求」「2:マニュアル締日請求」以外の場合は入力不可 | BO91: 請求先項目（任意） 月末日を指定する場合は99を設定する 指定された日が存在しない年月については月末日とみなす（例えば30と設定されている場合、2月に対しては月末日を対象とする） 毎月５日、１０日、１５日、２０日、月末日の５回締処理を行う（請求書を発行する）場合は、請求締日１に5を設定する | BR91: 請
A92: 84 | C92: T | D92: 取引先マスタ（共通） | K92: 請求締日２ | AF92: NULL | BM92: バッチ締日請求やマニュアル締日請求で使用する２回目の請求締日 | BN92: 「1」～「31」、「99」 請求締処理区分が「1:バッチ締日請求」「2:マニュアル締日請求」の場合は入力可能 ※請求締日１が設定された場合に入力可能 | BO92: 請求先項目（任意） 月末日を指定する場合は99を設定する 指定された日が存在しない年月については月末日とみなす（例えば30と設定されている場合、2月に対しては月末日を対象とする） 毎月5日、１0日、15日、２0日、月末日の５回締処理を行う（請求書を発行する）場合は、請求締日２に10を設定する | BP92: 月に２回の請求締処理を行わない | BR92: 請
A93: 85 | C93: T | D93: 取引先マスタ（共通） | K93: 請求締日３ | AF93: NULL | BM93: バッチ締日請求やマニュアル締日請求で使用する３回目の請求締日 | BN93: 「1」～「31」、「99」 請求締処理区分が「1:バッチ締日請求」「2:マニュアル締日請求」の場合は入力可能 ※請求締日２が設定された場合に入力可能 | BO93: 請求先項目（任意） 月末日を指定する場合は99を設定する 指定された日が存在しない年月については月末日とみなす（例えば30と設定されている場合、2月に対しては月末日を対象とする） 毎月5日、１0日、15日、２0日、月末日の５回締処理を行う（請求書を発行する）場合は、請求締日３に15を設定する | BP93: 月に３回の請求締処理を行わない | BR93: 請
A94: 86 | C94: T | D94: 取引先マスタ（共通） | K94: 請求締日４ | AF94: NULL | BM94: バッチ締日請求やマニュアル締日請求で使用する４回目の請求締日 | BN94: 「1」～「31」、「99」 請求締処理区分が「1:バッチ締日請求」「2:マニュアル締日請求」の場合は入力可能 ※請求締日３が設定された場合に入力可能 | BO94: 請求先項目（任意） 月末日を指定する場合は99を設定する 指定された日が存在しない年月については月末日とみなす（例えば30と設定されている場合、2月に対しては月末日を対象とする） 毎月5日、１0日、15日、２0日、月末日の５回締処理を行う（請求書を発行する）場合は、請求締日４に20を設定する | BP94: 月に４回の請求締処理を行わない | BR94: 請
A95: 87 | C95: T | D95: 取引先マスタ（共通） | K95: 請求締日５ | AF95: NULL | BM95: バッチ締日請求やマニュアル締日請求で使用する５回目の請求締日 | BN95: 「1」～「31」、「99」 請求締処理区分が「1:バッチ締日請求」「2:マニュアル締日請求」の場合に入力可能 ※請求締日４が設定された場合に入力可能 | BO95: 請求先項目（任意） 月末日を指定する場合は99を設定する 指定された日が存在しない年月については月末日とみなす（例えば30と設定されている場合、2月に対しては月末日を対象とする） 毎月5日、１0日、15日、２0日、月末日の５回締処理を行う（請求書を発行する）場合は、請求締日５に99を設定する | BP95: 月に５回の請求締処理を行わない | BR95: 請
A96: 88 | C96: T | D96: 取引先マスタ（共通） | K96: 請求税計算ＦＬＧ | AF96: 固定：TRUE | BM96: 請求書単位で税額を計算することを制御するフラグ ※売上時には売上税計算区分に従って税額が計算され、 自動仕訳処理に連携される ※請求締処理で請求書単位で計算した税額に差額がある場合に、請求時税差額 伝票を計上して請求書に追加する （差額の税額が自動仕訳処理の連携対象となる） | BN96: 請求締処理区分が「4：売上都度請求」の場合は入力不可（常に0） | BO96: 請求先項目 請求単位で税額を再計算する場合に1を設定する | BR96: 請
A97: 89 | C97: T | D97: 取引先マスタ（共通） | K97: 請求税額端数処理区分 | AF97: 固定：3 | BM97: 請求書単位で税額を計算する際の端数処理方法 | BN97: 定数：端数処理区分 1: 切り上げ 2: 切り捨て 3: 四捨五入 請求税計算ＦＬＧが設定されている場合は必須 請求税計算ＦＬＧが設定されていない場合は入力不可（常にNULL） | BO97: 請求先項目（任意） | BR97: 請
A98: 90 | C98: T | D98: 取引先マスタ（共通） | K98: 請求締遅延日数 | AF98: NULL | BM98: 請求締日から請求締処理が実行されるまでの日数（営業日ベースでの日数） ※営業日を算出する際は会社マスタの請求締カレンダを参照する | BN98: 請求締処理区分が「1：バッチ締日請求」の場合は必須 それ以外は入力不可 | BO98: 請求先項目（任意） | BR98: 請
A99: 91 | C99: T | D99: 取引先マスタ（共通） | K99: 請求締前後区分 | AF99: NULL | BM99: 請求締遅延日数が0、かつ請求締処理日が休日の場合、前営業日とするか翌営業 日とするかを制御する区分 | BN99: 定数：前後区分 1：前倒し 2：後倒し 請求締遅延日数が「0」の場合は必須 上記以外は常にＮＵＬＬ | BO99: 請求先項目（任意） | BR99: 請
A100: 92 | C100: T | D100: 取引先マスタ（共通） | K100: 売上仮単価締ＦＬＧ | AF100: 固定：FALSE | BM100: 仮単価となる売上明細データが存在している場合でも請求締処理、売上締処理 を可能とするかどうかを制御するフラグ | BO100: 請求先項目 売上明細データに仮単価データ（本単価に更新されていないデータ）が存在している場合でも請求締処理や売上締処理を可能とする場合に設定する 設定しない場合は仮単価データが存在する場合は請求締処理や売上締処理が不可となる | BR100: 請
A101: 93 | C101: T | D101: 取引先マスタ（共通） | K101: 請求先カレンダＣＤ | AF101: 固定：CAL01 | BM101: 請求先に対する入金予定日を算出する際に参照するカレンダ | BN101: カレンダ基本マスタに登録されているカレンダＣＤ | BO101: 請求先項目（任意） | BP101: すべて稼働日として扱う | BR101: 請
...

Sheet 得意先担当マスタ入出力仕様
A1: =表紙!A54 -> Webシステム・mcframe7 | K1: 文書名 | U1: モジュールID | Z1: =表紙!$AJ$63 -> MS | AE1: モジュール名 | AJ1: =表紙!$AX$63 -> Webシステム | AS1: 文書番号 | AZ1: Version | BF1: Rev.
K2: =表紙!O64 -> アドオン設計書 | U2: ｻﾌﾞﾓｼﾞｭｰﾙID | Z2: =表紙!$AJ$64 -> MSBB | AE2: ｻﾌﾞﾓｼﾞｭｰﾙ名 | AJ2: =表紙!$AX$64 -> 販売Webシステム | AS2: =表紙!$BL$64 -> M7-US-1140 | AZ2: =表紙!$BU$64 -> 7.0.2 | BF2: =表紙!$CB$64 -> 1
K3: =RIGHT(CELL("filename",$A$1),LEN(CELL("filename",$A$1))-FIND("]",CELL("filename",$A$1))) -> 得意先担当マスタ入出力仕様 | U3: 表題 | Z3: =表紙!$AJ$65 -> MSBBBA020 | AE3: =表紙!$AQ$65 -> 取引先マスタ連携
A5: No | G5: 1 | S5: ロジック名称 | AH5: 備考
A6: 処理分類 | E6: 更新
A7: No | C7: 転送先 | V7: 転送元 | AQ7: 備考
C8: 種 | D8: オブジェクト | K8: 項目名 | V8: 種 | W8: オブジェクト | AF8: 項目名 | BM8: 説明 | BN8: 値の制限 | BO8: 設定仕様 | BP8: 未設定時の振る舞い
A9: 1 | C9: T | D9: 得意先担当マスタ | K9: 得意先ＣＤ | V9: T | W9: WEB取引先マスタ | AF9: 取引先ＣＤ | AQ9: 画面 | AS9: 取引先ＣＤ | BM9: 得意先ＣＤ | BN9: 取引先マスタで得意先ＦＬＧが設定されている取引先ＣＤ
A10: 2 | C10: T | D10: 得意先担当マスタ | K10: 適用開始日 | AF10: 登録日時 | BM10: 当該レコードを有効にする日 | BN10: 適用開始日≦適用終了日 適用開始日以外のキー項目が同一となる場合に、期間が重なるようなデータは登録できない
A11: 3 | C11: T | D11: 得意先担当マスタ | K11: 会社ＣＤ | AF11: (システム自動)
A12: 4 | C12: T | D12: 得意先担当マスタ | K12: 適用終了日 | AF12: 固定：2099/12/31 | BM12: 当該レコードが有効となる最終日 | BN12: 適用開始日≦適用終了日 適用開始日以外のキー項目が同一となる場合に、期間が重なるようなデータは登録できない
A13: 5 | C13: T | D13: 得意先担当マスタ | K13: 担当者ＣＤ | V13: T | W13: WEB取引先マスタ | AF13: 営業担当CD | AQ13: 画面 | AS13: 営業担当 | BM13: 得意先を担当する担当者ＣＤ 担当者ＣＤを設定した場合は担当者に対して担当者権限マスタに登録されている主部門が売上部門として連携される | BN13: 担当者マスタに登録されている担当者ＣＤ 部門ＣＤが設定されている場合は設定不可 担当者ＣＤもしくは部門ＣＤのどちらかは必須
A14: 6 | C14: T | D14: 得意先担当マスタ | K14: 部門ＣＤ | AF14: NULL | BM14: 得意先を担当する部門ＣＤ | BN14: 部門マスタで営業部門ＦＬＧが設定されている部門ＣＤ 担当者ＣＤが設定されている場合は設定不可 担当者ＣＤもしくは部門ＣＤのどちらかは必須
A15: 7 | C15: T | D15: 得意先担当マスタ | K15: メモ１
A16: 8 | C16: T | D16: 得意先担当マスタ | K16: メモ２
A17: 9 | C17: T | D17: 得意先担当マスタ | K17: メモ３
A18: 10 | C18: T | D18: 得意先担当マスタ | K18: 論理削除ＦＬＧ
A19: 11 | C19: T | D19: 得意先担当マスタ | K19: 論理削除ユーザＩＤ
A20: 12 | C20: T | D20: 得意先担当マスタ | K20: 論理削除ユーザ名
A21: 13 | C21: T | D21: 得意先担当マスタ | K21: 論理削除日時
A22: 14 | C22: T | D22: 得意先担当マスタ | K22: 登録ユーザＩＤ
A23: 15 | C23: T | D23: 得意先担当マスタ | K23: 登録ユーザ名
A24: 16 | C24: T | D24: 得意先担当マスタ | K24: 登録日時
A25: 17 | C25: T | D25: 得意先担当マスタ | K25: 登録機能ＩＤ
A26: 18 | C26: T | D26: 得意先担当マスタ | K26: 更新カウンタ
... A31: 23 | C31: T | D31: 得意先担当マスタ | K31: 更新リクエストＮＯ

Sheet 口座マスタ入出力仕様
A1: =表紙!A54 -> Webシステム・mcframe7 | K1: 文書名 | U1: モジュールID | Z1: =表紙!$AJ$63 -> MS | AE1: モジュール名 | AJ1: =表紙!$AX$63 -> Webシステム | AS1: 文書番号 | AZ1: Version | BF1: Rev.
K2: =表紙!O64 -> アドオン設計書 | U2: ｻﾌﾞﾓｼﾞｭｰﾙID | Z2: =表紙!$AJ$64 -> MSBB | AE2: ｻﾌﾞﾓｼﾞｭｰﾙ名 | AJ2: =表紙!$AX$64 -> 販売Webシステム | AS2: =表紙!$BL$64 -> M7-US-1140 | AZ2: =表紙!$BU$64 -> 7.0.2 | BF2: =表紙!$CB$64 -> 1
K3: =RIGHT(CELL("filename",$A$1),LEN(CELL("filename",$A$1))-FIND("]",CELL("filename",$A$1))) -> 口座マスタ入出力仕様 | U3: 表題 | Z3: =表紙!$AJ$65 -> MSBBBA020 | AE3: =表紙!$AQ$65 -> 取引先マスタ連携
A5: No | G5: 1 | S5: ロジック名称 | AH5: 備考
A6: 処理分類 | E6: 更新
A7: No | C7: 転送先 | V7: 転送元 | AQ7: 備考
C8: 種 | D8: オブジェクト | K8: 項目名 | V8: 種 | W8: オブジェクト | AF8: 項目名 | BM8: 説明 | BN8: 値の制限 | BO8: 設定仕様 | BP8: 未設定時の振る舞い
A9: 1 | C9: T | D9: 口座マスタ | K9: 口座ＣＤ | V9: T | W9: WEB取引先マスタ | AF9: 取引先ＣＤ | AQ9: 画面 | AS9: 取引先ＣＤ | BM9: 口座を表すＣＤ
A10: 2 | C10: T | D10: 口座マスタ | K10: 口座名 | V10: T | W10: WEB取引先マスタ | AF10: 取引先略称 | AQ10: 取引先略称 + 固定：口座 | BM10: 口座ＣＤに対する名称
A11: 3 | C11: T | D11: 口座マスタ | K11: 社外ＦＬＧ | AF11: 固定：1 | AQ11: チェック有り固定 | BM11: 社内口座か社外口座（振込先口座）かどうかを制御するフラグ | BO11: 支払先の口座として利用する場合に設定する フラグを設定した場合は社内用の口座としては利用できない
A12: 4 | C12: T | D12: 口座マスタ | K12: 銀行ＣＤ | V12: T | W12: WEB取引先マスタ | AF12: 銀行(支払予定管理先) | AQ12: 画面 | AS12: 銀行(支払予定管理先) | BM12: 口座ＣＤに対する銀行ＣＤ | BN12: 銀行マスタに登録されている銀行ＣＤ
A13: 5 | C13: T | D13: 口座マスタ | K13: 支店ＣＤ | V13: T | W13: WEB取引先マスタ | AF13: 銀行支店(支払予定管理先) | AQ13: 画面 | AS13: 銀行支店(支払予定管理先) | BM13: 口座ＣＤに対する支店ＣＤ | BN13: 銀行ＣＤに対して銀行支店マスタに登録されている支店ＣＤ
A14: 6 | C14: T | D14: 口座マスタ | K14: 口座番号 | V14: T | W14: WEB取引先マスタ | AF14: 支払口座 | AQ14: 画面 | AS14: 支払口座 | BM14: 口座ＣＤに対する口座番号
A15: 7 | C15: T | D15: 口座マスタ | K15: 口座区分 | V15: T | W15: WEB取引先マスタ | AF15: 支払口座区分 | AQ15: 画面 | AS15: 支払口座区分 | BM15: 口座ＣＤに対する口座区分 | BN15: 定数：口座区分 1：普通 2：当座 3：その他
A16: 8 | C16: T | D16: 口座マスタ | K16: 口座名義 | AF16: NULL | BM16: 口座ＣＤに対する口座名義
A17: 9 | C17: T | D17: 口座マスタ | K17: 口座名義別名 | V17: T | W17: WEB取引先マスタ | AF17: 口座名義(カナ) | AQ17: 画面 | AS17: 口座名義(カナ) | BM17: 口座名義に対する別名（口座名義に対するカナ名など）
A18: 10 | C18: T | D18: 口座マスタ | K18: メモ１
A19: 11 | C19: T | D19: 口座マスタ | K19: メモ２
A20: 12 | C20: T | D20: 口座マスタ | K20: メモ３
A21: 13 | C21: T | D21: 口座マスタ | K21: 論理削除ＦＬＧ
A22: 14 | C22: T | D22: 口座マスタ | K22: 論理削除ユーザＩＤ
A23: 15 | C23: T | D23: 口座マスタ | K23: 論理削除ユーザ名
A24: 16 | C24: T | D24: 口座マスタ | K24: 論理削除日時
A25: 17 | C25: T | D25: 口座マスタ | K25: 登録ユーザＩＤ
A26: 18 | C26: T | D26: 口座マスタ | K26: 登録ユーザ名
A27: 19 | C27: T | D27: 口座マスタ | K27: 登録日時
A28: 20 | C28: T | D28: 口座マスタ | K28: 登録機能ＩＤ
A29: 21 | C29: T | D29: 口座マスタ | K29: 更新カウンタ
... A34: 26 | C34: T | D34: 口座マスタ | K34: 更新リクエストＮＯ

Sheet 更新入出力仕様
A1: =表紙!A54 -> Webシステム・mcframe7 | K1: 文書名 | U1: モジュールID | Z1: =表紙!$AJ$63 -> MS | AE1: モジュール名 | AJ1: =表紙!$AX$63 -> Webシステム | AS1: 文書番号 | AZ1: Version | BF1: Rev.
K2: =表紙!O64 -> アドオン設計書 | U2: ｻﾌﾞﾓｼﾞｭｰﾙID | Z2: =表紙!$AJ$64 -> MSBB | AE2: ｻﾌﾞﾓｼﾞｭｰﾙ名 | AJ2: =表紙!$AX$64 -> 販売Webシステム | AS2: =表紙!$BL$64 -> M7-US-1140 | AZ2: =表紙!$BU$64 -> 7.0.2 | BF2: =表紙!$CB$64 -> 1
K3: =RIGHT(CELL("filename",$A$1),LEN(CELL("filename",$A$1))-FIND("]",CELL("filename",$A$1))) -> 更新入出力仕様 | U3: 表題 | Z3: =表紙!$AJ$65 -> MSBBBA020 | AE3: =表紙!$AQ$65 -> 取引先マスタ連携
A5: No | G5: 1 | S5: ロジック名称 | AH5: 備考
A6: 処理分類 | E6: 更新
A7: No | C7: 転送先 | V7: 転送元 | AQ7: 説明
C8: 種 | D8: オブジェクト | K8: 項目名 | V8: 種 | W8: オブジェクト | AF8: 項目名
C9: T | D9: WEB取引先マスタ | K9: mcframe7転送FLG | AF9: 1
C10: T | D10: WEB取引先マスタ | K10: mcframe7転送日時 | AF10: 処理日時
A12: 更新条件
C13: T | D13: WEB取引先マスタ | K13: 取引先CD | V13: T | W13: WEB取引先マスタ | AF13: 取引先CD | AQ13: 抽出したWEB取引先マスタの取引先CDをキーに更新する

Sheet 補足説明資料
A1: =表紙!A54 -> Webシステム・mcframe7 | O1: 文書名 | AC1: モジュールID | AJ1: =表紙!AJ63 -> MS | AQ1: モジュール名 | AX1: =表紙!AX63 -> Webシステム | BL1: 文書番号 | BU1: Version | CB1: Rev.
O2: =表紙!O64 -> アドオン設計書 | AC2: サブモジュールID | AJ2: =表紙!AJ64 -> MSBB | AQ2: サブモジュール名 | AX2: =表紙!AX64 -> 販売Webシステム | BL2: =表紙!BL64 -> M7-US-1140 | BU2: =表紙!BU64 -> 7.0.2 | CB2: =表紙!CB64 -> 1
O3: =RIGHT(CELL("filename",$A$1),LEN(CELL("filename",$A$1))-FIND("]",CELL("filename",$A$1))) -> 補足説明資料 | AC3: 表題 | AJ3: =表紙!AJ65 -> MSBBBA020 | AQ3: =表紙!AQ65 -> 取引先マスタ連携
AO5: 補足説明
D7: 「取引先出力定義.txt」定義に関して
E8: 概要：取引先マスタ連携のDB項目・固定項目を定義する
D10: 取引先出力定義.txt イメージ
D11: # 転送項目
D12: 取引先ＣＤ | N12: = | P12: @取引先ＣＤ@
D13: 取引先名 | N13: = | P13: @取引先略称@
D14: 取引先別名１ | N14: = | P14: @取引先名@
D15: 取引先別名２ | N15: = | P15: @取引先別名２@
D16: 取引先別名３ | N16: = | P16: @取引先別名３@
D17: 取引先別名４ | N17: = | P17: @取引先別名４@
D18: 郵便番号 | N18: = | P18: @郵便番号@
D19: 住所１ | N19: = | P19: @都道府県@
D20: 住所２ | N20: = | P20: @市区町村@
D21: 住所３ | N21: = | P21: @町域・番地@
D22: 住所４ | N22: = | P22: @建物など@
D23: ＴＥＬ | N23: = | P23: @ＴＥＬ@
... D209: 買戻義務ＦＬＧ | N209: = | P209: @買戻義務ＦＬＧ@

Sheet |→補足シート

Sheet マスタ入力定義
A1: mcframe 7 | K1: 文書名 | U1: モジュールID | Z1: MA | AE1: モジュール名 | AJ1: マスタ管理 | AS1: 文書番号 | AZ1: Version | BF1: Rev.
K2: 文書名 | U2: ｻﾌﾞﾓｼﾞｭｰﾙID | Z2: MABC | AE2: ｻﾌﾞﾓｼﾞｭｰﾙ名 | AJ2: マスタ（共通） | AS2: M7-US-1140 | AZ2: 7.0.2 | BF2: 1
K3: マスタ入力定義 | U3: 表題 | Z3: MABCP0510 | AE3: 取引先マスタ登録
A5: CP項目 要否 | E5: 画面名 | L5: タブ名 (タブ無画面は-) | S5: データ項目名 | Z5: 必須 項目 | AD5: 備考１ | AN5: メモ | AT5: 入力パターン１ | BL5: 入力パターン２ | CF5: 入力パターン3
AT6: 得意先関連 | BL6: 発注先(原材料、資材、副資材、購買品、他)関連 | CF6: 発注先(外注品)関連
AT7: 設定値 | BA7: 担当 | BF7: 登録方法 | BL7: 設定値 | BT7: 担当 | BZ7: 登録方法 | CF7: 設定値 | CN7: 担当 | CS7: 登録方法
L8: 共通１ | S8: 取引先 | Z8: 〇 | AT8: 事業所＋取引先 | BA8: システム | BF8: WEB→mcframe | BL8: 事業所＋取引先 | BT8: 業務or総務 | BZ8: 画面 | CF8: 事業所＋取引先 | CN8: 業務 | CS8: 画面
L9: 共通１ | S9: 標準取引先名 | Z9: 〇 | AT9: 得意先略称 | BA9: 営業 | BF9: WEB→mcframe | BL9: 発注先略称 | BT9: 業務or総務 | BZ9: 画面 | CF9: 発注先略称 | CN9: 業務 | CS9: 画面
L10: 共通１ | S10: 取引先別名１ | AT10: 得意先正式名称 | BA10: 営業 | BF10: WEB→mcframe | BL10: 発注先正式名称 | BT10: 業務or総務 | BZ10: 画面 | CF10: 発注先正式名称 | CN10: 業務 | CS10: 画面
A11: X | L11: 共通１ | S11: 取引先別名２ | AT11: 使用しない | BA11: システム | BF11: WEB→mcframe | BL11: 使用しない | CF11: 使用しない
A12: X | L12: 共通１ | S12: 取引先別名３ | AT12: 使用しない | BA12: システム | BF12: WEB→mcframe | BL12: 使用しない | CF12: 使用しない
A13: X | L13: 共通１ | S13: 取引先別名４ | AT13: 使用しない | BA13: システム | BF13: WEB→mcframe | BL13: 使用しない | CF13: 使用しない
L14: 共通１ | S14: 通貨 | AT14: 固定：JPY | BA14: システム | BF14: WEB→mcframe | BL14: JPY | BT14: 業務or総務 | BZ14: 画面 | CF14: JPY | CN14: 業務 | CS14: 画面
L15: 共通１ | S15: 通貨名 | AT15: 円 | BA15: システム | BF15: WEB→mcframe | BL15: 円 | CF15: 円
L16: 共通１ | S16: 国 | Z16: 〇 | AT16: 固定：JPY | BA16: システム | BF16: WEB→mcframe | BL16: JPN | BT16: 業務or総務 | BZ16: 画面 | CF16: JPN | CN16: 業務 | CS16: 画面
L17: 共通１ | S17: 国名 | AT17: 日本 | BA17: システム | BF17: WEB→mcframe | BL17: 日本 | CF17: 日本
L18: 共通１ | S18: 地域 | AT18: 都道府県 | BA18: 営業 | BF18: WEB→mcframe | BL18: 都道府県 | BT18: 業務or総務 | BZ18: 画面 | CF18: 都道府県 | CN18: 業務 | CS18: 画面
L19: 共通１ | S19: 地域名 | AT19: 都道府県名 | BA19: システム | BF19: WEB→mcframe | BL19: 都道府県名 | CF19: 都道府県名
L20: 共通２ | S20: 法人番号 | AT20: 法人番号 | BA20: 営業 | BF20: WEB→mcframe | BL20: 法人番号 | BT20: 業務or総務 | BZ20: 画面 | CF20: 法人番号 | CN20: 業務 | CS20: 画面
L21: 共通２ | S21: 標準企業コード | AT21: 標準企業コード | BA21: 営業 | BF21: WEB→mcframe | BL21: 標準企業コード | BT21: 業務or総務 | BZ21: 画面 | CF21: 標準企業コード | CN21: 業務 | CS21: 画面
L22: 共通２ | S22: 郵便番号 | AT22: 郵便番号 | BA22: 営業 | BF22: WEB→mcframe | BL22: 郵便番号 | BT22: 業務or総務 | BZ22: 画面 | CF22: 郵便番号 | CN22: 業務 | CS22: 画面
L23: 共通２ | S23: 住所１ | AT23: 住所 | BA23: 営業 | BF23: WEB→mcframe | BL23: 住所 | BT23: 業務or総務 | BZ23: 画面 | CF23: 住所 | CN23: 業務 | CS23: 画面
L24: 共通２ | S24: 住所２ | AT24: 使用しない | BA24: システム | BF24: WEB→mcframe | BT24: 業務or総務 | BZ24: 画面 | CN24: 業務 | CS24: 画面
L25: 共通２ | S25: 住所３ | AT25: 使用しない | BA25: システム | BF25: WEB→mcframe | BT25: 業務or総務 | BZ25: 画面 | CN25: 業務 | CS25: 画面
L26: 共通２ | S26: 住所４ | AT26: 使用しない | BA26: システム | BF26: WEB→mcframe | BT26: 業務or総務 | BZ26: 画面 | CN26: 業務 | CS26: 画面
L27: 共通２ | S27: ＴＥＬ | AT27: ＴＥＬ | BA27: 営業 | BF27: WEB→mcframe | BL27: ＴＥＬ | BT27: 業務or総務 | BZ27: 画面 | CF27: ＴＥＬ | CN27: 業務 | CS27: 画面
L28: 共通２ | S28: ＦＡＸ | AT28: ＦＡＸ | BA28: 営業 | BF28: WEB→mcframe | BL28: ＦＡＸ | BT28: 業務or総務 | BZ28: 画面 | CF28: ＦＡＸ | CN28: 業務 | CS28: 画面
L29: 共通２ | S29: 帳票出力ロケール | AT29: ja_jp | BA29: 営業 | BF29: WEB→mcframe | BL29: ja_jp | BT29: 業務or総務 | BZ29: 画面 | CF29: ja_jp | CN29: 業務 | CS29: 画面
L30: 共通２ | S30: 帳票出力ロケール名 | AT30: 日本語出力 | BA30: 営業 | BF30: WEB→mcframe | BL30: 日本語出力 | CF30: 日本語出力
L31: 共通２ | S31: 取引先配賦Ｇ | AT31: 原価で決定 | BA31: システム | BF31: WEB→mcframe | BL31: 原価で決定 | BT31: 業務or総務 | BZ31: 画面 | CF31: 原価で決定 | CN31: 業務 | CS31: 画面
L32: 共通２ | S32: メモ１ | AT32: 使用しない | BA32: システム | BF32: WEB→mcframe | BT32: 業務or総務 | BZ32: 画面 | CN32: 業務 | CS32: 画面
L33: 共通２ | S33: メモ２ | AT33: 使用しない | BA33: システム | BF33: WEB→mcframe | BT33: 業務or総務 | BZ33: 画面 | CN33: 業務 | CS33: 画面
L34: 共通２ | S34: メモ３ | AT34: 使用しない | BA34: システム | BF34: WEB→mcframe | BT34: 業務or総務 | BZ34: 画面 | CN34: 業務 | CS34: 画面
L35: 取引先分類 | S35: 取引先分類１ | AT35: 締め日 | BA35: 営業 | BF35: WEB→mcframe
L36: 取引先分類 | S36: 取引先分類名１ | AT36: 締め日 | BA36: 営業 | BF36: WEB→mcframe
L37: 取引先分類 | S37: 取引先分類２ | BF37: WEB→mcframe
L38: 取引先分類 | S38: 取引先分類名２ | BF38: WEB→mcframe
L39: 取引先分類 | S39: 取引先分類３ | BF39: WEB→mcframe
L40: 取引先分類 | S40: 取引先分類名３ | BF40: WEB→mcframe
L41: 取引先分類 | S41: 取引先分類４ | BF41: WEB→mcframe
L42: 取引先分類 | S42: 取引先分類名４ | BF42: WEB→mcframe
L43: 取引先分類 | S43: 取引先分類５ | BF43: WEB→mcframe
L44: 取引先分類 | S44: 取引先分類名５ | BF44: WEB→mcframe
L45: 取引先分類 | S45: 取引先分類６ | BF45: WEB→mcframe
L46: 取引先分類 | S46: 取引先分類名６ | BF46: WEB→mcframe
L47: 取引先分類 | S47: 取引先分類７ | BF47: WEB→mcframe
L48: 取引先分類 | S48: 取引先分類名７ | BF48: WEB→mcframe
... L54: 取引先分類 | S54: 取引先分類名１０ | BF54: WEB→mcframe
A55: ▲ | L55: システム情報（共通） | S55: 登録ユーザＩＤ | BF55: WEB→mcframe
A56: ▲ | L56: システム情報（共通） | S56: 登録ユーザ名 | BF56: WEB→mcframe
A57: ▲ | L57: システム情報（共通） | S57: 登録機能ＩＤ | BF57: WEB→mcframe
A58: ▲ | L58: システム情報（共通） | S58: 登録機能名 | BF58: WEB→mcframe
A59: ▲ | L59: システム情報（共通） | S59: 更新ユーザＩＤ | BF59: WEB→mcframe
A60: ▲ | L60: システム情報（共通） | S60: 更新ユーザ名 | BF60: WEB→mcframe
A61: ▲ | L61: システム情報（共通） | S61: 更新機能ＩＤ | BF61: WEB→mcframe
A62: ▲ | L62: システム情報（共通） | S62: 更新機能名 | BF62: WEB→mcframe
A63: ▲ | L63: システム情報（共通） | S63: 登録日時 | BF63: WEB→mcframe
A64: ▲ | L64: システム情報（共通） | S64: 更新日時 | BF64: WEB→mcframe
A65: ▲ | L65: システム情報（共通） | S65: 更新リクエストＮＯ | BF65: WEB→mcframe
A66: ▲ | L66: システム情報（共通） | S66: 論理削除ユーザＩＤ | BF66: WEB→mcframe
... A82: ▲ | L82: システム情報 | S82: 論理削除日時 | BF82: WEB→mcframe
L83: 取引先管理 | S83: 得意先 | AT83: TRUE | BA83: システム | BF83: WEB→mcframe | BL83: FALSE | BT83: 業務 | BZ83: 画面 | CF83: FALSE | CN83: 業務 | CS83: 画面
L84: 取引先管理 | S84: 売掛先 | AT84: TRUE | BA84: システム | BF84: WEB→mcframe | BL84: FALSE | BT84: 業務 | BZ84: 画面 | CF84: FALSE | CN84: 業務 | CS84: 画面
L85: 取引先管理 | S85: 請求先 | AT85: TRUE | BA85: システム | BF85: WEB→mcframe | BL85: FALSE | BT85: 業務 | BZ85: 画面 | CF85: FALSE | CN85: 業務 | CS85: 画面
L86: 取引先管理 | S86: 入金先 | AT86: TRUE | BA86: システム | BF86: WEB→mcframe | BL86: FALSE | BT86: 業務 | BZ86: 画面 | CF86: FALSE | CN86: 業務 | CS86: 画面
L87: 取引先管理 | S87: 納品先 | AT87: TRUE | BA87: システム | BF87: WEB→mcframe | BL87: FALSE | BT87: 業務 | BZ87: 画面 | CF87: FALSE | CN87: 業務 | CS87: 画面
L88: 取引先管理 | S88: 仕向先 | AT88: FALSE | BA88: システム | BF88: WEB→mcframe | BL88: FALSE | BT88: 業務 | BZ88: 画面 | CF88: FALSE | CN88: 業務 | CS88: 画面
L89: 取引先管理 | S89: 与信管理先 | AT89: TRUE | BA89: システム | BF89: WEB→mcframe | BT89: 業務 | BZ89: 画面 | CN89: 業務 | CS89: 画面
L90: 取引先管理 | S90: 発注先 | AT90: FALSE | BA90: システム | BF90: WEB→mcframe | BT90: 業務or総務 | BZ90: 画面 | CN90: 業務 | CS90: 画面
L91: 取引先管理 | S91: 買掛先 | AT91: FALSE | BA91: システム | BF91: WEB→mcframe | BT91: 業務or総務 | BZ91: 画面 | CN91: 業務 | CS91: 画面
L92: 取引先管理 | S92: 支払予定管理先 | AT92: FALSE | BA92: システム | BF92: WEB→mcframe | BT92: 業務or総務 | BZ92: 画面 | CN92: 業務 | CS92: 画面
L93: 取引先管理 | S93: 支払先 | AT93: FALSE | BA93: システム | BF93: WEB→mcframe | BT93: 業務or総務 | BZ93: 画面 | CN93: 業務 | CS93: 画面
L94: 取引先管理 | S94: メーカ | AT94: FALSE | BA94: システム | BF94: WEB→mcframe | BT94: 業務 | BZ94: 画面 | CN94: 業務 | CS94: 画面
L95: 得意先 | S95: 売掛先 | AT95: 売掛先CD | BA95: 営業 | BF95: WEB→mcframe | BL95: 使用しない | CF95: 使用しない
L96: 得意先 | S96: 売掛先名 | AT96: 売掛先 | BA96: 営業 | BF96: WEB→mcframe | BL96: 使用しない | CF96: 使用しない
L97: 得意先 | S97: 得意先部署 | AT97: 得意先部署 | BA97: 営業 | BF97: WEB→mcframe | BL97: 使用しない | CF97: 使用しない
L98: 得意先 | S98: 得意先担当者 | AT98: 得意先担当者 | BA98: 営業 | BF98: WEB→mcframe | BL98: 使用しない | CF98: 使用しない
L99: 得意先 | S99: 得意先担当者敬称 | AT99: 得意先担当者敬称 | BA99: 営業 | BF99: WEB→mcframe | BL99: 使用しない | CF99: 使用しない
L100: 得意先 | S100: 得意先諸口 | AT100: FALSE | BA100: システム | BF100: WEB→mcframe | BL100: 使用しない | CF100: 使用しない
L101: 得意先 | S101: 債権部門区分 | AT101: 1 | BA101: システム | BF101: WEB→mcframe | BL101: 使用しない | CF101: 使用しない
L102: 得意先 | S102: 債権部門区分名 | AT102: 売上部門 | BA102: 営業 | BF102: WEB→mcframe | BL102: 使用しない | CF102: 使用しない
L103: 得意先 | S103: 債権部門 | AT103: 使用しない | BA103: システム | BF103: WEB→mcframe | BL103: 使用しない | CF103: 使用しない
L104: 得意先 | S104: 債権部門名 | AT104: 使用しない | BA104: システム | BF104: WEB→mcframe | BL104: 使用しない | CF104: 使用しない
L105: 得意先 | S105: 販売単価端数処理区分 | AT105: 3 | BA105: システム | BF105: WEB→mcframe | BL105: 使用しない | CF105: 使用しない
L106: 得意先 | S106: 販売単価端数処理区分名 | AT106: 四捨五入 | BA106: システム | BF106: WEB→mcframe | BL106: 使用しない | CF106: 使用しない
L107: 得意先 | S107: 販売単価取得区分 | AT107: 1 | BA107: システム | BF107: WEB→mcframe | BL107: 使用しない | CF107: 使用しない
L108: 得意先 | S108: 販売単価取得区分名 | AT108: 受注日 | BA108: システム | BF108: WEB→mcframe | BL108: 使用しない | CF108: 使用しない
L109: 得意先 | S109: 販売単価変更許可 | AT109: TRUE | BA109: システム | BF109: WEB→mcframe | BL109: 使用しない | CF109: 使用しない
L110: 得意先 | S110: 売上金額端数処理区分 | AT110: 3 | BA110: システム | BF110: WEB→mcframe | BL110: 使用しない | CF110: 使用しない
L111: 得意先 | S111: 売上金額端数処理区分名 | AT111: 四捨五入 | BA111: システム | BF111: WEB→mcframe | BL111: 使用しない | CF111: 使用しない
L112: 得意先 | S112: 売上税計算区分 | AT112: 2 | BA112: システム | BF112: WEB→mcframe | BL112: 使用しない | CF112: 使用しない
L113: 得意先 | S113: 売上税計算区分名 | AT113: 伝票単位 | BA113: システム | BF113: WEB→mcframe | BL113: 使用しない | CF113: 使用しない
L114: 得意先 | S114: 売上税額端数処理区分 | AT114: 3 | BA114: システム | BF114: WEB→mcframe | BL114: 使用しない | CF114: 使用しない
L115: 得意先 | S115: 売上税額端数処理区分名 | AT115: 四捨五入 | BA115: システム | BF115: WEB→mcframe | BL115: 使用しない | CF115: 使用しない
L116: 得意先 | S116: 売上税 | AT116: S010 | BA116: システム | BF116: WEB→mcframe | BL116: 使用しない | CF116: 使用しない
L117: 得意先 | S117: 売上税名 | AT117: 消費税（売上10%） | BA117: システム | BF117: WEB→mcframe | BL117: 使用しない | CF117: 使用しない
L118: 得意先 | S118: 売上税優先 | AT118: FALSE | BA118: システム | BF118: WEB→mcframe | BL118: 使用しない | CF118: 使用しない
L119: 得意先 | S119: ロット逆転禁止区分 | AT119: FALSE | BA119: システム | BF119: WEB→mcframe | BL119: 使用しない | CF119: 使用しない
L120: 得意先 | S120: ロット逆転禁止区分名 | AT120: FALSE | BA120: システム | BF120: WEB→mcframe | BL120: 使用しない | CF120: 使用しない
L121: 得意先 | S121: 売上計上区分 | AT121: 2 | BA121: システム | BF121: WEB→mcframe | BL121: 使用しない | CF121: 使用しない
...

Sheet 補足説明資料(OLD)
A1: =表紙!A54 -> Webシステム・mcframe7 | O1: 文書名 | AC1: モジュールID | AJ1: =表紙!AJ64 -> MSBB | AQ1: モジュール名 | AX1: =表紙!AX64 -> 販売Webシステム | BL1: 文書番号 | BU1: Version | CB1: Rev.
O2: =表紙!O65 -> 表紙 | AC2: サブモジュールID | AJ2: =表紙!AJ65 -> MSBBBA020 | AQ2: サブモジュール名 | AX2: =表紙!AX65 -> 0 | BL2: =表紙!BL65 -> 0 | BU2: =表紙!BU65 -> 0 | CB2: =表紙!CB65 -> 0
O3: =RIGHT(CELL("filename",$A$1),LEN(CELL("filename",$A$1))-FIND("]",CELL("filename",$A$1))) -> 補足説明資料(OLD) | AC3: 表題 | AJ3: =表紙!AJ66 -> 0 | AQ3: =表紙!AQ66 -> 0
AO5: 補足説明
C33: 図 7-1 取引先場所系マスタ関連図
C53: 図 15-1 販売系マスタ関連図
B89: 固定値に関して
B91: 外部ファイルの読込みやワークテーブルで管理する。
B119: 得意先担当マスタ オペレーション案
B121: ① | C121: 現行データ：解除
B149: ② | C149: 新規データ：取込
F162: EXCEL加工し、インポート
