Workbook
Name Rev.: [2]表紙!$U$22
Name Rev.: 表紙!$U$22
Name Revision: #REF!
Name Revision: [3]表紙!$AP$5
Name Ver.: #REF!
Name Ver.: 表紙!$AE$26
Name Version: #REF!
Name Version: [3]表紙!$AJ$5
Name ご確認者: #REF!
Name ご確認者: 表紙!$AG$40
Name ご確認日: #REF!
Name ご確認日: 表紙!$AG$42
Name サブシステム名: #REF!
Name サブシステム名: 表紙!$U$28
Name システム名: #REF!
Name システム名: 表紙!$U$26
Name プロジェクト名: #REF!
Name プロジェクト名: 表紙!$U$18
Name 開発区分: #REF!
Name 開発区分: 表紙!$U$36
Name 機能ＩＤ: #REF!
Name 機能ＩＤ: 表紙!$U$32
Name 機能区分: #REF!
Name 機能区分: 表紙!$U$34
Name 機能名称: #REF!
Name 機能名称: 表紙!$U$30
Name 顧客名: #REF!
Name 顧客名: 表紙!$U$16
Name 最終更新者: #REF!
Name 最終更新者: 表紙!$AB$40
Name 最終更新日: #REF!
Name 最終更新日: 表紙!$AB$42
Name 作成者: #REF!
Name 作成者: 表紙!$W$40
Name 作成日: #REF!
Name 作成日: 表紙!$W$42
Name 章: #REF!
Name 章: 表紙!$M$10
Name 発行日: #REF!
Name 発行日: #REF!
Name 文書番号: #REF!
Name 文書番号: [3]表紙!$O$5
Name 文書番号_カスタマイズ: '[3]表紙（カスタマイズ）'!$U$20
Name 文書名: 表紙!$M$10
Name 文書名: #REF!
Name 文書名: [3]表紙!$M$15
Name 文書名_カスタマイズ: '[3]表紙（カスタマイズ）'!$M$10

Sheet 目次
A1: アドオン設計書作成ガイド
C3: ■アドオン設計と成果物について
D4: ・システム設計フェーズとソフトウェア設計フェーズでアドオンの処理仕様を定義する
D5: ・システム設計フェーズとソフトウェア設計フェーズの成果物がアドオン設計書であり、ソフトウェア製作フェーズのインプットとなる
C7: ■各設計フェーズ毎のアドオン設計書作成範囲
D8: ・システム設計フェーズ：他機能との関連を定義するとともに、画面や帳票、ファイル入出力を中心とした外部入出力の設計を行う
D9: ・ソフトウェア設計フェーズ：内部処理を中心とした設計を行う
U11: ◎ | W11: … | X11: システム設計フェーズで作成
U12: ○ | W12: … | X12: システム設計フェーズで基本仕様を定義して、ソフトウェア設計フェーズで詳細化する
U13: △ | W13: … | X13: 必要に応じて（例えば標準仕様から変更がない場合は不要）
U14: ‐ | W14: … | X14: 不要
W15: … | X15: ソフトウェア設計フェーズで作成
D17: 各設計書と作成対象シートのマトリックス | S17: ※カスタマイズ：標準機能に機能を追加する アドオン：新規で機能を開発する
D18: EXCELシート | N18: 画面設計書 | W18: バッチ設計書 | AF18: 帳票設計書 | AO18: ＢＩ設計書 | AT18: .Net設計書 | BB18: EXCELシート | BL18: WebDB設計書 | BR18: 帳票設計書 | BX18: 汎用申請設計書
N19: カスタマイズ | S19: アドオン | W19: カスタマイズ | AB19: アドオン | AF19: カスタマイズ | AK19: アドオン | AO19: アドオン | AT19: アドオン | BL19: アドオン | BR19: アドオン | BX19: アドオン
D20: 概要 | N20: ◎ | O20: ※1 | S20: ◎ | W20: ◎ | X20: ※1 | AB20: ◎ | AF20: ◎ | AG20: ※1 | AK20: ◎ | AO20: ◎ | AT20: ◎ | BB20: 機能概要 | BL20: ◎ | BR20: ◎ | BX20: ◎
D21: レイアウト | N21: ◎ | O21: ※2 | S21: ◎ | W21: ‐ | AB21: ‐ | AF21: ◎ | AG21: ※2 | AK21: ◎ | AO21: ◎ | AT21: ◎ | BB21: アプリケーションフロー | BL21: ◎ | BR21: ー | BX21: ◎
D22: 項目説明 | N22: △ | S22: ○ | W22: ‐ | AB22: ‐ | AF22: △ | AK22: ○ | AO22: ○ | AT22: ○ | BB22: データベース設定 | BL22: ◎ | BR22: ー | BX22: ◎
D23: 引数説明 | N23: ‐ | S23: ‐ | W23: △ | AB23: ◎ | AF23: ‐ | AK23: ‐ | AO23: ‐ | AT23: ◎ | BB23: フィールド設定 | BL23: ◎ | BR23: ー | BX23: ◎
D24: 処理概要 | N24: ◎ | S24: ◎ | W24: ◎ | AB24: ◎ | AF24: ◎ | AK24: ◎ | AO24: ◎ | AT24: ◎ | BB24: 一覧表示画面設定 | BL24: ◎ | BR24: ー | BX24: ◎
D25: 処理詳細 | BB25: 表示編集画面設定 | BL25: ◎ | BR25: ー | BX25: ◎
D26: 処理・サービス関連図 | N26: △ | S26: ◎ | W26: △ | AB26: ◎ | AF26: ‐ | AK26: ‐ | AO26: ‐ | AT26: ◎ | BB26: 明細画面設定 | BL26: △ | BN26: ※3 | BR26: ー | BX26: △ | BZ26: ※3
D27: 検索入出力仕様 | N27: △ | S27: ○ | W27: △ | AB27: ○ | AF27: ‐ | AK27: ‐ | AO27: ‐ | AT27: ○ | BB27: 集計表示設定 | BL27: △ | BN27: ※4 | BR27: ー | BX27: △ | BZ27: ※4
D28: 更新入出力仕様 | N28: △ | S28: ○ | W28: △ | AB28: ○ | AF28: ‐ | AK28: ‐ | AO28: ‐ | AT28: ○ | BB28: 絞り込み条件設定 | BL28: △ | BN28: ※5 | BR28: ー | BX28: △ | BZ28: ※5
D29: ファイル入出力仕様 | N29: △ | S29: △ | W29: ‐ | AB29: ‐ | AF29: ‐ | AK29: ‐ | AO29: ‐ | AT29: △ | BB29: その他設定 | BR29: ー
D30: 画面遷移 | N30: △ | S30: ◎ | W30: ‐ | AB30: ‐ | AF30: ‐ | AK30: ‐ | AO30: ‐ | AT30: ◎ | BB30: 帳票イメージ | BL30: ー | BR30: ◎ | BX30: ー
D31: メッセージ一覧 | N31: △ | S31: △ | W31: △ | AB31: △ | AF31: ‐ | AK31: ‐ | AO31: ‐ | AT31: △ | BB31: 項目設計 | BL31: ー | BR31: ◎ | BX31: ー
D32: 補足説明 | N32: △ | S32: △ | W32: △ | AB32: △ | AF32: △ | AK32: △ | AO32: △ | AT32: △ | BB32: 補足説明 | BL32: △ | BR32: △ | BX32: △
D33: サービス呼出編集仕様 | N33: - | S33: - | W33: - | AB33: - | AF33: - | AK33: - | AO33: - | AT33: - | BB33: 補足説明(詳細)
D35: ※1 | G35: 別シートでカスタマイズ内容を記載する | BB35: ※3 | BE35: 単票画面は記載しない
D36: ※2 | G36: 吹き出しでカスタマイズ内容を記載する | BB36: ※4 | BE36: 集計・グラフ機能を使用する場合に記載する
BB37: ※5 | BE37: 共通設定のみ記載する(個別設定は、記載しない)

Sheet 表紙
AW2: サブモジュール
AW3: MA_マスタ管理
AW4: MB_業務共通
AW5: MG_原価管理
AW6: MSBA_需給管理
M7: 基本設計 | AW7: MSBB_販売管理
AW8: MSBC_生産管理
AW9: MSBD_購買管理
M10: アドオン設計書 | AW10: MSBE_在庫物流管理
AW11: MSBF_品質管理
AW12: MSBG_債権管理
AW13: MSBH_債務管理
AW14: MSBI_締処理
AW15: MSUA_リスト・入力補助
M16: 顧客 | U16: 株式会社クラウン・パッケージ | AW16: PF_ESBアダプタ
M18: プロジェクト名 | U18: 基幹システム刷新PJ | AW18: 機能区分
AW19: 画面
M20: 文書番号 | AW20: 帳票
AW21: バッチ
M22: Ｒｅｖ． | U22: {=MAX(_xlfn.NUMBERVALUE(改訂!A7:E42))} -> 8 | AW22: マスタ
M24: 機密性区分 | U24: 取扱注意（Ｃ） | AW24: 開発区分
AW25: カスタマイズ
M26: システム名 | U26: mcframe7 | AC26: Ver. | AE26: 7.0.2 | AW26: アドオン
AW27: －
M28: サブモジュール | U28: MSBB_販売管理
M30: 機能名 | U30: =M50 -> 製品マスタ連携
M32: 機能ID | U32: =G50 -> MSBBA010
M34: 機能区分 | U34: バッチ
M36: 開発区分 | U36: アドオン
W39: 作成 | AB39: 最終更新 | AG39: ご確認
W40: MDSOL | AB40: =改訂!AZ2 -> MDSOL石田
W42: 44637 | AB42: =改訂!BJ2 -> 45016
A48: 文書番号 | G48: 画面ID | M48: 画面名 | V48: Version | AB48: Revision
A50: M7-US-1140 | G50: MSBBA010 | M50: 製品マスタ連携 | V50: 1.0.0 | AB50: 3
A53: 共通（元データ）
A54: Webシステム | K54: 文書名 | U54: モジュールID | Z54: MS | AE54: モジュール名 | AJ54: 見積管理 | AS54: 文書番号 | AZ54: Version | BF54: Rev.
K55: 画面説明書 | U55: ｻﾌﾞﾓｼﾞｭｰﾙID | Z55: MSBB | AE55: ｻﾌﾞﾓｼﾞｭｰﾙ名 | AJ55: Webシステム | AS55: M7-US-1140 | AZ55: 1.0.0 | BF55: 3
K56: 表紙 | U56: 表題 | Z56: - | AE56: 製品マスタ連携
A57: 共通（リンク用）
A58: =A54 -> Webシステム | K58: 文書名 | U58: モジュールID | Z58: =Z54 -> MS | AE58: モジュール名 | AJ58: =AJ54 -> 見積管理 | AS58: 文書番号 | AZ58: Version | BF58: Rev.
K59: =文書名 -> アドオン設計書 | U59: ｻﾌﾞﾓｼﾞｭｰﾙID | Z59: =Z55 -> MSBB | AE59: ｻﾌﾞﾓｼﾞｭｰﾙ名 | AJ59: =AJ55 -> Webシステム | AS59: =AS55 -> M7-US-1140 | AZ59: =AZ55 -> 1.0.0 | BF59: =BF55 -> 3
K60: =RIGHT(CELL("filename",$A$1),LEN(CELL("filename",$A$1))-FIND("]",CELL("filename",$A$1))) -> 表紙 | U60: 表題 | Z60: =Z56 -> - | AE60: =AE56 -> 製品マスタ連携
A62: 概要シート用
A63: =A58 -> Webシステム | O63: 文書名 | AC63: モジュールID | AJ63: =Z58 -> MS | AQ63: モジュール名 | AX63: =AJ58 -> 見積管理 | BL63: 文書番号 | BU63: Version | CB63: Rev.
O64: =K59 -> アドオン設計書 | AC64: サブモジュールID | AJ64: =Z59 -> MSBB | AQ64: サブモジュール名 | AX64: =AJ59 -> Webシステム | BL64: =AS59 -> M7-US-1140 | BU64: 7.0.2 | CB64: {=MAX(_xlfn.NUMBERVALUE(改訂!A7:E42))} -> 8
O65: =RIGHT(CELL("filename",$A$1),LEN(CELL("filename",$A$1))-FIND("]",CELL("filename",$A$1))) -> 表紙 | AC65: 表題 | AJ65: =Z60 -> - | AQ65: =AE60 -> 製品マスタ連携

Sheet 改訂
A1: 第7章 | K1: 改訂 | AU1: 作成者 | AZ1: MDSOL | BE1: 作成日 | BJ1: =表紙!W42 -> 44637 | BP1: Rev.
AU2: 修正者 | AZ2: =BM20 -> MDSOL石田 | BE2: 改訂日 | BJ2: =MAX(改訂!BM7:BQ58) -> 45016 | BP2: =表紙!CB64 -> 8
A5: Rev. | F5: 改定内容 | BC5: 頁 | BM5: 変更日 変更者 | BR5: 確認日 確認者
A7: 1 | F7: 新規作成 | BM7: 44865
BM8: MDSOL
A9: 2.0 | F9: 仕様連絡書：RCS-1040 品目の採番体系を変更 | BC9: 更新入出力仕様_品目マスタ 補足説明資料_mcframeとのキー比較 更新入出力仕様_（アドオン）事業所別原紙巾マスタ 更新入出力仕様_（アドオン）原紙マスタ | BM9: 44889 | BR9: 44889
BM10: MDSOL | BR10: MDSOL
A11: 2 | F11: 仕様連絡書：RCS-1062に伴う下記改定を実施 案件NOをDBの項目は、案件NO(親)＋案件NO(子)＋案件NO(部材)に分割する ※画面項目は、1つとする | BC11: 検索入出力仕様、更新入出力仕様_品目マスタ | BM11: 44894 | BR11: 44895
BM12: MDSOL | BR12: MDSOL 奥本
A13: 2 | F13: 仕様連絡書：RCS-1062に伴う下記改定を実施 FSC製品区分に統合(FSC認証製品＝FSC製品区分)、FSC材質区分が重複２つ | BC13: 検索入出力仕様 | BM13: 44894 | BR13: 44895
BM14: MDSOL | BR14: MDSOL 奥本
A15: 2 | F15: 仕様連絡書：RCS-1062に伴う下記改定を実施 高品質→高管理、各画面から項目削除、DB項目としては残す | BC15: 検索入出力仕様 更新入出力仕様_品目マスタ | BM15: 44896 | BR15: 44896
BM16: MDSOL | BR16: MDSOL 奥本
A17: 3 | F17: 仕様連絡書：RCS-1170に伴う下記改定を実施 印刷原紙の品目単位を追加する | BC17: 概要 処理概要 検索入出力仕様 更新入出力仕様_品目マスタ | BM17: 44945 | BR17: 44945
BM18: MDSOL | BR18: MDSOL 奥本
A19: 3 | F19: 仕様連絡書：RCS-1170に伴う下記改定を実施 原紙マスタの更新を削除する | BC19: 検索入出力仕様 更新入出力仕様_品目マスタ | BM19: 44945 | BR19: 44945
BM20: MDSOL石田 | BR20: MDSOL 奥本
A21: 4 | F21: 仕様連絡書：RCS-1115 処理概要図にMRP対象マップを追加 | BC21: 処理概要図 | BM21: 44959 | BR21: 44960
BM22: MDSOL石田 | BR22: MDSOL 奥本
A23: 4 | F23: 仕様連絡書：RCS-1115 概要シートと更新入出力仕様の表列を合わせる。 ※更新入出力仕様は概要をさらに細分化したものとする。 | BC23: 概要 更新入出力仕様_○○ | BM23: 44960 | BR23: 44960
BM24: MDSOL石田 | BR24: MDSOL 奥本
A25: 5 | F25: シ設計集中見直し（RCS-1229）:参照元_見積計算書ＮＯ 項目削除／項目見直し(見積計算書ＮＯ) | BC25: 検索入出力仕様 | BM25: 44964 | BR25: 44964
BM26: MDSOL野村 | BR26: MDSOL 奥本
A27: 6 | F27: シ設計集中見直し（RCS-1229）:品目区分と品目区分詳細設定の設定方法記載 | BC27: 更新入出力仕様_品目マスタ、 補足説明資料_品目区分設定方法 | BM27: 44965 | BR27: 44966
BM28: MDSOL石田 | BR28: MDSOL 奥本
A29: 6 | F29: シ設計集中見直し（RCS-1229）:マスタ設定値の変更 | BC29: 更新入出力仕様_品目詳細マスタ、 更新入出力仕様_BOMマスタ | BM29: 44965 | BR29: 44966
BM30: MDSOL石田 | BR30: MDSOL 奥本
A31: 6 | F31: シ設計集中見直し（RCS-1229）:本支店単価マスタの連携廃止 | BC31: 概要、処理概要、 更新入出力仕様_本支店単価マスタ、補足説明資料_mcframeとのキー比較 | BM31: 44965 | BR31: 44966
BM32: MDSOL石田 | BR32: MDSOL 奥本
A33: 6 | F33: シ設計集中見直し（RCS-1229）:刷版手配の親子関係補足 | BC33: 補足説明資料_親子関係 | BM33: 44965 | BR33: 44966
BM34: MDSOL石田 | BR34: MDSOL 奥本
A35: 7 | F35: シ設計集中見直し（RCS-1229）:事業所別原紙巾マスタのキー見直しによる訂正 | BC35: 更新入出力仕様_（アドオン）事業所別原紙巾マスタ | BM35: 44966 | BR35: 44966
BM36: MDSOL石田 | BR36: MDSOL 奥本
A37: 8 | F37: 仕様連絡書：RCS-1369 に伴う下記改定を実施 品目区分詳細の訂正 商品・製品印刷原紙の削除 | BC37: 補足説明資料_品目区分設定方法 | BM37: 45016 | BR37: 45016
BM38: MDSOL石田 | BR38: MDSOL 奥本
A39: 8 | F39: 仕様連絡書：RCS-1369 に伴う下記改定を実施 本支店単価マスタの連携復活 | BC39: 概要、処理概要、 更新入出力仕様_本支店単価マスタ、補足説明資料_mcframeとのキー比較 | BM39: 45016 | BR39: 45016
BM40: MDSOL石田 | BR40: MDSOL 奥本

Sheet 概要
A1: =表紙!A54 -> Webシステム | O1: 文書名 | AC1: モジュールID | AJ1: =表紙!AJ63 -> MS | AQ1: モジュール名 | AX1: =表紙!AX63 -> 見積管理 | BL1: 文書番号 | BU1: Version | CB1: Rev.
O2: =表紙!O64 -> アドオン設計書 | AC2: サブモジュールID | AJ2: =表紙!AJ64 -> MSBB | AQ2: サブモジュール名 | AX2: =表紙!AX64 -> Webシステム | BL2: =表紙!BL64 -> M7-US-1140 | BU2: =表紙!BU64 -> 7.0.2 | CB2: =表紙!CB64 -> 8
O3: =RIGHT(CELL("filename",$A$1),LEN(CELL("filename",$A$1))-FIND("]",CELL("filename",$A$1))) -> 概要 | AC3: 表題 | AJ3: =表紙!AJ65 -> - | AQ3: =表紙!AQ65 -> 製品マスタ連携
AO5: 概要
B7: 【業務要件】
C8: カスタマイズ | G8: 内容
C9: No.
C10: 97 | G10: ・WEB製品マスタ、受注からmcframe7への品目関連マスタ送信
B13: 【説明】
C14: 製品基本マスタ、製品加工工程マスタ、製品ロット別単価マスタからmcframeのマスタへ登録・更新を行う。
C15: 起動はジョブ起動となる。
B17: 【目的】
C18: ・WEBの製品マスタ、受注からmcframe７の販売管理、生産管理が動作するようにマスタ連携する。
AP20: 凡例
C21: 製品マスタ承認・更新時にマスタ連携を実施する。 | AR21: 〇：連携対象
M22: 品目区分 | AR22: △：条件により連携 | AZ22: 品目区分説明
C23: 製品マスタ連携対象テーブル | M23: 商品 | U23: 製品 | AC23: 中間品 | AK23: 資材 | AS23: 原材料 | AW23: 原材料 | BA23: 原材料 | BI23: 商品：商品構成あり（加工品）、商品構成なし（諸口品目在庫管理対象） | CJ23: REV4.0 更新入出力仕様に合わせて資材の追加
C24: テーブル | M24: 構成あり | Q24: 構成なし | U24: 内 | Y24: 外 | AC24: 内 | AG24: 外 | AK24: 在庫管理品 | AO24: 非在庫品 | AS24: 購買 | AW24: 印刷原紙 | BA24: 諸口 | BI24: 製品：製品
C25: 品目マスタ（共通） | M25: ○ | U25: 〇 | AC25: 〇 | AK25: ○ | AS25: 〇 | AW25: 〇 | BI25: 中間品：工程仕掛品
C26: 品目マスタ（会社） | M26: ○ | U26: 〇 | AC26: 〇 | AK26: ○ | AS26: 〇 | AW26: 〇 | BI26: 原材料：カートン、コートボール
C27: 品目詳細マスタ | M27: ○ | U27: 〇 | Y27: 〇 | AC27: 〇 | AG27: 〇 | AK27: ○ | AS27: 〇 | AW27: 〇 | BI27: 原材料（印刷原紙）：印刷原紙
C28: 品目格納先マスタ | M28: △ | U28: △ | Y28: △ | AC28: △ | AG28: △ | AK28: △ | AS28: △ | AW28: △ | BI28: 原材料（諸口）：梱包資材等
C29: BOMマスタ | M29: ○ | U29: 〇 | AC29: 〇 | AK29: 〇 | BI29: ※１ 連携処理で番号採番。番号体系は「コード体系」参照
C30: 品目工程マスタ | M30: ○ | U30: 〇 | Y30: 〇 | AC30: 〇 | AG30: 〇 | BI30: ※２ 印刷原紙とそれ以外で番号体系が異なる
C31: 工程工数マスタ | M31: ○ | U31: 〇 | AC31: 〇
C32: 得意先販売単価マスタ | M32: ○ | U32: 〇
C33: 加工単価マスタ | M33: △ | Y33: △ | AG33: △
C34: 購買単価マスタ | AK34: △ | AS34: △ | AW34: △
C35: （アドオン）本支店単価マスタ | M35: ○ | U35: 〇 | CJ35: REV6.0 本支店単価マスタの廃止 | CU35: REV8.0 本支店単価マスタの復活
C36: （アドオン）原紙マスタ | AW36: 〇
C37: （アドオン）事業所別原紙巾マスタ | AW37: 〇
C38: 品目単位マスタ | AW38: 〇 | CJ38: REV3.0 品目単位マスタの追加
AP40: 凡例
C41: シート受注、商品購買受注時にマスタ連携を実施する。 | AR41: 〇：連携対象
M42: 品目区分 | AR42: △：条件により連携 | BD42: 品目区分説明
C43: 受注マスタ連携対象テーブル | M43: 商品 | Y43: 製品 | AG43: 中間品 | AO43: 資材 | AW43: 原材料 | BA43: 原材料 | BE43: 原材料 | BJ43: 商品：商品構成あり（加工品）、商品構成なし（諸口品目在庫管理対象） | CJ43: REV4.0 更新入出力仕様に合わせて資材の追加
C44: テーブル | M44: 構成あり | Q44: 構成なし | U44: 版型 | Y44: 内 | AC44: 外 | AG44: 内 | AK44: 外 | AO44: 在庫管理品 | AS44: 非在庫品 | AW44: 購買 | BA44: 印刷原紙 | BE44: 諸口 | BJ44: 製品：製品
C45: 品目マスタ（共通） | U45: ○ | Y45: 〇 | AG45: 〇 | AO45: ○ | AW45: 〇 | BA45: 〇 | BJ45: 中間品：工程仕掛品
C46: 品目マスタ（会社） | U46: ○ | Y46: 〇 | AG46: 〇 | AO46: ○ | AW46: 〇 | BA46: 〇 | BJ46: 原材料：カートン、コートボール
C47: 品目詳細マスタ | Y47: 〇 | AC47: 〇 | AG47: 〇 | AK47: 〇 | AO47: ○ | AW47: 〇 | BA47: 〇 | BJ47: 原材料（印刷原紙）：印刷原紙
C48: 品目格納先マスタ | Y48: △ | AC48: △ | AG48: △ | AK48: △ | AO48: △ | AW48: △ | BA48: △ | BJ48: 原材料（諸口）：梱包資材等
C49: BOMマスタ | Y49: 〇 | AG49: 〇 | AO49: 〇 | BJ49: ※１ 連携処理で番号採番。番号体系は「コード体系」参照
C50: 品目工程マスタ | Y50: 〇 | AC50: 〇 | AG50: 〇 | AK50: 〇 | BJ50: ※２ 印刷原紙とそれ以外で番号体系が異なる
C51: 工程工数マスタ | Y51: 〇 | AG51: 〇
C52: 得意先販売単価マスタ | Y52: 〇
C53: 加工単価マスタ | AC53: △ | AK53: △
C54: 購買単価マスタ | AO54: △ | AW54: △ | BA54: △
C55: （アドオン）本支店単価マスタ | CJ55: REV8.0 本支店単価マスタの復活
C56: （アドオン）原紙マスタ | BA56: 〇
C57: （アドオン）事業所別原紙巾マスタ | BA57: 〇
C58: 品目単位マスタ | BA58: 〇 | CJ58: REV3.0 品目単位マスタの追加
C60: ※商品購買受注は受注明細で発注先、発注単位、購買単価を指定するため、購買単価マスタを作成しない
B64: 【処理関連図/サービス関連図】
C65: ※処理・サービス関連図シートに詳細記載
B69: 【SQLID一覧】
C70: なし
B72: 【ソート順】
C73: なし
B75: 【データアクセスコントロール】
C76: なし
B78: 【制約】
C79: ・支給品は無償支給固定（支給単価マスタ不要）となるため、支給単価マスタは連携しない。
C80: ・受注起動のマスタ連携処理では連携対象製品CDは手配NO別MRPの対象にはならない。受注登録のタイミングで処理対象となる。
C81: ・[製品マスタ連携対象テーブル」、「受注マスタ連携対象テーブル」記載以外の製品マスタ関連データはmcframe7には連携されない。連携対象外の項目はmcframe7から直接参照する事とする。

Sheet レイアウト_
A1: =表紙!A54 -> Webシステム | K1: 文書名 | U1: モジュールID | Z1: =表紙!$AJ$63 -> MS | AE1: モジュール名 | AJ1: =表紙!$AX$63 -> 見積管理 | AS1: 文書番号 | AZ1: Version | BF1: Rev.
K2: =表紙!O64 -> アドオン設計書 | U2: ｻﾌﾞﾓｼﾞｭｰﾙID | Z2: =表紙!$AJ$64 -> MSBB | AE2: ｻﾌﾞﾓｼﾞｭｰﾙ名 | AJ2: =表紙!$AX$64 -> Webシステム | AS2: =表紙!$BL$64 -> M7-US-1140 | AZ2: =表紙!$BU$64 -> 7.0.2 | BF2: =表紙!$CB$64 -> 8
K3: =RIGHT(CELL("filename",$A$1),LEN(CELL("filename",$A$1))-FIND("]",CELL("filename",$A$1))) -> レイアウト_ | U3: 表題 | Z3: =表紙!$AJ$65 -> - | AE3: =表紙!$AQ$65 -> 製品マスタ連携
A5: 画面イメージ
B7: ≫凡例
Q8: ・・・ | S8: ボタン
C9: 見積計算書№ | Q9: ・・・ | S9: 検索項目(検索画面表示選択)
C10: 品名 | Q10: ・・・ | S10: 入力項目
C11: 得意先 | Q11: ・・・ | S11: 表示項目(得意先名称、原紙名等)
C12: 操作種別 | I12: ●登録 | M12: ○訂正 | Q12: ・・・ | S12: 選択項目(一つのみ選択可能)
C13: 受注区分 | Q13: ・・・ | S13: 選択項目(一つのみ選択可能)
C14: 作業順 | I14: ☑AAA | M14: ☑BBB | Q14: ・・・ | S14: 選択項目(複数選択可能)
C16: TOP画面
D21: 操作種別 | J21: ●登録 | N21: ○訂正 | R21: ○削除 | V21: ○参照
D23: 御見積書№ | J23: (件名:オートフィルタ) | AD23: 製品CD | AJ23: (品名:オートフィルタ)
AD24: (セット品)
D25: ↑新規時 有効 | AD25: ↑訂正、削除、参照時 有効
D31: 案件№
D32: 得意先
D34: セット部品
D36: № | F36: 詳細 | I36: 製品CD | Q36: 製品名
E37: 1 | Q37: 味比べ3P箱 (見・蓋・仕切り)
D40: 部材
D42: № | F42: 確定 | I42: セット | L42: 詳細 | O42: 見積計算書№ | T42: 製品CD | AB42: 製品名
E43: 1 | F43: □ | I43: □ | AB43: 味比べ3P箱 身
E44: 2 | F44: □ | I44: □ | AB44: 味比べ3P箱 蓋
E45: 3 | F45: □ | I45: □ | AB45: 味比べ3P箱 仕切り
C54: 製品マスタ入力詳細（部材）
D59: 操作種別 | J59: ●登録 | N59: ○訂正 | R59: ○削除 | V59: ○参照
D61: 製品CD
D63: 案件№
D64: 得意先
D66: 受注区分 | J66: 1 | L66: 製品 | T66: 製品区分 | Z66: 13 | AB66: Gプリント | AJ66: 責任部門 | AP66: 5120 | AU66: 名古屋製造 | AZ66: FSC認証管理№
D67: セット比率 | J67: 1.000 | T67: 製品用途 | Z67: 81 | AB67: 雑貨 | AJ67: シート部門 | AP67: 5120 | AU67: 名古屋製造 | AZ67: 物流区分 | BJ67: (1:物流箱)
D68: 機密情報 | N68: (1:社外秘) | T68: 奪取区分 | AD68: (1:奪取) | AJ68: 重要区分 | AT68: (A B C D) | AZ68: Mチェン | BJ68: (1:ライバル、2:社内)
D69: 品質区分 | N69: (1:高品質) | T69: 出荷検査 | AD69: (1:要検査) | AJ69: 高管理 | AT69: (1:高) | AZ69: 製品計上区分
D70: ユネスコマーク | N70: (1:使用) | T70: 折鶴マーク | AD70: (1:広島折鶴、2:CP折鶴) | AZ70: FSC認証製品 | BJ70: (1:客、2:CP、3:マークナシ)
D71: 4M契約 | N71: (1:有) | T71: TKP折れシワ基準 | AD71: (1:標準、2:高品質) | AZ71: FSC材質区分 | BJ71: (1:ミックス、2:リサイクル)
D72: 容リ支払 | T72: 識別表示 | AZ72: 食品安全 | BJ72: (1:FSSC22000)
D74: 使用料 | M74: .0 | N74: / | Q74: .0 | R74: / | U74: .0 | V74: / | Y74: .0
D75: 個別包装使用量 | M75: .0 | Q75: .0 | R75: /
D77: 品名 | AD77: 品名カナ
D78: 別品名 | AD78: 客先品番 | AU78: JANコード
D80: シート 段 | V80: メーカー
D81: 構成 | F81: 表 | AM81: 65,526
F82: 中 | AM82: 10,694-
F83: 裏 | V83: 001 | AB83: 王子マテ
D86: 33:コート | J86: 表幅 | M86: 幅 | Q86: 流れ | V86: コルスリ | AA86: 割数 | AE86: 断裁区分
D87: シート寸法 | P87: × | V87: 4 | X87: 化半 | AH87: (1:外注)
D88: スリッター | P88: ×
D90: 印刷備考 | AD90: 製造備考
D91: 横持備考 | AD91: 納入備考
D92: 配車備考 | AD92: 伝票備考
D94: 号機指定 | S94: 受注回数 | AD94: デザイン提案№
C103: 製品マスタ入力詳細（加工）
D108: 操作種別 | J108: ●登録 | N108: ○訂正 | R108: ○削除 | V108: ○参照
D110: 製品CD
D112: 案件№
D113: 得意先
D120: 加工工程
D122: № | F122: 工程順 | I122: 工程内順序 | L122: 工程CD | O122: 工程名 | T122: 親工程CD | Y122: 親工程名 | AD122: 号機/発注先 | AI122: 使用材料 | AN122: 仕様1 | AR122: 仕様2 | AV122: 仕様3 | AZ122: 仕様4 | BD122: 仕様5 | BH122: 仕様6 | BL122: 仕様7 | BP122: 行追加 | BS122: 行削除
O123: 作業工程CD | T123: 作業名 | Y123: 作業順 | AD123: 号機/発注先 | AI123: 使用材料
E124: 1 | L124: 600 | O124: トムソン | T124: 760 | Y124: タンデム | AD124: 1
O125: 600 | T125: トムソン | Y125: 1 | AD125: 1号機
E126: 2 | L126: 760 | O126: タンデム | T126: 950 | Y126: 包装 | AD126: 1
E128: 3 | L128: 950 | O128: 包装
C139: 製品マスタ入力詳細（価格）
D144: 操作種別 | J144: ●登録 | N144: ○訂正 | R144: ○削除 | V144: ○参照
D146: 製品CD
D148: 案件№
D149: 得意先
D151: 売価区分 | N151: (1:セット、2:単品) | T151: 数量単位 | AJ151: 単価単位 | AT151: (2:枚、4:個)
D153: 現行単価 | T153: 新単価 | AJ153: 新本支店単価
D154: 単価適用日 | T154: 適用予定日 | AJ154: 適用予定日
T155: 単価適用基準 | AD155: (0:受注日、1:納入日基準/出荷、受注の単価も更新)
D158: № | F158: ロット | K158: セット単価 | O158: 個別単価 | V158: 新セット単価 | Z158: 新個別単価 | AI158: 本支店単価 | AP158: 新本支店単価 | AV158: 仕入単価
AV159: (購入品)
E160: 1 | I160: 以上 | T160: ← | AN160: ←
E161: 2 | I161: 以上 | T161: ← | AN161: ←
E162: 3 | I162: 以上 | T162: ← | AN162: ←
E163: 4 | I163: 以上 | T163: ← | AN163: ←
E164: 5 | I164: 以上 | T164: ← | AN164: ←
E165: 6 | I165: 以上 | T165: ← | AN165: ←
E166: 7 | I166: 以上 | T166: ← | AN166: ←
E167: 8 | I167: 以上 | T167: ← | AN167: ←
D169: 購買品の発注先
D170: 運賃請求 | N170: (0:込み、1:別途) | V170: 定数出荷 | AF170: (1:定数出荷)
D172: 予備必要 | J172: 納入予備 | S172: 製造予備 | AB172: 営業サンプル | AJ172: 毎回必要な場合に設定
AJ173: 初回のみの場合の予備は受注入力で入力する。
D174: 納入伝票 | N174: (0:標準、1:コクヨ、2:指定) | W174: ※未使用
D175: 売上伝票 | N175: (0:標準、1:コクヨ、2:指定) | W175: ※未使用

Sheet 処理詳細
A1: =表紙!A54 -> Webシステム | K1: 文書名 | U1: モジュールID | Z1: =表紙!$AJ$63 -> MS | AE1: モジュール名 | AJ1: =表紙!$AX$63 -> 見積管理 | AS1: 文書番号 | AZ1: Version | BF1: Rev.
K2: =表紙!O64 -> アドオン設計書 | U2: ｻﾌﾞﾓｼﾞｭｰﾙID | Z2: =表紙!$AJ$64 -> MSBB | AE2: ｻﾌﾞﾓｼﾞｭｰﾙ名 | AJ2: =表紙!$AX$64 -> Webシステム | AS2: =表紙!$BL$64 -> M7-US-1140 | AZ2: =表紙!$BU$64 -> 7.0.2 | BF2: =表紙!$CB$64 -> 8
K3: =RIGHT(CELL("filename",$A$1),LEN(CELL("filename",$A$1))-FIND("]",CELL("filename",$A$1))) -> 処理詳細 | U3: 表題 | Z3: =表紙!$AJ$65 -> - | AE3: =表紙!$AQ$65 -> 製品マスタ連携
A5: No | B5: 入力 | J5: 処理 | BD5: 出力
A6: 1 | B6: 初期表示
A12: 2 | B12: 画面操作
A18: 3 | B18: 検索【F1】

Sheet 処理・サービス関連図
A1: =表紙!A54 -> Webシステム | K1: 文書名 | U1: モジュールID | Z1: =表紙!$AJ$63 -> MS | AE1: モジュール名 | AJ1: =表紙!$AX$63 -> 見積管理 | AS1: 文書番号 | AZ1: Version | BF1: Rev.
K2: =表紙!O64 -> アドオン設計書 | U2: ｻﾌﾞﾓｼﾞｭｰﾙID | Z2: =表紙!$AJ$64 -> MSBB | AE2: ｻﾌﾞﾓｼﾞｭｰﾙ名 | AJ2: =表紙!$AX$64 -> Webシステム | AS2: =表紙!$BL$64 -> M7-US-1140 | AZ2: =表紙!$BU$64 -> 7.0.2 | BF2: =表紙!$CB$64 -> 8
K3: =RIGHT(CELL("filename",$A$1),LEN(CELL("filename",$A$1))-FIND("]",CELL("filename",$A$1))) -> 処理・サービス関連図 | U3: 表題 | Z3: =表紙!$AJ$65 -> - | AE3: =表紙!$AQ$65 -> 製品マスタ連携
BM25: REV4.0 品質対応 MRP処理対象マップテーブルの追加

Sheet 処理概要
A1: =表紙!A54 -> Webシステム | K1: 文書名 | U1: モジュールID | Z1: =表紙!$AJ$63 -> MS | AE1: モジュール名 | AJ1: =表紙!$AX$63 -> 見積管理 | AS1: 文書番号 | AZ1: Version | BF1: Rev.
K2: =表紙!O64 -> アドオン設計書 | U2: ｻﾌﾞﾓｼﾞｭｰﾙID | Z2: =表紙!$AJ$64 -> MSBB | AE2: ｻﾌﾞﾓｼﾞｭｰﾙ名 | AJ2: =表紙!$AX$64 -> Webシステム | AS2: =表紙!$BL$64 -> M7-US-1140 | AZ2: =表紙!$BU$64 -> 7.0.2 | BF2: =表紙!$CB$64 -> 8
K3: =RIGHT(CELL("filename",$A$1),LEN(CELL("filename",$A$1))-FIND("]",CELL("filename",$A$1))) -> 処理概要 | U3: 表題 | Z3: =表紙!$AJ$65 -> - | AE3: =表紙!$AQ$65 -> 製品マスタ連携
A5: No | B5: 入力 | J5: 処理 | BD5: 出力
A6: 1 | B6: 初期処理
B7: 入力引数）
C8: 起動区分
J9: １．起動区分判定
K10: 1-1)処理区分：1 製品マスタの場合
L11: 製品マスタ連携処理を実行する。
K12: 1-2)処理区分：それ以外 受注の場合
L13: 受注マスタ連携処理を実行する
A15: ２ | B15: 製品マスタ連携処理
J16: １．処理対象取得
K17: 1-1)製品基本マスタ取得
L18: 処理対象の製品基本マスタ情報を取得する。 | BD18: 検索入出力仕様1
L19: ・検索条件
L20: 製品基本マスタ.ステータス：承認済み
L21: 製品基本マスタ.mcframe7転送FLG:未転送
J24: 2 | K24: マスタ連携処理
L25: 製品CDごとに以下処理を実施する。
M26: １）製品関連マスタの取得
N27: 製品CDを条件に製品加工工程マスタを取得する。 | BD27: 検索入出力仕様2
N28: 製品CDを条件に製品加工材料マスタを取得する。 | BD28: 検索入出力仕様3
N29: 製品CDを条件に製品連産品マスタを取得する。 | BD29: 検索入出力仕様4
N30: 製品CDを条件に製品ロット別単価マスタを取得する。 | BD30: 検索入出力仕様5
M31: ２）製品加工工程マスタのデータ分、以下処理を実施する。
N32: 2-1)品目マスタマッピング | BD32: 更新入出力仕様_品目マスタ
O33: ※既に登録されていないか？製品CDと枝番２の工程で確認をする。
N34: 2-2)品目詳細マスタマッピング | BD34: 更新入出力仕様_品目詳細マスタ
N35: 2-3)品目工程マスタマッピング | BD35: 更新入出力仕様_品目工程マスタ
N36: 2-4)品目格納先マスタマッピング | BD36: 更新入出力仕様_品目格納先マスタ
N37: 2-5)工程工数マスタマッピング | BD37: 更新入出力仕様_工程工数マスタ
N38: 2-6)購買単価マスタマッピング | BD38: 更新入出力仕様_購買単価マスタ
N39: 2-7)加工単価マスタマッピング | BD39: 更新入出力仕様_加工単価マスタ
N40: 2-8)（アドオン）事業所別原紙巾マスタマッピング | BD40: 更新入出力仕様_（アドオン）事業所別原紙巾マスタ
N41: 2-9)（アドオン）原紙マスタマッピング | BD41: 更新入出力仕様_（アドオン）原紙マスタ
M42: ３）製品加工材料マスタを元にBOMマスタを作成する
N43: ３－１）BOMマスタの登録 | BD43: 更新入出力仕様_BOMマスタ
M44: ４）製品処理
N45: 4-1）客先販売単価マスタの登録 | BD45: 更新入出力仕様_客先販売単価マスタ
N46: 4-2）（アドオン）本支店単価マスタ の登録 | BD46: 更新入出力仕様_（アドオン）本支店単価マスタ | BM46: REV6.0 本支店単価マスタの廃止 | BX46: REV8.0 本支店単価マスタの復活
N47: 4-3）製品基本マスタの更新 | BD47: 更新入出力仕様.NO1
M48: ５)受注加工工程マスタの更新
O49: 5-1)以下条件で対象の受注加工工程マスタを取得し、OBJECTに格納する。0件の場合は６）へSKIP
O50: SELECT
R51: 受注加工工程マスタ.＊
O52: FROM
R53: mcf.受注明細 受注 、WEB受注明細 WEB受注、 受注加工工程 受注加工
O54: WHERE
R55: NOT EXISTS（SELECT
X56: １ FROM 品目オーダ情報 品目オーダ
W57: WHERE
W58: 受注.手配NO1 ＝ 品目オーダ.手配NO１
W59: AND 受注.手配NO2 ＝ 品目オーダ.手配NO2
W60: AND 受注.手配NO3 ＝ 品目オーダ.手配NO3
W61: AND 品目オーダ.品目オーダ状況区分 IN （2:保存,3:確定,4:一部指図・発注済,5:指図・発注済,6:完了）
R62: ）
R63: AND 受注.品目CD = 製品基本マスタ.製品連番
R64: AND 受注.品目枝番１ = 製品基本マスタ.製品枝番
R65: AND 受注.受注NO ＝WEB受注.受注NO
R66: AND 受注.受注明細NO ＝WEB受注.受注明細NO
R67: AND WEB受注.WEB受注NO ＝受注加工.WEB受注NO
R68: AND WEB受注.WEB受注明細NO ＝受注加工.WEB受注明細NO
O69: 5-2)受注加工工程マスタデータを削除する。
O70: 5-3)受注加工工程マスタを製品加工工程マスタを元に登録する。 | BD70: 更新入出力仕様2
O71: 5-4)MRP処理対象マップの追加を行う。 | BD71: 更新入出力仕様3
M72: 6)次の製品CDの処理へ
J73: ３．取込処理
M74: ２．で編集した内容を元に取込処理を実行する。
M75: ３－１）1テーブルずつmcfテーブルへ更新する。
M76: ３－２）途中でエラーとなった場合、全体をロールバックする。
M77: ３－３）正常登録できた場合、COMMITする。
A79: ３ | B79: 受注マスタ連携処理
J80: １．処理対象取得
K81: 1-1)受注明細を取得する
L82: 処理対象の受注明細情報を取得する。 | BD82: 検索入出力仕様6
L83: ・検索条件
L84: WEB受注明細.ステータス：承認済み
L85: WEB受注明細.mcframe7転送FLG:未転送
J86: 2 | K86: マスタ連携処理
K87: 製品CDごとに以下処理を実施する。
K88: 2-1)製品区分大がシート
M89: 2-1-1)製品関連マスタの取得
N90: 製品CDを条件に受注加工工程マスタを取得する。 | BD90: 検索入出力仕様7
N91: 製品CDを条件に受注加工材料マスタを取得する。 | BD91: 検索入出力仕様8
M92: ２-1-2)受注加工工程マスタのデータ分、以下処理を実施する。
N93: ２-1-2-1)品目マスタマッピング | BD93: 更新入出力仕様_品目マスタ
O94: ※既に登録されていないか？製品CDと枝番２の工程で確認をする。
N95: ２-1-2-2)品目詳細マスタマッピング | BD95: 更新入出力仕様_品目詳細マスタ
N96: ２-1-2-3)品目工程マスタマッピング | BD96: 更新入出力仕様_品目工程マスタ
N97: ２-1-2-4)品目格納先マスタマッピング | BD97: 更新入出力仕様_品目格納先マスタ
N98: ２-1-2-5)工程工数マスタマッピング | BD98: 更新入出力仕様_工程工数マスタ
N99: ２-1-2-6)購買単価マスタマッピング | BD99: 更新入出力仕様_購買単価マスタ
N100: ２-1-2-7)加工単価マスタマッピング | BD100: 更新入出力仕様_加工単価マスタ
N101: ２-1-2-8)（アドオン）事業所別原紙巾マスタマッピング | BD101: 更新入出力仕様_(アドオン）事業所別原紙巾マスタ
N102: ２-1-2-9)（アドオン）原紙マスタマッピング | BD102: 更新入出力仕様_（アドオン）原紙マスタ
N103: ２-1-2-10)品目単位マスタマッピング | BD103: 更新入出力仕様_品目単位マスタ | BM103: REV3.0 品目単位マスタの追加
M104: ２-1-3)受注加工材料マスタを元にBOMマスタを作成する
N105: ２-1-3-1)BOMマスタの登録 | BD105: 更新入出力仕様_BOMマスタ
...

Sheet 引数説明
A1: =表紙!A54 -> Webシステム | K1: 文書名 | U1: モジュールID | Z1: =表紙!$AJ$63 -> MS | AE1: モジュール名 | AJ1: =表紙!$AX$63 -> 見積管理 | AS1: 文書番号 | AZ1: Version | BF1: Rev.
K2: =表紙!O64 -> アドオン設計書 | U2: ｻﾌﾞﾓｼﾞｭｰﾙID | Z2: =表紙!$AJ$64 -> MSBB | AE2: ｻﾌﾞﾓｼﾞｭｰﾙ名 | AJ2: =表紙!$AX$64 -> Webシステム | AS2: =表紙!$BL$64 -> M7-US-1140 | AZ2: =表紙!$BU$64 -> 7.0.2 | BF2: =表紙!$CB$64 -> 8
K3: =RIGHT(CELL("filename",$A$1),LEN(CELL("filename",$A$1))-FIND("]",CELL("filename",$A$1))) -> 引数説明 | U3: 表題 | Z3: =表紙!$AJ$65 -> - | AE3: =表紙!$AQ$65 -> 製品マスタ連携
B5: オペレーションＩＤ/名称：SloRecvIfImp_Upd01/取込
A6: 必 | B6: 項目名 | N6: 説明 | AS6: 未設定時の振る舞い
B7: 得意先ＣＤ | M7: 受注受信ＩＦの検索条件

Sheet 検索入出力仕様
A1: =表紙!A54 -> Webシステム | K1: 文書名 | U1: モジュールID | Z1: =表紙!$AJ$63 -> MS | AE1: モジュール名 | AJ1: =表紙!$AX$63 -> 見積管理 | AS1: 文書番号 | AZ1: Version | BF1: Rev.
K2: =表紙!O64 -> アドオン設計書 | U2: ｻﾌﾞﾓｼﾞｭｰﾙID | Z2: =表紙!$AJ$64 -> MSBB | AE2: ｻﾌﾞﾓｼﾞｭｰﾙ名 | AJ2: =表紙!$AX$64 -> Webシステム | AS2: =表紙!$BL$64 -> M7-US-1140 | AZ2: =表紙!$BU$64 -> 7.0.2 | BF2: =表紙!$CB$64 -> 8
K3: =RIGHT(CELL("filename",$A$1),LEN(CELL("filename",$A$1))-FIND("]",CELL("filename",$A$1))) -> 検索入出力仕様 | U3: 表題 | Z3: =表紙!$AJ$65 -> - | AE3: =表紙!$AQ$65 -> 製品マスタ連携
A5: No | G5: 1 | H5: 製品基本マスタ | S5: ボタン | AH5: 備考
A6: 処理分類 | E6: 検索 | S6: ソート順
A7: No | C7: 転送先 | V7: 転送元 | AQ7: 説明
C8: 種 | D8: オブジェクト | K8: 項目名 | V8: 種 | W8: オブジェクト | AF8: 項目名
D9: 製品基本マスタ | K9: 製品コード | V9: T | W9: 製品基本マスタ | AF9: 製品コード
D10: 製品基本マスタ | K10: 品目コード | V10: T | W10: 製品基本マスタ | AF10: 品目コード
D11: 製品基本マスタ | K11: 枝番１ | V11: T | W11: 製品基本マスタ | AF11: 枝番１
D12: 製品基本マスタ | K12: 枝番２ | V12: T | W12: 製品基本マスタ | AF12: 枝番２
D13: 製品基本マスタ | K13: 枝番３ | V13: T | W13: 製品基本マスタ | AF13: 枝番３
D14: 製品基本マスタ | K14: 案件NO(親)、(子)、(部材) | V14: T | W14: 製品基本マスタ | AF14: 案件NO(親)、(子)、(部材) | BM14: Rev2.0 変更
D15: 製品基本マスタ | K15: 御見積書NO | V15: T | W15: 製品基本マスタ | AF15: 御見積書NO
D16: 製品基本マスタ | K16: 見積計算書NO | V16: T | W16: 製品基本マスタ | AF16: 見積計算書NO
D17: 製品基本マスタ | K17: 参照元_見積計算書NO | V17: T | W17: 製品基本マスタ | AF17: 参照元_見積計算書NO | BM17: Rev5.0 見積計算書ＮＯ項目 重複削除
D18: 製品基本マスタ | K18: 得意先コード | V18: T | W18: 製品基本マスタ | AF18: 得意先コード
D19: 製品基本マスタ | K19: セット製品CD | V19: T | W19: 製品基本マスタ | AF19: セット製品CD
D20: 製品基本マスタ | K20: セット品名 | V20: T | W20: 製品基本マスタ | AF20: セット品名
D21: 製品基本マスタ | K21: 親子区分 | V21: T | W21: 製品基本マスタ | AF21: 親子区分
D22: 製品基本マスタ | K22: 顧客品名1 | V22: T | W22: 製品基本マスタ | AF22: 顧客品名1
D23: 製品基本マスタ | K23: 顧客品名2 | V23: T | W23: 製品基本マスタ | AF23: 顧客品名2
D24: 製品基本マスタ | K24: 顧客品番 | V24: T | W24: 製品基本マスタ | AF24: 顧客品番
D25: 製品基本マスタ | K25: CP品名1 | V25: T | W25: 製品基本マスタ | AF25: CP品名1
D26: 製品基本マスタ | K26: CP品名2 | V26: T | W26: 製品基本マスタ | AF26: CP品名2
D27: 製品基本マスタ | K27: JANコード | V27: T | W27: 製品基本マスタ | AF27: JANコード
D28: 製品基本マスタ | K28: セット比率 | V28: T | W28: 製品基本マスタ | AF28: セット比率
D29: 製品基本マスタ | K29: 製品用途 | V29: T | W29: 製品基本マスタ | AF29: 製品用途
... D36: 製品基本マスタ | K36: 出荷検査 | V36: T | W36: 製品基本マスタ | AF36: 出荷検査
D37: 製品基本マスタ | K37: 高品質 | V37: T | W37: 製品基本マスタ | AF37: 高品質 | BM37: Rev2.0 項目削除(高品質 項目削除)
D38: 製品基本マスタ | K38: 製品形状 | V38: T | W38: 製品基本マスタ | AF38: 製品形状
D39: 製品基本マスタ | K39: ユネスコマーク | V39: T | W39: 製品基本マスタ | AF39: ユネスコマーク
D40: 製品基本マスタ | K40: 折鶴マーク | V40: T | W40: 製品基本マスタ | AF40: 折鶴マーク
D41: 製品基本マスタ | K41: FSC認証製品 | V41: T | W41: 製品基本マスタ | AF41: FSC認証製品 | BM41: Rev2.0 項目削除(FSC認証製品＝FSC製品区分)
D42: 製品基本マスタ | K42: FSC材質区分 | V42: T | W42: 製品基本マスタ | AF42: FSC材質区分
D43: 製品基本マスタ | K43: FSC製品区分 | V43: T | W43: 製品基本マスタ | AF43: FSC製品区分
D44: 製品基本マスタ | K44: FSC管理NO | V44: T | W44: 製品基本マスタ | AF44: FSC管理NO
D45: 製品基本マスタ | K45: 4M契約 | V45: T | W45: 製品基本マスタ | AF45: 4M契約
D46: 製品基本マスタ | K46: TKP折れシワ基準 | V46: T | W46: 製品基本マスタ | AF46: TKP折れシワ基準
D47: 製品基本マスタ | K47: FSC材質区分 | V47: T | W47: 製品基本マスタ | AF47: FSC材質区分 | BM47: Rev2.0 項目削除(FSC材質区分が２つ)
D48: 製品基本マスタ | K48: 容リ支払 | V48: T | W48: 製品基本マスタ | AF48: 容リ支払
D49: 製品基本マスタ | K49: 識別表示 | V49: T | W49: 製品基本マスタ | AF49: 識別表示
D50: 製品基本マスタ | K50: 食品安全 | V50: T | W50: 製品基本マスタ | AF50: 食品安全
D51: 製品基本マスタ | K51: 製品区分_大 | V51: T | W51: 製品基本マスタ | AF51: 製品区分_大
D52: 製品基本マスタ | K52: 製品区分_中 | V52: T | W52: 製品基本マスタ | AF52: 製品区分_中
D53: 製品基本マスタ | K53: 製品区分_小 | V53: T | W53: 製品基本マスタ | AF53: 製品区分_小
D54: 製品基本マスタ | K54: 紙使用量ｇ | V54: T | W54: 製品基本マスタ | AF54: 紙使用量ｇ
D55: 製品基本マスタ | K55: プラ使用量ｇ | V55: T | W55: 製品基本マスタ | AF55: プラ使用量ｇ
D56: 製品基本マスタ | K56: ガラス使用量ｇ | V56: T | W56: 製品基本マスタ | AF56: ガラス使用量ｇ
D57: 製品基本マスタ | K57: ＰＥＴ使用量ｇ | V57: T | W57: 製品基本マスタ | AF57: ＰＥＴ使用量ｇ
D58: 製品基本マスタ | K58: 梱包紙使用量ｇ | V58: T | W58: 製品基本マスタ | AF58: 梱包紙使用量ｇ
D59: 製品基本マスタ | K59: 梱包プラ使用量ｇ | V59: T | W59: 製品基本マスタ | AF59: 梱包プラ使用量ｇ
... D99: 製品基本マスタ | K99: mcframe7転送FLG | V99: T | W99: 製品基本マスタ | AF99: mcframe7転送FLG
A100: No | G100: 2 | H100: 製品加工工程マスタ | S100: ボタン | AH100: 備考
A101: 処理分類 | E101: 検索 | S101: ソート順
A102: No | C102: 転送先 | V102: 転送元 | AQ102: 説明
C103: 種 | D103: オブジェクト | K103: 項目名 | V103: 種 | W103: オブジェクト | AF103: 項目名
D104: 製品加工工程マスタ | K104: 製品コード | V104: T | W104: 製品加工工程マスタ | AF104: 製品コード
D105: 製品加工工程マスタ | K105: 作業コード | V105: T | W105: 製品加工工程マスタ | AF105: 作業コード
D106: 製品加工工程マスタ | K106: 工程コード | V106: T | W106: 製品加工工程マスタ | AF106: 工程コード
D107: 製品加工工程マスタ | K107: TOP品目コード | V107: T | W107: 製品加工工程マスタ | AF107: TOP品目コード
D108: 製品加工工程マスタ | K108: TOP品目_枝番1 | V108: T | W108: 製品加工工程マスタ | AF108: TOP品目_枝番1
D109: 製品加工工程マスタ | K109: TOP品目_枝番2 | V109: T | W109: 製品加工工程マスタ | AF109: TOP品目_枝番2
D110: 製品加工工程マスタ | K110: TOP品目_枝番3 | V110: T | W110: 製品加工工程マスタ | AF110: TOP品目_枝番3
D111: 製品加工工程マスタ | K111: 品目コード | V111: T | W111: 製品加工工程マスタ | AF111: 品目コード
D112: 製品加工工程マスタ | K112: 枝番1 | V112: T | W112: 製品加工工程マスタ | AF112: 枝番1
D113: 製品加工工程マスタ | K113: 枝番2 | V113: T | W113: 製品加工工程マスタ | AF113: 枝番2
D114: 製品加工工程マスタ | K114: 枝番3 | V114: T | W114: 製品加工工程マスタ | AF114: 枝番3
D115: 製品加工工程マスタ | K115: ワーキンググループＣＤ | V115: T | W115: 製品加工工程マスタ | AF115: ワーキンググループＣＤ
... D151: 製品加工工程マスタ | K151: 製造順優先項目８ | V151: T | W151: 製品加工工程マスタ | AF151: 製造順優先項目８
A152: No | G152: 3 | H152: 製品加工材料マスタ | S152: ボタン | AH152: 備考
A153: 処理分類 | E153: 検索 | S153: ソート順
A154: No | C154: 転送先 | V154: 転送元 | AQ154: 説明
C155: 種 | D155: オブジェクト | K155: 項目名 | V155: 種 | W155: オブジェクト | AF155: 項目名
D156: 製品加工材料マスタ | K156: 製品コード | V156: T | W156: 製品加工材料マスタ | AF156: 製品コード
D157: 製品加工材料マスタ | K157: 工程コード | V157: T | W157: 製品加工材料マスタ | AF157: 工程コード
D158: 製品加工材料マスタ | K158: 材料CD | V158: T | W158: 製品加工材料マスタ | AF158: 材料CD
D159: 製品加工材料マスタ | K159: 工程材料区分 | V159: T | W159: 製品加工材料マスタ | AF159: 工程材料区分
D160: 製品加工材料マスタ | K160: 品目ＣＤ | V160: T | W160: 製品加工材料マスタ | AF160: 品目ＣＤ
D161: 製品加工材料マスタ | K161: 枝番１ | V161: T | W161: 製品加工材料マスタ | AF161: 枝番１
D162: 製品加工材料マスタ | K162: 枝番２ | V162: T | W162: 製品加工材料マスタ | AF162: 枝番２
D163: 製品加工材料マスタ | K163: 枝番３ | V163: T | W163: 製品加工材料マスタ | AF163: 枝番３
D164: 製品加工材料マスタ | K164: 受給区分 | V164: T | W164: 製品加工材料マスタ | AF164: 受給区分
D165: 製品加工材料マスタ | K165: 受給単価 | V165: T | W165: 製品加工材料マスタ | AF165: 受給単価
D166: 製品加工材料マスタ | K166: 並び順 | V166: T | W166: 製品加工材料マスタ | AF166: 並び順
A167: No | G167: 4 | H167: 製品連産品マスタ | S167: ボタン | AH167: 備考
A168: 処理分類 | E168: 検索 | S168: ソート順
A169: No | C169: 転送先 | V169: 転送元 | AQ169: 説明
C170: 種 | D170: オブジェクト | K170: 項目名 | V170: 種 | W170: オブジェクト | AF170: 項目名
D171: 製品連産品マスタ | K171: 製品コード | V171: T | W171: 製品連産品マスタ | AF171: 製品コード
D172: 製品連産品マスタ | K172: 工程コード | V172: T | W172: 製品連産品マスタ | AF172: 工程コード
D173: 製品連産品マスタ | K173: 行番 | V173: T | W173: 製品連産品マスタ | AF173: 行番
D174: 製品連産品マスタ | K174: 連産品名 | V174: T | W174: 製品連産品マスタ | AF174: 連産品名
D175: 製品連産品マスタ | K175: 数量比率 | W175: 製品連産品マスタ | AF175: 数量比率
D176: 製品連産品マスタ | K176: 次工程 | W176: 製品連産品マスタ | AF176: 次工程
A177: No | G177: 5 | H177: 製品ロット別単価マスタ | S177: ボタン | AH177: 備考
A178: 処理分類 | E178: 検索 | S178: ソート順
A179: No | C179: 転送先 | V179: 転送元 | AQ179: 説明
C180: 種 | D180: オブジェクト | K180: 項目名 | V180: 種 | W180: オブジェクト | AF180: 項目名
D181: 製品ロット別単価マスタ | K181: 製品コード | V181: T | W181: 製品ロット別単価マスタ | AF181: 製品コード
...

Sheet 更新入出力仕様
A1: =表紙!A54 -> Webシステム | K1: 文書名 | U1: モジュールID | Z1: =表紙!$AJ$63 -> MS | AE1: モジュール名 | AJ1: =表紙!$AX$63 -> 見積管理 | AS1: 文書番号 | AZ1: Version | BF1: Rev.
K2: =表紙!O64 -> アドオン設計書 | U2: ｻﾌﾞﾓｼﾞｭｰﾙID | Z2: =表紙!$AJ$64 -> MSBB | AE2: ｻﾌﾞﾓｼﾞｭｰﾙ名 | AJ2: =表紙!$AX$64 -> Webシステム | AS2: =表紙!$BL$64 -> M7-US-1140 | AZ2: =表紙!$BU$64 -> 7.0.2 | BF2: =表紙!$CB$64 -> 8
K3: =RIGHT(CELL("filename",$A$1),LEN(CELL("filename",$A$1))-FIND("]",CELL("filename",$A$1))) -> 更新入出力仕様 | U3: 表題 | Z3: =表紙!$AJ$65 -> - | AE3: =表紙!$AQ$65 -> 製品マスタ連携
A5: No | G5: 1 | H5: 製品基本マスタ | S5: ロジック名称 | AH5: 備考
A6: 処理分類 | E6: 更新
A7: No | C7: 転送先 | V7: 転送元 | AQ7: 説明
C8: 種 | D8: オブジェクト | K8: 項目名 | V8: 種 | W8: オブジェクト | AF8: 項目名
A9: 1 | C9: T | D9: 製品基本マスタ | K9: ステータス | AQ9: 固定:9 転送済み
A10: 2 | C10: T | D10: 製品基本マスタ | K10: mcframe7転送FLG | AQ10: 固定:1
A17: No | G17: 2 | H17: 受注加工工程マスタ | S17: ロジック名称 | AH17: 備考
A18: 処理分類 | E18: 追加
A19: No | C19: 転送先 | V19: 転送元 | AQ19: 説明
C20: 種 | D20: オブジェクト | K20: 項目名 | V20: 種 | W20: オブジェクト | AF20: 項目名
A21: 1 | C21: T | D21: 受注加工工程マスタ | K21: Web受注NO | V21: T | W21: 受注加工工程マスタ | AF21: Web受注NO | AQ21: OBJECTで保持している受注加工工程マスタ
A22: 2 | C22: T | D22: 受注加工工程マスタ | K22: Web受注明細NO | V22: T | W22: 受注加工工程マスタ | AF22: Web受注明細NO | AQ22: OBJECTで保持している受注加工工程マスタ
A23: 3 | C23: T | D23: 受注加工工程マスタ | K23: 製品コード | V23: T | W23: 製品加工工程マスタ | AF23: 製品コード
A24: 4 | C24: T | D24: 受注加工工程マスタ | K24: 作業コード | V24: T | W24: 製品加工工程マスタ | AF24: 作業コード
A25: 5 | C25: T | D25: 受注加工工程マスタ | K25: 工程コード | V25: T | W25: 製品加工工程マスタ | AF25: 工程コード
A26: 6 | C26: T | D26: 受注加工工程マスタ | K26: TOP品目コード | V26: T | W26: 製品加工工程マスタ | AF26: TOP品目コード
A27: 7 | C27: T | D27: 受注加工工程マスタ | K27: TOP品目_枝番1 | V27: T | W27: 製品加工工程マスタ | AF27: TOP品目_枝番1
A28: 8 | C28: T | D28: 受注加工工程マスタ | K28: TOP品目_枝番2 | V28: T | W28: 製品加工工程マスタ | AF28: TOP品目_枝番2
A29: 9 | C29: T | D29: 受注加工工程マスタ | K29: TOP品目_枝番3 | V29: T | W29: 製品加工工程マスタ | AF29: TOP品目_枝番3
A30: 10 | C30: T | D30: 受注加工工程マスタ | K30: 品目コード | V30: T | W30: 製品加工工程マスタ | AF30: 品目コード
A31: 11 | C31: T | D31: 受注加工工程マスタ | K31: 枝番1 | V31: T | W31: 製品加工工程マスタ | AF31: 枝番1
A32: 12 | C32: T | D32: 受注加工工程マスタ | K32: 枝番2 | V32: T | W32: 製品加工工程マスタ | AF32: 枝番2
A33: 13 | C33: T | D33: 受注加工工程マスタ | K33: 枝番3 | V33: T | W33: 製品加工工程マスタ | AF33: 枝番3
A34: 14 | C34: T | D34: 受注加工工程マスタ | K34: ワーキンググループＣＤ | V34: T | W34: 製品加工工程マスタ | AF34: ワーキンググループＣＤ
... A67: 47 | C67: T | D67: 受注加工工程マスタ | K67: 製造順優先項目８ | V67: T | W67: 製品加工工程マスタ | AF67: 製造順優先項目８
A69: No | G69: 3 | H69: MRP処理対象マップ | S69: ロジック名称 | AH69: 備考
A70: 処理分類 | E70: 追加
A71: No | C71: 転送先 | V71: 転送元 | AQ71: 説明
C72: 種 | D72: オブジェクト | K72: 項目名 | V72: 種 | W72: オブジェクト | AF72: 項目名
A73: 1 | C73: T | D73: MRP処理対象マップ | K73: 手配ＮＯ１ | V73: T | W73: 受注加工工程マスタ | AF73: 手配NO１ | AQ73: OBJECTで保持している受注加工工程マスタ
A74: 2 | C74: T | D74: MRP処理対象マップ | K74: 実行順 | V74: T | AQ74: 固定:0
A75: 3 | C75: T | D75: MRP処理対象マップ | K75: 会社ＣＤ | V75: T | AQ75: 会社CD
A76: 4 | C76: T | D76: MRP処理対象マップ | K76: ワーキンググループＣＤ | V76: T | W76: 受注加工工程マスタ | AF76: ワーキンググループＣＤ
A77: 5 | C77: T | D77: MRP処理対象マップ | K77: MRPeaフォルダ | V77: T | AQ77: 固定：NULL

Sheet 更新入出力仕様_品目マスタ
A1: =表紙!A54 -> Webシステム | K1: 文書名 | U1: モジュールID | Z1: =表紙!$AJ$63 -> MS | AE1: モジュール名 | AJ1: =表紙!$AX$63 -> 見積管理 | AS1: 文書番号 | AZ1: Version | BF1: Rev.
K2: =表紙!O64 -> アドオン設計書 | U2: ｻﾌﾞﾓｼﾞｭｰﾙID | Z2: =表紙!$AJ$64 -> MSBB | AE2: ｻﾌﾞﾓｼﾞｭｰﾙ名 | AJ2: =表紙!$AX$64 -> Webシステム | AS2: =表紙!$BL$64 -> M7-US-1140 | AZ2: =表紙!$BU$64 -> 7.0.2 | BF2: =表紙!$CB$64 -> 8
K3: =RIGHT(CELL("filename",$A$1),LEN(CELL("filename",$A$1))-FIND("]",CELL("filename",$A$1))) -> 更新入出力仕様_品目マスタ | U3: 表題 | Z3: =表紙!$AJ$65 -> - | AE3: =表紙!$AQ$65 -> 製品マスタ連携
A5: No | G5: 1 | H5: 品目マスタ（共通）_製品 | S5: ロジック名称 | AH5: 備考 | BP5: 品目区分別設定値
A6: 処理分類 | E6: 登録 | BP6: 商品 | BV6: 製品 | BZ6: 中間品 | CD6: 資材 | CF6: 資材 | CH6: 原料 | CJ6: 原料 | CL6: その他
A7: No | C7: 転送先 | V7: 転送元 | AQ7: 説明 | BP7: 構成あり | BR7: 構成なし | BT7: 版型 | BV7: 内 | BX7: 外 | BZ7: 内 | CB7: 外 | CD7: 在庫管理品（カートン等） | CF7: 非在庫品 | CH7: 購買 | CJ7: 印刷原紙 | CL7: 購買
C8: 種 | D8: オブジェクト | K8: 項目名 | V8: 種 | W8: オブジェクト | AF8: 項目名 | BP8: オブジェクト | BQ8: 項目名 | BR8: オブジェクト | BS8: 項目名 | BT8: オブジェクト | BU8: 項目名 | BV8: オブジェクト | BW8: 項目名 | BX8: オブジェクト | BY8: 項目名 | BZ8: オブジェクト | CA8: 項目名 | CB8: オブジェクト | CC8: 項目名 | CD8: オブジェクト | CE8: 項目名 | CF8: オブジェクト | CG8: 項目名 | CH8: オブジェクト | CI8: 項目名 | CJ8: オブジェクト | CK8: 項目名 | CL8: オブジェクト | CM8: 項目名
C9: T | D9: 品目マスタ（共通） | K9: 品目ＣＤ | AQ9: 自動設定 | BT9: WEB受注明細 | BU9: 版型NO ※H+数値7桁 | BV9: 製品基本マスタ | BW9: 製品連番 | BZ9: 製品基本マスタ | CA9: 製品連番 | CE9: M＋1000000～連番 | CK9: 製品基本マスタ.原紙コード＋製品基本マスタ.印刷コード＋製品基本マスタ.エンボスコード | CN9: Rev2.0変更 資材と原紙、版型の採番ルール変更
C10: T | D10: 品目マスタ（共通） | K10: 枝番１ | V10: 画 | W10: 製品基本マスタ | BU10: NULL | BV10: 製品基本マスタ | BW10: 製品枝番 | BZ10: 製品基本マスタ | CA10: 製品枝番 | CE10: NULL | CJ10: 原紙マスタ | CK10: 坪量
C11: T | D11: 品目マスタ（共通） | K11: 枝番２ | V11: 画 | W11: 製品基本マスタ | BU11: NULL | BW11: NULL | BZ11: 加工工程マスタ | CA11: 工程 | CE11: NULL | CJ11: 製品基本マスタ | CK11: 刃渡り_巾
C12: T | D12: 品目マスタ（共通） | K12: 枝番３ | V12: 画 | W12: 製品基本マスタ | BU12: NULL | BW12: NULL | CA12: NULL | CE12: NULL | CJ12: 製品加工工程マスタ | CK12: 工程
C13: T | D13: 品目マスタ（共通） | K13: 品名 | V13: 画 | W13: 製品基本マスタ | AF13: CP品名（CP品名1+全角スペース＋CP品名2） | BT13: WEB受注明細 | BU13: CP品名（CP品名1+全角スペース＋CP品名2） | BV13: 製品基本マスタ | BW13: CP品名（CP品名1+全角スペース＋CP品名2） 例：もつ鍋化粧箱（海千様） 身 | BZ13: 製品基本マスタ | CA13: CP品名+工程名（CP品名1+全角スペース＋ CP品名2＋全角スペース＋工程名） | CD13: 製品基本マスタ | CE13: 得意先品名＋部材名 | CJ13: 原紙マスタ | CK13: 原紙名
C14: T | D14: 品目マスタ（共通） | K14: 品目別名１ | V14: 画 | W14: 製品基本マスタ | AF14: 得意先品名（部材名は入れない） | BT14: WEB受注明細 | BU14: 得意先品名（部材名は入れない） | BV14: 製品基本マスタ | BW14: 得意先品名（部材名は入れない） | BZ14: 製品基本マスタ | CA14: 得意先品名（部材名は入れない） | CD14: 製品基本マスタ | CE14: クラウン品名 | CJ14: 原紙マスタ | CK14: 原紙略称
C15: T | D15: 品目マスタ（共通） | K15: 品目別名２ | V15: 画 | W15: 製品基本マスタ | AF15: 得意先品名２ （部材名） | BU15: 得意先品名２ （部材名） | BV15: 製品基本マスタ | BW15: 得意先品名２ （部材名） | BZ15: 製品基本マスタ | CA15: 得意先品名２ （部材名） | CD15: 製品基本マスタ | CE15: 部材名（身、蓋、仕切り） | CJ15: 原紙マスタ | CK15: 原紙カナ名
C16: T | D16: 品目マスタ（共通） | K16: 品目別名３ | V16: 画 | W16: 製品基本マスタ | AF16: CP品名1 | BU16: CP品名1 | BV16: 製品基本マスタ | BW16: CP品名1 | CA16: CP品名1 | CE16: 荷姿 | CJ16: 製品基本マスタ | CK16: メーカー名
C17: T | D17: 品目マスタ（共通） | K17: 品目別名４ | V17: 画 | W17: 製品基本マスタ | AF17: CP品名2 | BU17: CP品名2 | BV17: 製品基本マスタ | BW17: CP品名2 | CA17: CP品名2 | CE17: NULL | CK17: NULL
C18: T | D18: 品目マスタ（共通） | K18: 品目分類ＣＤ１ | V18: 画 | W18: 製品基本マスタ | AF18: 段 | BU18: NULL | BV18: 製品基本マスタ | BW18: 段 | BZ18: 製品基本マスタ | CA18: 段 | CE18: NULL | CK18: NULL
C19: T | D19: 品目マスタ（共通） | K19: 品目分類ＣＤ２ | V19: 画 | W19: 製品基本マスタ | AF19: 製品区分 | BU19: NULL | BV19: 製品基本マスタ | BW19: 製品区分 | BZ19: 製品基本マスタ | CA19: 製品区分 | CE19: NULL | CK19: NULL
C20: T | D20: 品目マスタ（共通） | K20: 品目分類ＣＤ３ | AQ20: NULL | BU20: NULL | BW20: NULL | CA20: NULL | CE20: 製品の品目CD | CK20: NULL
C21: T | D21: 品目マスタ（共通） | K21: 品目分類ＣＤ４ | V21: 画 | W21: 製品基本マスタ | AF21: 戦略商品区分 | BU21: NULL | BV21: 製品基本マスタ | BW21: 戦略商品区分 | BZ21: 製品基本マスタ | CA21: NULL | CE21: NULL | CK21: NULL
C22: T | D22: 品目マスタ（共通） | K22: 品目分類ＣＤ５ | V22: 画 | W22: 製品基本マスタ | AF22: 原紙区分（小） | BU22: NULL | BV22: 製品基本マスタ | BW22: 原紙区分（小） | BZ22: 製品基本マスタ | CA22: NULL | CE22: NULL | CJ22: 原紙マスタ | CK22: 原紙区分（小）
C23: T | D23: 品目マスタ（共通） | K23: 品目分類ＣＤ６ | V23: 画 | W23: 製品基本マスタ | AF23: 用途 | BU23: NULL | BV23: 製品基本マスタ | BW23: 用途 | BZ23: 製品基本マスタ | CA23: 用途 | CE23: NULL | CK23: NULL
C24: T | D24: 品目マスタ（共通） | K24: 品目分類ＣＤ７ | V24: 画 | W24: 製品基本マスタ | AF24: 機密区分 | BU24: NULL | BV24: 製品基本マスタ | BW24: 機密区分 | BZ24: 製品基本マスタ | CA24: 機密区分 | CE24: NULL | CK24: NULL
C25: T | D25: 品目マスタ（共通） | K25: 品目分類ＣＤ８ | V25: 画 | W25: 製品基本マスタ | AF25: 品質区分 | BU25: NULL | BV25: 製品基本マスタ | BW25: 品質区分 | BZ25: 製品基本マスタ | CA25: 品質区分 | CE25: NULL | CK25: NULL | CP25: Rev2.0 項目変更(高品質 項目削除、品質区分に変更)
C26: T | D26: 品目マスタ（共通） | K26: 品目分類ＣＤ９ | V26: 画 | W26: 製品基本マスタ | AF26: ＦＳＣ区分 | BU26: NULL | BV26: 製品基本マスタ | BW26: ＦＳＣ区分 | BZ26: 製品基本マスタ | CA26: ＦＳＣ区分 | CE26: NULL | CJ26: 原紙マスタ | CK26: ＦＳＣ区分
C27: T | D27: 品目マスタ（共通） | K27: 品目分類ＣＤ１０ | V27: 画 | W27: 製品基本マスタ | AF27: 製品パターン | BU27: NULL | BV27: 製品基本マスタ | BW27: 製品パターン | BZ27: 製品基本マスタ | CA27: 製品パターン | CE27: NULL | CK27: NULL
C28: T | D28: 品目マスタ（共通） | K28: 在庫管理区分 | AQ28: 1:する | BU28: 1:する | BW28: 1:する | CA28: 1:する | CE28: 1:する | CK28: 1:する
C29: T | D29: 品目マスタ（共通） | K29: 資産管理区分 | AQ29: 1:する | BU29: 1:する | BW29: 1:する | CA29: 1:する | CE29: 1:する | CK29: 1:する
C30: T | D30: 品目マスタ（共通） | K30: 諸口品ＦＬＧ | AQ30: 0:しない | BU30: 0:しない | BW30: 0:しない | CA30: 0:しない | CE30: 0:しない | CK30: 0:しない
C31: T | D31: 品目マスタ（共通） | K31: 値引品目ＦＬＧ | AQ31: 0:しない | BU31: 0:しない | BW31: 0:しない | CA31: 0:しない | CE31: 0:しない | CK31: 0:しない
C32: T | D32: 品目マスタ（共通） | K32: 単位ＣＤ | V32: 画 | W32: 製品基本マスタ | AF32: 単位 | BT32: WEB受注明細 | BU32: 数量単位 | BV32: 製品基本マスタ | BW32: 数量単位 | BZ32: 製品基本マスタ | CA32: 枚 | CE32: 個 | CK32: 個
C33: T | D33: 品目マスタ（共通） | K33: 小数部有効桁数 | V33: 画 | W33: 製品基本マスタ→単位マスタ | AF33: 単位小数部有効桁数 | BT33: 単位マスタ | BU33: 単位小数部有効桁数 | BV33: 単位マスタ | BW33: 単位小数部有効桁数 | BZ33: 単位マスタ | CA33: 単位小数部有効桁数 | CD33: 単位マスタ | CE33: 単位小数部有効桁数 | CK33: 単位小数部有効桁数
C34: T | D34: 品目マスタ（共通） | K34: 端数処理区分 | V34: 画 | W34: 製品基本マスタ→単位マスタ | AF34: 端数処理区分 | BT34: 単位マスタ | BU34: 端数処理区分 | BV34: 単位マスタ | BW34: 端数処理区分 | BZ34: 単位マスタ | CA34: 端数処理区分 | CD34: 単位マスタ | CE34: 端数処理区分 | CK34: 端数処理区分
C35: T | D35: 品目マスタ（共通） | K35: 容積単位ＣＤ | AQ35: m3 | BU35: NULL | BW35: NULL | CA35: NULL | CE35: NULL | CK35: NULL
C36: T | D36: 品目マスタ（共通） | K36: 容積 | AQ36: 計算 | BU36: NULL | BW36: NULL | CA36: NULL | CE36: NULL | CK36: NULL
C37: T | D37: 品目マスタ（共通） | K37: 重量単位ＣＤ | AQ37: KG | BU37: NULL | BW37: NULL | CA37: NULL | CE37: NULL | CK37: NULL
C38: T | D38: 品目マスタ（共通） | K38: 重量 | AQ38: 計算 | BU38: NULL | BW38: NULL | CA38: NULL | CE38: NULL | CK38: NULL
C39: T | D39: 品目マスタ（共通） | K39: 入り目単位ＣＤ | AQ39: NULL | BU39: NULL | BW39: NULL | CA39: NULL | CE39: NULL | CK39: NULL
C40: T | D40: 品目マスタ（共通） | K40: 入り目数量 | AQ40: NULL | BU40: NULL | BW40: NULL | CA40: NULL | CE40: NULL | CK40: NULL
C41: T | D41: 品目マスタ（共通） | K41: 単位容積（ｍ３） | AQ41: 計算 | BU41: NULL | BW41: NULL | CA41: NULL | CE41: NULL | CK41: NULL
C42: T | D42: 品目マスタ（共通） | K42: 単位重量（ＫＧ） | AQ42: 計算 | BU42: NULL | BW42: NULL | CA42: NULL | CE42: NULL | CK42: NULL
C43: T | D43: 品目マスタ（共通） | K43: ＨＳ ＣＤ | V43: 画 | W43: 製品基本マスタ | AF43: 取引先品目CD | BU43: NULL | BV43: 製品基本マスタ | BW43: 取引先品目CD | CA43: NULL | CE43: NULL | CK43: NULL
C44: T | D44: 品目マスタ（共通） | K44: ＪＡＮ区分 | AQ44: NULL | BU44: NULL | BW44: NULL | CA44: NULL | CE44: NULL | CK44: NULL
C45: T | D45: 品目マスタ（共通） | K45: ＪＡＮ ＣＤ | V45: 画 | W45: 製品基本マスタ | AF45: ＪＡＮ ＣＤ | BU45: NULL | BV45: 製品基本マスタ | BW45: ＪＡＮ ＣＤ | CA45: NULL | CE45: NULL | CK45: NULL
C46: T | D46: 品目マスタ（共通） | K46: ＩＴＦ ＣＤ | AQ46: NULL | BU46: NULL | BW46: NULL | CA46: NULL | CE46: NULL | CK46: NULL
C47: T | D47: 品目マスタ（共通） | K47: ＧＴＩＮ ＣＤ | AQ47: NULL | BU47: NULL | BW47: NULL | CA47: NULL | CE47: NULL | CK47: NULL
C48: T | D48: 品目マスタ（共通） | K48: サムネイル画像 | AQ48: NULL | BU48: NULL | BW48: NULL | CA48: NULL | CE48: NULL | CK48: NULL
C49: T | D49: 品目マスタ（共通） | K49: 販売品目体系ＣＤ | V49: 画 | W49: 製品基本マスタ | AF49: 販売品目体系ＣＤ | AQ49: 製品区分と製品分類の階層分け | BU49: NULL | BV49: 製品基本マスタ | BW49: 販売品目体系ＣＤ | CA49: NULL | CE49: NULL | CK49: NULL
C50: T | D50: 品目マスタ（共通） | K50: メモ１ | BU50: NULL | BW50: NULL | CA50: NULL | CE50: NULL | CK50: NULL
C51: T | D51: 品目マスタ（共通） | K51: メモ２ | BU51: NULL | BW51: NULL | CA51: NULL | CE51: NULL | CK51: NULL
C52: T | D52: 品目マスタ（共通） | K52: メモ３ | BU52: NULL | BW52: NULL | CA52: NULL | CE52: NULL | CK52: NULL
C53: T | D53: 品目マスタ（共通） | K53: 論理削除ＦＬＧ | AQ53: 0 | BU53: 0 | BW53: 0 | CA53: 0 | CE53: 0 | CK53: 0
C54: T | D54: 品目マスタ（共通） | K54: 論理削除ユーザＩＤ | AQ54: NULL | BU54: NULL | BW54: NULL | CA54: NULL | CE54: NULL | CK54: NULL
C55: T | D55: 品目マスタ（共通） | K55: 論理削除ユーザ名 | AQ55: NULL | BU55: NULL | BW55: NULL | CA55: NULL | CE55: NULL | CK55: NULL
C56: T | D56: 品目マスタ（共通） | K56: 論理削除日時 | AQ56: NULL | BU56: NULL | BW56: NULL | CA56: NULL | CE56: NULL | CK56: NULL
C57: T | D57: 品目マスタ（共通） | K57: 登録ユーザＩＤ | AQ57: 登録ユーザー | BU57: 登録ユーザー | BW57: 登録ユーザー | CA57: 登録ユーザー | CE57: 登録ユーザー | CK57: 登録ユーザー
C58: T | D58: 品目マスタ（共通） | K58: 登録ユーザ名 | AQ58: 登録ユーザー名 | BU58: 登録ユーザー名 | BW58: 登録ユーザー名 | CA58: 登録ユーザー名 | CE58: 登録ユーザー名 | CK58: 登録ユーザー名
C59: T | D59: 品目マスタ（共通） | K59: 登録日時 | AQ59: 処理日時 | BU59: 処理日時 | BW59: 処理日時 | CA59: 処理日時 | CE59: 処理日時 | CK59: 処理日時
C60: T | D60: 品目マスタ（共通） | K60: 登録機能ＩＤ
C61: T | D61: 品目マスタ（共通） | K61: 更新カウンタ
C62: T | D62: 品目マスタ（共通） | K62: 更新ユーザＩＤ | AQ62: 登録ユーザー | BU62: 登録ユーザー | BW62: 登録ユーザー | CA62: 登録ユーザー | CE62: 登録ユーザー | CK62: 登録ユーザー
C63: T | D63: 品目マスタ（共通） | K63: 更新ユーザ名 | AQ63: 登録ユーザー名 | BU63: 登録ユーザー名 | BW63: 登録ユーザー名 | CA63: 登録ユーザー名 | CE63: 登録ユーザー名 | CK63: 登録ユーザー名
C64: T | D64: 品目マスタ（共通） | K64: 更新日時 | AQ64: 処理日時 | BU64: 処理日時 | BW64: 処理日時 | CA64: 処理日時 | CE64: 処理日時 | CK64: 処理日時
C65: T | D65: 品目マスタ（共通） | K65: 更新機能ＩＤ
C66: T | D66: 品目マスタ（共通） | K66: 更新リクエストＮＯ
C67: T | D67: 品目マスタ（共通） | K67: 製品CD | V67: 画 | W67: 製品基本マスタ | AF67: 製品CD | BU67: NULL | BV67: 製品基本マスタ | BW67: 製品CD | BZ67: 製品基本マスタ | CA67: 製品CD | CD67: 製品基本マスタ | CE67: 製品CD | CK67: NULL
C68: T | D68: 品目マスタ（共通） | K68: セット部品CD | V68: 画 | W68: 製品基本マスタ | AF68: 製品CD | BU68: NULL | BV68: 製品基本マスタ | BW68: セット製品CD | BZ68: 製品基本マスタ | CA68: 製品CD | CD68: 製品基本マスタ | CE68: 製品CD | CK68: NULL
C69: T | D69: 品目マスタ（共通） | K69: 案件NO(親)、(子)、(部材) | V69: 画 | W69: 製品基本マスタ | AF69: 案件NO(親)、(子)、(部材) | BU69: NULL | BV69: 製品基本マスタ | BW69: 案件NO(親)、(子)、(部材) | BZ69: 製品基本マスタ | CA69: 案件NO(親)、(子)、(部材) | CD69: 製品基本マスタ | CE69: 案件NO(親)、(子)、(部材) | CK69: NULL | CO69: Rev2.0 変更
C70: T | D70: 品目マスタ（共通） | K70: 見積計算書NO | V70: 画 | W70: 製品基本マスタ | AF70: 見積計算書NO | BU70: NULL | BV70: 製品基本マスタ | BW70: 見積計算書NO | BZ70: 製品基本マスタ | CA70: 見積計算書NO | CD70: 製品基本マスタ | CE70: 見積計算書NO | CK70: NULL
C71: T | D71: 品目マスタ（共通） | K71: 取引先 | V71: 画 | W71: 製品基本マスタ | AF71: 得意先 | BT71: WEB受注明細 | BU71: 得意先 | BV71: 製品基本マスタ | BW71: 得意先 | BZ71: 製品基本マスタ | CA71: 得意先 | CD71: 製品基本マスタ | CE71: 得意先 | CK71: NULL
C72: T | D72: 品目マスタ（共通） | K72: 単価単位 | BU72: NULL | BW72: NULL | CA72: NULL | CE72: NULL
A73: No | G73: 2 | H73: 品目マスタ（共通）_製品 | S73: ロジック名称 | AH73: 備考 | BP73: 品目区分別設定値
A74: 処理分類 | E74: 更新 | BP74: 商品 | BR74: 商品 | BT74: 商品 | BV74: 製品 | BZ74: 中間品 | CD74: 資材 | CF74: 資材 | CH74: 原料 | CJ74: 原料 | CL74: その他
A75: No | C75: 転送先 | V75: 転送元 | AQ75: 説明 | BP75: 購買 | BR75: 購買 | BT75: 購買 | BV75: 内 | BX75: 外 | BZ75: 内 | CB75: 外 | CD75: 在庫管理品（カートン等） | CF75: 非在庫品 | CH75: 購買 | CJ75: 印刷原紙 | CL75: 購買
C76: 種 | D76: オブジェクト | K76: 項目名 | V76: 種 | W76: オブジェクト | AF76: 項目名 | BP76: オブジェクト | BQ76: 項目名 | BR76: オブジェクト | BS76: 項目名 | BT76: オブジェクト | BU76: 項目名 | BV76: オブジェクト | BW76: 項目名 | BX76: オブジェクト | BY76: 項目名 | BZ76: オブジェクト | CA76: 項目名 | CB76: オブジェクト | CC76: 項目名 | CD76: オブジェクト | CE76: 項目名 | CF76: オブジェクト | CG76: 項目名 | CH76: オブジェクト | CI76: 項目名 | CJ76: オブジェクト | CK76: 項目名 | CL76: オブジェクト | CM76: 項目名
C77: T | D77: 品目マスタ（共通） | K77: 品名 | V77: 画 | W77: 製品基本マスタ | AF77: 得意先品名＋部材名 | BU77: CP品名（CP品名1+全角スペース＋CP品名2） 例：もつ鍋化粧箱（海千様） 身 | BV77: 製品基本マスタ | BW77: CP品名（CP品名1+全角スペース＋CP品名2） 例：もつ鍋化粧箱（海千様） 身 | BZ77: 製品基本マスタ | CA77: 得意先品名＋部材名
C78: T | D78: 品目マスタ（共通） | K78: 品目別名１ | V78: 画 | W78: 製品基本マスタ | AF78: クラウン品名 | BT78: WEB受注明細 | BU78: 得意先品名（部材名は入れない） | BV78: 製品基本マスタ | BW78: 得意先品名（部材名は入れない） | BZ78: 製品基本マスタ | CA78: クラウン品名
C79: T | D79: 品目マスタ（共通） | K79: 品目別名２ | V79: 画 | W79: 製品基本マスタ | AF79: 部材名（身、蓋、仕切り） | BT79: WEB受注明細 | BU79: 得意先品名２ （部材名） | BV79: 製品基本マスタ | BW79: 得意先品名２ （部材名） | BZ79: 製品基本マスタ | CA79: 部材名（身、蓋、仕切り）
C80: T | D80: 品目マスタ（共通） | K80: 品目別名３ | AQ80: NULL | BT80: WEB受注明細 | BU80: CP品名1 | BV80: 製品基本マスタ | BW80: CP品名1
C81: T | D81: 品目マスタ（共通） | K81: 品目別名４ | AQ81: NULL | BT81: WEB受注明細 | BU81: CP品名2 | BV81: 製品基本マスタ | BW81: CP品名2
C82: T | D82: 品目マスタ（共通） | K82: 品目分類ＣＤ１ | V82: 画 | W82: 製品基本マスタ | AF82: 段 | BT82: WEB受注明細 | BU82: 段 | BV82: 製品基本マスタ | BW82: 段 | BZ82: 製品基本マスタ | CA82: 段 | CE82: NULL
C83: T | D83: 品目マスタ（共通） | K83: 品目分類ＣＤ２ | V83: 画 | W83: 製品基本マスタ | AF83: 製品区分 | BT83: WEB受注明細 | BU83: 製品区分 | BV83: 製品基本マスタ | BW83: 製品区分 | BZ83: 製品基本マスタ | CA83: 製品区分 | CE83: NULL
C84: T | D84: 品目マスタ（共通） | K84: 品目分類ＣＤ３ | AQ84: NULL | BT84: WEB受注明細 | CA84: NULL | CE84: 製品の品目CD
C85: T | D85: 品目マスタ（共通） | K85: 品目分類ＣＤ４ | V85: 画 | W85: 製品基本マスタ | AF85: 戦略商品区分 | BT85: WEB受注明細 | BU85: 戦略商品区分 | BV85: 製品基本マスタ | BW85: 戦略商品区分 | BZ85: 製品基本マスタ | CA85: NULL | CE85: NULL
C86: T | D86: 品目マスタ（共通） | K86: 品目分類ＣＤ５ | V86: 画 | W86: 製品基本マスタ | AF86: 原紙区分（小） | BT86: WEB受注明細 | BU86: 原紙区分（小） | BV86: 製品基本マスタ | BW86: 原紙区分（小） | BZ86: 製品基本マスタ | CA86: NULL | CE86: NULL
C87: T | D87: 品目マスタ（共通） | K87: 品目分類ＣＤ６ | V87: 画 | W87: 製品基本マスタ | AF87: 用途 | BT87: WEB受注明細 | BU87: 用途 | BV87: 製品基本マスタ | BW87: 用途 | BZ87: 製品基本マスタ | CA87: 用途 | CE87: NULL
C88: T | D88: 品目マスタ（共通） | K88: 品目分類ＣＤ７ | V88: 画 | W88: 製品基本マスタ | AF88: 機密区分 | BT88: WEB受注明細 | BU88: 機密区分 | BV88: 製品基本マスタ | BW88: 機密区分 | BZ88: 製品基本マスタ | CA88: 機密区分 | CE88: NULL
C89: T | D89: 品目マスタ（共通） | K89: 品目分類ＣＤ８ | V89: 画 | W89: 製品基本マスタ | AF89: 品質区分 | BT89: WEB受注明細 | BU89: 品質区分 | BV89: 製品基本マスタ | BW89: 品質区分 | BZ89: 製品基本マスタ | CA89: 品質区分 | CE89: NULL | CO89: Rev2.0 項目変更(高品質 項目削除、品質区分に変更)
C90: T | D90: 品目マスタ（共通） | K90: 品目分類ＣＤ９ | V90: 画 | W90: 製品基本マスタ | AF90: ＦＳＣ区分 | BT90: WEB受注明細 | BU90: ＦＳＣ区分 | BV90: 製品基本マスタ | BW90: ＦＳＣ区分 | BZ90: 製品基本マスタ | CA90: ＦＳＣ区分 | CE90: NULL
C91: T | D91: 品目マスタ（共通） | K91: 品目分類ＣＤ１０ | V91: 画 | W91: 製品基本マスタ | AF91: 製品パターン | BT91: WEB受注明細 | BU91: 製品パターン | BV91: 製品基本マスタ | BW91: 製品パターン | BZ91: 製品基本マスタ | CA91: 製品パターン | CE91: NULL
C92: T | D92: 品目マスタ（共通） | K92: 単位ＣＤ | V92: 画 | W92: 製品基本マスタ | AF92: 数量単位 | BT92: WEB受注明細 | BU92: 数量単位 | BV92: 製品基本マスタ | BW92: 数量単位 | CA92: 枚 | CE92: 個
C93: T | D93: 品目マスタ（共通） | K93: 小数部有効桁数 | V93: 画 | W93: 製品基本マスタ→単位マスタ | AF93: 単位小数部有効桁数 | BT93: WEB受注明細 | BU93: 単位小数部有効桁数 | BV93: 単位マスタ | BW93: 単位小数部有効桁数 | BZ93: 単位マスタ | CA93: 単位小数部有効桁数 | CD93: 単位マスタ | CE93: 単位小数部有効桁数
C94: T | D94: 品目マスタ（共通） | K94: 端数処理区分 | V94: 画 | W94: 製品基本マスタ→単位マスタ | AF94: 端数処理区分 | BT94: WEB受注明細 | BU94: 端数処理区分 | BV94: 単位マスタ | BW94: 端数処理区分 | BZ94: 単位マスタ | CA94: 端数処理区分 | CD94: 単位マスタ | CE94: 端数処理区分
C95: T | D95: 品目マスタ（共通） | K95: ＨＳ ＣＤ | V95: 画 | W95: 製品基本マスタ | AF95: 取引先品目CD | BT95: WEB受注明細 | BU95: 取引先品目CD | BV95: 製品基本マスタ | BW95: 取引先品目CD | CA95: NULL | CE95: NULL
C96: T | D96: 品目マスタ（共通） | K96: 販売品目体系ＣＤ | V96: 画 | W96: 製品基本マスタ | AF96: 販売品目体系ＣＤ | BT96: WEB受注明細 | BU96: 販売品目体系ＣＤ | BV96: 製品基本マスタ | BW96: 販売品目体系ＣＤ | CA96: NULL | CE96: NULL
C97: T | D97: 品目マスタ（共通） | K97: 更新カウンタ | AQ97: カウントアップ | BU97: カウントアップ | BW97: カウントアップ | CA97: カウントアップ | CE97: カウントアップ
C98: T | D98: 品目マスタ（共通） | K98: 更新ユーザＩＤ | AQ98: 更新ユーザー | BU98: 更新ユーザー | BW98: 更新ユーザー | CA98: 更新ユーザー | CE98: 更新ユーザー
C99: T | D99: 品目マスタ（共通） | K99: 更新ユーザ名 | AQ99: 更新ユーザー名 | BU99: 更新ユーザー名 | BW99: 更新ユーザー名 | CA99: 更新ユーザー名 | CE99: 更新ユーザー名
C100: T | D100: 品目マスタ（共通） | K100: 更新日時 | AQ100: 処理日時 | BU100: 処理日時 | BW100: 処理日時 | CA100: 処理日時 | CE100: 処理日時
C101: T | D101: 品目マスタ（共通） | K101: 更新機能ＩＤ
...

Sheet 更新入出力仕様_品目詳細マスタ
A1: =表紙!A54 -> Webシステム | K1: 文書名 | U1: モジュールID | Z1: =表紙!$AJ$63 -> MS | AE1: モジュール名 | AJ1: =表紙!$AX$63 -> 見積管理 | AS1: 文書番号 | AZ1: Version | BF1: Rev.
K2: =表紙!O64 -> アドオン設計書 | U2: ｻﾌﾞﾓｼﾞｭｰﾙID | Z2: =表紙!$AJ$64 -> MSBB | AE2: ｻﾌﾞﾓｼﾞｭｰﾙ名 | AJ2: =表紙!$AX$64 -> Webシステム | AS2: =表紙!$BL$64 -> M7-US-1140 | AZ2: =表紙!$BU$64 -> 7.0.2 | BF2: =表紙!$CB$64 -> 8
K3: =RIGHT(CELL("filename",$A$1),LEN(CELL("filename",$A$1))-FIND("]",CELL("filename",$A$1))) -> 更新入出力仕様_品目詳細マスタ | U3: 表題 | Z3: =表紙!$AJ$65 -> - | AE3: =表紙!$AQ$65 -> 製品マスタ連携
A5: No | G5: 1 | H5: 品目詳細マスタ_製品 | S5: ロジック名称 | AH5: 備考 | BP5: 品目区分別設定値 | CR5: 通常パタン （前工程仕掛品を投入して、加工） | CT5: 連産品（N丁取り） | CV5: 複数仕掛品を投入 （タンデム） | CX5: 購入品（都度採番）手配対象 | CZ5: 外注品（都度採番）手配対象 ※有償/無償支給 | DB5: 外注品（都度採番）手配対象 ※自給品（無償支給）（材料・仕入の支払い分割） | DD5: 消耗品（在庫管理対象外）手配対象 | DF5: 共通品目（発注点発注）を投入 | DH5: 共通品目（MRP発注）を投入 | DK5: REV4.0 商品を概要と合わせる
A6: 処理分類 | E6: 登録 | BP6: 商品 | BV6: 製品 | BZ6: 中間品 | CH6: 資材 | CJ6: 資材 | CL6: 原料 | CN6: その他 | DK6: REV6.0 版型をMRP対象外にする
A7: No | C7: 転送先 | V7: 転送元 | AQ7: 説明 | BP7: 構成あり | BR7: 構成なし | BT7: 版型 | BV7: 内 | BX7: 外 | BZ7: 内（自事業所） | CB7: 内（他事業所） | CD7: 外 | CF7: 購買 | CH7: 在庫管理品（カートン等） | CJ7: 非在庫品 | CL7: 購買 | CN7: 購買
C8: 種 | D8: オブジェクト | K8: 項目名 | V8: 種 | W8: オブジェクト | AF8: 項目名 | BP8: オブジェクト | BQ8: 項目名 | BR8: オブジェクト | BS8: 項目名 | BT8: オブジェクト | BU8: 項目名 | BV8: オブジェクト | BW8: 項目名 | BX8: オブジェクト | BY8: 項目名 | BZ8: オブジェクト | CA8: 項目名 | CB8: オブジェクト | CC8: 項目名 | CD8: オブジェクト | CE8: 項目名 | CF8: オブジェクト | CG8: 項目名 | CH8: オブジェクト | CI8: 項目名 | CJ8: オブジェクト | CK8: 項目名 | CL8: オブジェクト | CM8: 項目名 | CN8: オブジェクト | CO8: 項目名 | CR8: オブジェクト | CS8: 項目名 | CT8: オブジェクト | CU8: 項目名 | CV8: オブジェクト | CW8: 項目名 | CX8: オブジェクト | CY8: 項目名 | CZ8: オブジェクト | DA8: 項目名 | DB8: オブジェクト | DC8: 項目名 | DD8: オブジェクト | DE8: 項目名 | DF8: オブジェクト | DG8: 項目名 | DH8: オブジェクト | DI8: 項目名
C9: T | D9: 品目詳細マスタ | K9: 品目ＣＤ | V9: T | W9: 品目マスタ | AF9: 品目CD | BT9: 品目マスタ（共通） | BU9: 品目ＣＤ | BV9: 品目マスタ（共通） | BW9: 品目ＣＤ | BX9: 品目マスタ（共通） | BY9: 品目ＣＤ | BZ9: 品目マスタ（共通） | CA9: 品目ＣＤ | CB9: 品目マスタ（共通） | CC9: 品目ＣＤ | CD9: 品目マスタ（共通） | CE9: 品目ＣＤ | CF9: 品目マスタ（共通） | CG9: 品目ＣＤ | CH9: 品目マスタ（共通） | CI9: 品目ＣＤ | CR9: 品目マスタ（共通） | CS9: 品目ＣＤ | CT9: 品目マスタ（共通） | CU9: 品目ＣＤ | CV9: 品目マスタ（共通） | CW9: 品目ＣＤ | CX9: 品目マスタ（共通） | CY9: 品目ＣＤ | CZ9: 品目マスタ（共通） | DA9: 品目ＣＤ | DB9: 品目マスタ（共通） | DC9: 品目ＣＤ | DF9: 品目マスタ（共通） | DG9: 品目ＣＤ | DH9: 品目マスタ（共通） | DI9: 品目ＣＤ
C10: T | D10: 品目詳細マスタ | K10: 枝番１ | V10: T | W10: 品目マスタ | AF10: 枝番１ | BT10: 品目マスタ（共通） | BU10: 枝番１ | BV10: 品目マスタ（共通） | BW10: 枝番１ | BX10: 品目マスタ（共通） | BY10: 枝番１ | BZ10: 品目マスタ（共通） | CA10: 枝番１ | CB10: 品目マスタ（共通） | CC10: 枝番１ | CD10: 品目マスタ（共通） | CE10: 枝番１ | CF10: 品目マスタ（共通） | CG10: 枝番１ | CH10: 品目マスタ（共通） | CI10: 枝番１ | CR10: 品目マスタ（共通） | CS10: 枝番１ | CT10: 品目マスタ（共通） | CU10: 枝番１ | CV10: 品目マスタ（共通） | CW10: 枝番１ | CX10: 品目マスタ（共通） | CY10: 枝番１ | CZ10: 品目マスタ（共通） | DA10: 枝番１ | DB10: 品目マスタ（共通） | DC10: 枝番１ | DF10: 品目マスタ（共通） | DG10: 枝番１ | DH10: 品目マスタ（共通） | DI10: 枝番１
C11: T | D11: 品目詳細マスタ | K11: 枝番２ | V11: T | W11: 品目マスタ | AF11: 枝番２ | BT11: 品目マスタ（共通） | BU11: 枝番２ | BV11: 品目マスタ（共通） | BW11: 枝番２ | BX11: 品目マスタ（共通） | BY11: 枝番２ | BZ11: 品目マスタ（共通） | CA11: 枝番２ | CB11: 品目マスタ（共通） | CC11: 枝番２ | CD11: 品目マスタ（共通） | CE11: 枝番２ | CF11: 品目マスタ（共通） | CG11: 枝番２ | CH11: 品目マスタ（共通） | CI11: 枝番２ | CR11: 品目マスタ（共通） | CS11: 枝番２ | CT11: 品目マスタ（共通） | CU11: 枝番２ | CV11: 品目マスタ（共通） | CW11: 枝番２ | CX11: 品目マスタ（共通） | CY11: 枝番２ | CZ11: 品目マスタ（共通） | DA11: 枝番２ | DB11: 品目マスタ（共通） | DC11: 枝番２ | DF11: 品目マスタ（共通） | DG11: 枝番２ | DH11: 品目マスタ（共通） | DI11: 枝番２
C12: T | D12: 品目詳細マスタ | K12: 枝番３ | V12: T | W12: 品目マスタ | AF12: 枝番３ | BT12: 品目マスタ（共通） | BU12: 枝番３ | BV12: 品目マスタ（共通） | BW12: 枝番３ | BX12: 品目マスタ（共通） | BY12: 枝番３ | BZ12: 品目マスタ（共通） | CA12: 枝番３ | CB12: 品目マスタ（共通） | CC12: 枝番３ | CD12: 品目マスタ（共通） | CE12: 枝番３ | CF12: 品目マスタ（共通） | CG12: 枝番３ | CH12: 品目マスタ（共通） | CI12: 枝番３ | CR12: 品目マスタ（共通） | CS12: 枝番３ | CT12: 品目マスタ（共通） | CU12: 枝番３ | CV12: 品目マスタ（共通） | CW12: 枝番３ | CX12: 品目マスタ（共通） | CY12: 枝番３ | CZ12: 品目マスタ（共通） | DA12: 枝番３ | DB12: 品目マスタ（共通） | DC12: 枝番３ | DF12: 品目マスタ（共通） | DG12: 枝番３ | DH12: 品目マスタ（共通） | DI12: 枝番３
C13: T | D13: 品目詳細マスタ | K13: 製造場所ＣＤ | V13: 画 | W13: 製品基本マスタ | AF13: 製造場所 | AQ13: 最終工程製造場所 | BU13: NULL | BV13: 製品加工工程マスタ | BW13: 号機 | BX13: 場所マスタ | BY13: 場所 ※外注場所 | BZ13: 製品加工工程マスタ | CA13: 号機 | CC13: NULL | CD13: 場所マスタ | CE13: 場所 ※外注場所 | CG13: NULL | CI13: NULL | CR13: 製品加工工程マスタ | CS13: 号機 | CT13: 製品加工工程マスタ | CU13: 号機 | CV13: 製品加工工程マスタ | CW13: 号機 | CY13: NULL | CZ13: 場所マスタ | DA13: 場所 ※外注場所 | DB13: 場所マスタ | DC13: 場所 ※外注場所 | DG13: NULL | DI13: NULL
C14: T | D14: 品目詳細マスタ | K14: 発注先ＣＤ | V14: 画 | W14: 製品基本マスタ | AF14: 発注先 | BT14: WEB木型・版型管理マスタ | BU14: 発注先 | BW14: NULL | BX14: 製品加工工程マスタ | BY14: 発注先 | CA14: NULL | CC14: NULL | CD14: 製品加工工程マスタ | CE14: 発注先 | CF14: 製品加工工程マスタ | CG14: 発注先 | CH14: 製品加工工程マスタ | CI14: 発注先 | CS14: NULL | CU14: NULL | CW14: NULL | CX14: 製品加工工程マスタ | CY14: 発注先 | CZ14: 製品加工工程マスタ | DA14: 発注先 | DB14: 製品加工工程マスタ | DC14: 発注先 | DF14: 製品加工工程マスタ | DG14: 発注先 | DH14: 製品加工工程マスタ | DI14: 発注先
C15: T | D15: 品目詳細マスタ | K15: メーカＣＤ | AQ15: NULL | BU15: NULL | BW15: NULL | BY15: NULL | CA15: NULL | CC15: NULL | CE15: NULL | CG15: NULL | CI15: NULL | CS15: NULL | CU15: NULL | CW15: NULL | CY15: NULL | DA15: NULL | DC15: NULL | DG15: NULL | DI15: NULL
C16: T | D16: 品目詳細マスタ | K16: 依頼先場所ＣＤ | AQ16: NULL | BU16: NULL | BW16: NULL | BY16: NULL | CA16: NULL | CB16: 製品加工工程マスタ | CC16: 号機 | CE16: NULL | CG16: NULL | CI16: NULL | CS16: NULL | CU16: NULL | CW16: NULL | CY16: NULL | DA16: NULL | DC16: NULL | DG16: NULL | DI16: NULL
C17: T | D17: 品目詳細マスタ | K17: ワーキンググループＣＤ | BT17: WEB木型・版型管理マスタ | BU17: 拠点 | BV17: 製品基本マスタ | BW17: WG | BX17: 製品基本マスタ | BY17: WG | BZ17: 製品基本マスタ | CA17: WG | CB17: 製品基本マスタ | CC17: WG | CD17: 製品基本マスタ | CE17: WG | CF17: 製品基本マスタ | CG17: WG | CH17: 製品基本マスタ | CI17: WG | CR17: 製品基本マスタ | CS17: WG | CT17: 製品基本マスタ | CU17: WG | CV17: 製品基本マスタ | CW17: WG | CX17: 製品基本マスタ | CY17: WG | CZ17: 製品基本マスタ | DA17: WG | DB17: 製品基本マスタ | DC17: WG | DF17: 製品基本マスタ | DG17: WG | DH17: 製品基本マスタ | DI17: WG
C18: T | D18: 品目詳細マスタ | K18: 構成パタン | AQ18: 1 | BU18: 1 | BW18: 1 | BY18: 1 | CA18: 1 | CC18: 1 | CE18: 1 | CG18: 1 | CI18: 1 | CS18: 1 | CU18: 1 | CW18: 1 | CY18: 1 | DA18: 1 | DC18: 1 | DG18: 1 | DI18: 1
C19: T | D19: 品目詳細マスタ | K19: 適用開始日 | AQ19: 処理日 | BU19: 処理日 | BW19: 処理日 | BY19: 処理日 | CA19: 処理日 | CC19: 処理日 | CE19: 処理日 | CG19: 処理日 | CI19: 処理日 | CS19: 処理日 | CU19: 処理日 | CW19: 処理日 | CY19: 処理日 | DA19: 処理日 | DC19: 処理日 | DG19: 処理日 | DI19: 処理日
C20: T | D20: 品目詳細マスタ | K20: 会社ＣＤ | AQ20: 会社CD | BU20: 会社CD | BW20: 会社CD | BY20: 会社CD | CA20: 会社CD | CC20: 会社CD | CE20: 会社CD | CG20: 会社CD | CI20: 会社CD | CS20: 会社CD | CU20: 会社CD | CW20: 会社CD | CY20: 会社CD | DA20: 会社CD | DC20: 会社CD | DG20: 会社CD | DI20: 会社CD
C21: T | D21: 品目詳細マスタ | K21: 適用終了日 | AQ21: 2099/12/31 | BU21: 73050 | BW21: 73050 | BY21: 73050 | CA21: 73050 | CC21: 73050 | CE21: 73050 | CG21: 73050 | CI21: 73050 | CS21: 73050 | CU21: 73050 | CW21: 73050 | CY21: 73050 | DA21: 73050 | DC21: 73050 | DG21: 73050 | DI21: 73050
C22: T | D22: 品目詳細マスタ | K22: 工程パタン | AQ22: 1 | BU22: 1 | BW22: 1 | BY22: 1 | CA22: 1 | CC22: 1 | CE22: 1 | CG22: 1 | CI22: 1 | CS22: 1 | CU22: 1 | CW22: 1 | CY22: 1 | DA22: 1 | DC22: 1 | DG22: 1 | DI22: 1
C23: T | D23: 品目詳細マスタ | K23: 製造ＬＴ | V23: 画 | W23: 製品加工マスタ | AF23: 負荷日数 | AQ23: 0 | BU23: 0 | BW23: 0 | BY23: 0 | CA23: 0 | CC23: 0 | CE23: 0 | CG23: 0 | CI23: 0 | CS23: 0 | CU23: 0 | CW23: 0 | CY23: 0 | DA23: 0 | DC23: 0 | DG23: 0 | DI23: 0
C24: T | D24: 品目詳細マスタ | K24: 製造ＬＴ加算基準数量 | AQ24: NULL | BU24: NULL | BW24: NULL | BY24: NULL | CA24: NULL | CC24: NULL | CE24: NULL | CG24: NULL | CI24: NULL | CS24: NULL | CU24: NULL | CW24: NULL | CY24: NULL | DA24: NULL | DC24: NULL | DG24: NULL | DI24: NULL
C25: T | D25: 品目詳細マスタ | K25: 購入ＬＴ | V25: 画 | W25: 製品加工マスタ | AF25: 負荷日数
C26: T | D26: 品目詳細マスタ | K26: 購入ＬＴ加算基準数量 | AQ26: NULL | BU26: NULL | BW26: NULL | BY26: NULL | CA26: NULL | CC26: NULL | CE26: NULL | CG26: NULL | CI26: NULL | CS26: NULL | CU26: NULL | CW26: NULL | CY26: NULL | DA26: NULL | DC26: NULL | DG26: NULL | DI26: NULL
C27: T | D27: 品目詳細マスタ | K27: 検収ＬＴ | AQ27: NULL | BU27: NULL | BW27: NULL | BY27: NULL | CA27: NULL | CC27: NULL | CE27: NULL | CG27: NULL | CI27: NULL | CS27: NULL | CU27: NULL | CW27: NULL | CY27: NULL | DA27: NULL | DC27: NULL | DG27: NULL | DI27: NULL
C28: T | D28: 品目詳細マスタ | K28: 安全ＬＴ | AQ28: 固定:1 | BU28: 固定:1 | BW28: 固定:1 | BY28: 固定:1 | CA28: 固定:1 | CC28: 固定:1 | CE28: 固定:1 | CG28: 固定:1 | CI28: 固定:1 | CS28: 固定:1 | CU28: 固定:1 | CW28: 固定:1 | CY28: 固定:1 | DA28: 固定:1 | DC28: 固定:1 | DG28: 固定:1 | DI28: 固定:1
C29: T | D29: 品目詳細マスタ | K29: オーダ自動確定期間（日） | AQ29: NULL | BU29: NULL | BW29: NULL | BY29: NULL | CA29: NULL | CC29: NULL | CE29: NULL | CG29: NULL | CI29: NULL | CS29: NULL | CU29: NULL | CW29: NULL | CY29: NULL | DA29: NULL | DC29: NULL | DG29: NULL | DI29: NULL
C30: T | D30: 品目詳細マスタ | K30: 曜日まとめ区分 | AQ30: NULL | BU30: NULL | BW30: NULL | BY30: NULL | CA30: NULL | CC30: NULL | CE30: NULL | CG30: NULL | CI30: NULL | CS30: NULL | CU30: NULL | CW30: NULL | CY30: NULL | DA30: NULL | DC30: NULL | DG30: NULL | DI30: NULL
C31: T | D31: 品目詳細マスタ | K31: 曜日まとめ期間（週） | AQ31: NULL | BU31: NULL | BW31: NULL | BY31: NULL | CA31: NULL | CC31: NULL | CE31: NULL | CG31: NULL | CI31: NULL | CS31: NULL | CU31: NULL | CW31: NULL | CY31: NULL | DA31: NULL | DC31: NULL | DG31: NULL | DI31: NULL
C32: T | D32: 品目詳細マスタ | K32: ロットまとめ期間（日） | AQ32: NULL | BU32: NULL | BW32: NULL | BY32: NULL | CA32: NULL | CC32: NULL | CE32: NULL | CG32: NULL | CI32: NULL | CS32: NULL | CU32: NULL | CW32: NULL | CY32: NULL | DA32: NULL | DC32: NULL | DG32: NULL | DI32: NULL
C33: T | D33: 品目詳細マスタ | K33: 最小ロット数量 | CT33: 製品加工マスタ | CU33: 台数
C34: T | D34: 品目詳細マスタ | K34: 刻みロット数量 | CT34: 製品加工マスタ | CU34: 台数
C35: T | D35: 品目詳細マスタ | K35: 最大ロット数量
C36: T | D36: 品目詳細マスタ | K36: 最大オーダ件数 | AQ36: NULL | BU36: NULL | BW36: NULL | BY36: NULL | CA36: NULL | CC36: NULL | CE36: NULL | CG36: NULL | CI36: NULL | CS36: NULL | CU36: NULL | CW36: NULL | CY36: NULL | DA36: NULL | DC36: NULL | DG36: NULL | DI36: NULL
C37: T | D37: 品目詳細マスタ | K37: 優先順 | AQ37: NULL | BU37: NULL | BW37: NULL | BY37: NULL | CA37: NULL | CC37: NULL | CE37: NULL | CG37: NULL | CI37: NULL | CS37: NULL | CU37: NULL | CW37: NULL | CY37: NULL | DA37: NULL | DC37: NULL | DG37: NULL | DI37: NULL
C38: T | D38: 品目詳細マスタ | K38: オーダ比率 | AQ38: 1 | BU38: 1 | BW38: 1 | BY38: 1 | CA38: 1 | CC38: 1 | CE38: 1 | CG38: 1 | CI38: 1 | CS38: 1 | CU38: 1 | CW38: 1 | CY38: 1 | DA38: 1 | DC38: 1 | DG38: 1 | DI38: 1
C39: T | D39: 品目詳細マスタ | K39: 出来高予定数量 | AQ39: 1 | BU39: 1 | BW39: 1 | BY39: 1 | CA39: 1 | CC39: 1 | CE39: 1 | CG39: 1 | CI39: 1 | CS39: 1 | CU39: 1 | CW39: 1 | CY39: 1 | DA39: 1 | DC39: 1 | DG39: 1 | DI39: 1
C40: T | D40: 品目詳細マスタ | K40: 製造指図数量 | AQ40: 1 | BU40: 0 | BW40: 0 | BY40: 0 | CA40: 0 | CC40: 0 | CE40: 0 | CG40: 0 | CI40: 0 | CS40: 0 | CU40: 0 | CW40: 0 | CY40: 0 | DA40: 0 | DC40: 0 | DG40: 0 | DI40: 0
C41: T | D41: 品目詳細マスタ | K41: 固定必要数量 | AQ41: NULL | BU41: NULL | BW41: NULL | BY41: NULL | CA41: NULL | CC41: NULL | CE41: NULL | CG41: NULL | CI41: NULL | CS41: NULL | CU41: NULL | CW41: NULL | CY41: NULL | DA41: NULL | DC41: NULL | DG41: NULL | DI41: NULL
C42: T | D42: 品目詳細マスタ | K42: ロット発番タイミング区分 | AQ42: 1:製造指図時 | BU42: NULL | BW42: 1:製造指図時 | BY42: 1:製造指図時 | CA42: 1:製造指図時 | CC42: 1:製造指図時 | CE42: NULL | CG42: NULL | CI42: NULL | CS42: 1:製造指図時 | CU42: 1:製造指図時 | CW42: 1:製造指図時 | CY42: NULL | DA42: NULL | DC42: NULL | DG42: NULL | DI42: NULL
C43: T | D43: 品目詳細マスタ | K43: バックフラッシュ許可ＦＬＧ | AQ43: 0 | BU43: 0 | BW43: 0 | BY43: 0 | CA43: 0 | CC43: 0 | CE43: 0 | CG43: 0 | CI43: 0 | CS43: 0 | CU43: 0 | CW43: 0 | CY43: 0 | DA43: 0 | DC43: 0 | DG43: 0 | DI43: 0
C44: T | D44: 品目詳細マスタ | K44: 棚・ライン格納ＦＬＧ | AQ44: 0 | BU44: 0 | BW44: 0 | BY44: 0 | CA44: 0 | CC44: 0 | CE44: 0 | CG44: 0 | CI44: 0 | CS44: 0 | CU44: 0 | CW44: 0 | CY44: 0 | DA44: 0 | DC44: 0 | DG44: 0 | DI44: 0
C45: T | D45: 品目詳細マスタ | K45: 先行手配対象ＦＬＧ | AQ45: 0 | BU45: 0 | BW45: 0 | BY45: 0 | CA45: 0 | CC45: 0 | CE45: 0 | CG45: 0 | CI45: 0 | CS45: 0 | CU45: 0 | CW45: 0 | CY45: 0 | DA45: 0 | DC45: 0 | DG45: 0 | DI45: 0
C46: T | D46: 品目詳細マスタ | K46: 製造指図時記録書発行ＦＬＧ | AQ46: 0 | BU46: 0 | BW46: 0 | BY46: 0 | CA46: 0 | CC46: 0 | CE46: 0 | CG46: 0 | CI46: 0 | CS46: 0 | CU46: 0 | CW46: 0 | CY46: 0 | DA46: 0 | DC46: 0 | DG46: 0 | DI46: 0
C47: T | D47: 品目詳細マスタ | K47: 製造承認対象外ＦＬＧ | AQ47: 0 | BU47: 0 | BW47: 0 | BY47: 0 | CA47: 0 | CC47: 0 | CE47: 0 | CG47: 0 | CI47: 0 | CS47: 0 | CU47: 0 | CW47: 0 | CY47: 0 | DA47: 0 | DC47: 0 | DG47: 0 | DI47: 0
C48: T | D48: 品目詳細マスタ | K48: 品目下限収率 | AQ48: NULL | BU48: NULL | BW48: NULL | BY48: NULL | CA48: NULL | CC48: NULL | CE48: NULL | CG48: NULL | CI48: NULL | CS48: NULL | CU48: NULL | CW48: NULL | CY48: NULL | DA48: NULL | DC48: NULL | DG48: NULL | DI48: NULL
C49: T | D49: 品目詳細マスタ | K49: 品目標準収率 | AQ49: NULL | BU49: NULL | BW49: NULL | BY49: NULL | CA49: NULL | CC49: NULL | CE49: NULL | CG49: NULL | CI49: NULL | CS49: NULL | CU49: NULL | CW49: NULL | CY49: NULL | DA49: NULL | DC49: NULL | DG49: NULL | DI49: NULL
C50: T | D50: 品目詳細マスタ | K50: 品目上限収率 | AQ50: NULL | BU50: NULL | BW50: NULL | BY50: NULL | CA50: NULL | CC50: NULL | CE50: NULL | CG50: NULL | CI50: NULL | CS50: NULL | CU50: NULL | CW50: NULL | CY50: NULL | DA50: NULL | DC50: NULL | DG50: NULL | DI50: NULL
C51: T | D51: 品目詳細マスタ | K51: 購買識別区分 | AQ51: NULL | BU51: NULL | BW51: NULL | BY51: NULL | CA51: NULL | CC51: NULL | CE51: NULL | CG51: NULL | CI51: NULL | CS51: NULL | CU51: NULL | CW51: NULL | CY51: NULL | DA51: NULL | DC51: NULL | DG51: NULL | DI51: NULL
... C62: T | D62: 品目詳細マスタ | K62: ＭＲＰ対象外ＦＬＧ | AQ62: 0 | BU62: 1 | BW62: 0 | BY62: 0 | CA62: 0 | CC62: 0 | CE62: 0 | CG62: 0 | CI62: 0 | CS62: 0 | CU62: 1:対象外 | CW62: 0 | CY62: 0 | DA62: 0 | DC62: 0 | DG62: 0 | DI62: 0
C63: T | D63: 品目詳細マスタ | K63: 原価比率 | BU63: NULL | BW63: NULL | BY63: NULL | CA63: NULL | CC63: NULL | CE63: NULL | CG63: NULL | CI63: NULL | CS63: NULL | CU63: NULL | CW63: NULL | CY63: NULL | DA63: NULL | DC63: NULL | DG63: NULL | DI63: NULL
C64: T | D64: 品目詳細マスタ | K64: メモ１ | BU64: NULL | BW64: NULL | BY64: NULL | CA64: NULL | CC64: NULL | CE64: NULL | CG64: NULL | CI64: NULL | CS64: NULL | CU64: NULL | CW64: NULL | CY64: NULL | DA64: NULL | DC64: NULL | DG64: NULL | DI64: NULL
C65: T | D65: 品目詳細マスタ | K65: メモ２ | BU65: NULL | BW65: NULL | BY65: NULL | CA65: NULL | CC65: NULL | CE65: NULL | CG65: NULL | CI65: NULL | CS65: NULL | CU65: NULL | CW65: NULL | CY65: NULL | DA65: NULL | DC65: NULL | DG65: NULL | DI65: NULL
C66: T | D66: 品目詳細マスタ | K66: メモ３ | BU66: NULL | BW66: NULL | BY66: NULL | CA66: NULL | CC66: NULL | CE66: NULL | CG66: NULL | CI66: NULL | CS66: NULL | CU66: NULL | CW66: NULL | CY66: NULL | DA66: NULL | DC66: NULL | DG66: NULL | DI66: NULL
C67: T | D67: 品目詳細マスタ | K67: 論理削除ＦＬＧ | AQ67: 0 | BU67: 0 | BW67: 0 | BY67: 0 | CA67: 0 | CC67: 0 | CE67: 0 | CG67: 0 | CI67: 0 | CS67: 0 | CU67: 0 | CW67: 0 | CY67: 0 | DA67: 0 | DC67: 0 | DG67: 0 | DI67: 0
C68: T | D68: 品目詳細マスタ | K68: 論理削除ユーザＩＤ | AQ68: NULL | BU68: NULL | BW68: NULL | BY68: NULL | CA68: NULL | CC68: NULL | CE68: NULL | CG68: NULL | CI68: NULL | CS68: NULL | CU68: NULL | CW68: NULL | CY68: NULL | DA68: NULL | DC68: NULL | DG68: NULL | DI68: NULL
C69: T | D69: 品目詳細マスタ | K69: 論理削除ユーザ名 | AQ69: NULL | BU69: NULL | BW69: NULL | BY69: NULL | CA69: NULL | CC69: NULL | CE69: NULL | CG69: NULL | CI69: NULL | CS69: NULL | CU69: NULL | CW69: NULL | CY69: NULL | DA69: NULL | DC69: NULL | DG69: NULL | DI69: NULL
C70: T | D70: 品目詳細マスタ | K70: 論理削除日時 | AQ70: NULL | BU70: NULL | BW70: NULL | BY70: NULL | CA70: NULL | CC70: NULL | CE70: NULL | CG70: NULL | CI70: NULL | CS70: NULL | CU70: NULL | CW70: NULL | CY70: NULL | DA70: NULL | DC70: NULL | DG70: NULL | DI70: NULL
C71: T | D71: 品目詳細マスタ | K71: 登録ユーザＩＤ | AQ71: 登録ユーザー | BU71: 登録ユーザー | BW71: 登録ユーザー | BY71: 登録ユーザー | CA71: 登録ユーザー | CC71: 登録ユーザー | CE71: 登録ユーザー | CG71: 登録ユーザー | CI71: 登録ユーザー | CS71: 登録ユーザー | CU71: 登録ユーザー | CW71: 登録ユーザー | CY71: 登録ユーザー | DA71: 登録ユーザー | DC71: 登録ユーザー | DG71: 登録ユーザー | DI71: 登録ユーザー
C72: T | D72: 品目詳細マスタ | K72: 登録ユーザ名 | AQ72: 登録ユーザー名 | BU72: 登録ユーザー名 | BW72: 登録ユーザー名 | BY72: 登録ユーザー名 | CA72: 登録ユーザー名 | CC72: 登録ユーザー名 | CE72: 登録ユーザー名 | CG72: 登録ユーザー名 | CI72: 登録ユーザー名 | CS72: 登録ユーザー名 | CU72: 登録ユーザー名 | CW72: 登録ユーザー名 | CY72: 登録ユーザー名 | DA72: 登録ユーザー名 | DC72: 登録ユーザー名 | DG72: 登録ユーザー名 | DI72: 登録ユーザー名
C73: T | D73: 品目詳細マスタ | K73: 登録日時 | AQ73: 処理日時 | BU73: 処理日時 | BW73: 処理日時 | BY73: 処理日時 | CA73: 処理日時 | CC73: 処理日時 | CE73: 処理日時 | CG73: 処理日時 | CI73: 処理日時 | CS73: 処理日時 | CU73: 処理日時 | CW73: 処理日時 | CY73: 処理日時 | DA73: 処理日時 | DC73: 処理日時 | DG73: 処理日時 | DI73: 処理日時
C74: T | D74: 品目詳細マスタ | K74: 登録機能ＩＤ
C75: T | D75: 品目詳細マスタ | K75: 更新カウンタ | AQ75: 0 | BU75: 0 | BW75: 0 | BY75: 0 | CA75: 0 | CC75: 0 | CE75: 0 | CG75: 0 | CI75: 0 | CS75: 0 | CU75: 0 | CW75: 0 | CY75: 0 | DA75: 0 | DC75: 0 | DG75: 0 | DI75: 0
C76: T | D76: 品目詳細マスタ | K76: 更新ユーザＩＤ | AQ76: 登録ユーザー | BU76: 登録ユーザー | BW76: 登録ユーザー | BY76: 登録ユーザー | CA76: 登録ユーザー | CC76: 登録ユーザー | CE76: 登録ユーザー | CG76: 登録ユーザー | CI76: 登録ユーザー | CS76: 登録ユーザー | CU76: 登録ユーザー | CW76: 登録ユーザー | CY76: 登録ユーザー | DA76: 登録ユーザー | DC76: 登録ユーザー | DG76: 登録ユーザー | DI76: 登録ユーザー
C77: T | D77: 品目詳細マスタ | K77: 更新ユーザ名 | AQ77: 登録ユーザー名 | BU77: 登録ユーザー名 | BW77: 登録ユーザー名 | BY77: 登録ユーザー名 | CA77: 登録ユーザー名 | CC77: 登録ユーザー名 | CE77: 登録ユーザー名 | CG77: 登録ユーザー名 | CI77: 登録ユーザー名 | CS77: 登録ユーザー名 | CU77: 登録ユーザー名 | CW77: 登録ユーザー名 | CY77: 登録ユーザー名 | DA77: 登録ユーザー名 | DC77: 登録ユーザー名 | DG77: 登録ユーザー名 | DI77: 登録ユーザー名
C78: T | D78: 品目詳細マスタ | K78: 更新日時 | AQ78: 処理日時 | BU78: 処理日時 | BW78: 処理日時 | BY78: 処理日時 | CA78: 処理日時 | CC78: 処理日時 | CE78: 処理日時 | CG78: 処理日時 | CI78: 処理日時 | CS78: 処理日時 | CU78: 処理日時 | CW78: 処理日時 | CY78: 処理日時 | DA78: 処理日時 | DC78: 処理日時 | DG78: 処理日時 | DI78: 処理日時
C79: T | D79: 品目詳細マスタ | K79: 更新機能ＩＤ
C80: T | D80: 品目詳細マスタ | K80: 更新リクエストＮＯ
C81: T | D81: 品目詳細マスタ | K81: 仕入計上区分
A82: No | G82: 1 | H82: 品目詳細マスタ_製品 | S82: ロジック名称 | AH82: 備考 | BP82: 品目区分別設定値 | CR82: 通常パタン （前工程仕掛品を投入して、加工） | CT82: 連産品（N丁取り） | CV82: 複数仕掛品を投入 （タンデム） | CX82: 購入品（都度採番）手配対象 | CZ82: 外注品（都度採番）手配対象 ※有償/無償支給 | DB82: 外注品（都度採番）手配対象 ※自給品（無償支給）（材料・仕入の支払い分割） | DD82: 消耗品（在庫管理対象外）手配対象 | DF82: 共通品目（発注点発注）を投入 | DH82: 共通品目（MRP発注）を投入
A83: 処理分類 | E83: 更新 | BP83: 商品 | BV83: 製品 | BZ83: 中間品 | CH83: 資材 | CJ83: 資材 | CL83: 原料 | CN83: その他
A84: No | C84: 転送先 | V84: 転送元 | AQ84: 説明 | BP84: 構成あり | BR84: 構成なし | BT84: 版型 | BV84: 内 | BX84: 外 | BZ84: 内（自事業所） | CB84: 内（他事業所） | CD84: 外 | CF84: 購買 | CH84: 在庫管理品（カートン等） | CJ84: 非在庫品 | CL84: 購買 | CN84: 購買
C85: 種 | D85: オブジェクト | K85: 項目名 | V85: 種 | W85: オブジェクト | AF85: 項目名 | BP85: オブジェクト | BQ85: 項目名 | BR85: オブジェクト | BS85: 項目名 | BT85: オブジェクト | BU85: 項目名 | BV85: オブジェクト | BW85: 項目名 | BX85: オブジェクト | BY85: 項目名 | BZ85: オブジェクト | CA85: 項目名 | CB85: オブジェクト | CC85: 項目名 | CD85: オブジェクト | CE85: 項目名 | CF85: オブジェクト | CG85: 項目名 | CH85: オブジェクト | CI85: 項目名 | CJ85: オブジェクト | CK85: 項目名 | CL85: オブジェクト | CM85: 項目名 | CN85: オブジェクト | CO85: 項目名 | CR85: オブジェクト | CS85: 項目名 | CT85: オブジェクト | CU85: 項目名 | CV85: オブジェクト | CW85: 項目名 | CX85: オブジェクト | CY85: 項目名 | CZ85: オブジェクト | DA85: 項目名 | DB85: オブジェクト | DC85: 項目名 | DD85: オブジェクト | DE85: 項目名 | DF85: オブジェクト | DG85: 項目名 | DH85: オブジェクト | DI85: 項目名
C86: T | D86: 品目詳細マスタ | K86: 適用終了日 | AQ86: 2099/12/31 | BU86: 処理日時-1 | BW86: 処理日時-1 | BY86: 処理日時-1 | CA86: 処理日時-1 | CC86: 処理日時-1 | CE86: 処理日時-1 | CG86: 処理日時-1 | CI86: 処理日時-1 | CS86: 処理日時-1 | CU86: 処理日時-1 | CW86: 処理日時-1 | CY86: 処理日時-1 | DA86: 処理日時-1 | DC86: 処理日時-1 | DG86: 処理日時-1 | DI86: 処理日時-1
C87: T | D87: 品目詳細マスタ | K87: 更新カウンタ | AQ87: 0 | BU87: 0 | BW87: 0 | BY87: 0 | CA87: 0 | CC87: 0 | CE87: 0 | CG87: 0 | CI87: 0 | CS87: 0 | CU87: 0 | CW87: 0 | CY87: 0 | DA87: 0 | DC87: 0 | DG87: 0 | DI87: 0
C88: T | D88: 品目詳細マスタ | K88: 更新ユーザＩＤ | AQ88: 登録ユーザー | BU88: 登録ユーザー | BW88: 登録ユーザー | BY88: 登録ユーザー | CA88: 登録ユーザー | CC88: 登録ユーザー | CE88: 登録ユーザー | CG88: 登録ユーザー | CI88: 登録ユーザー | CS88: 登録ユーザー | CU88: 登録ユーザー | CW88: 登録ユーザー | CY88: 登録ユーザー | DA88: 登録ユーザー | DC88: 登録ユーザー | DG88: 登録ユーザー | DI88: 登録ユーザー
C89: T | D89: 品目詳細マスタ | K89: 更新ユーザ名 | AQ89: 登録ユーザー名 | BU89: 登録ユーザー名 | BW89: 登録ユーザー名 | BY89: 登録ユーザー名 | CA89: 登録ユーザー名 | CC89: 登録ユーザー名 | CE89: 登録ユーザー名 | CG89: 登録ユーザー名 | CI89: 登録ユーザー名 | CS89: 登録ユーザー名 | CU89: 登録ユーザー名 | CW89: 登録ユーザー名 | CY89: 登録ユーザー名 | DA89: 登録ユーザー名 | DC89: 登録ユーザー名 | DG89: 登録ユーザー名 | DI89: 登録ユーザー名
C90: T | D90: 品目詳細マスタ | K90: 更新日時 | AQ90: 処理日時 | BU90: 処理日時 | BW90: 処理日時 | BY90: 処理日時 | CA90: 処理日時 | CC90: 処理日時 | CE90: 処理日時 | CG90: 処理日時 | CI90: 処理日時 | CS90: 処理日時 | CU90: 処理日時 | CW90: 処理日時 | CY90: 処理日時 | DA90: 処理日時 | DC90: 処理日時 | DG90: 処理日時 | DI90: 処理日時
C91: T | D91: 品目詳細マスタ | K91: 更新機能ＩＤ
C92: T | D92: 品目詳細マスタ | K92: 更新リクエストＮＯ

Sheet 更新入出力仕様_品目工程マスタ 
A1: =表紙!A54 -> Webシステム | K1: 文書名 | U1: モジュールID | Z1: =表紙!$AJ$63 -> MS | AE1: モジュール名 | AJ1: =表紙!$AX$63 -> 見積管理 | AS1: 文書番号 | AZ1: Version | BF1: Rev.
K2: =表紙!O64 -> アドオン設計書 | U2: ｻﾌﾞﾓｼﾞｭｰﾙID | Z2: =表紙!$AJ$64 -> MSBB | AE2: ｻﾌﾞﾓｼﾞｭｰﾙ名 | AJ2: =表紙!$AX$64 -> Webシステム | AS2: =表紙!$BL$64 -> M7-US-1140 | AZ2: =表紙!$BU$64 -> 7.0.2 | BF2: =表紙!$CB$64 -> 8
K3: =RIGHT(CELL("filename",$A$1),LEN(CELL("filename",$A$1))-FIND("]",CELL("filename",$A$1))) -> 更新入出力仕様_品目工程マスタ | U3: 表題 | Z3: =表紙!$AJ$65 -> - | AE3: =表紙!$AQ$65 -> 製品マスタ連携
A5: No | G5: 1 | H5: 品目工程マスタ | S5: ロジック名称 | AH5: 備考 | BP5: 品目区分別設定値 | CP5: REV4.0 商品を概要と合わせる
A6: 処理分類 | E6: 登録 | BP6: 商品 | BV6: 製品 | BZ6: 中間品 | CF6: 資材 | CH6: 資材 | CJ6: 原料 | CL6: その他
A7: No | C7: 転送先 | V7: 転送元 | AQ7: 説明 | BP7: 構成あり | BR7: 構成なし | BT7: 版型 | BV7: 内 | BX7: 外 | BZ7: 内 | CB7: 外 | CD7: 購買 | CF7: 在庫管理品（カートン等） | CH7: 非在庫品 | CJ7: 購買 | CL7: 購買
C8: 種 | D8: オブジェクト | K8: 項目名 | V8: 種 | W8: オブジェクト | AF8: 項目名 | BP8: オブジェクト | BQ8: 項目名 | BR8: オブジェクト | BS8: 項目名 | BT8: オブジェクト | BU8: 項目名 | BV8: オブジェクト | BW8: 項目名 | BX8: オブジェクト | BY8: 項目名 | BZ8: オブジェクト | CA8: 項目名 | CB8: オブジェクト | CC8: 項目名 | CD8: オブジェクト | CE8: 項目名 | CF8: オブジェクト | CG8: 項目名 | CH8: オブジェクト | CI8: 項目名 | CJ8: オブジェクト | CK8: 項目名 | CL8: オブジェクト | CM8: 項目名
C9: T | D9: 品目工程マスタ | K9: 品目ＣＤ | V9: T | W9: 品目マスタ | AF9: 品目CD | AQ9: 工程CDに対応する品目CD | BV9: 品目マスタ（共通） | BW9: 品目ＣＤ | BZ9: 品目マスタ（共通） | CA9: 品目ＣＤ
C10: T | D10: 品目工程マスタ | K10: 枝番１ | V10: T | W10: 品目マスタ | AF10: 枝番１ | AQ10: 工程CDに対応する品目枝番１ | BV10: 品目マスタ（共通） | BW10: 枝番１ | BZ10: 品目マスタ（共通） | CA10: 枝番１
C11: T | D11: 品目工程マスタ | K11: 枝番２ | V11: T | W11: 品目マスタ | AF11: 枝番２ | AQ11: 工程CDに対応する品目枝番２ | BV11: 品目マスタ（共通） | BW11: 枝番２ | BZ11: 品目マスタ（共通） | CA11: 枝番２
C12: T | D12: 品目工程マスタ | K12: 枝番３ | V12: T | W12: 品目マスタ | AF12: 枝番３ | AQ12: 工程CDに対応する品目枝番３ | BV12: 品目マスタ（共通） | BW12: 枝番３ | BZ12: 品目マスタ（共通） | CA12: 枝番３
C13: T | D13: 品目工程マスタ | K13: 場所ＣＤ | V13: 画 | W13: 製品加工工程マスタ | AF13: 号機/発注 | AQ13: ワーキンググループごと、工程毎の号機 | BV13: 製品加工工程マスタ | BW13: 号機 | BZ13: 製品加工工程マスタ | CA13: 号機
C14: T | D14: 品目工程マスタ | K14: 工程パタン | AQ14: 固定:1 | BW14: 固定:1 | CA14: 固定:1
C15: T | D15: 品目工程マスタ | K15: 工程ＣＤ | V15: 画 | W15: 製品加工工程マスタ | AF15: 作業順CD | BV15: 製品加工工程マスタ | BW15: 作業工程CD | BZ15: 製品加工工程マスタ | CA15: 作業工程CD
C16: T | D16: 品目工程マスタ | K16: 工程連番 | AQ16: 固定:1 | BW16: 固定:1 | CA16: 固定:1
C17: T | D17: 品目工程マスタ | K17: 適用開始日 | AQ17: 処理日付 | BW17: 処理日付 | CA17: 処理日付
C18: T | D18: 品目工程マスタ | K18: 会社ＣＤ | AQ18: 固定：会社CD | BW18: 固定：会社CD | CA18: 固定：会社CD
C19: T | D19: 品目工程マスタ | K19: 適用終了日 | AQ19: 固定：2099/12/31 | BW19: 固定：2099/12/31 | CA19: 固定：2099/12/31
C20: T | D20: 品目工程マスタ | K20: 工順 | V20: 画 | W20: 製品加工工程マスタ | AF20: 作業順 | BV20: 製品加工工程マスタ | BW20: 作業順 | BZ20: 製品加工工程マスタ | CA20: 作業順
C21: T | D21: 品目工程マスタ | K21: 工程ＬＴ | AQ21: 固定:0 | BW21: 固定:0 | CA21: 固定:0
C22: T | D22: 品目工程マスタ | K22: 工程ＬＴ加算基準数量 | AQ22: 固定：NULL | BW22: 固定：NULL | CA22: 固定：NULL
C23: T | D23: 品目工程マスタ | K23: 工程オフセット区分 | AQ23: 1：着手日起算 2：完了日起算 1：着手日起算 | BW23: 1：着手日起算 2：完了日起算 1：着手日起算 | CA23: 1：着手日起算 2：完了日起算 1：着手日起算
C24: T | D24: 品目工程マスタ | K24: 工程オフセット | AQ24: 固定：0 | BW24: 固定：0 | CA24: 固定：0
C25: T | D25: 品目工程マスタ | K25: 工程オフセット加算基準数量 | AQ25: 固定：NULL | BW25: 固定：NULL | CA25: 固定：NULL
C26: T | D26: 品目工程マスタ | K26: 工程管理単位ＣＤ | AQ26: 固定：NULL | BW26: 固定：NULL | CA26: 固定：NULL
C27: T | D27: 品目工程マスタ | K27: 工程基準単位数量 | AQ27: 固定：NULL | BW27: 固定：NULL | CA27: 固定：NULL
C28: T | D28: 品目工程マスタ | K28: 工程換算単位数量 | AQ28: 固定：NULL | BW28: 固定：NULL | CA28: 固定：NULL
C29: T | D29: 品目工程マスタ | K29: 小数部有効桁数 | AQ29: 固定：0 | BW29: 固定：0 | CA29: 固定：0
C30: T | D30: 品目工程マスタ | K30: 換算端数処理区分 | AQ30: 1：切り上げ 2：切り捨て 3：四捨五入 固定：NULL | BW30: 1：切り上げ 2：切り捨て 3：四捨五入 固定：NULL | CA30: 1：切り上げ 2：切り捨て 3：四捨五入 固定：NULL
C31: T | D31: 品目工程マスタ | K31: 出来高計上工程ＦＬＧ | AQ31: 最終作業順：1 出来高工程 それ以外:0 | BW31: 最終作業順：1 出来高工程 それ以外:0 | CA31: 最終作業順：1 出来高工程 それ以外:0
C32: T | D32: 品目工程マスタ | K32: 出来高工程比率 | AQ32: 出来高工程以外： 固定：NULL 出来高工程： 0 | BW32: 出来高工程以外： 固定：NULL 出来高工程： 0 | CA32: 出来高工程以外： 固定：NULL 出来高工程： 0
... C34: T | D34: 品目工程マスタ | K34: 工程場所ＣＤ | AQ34: 固定：NULL | BW34: 固定：NULL | CA34: 固定：NULL
C35: T | D35: 品目工程マスタ | K35: 期限起算日使用工程ＦＬＧ | AQ35: 0 | BW35: 0 | CA35: 0
C36: T | D36: 品目工程マスタ | K36: 工程下限収率 | AQ36: 固定：NULL | BW36: 固定：NULL | CA36: 固定：NULL
C37: T | D37: 品目工程マスタ | K37: 工程標準収率 | AQ37: 固定：NULL | BW37: 固定：NULL | CA37: 固定：NULL
C38: T | D38: 品目工程マスタ | K38: 工程上限収率 | AQ38: 固定：NULL | BW38: 固定：NULL | CA38: 固定：NULL
C39: T | D39: 品目工程マスタ | K39: 仕掛進捗率 | AQ39: 固定：NULL | BW39: 固定：NULL | CA39: 固定：NULL
C40: T | D40: 品目工程マスタ | K40: 手配ＮＯ１ | AQ40: 固定：NULL | BW40: 固定：NULL | CA40: 固定：NULL
C41: T | D41: 品目工程マスタ | K41: 手配ＮＯ２ | AQ41: 固定：NULL | BW41: 固定：NULL | CA41: 固定：NULL
C42: T | D42: 品目工程マスタ | K42: 手配ＮＯ３ | AQ42: 固定：NULL | BW42: 固定：NULL | CA42: 固定：NULL
C43: T | D43: 品目工程マスタ | K43: 手配ＮＯ４ | AQ43: 固定：NULL | BW43: 固定：NULL | CA43: 固定：NULL
C44: T | D44: 品目工程マスタ | K44: 原価対象外ＦＬＧ | AQ44: 0 | BW44: 0 | CA44: 0
C45: T | D45: 品目工程マスタ | K45: メモ１ | AQ45: 固定：NULL | BW45: 固定：NULL | CA45: 固定：NULL
C46: T | D46: 品目工程マスタ | K46: メモ２ | AQ46: 固定：NULL | BW46: 固定：NULL | CA46: 固定：NULL
C47: T | D47: 品目工程マスタ | K47: メモ３ | AQ47: 固定：NULL | BW47: 固定：NULL | CA47: 固定：NULL
C48: T | D48: 品目工程マスタ | K48: 論理削除ＦＬＧ | AQ48: 0 | BW48: 0 | CA48: 0
C49: T | D49: 品目工程マスタ | K49: 論理削除ユーザＩＤ | AQ49: 固定：NULL | BW49: 固定：NULL | CA49: 固定：NULL
C50: T | D50: 品目工程マスタ | K50: 論理削除ユーザ名 | AQ50: 固定：NULL | BW50: 固定：NULL | CA50: 固定：NULL
C51: T | D51: 品目工程マスタ | K51: 論理削除日時 | AQ51: 固定：NULL | BW51: 固定：NULL | CA51: 固定：NULL
C52: T | D52: 品目工程マスタ | K52: 登録ユーザＩＤ | AQ52: 登録ユーザー | BW52: 登録ユーザー | CA52: 登録ユーザー
C53: T | D53: 品目工程マスタ | K53: 登録ユーザ名 | AQ53: 登録ユーザー名 | BW53: 登録ユーザー名 | CA53: 登録ユーザー名
C54: T | D54: 品目工程マスタ | K54: 登録日時 | AQ54: 処理日時 | BW54: 処理日時 | CA54: 処理日時
C55: T | D55: 品目工程マスタ | K55: 登録機能ＩＤ
C56: T | D56: 品目工程マスタ | K56: 更新カウンタ | AQ56: 0 | BW56: 0 | CA56: 0
C57: T | D57: 品目工程マスタ | K57: 更新ユーザＩＤ | AQ57: 登録ユーザー | BW57: 登録ユーザー | CA57: 登録ユーザー
C58: T | D58: 品目工程マスタ | K58: 更新ユーザ名 | AQ58: 登録ユーザー名 | BW58: 登録ユーザー名 | CA58: 登録ユーザー名
C59: T | D59: 品目工程マスタ | K59: 更新日時 | AQ59: 処理日時 | BW59: 処理日時 | CA59: 処理日時
C60: T | D60: 品目工程マスタ | K60: 更新機能ＩＤ
C61: T | D61: 品目工程マスタ | K61: 更新リクエストＮＯ
A62: No | G62: 1 | H62: 品目工程マスタ | S62: ロジック名称 | AH62: 備考 | BP62: 品目区分別設定値
A63: 処理分類 | E63: 登録 | BP63: 商品 | BV63: 製品 | BZ63: 中間品 | CF63: 資材 | CH63: 資材 | CJ63: 原料 | CL63: その他
A64: No | C64: 転送先 | V64: 転送元 | AQ64: 説明 | BP64: 構成あり | BR64: 構成なし | BT64: 版型 | BV64: 内 | BX64: 外 | BZ64: 内 | CB64: 外 | CD64: 購買 | CF64: 在庫管理品（カートン等） | CH64: 非在庫品 | CJ64: 購買 | CL64: 購買
C65: 種 | D65: オブジェクト | K65: 項目名 | V65: 種 | W65: オブジェクト | AF65: 項目名 | BP65: オブジェクト | BQ65: 項目名 | BR65: オブジェクト | BS65: 項目名 | BT65: オブジェクト | BU65: 項目名 | BV65: オブジェクト | BW65: 項目名 | BX65: オブジェクト | BY65: 項目名 | BZ65: オブジェクト | CA65: 項目名 | CB65: オブジェクト | CC65: 項目名 | CD65: オブジェクト | CE65: 項目名 | CF65: オブジェクト | CG65: 項目名 | CH65: オブジェクト | CI65: 項目名 | CJ65: オブジェクト | CK65: 項目名 | CL65: オブジェクト | CM65: 項目名
C66: T | D66: 品目工程マスタ | K66: 適用終了日 | AQ66: 固定：2099/12/31 | BW66: 処理日時-1 | CA66: 処理日時-1
C67: T | D67: 品目工程マスタ | K67: 論理削除ＦＬＧ | AQ67: 0 | BW67: 0 | CA67: 0
C68: T | D68: 品目工程マスタ | K68: 論理削除ユーザＩＤ | AQ68: 固定：NULL | BW68: 固定：NULL | CA68: 固定：NULL
C69: T | D69: 品目工程マスタ | K69: 論理削除ユーザ名 | AQ69: 固定：NULL | BW69: 固定：NULL | CA69: 固定：NULL
C70: T | D70: 品目工程マスタ | K70: 論理削除日時 | AQ70: 固定：NULL | BW70: 固定：NULL | CA70: 固定：NULL
C71: T | D71: 品目工程マスタ | K71: 更新カウンタ | AQ71: 0 | BW71: 0 | CA71: 0
C72: T | D72: 品目工程マスタ | K72: 更新ユーザＩＤ | AQ72: 登録ユーザー | BW72: 登録ユーザー | CA72: 登録ユーザー
C73: T | D73: 品目工程マスタ | K73: 更新ユーザ名 | AQ73: 登録ユーザー名 | BW73: 登録ユーザー名 | CA73: 登録ユーザー名
C74: T | D74: 品目工程マスタ | K74: 更新日時 | AQ74: 処理日時 | BW74: 処理日時 | CA74: 処理日時
C75: T | D75: 品目工程マスタ | K75: 更新機能ＩＤ
C76: T | D76: 品目工程マスタ | K76: 更新リクエストＮＯ

Sheet 更新入出力仕様_品目格納先マスタ 
A1: =表紙!A54 -> Webシステム | K1: 文書名 | U1: モジュールID | Z1: =表紙!$AJ$63 -> MS | AE1: モジュール名 | AJ1: =表紙!$AX$63 -> 見積管理 | AS1: 文書番号 | AZ1: Version | BF1: Rev.
K2: =表紙!O64 -> アドオン設計書 | U2: ｻﾌﾞﾓｼﾞｭｰﾙID | Z2: =表紙!$AJ$64 -> MSBB | AE2: ｻﾌﾞﾓｼﾞｭｰﾙ名 | AJ2: =表紙!$AX$64 -> Webシステム | AS2: =表紙!$BL$64 -> M7-US-1140 | AZ2: =表紙!$BU$64 -> 7.0.2 | BF2: =表紙!$CB$64 -> 8
K3: =RIGHT(CELL("filename",$A$1),LEN(CELL("filename",$A$1))-FIND("]",CELL("filename",$A$1))) -> 更新入出力仕様_品目格納先マスタ | U3: 表題 | Z3: =表紙!$AJ$65 -> - | AE3: =表紙!$AQ$65 -> 製品マスタ連携
A5: No | G5: 1 | H5: 品目格納先マスタ_製品 | S5: ロジック名称 | AH5: 備考 | BP5: 品目区分別設定値 | CQ5: REV4.0 商品を概要と合わせる
A6: 処理分類 | E6: 登録 | BP6: 商品 | BV6: 製品 | CB6: 中間品 | CH6: 資材 | CJ6: 資材 | CL6: 原料 | CN6: その他
A7: No | C7: 転送先 | V7: 転送元 | AQ7: 説明 | BP7: 構成あり | BR7: 構成なし | BT7: 版型 | BV7: 内 | BX7: 外 | BZ7: 購買 | CB7: 内 | CD7: 外 | CF7: 購買 | CH7: 在庫管理品（カートン等） | CJ7: 非在庫品 | CL7: 購買 | CN7: 購買
C8: 種 | D8: オブジェクト | K8: 項目名 | V8: 種 | W8: オブジェクト | AF8: 項目名 | BP8: オブジェクト | BQ8: 項目名 | BR8: オブジェクト | BS8: 項目名 | BT8: オブジェクト | BU8: 項目名 | BV8: オブジェクト | BW8: 項目名 | BX8: オブジェクト | BY8: 項目名 | BZ8: オブジェクト | CA8: 項目名 | CB8: オブジェクト | CC8: 項目名 | CD8: オブジェクト | CE8: 項目名 | CF8: オブジェクト | CG8: 項目名 | CH8: オブジェクト | CI8: 項目名 | CJ8: オブジェクト | CK8: 項目名 | CL8: オブジェクト | CM8: 項目名 | CN8: オブジェクト | CO8: 項目名
C9: T | D9: 品目格納先マスタ | K9: 品目ＣＤ | V9: T | W9: 品目マスタ | AF9: 品目CD | BV9: 品目マスタ（共通） | BW9: 品目ＣＤ | BX9: 品目マスタ（共通） | BY9: 品目ＣＤ | CB9: 品目マスタ（共通） | CC9: 品目ＣＤ | CD9: 品目マスタ（共通） | CE9: 品目ＣＤ | CF9: 品目マスタ（共通） | CG9: 品目ＣＤ | CH9: 品目マスタ（共通） | CI9: 品目ＣＤ
C10: T | D10: 品目格納先マスタ | K10: 枝番１ | V10: T | W10: 品目マスタ | AF10: 枝番１ | BV10: 品目マスタ（共通） | BW10: 枝番１ | BX10: 品目マスタ（共通） | BY10: 枝番１ | CB10: 品目マスタ（共通） | CC10: 枝番１ | CD10: 品目マスタ（共通） | CE10: 枝番１ | CF10: 品目マスタ（共通） | CG10: 枝番１ | CH10: 品目マスタ（共通） | CI10: 枝番１
C11: T | D11: 品目格納先マスタ | K11: 枝番２ | V11: T | W11: 品目マスタ | AF11: 枝番２ | BV11: 品目マスタ（共通） | BW11: 枝番２ | BX11: 品目マスタ（共通） | BY11: 枝番２ | CB11: 品目マスタ（共通） | CC11: 枝番２ | CD11: 品目マスタ（共通） | CE11: 枝番２ | CF11: 品目マスタ（共通） | CG11: 枝番２ | CH11: 品目マスタ（共通） | CI11: 枝番２
C12: T | D12: 品目格納先マスタ | K12: 枝番３ | V12: T | W12: 品目マスタ | AF12: 枝番３ | BV12: 品目マスタ（共通） | BW12: 枝番３ | BX12: 品目マスタ（共通） | BY12: 枝番３ | CB12: 品目マスタ（共通） | CC12: 枝番３ | CD12: 品目マスタ（共通） | CE12: 枝番３ | CF12: 品目マスタ（共通） | CG12: 枝番３ | CH12: 品目マスタ（共通） | CI12: 枝番３
C13: T | D13: 品目格納先マスタ | K13: 格納場所ＣＤ | BV13: 製品加工工程マスタ | BW13: 入庫先 | BX13: 製品加工工程マスタ | BY13: 入庫先 | CB13: 製品加工工程マスタ | CC13: 入庫先 | CD13: 製品加工工程マスタ | CE13: 入庫先 | CF13: 製品加工工程マスタ | CG13: 入庫先 | CH13: 製品加工工程マスタ | CI13: 入庫先
C14: T | D14: 品目格納先マスタ | K14: 会社ＣＤ | AQ14: 会社 | BW14: 定数.会社 | BY14: 定数.会社 | CC14: 定数.会社 | CE14: 定数.会社 | CG14: 定数.会社 | CI14: 定数.会社
C15: T | D15: 品目格納先マスタ | K15: 優先順 | BW15: 固定:1 | BY15: 固定:1 | CC15: 固定:1 | CE15: 固定:1 | CG15: 固定:1 | CI15: 固定:1
C16: T | D16: 品目格納先マスタ | K16: メモ１ | BW16: NULL | BY16: NULL | CC16: NULL | CE16: NULL | CG16: NULL | CI16: NULL
C17: T | D17: 品目格納先マスタ | K17: メモ２ | BW17: NULL | BY17: NULL | CC17: NULL | CE17: NULL | CG17: NULL | CI17: NULL
C18: T | D18: 品目格納先マスタ | K18: メモ３ | BW18: NULL | BY18: NULL | CC18: NULL | CE18: NULL | CG18: NULL | CI18: NULL
C19: T | D19: 品目格納先マスタ | K19: 論理削除ＦＬＧ | AQ19: 0 | BW19: 0 | BY19: 0 | CC19: 0 | CE19: 0 | CG19: 0 | CI19: 0
C20: T | D20: 品目格納先マスタ | K20: 論理削除ユーザＩＤ | AQ20: NULL | BW20: NULL | BY20: NULL | CC20: NULL | CE20: NULL | CG20: NULL | CI20: NULL
C21: T | D21: 品目格納先マスタ | K21: 論理削除ユーザ名 | AQ21: NULL | BW21: NULL | BY21: NULL | CC21: NULL | CE21: NULL | CG21: NULL | CI21: NULL
C22: T | D22: 品目格納先マスタ | K22: 論理削除日時 | AQ22: NULL | BW22: NULL | BY22: NULL | CC22: NULL | CE22: NULL | CG22: NULL | CI22: NULL
C23: T | D23: 品目格納先マスタ | K23: 登録ユーザＩＤ | AQ23: 登録ユーザー | BW23: 登録ユーザー | BY23: 登録ユーザー | CC23: 登録ユーザー | CE23: 登録ユーザー | CG23: 登録ユーザー | CI23: 登録ユーザー
C24: T | D24: 品目格納先マスタ | K24: 登録ユーザ名 | AQ24: 登録ユーザー名 | BW24: 登録ユーザー名 | BY24: 登録ユーザー名 | CC24: 登録ユーザー名 | CE24: 登録ユーザー名 | CG24: 登録ユーザー名 | CI24: 登録ユーザー名
C25: T | D25: 品目格納先マスタ | K25: 登録日時 | AQ25: 処理日時 | BW25: 処理日時 | BY25: 処理日時 | CC25: 処理日時 | CE25: 処理日時 | CG25: 処理日時 | CI25: 処理日時
C26: T | D26: 品目格納先マスタ | K26: 登録機能ＩＤ
C27: T | D27: 品目格納先マスタ | K27: 更新カウンタ | AQ27: 0 | BW27: 0 | BY27: 0 | CC27: 0 | CE27: 0 | CG27: 0 | CI27: 0
C28: T | D28: 品目格納先マスタ | K28: 更新ユーザＩＤ | AQ28: 登録ユーザー | BW28: 登録ユーザー | BY28: 登録ユーザー | CC28: 登録ユーザー | CE28: 登録ユーザー | CG28: 登録ユーザー | CI28: 登録ユーザー
C29: T | D29: 品目格納先マスタ | K29: 更新ユーザ名 | AQ29: 登録ユーザー名 | BW29: 登録ユーザー名 | BY29: 登録ユーザー名 | CC29: 登録ユーザー名 | CE29: 登録ユーザー名 | CG29: 登録ユーザー名 | CI29: 登録ユーザー名
C30: T | D30: 品目格納先マスタ | K30: 更新日時 | AQ30: 処理日時 | BW30: 処理日時 | BY30: 処理日時 | CC30: 処理日時 | CE30: 処理日時 | CG30: 処理日時 | CI30: 処理日時
C31: T | D31: 品目格納先マスタ | K31: 更新機能ＩＤ
C32: T | D32: 品目格納先マスタ | K32: 更新リクエストＮＯ
BP34: 品目格納先は同一物流グループ内の場合に作成する。 | BR34: 品目格納先は同一物流グループ内の場合に作成する。 | BT34: 品目格納先は同一物流グループ内の場合に作成する。

Sheet 更新入出力仕様_得意先販売単価マスタ 
A1: =表紙!A54 -> Webシステム | K1: 文書名 | U1: モジュールID | Z1: =表紙!$AJ$63 -> MS | AE1: モジュール名 | AJ1: =表紙!$AX$63 -> 見積管理 | AS1: 文書番号 | AZ1: Version | BF1: Rev.
K2: =表紙!O64 -> アドオン設計書 | U2: ｻﾌﾞﾓｼﾞｭｰﾙID | Z2: =表紙!$AJ$64 -> MSBB | AE2: ｻﾌﾞﾓｼﾞｭｰﾙ名 | AJ2: =表紙!$AX$64 -> Webシステム | AS2: =表紙!$BL$64 -> M7-US-1140 | AZ2: =表紙!$BU$64 -> 7.0.2 | BF2: =表紙!$CB$64 -> 8
K3: =RIGHT(CELL("filename",$A$1),LEN(CELL("filename",$A$1))-FIND("]",CELL("filename",$A$1))) -> 更新入出力仕様_得意先販売単価マスタ | U3: 表題 | Z3: =表紙!$AJ$65 -> - | AE3: =表紙!$AQ$65 -> 製品マスタ連携
A5: No | G5: 1 | H5: 客先販売単価マスタ_製品 | S5: ロジック名称 | AH5: 備考 | BP5: 品目区分別設定値 | CM5: REV4.0 商品を概要と合わせる
A6: 処理分類 | E6: 登録 | BP6: 商品 | BV6: 製品 | BZ6: 中間品 | CD6: 資材 | CF6: 資材 | CH6: 原料 | CJ6: その他
A7: No | C7: 転送先 | V7: 転送元 | AQ7: 説明 | BP7: 構成あり | BR7: 構成なし | BT7: 版型 | BV7: 内 | BX7: 外 | BZ7: 内 | CB7: 外 | CD7: 在庫管理品（カートン等） | CF7: 非在庫品 | CH7: 購買 | CJ7: 購買
C8: 種 | D8: オブジェクト | K8: 項目名 | V8: 種 | W8: オブジェクト | AF8: 項目名 | BP8: オブジェクト | BQ8: 項目名 | BR8: オブジェクト | BS8: 項目名 | BT8: オブジェクト | BU8: 項目名 | BV8: オブジェクト | BW8: 項目名 | BX8: オブジェクト | BY8: 項目名 | BZ8: オブジェクト | CA8: 項目名 | CB8: オブジェクト | CC8: 項目名 | CD8: オブジェクト | CE8: 項目名 | CF8: オブジェクト | CG8: 項目名 | CH8: オブジェクト | CI8: 項目名 | CJ8: オブジェクト | CK8: 項目名
C9: T | D9: 客先販売単価マスタ | K9: 得意先ＣＤ | V9: 画 | W9: 製品ロット別単価マスタ | AF9: 得意先CD | BV9: 製品ロット別単価マスタ | BW9: 得意先CD
C10: T | D10: 客先販売単価マスタ | K10: 納品先ＣＤ | AQ10: NULL | BW10: NULL
C11: T | D11: 客先販売単価マスタ | K11: 仕向先ＣＤ１ | AQ11: NULL | BW11: NULL
C12: T | D12: 客先販売単価マスタ | K12: 仕向先ＣＤ２ | AQ12: NULL | BW12: NULL
C13: T | D13: 客先販売単価マスタ | K13: 仕向先ＣＤ３ | AQ13: NULL | BW13: NULL
C14: T | D14: 客先販売単価マスタ | K14: 販売単価分類ＣＤ | AQ14: NULL | BW14: NULL
C15: T | D15: 客先販売単価マスタ | K15: 品目ＣＤ | V15: T | W15: 品目マスタ | AF15: 品目CD | BV15: 品目マスタ（共通） | BW15: 品目ＣＤ
C16: T | D16: 客先販売単価マスタ | K16: 枝番１ | V16: T | W16: 品目マスタ | AF16: 枝番１ | BV16: 品目マスタ（共通） | BW16: 枝番１
C17: T | D17: 客先販売単価マスタ | K17: 枝番２ | V17: T | W17: 品目マスタ | AF17: 枝番２ | BV17: 品目マスタ（共通） | BW17: 枝番２
C18: T | D18: 客先販売単価マスタ | K18: 枝番３ | V18: T | W18: 品目マスタ | AF18: 枝番３ | BV18: 品目マスタ（共通） | BW18: 枝番３
C19: T | D19: 客先販売単価マスタ | K19: 単位ＣＤ | V19: T | W19: 品目マスタ | AF19: 単位CD | BV19: 品目マスタ（共通） | BW19: 単位CD
C20: T | D20: 客先販売単価マスタ | K20: ロット数量 | V20: 画 | W20: 製品ロット別単価マスタ | AF20: ロット | BV20: 製品ロット別単価マスタ | BW20: ロット別数量
C21: T | D21: 客先販売単価マスタ | K21: 通貨ＣＤ | AQ21: JPY | BW21: JPY
C22: T | D22: 客先販売単価マスタ | K22: ワーキンググループＣＤ | AQ22: 最終工程のWGを設定する | BV22: 製品ロット別単価マスタ | BW22: WG
C23: T | D23: 客先販売単価マスタ | K23: 適用開始日 | V23: 画 | W23: 製品ロット別単価マスタ | AF23: 適用開始日 | BV23: 製品ロット別単価マスタ | BW23: 適用日
C24: T | D24: 客先販売単価マスタ | K24: 会社ＣＤ | AQ24: 会社CD | BW24: 会社CD
C25: T | D25: 客先販売単価マスタ | K25: 適用終了日 | V25: 画 | W25: 製品ロット別単価マスタ | AF25: 適用終了日 | BW25: 73050
C26: T | D26: 客先販売単価マスタ | K26: 単価 | V26: 画 | W26: 製品ロット別単価マスタ | AF26: 単価 | BV26: 製品ロット別単価マスタ | BW26: ロット別単価
C27: T | D27: 客先販売単価マスタ | K27: 改定前単価 | AQ27: NULL | BW27: NULL
C28: T | D28: 客先販売単価マスタ | K28: 仮単価ＦＬＧ | BW28: 本単価
C29: T | D29: 客先販売単価マスタ | K29: 掛率（％） | AQ29: NULL | BV29: 製品ロット別単価マスタ | BW29: NULL
C30: T | D30: 客先販売単価マスタ | K30: 改定前掛率（％） | AQ30: NULL | BW30: NULL
C31: T | D31: 客先販売単価マスタ | K31: 予備単価１ | AQ31: NULL | BW31: NULL
C32: T | D32: 客先販売単価マスタ | K32: 予備単価２ | AQ32: NULL | BW32: NULL
C33: T | D33: 客先販売単価マスタ | K33: 予備単価３ | AQ33: NULL | BW33: NULL
C34: T | D34: 客先販売単価マスタ | K34: 原価対象外ＦＬＧ | AQ34: 1 | BW34: 1
C35: T | D35: 客先販売単価マスタ | K35: メモ１
C36: T | D36: 客先販売単価マスタ | K36: メモ２
C37: T | D37: 客先販売単価マスタ | K37: メモ３
C38: T | D38: 客先販売単価マスタ | K38: 論理削除ＦＬＧ | AQ38: 0 | BW38: 0
C39: T | D39: 客先販売単価マスタ | K39: 論理削除ユーザＩＤ | AQ39: NULL | BW39: NULL
C40: T | D40: 客先販売単価マスタ | K40: 論理削除ユーザ名 | AQ40: NULL | BW40: NULL
C41: T | D41: 客先販売単価マスタ | K41: 論理削除日時 | AQ41: NULL | BW41: NULL
C42: T | D42: 客先販売単価マスタ | K42: 登録ユーザＩＤ | AQ42: 登録ユーザー | BW42: 登録ユーザー
C43: T | D43: 客先販売単価マスタ | K43: 登録ユーザ名 | AQ43: 登録ユーザー名 | BW43: 登録ユーザー名
C44: T | D44: 客先販売単価マスタ | K44: 登録日時 | AQ44: 処理日時 | BW44: 処理日時
C45: T | D45: 客先販売単価マスタ | K45: 登録機能ＩＤ
C46: T | D46: 客先販売単価マスタ | K46: 更新カウンタ | AQ46: 0 | BW46: 0
C47: T | D47: 客先販売単価マスタ | K47: 更新ユーザＩＤ | AQ47: 登録ユーザー | BW47: 登録ユーザー
C48: T | D48: 客先販売単価マスタ | K48: 更新ユーザ名 | AQ48: 登録ユーザー名 | BW48: 登録ユーザー名
C49: T | D49: 客先販売単価マスタ | K49: 更新日時 | AQ49: 処理日時 | BW49: 処理日時
C50: T | D50: 客先販売単価マスタ | K50: 更新機能ＩＤ
C51: T | D51: 客先販売単価マスタ | K51: 更新リクエストＮＯ
A52: No | G52: 2 | H52: 客先販売単価マスタ_製品 | S52: ロジック名称 | AH52: 備考 | BT52: 品目区分別設定値
A53: 処理分類 | E53: 更新 | BP53: 商品 | BR53: 商品 | BT53: 商品 | BV53: 製品 | BZ53: 中間品 | CD53: 資材 | CF53: 資材 | CH53: 原料 | CJ53: その他
A54: No | C54: 転送先 | V54: 転送元 | AQ54: 説明 | BP54: 購買 | BR54: 購買 | BT54: 購買 | BV54: 内 | BX54: 外 | BZ54: 内 | CB54: 外 | CD54: 在庫管理品（カートン等） | CF54: 非在庫品 | CH54: 購買 | CJ54: 購買
C55: 種 | D55: オブジェクト | K55: 項目名 | V55: 種 | W55: オブジェクト | AF55: 項目名 | BP55: オブジェクト | BQ55: 項目名 | BR55: オブジェクト | BS55: 項目名 | BT55: オブジェクト | BU55: 項目名 | BV55: オブジェクト | BW55: 項目名 | BX55: オブジェクト | BY55: 項目名 | BZ55: オブジェクト | CA55: 項目名 | CB55: オブジェクト | CC55: 項目名 | CD55: オブジェクト | CE55: 項目名 | CF55: オブジェクト | CG55: 項目名 | CH55: オブジェクト | CI55: 項目名 | CJ55: オブジェクト | CK55: 項目名
C56: T | D56: 客先販売単価マスタ | K56: 適用終了日 | V56: 画 | W56: 製品ロット別単価マスタ | AF56: 適用終了日 | BV56: 製品ロット別単価マスタ | BW56: 適用予定日-1
C57: T | D57: 客先販売単価マスタ | K57: 更新カウンタ | AQ57: 0 | BW57: 自動
C58: T | D58: 客先販売単価マスタ | K58: 更新ユーザＩＤ | AQ58: 登録ユーザー | BW58: 登録ユーザー
C59: T | D59: 客先販売単価マスタ | K59: 更新ユーザ名 | AQ59: 登録ユーザー名 | BW59: 登録ユーザー名
C60: T | D60: 客先販売単価マスタ | K60: 更新日時 | AQ60: 処理日時 | BW60: 処理日時
C61: T | D61: 客先販売単価マスタ | K61: 更新機能ＩＤ
C62: T | D62: 客先販売単価マスタ | K62: 更新リクエストＮＯ
A63: No | G63: 3 | H63: 客先販売単価マスタ_製品 | S63: ロジック名称 | AH63: 備考 | BT63: 品目区分別設定値
A64: 処理分類 | E64: 登録（新単価） | BP64: 商品 | BR64: 商品 | BT64: 商品 | BV64: 製品 | BZ64: 中間品 | CD64: 資材 | CF64: 資材 | CH64: 原料 | CJ64: その他
A65: No | C65: 転送先 | V65: 転送元 | AQ65: 説明 | BP65: 購買 | BR65: 購買 | BT65: 購買 | BV65: 内 | BX65: 外 | BZ65: 内 | CB65: 外 | CD65: 在庫管理品（カートン等） | CF65: 非在庫品 | CH65: 購買 | CJ65: 購買
C66: 種 | D66: オブジェクト | K66: 項目名 | V66: 種 | W66: オブジェクト | AF66: 項目名 | BP66: オブジェクト | BQ66: 項目名 | BR66: オブジェクト | BS66: 項目名 | BT66: オブジェクト | BU66: 項目名 | BV66: オブジェクト | BW66: 項目名 | BX66: オブジェクト | BY66: 項目名 | BZ66: オブジェクト | CA66: 項目名 | CB66: オブジェクト | CC66: 項目名 | CD66: オブジェクト | CE66: 項目名 | CF66: オブジェクト | CG66: 項目名 | CH66: オブジェクト | CI66: 項目名 | CJ66: オブジェクト | CK66: 項目名
C67: T | D67: 客先販売単価マスタ | K67: 得意先ＣＤ | V67: 画 | W67: 製品ロット別単価マスタ | AF67: 得意先CD | BV67: 製品ロット別単価マスタ | BW67: 得意先CD
C68: T | D68: 客先販売単価マスタ | K68: 納品先ＣＤ | AQ68: NULL | BW68: NULL
C69: T | D69: 客先販売単価マスタ | K69: 仕向先ＣＤ１ | AQ69: NULL | BW69: NULL
C70: T | D70: 客先販売単価マスタ | K70: 仕向先ＣＤ２ | AQ70: NULL | BW70: NULL
C71: T | D71: 客先販売単価マスタ | K71: 仕向先ＣＤ３ | AQ71: NULL | BW71: NULL
C72: T | D72: 客先販売単価マスタ | K72: 販売単価分類ＣＤ | AQ72: NULL | BW72: NULL
C73: T | D73: 客先販売単価マスタ | K73: 品目ＣＤ | V73: T | W73: 品目マスタ | AF73: 品目CD | BV73: 品目マスタ（共通） | BW73: 品目ＣＤ
C74: T | D74: 客先販売単価マスタ | K74: 枝番１ | V74: T | W74: 品目マスタ | AF74: 枝番１ | BV74: 品目マスタ（共通） | BW74: 枝番１
C75: T | D75: 客先販売単価マスタ | K75: 枝番２ | V75: T | W75: 品目マスタ | AF75: 枝番２ | BV75: 品目マスタ（共通） | BW75: 枝番２
C76: T | D76: 客先販売単価マスタ | K76: 枝番３ | V76: T | W76: 品目マスタ | AF76: 枝番３ | BV76: 品目マスタ（共通） | BW76: 枝番３
C77: T | D77: 客先販売単価マスタ | K77: 単位ＣＤ | V77: T | W77: 品目マスタ | AF77: 単位CD | BV77: 品目マスタ（共通） | BW77: 単位CD
C78: T | D78: 客先販売単価マスタ | K78: ロット数量 | V78: 画 | W78: 製品ロット別単価マスタ | AF78: ロット | BV78: 製品ロット別単価マスタ | BW78: 新ロット別数量1~5
C79: T | D79: 客先販売単価マスタ | K79: 通貨ＣＤ | AQ79: JPY | BW79: JPY
C80: T | D80: 客先販売単価マスタ | K80: ワーキンググループＣＤ | AQ80: 最終工程のWGを設定する | BV80: 製品ロット別単価マスタ | BW80: WG
C81: T | D81: 客先販売単価マスタ | K81: 適用開始日 | V81: 画 | W81: 製品ロット別単価マスタ | AF81: 適用開始日 | BV81: 製品ロット別単価マスタ | BW81: 適用予定日
C82: T | D82: 客先販売単価マスタ | K82: 会社ＣＤ | AQ82: 会社CD | BW82: 会社CD
C83: T | D83: 客先販売単価マスタ | K83: 適用終了日 | V83: 画 | W83: 製品ロット別単価マスタ | AF83: 適用終了日 | BW83: 73050
C84: T | D84: 客先販売単価マスタ | K84: 単価 | V84: 画 | W84: 製品ロット別単価マスタ | AF84: 単価 | BV84: 製品ロット別単価マスタ | BW84: 新ロット別単価1~5
C85: T | D85: 客先販売単価マスタ | K85: 改定前単価 | AQ85: NULL | BW85: NULL
C86: T | D86: 客先販売単価マスタ | K86: 仮単価ＦＬＧ | V86: 画 | W86: 製品ロット別単価マスタ | AF86: 仮単価 | BW86: 本単価
C87: T | D87: 客先販売単価マスタ | K87: 掛率（％） | AQ87: NULL | BV87: 製品ロット別単価マスタ | BW87: NULL
C88: T | D88: 客先販売単価マスタ | K88: 改定前掛率（％） | AQ88: NULL | BW88: NULL
C89: T | D89: 客先販売単価マスタ | K89: 予備単価１ | AQ89: NULL | BW89: NULL
C90: T | D90: 客先販売単価マスタ | K90: 予備単価２ | AQ90: NULL | BW90: NULL
C91: T | D91: 客先販売単価マスタ | K91: 予備単価３ | AQ91: NULL | BW91: NULL
C92: T | D92: 客先販売単価マスタ | K92: 原価対象外ＦＬＧ | AQ92: 1 | BW92: 1
C93: T | D93: 客先販売単価マスタ | K93: メモ１
C94: T | D94: 客先販売単価マスタ | K94: メモ２
C95: T | D95: 客先販売単価マスタ | K95: メモ３
C96: T | D96: 客先販売単価マスタ | K96: 論理削除ＦＬＧ | AQ96: 0 | BW96: 0
C97: T | D97: 客先販売単価マスタ | K97: 論理削除ユーザＩＤ | AQ97: NULL | BW97: NULL
C98: T | D98: 客先販売単価マスタ | K98: 論理削除ユーザ名 | AQ98: NULL | BW98: NULL
C99: T | D99: 客先販売単価マスタ | K99: 論理削除日時 | AQ99: NULL | BW99: NULL
C100: T | D100: 客先販売単価マスタ | K100: 登録ユーザＩＤ | AQ100: 登録ユーザー | BW100: 登録ユーザー
C101: T | D101: 客先販売単価マスタ | K101: 登録ユーザ名 | AQ101: 登録ユーザー名 | BW101: 登録ユーザー名
...

Sheet 更新入出力仕様_（アドオン）本支店単価マスタ 
A1: =表紙!A54 -> Webシステム | K1: 文書名 | U1: モジュールID | Z1: =表紙!$AJ$63 -> MS | AE1: モジュール名 | AJ1: =表紙!$AX$63 -> 見積管理 | AS1: 文書番号 | AZ1: Version | BF1: Rev.
K2: =表紙!O64 -> アドオン設計書 | U2: ｻﾌﾞﾓｼﾞｭｰﾙID | Z2: =表紙!$AJ$64 -> MSBB | AE2: ｻﾌﾞﾓｼﾞｭｰﾙ名 | AJ2: =表紙!$AX$64 -> Webシステム | AS2: =表紙!$BL$64 -> M7-US-1140 | AZ2: =表紙!$BU$64 -> 7.0.2 | BF2: =表紙!$CB$64 -> 8
K3: =RIGHT(CELL("filename",$A$1),LEN(CELL("filename",$A$1))-FIND("]",CELL("filename",$A$1))) -> 更新入出力仕様_（アドオン）本支店単価マスタ | U3: 表題 | Z3: =表紙!$AJ$65 -> - | AE3: =表紙!$AQ$65 -> 製品マスタ連携
A5: No | G5: 1 | H5: （アドオン）本支店単価マスタ | S5: ロジック名称 | AH5: 備考 | BP5: 品目区分別設定値 | CM5: REV4.0 商品を概要と合わせる
A6: 処理分類 | E6: 登録 | BP6: 商品 | BV6: 製品 | BZ6: 中間品 | CD6: 資材 | CF6: 資材 | CH6: 原料 | CJ6: その他 | CM6: REV6.0 本支店単価マスタの連携廃止 | DA6: REV8.0 本支店単価マスタの復活
A7: No | C7: 転送先 | V7: 転送元 | AQ7: 説明 | BP7: 構成あり | BR7: 構成なし | BT7: 版型 | BV7: 内 | BX7: 外 | BZ7: 内 | CB7: 外 | CD7: 在庫管理品（カートン等） | CF7: 非在庫品 | CH7: 購買 | CJ7: 購買
C8: 種 | D8: オブジェクト | K8: 項目名 | V8: 種 | W8: オブジェクト | AF8: 項目名 | BP8: オブジェクト | BQ8: 項目名 | BR8: オブジェクト | BS8: 項目名 | BT8: オブジェクト | BU8: 項目名 | BV8: オブジェクト | BW8: 項目名 | BX8: オブジェクト | BY8: 項目名 | BZ8: オブジェクト | CA8: 項目名 | CB8: オブジェクト | CC8: 項目名 | CD8: オブジェクト | CE8: 項目名 | CF8: オブジェクト | CG8: 項目名 | CH8: オブジェクト | CI8: 項目名 | CJ8: オブジェクト | CK8: 項目名
C9: T | D9: （アドオン）本支店単価マスタ | K9: 得意先ＣＤ | V9: 画 | W9: 製品基本マスタ | AF9: 得意先CD | BV9: 製品ロット別単価マスタ | BW9: 得意先CD
C10: T | D10: （アドオン）本支店単価マスタ | K10: 品目ＣＤ | V10: T | W10: 品目マスタ | AF10: 品目CD | BV10: 品目マスタ（共通） | BW10: 品目ＣＤ
C11: T | D11: （アドオン）本支店単価マスタ | K11: 枝番１ | V11: T | W11: 品目マスタ | AF11: 枝番１ | BV11: 品目マスタ（共通） | BW11: 枝番１
C12: T | D12: （アドオン）本支店単価マスタ | K12: 枝番２ | V12: T | W12: 品目マスタ | AF12: 枝番２ | BV12: 品目マスタ（共通） | BW12: 枝番２
C13: T | D13: （アドオン）本支店単価マスタ | K13: 枝番３ | V13: T | W13: 品目マスタ | AF13: 枝番３ | BV13: 品目マスタ（共通） | BW13: 枝番３
C14: T | D14: （アドオン）本支店単価マスタ | K14: 単位ＣＤ | V14: T | W14: 品目マスタ | AF14: 単位CD | BV14: 品目マスタ（共通） | BW14: 単位CD
C15: T | D15: （アドオン）本支店単価マスタ | K15: ロット数量 | V15: 画 | W15: 製品基本マスタ | AF15: ロット | BV15: 製品ロット別単価マスタ | BW15: ロット別数量1~5
C16: T | D16: （アドオン）本支店単価マスタ | K16: 通貨ＣＤ | AQ16: JPY | BW16: JPY
C17: T | D17: （アドオン）本支店単価マスタ | K17: 適用開始日 | V17: 画 | W17: 製品基本マスタ | AF17: 適用開始日 | BW17: 処理日付
C18: T | D18: （アドオン）本支店単価マスタ | K18: 適用終了日 | V18: 画 | W18: 製品基本マスタ | AF18: 適用終了日 | BW18: 73050
C19: T | D19: （アドオン）本支店単価マスタ | K19: 単価 | V19: 画 | W19: 製品基本マスタ | AF19: 本支店単価 | BV19: 製品ロット別単価マスタ | BW19: 本支店単価１~５
C20: T | D20: （アドオン）本支店単価マスタ | K20: 仮単価ＦＬＧ | V20: 画 | W20: 製品基本マスタ | AF20: 仮単価 | BV20: 製品ロット別単価マスタ | BW20: 仮単価
C21: T | D21: （アドオン）本支店単価マスタ | K21: 原価対象外ＦＬＧ | AQ21: 1 | BW21: 1
C22: T | D22: （アドオン）本支店単価マスタ | K22: メモ１ | BW22: NULL
C23: T | D23: （アドオン）本支店単価マスタ | K23: メモ２ | BW23: NULL
C24: T | D24: （アドオン）本支店単価マスタ | K24: メモ３ | BW24: NULL
C25: T | D25: （アドオン）本支店単価マスタ | K25: 論理削除ＦＬＧ | AQ25: 0 | BW25: 0
C26: T | D26: （アドオン）本支店単価マスタ | K26: 論理削除ユーザＩＤ | AQ26: NULL | BW26: NULL
C27: T | D27: （アドオン）本支店単価マスタ | K27: 論理削除ユーザ名 | AQ27: NULL | BW27: NULL
C28: T | D28: （アドオン）本支店単価マスタ | K28: 論理削除日時 | AQ28: NULL | BW28: NULL
C29: T | D29: （アドオン）本支店単価マスタ | K29: 登録ユーザＩＤ | AQ29: 登録ユーザー | BW29: 登録ユーザー
C30: T | D30: （アドオン）本支店単価マスタ | K30: 登録ユーザ名 | AQ30: 登録ユーザー名 | BW30: 登録ユーザー名
C31: T | D31: （アドオン）本支店単価マスタ | K31: 登録日時 | AQ31: 処理日時 | BW31: 処理日時
C32: T | D32: （アドオン）本支店単価マスタ | K32: 登録機能ＩＤ
C33: T | D33: （アドオン）本支店単価マスタ | K33: 更新カウンタ | AQ33: 0 | BW33: 0
C34: T | D34: （アドオン）本支店単価マスタ | K34: 更新ユーザＩＤ | AQ34: 登録ユーザー | BW34: 登録ユーザー
C35: T | D35: （アドオン）本支店単価マスタ | K35: 更新ユーザ名 | AQ35: 登録ユーザー名 | BW35: 登録ユーザー名
C36: T | D36: （アドオン）本支店単価マスタ | K36: 更新日時 | AQ36: 処理日時 | BW36: 処理日時
C37: T | D37: （アドオン）本支店単価マスタ | K37: 更新機能ＩＤ
C38: T | D38: （アドオン）本支店単価マスタ | K38: 更新リクエストＮＯ
A39: No | G39: 2 | H39: （アドオン）本支店単価マスタ | S39: ロジック名称 | AH39: 備考 | BP39: 品目区分別設定値
A40: 処理分類 | E40: 更新 | BP40: 商品 | BV40: 製品 | BZ40: 中間品 | CD40: 資材 | CF40: 資材 | CH40: 原料 | CJ40: その他
A41: No | C41: 転送先 | V41: 転送元 | AQ41: 説明 | BP41: 構成あり | BR41: 構成なし | BT41: 版型 | BV41: 内 | BX41: 外 | BZ41: 内 | CB41: 外 | CD41: 在庫管理品（カートン等） | CF41: 非在庫品 | CH41: 購買 | CJ41: 購買
C42: 種 | D42: オブジェクト | K42: 項目名 | V42: 種 | W42: オブジェクト | AF42: 項目名 | BP42: オブジェクト | BQ42: 項目名 | BR42: オブジェクト | BS42: 項目名 | BT42: オブジェクト | BU42: 項目名 | BV42: オブジェクト | BW42: 項目名 | BX42: オブジェクト | BY42: 項目名 | BZ42: オブジェクト | CA42: 項目名 | CB42: オブジェクト | CC42: 項目名 | CD42: オブジェクト | CE42: 項目名 | CF42: オブジェクト | CG42: 項目名 | CH42: オブジェクト | CI42: 項目名 | CJ42: オブジェクト | CK42: 項目名
C43: T | D43: （アドオン）本支店単価マスタ | K43: 適用終了日 | V43: 画 | W43: 製品基本マスタ | AF43: 適用終了日 | BV43: 製品ロット別単価マスタ | BW43: 本支店適用予定日-1
C44: T | D44: （アドオン）本支店単価マスタ | K44: 更新カウンタ | AQ44: 0 | BW44: 自動
C45: T | D45: （アドオン）本支店単価マスタ | K45: 更新ユーザＩＤ | AQ45: 登録ユーザー | BW45: 登録ユーザー
C46: T | D46: （アドオン）本支店単価マスタ | K46: 更新ユーザ名 | AQ46: 登録ユーザー名 | BW46: 登録ユーザー名
C47: T | D47: （アドオン）本支店単価マスタ | K47: 更新日時 | AQ47: 処理日時 | BW47: 処理日時
C48: T | D48: （アドオン）本支店単価マスタ | K48: 更新機能ＩＤ
C49: T | D49: （アドオン）本支店単価マスタ | K49: 更新リクエストＮＯ
A50: No | G50: 3 | H50: （アドオン）本支店単価マスタ | S50: ロジック名称 | AH50: 備考 | BP50: 品目区分別設定値
A51: 処理分類 | E51: 登録（新単価） | BP51: 商品 | BV51: 製品 | BZ51: 中間品 | CD51: 資材 | CF51: 資材 | CH51: 原料 | CJ51: その他
A52: No | C52: 転送先 | V52: 転送元 | AQ52: 説明 | BP52: 構成あり | BR52: 構成なし | BT52: 版型 | BV52: 内 | BX52: 外 | BZ52: 内 | CB52: 外 | CD52: 在庫管理品（カートン等） | CF52: 非在庫品 | CH52: 購買 | CJ52: 購買
C53: 種 | D53: オブジェクト | K53: 項目名 | V53: 種 | W53: オブジェクト | AF53: 項目名 | BP53: オブジェクト | BQ53: 項目名 | BR53: オブジェクト | BS53: 項目名 | BT53: オブジェクト | BU53: 項目名 | BV53: オブジェクト | BW53: 項目名 | BX53: オブジェクト | BY53: 項目名 | BZ53: オブジェクト | CA53: 項目名 | CB53: オブジェクト | CC53: 項目名 | CD53: オブジェクト | CE53: 項目名 | CF53: オブジェクト | CG53: 項目名 | CH53: オブジェクト | CI53: 項目名 | CJ53: オブジェクト | CK53: 項目名
C54: T | D54: （アドオン）本支店単価マスタ | K54: 得意先ＣＤ | V54: 画 | W54: 製品基本マスタ | AF54: 得意先CD | BV54: 製品ロット別単価マスタ | BW54: 得意先CD
C55: T | D55: （アドオン）本支店単価マスタ | K55: 品目ＣＤ | V55: T | W55: 品目マスタ | AF55: 品目CD | BV55: 品目マスタ（共通） | BW55: 品目ＣＤ
C56: T | D56: （アドオン）本支店単価マスタ | K56: 枝番１ | V56: T | W56: 品目マスタ | AF56: 枝番１ | BV56: 品目マスタ（共通） | BW56: 枝番１
C57: T | D57: （アドオン）本支店単価マスタ | K57: 枝番２ | V57: T | W57: 品目マスタ | AF57: 枝番２ | BV57: 品目マスタ（共通） | BW57: 枝番２
C58: T | D58: （アドオン）本支店単価マスタ | K58: 枝番３ | V58: T | W58: 品目マスタ | AF58: 枝番３ | BV58: 品目マスタ（共通） | BW58: 枝番３
C59: T | D59: （アドオン）本支店単価マスタ | K59: 単位ＣＤ | V59: T | W59: 品目マスタ | AF59: 単位CD | BV59: 品目マスタ（共通） | BW59: 単位CD
C60: T | D60: （アドオン）本支店単価マスタ | K60: ロット数量 | V60: 画 | W60: 製品基本マスタ | AF60: ロット | BV60: 製品ロット別単価マスタ | BW60: ロット別数量1~5
C61: T | D61: （アドオン）本支店単価マスタ | K61: 通貨ＣＤ | AQ61: JPY | BW61: JPY
C62: T | D62: （アドオン）本支店単価マスタ | K62: 適用開始日 | V62: 画 | W62: 製品基本マスタ | AF62: 適用開始日 | BV62: 製品ロット別単価マスタ | BW62: 本支店適用予定日
C63: T | D63: （アドオン）本支店単価マスタ | K63: 適用終了日 | V63: 画 | W63: 製品基本マスタ | AF63: 適用終了日 | BW63: 73050
C64: T | D64: （アドオン）本支店単価マスタ | K64: 単価 | V64: 画 | W64: 製品基本マスタ | AF64: 本支店単価 | BV64: 製品ロット別単価マスタ | BW64: 新本支店単価１~５
C65: T | D65: （アドオン）本支店単価マスタ | K65: 仮単価ＦＬＧ | V65: 画 | W65: 製品基本マスタ | AF65: 仮単価 | BW65: 本単価
C66: T | D66: （アドオン）本支店単価マスタ | K66: 原価対象外ＦＬＧ | AQ66: 1 | BW66: 1
C67: T | D67: （アドオン）本支店単価マスタ | K67: メモ１ | BW67: NULL
C68: T | D68: （アドオン）本支店単価マスタ | K68: メモ２ | BW68: NULL
C69: T | D69: （アドオン）本支店単価マスタ | K69: メモ３ | BW69: NULL
C70: T | D70: （アドオン）本支店単価マスタ | K70: 論理削除ＦＬＧ | AQ70: 0 | BW70: 0
C71: T | D71: （アドオン）本支店単価マスタ | K71: 論理削除ユーザＩＤ | AQ71: NULL | BW71: NULL
C72: T | D72: （アドオン）本支店単価マスタ | K72: 論理削除ユーザ名 | AQ72: NULL | BW72: NULL
C73: T | D73: （アドオン）本支店単価マスタ | K73: 論理削除日時 | AQ73: NULL | BW73: NULL
C74: T | D74: （アドオン）本支店単価マスタ | K74: 登録ユーザＩＤ | AQ74: 登録ユーザー | BW74: 登録ユーザー
C75: T | D75: （アドオン）本支店単価マスタ | K75: 登録ユーザ名 | AQ75: 登録ユーザー名 | BW75: 登録ユーザー名
C76: T | D76: （アドオン）本支店単価マスタ | K76: 登録日時 | AQ76: 処理日時 | BW76: 処理日時
C77: T | D77: （アドオン）本支店単価マスタ | K77: 登録機能ＩＤ
C78: T | D78: （アドオン）本支店単価マスタ | K78: 更新カウンタ | AQ78: 0 | BW78: 0
C79: T | D79: （アドオン）本支店単価マスタ | K79: 更新ユーザＩＤ | AQ79: 登録ユーザー | BW79: 登録ユーザー
C80: T | D80: （アドオン）本支店単価マスタ | K80: 更新ユーザ名 | AQ80: 登録ユーザー名 | BW80: 登録ユーザー名
C81: T | D81: （アドオン）本支店単価マスタ | K81: 更新日時 | AQ81: 処理日時 | BW81: 処理日時
C82: T | D82: （アドオン）本支店単価マスタ | K82: 更新機能ＩＤ
C83: T | D83: （アドオン）本支店単価マスタ | K83: 更新リクエストＮＯ

Sheet 更新入出力仕様_購買単価マスタ 
A1: =表紙!A54 -> Webシステム | K1: 文書名 | U1: モジュールID | Z1: =表紙!$AJ$63 -> MS | AE1: モジュール名 | AJ1: =表紙!$AX$63 -> 見積管理 | AS1: 文書番号 | AZ1: Version | BF1: Rev.
K2: =表紙!O64 -> アドオン設計書 | U2: ｻﾌﾞﾓｼﾞｭｰﾙID | Z2: =表紙!$AJ$64 -> MSBB | AE2: ｻﾌﾞﾓｼﾞｭｰﾙ名 | AJ2: =表紙!$AX$64 -> Webシステム | AS2: =表紙!$BL$64 -> M7-US-1140 | AZ2: =表紙!$BU$64 -> 7.0.2 | BF2: =表紙!$CB$64 -> 8
K3: =RIGHT(CELL("filename",$A$1),LEN(CELL("filename",$A$1))-FIND("]",CELL("filename",$A$1))) -> 更新入出力仕様_購買単価マスタ | U3: 表題 | Z3: =表紙!$AJ$65 -> - | AE3: =表紙!$AQ$65 -> 製品マスタ連携
A5: No | G5: 1 | H5: 購買単価マスタ_製品 | S5: ロジック名称 | AH5: 備考 | BR5: 品目区分別設定値 | CP5: REV4.0 商品を概要と合わせる
A6: 処理分類 | E6: 登録 | BR6: 商品 | BX6: 製品 | CB6: 中間品 | CH6: 資材 | CJ6: 資材 | CL6: 原料 | CN6: その他
A7: No | C7: 転送先 | V7: 転送元 | AQ7: 説明 | BR7: 構成あり | BT7: 構成なし | BV7: 版型 | BX7: 内 | BZ7: 外 | CB7: 内 | CD7: 外 | CF7: 購買 | CH7: 在庫管理品（カートン等） | CJ7: 非在庫品 | CL7: 購買 | CN7: 購買
C8: 種 | D8: オブジェクト | K8: 項目名 | V8: 種 | W8: オブジェクト | AF8: 項目名 | BR8: オブジェクト | BS8: 項目名 | BT8: オブジェクト | BU8: 項目名 | BV8: オブジェクト | BW8: 項目名 | BX8: オブジェクト | BY8: 項目名 | BZ8: オブジェクト | CA8: 項目名 | CB8: オブジェクト | CC8: 項目名 | CD8: オブジェクト | CE8: 項目名 | CF8: オブジェクト | CG8: 項目名 | CH8: オブジェクト | CI8: 項目名 | CJ8: オブジェクト | CK8: 項目名 | CL8: オブジェクト | CM8: 項目名 | CN8: オブジェクト | CO8: 項目名
C9: T | D9: 購買単価マスタ | K9: 品目ＣＤ | V9: T | W9: 品目マスタ | AF9: 品目CD | CF9: 品目マスタ（共通） | CG9: 品目ＣＤ | CH9: 品目マスタ（共通） | CI9: 品目ＣＤ
C10: T | D10: 購買単価マスタ | K10: 枝番１ | V10: T | W10: 品目マスタ | AF10: 枝番１ | CF10: 品目マスタ（共通） | CG10: 枝番１ | CH10: 品目マスタ（共通） | CI10: 枝番１
C11: T | D11: 購買単価マスタ | K11: 枝番２ | V11: T | W11: 品目マスタ | AF11: 枝番２ | CF11: 品目マスタ（共通） | CG11: 枝番２ | CH11: 品目マスタ（共通） | CI11: 枝番２
C12: T | D12: 購買単価マスタ | K12: 枝番３ | V12: T | W12: 品目マスタ | AF12: 枝番３ | CF12: 品目マスタ（共通） | CG12: 枝番３ | CH12: 品目マスタ（共通） | CI12: 枝番３
C13: T | D13: 購買単価マスタ | K13: 発注先ＣＤ | V13: 画 | W13: 製品ロット別単価マスタ | AF13: 購買品の発注先 | CF13: 製品加工工程マスタ | CG13: 発注先 | CH13: 製品加工工程マスタ | CI13: 発注先
C14: T | D14: 購買単価マスタ | K14: メーカＣＤ | AQ14: NULL | CG14: NULL | CI14: NULL
C15: T | D15: 購買単価マスタ | K15: 単位ＣＤ | V15: 画 | W15: 製品ロット別単価マスタ | AF15: 単価単位 | CF15: 品目マスタ（共通） | CG15: 単位CD | CH15: 品目マスタ（共通） | CI15: 単位CD
C16: T | D16: 購買単価マスタ | K16: ロット数量 | V16: 画 | W16: 製品ロット別単価マスタ | AF16: ロット | CG16: 1 | CI16: 1
C17: T | D17: 購買単価マスタ | K17: 通貨ＣＤ | AQ17: JPY | CG17: JPY | CI17: JPY
C18: T | D18: 購買単価マスタ | K18: 納入場所ＣＤ | AQ18: NULL | CG18: NULL | CI18: NULL
C19: T | D19: 購買単価マスタ | K19: 納品先ＣＤ | AQ19: NULL | CG19: NULL | CI19: NULL
C20: T | D20: 購買単価マスタ | K20: ワーキンググループＣＤ | AQ20: NULL | CG20: NULL | CI20: NULL
C21: T | D21: 購買単価マスタ | K21: 適用開始日 | V21: 画 | W21: 製品ロット別単価マスタ | AF21: 適用開始日 | CG21: 単価適用日
C22: T | D22: 購買単価マスタ | K22: 会社ＣＤ | CG22: 固定：会社CD
C23: T | D23: 購買単価マスタ | K23: 適用終了日 | AQ23: 固定：2099/12/31 | CG23: 固定：2099/12/31 | CI23: 固定：2099/12/31
C24: T | D24: 購買単価マスタ | K24: 単価 | V24: 画 | W24: 製品ロット別単価マスタ | AF24: 仕入単価
C25: T | D25: 購買単価マスタ | K25: 改定前単価 | AQ25: NULL | CG25: NULL | CI25: NULL
C26: T | D26: 購買単価マスタ | K26: 仮単価ＦＬＧ | AQ26: 0 | CG26: 0 | CI26: 0
C27: T | D27: 購買単価マスタ | K27: 原価対象外ＦＬＧ | AQ27: 0 | CG27: 0 | CI27: 0
C28: T | D28: 購買単価マスタ | K28: 予備単価１ | AQ28: NULL | CG28: NULL | CI28: NULL
C29: T | D29: 購買単価マスタ | K29: 予備単価２ | AQ29: NULL | CG29: NULL | CI29: NULL
C30: T | D30: 購買単価マスタ | K30: 予備単価３ | AQ30: NULL | CG30: NULL | CI30: NULL
C31: T | D31: 購買単価マスタ | K31: メモ１ | AQ31: NULL | CG31: NULL | CI31: NULL
C32: T | D32: 購買単価マスタ | K32: メモ２ | AQ32: NULL | CG32: NULL | CI32: NULL
C33: T | D33: 購買単価マスタ | K33: メモ３ | AQ33: NULL | CG33: NULL | CI33: NULL
C34: T | D34: 購買単価マスタ | K34: 論理削除ＦＬＧ | AQ34: 0 | CG34: 0 | CI34: 0
C35: T | D35: 購買単価マスタ | K35: 論理削除ユーザＩＤ | AQ35: NULL | CG35: NULL | CI35: NULL
C36: T | D36: 購買単価マスタ | K36: 論理削除ユーザ名 | AQ36: NULL | CG36: NULL | CI36: NULL
... C40: T | D40: 購買単価マスタ | K40: 登録日時 | AQ40: 処理日時 | CG40: 処理日時 | CI40: 処理日時
C41: T | D41: 購買単価マスタ | K41: 登録機能ＩＤ
C42: T | D42: 購買単価マスタ | K42: 更新カウンタ | AQ42: 0 | CG42: 0 | CI42: 0
C43: T | D43: 購買単価マスタ | K43: 更新ユーザＩＤ | AQ43: 登録ユーザー | CG43: 登録ユーザー | CI43: 登録ユーザー
C44: T | D44: 購買単価マスタ | K44: 更新ユーザ名 | AQ44: 登録ユーザー名 | CG44: 登録ユーザー名 | CI44: 登録ユーザー名
C45: T | D45: 購買単価マスタ | K45: 更新日時 | AQ45: 処理日時 | CG45: 処理日時 | CI45: 処理日時
C46: T | D46: 購買単価マスタ | K46: 更新機能ＩＤ
C47: T | D47: 購買単価マスタ | K47: 更新リクエストＮＯ
A48: No | G48: 1 | H48: 購買単価マスタ_製品 | S48: ロジック名称 | AH48: 備考 | BR48: 品目区分別設定値
A49: 処理分類 | E49: 更新 | BR49: 商品 | BX49: 製品 | CB49: 中間品 | CH49: 資材 | CJ49: 資材 | CL49: 原料 | CN49: その他
A50: No | C50: 転送先 | V50: 転送元 | AQ50: 説明 | BR50: 構成あり | BT50: 構成なし | BV50: 版型 | BX50: 内 | BZ50: 外 | CB50: 内 | CD50: 外 | CF50: 購買 | CH50: 在庫管理品（カートン等） | CJ50: 非在庫品 | CL50: 購買 | CN50: 購買
C51: 種 | D51: オブジェクト | K51: 項目名 | V51: 種 | W51: オブジェクト | AF51: 項目名 | BR51: オブジェクト | BS51: 項目名 | BT51: オブジェクト | BU51: 項目名 | BV51: オブジェクト | BW51: 項目名 | BX51: オブジェクト | BY51: 項目名 | BZ51: オブジェクト | CA51: 項目名 | CB51: オブジェクト | CC51: 項目名 | CD51: オブジェクト | CE51: 項目名 | CF51: オブジェクト | CG51: 項目名 | CH51: オブジェクト | CI51: 項目名 | CJ51: オブジェクト | CK51: 項目名 | CL51: オブジェクト | CM51: 項目名 | CN51: オブジェクト | CO51: 項目名
C52: T | D52: 購買単価マスタ | K52: 適用終了日 | AQ52: 固定：2099/12/31 | CG52: 処理日-1 | CI52: 処理日-1
C53: T | D53: 購買単価マスタ | K53: 更新カウンタ | AQ53: 0 | CG53: 0 | CI53: 0
C54: T | D54: 購買単価マスタ | K54: 更新ユーザＩＤ | AQ54: 登録ユーザー | CG54: 登録ユーザー | CI54: 登録ユーザー
C55: T | D55: 購買単価マスタ | K55: 更新ユーザ名 | AQ55: 登録ユーザー名 | CG55: 登録ユーザー名 | CI55: 登録ユーザー名
C56: T | D56: 購買単価マスタ | K56: 更新日時 | AQ56: 処理日時 | CG56: 処理日時 | CI56: 処理日時
C57: T | D57: 購買単価マスタ | K57: 更新機能ＩＤ
C58: T | D58: 購買単価マスタ | K58: 更新リクエストＮＯ
A59: No | G59: 1 | H59: 購買単価マスタ_製品 | S59: ロジック名称 | AH59: 備考 | BR59: 品目区分別設定値
A60: 処理分類 | E60: 登録 | BR60: 商品 | BX60: 製品 | CB60: 中間品 | CH60: 資材 | CJ60: 資材 | CL60: 原料 | CN60: その他
A61: No | C61: 転送先 | V61: 転送元 | AQ61: 説明 | BR61: 構成あり | BT61: 構成なし | BV61: 版型 | BX61: 内 | BZ61: 外 | CB61: 内 | CD61: 外 | CF61: 購買 | CH61: 在庫管理品（カートン等） | CJ61: 非在庫品 | CL61: 購買 | CN61: 購買
C62: 種 | D62: オブジェクト | K62: 項目名 | V62: 種 | W62: オブジェクト | AF62: 項目名 | BR62: オブジェクト | BS62: 項目名 | BT62: オブジェクト | BU62: 項目名 | BV62: オブジェクト | BW62: 項目名 | BX62: オブジェクト | BY62: 項目名 | BZ62: オブジェクト | CA62: 項目名 | CB62: オブジェクト | CC62: 項目名 | CD62: オブジェクト | CE62: 項目名 | CF62: オブジェクト | CG62: 項目名 | CH62: オブジェクト | CI62: 項目名 | CJ62: オブジェクト | CK62: 項目名 | CL62: オブジェクト | CM62: 項目名 | CN62: オブジェクト | CO62: 項目名
C63: T | D63: 購買単価マスタ | K63: 品目ＣＤ | V63: T | W63: 品目マスタ | AF63: 品目CD | CF63: 品目マスタ（共通） | CG63: 品目ＣＤ | CH63: 品目マスタ（共通） | CI63: 品目ＣＤ
C64: T | D64: 購買単価マスタ | K64: 枝番１ | V64: T | W64: 品目マスタ | AF64: 枝番１ | CF64: 品目マスタ（共通） | CG64: 枝番１ | CH64: 品目マスタ（共通） | CI64: 枝番１
C65: T | D65: 購買単価マスタ | K65: 枝番２ | V65: T | W65: 品目マスタ | AF65: 枝番２ | CF65: 品目マスタ（共通） | CG65: 枝番２ | CH65: 品目マスタ（共通） | CI65: 枝番２
C66: T | D66: 購買単価マスタ | K66: 枝番３ | V66: T | W66: 品目マスタ | AF66: 枝番３ | CF66: 品目マスタ（共通） | CG66: 枝番３ | CH66: 品目マスタ（共通） | CI66: 枝番３
C67: T | D67: 購買単価マスタ | K67: 発注先ＣＤ | V67: 画 | W67: 製品ロット別単価マスタ | AF67: 購買品の発注先 | CF67: 製品加工工程マスタ | CG67: 発注先 | CH67: 製品加工工程マスタ | CI67: 発注先
C68: T | D68: 購買単価マスタ | K68: メーカＣＤ | AQ68: NULL | CG68: NULL | CI68: NULL
C69: T | D69: 購買単価マスタ | K69: 単位ＣＤ | V69: 画 | W69: 製品ロット別単価マスタ | AF69: 単価単位 | CF69: 品目マスタ（共通） | CG69: 単位CD | CH69: 品目マスタ（共通） | CI69: 単位CD
C70: T | D70: 購買単価マスタ | K70: ロット数量 | V70: 画 | W70: 製品ロット別単価マスタ | AF70: ロット | CG70: 1 | CI70: 1
C71: T | D71: 購買単価マスタ | K71: 通貨ＣＤ | AQ71: JPY | CG71: JPY | CI71: JPY
C72: T | D72: 購買単価マスタ | K72: 納入場所ＣＤ | AQ72: NULL | CG72: NULL | CI72: NULL
C73: T | D73: 購買単価マスタ | K73: 納品先ＣＤ | AQ73: NULL | CG73: NULL | CI73: NULL
C74: T | D74: 購買単価マスタ | K74: ワーキンググループＣＤ | AQ74: NULL | CG74: NULL | CI74: NULL
C75: T | D75: 購買単価マスタ | K75: 適用開始日 | V75: 画 | W75: 製品ロット別単価マスタ | AF75: 適用開始日 | CG75: 処理日 | CI75: 処理日
C76: T | D76: 購買単価マスタ | K76: 会社ＣＤ | CG76: 固定：会社CD | CI76: 固定：会社CD
C77: T | D77: 購買単価マスタ | K77: 適用終了日 | AQ77: 固定：2099/12/31 | CG77: 固定：2099/12/31 | CI77: 固定：2099/12/31
C78: T | D78: 購買単価マスタ | K78: 単価 | V78: 画 | W78: 製品ロット別単価マスタ | AF78: 仕入単価 | CF78: 製品加工工程マスタ | CG78: 仕入単価 | CH78: 製品加工工程マスタ | CI78: 仕入単価
C79: T | D79: 購買単価マスタ | K79: 改定前単価 | AQ79: NULL | CG79: NULL | CI79: NULL
C80: T | D80: 購買単価マスタ | K80: 仮単価ＦＬＧ | AQ80: 0 | CG80: 0 | CI80: 0
C81: T | D81: 購買単価マスタ | K81: 原価対象外ＦＬＧ | AQ81: 0 | CG81: 0 | CI81: 0
C82: T | D82: 購買単価マスタ | K82: 予備単価１ | AQ82: NULL | CG82: NULL | CI82: NULL
C83: T | D83: 購買単価マスタ | K83: 予備単価２ | AQ83: NULL | CG83: NULL | CI83: NULL
C84: T | D84: 購買単価マスタ | K84: 予備単価３ | AQ84: NULL | CG84: NULL | CI84: NULL
C85: T | D85: 購買単価マスタ | K85: メモ１ | AQ85: NULL | CG85: NULL | CI85: NULL
C86: T | D86: 購買単価マスタ | K86: メモ２ | AQ86: NULL | CG86: NULL | CI86: NULL
C87: T | D87: 購買単価マスタ | K87: メモ３ | AQ87: NULL | CG87: NULL | CI87: NULL
C88: T | D88: 購買単価マスタ | K88: 論理削除ＦＬＧ | AQ88: 0 | CG88: 0 | CI88: 0
C89: T | D89: 購買単価マスタ | K89: 論理削除ユーザＩＤ | AQ89: NULL | CG89: NULL | CI89: NULL
C90: T | D90: 購買単価マスタ | K90: 論理削除ユーザ名 | AQ90: NULL | CG90: NULL | CI90: NULL
... C94: T | D94: 購買単価マスタ | K94: 登録日時 | AQ94: 処理日時 | CG94: 処理日時 | CI94: 処理日時
C95: T | D95: 購買単価マスタ | K95: 登録機能ＩＤ
C96: T | D96: 購買単価マスタ | K96: 更新カウンタ | AQ96: 0 | CG96: 0 | CI96: 0
C97: T | D97: 購買単価マスタ | K97: 更新ユーザＩＤ | AQ97: 登録ユーザー | CG97: 登録ユーザー | CI97: 登録ユーザー
C98: T | D98: 購買単価マスタ | K98: 更新ユーザ名 | AQ98: 登録ユーザー名 | CG98: 登録ユーザー名 | CI98: 登録ユーザー名
C99: T | D99: 購買単価マスタ | K99: 更新日時 | AQ99: 処理日時 | CG99: 処理日時 | CI99: 処理日時
C100: T | D100: 購買単価マスタ | K100: 更新機能ＩＤ
C101: T | D101: 購買単価マスタ | K101: 更新リクエストＮＯ

Sheet 更新入出力仕様_BOMマスタ
A1: =表紙!A54 -> Webシステム | K1: 文書名 | U1: モジュールID | Z1: =表紙!$AJ$63 -> MS | AE1: モジュール名 | AJ1: =表紙!$AX$63 -> 見積管理 | AS1: 文書番号 | AZ1: Version | BF1: Rev.
K2: =表紙!O64 -> アドオン設計書 | U2: ｻﾌﾞﾓｼﾞｭｰﾙID | Z2: =表紙!$AJ$64 -> MSBB | AE2: ｻﾌﾞﾓｼﾞｭｰﾙ名 | AJ2: =表紙!$AX$64 -> Webシステム | AS2: =表紙!$BL$64 -> M7-US-1140 | AZ2: =表紙!$BU$64 -> 7.0.2 | BF2: =表紙!$CB$64 -> 8
K3: =RIGHT(CELL("filename",$A$1),LEN(CELL("filename",$A$1))-FIND("]",CELL("filename",$A$1))) -> 更新入出力仕様_BOMマスタ | U3: 表題 | Z3: =表紙!$AJ$65 -> - | AE3: =表紙!$AQ$65 -> 製品マスタ連携
A5: No | G5: 1 | H5: BOMマスタ | S5: ロジック名称 | AH5: 備考 | BP5: 品目区分別設定値 | CP5: 通常パタン （前工程仕掛品を投入して、加工） | CR5: 連産品（N丁取り） | CT5: 複数仕掛品を投入 （タンデム） | CV5: 購入品（都度採番）手配対象 | CX5: 外注品（都度採番）手配対象 ※有償/無償支給 | CZ5: 外注品（都度採番）手配対象 ※自給品（無償支給）（材料・仕入の支払い分割） | DB5: 消耗品（在庫管理対象外）手配対象 | DD5: 共通品目（発注点発注）を投入 | DF5: 共通品目（MRP発注）を投入 | DH5: REV4.0 商品を概要と合わせる
A6: 処理分類 | E6: 登録 | BP6: 商品 | BV6: 製品 | BZ6: 中間品 | CF6: 資材 | CH6: 資材 | CJ6: 原料 | CL6: その他
A7: No | C7: 転送先 | V7: 転送元 | AQ7: 説明 | BP7: 構成あり | BR7: 構成なし | BT7: 版型 | BV7: 内 | BX7: 外 | BZ7: 内 | CB7: 外 | CD7: 購買 | CF7: 在庫管理品（カートン等） | CH7: 非在庫品 | CJ7: 購買 | CL7: 購買
C8: 種 | D8: オブジェクト | K8: 項目名 | V8: 種 | W8: オブジェクト | AF8: 項目名 | BP8: オブジェクト | BQ8: 項目名 | BR8: オブジェクト | BS8: 項目名 | BT8: オブジェクト | BU8: 項目名 | BV8: オブジェクト | BW8: 項目名 | BX8: オブジェクト | BY8: 項目名 | BZ8: オブジェクト | CA8: 項目名 | CB8: オブジェクト | CC8: 項目名 | CD8: オブジェクト | CE8: 項目名 | CF8: オブジェクト | CG8: 項目名 | CH8: オブジェクト | CI8: 項目名 | CJ8: オブジェクト | CK8: 項目名 | CL8: オブジェクト | CM8: 項目名 | CP8: オブジェクト | CQ8: 項目名 | CR8: オブジェクト | CS8: 項目名 | CT8: オブジェクト | CU8: 項目名 | CV8: オブジェクト | CW8: 項目名 | CX8: オブジェクト | CY8: 項目名 | CZ8: オブジェクト | DA8: 項目名 | DB8: オブジェクト | DC8: 項目名 | DD8: オブジェクト | DE8: 項目名 | DF8: オブジェクト | DG8: 項目名
C9: T | D9: BOMマスタ | K9: ＢＯＭキー | AQ9: 自動採番 | BW9: 自動採番 | CQ9: 自動採番 | CS9: 自動採番 | CU9: 自動採番 | CW9: 自動採番 | CY9: 自動採番 | DA9: 自動採番 | DC9: 自動採番 | DE9: 自動採番 | DG9: 自動採番
C10: T | D10: BOMマスタ | K10: 会社ＣＤ | AQ10: 固定：会社CD | BW10: 固定：会社CD | CQ10: 固定：会社CD | CS10: 固定：会社CD | CU10: 固定：会社CD | CW10: 固定：会社CD | CY10: 固定：会社CD | DA10: 固定：会社CD | DC10: 固定：会社CD | DE10: 固定：会社CD | DG10: 固定：会社CD
C11: T | D11: BOMマスタ | K11: ワーキンググループＣＤ | AQ11: 加工工程マスタの号機/発注先からワーキンググループ | BV11: 加工工程マスタ | BW11: WG | CP11: 製品加工工程マスタ | CQ11: WG | CR11: 製品加工工程マスタ | CS11: WG | CT11: 加工工程マスタ | CU11: WG | CV11: 製品加工工程マスタ | CW11: WG | CX11: 製品加工工程マスタ | CY11: WG | CZ11: 製品加工工程マスタ | DA11: WG | DB11: 製品加工工程マスタ | DC11: WG | DD11: 製品加工工程マスタ | DE11: WG | DF11: 製品加工工程マスタ | DG11: WG
C12: T | D12: BOMマスタ | K12: 親品目ＣＤ | V12: T | W12: 品目マスタ | AF12: 品目CD | AQ12: 次工程CDに対応する品目CD | BV12: 品目マスタ（共通） | BW12: 品目CD | CP12: 品目マスタ（共通） | CQ12: 品目CD ※工程から設定 | CR12: 品目マスタ（共通） | CS12: 品目CD ※工程から設定 | CT12: 品目マスタ（共通） | CU12: 品目CD | CV12: 品目マスタ（共通） | CW12: 品目CD ※工程から設定 | CX12: 品目マスタ（共通） | CY12: 品目CD ※工程から設定 | CZ12: 品目マスタ（共通） | DA12: 品目CD ※工程から設定 | DB12: 品目マスタ（共通） | DC12: 品目CD ※工程から設定 | DD12: 品目マスタ（共通） | DE12: 品目CD ※工程から設定 | DF12: 品目マスタ（共通） | DG12: 品目CD ※工程から設定
C13: T | D13: BOMマスタ | K13: 親枝番１ | V13: T | W13: 品目マスタ | AF13: 枝番１ | AQ13: 次工程CDに対応する品目枝番１ | BV13: 品目マスタ（共通） | BW13: 枝番１ | CP13: 品目マスタ（共通） | CQ13: 枝番１ | CR13: 品目マスタ（共通） | CS13: 枝番１ | CT13: 品目マスタ（共通） | CU13: 枝番１ | CV13: 品目マスタ（共通） | CW13: 枝番１ | CX13: 品目マスタ（共通） | CY13: 枝番１ | CZ13: 品目マスタ（共通） | DA13: 枝番１ | DB13: 品目マスタ（共通） | DC13: 枝番１ | DD13: 品目マスタ（共通） | DE13: 枝番１ | DF13: 品目マスタ（共通） | DG13: 枝番１
C14: T | D14: BOMマスタ | K14: 親枝番２ | V14: T | W14: 品目マスタ | AF14: 枝番２ | AQ14: 次工程CDに対応する品目枝番２ | BV14: 品目マスタ（共通） | BW14: 枝番２ | CP14: 品目マスタ（共通） | CQ14: 枝番２ | CR14: 品目マスタ（共通） | CS14: 枝番２ | CT14: 品目マスタ（共通） | CU14: 枝番２ | CV14: 品目マスタ（共通） | CW14: 枝番２ | CX14: 品目マスタ（共通） | CY14: 枝番２ | CZ14: 品目マスタ（共通） | DA14: 枝番２ | DB14: 品目マスタ（共通） | DC14: 枝番２ | DD14: 品目マスタ（共通） | DE14: 枝番２ | DF14: 品目マスタ（共通） | DG14: 枝番２
C15: T | D15: BOMマスタ | K15: 親枝番３ | V15: T | W15: 品目マスタ | AF15: 枝番３ | AQ15: 次工程CDに対応する品目枝番３ | BV15: 品目マスタ（共通） | BW15: 枝番３ | CP15: 品目マスタ（共通） | CQ15: 枝番３ | CR15: 品目マスタ（共通） | CS15: 枝番３ | CT15: 品目マスタ（共通） | CU15: 枝番３ | CV15: 品目マスタ（共通） | CW15: 枝番３ | CX15: 品目マスタ（共通） | CY15: 枝番３ | CZ15: 品目マスタ（共通） | DA15: 枝番３ | DB15: 品目マスタ（共通） | DC15: 枝番３ | DD15: 品目マスタ（共通） | DE15: 枝番３ | DF15: 品目マスタ（共通） | DG15: 枝番３
C16: T | D16: BOMマスタ | K16: 構成パタン | AQ16: 固定：1 | BW16: 固定：1 | CQ16: 固定：1 | CS16: 固定：1 | CU16: 固定：1 | CW16: 固定：1 | CY16: 固定：1 | DA16: 固定：1 | DC16: 固定：1 | DE16: 固定：1 | DG16: 固定：1
C17: T | D17: BOMマスタ | K17: 工程ＣＤ | V17: 画 | W17: 加工工程マスタ | AF17: 作業工程CD | AQ17: 親工程CDの作業CD | BV17: 加工工程マスタ | BW17: 作業CD | CP17: 製品加工工程マスタ | CQ17: 作業CD | CR17: 製品加工工程マスタ | CS17: 作業CD | CT17: 加工工程マスタ | CU17: 作業CD | CV17: 製品加工工程マスタ | CW17: 作業CD | CX17: 製品加工工程マスタ | CY17: 作業CD | CZ17: 製品加工工程マスタ | DA17: 作業CD | DB17: 製品加工工程マスタ | DC17: 作業CD | DD17: 製品加工工程マスタ | DE17: 作業CD | DF17: 製品加工工程マスタ | DG17: 作業CD
C18: T | D18: BOMマスタ | K18: 工程連番 | V18: 画 | W18: 加工工程マスタ | AF18: 作業順 | AQ18: 親工程CDの作業順 | BV18: 加工工程マスタ | BW18: 作業順 | CP18: 製品加工工程マスタ | CQ18: 作業順 | CR18: 製品加工工程マスタ | CS18: 作業順 | CT18: 加工工程マスタ | CU18: 作業順 | CV18: 製品加工工程マスタ | CW18: 作業順 | CX18: 製品加工工程マスタ | CY18: 作業順 | CZ18: 製品加工工程マスタ | DA18: 作業順 | DB18: 製品加工工程マスタ | DC18: 作業順 | DD18: 製品加工工程マスタ | DE18: 作業順 | DF18: 製品加工工程マスタ | DG18: 作業順
C19: T | D19: BOMマスタ | K19: 子品目ＣＤ | V19: T | W19: 品目マスタ | AF19: 品目CD | AQ19: 製品基本マスタ 使用材料に対応する品目CD | BV19: 品目マスタ（共通） | BW19: 品目CD | CP19: 品目マスタ（共通） | CQ19: 品目CD ※材料から設定 | CR19: 品目マスタ（共通） | CS19: 品目CD ※材料から設定 | CT19: 品目マスタ（共通） | CU19: 品目CD | CV19: 品目マスタ（共通） | CW19: 品目CD ※材料から設定 | CX19: 品目マスタ（共通） | CY19: 品目CD ※材料から設定 | CZ19: 品目マスタ（共通） | DA19: 品目CD ※材料から設定 | DB19: 品目マスタ（共通） | DC19: 品目CD ※材料から設定 | DD19: 品目マスタ（共通） | DE19: 品目CD ※材料から設定 | DF19: 品目マスタ（共通） | DG19: 品目CD ※材料から設定
C20: T | D20: BOMマスタ | K20: 子枝番１ | V20: T | W20: 品目マスタ | AF20: 枝番１ | AQ20: 製品基本マスタ 使用材料に対応する品目枝番１ | BV20: 品目マスタ（共通） | BW20: 枝番１ | CP20: 品目マスタ（共通） | CQ20: 枝番１ | CR20: 品目マスタ（共通） | CS20: 枝番１ | CT20: 品目マスタ（共通） | CU20: 枝番１ | CV20: 品目マスタ（共通） | CW20: 枝番１ | CX20: 品目マスタ（共通） | CY20: 枝番１ | CZ20: 品目マスタ（共通） | DA20: 枝番１ | DB20: 品目マスタ（共通） | DC20: 枝番１ | DD20: 品目マスタ（共通） | DE20: 枝番１ | DF20: 品目マスタ（共通） | DG20: 枝番１
C21: T | D21: BOMマスタ | K21: 子枝番２ | V21: T | W21: 品目マスタ | AF21: 枝番２ | AQ21: 製品基本マスタ 使用材料に対応する品目枝番２ | BV21: 品目マスタ（共通） | BW21: 枝番２ | CP21: 品目マスタ（共通） | CQ21: 枝番２ | CR21: 品目マスタ（共通） | CS21: 枝番２ | CT21: 品目マスタ（共通） | CU21: 枝番２ | CV21: 品目マスタ（共通） | CW21: 枝番２ | CX21: 品目マスタ（共通） | CY21: 枝番２ | CZ21: 品目マスタ（共通） | DA21: 枝番２ | DB21: 品目マスタ（共通） | DC21: 枝番２ | DD21: 品目マスタ（共通） | DE21: 枝番２ | DF21: 品目マスタ（共通） | DG21: 枝番２
C22: T | D22: BOMマスタ | K22: 子枝番３ | V22: T | W22: 品目マスタ | AF22: 枝番３ | AQ22: 製品基本マスタ 使用材料に対応する品目枝番３ | BV22: 品目マスタ（共通） | BW22: 枝番３ | CP22: 品目マスタ（共通） | CQ22: 枝番３ | CR22: 品目マスタ（共通） | CS22: 枝番３ | CT22: 品目マスタ（共通） | CU22: 枝番３ | CV22: 品目マスタ（共通） | CW22: 枝番３ | CX22: 品目マスタ（共通） | CY22: 枝番３ | CZ22: 品目マスタ（共通） | DA22: 枝番３ | DB22: 品目マスタ（共通） | DC22: 枝番３ | DD22: 品目マスタ（共通） | DE22: 枝番３ | DF22: 品目マスタ（共通） | DG22: 枝番３
C23: T | D23: BOMマスタ | K23: 版ＮＯ | AQ23: 固定：NULL | BW23: 固定：NULL | CQ23: 固定：NULL | CS23: 固定：NULL | CU23: 固定：NULL | CW23: 固定：NULL | CY23: 固定：NULL | DA23: 固定：NULL | DC23: 固定：NULL | DE23: 固定：NULL | DG23: 固定：NULL
C24: T | D24: BOMマスタ | K24: 架空ＦＬＧ | AQ24: 固定：NULL | BW24: 固定：NULL | CQ24: 固定：NULL | CS24: 固定：NULL | CU24: 固定：NULL | CW24: 固定：NULL | CY24: 固定：NULL | DA24: 固定：NULL | DC24: 固定：NULL | DE24: 固定：NULL | DG24: 固定：NULL
C25: T | D25: BOMマスタ | K25: 架空構成パタン | AQ25: 固定：NULL | BW25: 固定：NULL | CQ25: 固定：NULL | CS25: 固定：NULL | CU25: 固定：NULL | CW25: 固定：NULL | CY25: 固定：NULL | DA25: 固定：NULL | DC25: 固定：NULL | DE25: 固定：NULL | DG25: 固定：NULL
C26: T | D26: BOMマスタ | K26: 代替品目ＦＬＧ | AQ26: 固定：NULL | BW26: 固定：NULL | CQ26: 固定：NULL | CS26: 固定：NULL | CU26: 固定：NULL | CW26: 固定：NULL | CY26: 固定：NULL | DA26: 固定：NULL | DC26: 固定：NULL | DE26: 固定：NULL | DG26: 固定：NULL
C27: T | D27: BOMマスタ | K27: 代替グループＣＤ | AQ27: 固定：NULL | BW27: 固定：NULL | CQ27: 固定：NULL | CS27: 固定：NULL | CU27: 固定：NULL | CW27: 固定：NULL | CY27: 固定：NULL | DA27: 固定：NULL | DC27: 固定：NULL | DE27: 固定：NULL | DG27: 固定：NULL
C28: T | D28: BOMマスタ | K28: 代替品目選択区分 | AQ28: 固定：NULL | BW28: 固定：NULL | CQ28: 固定：NULL | CS28: 固定：NULL | CU28: 固定：NULL | CW28: 固定：NULL | CY28: 固定：NULL | DA28: 固定：NULL | DC28: 固定：NULL | DE28: 固定：NULL | DG28: 固定：NULL
C29: T | D29: BOMマスタ | K29: 代替品目比率 | AQ29: 固定：NULL | BW29: 固定：NULL | CQ29: 固定：NULL | CS29: 固定：NULL | CU29: 固定：NULL | CW29: 固定：NULL | CY29: 固定：NULL | DA29: 固定：NULL | DC29: 固定：NULL | DE29: 固定：NULL | DG29: 固定：NULL
C30: T | D30: BOMマスタ | K30: 引当優先順 | AQ30: 固定：NULL | BW30: 固定：NULL | CQ30: 固定：NULL | CS30: 固定：NULL | CU30: 固定：NULL | CW30: 固定：NULL | CY30: 固定：NULL | DA30: 固定：NULL | DC30: 固定：NULL | DE30: 固定：NULL | DG30: 固定：NULL
C31: T | D31: BOMマスタ | K31: 手配ＮＯ１区分 | AQ31: 1：展開 2：展開しない 3：展開(無し可) 原紙：２：展開しない ※顧客支給品だったら原紙でも２：展開しない それ以外：３：展開（無し可） コートボール：３：展開（無し可） | BW31: 1：展開 2：展開しない 3：展開(無し可) 原紙：２：展開しない ※顧客支給品だったら原紙でも２：展開しない それ以外：３：展開（無し可） コートボール：３：展開（無し可） | CQ31: 1：展開 2：展開しない 3：展開(無し可) 原紙：２：展開しない ※顧客支給品だったら原紙でも２：展開しない それ以外：３：展開（無し可） コートボール：３：展開（無し可） | CS31: 1：展開 2：展開しない 3：展開(無し可) 原紙：２：展開しない ※顧客支給品だったら原紙でも２：展開しない それ以外：３：展開（無し可） コートボール：３：展開（無し可） | CU31: 1：展開 2：展開しない 3：展開(無し可) 原紙：２：展開しない ※顧客支給品だったら原紙でも２：展開しない それ以外：３：展開（無し可） コートボール：３：展開（無し可） | CW31: 1：展開 2：展開しない 3：展開(無し可) 原紙：２：展開しない ※顧客支給品だったら原紙でも２：展開しない それ以外：３：展開（無し可） コートボール：３：展開（無し可） | CY31: 1：展開 2：展開しない 3：展開(無し可) 原紙：２：展開しない ※顧客支給品だったら原紙でも２：展開しない それ以外：３：展開（無し可） コートボール：３：展開（無し可） | DA31: 1：展開 2：展開しない 3：展開(無し可) 原紙：２：展開しない ※顧客支給品だったら原紙でも２：展開しない それ以外：３：展開（無し可） コートボール：３：展開（無し可） | DC31: 1：展開 2：展開しない 3：展開(無し可) 原紙：２：展開しない ※顧客支給品だったら原紙でも２：展開しない それ以外：３：展開（無し可） コートボール：３：展開（無し可） | DE31: 1：展開 2：展開しない 3：展開(無し可) 原紙：２：展開しない ※顧客支給品だったら原紙でも２：展開しない それ以外：３：展開（無し可） コートボール：３：展開（無し可） | DG31: 1：展開 2：展開しない 3：展開(無し可) 原紙：２：展開しない ※顧客支給品だったら原紙でも２：展開しない それ以外：３：展開（無し可） コートボール：３：展開（無し可）
C32: T | D32: BOMマスタ | K32: 手配ＮＯ２区分 | AQ32: 1：展開 2：展開しない 3：展開(無し可) 原紙：２：展開しない ※顧客支給品だったら原紙でも２：展開しない それ以外：３：展開（無し可） コートボール：３：展開（無し可） | BW32: 1：展開 2：展開しない 3：展開(無し可) 原紙：２：展開しない ※顧客支給品だったら原紙でも２：展開しない それ以外：３：展開（無し可） コートボール：３：展開（無し可） | CQ32: 1：展開 2：展開しない 3：展開(無し可) 原紙：２：展開しない ※顧客支給品だったら原紙でも２：展開しない それ以外：３：展開（無し可） コートボール：３：展開（無し可） | CS32: 1：展開 2：展開しない 3：展開(無し可) 原紙：２：展開しない ※顧客支給品だったら原紙でも２：展開しない それ以外：３：展開（無し可） コートボール：３：展開（無し可） | CU32: 1：展開 2：展開しない 3：展開(無し可) 原紙：２：展開しない ※顧客支給品だったら原紙でも２：展開しない それ以外：３：展開（無し可） コートボール：３：展開（無し可） | CW32: 1：展開 2：展開しない 3：展開(無し可) 原紙：２：展開しない ※顧客支給品だったら原紙でも２：展開しない それ以外：３：展開（無し可） コートボール：３：展開（無し可） | CY32: 1：展開 2：展開しない 3：展開(無し可) 原紙：２：展開しない ※顧客支給品だったら原紙でも２：展開しない それ以外：３：展開（無し可） コートボール：３：展開（無し可） | DA32: 1：展開 2：展開しない 3：展開(無し可) 原紙：２：展開しない ※顧客支給品だったら原紙でも２：展開しない それ以外：３：展開（無し可） コートボール：３：展開（無し可） | DC32: 1：展開 2：展開しない 3：展開(無し可) 原紙：２：展開しない ※顧客支給品だったら原紙でも２：展開しない それ以外：３：展開（無し可） コートボール：３：展開（無し可） | DE32: 1：展開 2：展開しない 3：展開(無し可) 原紙：２：展開しない ※顧客支給品だったら原紙でも２：展開しない それ以外：３：展開（無し可） コートボール：３：展開（無し可） | DG32: 1：展開 2：展開しない 3：展開(無し可) 原紙：２：展開しない ※顧客支給品だったら原紙でも２：展開しない それ以外：３：展開（無し可） コートボール：３：展開（無し可）
C33: T | D33: BOMマスタ | K33: 手配ＮＯ３区分 | AQ33: 1：展開 2：展開しない 3：展開(無し可) 原紙：２：展開しない ※顧客支給品だったら原紙でも２：展開しない それ以外：３：展開（無し可） コートボール：３：展開（無し可） | BW33: 1：展開 2：展開しない 3：展開(無し可) 原紙：２：展開しない ※顧客支給品だったら原紙でも２：展開しない それ以外：３：展開（無し可） コートボール：３：展開（無し可） | CQ33: 1：展開 2：展開しない 3：展開(無し可) 原紙：２：展開しない ※顧客支給品だったら原紙でも２：展開しない それ以外：３：展開（無し可） コートボール：３：展開（無し可） | CS33: 1：展開 2：展開しない 3：展開(無し可) 原紙：２：展開しない ※顧客支給品だったら原紙でも２：展開しない それ以外：３：展開（無し可） コートボール：３：展開（無し可） | CU33: 1：展開 2：展開しない 3：展開(無し可) 原紙：２：展開しない ※顧客支給品だったら原紙でも２：展開しない それ以外：３：展開（無し可） コートボール：３：展開（無し可） | CW33: 1：展開 2：展開しない 3：展開(無し可) 原紙：２：展開しない ※顧客支給品だったら原紙でも２：展開しない それ以外：３：展開（無し可） コートボール：３：展開（無し可） | CY33: 1：展開 2：展開しない 3：展開(無し可) 原紙：２：展開しない ※顧客支給品だったら原紙でも２：展開しない それ以外：３：展開（無し可） コートボール：３：展開（無し可） | DA33: 1：展開 2：展開しない 3：展開(無し可) 原紙：２：展開しない ※顧客支給品だったら原紙でも２：展開しない それ以外：３：展開（無し可） コートボール：３：展開（無し可） | DC33: 1：展開 2：展開しない 3：展開(無し可) 原紙：２：展開しない ※顧客支給品だったら原紙でも２：展開しない それ以外：３：展開（無し可） コートボール：３：展開（無し可） | DE33: 1：展開 2：展開しない 3：展開(無し可) 原紙：２：展開しない ※顧客支給品だったら原紙でも２：展開しない それ以外：３：展開（無し可） コートボール：３：展開（無し可） | DG33: 1：展開 2：展開しない 3：展開(無し可) 原紙：２：展開しない ※顧客支給品だったら原紙でも２：展開しない それ以外：３：展開（無し可） コートボール：３：展開（無し可）
C34: T | D34: BOMマスタ | K34: 手配ＮＯ４区分 | AQ34: 固定：NULL | BW34: 固定：NULL | CQ34: 固定：NULL | CS34: 固定：NULL | CU34: 固定：NULL | CW34: 固定：NULL | CY34: 固定：NULL | DA34: 固定：NULL | DC34: 固定：NULL | DE34: 固定：NULL | DG34: 固定：NULL
... C42: T | D42: BOMマスタ | K42: 上限手配ＮＯ４ | AQ42: 固定：NULL | BW42: 固定：NULL | CQ42: 固定：NULL | CS42: 固定：NULL | CU42: 固定：NULL | CW42: 固定：NULL | CY42: 固定：NULL | DA42: 固定：NULL | DC42: 固定：NULL | DE42: 固定：NULL | DG42: 固定：NULL
C43: T | D43: BOMマスタ | K43: 親指図数量 | V43: 画 | W43: 加工工程マスタ | AF43: 数量 | AQ43: スリッタとトムソンのみ数が変わる | CQ43: 補足資料_親子関係設定参照 | CS43: 補足資料_親子関係設定参照 | CW43: 補足資料_親子関係設定参照 | CY43: 補足資料_親子関係設定参照 | DA43: 補足資料_親子関係設定参照 | DC43: 補足資料_親子関係設定参照 | DE43: 補足資料_親子関係設定参照 | DG43: 補足資料_親子関係設定参照
C44: T | D44: BOMマスタ | K44: 子投入数量 | V44: 画 | W44: 加工工程マスタ | AF44: 使用材料数量 | CQ44: 補足資料_親子関係設定参照 | CS44: 補足資料_親子関係設定参照 | CW44: 補足資料_親子関係設定参照 | CY44: 補足資料_親子関係設定参照 | DA44: 補足資料_親子関係設定参照 | DC44: 補足資料_親子関係設定参照 | DE44: 補足資料_親子関係設定参照 | DG44: 補足資料_親子関係設定参照
C45: T | D45: BOMマスタ | K45: 子必要数量 | V45: 画 | W45: 加工工程マスタ | AF45: 子必要数量 | AQ45: ロス率を加味して設定する | CQ45: 補足資料_親子関係設定参照 | CS45: 補足資料_親子関係設定参照 | CW45: 補足資料_親子関係設定参照 | CY45: 補足資料_親子関係設定参照 | DA45: 補足資料_親子関係設定参照 | DC45: 補足資料_親子関係設定参照 | DE45: 補足資料_親子関係設定参照 | DG45: 補足資料_親子関係設定参照
C46: T | D46: BOMマスタ | K46: 子固定必要数量 | AQ46: 坪量に皮むき数量 | BW46: 坪量に皮むき数量台数 | CQ46: 補足資料_親子関係設定参照 | CS46: 補足資料_親子関係設定参照 | CU46: 坪量に皮むき数量台数 | CW46: 補足資料_親子関係設定参照 | CY46: 補足資料_親子関係設定参照 | DA46: 補足資料_親子関係設定参照 | DC46: 補足資料_親子関係設定参照 | DE46: 補足資料_親子関係設定参照 | DG46: 補足資料_親子関係設定参照 | DH46: REV6.0 連産品の副産品FLGON
C47: T | D47: BOMマスタ | K47: 副産品ＦＬＧ | AQ47: 0：副産品ではない。１：副産品 固定：0 OFF | BW47: 0：副産品ではない。１：副産品 固定：0 OFF | CQ47: 0：副産品ではない。１：副産品 固定：0 OFF | CS47: 0：副産品ではない。１：副産品 固定：1 ON | CU47: 0：副産品ではない。１：副産品 固定：0 OFF | CW47: 0：副産品ではない。１：副産品 固定：0 OFF | CY47: 0：副産品ではない。１：副産品 固定：0 OFF | DA47: 0：副産品ではない。１：副産品 固定：0 OFF | DC47: 0：副産品ではない。１：副産品 固定：0 OFF | DE47: 0：副産品ではない。１：副産品 固定：0 OFF | DG47: 0：副産品ではない。１：副産品 固定：0 OFF
C48: T | D48: BOMマスタ | K48: 投入オフセット区分 | AQ48: 1：着手日起算 2：完了日起算 1：着手日起算 | BW48: 1：着手日起算 2：完了日起算 1：着手日起算 | CQ48: 1：着手日起算 2：完了日起算 1：着手日起算 | CS48: 1：着手日起算 2：完了日起算 1：着手日起算 | CU48: 1：着手日起算 2：完了日起算 1：着手日起算 | CW48: 1：着手日起算 2：完了日起算 1：着手日起算 | CY48: 1：着手日起算 2：完了日起算 1：着手日起算 | DA48: 1：着手日起算 2：完了日起算 1：着手日起算 | DC48: 1：着手日起算 2：完了日起算 1：着手日起算 | DE48: 1：着手日起算 2：完了日起算 1：着手日起算 | DG48: 1：着手日起算 2：完了日起算 1：着手日起算
C49: T | D49: BOMマスタ | K49: 投入オフセット | AQ49: 固定：0 | BW49: 固定：0 | CQ49: 固定：0 | CS49: 固定：0 | CU49: 固定：0 | CW49: 固定：0 | CY49: 固定：0 | DA49: 固定：0 | DC49: 固定：0 | DE49: 固定：0 | DG49: 固定：0
C50: T | D50: BOMマスタ | K50: バックフラッシュ区分 | AQ50: 1：出来高比例 2：工程実績数比例（工程着手日） 3：工程実績数比例（工程完了日） 4：予定投入量固定（工程着手日） 5：予定投入量固定（工程完了日） 6：対象外 外注品：4：予定投入量固定（工程着手日） それ以外：6：対象外 ワーキンググループ単位、工程がコルゲータでFELIXがない場合は １：出来高比例 | BW50: 1：出来高比例 2：工程実績数比例（工程着手日） 3：工程実績数比例（工程完了日） 4：予定投入量固定（工程着手日） 5：予定投入量固定（工程完了日） 6：対象外 外注品：4：予定投入量固定（工程着手日） それ以外：6：対象外 ワーキンググループ単位、工程がコルゲータでFELIXがない場合は １：出来高比例 | CQ50: 1：出来高比例 2：工程実績数比例（工程着手日） 3：工程実績数比例（工程完了日） 4：予定投入量固定（工程着手日） 5：予定投入量固定（工程完了日） 6：対象外 外注品：4：予定投入量固定（工程着手日） それ以外：6：対象外 ワーキンググループ単位、工程がコルゲータでFELIXがない場合は １：出来高比例 | CS50: 1：出来高比例 2：工程実績数比例（工程着手日） 3：工程実績数比例（工程完了日） 4：予定投入量固定（工程着手日） 5：予定投入量固定（工程完了日） 6：対象外 外注品：4：予定投入量固定（工程着手日） それ以外：6：対象外 ワーキンググループ単位、工程がコルゲータでFELIXがない場合は １：出来高比例 | CU50: 1：出来高比例 2：工程実績数比例（工程着手日） 3：工程実績数比例（工程完了日） 4：予定投入量固定（工程着手日） 5：予定投入量固定（工程完了日） 6：対象外 外注品：4：予定投入量固定（工程着手日） それ以外：6：対象外 ワーキンググループ単位、工程がコルゲータでFELIXがない場合は １：出来高比例 | CW50: 1：出来高比例 2：工程実績数比例（工程着手日） 3：工程実績数比例（工程完了日） 4：予定投入量固定（工程着手日） 5：予定投入量固定（工程完了日） 6：対象外 外注品：4：予定投入量固定（工程着手日） | CY50: 1：出来高比例 2：工程実績数比例（工程着手日） 3：工程実績数比例（工程完了日） 4：予定投入量固定（工程着手日） 5：予定投入量固定（工程完了日） 6：対象外 外注品：4：予定投入量固定（工程着手日） それ以外：6：対象外 ワーキンググループ単位、工程がコルゲータでFELIXがない場合は １：出来高比例 | DA50: 1：出来高比例 2：工程実績数比例（工程着手日） 3：工程実績数比例（工程完了日） 4：予定投入量固定（工程着手日） 5：予定投入量固定（工程完了日） 6：対象外 外注品：4：予定投入量固定（工程着手日） それ以外：6：対象外 ワーキンググループ単位、工程がコルゲータでFELIXがない場合は １：出来高比例 | DC50: 1：出来高比例 2：工程実績数比例（工程着手日） 3：工程実績数比例（工程完了日） 4：予定投入量固定（工程着手日） 5：予定投入量固定（工程完了日） 6：対象外 外注品：4：予定投入量固定（工程着手日） それ以外：6：対象外 ワーキンググループ単位、工程がコルゲータでFELIXがない場合は １：出来高比例 | DE50: 1：出来高比例 2：工程実績数比例（工程着手日） 3：工程実績数比例（工程完了日） 4：予定投入量固定（工程着手日） 5：予定投入量固定（工程完了日） 6：対象外 外注品：4：予定投入量固定（工程着手日） それ以外：6：対象外 ワーキンググループ単位、工程がコルゲータでFELIXがない場合は １：出来高比例 | DG50: 1：出来高比例 2：工程実績数比例（工程着手日） 3：工程実績数比例（工程完了日） 4：予定投入量固定（工程着手日） 5：予定投入量固定（工程完了日） 6：対象外 外注品：4：予定投入量固定（工程着手日） それ以外：6：対象外 ワーキンググループ単位、工程がコルゲータでFELIXがない場合は １：出来高比例
C51: T | D51: BOMマスタ | K51: 指図時ロット指定ＦＬＧ | AQ51: 固定：0 | BW51: 固定：0 | CQ51: 固定：0 | CS51: 固定：0 | CU51: 固定：0 | CW51: 固定：0 | CY51: 固定：0 | DA51: 固定：0 | DC51: 固定：0 | DE51: 固定：0 | DG51: 固定：0
C52: T | D52: BOMマスタ | K52: ロット混在ＦＬＧ | AQ52: 固定：0 | BW52: 固定：0 | CQ52: 固定：0 | CS52: 固定：0 | CU52: 固定：0 | CW52: 固定：0 | CY52: 固定：0 | DA52: 固定：0 | DC52: 固定：0 | DE52: 固定：0 | DG52: 固定：0
C53: T | D53: BOMマスタ | K53: サブロット混在ＦＬＧ | AQ53: 固定：0 | BW53: 固定：0 | CQ53: 固定：0 | CS53: 固定：0 | CU53: 固定：0 | CW53: 固定：0 | CY53: 固定：0 | DA53: 固定：0 | DC53: 固定：0 | DE53: 固定：0 | DG53: 固定：0
C54: T | D54: BOMマスタ | K54: 引当制御区分 | AQ54: 1：引当対象外 2：引当対象（未引当指図不可） 3：引当対象（未引当指図可） 3:引当対象（未引当指図可） | BW54: 1：引当対象外 2：引当対象（未引当指図不可） 3：引当対象（未引当指図可） 3:引当対象（未引当指図可） | CQ54: 1：引当対象外 2：引当対象（未引当指図不可） 3：引当対象（未引当指図可） 3:引当対象（未引当指図可） | CS54: 1：引当対象外 2：引当対象（未引当指図不可） 3：引当対象（未引当指図可） 3:引当対象（未引当指図可） | CU54: 1：引当対象外 2：引当対象（未引当指図不可） 3：引当対象（未引当指図可） 3:引当対象（未引当指図可） | CW54: 1：引当対象外 2：引当対象（未引当指図不可） 3：引当対象（未引当指図可） 3:引当対象（未引当指図可） | CY54: 1：引当対象外 2：引当対象（未引当指図不可） 3：引当対象（未引当指図可） 3:引当対象（未引当指図可） | DA54: 1：引当対象外 2：引当対象（未引当指図不可） 3：引当対象（未引当指図可） 3:引当対象（未引当指図可） | DC54: 1：引当対象外 2：引当対象（未引当指図不可） 3：引当対象（未引当指図可） 3:引当対象（未引当指図可） | DE54: 1：引当対象外 2：引当対象（未引当指図不可） 3：引当対象（未引当指図可） 3:引当対象（未引当指図可） | DG54: 1：引当対象外 2：引当対象（未引当指図不可） 3：引当対象（未引当指図可） 3:引当対象（未引当指図可）
C55: T | D55: BOMマスタ | K55: 引継対象子品目ＦＬＧ | AQ55: 固定：0 | BW55: 固定：0 | CQ55: 固定：0 | CS55: 固定：0 | CU55: 固定：0 | CW55: 固定：0 | CY55: 固定：0 | DA55: 固定：0 | DC55: 固定：0 | DE55: 固定：0 | DG55: 固定：0
C56: T | D56: BOMマスタ | K56: 収率計算用ＦＬＧ | AQ56: 固定：0 | BW56: 固定：0 | CQ56: 固定：0 | CS56: 固定：0 | CU56: 固定：0 | CW56: 固定：0 | CY56: 固定：0 | DA56: 固定：0 | DC56: 固定：0 | DE56: 固定：0 | DG56: 固定：0
C57: T | D57: BOMマスタ | K57: 投入制御区分 | AQ57: 1：ＭＲＰ・投入対象 2：ＭＲＰ対象外（投入可） 3：ＭＲＰ対象外（指図書のみ） 4：ＭＲＰ対象・オーダ確定不可 支給品：1：ＭＲＰ・投入対象 自給品：3：ＭＲＰ対象外（指図書のみ） それ以外：1：ＭＲＰ・投入対象 | BW57: 1：ＭＲＰ・投入対象 2：ＭＲＰ対象外（投入可） 3：ＭＲＰ対象外（指図書のみ） 4：ＭＲＰ対象・オーダ確定不可 支給品：1：ＭＲＰ・投入対象 自給品：3：ＭＲＰ対象外（指図書のみ） それ以外：1：ＭＲＰ・投入対象 | CQ57: 1：ＭＲＰ・投入対象 2：ＭＲＰ対象外（投入可） 3：ＭＲＰ対象外（指図書のみ） 4：ＭＲＰ対象・オーダ確定不可 支給品：1：ＭＲＰ・投入対象 自給品：3：ＭＲＰ対象外（指図書のみ） それ以外：1：ＭＲＰ・投入対象 | CS57: 1：ＭＲＰ・投入対象 2：ＭＲＰ対象外（投入可） 3：ＭＲＰ対象外（指図書のみ） 4：ＭＲＰ対象・オーダ確定不可 支給品：1：ＭＲＰ・投入対象 自給品：3：ＭＲＰ対象外（指図書のみ） それ以外：1：ＭＲＰ・投入対象 | CU57: 1：ＭＲＰ・投入対象 2：ＭＲＰ対象外（投入可） 3：ＭＲＰ対象外（指図書のみ） 4：ＭＲＰ対象・オーダ確定不可 支給品：1：ＭＲＰ・投入対象 自給品：3：ＭＲＰ対象外（指図書のみ） それ以外：1：ＭＲＰ・投入対象 | CW57: 1：ＭＲＰ・投入対象 2：ＭＲＰ対象外（投入可） 3：ＭＲＰ対象外（指図書のみ） 4：ＭＲＰ対象・オーダ確定不可 支給品：1：ＭＲＰ・投入対象 自給品：3：ＭＲＰ対象外（指図書のみ） それ以外：1：ＭＲＰ・投入対象 | CY57: 1：ＭＲＰ・投入対象 2：ＭＲＰ対象外（投入可） 3：ＭＲＰ対象外（指図書のみ） 4：ＭＲＰ対象・オーダ確定不可 支給品：1：ＭＲＰ・投入対象 自給品：3：ＭＲＰ対象外（指図書のみ） それ以外：1：ＭＲＰ・投入対象 | DA57: 1：ＭＲＰ・投入対象 2：ＭＲＰ対象外（投入可） 3：ＭＲＰ対象外（指図書のみ） 4：ＭＲＰ対象・オーダ確定不可 支給品：1：ＭＲＰ・投入対象 自給品：3：ＭＲＰ対象外（指図書のみ） それ以外：1：ＭＲＰ・投入対象 | DC57: 1：ＭＲＰ・投入対象 2：ＭＲＰ対象外（投入可） 3：ＭＲＰ対象外（指図書のみ） 4：ＭＲＰ対象・オーダ確定不可 支給品：1：ＭＲＰ・投入対象 自給品：3：ＭＲＰ対象外（指図書のみ） それ以外：1：ＭＲＰ・投入対象 | DE57: 1：ＭＲＰ・投入対象 2：ＭＲＰ対象外（投入可） 3：ＭＲＰ対象外（指図書のみ） 4：ＭＲＰ対象・オーダ確定不可 支給品：1：ＭＲＰ・投入対象 自給品：3：ＭＲＰ対象外（指図書のみ） それ以外：1：ＭＲＰ・投入対象 | DG57: 1：ＭＲＰ・投入対象 2：ＭＲＰ対象外（投入可） 3：ＭＲＰ対象外（指図書のみ） 4：ＭＲＰ対象・オーダ確定不可 支給品：1：ＭＲＰ・投入対象 自給品：3：ＭＲＰ対象外（指図書のみ） それ以外：1：ＭＲＰ・投入対象
C58: T | D58: BOMマスタ | K58: 表示順 | AQ58: 原紙：表:1中:2裏:3 包装：仕掛品:1 、カートン:2 タンデム：される方：1 する方:２からの連番 その他：仕掛品：１ コートボール：表１：中：2裏:３ | BW58: 原紙：表:1中:2裏:3 包装：仕掛品:1 、カートン:2 タンデム：される方：1 する方:２からの連番 その他：仕掛品：１ コートボール：表１：中：2裏:３ | CQ58: 原紙：表:1中:2裏:3 包装：仕掛品:1 、カートン:2 タンデム：される方：1 する方:２からの連番 その他：仕掛品：１ コートボール：表１：中：2裏:３ | CS58: 原紙：表:1中:2裏:3 包装：仕掛品:1 、カートン:2 タンデム：される方：1 する方:２からの連番 その他：仕掛品：１ コートボール：表１：中：2裏:３ | CU58: 原紙：表:1中:2裏:3 包装：仕掛品:1 、カートン:2 タンデム：される方：1 する方:２からの連番 その他：仕掛品：１ コートボール：表１：中：2裏:３ | CW58: 原紙：表:1中:2裏:3 包装：仕掛品:1 、カートン:2 タンデム：される方：1 する方:２からの連番 その他：仕掛品：１ コートボール：表１：中：2裏:３ | CY58: 原紙：表:1中:2裏:3 包装：仕掛品:1 、カートン:2 タンデム：される方：1 する方:２からの連番 その他：仕掛品：１ コートボール：表１：中：2裏:３ | DA58: 原紙：表:1中:2裏:3 包装：仕掛品:1 、カートン:2 タンデム：される方：1 する方:２からの連番 その他：仕掛品：１ コートボール：表１：中：2裏:３ | DC58: 原紙：表:1中:2裏:3 包装：仕掛品:1 、カートン:2 タンデム：される方：1 する方:２からの連番 その他：仕掛品：１ コートボール：表１：中：2裏:３ | DE58: 原紙：表:1中:2裏:3 包装：仕掛品:1 、カートン:2 タンデム：される方：1 する方:２からの連番 その他：仕掛品：１ コートボール：表１：中：2裏:３ | DG58: 原紙：表:1中:2裏:3 包装：仕掛品:1 、カートン:2 タンデム：される方：1 する方:２からの連番 その他：仕掛品：１ コートボール：表１：中：2裏:３
... C66: T | D66: BOMマスタ | K66: メモ３ | AQ66: 固定：NULL | BW66: 固定：NULL | CQ66: 固定：NULL | CS66: 固定：NULL | CU66: 固定：NULL | CW66: 固定：NULL | CY66: 固定：NULL | DA66: 固定：NULL | DC66: 固定：NULL | DE66: 固定：NULL | DG66: 固定：NULL
C67: T | D67: BOMマスタ | K67: 論理削除ＦＬＧ | AQ67: 0 | BW67: 0 | CQ67: 0 | CS67: 0 | CU67: 0 | CW67: 0 | CY67: 0 | DA67: 0 | DC67: 0 | DE67: 0 | DG67: 0
C68: T | D68: BOMマスタ | K68: 論理削除ユーザＩＤ | AQ68: NULL | BW68: NULL | CQ68: NULL | CS68: NULL | CU68: NULL | CW68: NULL | CY68: NULL | DA68: NULL | DC68: NULL | DE68: NULL | DG68: NULL
C69: T | D69: BOMマスタ | K69: 論理削除ユーザ名 | AQ69: NULL | BW69: NULL | CQ69: NULL | CS69: NULL | CU69: NULL | CW69: NULL | CY69: NULL | DA69: NULL | DC69: NULL | DE69: NULL | DG69: NULL
C70: T | D70: BOMマスタ | K70: 論理削除日時 | AQ70: NULL | BW70: NULL | CQ70: NULL | CS70: NULL | CU70: NULL | CW70: NULL | CY70: NULL | DA70: NULL | DC70: NULL | DE70: NULL | DG70: NULL
C71: T | D71: BOMマスタ | K71: 登録ユーザＩＤ | AQ71: 登録ユーザー | BW71: 登録ユーザー | CQ71: 登録ユーザー | CS71: 登録ユーザー | CU71: 登録ユーザー | CW71: 登録ユーザー | CY71: 登録ユーザー | DA71: 登録ユーザー | DC71: 登録ユーザー | DE71: 登録ユーザー | DG71: 登録ユーザー
C72: T | D72: BOMマスタ | K72: 登録ユーザ名 | AQ72: 登録ユーザー名 | BW72: 登録ユーザー名 | CQ72: 登録ユーザー名 | CS72: 登録ユーザー名 | CU72: 登録ユーザー名 | CW72: 登録ユーザー名 | CY72: 登録ユーザー名 | DA72: 登録ユーザー名 | DC72: 登録ユーザー名 | DE72: 登録ユーザー名 | DG72: 登録ユーザー名
C73: T | D73: BOMマスタ | K73: 登録日時 | AQ73: 処理日時 | BW73: 処理日時 | CQ73: 処理日時 | CS73: 処理日時 | CU73: 処理日時 | CW73: 処理日時 | CY73: 処理日時 | DA73: 処理日時 | DC73: 処理日時 | DE73: 処理日時 | DG73: 処理日時
C74: T | D74: BOMマスタ | K74: 登録機能ＩＤ
C75: T | D75: BOMマスタ | K75: 更新カウンタ | AQ75: 0 | BW75: 0 | CQ75: 0 | CS75: 0 | CU75: 0 | CW75: 0 | CY75: 0 | DA75: 0 | DC75: 0 | DE75: 0 | DG75: 0
C76: T | D76: BOMマスタ | K76: 更新ユーザＩＤ | AQ76: 登録ユーザー | BW76: 登録ユーザー | CQ76: 登録ユーザー | CS76: 登録ユーザー | CU76: 登録ユーザー | CW76: 登録ユーザー | CY76: 登録ユーザー | DA76: 登録ユーザー | DC76: 登録ユーザー | DE76: 登録ユーザー | DG76: 登録ユーザー
C77: T | D77: BOMマスタ | K77: 更新ユーザ名 | AQ77: 登録ユーザー名 | BW77: 登録ユーザー名 | CQ77: 登録ユーザー名 | CS77: 登録ユーザー名 | CU77: 登録ユーザー名 | CW77: 登録ユーザー名 | CY77: 登録ユーザー名 | DA77: 登録ユーザー名 | DC77: 登録ユーザー名 | DE77: 登録ユーザー名 | DG77: 登録ユーザー名
C78: T | D78: BOMマスタ | K78: 更新日時 | AQ78: 処理日時 | BW78: 処理日時 | CQ78: 処理日時 | CS78: 処理日時 | CU78: 処理日時 | CW78: 処理日時 | CY78: 処理日時 | DA78: 処理日時 | DC78: 処理日時 | DE78: 処理日時 | DG78: 処理日時
C79: T | D79: BOMマスタ | K79: 更新機能ＩＤ
C80: T | D80: BOMマスタ | K80: 更新リクエストＮＯ
C81: T | D81: BOMマスタ | K81: 自給品仕入計上ＦＬＧ
A82: No | F82: 2 | G82: 1 | H82: BOMマスタ | S82: ロジック名称 | AH82: 備考 | BP82: 品目区分別設定値 | CP82: 通常パタン （前工程仕掛品を投入して、加工） | CR82: 連産品（N丁取り） | CT82: 複数仕掛品を投入 （タンデム） | CV82: 購入品（都度採番）手配対象 | CX82: 外注品（都度採番）手配対象 ※有償/無償支給 | CZ82: 外注品（都度採番）手配対象 ※自給品（無償支給）（材料・仕入の支払い分割） | DB82: 消耗品（在庫管理対象外）手配対象 | DD82: 共通品目（発注点発注）を投入 | DF82: 共通品目（MRP発注）を投入
A83: 処理分類 | E83: 更新 | BP83: 商品 | BV83: 製品 | BZ83: 中間品 | CF83: 資材 | CH83: 資材 | CJ83: 原料 | CL83: その他
A84: No | C84: 転送先 | V84: 転送元 | AQ84: 説明 | BP84: 構成あり | BR84: 構成なし | BT84: 版型 | BV84: 内 | BX84: 外 | BZ84: 内 | CB84: 外 | CD84: 購買 | CF84: 在庫管理品（カートン等） | CH84: 非在庫品 | CJ84: 購買 | CL84: 購買
C85: 種 | D85: オブジェクト | K85: 項目名 | V85: 種 | W85: オブジェクト | AF85: 項目名 | BP85: オブジェクト | BQ85: 項目名 | BR85: オブジェクト | BS85: 項目名 | BT85: オブジェクト | BU85: 項目名 | BV85: オブジェクト | BW85: 項目名 | BX85: オブジェクト | BY85: 項目名 | BZ85: オブジェクト | CA85: 項目名 | CB85: オブジェクト | CC85: 項目名 | CD85: オブジェクト | CE85: 項目名 | CF85: オブジェクト | CG85: 項目名 | CH85: オブジェクト | CI85: 項目名 | CJ85: オブジェクト | CK85: 項目名 | CL85: オブジェクト | CM85: 項目名 | CP85: オブジェクト | CQ85: 項目名 | CR85: オブジェクト | CS85: 項目名 | CT85: オブジェクト | CU85: 項目名 | CV85: オブジェクト | CW85: 項目名 | CX85: オブジェクト | CY85: 項目名 | CZ85: オブジェクト | DA85: 項目名 | DB85: オブジェクト | DC85: 項目名 | DD85: オブジェクト | DE85: 項目名 | DF85: オブジェクト | DG85: 項目名
C86: T | D86: BOMマスタ | K86: 論理削除ＦＬＧ | AQ86: 0 | BW86: 1 | CQ86: 1 | CS86: 1 | CU86: 1 | CW86: 1 | CY86: 1 | DA86: 1 | DC86: 1 | DE86: 1 | DG86: 1
C87: T | D87: BOMマスタ | K87: 論理削除ユーザＩＤ | AQ87: NULL | BW87: NULL | CQ87: NULL | CS87: NULL | CU87: NULL | CW87: NULL | CY87: NULL | DA87: NULL | DC87: NULL | DE87: NULL | DG87: NULL
C88: T | D88: BOMマスタ | K88: 論理削除ユーザ名 | AQ88: NULL | BW88: NULL | CQ88: NULL | CS88: NULL | CU88: NULL | CW88: NULL | CY88: NULL | DA88: NULL | DC88: NULL | DE88: NULL | DG88: NULL
C89: T | D89: BOMマスタ | K89: 論理削除日時 | AQ89: NULL | BW89: NULL | CQ89: NULL | CS89: NULL | CU89: NULL | CW89: NULL | CY89: NULL | DA89: NULL | DC89: NULL | DE89: NULL | DG89: NULL
C90: T | D90: BOMマスタ | K90: 更新カウンタ | AQ90: 0 | BW90: 0 | CQ90: 0 | CS90: 0 | CU90: 0 | CW90: 0 | CY90: 0 | DA90: 0 | DC90: 0 | DE90: 0 | DG90: 0
C91: T | D91: BOMマスタ | K91: 更新ユーザＩＤ | AQ91: 登録ユーザー | BW91: 登録ユーザー | CQ91: 登録ユーザー | CS91: 登録ユーザー | CU91: 登録ユーザー | CW91: 登録ユーザー | CY91: 登録ユーザー | DA91: 登録ユーザー | DC91: 登録ユーザー | DE91: 登録ユーザー | DG91: 登録ユーザー
C92: T | D92: BOMマスタ | K92: 更新ユーザ名 | AQ92: 登録ユーザー名 | BW92: 登録ユーザー名 | CQ92: 登録ユーザー名 | CS92: 登録ユーザー名 | CU92: 登録ユーザー名 | CW92: 登録ユーザー名 | CY92: 登録ユーザー名 | DA92: 登録ユーザー名 | DC92: 登録ユーザー名 | DE92: 登録ユーザー名 | DG92: 登録ユーザー名
C93: T | D93: BOMマスタ | K93: 更新日時 | AQ93: 処理日時 | BW93: 処理日時 | CQ93: 処理日時 | CS93: 処理日時 | CU93: 処理日時 | CW93: 処理日時 | CY93: 処理日時 | DA93: 処理日時 | DC93: 処理日時 | DE93: 処理日時 | DG93: 処理日時
C94: T | D94: BOMマスタ | K94: 更新機能ＩＤ
C95: T | D95: BOMマスタ | K95: 更新リクエストＮＯ

Sheet 更新入出力仕様_工程工数
A1: =表紙!A54 -> Webシステム | K1: 文書名 | U1: モジュールID | Z1: =表紙!$AJ$63 -> MS | AE1: モジュール名 | AJ1: =表紙!$AX$63 -> 見積管理 | AS1: 文書番号 | AZ1: Version | BF1: Rev.
K2: =表紙!O64 -> アドオン設計書 | U2: ｻﾌﾞﾓｼﾞｭｰﾙID | Z2: =表紙!$AJ$64 -> MSBB | AE2: ｻﾌﾞﾓｼﾞｭｰﾙ名 | AJ2: =表紙!$AX$64 -> Webシステム | AS2: =表紙!$BL$64 -> M7-US-1140 | AZ2: =表紙!$BU$64 -> 7.0.2 | BF2: =表紙!$CB$64 -> 8
K3: =RIGHT(CELL("filename",$A$1),LEN(CELL("filename",$A$1))-FIND("]",CELL("filename",$A$1))) -> 更新入出力仕様_工程工数 | U3: 表題 | Z3: =表紙!$AJ$65 -> - | AE3: =表紙!$AQ$65 -> 製品マスタ連携
A5: No | G5: 1 | H5: 工程工数マスタ | S5: ロジック名称 | AH5: 備考 | BP5: 品目区分別設定値 | CN5: REV4.0 商品を概要と合わせる
A6: 処理分類 | E6: 登録 | BP6: 商品 | BV6: 製品 | BZ6: 中間品 | CF6: 資材 | CH6: 資材 | CJ6: 原料 | CL6: その他
A7: No | C7: 転送先 | V7: 転送元 | AQ7: 説明 | BP7: 構成あり | BR7: 構成なし | BT7: 版型 | BV7: 内 | BX7: 外 | BZ7: 内 | CB7: 外 | CD7: 購買 | CF7: 在庫管理品（カートン等） | CH7: 非在庫品 | CJ7: 購買 | CL7: 購買
C8: 種 | D8: オブジェクト | K8: 項目名 | V8: 種 | W8: オブジェクト | AF8: 項目名 | BP8: オブジェクト | BQ8: 項目名 | BR8: オブジェクト | BS8: 項目名 | BT8: オブジェクト | BU8: 項目名 | BV8: オブジェクト | BW8: 項目名 | BX8: オブジェクト | BY8: 項目名 | BZ8: オブジェクト | CA8: 項目名 | CB8: オブジェクト | CC8: 項目名 | CD8: オブジェクト | CE8: 項目名 | CF8: オブジェクト | CG8: 項目名 | CH8: オブジェクト | CI8: 項目名 | CJ8: オブジェクト | CK8: 項目名 | CL8: オブジェクト | CM8: 項目名
C9: T | D9: 工程工数マスタ | K9: 品目ＣＤ | V9: T | W9: 品目工程マスタ | AF9: 品目CD | BV9: 品目マスタ（共通） | BW9: 品目ＣＤ | BZ9: 品目マスタ（共通） | CA9: 品目ＣＤ
C10: T | D10: 工程工数マスタ | K10: 枝番１ | V10: T | W10: 品目工程マスタ | AF10: 枝番１ | BV10: 品目マスタ（共通） | BW10: 枝番１ | BZ10: 品目マスタ（共通） | CA10: 枝番１
C11: T | D11: 工程工数マスタ | K11: 枝番２ | V11: T | W11: 品目工程マスタ | AF11: 枝番２ | BV11: 品目マスタ（共通） | BW11: 枝番２ | BZ11: 品目マスタ（共通） | CA11: 枝番２
C12: T | D12: 工程工数マスタ | K12: 枝番３ | V12: T | W12: 品目工程マスタ | AF12: 枝番３ | BV12: 品目マスタ（共通） | BW12: 枝番３ | BZ12: 品目マスタ（共通） | CA12: 枝番３
C13: T | D13: 工程工数マスタ | K13: 場所ＣＤ | V13: T | W13: 品目工程マスタ | AF13: 場所ＣＤ | BV13: 製品加工工程マスタ | BW13: 号機 | BZ13: 製品加工工程マスタ | CA13: 号機
C14: T | D14: 工程工数マスタ | K14: 工程パタン | V14: T | W14: 品目工程マスタ | AF14: 工程パタン | BW14: 固定:1 | CA14: 固定:1
C15: T | D15: 工程工数マスタ | K15: 工程ＣＤ | V15: T | W15: 品目工程マスタ | AF15: 工程ＣＤ | BV15: 製品加工工程マスタ | BW15: 作業工程CD | BZ15: 製品加工工程マスタ | CA15: 作業工程CD
C16: T | D16: 工程工数マスタ | K16: 工程連番 | V16: T | W16: 品目工程マスタ | AF16: 工程連番 | BV16: 製品加工工程マスタ | BW16: 作業順 | BZ16: 製品加工工程マスタ | CA16: 作業順
C17: T | D17: 工程工数マスタ | K17: 工数管理ＣＤ | AQ17: 人、機械作業の工数管理CDを汎用マスタで自動設定 設備の有無で機械作業を作る・作らない 場所から設備グループ、工程CDで取得する | BW17: 人、機械作業の工数管理CDを汎用マスタで自動設定 設備の有無で機械作業を作る・作らない 場所から設備グループ、工程CDで取得する | CA17: 人、機械作業の工数管理CDを汎用マスタで自動設定 設備の有無で機械作業を作る・作らない 場所から設備グループ、工程CDで取得する
C18: T | D18: 工程工数マスタ | K18: 適用開始日 | V18: T | W18: 品目工程マスタ | AF18: 適用開始日 | BW18: 処理日付 | CA18: 処理日付
C19: T | D19: 工程工数マスタ | K19: 会社ＣＤ | V19: T | W19: 品目工程マスタ | AF19: 会社ＣＤ | BW19: 会社ＣＤ | CA19: 会社ＣＤ
C20: T | D20: 工程工数マスタ | K20: 適用終了日 | V20: T | W20: 品目工程マスタ | AF20: 適用終了日 | BW20: 73050 | CA20: 73050
C21: T | D21: 工程工数マスタ | K21: 工数（固定） | AQ21: 汎用マスタから場所、工程CDで取得する | BW21: 汎用マスタから場所、工程CDで取得する | CA21: 汎用マスタから場所、工程CDで取得する
C22: T | D22: 工程工数マスタ | K22: 工数（数量依存） | AQ22: 汎用マスタから場所、工程CDで数量依存の工数を取得する | BW22: 汎用マスタから場所、工程CDで数量依存の工数を取得する | CA22: 汎用マスタから場所、工程CDで数量依存の工数を取得する
C23: T | D23: 工程工数マスタ | K23: 基準数量 | AQ23: スリッタなら割り数、トムソンなら個数/丁数、それ以外1 汎用マスタから設定する。工数が小さい単位にならないよう5000とか大きな数字にする。出来高ではなく通し数が基準となる。 | BW23: スリッタなら割り数、トムソンなら個数/丁数、それ以外1 汎用マスタから設定する。工数が小さい単位にならないよう5000とか大きな数字にする。出来高ではなく通し数が基準となる。 | CA23: スリッタなら割り数、トムソンなら個数/丁数、それ以外1 汎用マスタから設定する。工数が小さい単位にならないよう5000とか大きな数字にする。出来高ではなく通し数が基準となる。
C24: T | D24: 工程工数マスタ | K24: 自動工数計算ＦＬＧ | AQ24: 0:自動計算しない １：自動計算する 0：自動計算しない 設備連携情報を正とする。 FACNET連携のない場合 １：自動計算する | BW24: 0:自動計算しない １：自動計算する 0：自動計算しない 設備連携情報を正とする。 FACNET連携のない場合 １：自動計算する | CA24: 0:自動計算しない １：自動計算する 0：自動計算しない 設備連携情報を正とする。 FACNET連携のない場合 １：自動計算する
C25: T | D25: 工程工数マスタ | K25: 表示順 | AQ25: 人：2、設備:1 | BW25: 人：2、設備:1 | CA25: 人：2、設備:1
C26: T | D26: 工程工数マスタ | K26: 原価対象外ＦＬＧ | AQ26: 0 | BW26: 0 | CA26: 0
C27: T | D27: 工程工数マスタ | K27: メモ１ | AQ27: 固定：NULL | BW27: 固定：NULL | CA27: 固定：NULL
C28: T | D28: 工程工数マスタ | K28: メモ２ | AQ28: 固定：NULL | BW28: 固定：NULL | CA28: 固定：NULL
C29: T | D29: 工程工数マスタ | K29: メモ３ | AQ29: 固定：NULL | BW29: 固定：NULL | CA29: 固定：NULL
C30: T | D30: 工程工数マスタ | K30: 論理削除ＦＬＧ | AQ30: 0 | BW30: 0 | CA30: 0
C31: T | D31: 工程工数マスタ | K31: 論理削除ユーザＩＤ | AQ31: 固定：NULL | BW31: 固定：NULL | CA31: 固定：NULL
C32: T | D32: 工程工数マスタ | K32: 論理削除ユーザ名 | AQ32: 固定：NULL | BW32: 固定：NULL | CA32: 固定：NULL
C33: T | D33: 工程工数マスタ | K33: 論理削除日時 | AQ33: 固定：NULL | BW33: 固定：NULL | CA33: 固定：NULL
C34: T | D34: 工程工数マスタ | K34: 登録ユーザＩＤ | AQ34: 登録ユーザー | BW34: 登録ユーザー | CA34: 登録ユーザー
C35: T | D35: 工程工数マスタ | K35: 登録ユーザ名 | AQ35: 登録ユーザー名 | BW35: 登録ユーザー名 | CA35: 登録ユーザー名
C36: T | D36: 工程工数マスタ | K36: 登録日時 | AQ36: 処理日時 | BW36: 処理日時 | CA36: 処理日時
C37: T | D37: 工程工数マスタ | K37: 登録機能ＩＤ
C38: T | D38: 工程工数マスタ | K38: 更新カウンタ | AQ38: 0 | BW38: 0 | CA38: 0
C39: T | D39: 工程工数マスタ | K39: 更新ユーザＩＤ | AQ39: 登録ユーザー | BW39: 登録ユーザー | CA39: 登録ユーザー
C40: T | D40: 工程工数マスタ | K40: 更新ユーザ名 | AQ40: 登録ユーザー名 | BW40: 登録ユーザー名 | CA40: 登録ユーザー名
C41: T | D41: 工程工数マスタ | K41: 更新日時 | AQ41: 処理日時 | BW41: 処理日時 | CA41: 処理日時
C42: T | D42: 工程工数マスタ | K42: 更新機能ＩＤ
C43: T | D43: 工程工数マスタ | K43: 更新リクエストＮＯ
A44: No | G44: 2 | H44: 工程工数マスタ | S44: ロジック名称 | AH44: 備考 | BP44: 品目区分別設定値
A45: 処理分類 | E45: 更新 | BP45: 商品 | BV45: 製品 | BZ45: 中間品 | CF45: 資材 | CH45: 資材 | CJ45: 原料 | CL45: その他
A46: No | C46: 転送先 | V46: 転送元 | AQ46: 説明 | BP46: 構成あり | BR46: 構成なし | BT46: 版型 | BV46: 内 | BX46: 外 | BZ46: 内 | CB46: 外 | CD46: 購買 | CF46: 在庫管理品（カートン等） | CH46: 非在庫品 | CJ46: 購買 | CL46: 購買
C47: 種 | D47: オブジェクト | K47: 項目名 | V47: 種 | W47: オブジェクト | AF47: 項目名 | BP47: オブジェクト | BQ47: 項目名 | BR47: オブジェクト | BS47: 項目名 | BT47: オブジェクト | BU47: 項目名 | BV47: オブジェクト | BW47: 項目名 | BX47: オブジェクト | BY47: 項目名 | BZ47: オブジェクト | CA47: 項目名 | CB47: オブジェクト | CC47: 項目名 | CD47: オブジェクト | CE47: 項目名 | CF47: オブジェクト | CG47: 項目名 | CH47: オブジェクト | CI47: 項目名 | CJ47: オブジェクト | CK47: 項目名 | CL47: オブジェクト | CM47: 項目名
C48: T | D48: 工程工数マスタ | K48: 適用終了日 | V48: T | W48: 品目工程マスタ | AF48: 適用終了日 | BW48: 処理日-1 | CA48: 処理日-1
C49: T | D49: 工程工数マスタ | K49: 論理削除ＦＬＧ | AQ49: 0 | BW49: 0 | CA49: 0
C50: T | D50: 工程工数マスタ | K50: 論理削除ユーザＩＤ | AQ50: 固定：NULL | BW50: 固定：NULL | CA50: 固定：NULL
C51: T | D51: 工程工数マスタ | K51: 論理削除ユーザ名 | AQ51: 固定：NULL | BW51: 固定：NULL | CA51: 固定：NULL
C52: T | D52: 工程工数マスタ | K52: 論理削除日時 | AQ52: 固定：NULL | BW52: 固定：NULL | CA52: 固定：NULL
C53: T | D53: 工程工数マスタ | K53: 更新カウンタ | AQ53: 0 | BW53: 0 | CA53: 0
C54: T | D54: 工程工数マスタ | K54: 更新ユーザＩＤ | AQ54: 登録ユーザー | BW54: 登録ユーザー | CA54: 登録ユーザー
C55: T | D55: 工程工数マスタ | K55: 更新ユーザ名 | AQ55: 登録ユーザー名 | BW55: 登録ユーザー名 | CA55: 登録ユーザー名
C56: T | D56: 工程工数マスタ | K56: 更新日時 | AQ56: 処理日時 | BW56: 処理日時 | CA56: 処理日時
C57: T | D57: 工程工数マスタ | K57: 更新機能ＩＤ
C58: T | D58: 工程工数マスタ | K58: 更新リクエストＮＯ

Sheet 更新入出力仕様_加工単価 
A1: =表紙!A54 -> Webシステム | K1: 文書名 | U1: モジュールID | Z1: =表紙!$AJ$63 -> MS | AE1: モジュール名 | AJ1: =表紙!$AX$63 -> 見積管理 | AS1: 文書番号 | AZ1: Version | BF1: Rev.
K2: =表紙!O64 -> アドオン設計書 | U2: ｻﾌﾞﾓｼﾞｭｰﾙID | Z2: =表紙!$AJ$64 -> MSBB | AE2: ｻﾌﾞﾓｼﾞｭｰﾙ名 | AJ2: =表紙!$AX$64 -> Webシステム | AS2: =表紙!$BL$64 -> M7-US-1140 | AZ2: =表紙!$BU$64 -> 7.0.2 | BF2: =表紙!$CB$64 -> 8
K3: =RIGHT(CELL("filename",$A$1),LEN(CELL("filename",$A$1))-FIND("]",CELL("filename",$A$1))) -> 更新入出力仕様_加工単価 | U3: 表題 | Z3: =表紙!$AJ$65 -> - | AE3: =表紙!$AQ$65 -> 製品マスタ連携
A5: No | G5: 1 | H5: 加工単価マスタ | S5: ロジック名称 | AH5: 備考 | BM5: 品目区分別設定値 | CK5: REV4.0 商品を概要と合わせる
A6: 処理分類 | E6: 登録 | BM6: 商品 | BS6: 製品 | BW6: 中間品 | CC6: 資材 | CE6: 資材 | CG6: 原料 | CI6: その他
A7: No | C7: 転送先 | V7: 転送元 | AQ7: 説明 | BM7: 構成あり | BO7: 構成なし | BQ7: 版型 | BS7: 内 | BU7: 外 | BW7: 内 | BY7: 外 | CA7: 購買 | CC7: 在庫管理品（カートン等） | CE7: 非在庫品 | CG7: 購買 | CI7: 購買
C8: 種 | D8: オブジェクト | K8: 項目名 | V8: 種 | W8: オブジェクト | AF8: 項目名 | BM8: オブジェクト | BN8: 項目名 | BO8: オブジェクト | BP8: 項目名 | BQ8: オブジェクト | BR8: 項目名 | BS8: オブジェクト | BT8: 項目名 | BU8: オブジェクト | BV8: 項目名 | BW8: オブジェクト | BX8: 項目名 | BY8: オブジェクト | BZ8: 項目名 | CA8: オブジェクト | CB8: 項目名 | CC8: オブジェクト | CD8: 項目名 | CE8: オブジェクト | CF8: 項目名 | CG8: オブジェクト | CH8: 項目名 | CI8: オブジェクト | CJ8: 項目名
C9: T | D9: 加工単価マスタ | K9: 品目ＣＤ | V9: T | AQ9: 工程毎のダミー品目 | BU9: 品目マスタ（共通） | BV9: 品目ＣＤ | BY9: 品目マスタ（共通） | BZ9: 品目ＣＤ
C10: T | D10: 加工単価マスタ | K10: 枝番１ | V10: T | BU10: 品目マスタ（共通） | BV10: 枝番１ | BY10: 品目マスタ（共通） | BZ10: 枝番１
C11: T | D11: 加工単価マスタ | K11: 枝番２ | V11: T | BU11: 品目マスタ（共通） | BV11: 枝番２ | BY11: 品目マスタ（共通） | BZ11: 枝番２
C12: T | D12: 加工単価マスタ | K12: 枝番３ | V12: T | BU12: 品目マスタ（共通） | BV12: 枝番３ | BY12: 品目マスタ（共通） | BZ12: 枝番３
C13: T | D13: 加工単価マスタ | K13: 発注先ＣＤ | V13: 画 | W13: 加工工程マスタ | AF13: 号機/発注先 | BU13: 製品ロット別単価マスタ | BV13: 発注先 | BY13: 製品加工工程マスタ | BZ13: 発注先
C14: T | D14: 加工単価マスタ | K14: メーカＣＤ | AQ14: NULL | BV14: NULL | BZ14: NULL
C15: T | D15: 加工単価マスタ | K15: 単位ＣＤ | V15: 画 | W15: 加工工程マスタ | AF15: 単位 | BU15: 製品ロット別単価マスタ | BV15: 数量単位 | BY15: 製品加工工程マスタ | BZ15: 個
C16: T | D16: 加工単価マスタ | K16: ロット数量 | V16: 画 | W16: 加工工程マスタ | AF16: 数量 | BU16: 製品ロット別単価マスタ | BV16: ロット別数量1~５ | BY16: 製品加工工程マスタ | BZ16: 1
C17: T | D17: 加工単価マスタ | K17: 通貨ＣＤ | AQ17: JPY | BV17: JPY | BZ17: JPY
C18: T | D18: 加工単価マスタ | K18: 加工単価区分 | AQ18: 1：品目外注 | BV18: 1：品目外注 | BZ18: 1：品目外注
C19: T | D19: 加工単価マスタ | K19: 納入場所ＣＤ | AQ19: NULL | BV19: NULL | BZ19: NULL
C20: T | D20: 加工単価マスタ | K20: 納品先ＣＤ | AQ20: NULL | BV20: NULL | BZ20: NULL
C21: T | D21: 加工単価マスタ | K21: ワーキンググループＣＤ | V21: T | W21: 場所マスタ | AF21: ワーキンググループCD
C22: T | D22: 加工単価マスタ | K22: 適用開始日 | AQ22: 処理日付 | BV22: 処理日付 | BZ22: 処理日付
C23: T | D23: 加工単価マスタ | K23: 会社ＣＤ | AQ23: 固定：会社 | BV23: 固定：会社 | BZ23: 固定：会社
C24: T | D24: 加工単価マスタ | K24: 適用終了日 | AQ24: 固定：2099/12/31 | BV24: 固定：2099/12/31 | BZ24: 固定：2099/12/31
C25: T | D25: 加工単価マスタ | K25: 単価 | V25: 画 | W25: 加工工程マスタ | AF25: 仕入単価 | AQ25: 号機/発注先で判断する | BU25: 製品ロット別単価マスタ | BV25: 仕入単価1~５ | BY25: 製品加工工程マスタ | BZ25: 仕入単価
C26: T | D26: 加工単価マスタ | K26: 改定前単価 | AQ26: NULL | BV26: NULL | BZ26: NULL
C27: T | D27: 加工単価マスタ | K27: 仮単価ＦＬＧ | AQ27: 0：本単価 1:仮単価 0：本単価 | BV27: 0：本単価 1:仮単価 0：本単価 | BZ27: 0：本単価 1:仮単価 0：本単価
C28: T | D28: 加工単価マスタ | K28: 標準工数 | AQ28: NULL | BV28: NULL | BZ28: NULL
C29: T | D29: 加工単価マスタ | K29: 標準工数単価 | AQ29: NULL | BV29: NULL | BZ29: NULL
C30: T | D30: 加工単価マスタ | K30: 原価対象外ＦＬＧ | AQ30: 0：対象 1:対象外 0：対象 | BV30: 0：対象 1:対象外 0：対象 | BZ30: 0：対象 1:対象外 0：対象
C31: T | D31: 加工単価マスタ | K31: 予備単価１ | AQ31: NULL | BV31: NULL | BZ31: NULL
C32: T | D32: 加工単価マスタ | K32: 予備単価２ | AQ32: NULL | BV32: NULL | BZ32: NULL
C33: T | D33: 加工単価マスタ | K33: 予備単価３ | AQ33: NULL | BV33: NULL | BZ33: NULL
C34: T | D34: 加工単価マスタ | K34: メモ１ | AQ34: NULL | BV34: NULL | BZ34: NULL
C35: T | D35: 加工単価マスタ | K35: メモ２ | AQ35: NULL | BV35: NULL | BZ35: NULL
C36: T | D36: 加工単価マスタ | K36: メモ３ | AQ36: NULL | BV36: NULL | BZ36: NULL
C37: T | D37: 加工単価マスタ | K37: 論理削除ＦＬＧ | AQ37: 0 | BV37: 0 | BZ37: 0
C38: T | D38: 加工単価マスタ | K38: 論理削除ユーザＩＤ | AQ38: NULL | BV38: NULL | BZ38: NULL
C39: T | D39: 加工単価マスタ | K39: 論理削除ユーザ名 | AQ39: NULL | BV39: NULL | BZ39: NULL
C40: T | D40: 加工単価マスタ | K40: 論理削除日時 | AQ40: NULL | BV40: NULL | BZ40: NULL
C41: T | D41: 加工単価マスタ | K41: 登録ユーザＩＤ | AQ41: 登録ユーザー | BV41: 登録ユーザー | BZ41: 登録ユーザー
C42: T | D42: 加工単価マスタ | K42: 登録ユーザ名 | AQ42: 登録ユーザー名 | BV42: 登録ユーザー名 | BZ42: 登録ユーザー名
C43: T | D43: 加工単価マスタ | K43: 登録日時 | AQ43: 処理日時 | BV43: 処理日時 | BZ43: 処理日時
C44: T | D44: 加工単価マスタ | K44: 登録機能ＩＤ
C45: T | D45: 加工単価マスタ | K45: 更新カウンタ | AQ45: 0 | BV45: 0 | BZ45: 0
C46: T | D46: 加工単価マスタ | K46: 更新ユーザＩＤ | AQ46: 登録ユーザー | BV46: 登録ユーザー | BZ46: 登録ユーザー
C47: T | D47: 加工単価マスタ | K47: 更新ユーザ名 | AQ47: 登録ユーザー名 | BV47: 登録ユーザー名 | BZ47: 登録ユーザー名
C48: T | D48: 加工単価マスタ | K48: 更新日時 | AQ48: 処理日時 | BV48: 処理日時 | BZ48: 処理日時
C49: T | D49: 加工単価マスタ | K49: 更新機能ＩＤ
C50: T | D50: 加工単価マスタ | K50: 更新リクエストＮＯ
A51: No | G51: 2 | H51: 加工単価マスタ | S51: ロジック名称 | AH51: 備考 | BM51: 品目区分別設定値
A52: 処理分類 | E52: 更新 | BM52: 商品 | BS52: 製品 | BW52: 中間品 | CC52: 資材 | CE52: 資材 | CG52: 原料 | CI52: その他
A53: No | C53: 転送先 | V53: 転送元 | AQ53: 説明 | BM53: 構成あり | BO53: 構成なし | BQ53: 版型 | BS53: 内 | BU53: 外 | BW53: 内 | BY53: 外 | CA53: 購買 | CC53: 在庫管理品（カートン等） | CE53: 非在庫品 | CG53: 購買 | CI53: 購買
C54: 種 | D54: オブジェクト | K54: 項目名 | V54: 種 | W54: オブジェクト | AF54: 項目名 | BM54: オブジェクト | BN54: 項目名 | BO54: オブジェクト | BP54: 項目名 | BQ54: オブジェクト | BR54: 項目名 | BS54: オブジェクト | BT54: 項目名 | BU54: オブジェクト | BV54: 項目名 | BW54: オブジェクト | BX54: 項目名 | BY54: オブジェクト | BZ54: 項目名 | CA54: オブジェクト | CB54: 項目名 | CC54: オブジェクト | CD54: 項目名 | CE54: オブジェクト | CF54: 項目名 | CG54: オブジェクト | CH54: 項目名 | CI54: オブジェクト | CJ54: 項目名
C55: T | D55: 加工単価マスタ | K55: 適用終了日 | AQ55: 固定：2099/12/31 | BV55: 処理日時-1 | BZ55: 処理日時-1
C56: T | D56: 加工単価マスタ | K56: 論理削除ＦＬＧ | AQ56: 0 | BV56: 0 | BZ56: 0
C57: T | D57: 加工単価マスタ | K57: 論理削除ユーザＩＤ | AQ57: NULL | BV57: 固定：NULL | BZ57: 固定：NULL
C58: T | D58: 加工単価マスタ | K58: 論理削除ユーザ名 | AQ58: NULL | BV58: 固定：NULL | BZ58: 固定：NULL
C59: T | D59: 加工単価マスタ | K59: 論理削除日時 | AQ59: NULL | BV59: 固定：NULL | BZ59: 固定：NULL
C60: T | D60: 加工単価マスタ | K60: 更新カウンタ | AQ60: 0 | BV60: 0 | BZ60: 0
C61: T | D61: 加工単価マスタ | K61: 更新ユーザＩＤ | AQ61: 登録ユーザー | BV61: 登録ユーザー | BZ61: 登録ユーザー
C62: T | D62: 加工単価マスタ | K62: 更新ユーザ名 | AQ62: 登録ユーザー名 | BV62: 登録ユーザー名 | BZ62: 登録ユーザー名
C63: T | D63: 加工単価マスタ | K63: 更新日時 | AQ63: 処理日時 | BV63: 処理日時 | BZ63: 処理日時
C64: T | D64: 加工単価マスタ | K64: 更新機能ＩＤ
C65: T | D65: 加工単価マスタ | K65: 更新リクエストＮＯ
A66: No | G66: 3 | H66: 加工単価マスタ | S66: ロジック名称 | AH66: 備考 | BM66: 品目区分別設定値
A67: 処理分類 | E67: 登録 | BM67: 商品 | BS67: 製品 | BW67: 中間品 | CC67: 資材 | CE67: 資材 | CG67: 原料 | CI67: その他
A68: No | C68: 転送先 | V68: 転送元 | AQ68: 説明 | BM68: 構成あり | BO68: 構成なし | BQ68: 版型 | BS68: 内 | BU68: 外 | BW68: 内 | BY68: 外 | CA68: 購買 | CC68: 在庫管理品（カートン等） | CE68: 非在庫品 | CG68: 購買 | CI68: 購買
C69: 種 | D69: オブジェクト | K69: 項目名 | V69: 種 | W69: オブジェクト | AF69: 項目名 | BM69: オブジェクト | BN69: 項目名 | BO69: オブジェクト | BP69: 項目名 | BQ69: オブジェクト | BR69: 項目名 | BS69: オブジェクト | BT69: 項目名 | BU69: オブジェクト | BV69: 項目名 | BW69: オブジェクト | BX69: 項目名 | BY69: オブジェクト | BZ69: 項目名 | CA69: オブジェクト | CB69: 項目名 | CC69: オブジェクト | CD69: 項目名 | CE69: オブジェクト | CF69: 項目名 | CG69: オブジェクト | CH69: 項目名 | CI69: オブジェクト | CJ69: 項目名
C70: T | D70: 加工単価マスタ | K70: 品目ＣＤ | V70: T | AQ70: 工程毎のダミー品目 | BU70: 品目マスタ（共通） | BV70: 品目ＣＤ | BY70: 品目マスタ（共通） | BZ70: 品目ＣＤ
C71: T | D71: 加工単価マスタ | K71: 枝番１ | V71: T | BU71: 品目マスタ（共通） | BV71: 枝番１ | BY71: 品目マスタ（共通） | BZ71: 枝番１
C72: T | D72: 加工単価マスタ | K72: 枝番２ | V72: T | BU72: 品目マスタ（共通） | BV72: 枝番２ | BY72: 品目マスタ（共通） | BZ72: 枝番２
C73: T | D73: 加工単価マスタ | K73: 枝番３ | V73: T | BU73: 品目マスタ（共通） | BV73: 枝番３ | BY73: 品目マスタ（共通） | BZ73: 枝番３
C74: T | D74: 加工単価マスタ | K74: 発注先ＣＤ | V74: 画 | W74: 加工工程マスタ | AF74: 号機/発注先 | BU74: 製品基本マスタ | BV74: 発注先 | BY74: 製品基本マスタ | BZ74: 発注先
C75: T | D75: 加工単価マスタ | K75: メーカＣＤ | AQ75: NULL | BV75: NULL | BZ75: NULL
C76: T | D76: 加工単価マスタ | K76: 単位ＣＤ | V76: 画 | W76: 加工工程マスタ | AF76: 単位 | BU76: 製品ロット別単価マスタ | BV76: 数量単位 | BY76: 製品ロット別単価マスタ | BZ76: 数量単位
C77: T | D77: 加工単価マスタ | K77: ロット数量 | V77: 画 | W77: 加工工程マスタ | AF77: 数量 | BU77: 製品ロット別単価マスタ | BV77: ロット別数量1~５ | BY77: 製品ロット別単価マスタ | BZ77: ロット別数量1~５
C78: T | D78: 加工単価マスタ | K78: 通貨ＣＤ | AQ78: JPY | BV78: JPY | BZ78: JPY
C79: T | D79: 加工単価マスタ | K79: 加工単価区分 | AQ79: 1：品目外注 | BV79: 1：品目外注 | BZ79: 1：品目外注
C80: T | D80: 加工単価マスタ | K80: 納入場所ＣＤ | AQ80: NULL | BV80: NULL | BZ80: NULL
C81: T | D81: 加工単価マスタ | K81: 納品先ＣＤ | AQ81: NULL | BV81: NULL | BZ81: NULL
C82: T | D82: 加工単価マスタ | K82: ワーキンググループＣＤ | V82: T | W82: 場所マスタ | AF82: ワーキンググループCD
C83: T | D83: 加工単価マスタ | K83: 適用開始日 | AQ83: 処理日付 | BV83: 処理日付 | BZ83: 処理日付
C84: T | D84: 加工単価マスタ | K84: 会社ＣＤ | AQ84: 固定：会社 | BV84: 固定：会社 | BZ84: 固定：会社
C85: T | D85: 加工単価マスタ | K85: 適用終了日 | AQ85: 固定：2099/12/31 | BV85: 固定：2099/12/31 | BZ85: 固定：2099/12/31
C86: T | D86: 加工単価マスタ | K86: 単価 | V86: 画 | W86: 加工工程マスタ | AF86: 仕入単価 | AQ86: 号機/発注先で判断する | BU86: 製品ロット別単価マスタ | BV86: 仕入単価1~５ | BY86: 製品加工工程マスタ | BZ86: 仕入単価
C87: T | D87: 加工単価マスタ | K87: 改定前単価 | AQ87: NULL | BU87: NULL | BV87: NULL | BZ87: NULL
C88: T | D88: 加工単価マスタ | K88: 仮単価ＦＬＧ | AQ88: 0：本単価 1:仮単価 0：本単価 | BV88: 0：本単価 1:仮単価 0：本単価 | BZ88: 0：本単価 1:仮単価 0：本単価
C89: T | D89: 加工単価マスタ | K89: 標準工数 | AQ89: NULL | BV89: NULL | BZ89: NULL
C90: T | D90: 加工単価マスタ | K90: 標準工数単価 | AQ90: NULL | BV90: NULL | BZ90: NULL
C91: T | D91: 加工単価マスタ | K91: 原価対象外ＦＬＧ | AQ91: 0：対象 1:対象外 0：対象 | BV91: 0：対象 1:対象外 0：対象 | BZ91: 0：対象 1:対象外 0：対象
C92: T | D92: 加工単価マスタ | K92: 予備単価１ | AQ92: NULL | BV92: NULL | BZ92: NULL
C93: T | D93: 加工単価マスタ | K93: 予備単価２ | AQ93: NULL | BV93: NULL | BZ93: NULL
C94: T | D94: 加工単価マスタ | K94: 予備単価３ | AQ94: NULL | BV94: NULL | BZ94: NULL
C95: T | D95: 加工単価マスタ | K95: メモ１ | AQ95: NULL | BV95: NULL | BZ95: NULL
C96: T | D96: 加工単価マスタ | K96: メモ２ | AQ96: NULL | BV96: NULL | BZ96: NULL
C97: T | D97: 加工単価マスタ | K97: メモ３ | AQ97: NULL | BV97: NULL | BZ97: NULL
C98: T | D98: 加工単価マスタ | K98: 論理削除ＦＬＧ | AQ98: 0 | BV98: 0 | BZ98: 0
C99: T | D99: 加工単価マスタ | K99: 論理削除ユーザＩＤ | AQ99: NULL | BV99: NULL | BZ99: NULL
C100: T | D100: 加工単価マスタ | K100: 論理削除ユーザ名 | AQ100: NULL | BV100: NULL | BZ100: NULL
C101: T | D101: 加工単価マスタ | K101: 論理削除日時 | AQ101: NULL | BV101: NULL | BZ101: NULL
...

Sheet 更新入出力仕様_（アドオン）事業所別原紙巾マスタ
A1: =表紙!A54 -> Webシステム | K1: 文書名 | U1: モジュールID | Z1: =表紙!$AJ$63 -> MS | AE1: モジュール名 | AJ1: =表紙!$AX$63 -> 見積管理 | AS1: 文書番号 | AZ1: Version | BF1: Rev.
K2: =表紙!O64 -> アドオン設計書 | U2: ｻﾌﾞﾓｼﾞｭｰﾙID | Z2: =表紙!$AJ$64 -> MSBB | AE2: ｻﾌﾞﾓｼﾞｭｰﾙ名 | AJ2: =表紙!$AX$64 -> Webシステム | AS2: =表紙!$BL$64 -> M7-US-1140 | AZ2: =表紙!$BU$64 -> 7.0.2 | BF2: =表紙!$CB$64 -> 8
K3: =RIGHT(CELL("filename",$A$1),LEN(CELL("filename",$A$1))-FIND("]",CELL("filename",$A$1))) -> 更新入出力仕様_（アドオン）事業所別原紙巾マスタ | U3: 表題 | Z3: =表紙!$AJ$65 -> - | AE3: =表紙!$AQ$65 -> 製品マスタ連携
A5: No | G5: 1 | H5: （アドオン）事業所別原紙巾マスタ | S5: ロジック名称 | AH5: 備考 | BP5: 品目区分別設定値 | CP5: REV4.0 商品を概要と合わせる
A6: 処理分類 | E6: 登録 | BP6: 商品 | BV6: 製品 | BZ6: 中間品 | CF6: 資材 | CH6: 資材 | CJ6: 原料 | CL6: 原料 | CN6: その他
A7: No | C7: 転送先 | V7: 転送元 | AQ7: 説明 | BP7: 構成あり | BR7: 構成なし | BT7: 版型 | BV7: 内 | BX7: 外 | BZ7: 内 | CB7: 外 | CD7: 購買 | CF7: 在庫管理品（カートン等） | CH7: 非在庫品 | CJ7: 購買 | CL7: 印刷原紙 | CN7: 購買
C8: 種 | D8: オブジェクト | K8: 項目名 | V8: 種 | W8: オブジェクト | AF8: 項目名 | BP8: オブジェクト | BQ8: 項目名 | BR8: オブジェクト | BS8: 項目名 | BT8: オブジェクト | BU8: 項目名 | BV8: オブジェクト | BW8: 項目名 | BX8: オブジェクト | BY8: 項目名 | BZ8: オブジェクト | CA8: 項目名 | CB8: オブジェクト | CC8: 項目名 | CD8: オブジェクト | CE8: 項目名 | CF8: オブジェクト | CG8: 項目名 | CH8: オブジェクト | CI8: 項目名 | CJ8: オブジェクト | CK8: 項目名 | CL8: オブジェクト | CM8: 項目名 | CN8: オブジェクト | CO8: 項目名
A9: 1 | C9: T | D9: 事業所別原紙巾マスタ | K9: WG | V9: T | W9: 製品加工工程マスタ | AQ9: 使用工程のワーキンググループ | CL9: 品目マスタ（共通） | CM9: 使用工程のワーキンググループ
B10: 2 | C10: T | D10: 事業所別原紙巾マスタ | K10: 品目ＣＤ | V10: T | AQ10: 製品基本マスタ.原紙コード＋製品基本マスタ.印刷コード＋製品基本マスタ.エンボスコード | CL10: 品目マスタ(共通) | CM10: 品目CD | CP10: Rev2.0変更 資材と原紙、版型の採番ルール変更
B11: 3 | C11: T | D11: 事業所別原紙巾マスタ | K11: 枝番１ | V11: T | W11: 品目マスタ(共通) | AF11: 枝番１ | AQ11: 坪量 | CL11: 品目マスタ(共通) | CM11: 枝番１ | CP11: Rev2.0変更 資材と原紙、版型の採番ルール変更 | DF11: REV7.0 | DJ11: 事業所別原紙巾マスタのキー見直し
B12: 4 | C12: T | D12: 事業所別原紙巾マスタ | K12: 枝番２ | V12: T | W12: 品目マスタ(共通) | AF12: 枝番２ | AQ12: 巾 | CL12: 品目マスタ(共通) | CM12: 枝番２ | CP12: Rev2.0変更 資材と原紙、版型の採番ルール変更 | DF12: REV7.0 | DJ12: 事業所別原紙巾マスタのキー見直し
B13: 5 | C13: T | D13: 事業所別原紙巾マスタ | K13: 枝番３ | V13: T | W13: 品目マスタ(共通) | AF13: 枝番３ | AQ13: 工程 | CL13: 品目マスタ(共通) | CM13: 枝番３ | CP13: Rev2.0変更 資材と原紙、版型の採番ルール変更 | DF13: REV7.0 | DJ13: 事業所別原紙巾マスタのキー見直し
B14: 6 | C14: T | D14: 事業所別原紙巾マスタ | K14: 巾 | V14: T | W14: 製品加工工程マスタ | AF14: 全般巾 | CL14: 品目マスタ（共通） | CM14: 刃渡り_巾
B15: 7 | C15: T | D15: 事業所別原紙巾マスタ | K15: 流れ(CB) | AQ15: NULL | CL15: 品目マスタ（共通） | CM15: 刃渡り_流れ
B16: 8 | C16: T | D16: 事業所別原紙巾マスタ | K16: 顧客品番 | AQ16: 固定：NULL | CM16: 固定：NULL
B17: 9 | C17: T | D17: 事業所別原紙巾マスタ | K17: 常備外 | AQ17: 固定：常備外 | CM17: 固定：常備外

Sheet 更新入出力仕様_（アドオン）原紙マスタ
A1: =表紙!A54 -> Webシステム | K1: 文書名 | U1: モジュールID | Z1: =表紙!$AJ$63 -> MS | AE1: モジュール名 | AJ1: =表紙!$AX$63 -> 見積管理 | AS1: 文書番号 | AZ1: Version | BF1: Rev.
K2: =表紙!O64 -> アドオン設計書 | U2: ｻﾌﾞﾓｼﾞｭｰﾙID | Z2: =表紙!$AJ$64 -> MSBB | AE2: ｻﾌﾞﾓｼﾞｭｰﾙ名 | AJ2: =表紙!$AX$64 -> Webシステム | AS2: =表紙!$BL$64 -> M7-US-1140 | AZ2: =表紙!$BU$64 -> 7.0.2 | BF2: =表紙!$CB$64 -> 8
K3: =RIGHT(CELL("filename",$A$1),LEN(CELL("filename",$A$1))-FIND("]",CELL("filename",$A$1))) -> 更新入出力仕様_（アドオン）原紙マスタ | U3: 表題 | Z3: =表紙!$AJ$65 -> - | AE3: =表紙!$AQ$65 -> 製品マスタ連携
A5: No | G5: 1 | H5: （アドオン）原紙マスタ | S5: ロジック名称 | AH5: 備考 | BP5: 品目区分別設定値 | CP5: REV4.0 商品を概要と合わせる
A6: 処理分類 | E6: 登録 | BP6: 商品 | BV6: 製品 | BZ6: 中間品 | CF6: 資材 | CH6: 資材 | CJ6: 原料 | CL6: 原料 | CN6: その他
A7: No | C7: 転送先 | V7: 転送元 | AQ7: 説明 | BP7: 構成あり | BR7: 構成なし | BT7: 版型 | BV7: 内 | BX7: 外 | BZ7: 内 | CB7: 外 | CD7: 購買 | CF7: 在庫管理品（カートン等） | CH7: 非在庫品 | CJ7: 購買 | CL7: 印刷原紙 | CN7: 購買
C8: 種 | D8: オブジェクト | K8: 項目名 | V8: 種 | W8: オブジェクト | AF8: 項目名 | BP8: オブジェクト | BQ8: 項目名 | BR8: オブジェクト | BS8: 項目名 | BT8: オブジェクト | BU8: 項目名 | BV8: オブジェクト | BW8: 項目名 | BX8: オブジェクト | BY8: 項目名 | BZ8: オブジェクト | CA8: 項目名 | CB8: オブジェクト | CC8: 項目名 | CD8: オブジェクト | CE8: 項目名 | CF8: オブジェクト | CG8: 項目名 | CH8: オブジェクト | CI8: 項目名 | CJ8: オブジェクト | CK8: 項目名 | CL8: オブジェクト | CM8: 項目名 | CN8: オブジェクト | CO8: 項目名
A9: 1 | C9: T | D9: 原紙マスタ | K9: 品目ＣＤ | AQ9: 製品基本マスタ.原紙コード＋製品基本マスタ.印刷コード＋製品基本マスタ.エンボスコード | CL9: 品目マスタ（共通） | CM9: 品目CD | CP9: Rev2.0変更 資材と原紙、版型の採番ルール変更
A10: 2 | C10: T | D10: 原紙マスタ | K10: 原紙ＣＤ | V10: T | W10: 原紙マスタ | AF10: 原紙ＣＤ | CL10: 原紙マスタ | CM10: 原紙ＣＤ
A11: 3 | C11: T | D11: 原紙マスタ | K11: 印刷ＣＤ | V11: T | W11: 原紙マスタ | AF11: 印刷ＣＤ | CL11: 原紙マスタ | CM11: 印刷ＣＤ
A12: 4 | C12: T | D12: 原紙マスタ | K12: エンボスＣＤ | V12: T | W12: 原紙マスタ | AF12: エンボスＣＤ | CL12: 原紙マスタ | CM12: エンボスＣＤ
A13: 5 | C13: T | D13: 原紙マスタ | K13: 坪量 | V13: T | W13: 原紙マスタ | AF13: 坪量 | AQ13: (g/㎡ ) | CL13: 原紙マスタ | CM13: 坪量
A14: 6 | C14: T | D14: 原紙マスタ | K14: 大区分 | V14: T | W14: 原紙マスタ | AF14: 大区分 | CL14: 原紙マスタ | CM14: 大区分
A15: 7 | C15: T | D15: 原紙マスタ | K15: 小区分 | V15: T | W15: 原紙マスタ | AF15: 小区分 | CL15: 原紙マスタ | CM15: 小区分
A16: 8 | C16: T | D16: 原紙マスタ | K16: ＦＳＣ区分 | V16: T | W16: 原紙マスタ | AF16: ＦＳＣ区分 | CL16: 原紙マスタ | CM16: ＦＳＣ区分
A17: 9 | C17: T | D17: 原紙マスタ | K17: ＦＳＣ製品グループ | V17: T | W17: 原紙マスタ | AF17: ＦＳＣ製品グループ | CL17: 原紙マスタ | CM17: ＦＳＣ製品グループ
A18: 10 | C18: T | D18: 原紙マスタ | K18: 種類 | V18: T | W18: 原紙マスタ | AF18: 種類 | CL18: 原紙マスタ | CM18: 種類
A19: 11 | C19: T | D19: 原紙マスタ | K19: 紙種 | V19: T | W19: 原紙マスタ | AF19: 紙種 | CL19: 原紙マスタ | CM19: 紙種
A20: 12 | C20: T | D20: 原紙マスタ | K20: 原紙印刷区分 | V20: T | W20: 原紙マスタ | AF20: 原紙印刷区分 | CM20: 印刷CDがある場合、印刷マスタの凹凸区分インキ性質区分よりセット
A21: 13 | C21: T | D21: 原紙マスタ | K21: パピエ区分 | V21: T | W21: 原紙マスタ | AF21: パピエ区分 | CM21: 原紙＋印刷＋エンボスそれぞれのﾊﾟﾋﾟｴ区分の組み合わせで判定必要。 いずれかのマスタがﾊﾟﾋﾟｴであれば1をセット
A22: 14 | C22: T | D22: 原紙マスタ | K22: エコファンシー区分 | V22: T | W22: 原紙マスタ | AF22: エコファンシー区分 | CL22: 原紙マスタ | CM22: エコファンシー区分
A23: 15 | C23: T | D23: 原紙マスタ | K23: 色区分 | V23: T | W23: 原紙マスタ | AF23: 色区分 | CL23: 原紙マスタ | CM23: 色区分
A24: 16 | C24: T | D24: 原紙マスタ | K24: 段原紙区分 | V24: T | W24: 原紙マスタ | AF24: 段原紙区分 | CL24: 原紙マスタ | CM24: 段原紙区分
A25: 17 | C25: T | D25: 原紙マスタ | K25: 古紙産廃区分 | V25: T | W25: 原紙マスタ | AF25: 古紙産廃区分 | CM25: 原紙＋印刷＋エンボスそれぞれの古紙産廃区分の組み合わせで判定必要 いずれかのマスタが2：不燃であれば 2:不燃。 いずれかが１：燃料であれば１：燃料。 その他は通常。
A26: 18 | C26: T | D26: 原紙マスタ | K26: 特注得意先区分 | V26: T | W26: 原紙マスタ | AF26: 特注得意先区分 | CL26: 原紙マスタ | CM26: 特注得意先区分
A27: 19 | C27: T | D27: 原紙マスタ | K27: 特注得意先 | V27: T | W27: 原紙マスタ | AF27: 特注得意先 | CL27: 原紙マスタ | CM27: 特注得意先
A28: 20 | C28: T | D28: 原紙マスタ | K28: 受給区分 | V28: T | W28: 原紙マスタ | AF28: 受給区分 | CL28: 原紙マスタ | CM28: 受給区分
A29: 21 | C29: T | D29: 原紙マスタ | K29: 管理区分１ | V29: T | W29: 原紙マスタ | AF29: 管理区分１ | CL29: 原紙マスタ | CM29: 管理区分１
A30: 22 | C30: T | D30: 原紙マスタ | K30: 管理区分２ | V30: T | W30: 原紙マスタ | AF30: 管理区分２ | CL30: 原紙マスタ | CM30: 管理区分２
A31: 23 | C31: T | D31: 原紙マスタ | K31: 管理区分３ | V31: T | W31: 原紙マスタ | AF31: 管理区分３ | CL31: 原紙マスタ | CM31: 管理区分３
A32: 24 | C32: T | D32: 原紙マスタ | K32: 管理区分４ | V32: T | W32: 原紙マスタ | AF32: 管理区分４ | CL32: 原紙マスタ | CM32: 管理区分４
A33: 25 | C33: T | D33: 原紙マスタ | K33: 管理区分５ | V33: T | W33: 原紙マスタ | AF33: 管理区分５ | CL33: 原紙マスタ | CM33: 管理区分５
A34: 26 | C34: T | D34: 原紙マスタ | K34: 管理区分６ | V34: T | W34: 原紙マスタ | AF34: 管理区分６ | CL34: 原紙マスタ | CM34: 管理区分６
A35: 27 | C35: T | D35: 原紙マスタ | K35: 管理区分７ | V35: T | W35: 原紙マスタ | AF35: 管理区分７ | CL35: 原紙マスタ | CM35: 管理区分７
A36: 28 | C36: T | D36: 原紙マスタ | K36: 管理区分８ | V36: T | W36: 原紙マスタ | AF36: 管理区分８ | CL36: 原紙マスタ | CM36: 管理区分８
A37: 29 | C37: T | D37: 原紙マスタ | K37: 管理区分９ | V37: T | W37: 原紙マスタ | AF37: 管理区分９ | CL37: 原紙マスタ | CM37: 管理区分９
A38: 28 | C38: T | D38: 原紙マスタ | K38: 管理区分１０ | V38: T | W38: 原紙マスタ | AF38: 管理区分１０ | CL38: 原紙マスタ | CM38: 管理区分１０
A40: No | G40: 2 | H40: （アドオン）原紙マスタ | S40: ロジック名称 | AH40: 備考 | BP40: 品目区分別設定値 | CQ40: REV3.0 原紙マスタの更新取消
A41: 処理分類 | E41: 更新 | BP41: 商品 | BV41: 製品 | BZ41: 中間品 | CF41: 資材 | CH41: 資材 | CJ41: 原料 | CL41: 原料 | CN41: その他 | CQ41: REV3.0 原紙マスタの更新取消
A42: No | C42: 転送先 | V42: 転送元 | AQ42: 説明 | BP42: 構成あり | BR42: 構成なし | BT42: 版型 | BV42: 内 | BX42: 外 | BZ42: 内 | CB42: 外 | CD42: 購買 | CF42: 在庫管理品（カートン等） | CH42: 非在庫品 | CJ42: 購買 | CL42: 印刷原紙 | CN42: 購買 | CQ42: REV3.0 原紙マスタの更新取消
C43: 種 | D43: オブジェクト | K43: 項目名 | V43: 種 | W43: オブジェクト | AF43: 項目名 | BP43: オブジェクト | BQ43: 項目名 | BR43: オブジェクト | BS43: 項目名 | BT43: オブジェクト | BU43: 項目名 | BV43: オブジェクト | BW43: 項目名 | BX43: オブジェクト | BY43: 項目名 | BZ43: オブジェクト | CA43: 項目名 | CB43: オブジェクト | CC43: 項目名 | CD43: オブジェクト | CE43: 項目名 | CF43: オブジェクト | CG43: 項目名 | CH43: オブジェクト | CI43: 項目名 | CJ43: オブジェクト | CK43: 項目名 | CL43: オブジェクト | CM43: 項目名 | CN43: オブジェクト | CO43: 項目名 | CQ43: REV3.0 原紙マスタの更新取消
A44: 2 | C44: T | D44: 原紙マスタ | K44: 大区分 | V44: 画 | W44: 登録 | AF44: 大区分 | CL44: 原紙マスタ | CM44: 大区分 | CQ44: REV3.0 原紙マスタの更新取消
A45: 3 | C45: T | D45: 原紙マスタ | K45: 小区分 | V45: 画 | W45: 登録 | AF45: 小区分 | CL45: 原紙マスタ | CM45: 小区分 | CQ45: REV3.0 原紙マスタの更新取消
A46: 4 | C46: T | D46: 原紙マスタ | K46: ＦＳＣ区分 | V46: 画 | W46: 登録 | AF46: ＦＳＣ区分 | CL46: 原紙マスタ | CM46: ＦＳＣ区分 | CQ46: REV3.0 原紙マスタの更新取消
A47: 5 | C47: T | D47: 原紙マスタ | K47: ＦＳＣ製品グループ | V47: 画 | W47: 登録 | AF47: ＦＳＣ製品グループ | CL47: 原紙マスタ | CM47: ＦＳＣ製品グループ | CQ47: REV3.0 原紙マスタの更新取消
A48: 6 | C48: T | D48: 原紙マスタ | K48: 種類 | V48: 画 | W48: 登録 | AF48: 種類 | CL48: 原紙マスタ | CM48: 種類 | CQ48: REV3.0 原紙マスタの更新取消
A49: 7 | C49: T | D49: 原紙マスタ | K49: 紙種 | V49: 画 | W49: 登録 | AF49: 紙種 | CL49: 原紙マスタ | CM49: 紙種 | CQ49: REV3.0 原紙マスタの更新取消
A50: 8 | C50: T | D50: 原紙マスタ | K50: 原紙印刷区分 | V50: 画 | W50: 登録 | AF50: 原紙印刷区分 | CM50: 印刷CDがある場合、印刷マスタの凹凸区分インキ性質区分よりセット | CQ50: REV3.0 原紙マスタの更新取消
A51: 9 | C51: T | D51: 原紙マスタ | K51: パピエ区分 | V51: 画 | W51: 登録 | AF51: パピエ区分 | CM51: 原紙＋印刷＋エンボスそれぞれのﾊﾟﾋﾟｴ区分の組み合わせで判定必要。 いずれかのマスタがﾊﾟﾋﾟｴであれば1をセット | CQ51: REV3.0 原紙マスタの更新取消
A52: 10 | C52: T | D52: 原紙マスタ | K52: エコファンシー区分 | V52: 画 | W52: 登録 | AF52: エコファンシー区分 | CL52: 原紙マスタ | CM52: エコファンシー区分 | CQ52: REV3.0 原紙マスタの更新取消
A53: 11 | C53: T | D53: 原紙マスタ | K53: 色区分 | V53: 画 | W53: 登録 | AF53: 色区分 | CL53: 原紙マスタ | CM53: 色区分 | CQ53: REV3.0 原紙マスタの更新取消
A54: 12 | C54: T | D54: 原紙マスタ | K54: 段原紙区分 | V54: 画 | W54: 登録 | AF54: 段原紙区分 | CL54: 原紙マスタ | CM54: 段原紙区分 | CQ54: REV3.0 原紙マスタの更新取消
A55: 13 | C55: T | D55: 原紙マスタ | K55: 古紙産廃区分 | V55: 画 | W55: 登録 | AF55: 古紙産廃区分 | CM55: 原紙＋印刷＋エンボスそれぞれの古紙産廃区分の組み合わせで判定必要 いずれかのマスタが2：不燃であれば 2:不燃。 いずれかが１：燃料であれば１：燃料。 その他は通常。 | CQ55: REV3.0 原紙マスタの更新取消
A56: 14 | C56: T | D56: 原紙マスタ | K56: 特注得意先区分 | V56: 画 | W56: 登録 | AF56: 特注得意先区分 | CL56: 原紙マスタ | CM56: 特注得意先区分 | CQ56: REV3.0 原紙マスタの更新取消
A57: 15 | C57: T | D57: 原紙マスタ | K57: 特注得意先 | V57: 画 | W57: 登録 | AF57: 特注得意先 | CL57: 原紙マスタ | CM57: 特注得意先 | CQ57: REV3.0 原紙マスタの更新取消
A58: 16 | C58: T | D58: 原紙マスタ | K58: 受給区分 | V58: 画 | W58: 登録 | AF58: 受給区分 | CL58: 原紙マスタ | CM58: 受給区分 | CQ58: REV3.0 原紙マスタの更新取消
A59: 17 | C59: T | D59: 原紙マスタ | K59: 管理区分１ | V59: 画 | W59: 登録 | AF59: 管理区分１ | CL59: 原紙マスタ | CM59: 管理区分１ | CQ59: REV3.0 原紙マスタの更新取消
A60: 18 | C60: T | D60: 原紙マスタ | K60: 管理区分２ | V60: 画 | W60: 登録 | AF60: 管理区分２ | CL60: 原紙マスタ | CM60: 管理区分２ | CQ60: REV3.0 原紙マスタの更新取消
A61: 19 | C61: T | D61: 原紙マスタ | K61: 管理区分３ | V61: 画 | W61: 登録 | AF61: 管理区分３ | CL61: 原紙マスタ | CM61: 管理区分３ | CQ61: REV3.0 原紙マスタの更新取消
A62: 20 | C62: T | D62: 原紙マスタ | K62: 管理区分４ | V62: 画 | W62: 登録 | AF62: 管理区分４ | CL62: 原紙マスタ | CM62: 管理区分４ | CQ62: REV3.0 原紙マスタの更新取消
A63: 21 | C63: T | D63: 原紙マスタ | K63: 管理区分５ | V63: 画 | W63: 登録 | AF63: 管理区分５ | CL63: 原紙マスタ | CM63: 管理区分５ | CQ63: REV3.0 原紙マスタの更新取消
A64: 22 | C64: T | D64: 原紙マスタ | K64: 管理区分６ | V64: 画 | W64: 登録 | AF64: 管理区分６ | CL64: 原紙マスタ | CM64: 管理区分６ | CQ64: REV3.0 原紙マスタの更新取消
A65: 23 | C65: T | D65: 原紙マスタ | K65: 管理区分７ | V65: 画 | W65: 登録 | AF65: 管理区分７ | CL65: 原紙マスタ | CM65: 管理区分７ | CQ65: REV3.0 原紙マスタの更新取消
A66: 24 | C66: T | D66: 原紙マスタ | K66: 管理区分８ | V66: 画 | W66: 登録 | AF66: 管理区分８ | CL66: 原紙マスタ | CM66: 管理区分８ | CQ66: REV3.0 原紙マスタの更新取消
A67: 25 | C67: T | D67: 原紙マスタ | K67: 管理区分９ | V67: 画 | W67: 登録 | AF67: 管理区分９ | CL67: 原紙マスタ | CM67: 管理区分９ | CQ67: REV3.0 原紙マスタの更新取消
A68: 26 | C68: T | D68: 原紙マスタ | K68: 管理区分１０ | V68: 画 | W68: 登録 | AF68: 管理区分１０ | CL68: 原紙マスタ | CM68: 管理区分１０ | CQ68: REV3.0 原紙マスタの更新取消
CQ69: REV3.0 原紙マスタの更新取消

Sheet 更新入出力仕様_品目単位マスタ
A1: =表紙!A54 -> Webシステム | K1: 文書名 | U1: モジュールID | Z1: =表紙!$AJ$63 -> MS | AE1: モジュール名 | AJ1: =表紙!$AX$63 -> 見積管理 | AS1: 文書番号 | AZ1: Version | BF1: Rev.
K2: =表紙!O64 -> アドオン設計書 | U2: ｻﾌﾞﾓｼﾞｭｰﾙID | Z2: =表紙!$AJ$64 -> MSBB | AE2: ｻﾌﾞﾓｼﾞｭｰﾙ名 | AJ2: =表紙!$AX$64 -> Webシステム | AS2: =表紙!$BL$64 -> M7-US-1140 | AZ2: =表紙!$BU$64 -> 7.0.2 | BF2: =表紙!$CB$64 -> 8
K3: =RIGHT(CELL("filename",$A$1),LEN(CELL("filename",$A$1))-FIND("]",CELL("filename",$A$1))) -> 更新入出力仕様_品目単位マスタ | U3: 表題 | Z3: =表紙!$AJ$65 -> - | AE3: =表紙!$AQ$65 -> 製品マスタ連携
A5: No | G5: 1 | H5: 品目単位マスタ | S5: ロジック名称 | AH5: 備考 | BP5: 品目区分別設定値 | CP5: REV4.0 商品を概要と合わせる
A6: 処理分類 | E6: 登録 | BP6: 商品 | BV6: 製品 | BZ6: 中間品 | CF6: 資材 | CH6: 資材 | CJ6: 原料 | CL6: 原料 | CN6: その他
A7: No | C7: 転送先 | V7: 転送元 | AQ7: 説明 | BP7: 構成あり | BR7: 構成なし | BT7: 版型 | BV7: 内 | BX7: 外 | BZ7: 内 | CB7: 外 | CD7: 購買 | CF7: 在庫管理品（カートン等） | CH7: 非在庫品 | CJ7: 購買 | CL7: 印刷原紙 | CN7: 購買
C8: 種 | D8: オブジェクト | K8: 項目名 | V8: 種 | W8: オブジェクト | AF8: 項目名 | BP8: オブジェクト | BQ8: 項目名 | BR8: オブジェクト | BS8: 項目名 | BT8: オブジェクト | BU8: 項目名 | BV8: オブジェクト | BW8: 項目名 | BX8: オブジェクト | BY8: 項目名 | BZ8: オブジェクト | CA8: 項目名 | CB8: オブジェクト | CC8: 項目名 | CD8: オブジェクト | CE8: 項目名 | CF8: オブジェクト | CG8: 項目名 | CH8: オブジェクト | CI8: 項目名 | CJ8: オブジェクト | CK8: 項目名 | CL8: オブジェクト | CM8: 項目名 | CN8: オブジェクト | CO8: 項目名
A9: 1 | C9: T | D9: 品目単位マスタ | K9: 品目ＣＤ | V9: T | W9: 品目マスタ(共通) | AF9: 品目CD | AQ9: 製品基本マスタ.原紙コード＋製品基本マスタ.印刷コード＋製品基本マスタ.エンボスコード | CL9: 品目マスタ(共通) | CM9: 品目CD | CP9: Rev3.0追加 品目単位マスタ
A10: 2 | C10: T | D10: 品目単位マスタ | K10: 枝番１ | V10: T | W10: 品目マスタ(共通) | AF10: 枝番１ | AQ10: 坪量 | CL10: 品目マスタ(共通) | CM10: 枝番１ | CP10: Rev3.0追加 品目単位マスタ
A11: 3 | C11: T | D11: 品目単位マスタ | K11: 枝番２ | V11: T | W11: 品目マスタ(共通) | AF11: 枝番２ | AQ11: 巾 | CL11: 品目マスタ(共通) | CM11: 枝番２ | CP11: Rev3.0追加 品目単位マスタ
A12: 4 | C12: T | D12: 品目単位マスタ | K12: 枝番３ | V12: T | W12: 品目マスタ(共通) | AF12: 枝番３ | AQ12: 工程 | CL12: 品目マスタ(共通) | CM12: 枝番３ | CP12: Rev3.0追加 品目単位マスタ
A13: 5 | C13: T | D13: 品目単位マスタ | K13: 単位ＣＤ | V13: T | W13: 品目単位マスタ | AF13: 単位ＣＤ | AQ13: 工程に投入している原紙の品目単位マスタを取得 | CL13: 品目単位マスタ | CM13: 単位ＣＤ | CP13: Rev3.0追加 品目単位マスタ
A14: 6 | C14: T | D14: 品目単位マスタ | K14: 換算基準数量 | V14: T | W14: 品目単位マスタ | AF14: 換算基準数量 | AQ14: 工程に投入している原紙の品目単位マスタを取得 | CL14: 品目単位マスタ | CM14: 換算基準数量 | CP14: Rev3.0追加 品目単位マスタ
A15: 7 | C15: T | D15: 品目単位マスタ | K15: 換算数量 | V15: T | W15: 品目単位マスタ | AF15: 換算数量 | AQ15: 工程に投入している原紙の品目単位マスタを取得 | CL15: 品目単位マスタ | CM15: 換算数量 | CP15: Rev3.0追加 品目単位マスタ
A16: 8 | C16: T | D16: 品目単位マスタ | K16: 小数部有効桁数 | V16: T | W16: 品目単位マスタ | AF16: 小数部有効桁数 | AQ16: 工程に投入している原紙の品目単位マスタを取得 | CL16: 品目単位マスタ | CM16: 小数部有効桁数 | CP16: Rev3.0追加 品目単位マスタ
A17: 9 | C17: T | D17: 品目単位マスタ | K17: 端数処理区分 | V17: T | W17: 品目単位マスタ | AF17: 端数処理区分 | AQ17: 工程に投入している原紙の品目単位マスタを取得 | CL17: 品目単位マスタ | CM17: 端数処理区分 | CP17: Rev3.0追加 品目単位マスタ
A18: 10 | C18: T | D18: 品目単位マスタ | K18: 荷姿ＦＬＧ | V18: T | W18: 品目単位マスタ | AF18: 荷姿ＦＬＧ | AQ18: 工程に投入している原紙の品目単位マスタを取得 | CL18: 品目単位マスタ | CM18: 荷姿ＦＬＧ | CP18: Rev3.0追加 品目単位マスタ
A19: 11 | C19: T | D19: 品目単位マスタ | K19: 梱包単位ＦＬＧ | V19: T | W19: 品目単位マスタ | AF19: 梱包単位ＦＬＧ | AQ19: 工程に投入している原紙の品目単位マスタを取得 | CL19: 品目単位マスタ | CM19: 梱包単位ＦＬＧ | CP19: Rev3.0追加 品目単位マスタ
A20: 12 | C20: T | D20: 品目単位マスタ | K20: 単位容積（ｍ３） | V20: T | W20: 品目単位マスタ | AF20: 単位容積（ｍ３） | AQ20: 工程に投入している原紙の品目単位マスタを取得 | CL20: 品目単位マスタ | CM20: 単位容積（ｍ３） | CP20: Rev3.0追加 品目単位マスタ
A21: 13 | C21: T | D21: 品目単位マスタ | K21: 単位重量（ＫＧ） | V21: T | W21: 品目単位マスタ | AF21: 単位重量（ＫＧ） | AQ21: 工程に投入している原紙の品目単位マスタを取得 | CL21: 品目単位マスタ | CM21: 単位重量（ＫＧ） | CP21: Rev3.0追加 品目単位マスタ

Sheet 補足説明資料_mcframeとのキー比較
A1: =表紙!A54 -> Webシステム | O1: 文書名 | AC1: モジュールID | AJ1: =表紙!AJ64 -> MSBB | AQ1: モジュール名 | AX1: =表紙!AX64 -> Webシステム | BL1: 文書番号 | BU1: Version | CB1: Rev.
O2: =表紙!O65 -> 表紙 | AC2: サブモジュールID | AJ2: =表紙!AJ65 -> - | AQ2: サブモジュール名 | AX2: =表紙!AX65 -> 0 | BL2: =表紙!BL65 -> 0 | BU2: =表紙!BU65 -> 0 | CB2: =表紙!CB65 -> 0
O3: =RIGHT(CELL("filename",$A$1),LEN(CELL("filename",$A$1))-FIND("]",CELL("filename",$A$1))) -> 補足説明資料_mcframeとのキー比較 | AC3: 表題 | AJ3: =表紙!AJ66 -> 0 | AQ3: =表紙!AQ66 -> 0
AO5: 補足説明
O7: 品目区分 | AU7: 品目区分説明
E8: 製品基本マスタ連携対象テーブル | O8: 商品 | S8: 製品 | AA8: 中間品 | AI8: 資材 | AM8: 原材料 | AY8: 商品：仕入直送製品
E9: テーブル | O9: 購買 | S9: 内 | W9: 外 | AA9: 内 | AE9: 外 | AI9: 在庫管理品 | AM9: 印刷コード | AQ9: 諸口 | AY9: 製品：製品
E10: 品目マスタ（共通） | S10: 〇 | AA10: 〇 | AI10: 〇 | AM10: 〇 | AY10: 中間品：工程仕掛品
E11: 品目マスタ（会社） | S11: 〇 | AA11: 〇 | AI11: 〇 | AM11: 〇 | AY11: 原材料：カートン、コートボール
E12: 品目詳細マスタ | S12: 〇 | W12: 〇 | AA12: 〇 | AE12: 〇 | AI12: 〇 | AM12: 〇 | AY12: 原材料（諸口）：梱包資材等
E13: 品目格納先マスタ | S13: 〇 | W13: 〇 | AA13: 〇 | AE13: 〇 | AI13: 〇 | AM13: 〇 | AY13: ※１ 連携処理で番号採番。番号体系は「XXXXXXX」参照
E14: BOMマスタ | S14: 〇 | AA14: 〇 | AY14: ※２ 印刷原紙とそれ以外で番号体系が異なる
E15: 品目工程マスタ | S15: 〇 | W15: 〇 | AA15: 〇 | AE15: 〇
E16: 工程工数マスタ | S16: 〇 | AA16: 〇
E17: 得意先販売単価マスタ | S17: 〇
E18: 加工単価マスタ | W18: 〇 | AE18: 〇
E19: 支給単価マスタ | W19: 〇 | AE19: 〇
E20: 購買単価マスタ | AI20: 〇 | AM20: 〇
E21: （アドオン）製品仕様マスタ | S21: 〇
E22: （アドオン）工程仕様マスタ | S22: 〇 | W22: 〇 | AA22: 〇 | AE22: 〇
E23: （アドオン）本支店単価マスタ | S23: 〇 | CJ23: REV6.0 本支店単価マスタ | CS23: REV8.0 本支店単価マスタの復活
E26: 品目マスタ（共通） | O26: 商品 | S26: 製品 | AG26: 中間品 | AT26: 原材料 | AZ26: 原材料
E27: キー項目 | O27: 購買 | S27: 内 | Z27: 外 | AG27: 内 | AN27: 外 | AT27: 購買 | BA27: 印刷原紙 | BF27: 諸口 | BI27: 備考
E28: 品目ＣＤ | S28: 製品基本マスタ.製品連番 | AG28: 製品基本マスタ.製品連番 | AT28: M＋1000000～連番 | AZ28: 製品基本マスタ.原紙コード＋ 製品基本マスタ.印刷コード＋ 製品基本マスタ.エンボスコード | CI28: Rev2.0変更 資材と原紙、版型の採番ルール変更
E29: 枝番１ | S29: 製品基本マスタ.製品枝番 | AG29: 製品基本マスタ.製品枝番
E30: 枝番２ | AG30: 製品加工工程マスタ.工程コード
E31: 枝番３
E34: 品目マスタ（会社） | O34: 商品 | S34: 製品 | AG34: 中間品 | AT34: 原材料 | AZ34: 原材料
E35: キー項目 | O35: 購買 | S35: 内 | Z35: 外 | AG35: 内 | AN35: 外 | AT35: 購買 | BA35: 印刷原紙 | BF35: 諸口 | BI35: 備考
E36: 品目ＣＤ | S36: 品目マスタ（共通）.品目CD | AG36: 品目マスタ（共通）.品目CD | AT36: 品目マスタ（共通）.品目CD | AZ36: 品目マスタ（共通）.品目CD
E37: 枝番１ | S37: 品目マスタ（共通）.枝番１ | AG37: 品目マスタ（共通）.枝番１ | AT37: 品目マスタ（共通）.枝番１ | AZ37: 品目マスタ（共通）.枝番１
E38: 枝番２ | S38: 品目マスタ（共通）.枝番２ | AG38: 品目マスタ（共通）.枝番２ | AT38: 品目マスタ（共通）.枝番2 | AZ38: 品目マスタ（共通）.枝番2
E39: 枝番３ | S39: 品目マスタ（共通）.枝番３ | AG39: 品目マスタ（共通）.枝番３ | AT39: 品目マスタ（共通）.枝番3 | AZ39: 品目マスタ（共通）.枝番3
E40: 会社ＣＤ | S40: 固定会社 | AG40: 固定会社 | AT40: 固定会社 | AZ40: 固定会社
E42: 品目詳細マスタ | O42: 商品 | S42: 製品 | AG42: 中間品 | AT42: 原材料 | AZ42: 原材料
E43: キー項目 | O43: 購買 | S43: 内 | Z43: 外 | AG43: 内 | AN43: 外 | AT43: 購買 | BA43: 印刷原紙 | BF43: 諸口 | BI43: 備考
E44: 品目ＣＤ | S44: 品目マスタ（共通）.品目CD | Z44: 品目マスタ（共通）.品目CD | AG44: 品目マスタ（共通）.品目CD | AN44: 品目マスタ（共通）.品目CD | AT44: 品目マスタ（共通）.品目CD | AZ44: 品目マスタ（共通）.品目CD
E45: 枝番１ | S45: 品目マスタ（共通）.枝番１ | Z45: 品目マスタ（共通）.枝番１ | AG45: 品目マスタ（共通）.枝番１ | AN45: 品目マスタ（共通）.枝番１ | AT45: 品目マスタ（共通）.枝番１ | AZ45: 品目マスタ（共通）.枝番１
E46: 枝番２ | S46: 品目マスタ（共通）.枝番２ | Z46: 品目マスタ（共通）.枝番２ | AG46: 品目マスタ（共通）.枝番２ | AN46: 品目マスタ（共通）.枝番２ | AT46: 品目マスタ（共通）.枝番2 | AZ46: 品目マスタ（共通）.枝番2
E47: 枝番３ | S47: 品目マスタ（共通）.枝番３ | Z47: 品目マスタ（共通）.枝番３ | AG47: 品目マスタ（共通）.枝番３ | AN47: 品目マスタ（共通）.枝番３ | AT47: 品目マスタ（共通）.枝番3 | AZ47: 品目マスタ（共通）.枝番3
E48: 製造場所ＣＤ | S48: 製品加工先マスタ.号機/発注先 AND 汎用マスタ.文字列１ ※WGの号機 | Z48: 製品加工先マスタ.号機/発注先 | AG48: 製品加工先マスタ.号機/発注先 AND 汎用マスタ.文字列１ ※WGの号機 | AN48: 製品加工先マスタ.号機/発注先 AND 汎用マスタ.文字列１ ※WGの号機 | AT48: ＊ | AZ48: ＊
E49: 発注先ＣＤ | S49: 製品加工先マスタ.号機/発注先 | Z49: 製品加工先マスタ.号機/発注先 | AG49: 製品加工先マスタ.号機/発注先 | AN49: 製品加工先マスタ.号機/発注先 | AT49: 製品加工先マスタ.号機/発注先 | AZ49: 製品加工先マスタ.号機/発注先
E50: メーカＣＤ | S50: ＊ | Z50: ＊ | AG50: ＊ | AN50: ＊ | AT50: ＊ | AZ50: ＊
E51: 依頼先場所ＣＤ | S51: ＊ | Z51: ＊ | AG51: 製品加工先マスタ.号機/発注先 | AN51: 製品加工先マスタ.号機/発注先 | AT51: ＊ | AZ51: ＊
E52: ワーキンググループＣＤ | S52: 製品加工先マスタ.ワーキンググループCD | Z52: 製品加工先マスタ.ワーキンググループCD | AG52: 製品加工先マスタ.ワーキンググループCD | AN52: 製品加工先マスタ.ワーキンググループCD | AT52: 製品加工先マスタ.ワーキンググループCD | AZ52: 製品加工先マスタ.ワーキンググループCD
E53: 構成パタン | S53: 1 | Z53: 1 | AG53: 1 | AN53: 1 | AT53: 1 | AZ53: 1
E54: 適用開始日 | S54: 処理日付 | Z54: 処理日付 | AG54: 処理日付 | AN54: 処理日付 | AT54: 処理日付 | AZ54: 処理日付
E55: 会社ＣＤ | S55: 固定会社 | Z55: 固定会社 | AG55: 固定会社 | AN55: 固定会社 | AT55: 固定会社 | AZ55: 固定会社
E58: 品目格納先マスタ | O58: 商品 | S58: 製品 | AG58: 中間品 | AT58: 原材料 | AZ58: 原材料
E59: キー項目 | O59: 購買 | S59: 内 | Z59: 外 | AG59: 内 | AN59: 外 | AT59: 購買 | BA59: 印刷原紙 | BF59: 諸口 | BI59: 備考
E60: 品目ＣＤ | S60: 品目マスタ（共通）.品目CD | Z60: 品目マスタ（共通）.品目CD | AG60: 品目マスタ（共通）.品目CD | AN60: 品目マスタ（共通）.品目CD | AT60: 品目マスタ（共通）.品目CD | AZ60: 品目マスタ（共通）.品目CD
E61: 枝番１ | S61: 品目マスタ（共通）.枝番１ | Z61: 品目マスタ（共通）.枝番１ | AG61: 品目マスタ（共通）.枝番１ | AN61: 品目マスタ（共通）.枝番１ | AT61: 品目マスタ（共通）.枝番１ | AZ61: 品目マスタ（共通）.枝番１
E62: 枝番２ | S62: 品目マスタ（共通）.枝番２ | Z62: 品目マスタ（共通）.枝番２ | AG62: 品目マスタ（共通）.枝番２ | AN62: 品目マスタ（共通）.枝番２ | AT62: 品目マスタ（共通）.枝番2 | AZ62: 品目マスタ（共通）.枝番2
E63: 枝番３ | S63: 品目マスタ（共通）.枝番３ | Z63: 品目マスタ（共通）.枝番３ | AG63: 品目マスタ（共通）.枝番３ | AN63: 品目マスタ（共通）.枝番３ | AT63: 品目マスタ（共通）.枝番3 | AZ63: 品目マスタ（共通）.枝番3
E64: 格納場所CD | S64: 汎用マスタ.文字列 | Z64: 製品加工工程マスタ.入庫先 | AG64: 汎用マスタ.文字列 | AN64: 製品加工工程マスタ.入庫先 | AT64: 製品加工工程マスタ. 入庫先 | AZ64: 汎用マスタ.文字列
E65: 会社CD | S65: 固定会社 | Z65: 固定会社 | AG65: 固定会社 | AN65: 固定会社 | AT65: 固定会社 | AZ65: 固定会社
E68: BOMマスタ | O68: 商品 | S68: 製品 | AG68: 中間品 | AT68: 原材料 | AZ68: 原材料
E69: キー項目 | O69: 購買 | S69: 内 | Z69: 外 | AG69: 内 | AN69: 外 | AT69: 購買 | BA69: 印刷原紙 | BF69: 諸口 | BI69: 備考
E70: BOMキー | S70: 自動採番 | Z70: 自動採番 | AG70: 自動採番 | AN70: 自動採番
E73: 品目工程マスタ | O73: 商品 | S73: 製品 | AG73: 中間品 | AT73: 原材料 | AZ73: 原材料
E74: キー項目 | O74: 購買 | S74: 内 | Z74: 外 | AG74: 内 | AN74: 外 | AT74: 購買 | BA74: 印刷原紙 | BF74: 諸口 | BI74: 備考
E75: 品目ＣＤ | S75: 品目マスタ（共通）.品目CD | Z75: 品目マスタ（共通）.品目CD | AG75: 品目マスタ（共通）.品目CD | AN75: 品目マスタ（共通）.品目CD
E76: 枝番１ | S76: 品目マスタ（共通）.枝番１ | Z76: 品目マスタ（共通）.枝番１ | AG76: 品目マスタ（共通）.枝番１ | AN76: 品目マスタ（共通）.枝番１
E77: 枝番２ | S77: 品目マスタ（共通）.枝番２ | Z77: 品目マスタ（共通）.枝番２ | AG77: 品目マスタ（共通）.枝番２ | AN77: 品目マスタ（共通）.枝番２
E78: 枝番３ | S78: 品目マスタ（共通）.枝番３ | Z78: 品目マスタ（共通）.枝番３ | AG78: 品目マスタ（共通）.枝番３ | AN78: 品目マスタ（共通）.枝番３
E79: 場所ＣＤ | S79: 汎用マスタ.文字列 | Z79: 製品加工工程マスタ.入庫先 | AG79: 汎用マスタ.文字列 | AN79: 製品加工工程マスタ.入庫先
E80: 工程パタン | S80: 1 | Z80: 1 | AG80: 1 | AN80: 1
E81: 工程ＣＤ | S81: 製品加工工程マスタ.作業CD | Z81: 製品加工工程マスタ.作業CD | AG81: 製品加工工程マスタ.作業CD | AN81: 製品加工工程マスタ.作業CD
E82: 工程連番 | S82: 製品加工工程マスタ.作業順 | Z82: 製品加工工程マスタ.作業順 | AG82: 製品加工工程マスタ.作業順 | AN82: 製品加工工程マスタ.作業順
E83: 適用開始日 | S83: 処理日付 | Z83: 処理日付 | AG83: 処理日付 | AN83: 処理日付
E84: 会社ＣＤ | S84: 固定会社 | Z84: 固定会社 | AG84: 固定会社 | AN84: 固定会社
E87: 工程工数マスタ | O87: 商品 | S87: 製品 | AG87: 中間品 | AT87: 原材料 | AZ87: 原材料
E88: キー項目 | O88: 購買 | S88: 内 | Z88: 外 | AG88: 内 | AN88: 外 | AT88: 購買 | BA88: 印刷原紙 | BF88: 諸口 | BI88: 備考
E89: 品目ＣＤ | S89: 品目マスタ（共通）.品目CD | AG89: 品目マスタ（共通）.品目CD
E90: 枝番１ | S90: 品目マスタ（共通）.枝番１ | AG90: 品目マスタ（共通）.枝番１
E91: 枝番２ | S91: 品目マスタ（共通）.枝番２ | AG91: 品目マスタ（共通）.枝番２
E92: 枝番３ | S92: 品目マスタ（共通）.枝番３ | AG92: 品目マスタ（共通）.枝番３
E93: 場所ＣＤ | S93: 製品加工先マスタ.号機/発注先 AND 汎用マスタ.文字列１ ※WGの号機 | AG93: 製品加工先マスタ.号機/発注先 AND 汎用マスタ.文字列１ ※WGの号機
E94: 工程パタン | S94: 1 | AG94: 1
E95: 工程ＣＤ | S95: 製品加工工程マスタ.作業CD | AG95: 製品加工工程マスタ.作業CD
E96: 工程連番 | S96: 製品加工工程マスタ.作業順 | AG96: 製品加工工程マスタ.作業順
E97: 工数管理ＣＤ | S97: 汎用マスタ.文字列 | AG97: 汎用マスタ.文字列
E98: 適用開始日 | S98: 処理日付 | AG98: 処理日付
E99: 会社ＣＤ | S99: 固定会社 | AG99: 固定会社
E102: 得意先販売単価マスタ | O102: 商品 | S102: 製品 | AG102: 中間品 | AT102: 原材料 | AZ102: 原材料
E103: キー項目 | O103: 購買 | S103: 内 | Z103: 外 | AG103: 内 | AN103: 外 | AT103: 購買 | BA103: 印刷原紙 | BF103: 諸口 | BI103: 備考
E104: 得意先ＣＤ | S104: 製品基本マスタ.得意先
E105: 納品先ＣＤ | S105: *
E106: 仕向先ＣＤ１ | S106: *
E107: 仕向先ＣＤ２ | S107: *
E108: 仕向先ＣＤ３ | S108: *
E109: 販売単価分類ＣＤ | S109: *
E110: 品目ＣＤ | S110: 品目マスタ（共通）.品目CD
E111: 枝番１ | S111: 品目マスタ（共通）.枝番１
E112: 枝番２ | S112: 品目マスタ（共通）.枝番２
E113: 枝番３ | S113: 品目マスタ（共通）.枝番３
E114: 単位ＣＤ | S114: 製品基本マスタ.数量単位
E115: ロット数量 | S115: 製品ロット別 単価マスタ.数量1~10
... E119: 会社ＣＤ | S119: 固定会社
E121: 加工単価マスタ | O121: 商品 | S121: 製品 | AG121: 中間品 | AT121: 原材料 | AZ121: 原材料
...

Sheet 補足説明資料_親子関係
A1: =表紙!A54 -> Webシステム | O1: 文書名 | AC1: モジュールID | AJ1: =表紙!AJ64 -> MSBB | AQ1: モジュール名 | AX1: =表紙!AX64 -> Webシステム | BL1: 文書番号 | BU1: Version | CB1: Rev.
O2: =表紙!O65 -> 表紙 | AC2: サブモジュールID | AJ2: =表紙!AJ65 -> - | AQ2: サブモジュール名 | AX2: =表紙!AX65 -> 0 | BL2: =表紙!BL65 -> 0 | BU2: =表紙!BU65 -> 0 | CB2: =表紙!CB65 -> 0
O3: =RIGHT(CELL("filename",$A$1),LEN(CELL("filename",$A$1))-FIND("]",CELL("filename",$A$1))) -> 補足説明資料_親子関係 | AC3: 表題 | AJ3: =表紙!AJ66 -> 0 | AQ3: =表紙!AQ66 -> 0
AO5: 補足説明
AK39: ※
AO40: 基本は1:1
AO41: ・包装、トムソン、コルゲータは工程仕様により親子関係が変動する
AO42: ・工程仕様のロス率＝歩留まり。パーセンテージを加算
AO43: ・中原紙は、段マスタに保持している段成率を加算する。（ギザギザの分、表や裏原紙よりも長いため必要量が多い）
AO44: 例 段成率：0.05 子必要量１＋0.05
H50: オフセットと刷版手配の親子関係抜粋 | CJ50: REV6.0 刷版手配の追加
CJ51: REV6.0 刷版手配の追加
Y52: 指図数 | CJ52: REV6.0 刷版手配の追加
CJ53: REV6.0 刷版手配の追加
CJ54: REV6.0 刷版手配の追加
CJ55: REV6.0 刷版手配の追加
Y56: 指図数 1,0000 刷版数:3 | CJ56: REV6.0 刷版手配の追加
CJ57: REV6.0 刷版手配の追加
CJ58: REV6.0 刷版手配の追加
CJ59: REV6.0 刷版手配の追加
CJ60: REV6.0 刷版手配の追加
CJ61: REV6.0 刷版手配の追加

Sheet 補足説明資料_荷姿区分設定
A1: =表紙!A54 -> Webシステム | O1: 文書名 | AC1: モジュールID | AJ1: =表紙!AJ64 -> MSBB | AQ1: モジュール名 | AX1: =表紙!AX64 -> Webシステム | BL1: 文書番号 | BU1: Version | CB1: Rev.
O2: =表紙!O65 -> 表紙 | AC2: サブモジュールID | AJ2: =表紙!AJ65 -> - | AQ2: サブモジュール名 | AX2: =表紙!AX65 -> 0 | BL2: =表紙!BL65 -> 0 | BU2: =表紙!BU65 -> 0 | CB2: =表紙!CB65 -> 0
O3: =RIGHT(CELL("filename",$A$1),LEN(CELL("filename",$A$1))-FIND("]",CELL("filename",$A$1))) -> 補足説明資料_荷姿区分設定 | AC3: 表題 | AJ3: =表紙!AJ66 -> 0 | AQ3: =表紙!AQ66 -> 0
AO5: 補足説明
E7: 工程の最終作業の荷姿を取得する。
E8: 汎用マスタ 分類：M040 作業マスタ キー１：作業ＣＤ で検索、数値２を取得
E9: ・数値２：4 製品区分の場合、
E10: ・製品区分で比較：
G11: 11～13：1:シート
I12: 上記以外：コートボール
E18: ・数値２：9 前工程の場合、
H19: 材料設定で荷姿が決まった前工程があるまで設定する
AK39: ※
AO40: 基本は1:1
AO41: ・包装、トムソン、コルゲータは工程仕様により親子関係が変動する
AO42: ・工程仕様のロス率＝歩留まり。パーセンテージを加算
AO43: ・中原紙は、段マスタに保持している段成率を加算する。（ギザギザの分、表や裏原紙よりも長いため必要量が多い）
AO44: 例 段成率：0.05 子必要量１＋0.05

Sheet 補足説明資料_ラベル要否設定
A1: =表紙!A54 -> Webシステム | O1: 文書名 | AC1: モジュールID | AJ1: =表紙!AJ64 -> MSBB | AQ1: モジュール名 | AX1: =表紙!AX64 -> Webシステム | BL1: 文書番号 | BU1: Version | CB1: Rev.
O2: =表紙!O65 -> 表紙 | AC2: サブモジュールID | AJ2: =表紙!AJ65 -> - | AQ2: サブモジュール名 | AX2: =表紙!AX65 -> 0 | BL2: =表紙!BL65 -> 0 | BU2: =表紙!BU65 -> 0 | CB2: =表紙!CB65 -> 0
O3: =RIGHT(CELL("filename",$A$1),LEN(CELL("filename",$A$1))-FIND("]",CELL("filename",$A$1))) -> 補足説明資料_ラベル要否設定 | AC3: 表題 | AJ3: =表紙!AJ66 -> 0 | AQ3: =表紙!AQ66 -> 0
AO5: 補足説明
E7: ラベル要否FLGの設定方法。
E8: 製品CDを元に製品加工工程マスタ、受注加工工程マスタを取得する。
E9: データに工程：仮包装、包装工程かつ作業仕様の仕様6が3:タックシールとなっている場合、
F10: 品目分類：製品品目、中間品の品目マスタ（会社）の「ラベル要否FLG」：ON
E11: それ以外の場合
F12: ラベル要否FLG：OFF

Sheet 補足説明資料_品目区分設定方法
A1: =表紙!A54 -> Webシステム | O1: 文書名 | AC1: モジュールID | AJ1: =表紙!AJ64 -> MSBB | AQ1: モジュール名 | AX1: =表紙!AX64 -> Webシステム | BL1: 文書番号 | BU1: Version | CB1: Rev.
O2: =表紙!O65 -> 表紙 | AC2: サブモジュールID | AJ2: =表紙!AJ65 -> - | AQ2: サブモジュール名 | AX2: =表紙!AX65 -> 0 | BL2: =表紙!BL65 -> 0 | BU2: =表紙!BU65 -> 0 | CB2: =表紙!CB65 -> 0
O3: =RIGHT(CELL("filename",$A$1),LEN(CELL("filename",$A$1))-FIND("]",CELL("filename",$A$1))) -> 補足説明資料_品目区分設定方法 | AC3: 表題 | AJ3: =表紙!AJ66 -> 0 | AQ3: =表紙!AQ66 -> 0
AO5: 補足説明
CJ6: V6.0 品目区分設定方法の明記
CJ7: V6.0 品目区分設定方法の明記
CJ8: V6.0 品目区分設定方法の明記
CJ9: V6.0 品目区分設定方法の明記
CJ10: V6.0 品目区分設定方法の明記
CJ11: V6.0 品目区分設定方法の明記
CJ12: V6.0 品目区分設定方法の明記
CJ13: V6.0 品目区分設定方法の明記
CJ14: V6.0 品目区分設定方法の明記
CJ15: V6.0 品目区分設定方法の明記
CJ16: V6.0 品目区分設定方法の明記
CJ17: V6.0 品目区分設定方法の明記
... CJ19: V6.0 品目区分設定方法の明記
CJ20: V6.0 品目区分設定方法の明記 | CT20: V8.0 商品・製品の印刷原紙廃止
CJ21: V6.0 品目区分設定方法の明記
CJ22: V6.0 品目区分設定方法の明記
CJ23: V6.0 品目区分設定方法の明記
CJ24: V6.0 品目区分設定方法の明記
CJ25: V6.0 品目区分設定方法の明記
CJ26: V6.0 品目区分設定方法の明記
CJ27: V6.0 品目区分設定方法の明記
CJ28: V6.0 品目区分設定方法の明記
CJ29: V6.0 品目区分設定方法の明記
CJ30: V6.0 品目区分設定方法の明記
CJ31: V6.0 品目区分設定方法の明記
CJ32: V6.0 品目区分設定方法の明記
... CJ34: V6.0 品目区分設定方法の明記
CJ35: V6.0 品目区分設定方法の明記 | CT35: V8.0 商品・製品の印刷原紙廃止
CJ36: V6.0 品目区分設定方法の明記
CJ37: V6.0 品目区分設定方法の明記
CJ38: V6.0 品目区分設定方法の明記
CJ39: V6.0 品目区分設定方法の明記
CJ40: V6.0 品目区分設定方法の明記
CJ41: V6.0 品目区分設定方法の明記
CJ42: V6.0 品目区分設定方法の明記
CJ43: V6.0 品目区分設定方法の明記
CJ44: V6.0 品目区分設定方法の明記
CJ45: V6.0 品目区分設定方法の明記
CJ46: V6.0 品目区分設定方法の明記
CJ47: V6.0 品目区分設定方法の明記
... CJ66: V6.0 品目区分設定方法の明記

Sheet メッセージ一覧
A1: =表紙!A54 -> Webシステム | K1: 文書名 | U1: モジュールID | Z1: =表紙!$AJ$63 -> MS | AE1: モジュール名 | AJ1: =表紙!$AX$63 -> 見積管理 | AS1: 文書番号 | AZ1: Version | BF1: Rev.
K2: =表紙!O64 -> アドオン設計書 | U2: ｻﾌﾞﾓｼﾞｭｰﾙID | Z2: =表紙!$AJ$64 -> MSBB | AE2: ｻﾌﾞﾓｼﾞｭｰﾙ名 | AJ2: =表紙!$AX$64 -> Webシステム | AS2: =表紙!$BL$64 -> M7-US-1140 | AZ2: =表紙!$BU$64 -> 7.0.2 | BF2: =表紙!$CB$64 -> 8
K3: =RIGHT(CELL("filename",$A$1),LEN(CELL("filename",$A$1))-FIND("]",CELL("filename",$A$1))) -> メッセージ一覧 | U3: 表題 | Z3: =表紙!$AJ$65 -> - | AE3: =表紙!$AQ$65 -> 製品マスタ連携
B6: =RIGHT(CELL("filename",B6),LEN(CELL("filename",B6))-FIND("]",CELL("filename",B6))) -> メッセージ一覧
C8: ID | G8: 説明

Sheet 補足説明資料_工程・作業とパタン
C2: 新設工程 | D2: 新仕様： 工程順を前後変更可能 ただし同じ工程は複数設定不可 | F2: 製品基本マスター **仕様一覧表** 単価欄の”必須”は自動計算しないので、入力が必要 赤色は仕様の値0はエラー | N2: 黄色は改定部分 | S2: 改定 2021/4/19 | AA2: (0) | AB2: (1) | AC2: (2) | AD2: (3) | AE2: (4) | AF2: (5) | AG2: (6) | AH2: (7) | AI2: (8)
A3: 旧CD | B3: 親工程 | C3: 新工程CD | D3: 工程名 | F3: 作業CD | G3: 作業名 | I3: 仕様1 | J3: 仕様2 | K3: 仕様3 | L3: 仕様4 | M3: 仕様5 | N3: 仕様6 | O3: 仕様7 | S3: 単価 | T3: 版ＮＯ， | U3: 備考 | V3: 外注先 | X3: 荷姿 | Y3: 所要量 | Z3: 通し数カウント対象 | AA3: 通常パタン （前工程仕掛品を投入して、加工） | AB3: 連産品（N丁取り） | AC3: 複数仕掛品を投入 （タンデム） | AD3: 購入品（都度採番）手配対象 | AE3: 外注品（都度採番） 手配対象 ※無償支給 | AF3: 消耗品（在庫管理対象外） 副資材検索対象 | AG3: 共通品目（発注点発注）を投入 | AH3: 共通品目（MRP発注）を投入 | AI3: 存在しない印刷原紙 | AJ3: 備考
A4: 20 | B4: 0020 | C4: 0020 | D4: 輪転（グラビア）1 | F4: 00201 | G4: （輪転）グラビア1 | I4: 印刷CD | J4: 印刷回数 | K4: 色数（「備考欄参照」印刷ＣＤの時の対応） | L4: ﾆｽ区分（「備考欄参照」印刷ＣＤの時の対応） | M4: ﾏｰｸ断裁（「備考欄参照」印刷ＣＤの時の対応） | X4: 原紙 | Y4: 〇 | Z4: ○ | AG4: ○ | AH4: ○ | AI4: ○
C6: 0021 | D6: 輪転（グラビア）2 | F6: 00201 | G6: （輪転）グラビア2 | I6: 印刷CD | J6: 印刷回数 | K6: 色数（「備考欄参照」印刷ＣＤの時の対応） | L6: ﾆｽ区分（「備考欄参照」印刷ＣＤの時の対応） | M6: ﾏｰｸ断裁（「備考欄参照」印刷ＣＤの時の対応） | X6: 原紙 | Y6: 〇 | Z6: ○ | AG6: ○ | AH6: ○ | AI6: ○
C8: 0022 | D8: 輪転（グラビア）3 | F8: 00201 | G8: （輪転）グラビア3 | I8: 印刷CD | J8: 印刷回数 | K8: 色数（「備考欄参照」印刷ＣＤの時の対応） | L8: ﾆｽ区分（「備考欄参照」印刷ＣＤの時の対応） | M8: ﾏｰｸ断裁（「備考欄参照」印刷ＣＤの時の対応） | X8: 原紙 | Y8: 〇 | Z8: ○ | AG8: ○ | AH8: ○ | AI8: ○
A10: 30 | B10: 0030 | C10: 0030 | D10: 輪転（フレマル）1 | F10: 00301 | G10: （輪転）フレマル1 | I10: 印刷CD | J10: 印刷回数 | K10: 色数（「備考欄参照」印刷ＣＤの時の対応） | L10: ﾆｽ区分（「備考欄参照」印刷ＣＤの時の対応） | M10: ﾏｰｸ断裁（「備考欄参照」印刷ＣＤの時の対応） | X10: 原紙 | Y10: 〇 | Z10: ○ | AG10: ○ | AH10: ○ | AI10: ○
C12: 0031 | D12: 輪転（フレマル）2 | F12: 00301 | G12: （輪転）フレマル2 | I12: 印刷CD | J12: 印刷回数 | K12: 色数（「備考欄参照」印刷ＣＤの時の対応） | L12: ﾆｽ区分（「備考欄参照」印刷ＣＤの時の対応） | M12: ﾏｰｸ断裁（「備考欄参照」印刷ＣＤの時の対応） | X12: 原紙 | Y12: 〇 | Z12: ○ | AG12: ○ | AH12: ○ | AI12: ○
C14: 0032 | D14: 輪転（フレマル）3 | F14: 00301 | G14: （輪転）フレマル3 | I14: 印刷CD | J14: 印刷回数 | K14: 色数（「備考欄参照」印刷ＣＤの時の対応） | L14: ﾆｽ区分（「備考欄参照」印刷ＣＤの時の対応） | M14: ﾏｰｸ断裁（「備考欄参照」印刷ＣＤの時の対応） | X14: 原紙 | Y14: 〇 | Z14: ○ | AG14: ○ | AH14: ○ | AI14: ○
A16: 40 | B16: 0040 | C16: 0040 | D16: エンボス1 | F16: 00401 | G16: （輪転）エンボス1 | I16: エンボスCD | J16: エンボスの深さ | K16: 水有り（加湿） | X16: 原紙 | Y16: 〇 | Z16: ○ | AA16: ○ | AG16: ○ | AH16: ○ | AI16: ○
J17: 0：普通 1：スーパー 2:Ｗスーパー | K17: 1：加湿要
C18: 0041 | D18: エンボス2 | F18: 00411 | G18: （輪転）エンボス2 | I18: エンボスCD | J18: エンボスの深さ | K18: 水有り（加湿） | X18: 原紙 | Y18: 〇 | Z18: ○ | AA18: ○ | AG18: ○ | AH18: ○ | AI18: ○
J19: 0：普通 1：スーパー 2:Ｗスーパー | K19: 1：加湿要
C20: 0042 | D20: エンボス3 | F20: 00411 | G20: （輪転）エンボス3 | I20: エンボスCD | J20: エンボスの深さ | K20: 水有り（加湿） | X20: 原紙 | Y20: 〇 | Z20: ○ | AA20: ○ | AG20: ○ | AH20: ○ | AI20: ○
J21: 0：普通 1：スーパー 2:Ｗスーパー | K21: 1：加湿要
A22: 100 | B22: 0100 | C22: 0100 | D22: 両面コルゲータ | F22: 01001 | G22: 貼合 | J22: 全判巾 | K22: 全判流れ | L22: 巾変更 | X22: シート | Y22: 〇 | Z22: ○ | AA22: ○ | AG22: ○ | AH22: ○ | AI22: ○
L23: 1:不可
F24: 01002 | G24: コルスリ | I24: 表巾 | J24: ｽﾘｯﾀｰ巾1 | K24: ｽﾘｯﾀｰ流れ1 | L24: ｽﾘｯﾀｰ巾2 | M24: ｽﾘｯﾀｰ流れ2 | N24: コルスリ | O24: 割り数 | X24: シート | Y24: 〇
N25: 1:耳落 2:半歳 3:化粧裁 4:化半
F26: 01005 | G26: エッヂプレス | I26: ｴｯﾁﾞﾌﾟﾚｽ | J26: 紙粉取り | K26: 一方積み | X26: シート
I27: 0.ナシ 1.アリ | J27: 0.ナシ 1.アリ | K27: 0.ナシ 1.アリ
F28: 01006 | G28: カットテープ | I28: センター左 ﾐﾘ | J28: センター右 ﾐﾘ | X28: シート
F30: 01010 | G30: スコアラ | I30: スコアラ寸法1 | J30: スコアラ寸法2 | K30: スコアラ寸法3 | L30: スコアラ寸法4 | M30: スコアラ寸法5 | X30: シート
A32: 100 | B32: 0110 | C32: 0110 | D32: 片面コルゲータ | F32: 01101 | G32: 貼合 | J32: 全判巾 | K32: 全判流れ | L32: 巾変更 | X32: シート | Y32: 〇 | Z32: ○ | AA32: ○ | AG32: ○ | AH32: ○
L33: 1:不可
F34: 01102 | G34: コルスリ | I34: 表巾 | J34: ｽﾘｯﾀｰ巾1 | K34: ｽﾘｯﾀｰ流れ1 | L34: ｽﾘｯﾀｰ巾2 | M34: ｽﾘｯﾀｰ流れ2 | N34: コルスリ | O34: 割り数 | X34: シート | Y34: 〇
N35: 1:耳落 2:半歳 3:化粧裁 4:化半
A36: 不要 | F36: 130 | G36: 基版代 | H36: 表
A37: 不要 | F37: 140 | G37: 基版代 | H37: 裏
A38: 150 | B38: 0150 | C38: 0150 | D38: スリッター | F38: 01501 | G38: スリッター | I38: 割り数 | J38: 巾 | K38: 流れ | X38: シート | Y38: 〇 | AA38: ○
F40: 01502 | G40: 原紙輪切り | I40: 割り数 | J40: 巾 | K40: 流れ | X40: 原紙 | Y40: 〇
C42: 0151 | D42: スリッター2 | F42: 01511 | G42: スリッター | I42: 割り数 | J42: 巾 | K42: 流れ | X42: シート | Y42: 〇 | Z42: ○ | AA42: ○
F44: 01512 | G44: 原紙輪切り | I44: 割り数 | J44: 巾 | K44: 流れ | X44: 原紙 | Y44: 〇
C46: 0152 | D46: スリッター3 | F46: 01521 | G46: スリッター | I46: 割り数 | J46: 巾 | K46: 流れ | X46: シート | Y46: 〇 | Z46: ○ | AA46: ○
F48: 01522 | G48: 原紙輪切り | I48: 割り数 | J48: 巾 | K48: 流れ | X48: 原紙 | Y48: 〇
A50: 160 | B50: 0160 | C50: 0160 | D50: パット | F50: 01601 | G50: パット | I50: 附数 | J50: 巾 | K50: 流れ | L50: 罫線 | M50: 巾 | N50: 箱の流れ | O50: アシ | X50: シート | Y50: 〇
L51: 0.ナシ アリは本数
B52: 0170 | C52: 0170 | D52: 反転機 | F52: 01701 | G52: 反転機 | I52: 枚数 | J52: 方向 | X52: シート | Y52: 前工程 | Z52: ○ | AA52: ○
J53: 1.裏上一方 2.表上一方
A54: 180 | C54: 0180 | D54: エッヂプレス | F54: 01801 | G54: エッヂプレス | I54: ｴｯﾁﾞﾌﾟﾚｽ | J54: 紙粉取り | K54: 一方積み
I55: 0.ナシ 1.アリ | J55: 0.ナシ 1.アリ | K55: 0.ナシ 1.アリ
A56: 190 | B56: 0190 | C56: 0190 | D56: パイルターナー | F56: 01901 | G56: パイルターナー | I56: ﾊﾟｲﾙ | X56: 前工程による | Y56: 前工程 | Z56: ○ | AA56: ○
I57: 0.ナシ 1.アリ
A58: 200 | B58: 0200 | C58: 0200 | D58: コートボール手配（表） | F58: 02001 | G58: ｺｰﾄﾎﾞｰﾙ手配 | H58: 表 | I58: 巾 | J58: 流れ | K58: 目なり | L58: 連量 | M58: ＠ | N58: 単位 | O58: 特スキ | X58: ｺｰﾄﾎﾞｰﾙ | Y58: 〇 | AG58: ○
K59: 1.縦目 2.横目
F60: 02002 | G60: ｺｰﾄﾎﾞｰﾙ断裁 | H60: 表 | I60: 巾 | J60: 流れ | X60: ｺｰﾄﾎﾞｰﾙ | Y60: 〇
A62: 260 | C62: 0201 | D62: コートボール手配（中） | F62: 02101 | G62: ｺｰﾄﾎﾞｰﾙ手配 | H62: 中 | I62: 巾 | J62: 流れ | K62: 目なり | L62: 連量 | M62: ＠ | N62: 単位 | O62: 特スキ | X62: ｺｰﾄﾎﾞｰﾙ | Y62: 〇 | AG62: ○
K63: 1.縦目 2.横目
F64: 02102 | G64: ｺｰﾄﾎﾞｰﾙ断裁 | H64: 中 | I64: 巾 | J64: 流れ | X64: ｺｰﾄﾎﾞｰﾙ | Y64: 〇
A66: 280 | C66: 0202 | D66: コートボール手配（裏） | F66: 02201 | G66: ｺｰﾄﾎﾞｰﾙ手配 | H66: 裏 | I66: 巾 | J66: 流れ | K66: 目なり | L66: 連量 | M66: ＠ | N66: 単位 | O66: 特スキ | X66: ｺｰﾄﾎﾞｰﾙ | Y66: 〇 | AG66: ○
K67: 1.縦目 2.横目
F68: 02202 | G68: ｺｰﾄﾎﾞｰﾙ断裁 | H68: 裏 | I68: 巾 | J68: 流れ | X68: ｺｰﾄﾎﾞｰﾙ | Y68: 〇
A70: 不要 | C70: 0280 | D70: 紙粉除去 | F70: 02801 | G70: 紙粉除去
A72: 300 | B72: 0300 | C72: 0300 | D72: フレキソ印刷 | F72: 03001 | G72: 製品情報 | I72: 原稿 | J72: ｸﾚｰﾑ情報 | K72: ｸﾚｰﾑ対象工程 | X72: シート
I73: 0.ﾅｼ 1.原稿袋 | J73: 0.ﾅｼ 1.ｱﾘ | K73: 1.ＡＬＬ 2.備考欄
I74: 2.図面ｼｽﾃﾑ
F75: 03002 | G75: フレキソ印刷（表） | I75: 色数 | J75: ﾍﾞﾀ 金銀 | K75: ﾆｽ | L75: 抗菌ニス・抗ウイルスニス | M75: ﾇﾘﾀｼ | X75: シート | Y75: 〇 | Z75: ○ | AA75: ○
J76: 割増% | K76: ０．ナシ 1.ﾆｽ 2.撥水ﾆｽ 3.ｼｯｸﾄｰﾝ | L76: 1.抗菌柄 2.抗菌ベタ 3.抗ウイルス柄 4.抗ウイルスベタ | M76: 0.ﾅｼ1.ｱﾘ
A77: 301 | C77: 0301 | D77: フレキソ印刷(2) | F77: 03011 | G77: 製品情報 | I77: 原稿 | J77: ｸﾚｰﾑ情報 | K77: ｸﾚｰﾑ対象工程 | X77: シート
I78: 0.ﾅｼ 1.原稿袋 | J78: 0.ﾅｼ 1.ｱﾘ | K78: 1.ＡＬＬ 2.備考欄
I79: 2.図面ｼｽﾃﾑ
F80: 03011 | G80: フレキソ印刷（2度目) | I80: 色数 | J80: ﾍﾞﾀ 金銀 | K80: ﾆｽ | L80: 抗菌ニス・抗ウイルスニス | M80: ﾇﾘﾀｼ | X80: シート | Y80: 〇 | Z80: ○ | AA80: ○
J81: 割増% | K81: ０．ナシ 1.ﾆｽ 2.撥水ﾆｽ 3.ｼｯｸﾄｰﾝ | L81: 1.抗菌柄 2.抗菌ベタ 3.抗ウイルス柄 4.抗ウイルスベタ | M81: 0.ﾅｼ1.ｱﾘ
A82: 302 | C82: 0302 | D82: フレキソ印刷(3) | F82: 03021 | G82: 製品情報 | I82: 原稿 | J82: ｸﾚｰﾑ情報 | K82: ｸﾚｰﾑ対象工程 | X82: シート
I83: 0.ﾅｼ 1.原稿袋 | J83: 0.ﾅｼ 1.ｱﾘ | K83: 1.ＡＬＬ 2.備考欄
I84: 2.図面ｼｽﾃﾑ
F85: 03021 | G85: フレキソ印刷（3度目) | I85: 色数 | J85: ﾍﾞﾀ 金銀 | K85: ﾆｽ | L85: 抗菌ニス・抗ウイルスニス | M85: ﾇﾘﾀｼ | X85: シート | Y85: 〇 | AA85: ○
J86: 割増% | K86: ０．ナシ 1.ﾆｽ 2.撥水ﾆｽ 3.ｼｯｸﾄｰﾝ | L86: 1.抗菌柄 2.抗菌ベタ 3.抗ウイルス柄 4.抗ウイルスベタ | M86: 0.ﾅｼ1.ｱﾘ
A87: 310 | C87: 0310 | D87: フレキソ印刷(裏) | F87: 03031 | G87: 製品情報 | I87: 原稿 | J87: ｸﾚｰﾑ情報 | K87: ｸﾚｰﾑ対象工程 | X87: シート
I88: 0.ﾅｼ 1.原稿袋 | J88: 0.ﾅｼ 1.ｱﾘ | K88: 1.ＡＬＬ 2.備考欄
I89: 2.図面ｼｽﾃﾑ
F90: 03031 | G90: フレキソ印刷（裏) | I90: 色数 | J90: ﾍﾞﾀ 金銀 | K90: ﾆｽ | L90: 抗菌ニス・抗ウイルスニス | M90: ﾇﾘﾀｼ | X90: シート | Y90: 〇 | Z90: ○ | AA90: ○
J91: 割増% | K91: ０．ナシ 1.ﾆｽ 2.撥水ﾆｽ 3.ｼｯｸﾄｰﾝ | L91: 1.抗菌柄 2.抗菌ベタ 3.抗ウイルス柄 4.抗ウイルスベタ | M91: 0.ﾅｼ1.ｱﾘ
A92: 310 | C92: 0311 | D92: フレキソ印刷(裏2) | F92: 03031 | G92: 製品情報 | I92: 原稿 | J92: ｸﾚｰﾑ情報 | K92: ｸﾚｰﾑ対象工程 | X92: シート
I93: 0.ﾅｼ 1.原稿袋 | J93: 0.ﾅｼ 1.ｱﾘ | K93: 1.ＡＬＬ 2.備考欄
I94: 2.図面ｼｽﾃﾑ
F95: 03031 | G95: フレキソ印刷（裏2) | I95: 色数 | J95: ﾍﾞﾀ 金銀 | K95: ﾆｽ | L95: 抗菌ニス・抗ウイルスニス | M95: ﾇﾘﾀｼ | X95: シート | Y95: 〇 | Z95: ○
J96: 割増% | K96: ０．ナシ 1.ﾆｽ 2.撥水ﾆｽ 3.ｼｯｸﾄｰﾝ | L96: 1.抗菌柄 2.抗菌ベタ 3.抗ウイルス柄 4.抗ウイルスベタ | M96: 0.ﾅｼ1.ｱﾘ
A97: 350 | B97: 0350 | C97: 0350 | D97: 段ボール印刷1 | F97: 03501 | G97: 段ボール印刷1 | I97: 色数 | J97: 区分 1.ﾌﾚｷｿ | K97: ｹﾝﾄｳ | L97: 面付数 | M97: ﾍﾞﾀ | N97: 特色 | X97: シート | Y97: 〇 | Z97: ○ | AA97: ○
J98: 2.ﾘﾝﾃﾞﾝ 3.ｼﾙｸ | K98: 0.ﾅｼ 1.ｱﾘ | N98: 0.ナシ 1.アリ
A99: 360 | C99: 0360 | D99: 段ボール印刷2 | F99: 03601 | G99: 段ボール印刷2 | I99: 色数 | J99: 区分 1.ﾌﾚｷｿ | K99: ｹﾝﾄｳ | L99: 面付数 | M99: ﾍﾞﾀ | N99: 特色 | X99: シート | Y99: 〇 | Z99: ○ | AA99: ○
J100: 2.ﾘﾝﾃﾞﾝ 3.ｼﾙｸ | K100: 0.ﾅｼ 1.ｱﾘ | N100: 0.ナシ 1.アリ
A101: 不要 | F101: 06001 | G101: 枚葉グラビア印刷 | I101: 色数 | J101: 版
J102: 0:ﾅｼ 1:ｱﾘ
A103: 400 | C103: 0400 | D103: スクリーン印刷 | F103: 04001 | G103: スクリーン印刷 | I103: 色数 | X103: シート | Y103: 〇 | Z103: ○ | AA103: ○
S104: 必須
A105: 440 | B105: 0440 | C105: 0440 | D105: 刷版手配(表) | F105: 04401 | G105: 刷版手配(表) | I105: 寸法 1.K | J105: 版作成 | K105: 面付数 | L105: 版数 | M105: 抜きｽﾞﾚ防止ﾏｰｸ | N105: 面付番号 | O105: 混入防止ﾏｰｸ | X105: 購買品
I106: 2.Ａ 3.L | J106: 0:ﾌｨﾙﾑ 1:ＣＴＰ | M106: 1.要 2.不可 | N106: 1.要 2.不可 | O106: 1.要 2不可
A107: 440 | C107: 0441 | D107: 刷版手配(裏) | F107: 04411 | G107: 刷版手配(裏) | I107: 寸法 1.K | J107: 版作成 | K107: 面付数 | L107: 版数 | M107: 抜きｽﾞﾚ防止ﾏｰｸ | N107: 面付番号 | O107: 混入防止ﾏｰｸ | X107: 購買品
I108: 2.Ａ 3.L | J108: 0:ﾌｨﾙﾑ 1:ＣＴＰ | M108: 1.要 2.不可 | N108: 1.要 2.不可 | O108: 1.要 2不可
A109: 450 | B109: 0450 | C109: 0450 | D109: オフセット印刷1 | F109: 04501 | G109: 製品情報 | I109: 原稿 | J109: ｸﾚｰﾑ情報 | K109: ｸﾚｰﾑ対象工程 | X109: シート
I110: 0.ﾅｼ 1.原稿袋 | J110: 0.ﾅｼ 1.ｱﾘ | K110: 1.ＡＬＬ 2.備考欄
I111: 2.図面ｼｽﾃﾑ
F112: 04502 | G112: オフセット印刷 | I112: 色数 | J112: 色数割増 | K112: 特色数 | L112: ｲﾝｷ区分 | M112: 針先 | X112: シート | Y112: 〇 | Z112: ○ | AA112: ○
L113: 1.油性 2.ﾊｲﾌﾞﾘｯﾄﾞ
L114: 3.ＵＶ 4.油性耐光 | M114: 1.突 2.引
L115: 5.HB耐光 6.UV耐光
F117: 04503 | G117: ニス | I117: 壺ﾆｽ | J117: ｺｰﾀｰﾆｽ | K117: ｽﾎﾟｯﾄ | X117: シート | AF117: ○
I118: 2.ﾏｯﾄ 3.OP 4:UVMOP | J118: 1.水性 2.ﾏｯﾄ | K118: 0.無し
I119: 5:UVOP 6.ｱｸｱﾆｽ 9 | J119: 4.UVｸﾘｱ 6.ﾌﾟﾚｽﾆｽ | K119: 1有り
I120: 7.抗菌ニス 8.抗ウイルスニス | J120: 7.抗菌ニス 8.抗ウイルスニス | K120: 2.ｱｸｱｴﾝﾎﾞｽ
...

Sheet 品目区分設定方法
A4: 品目区分・品目区分詳細の設定方法
B9: 1.最終工程の場合
B10: 製品加工工程マスタの並び順が最大値の工程
B12: 汎用マスタ：M036 受注区分 | E12: 汎用マスタ：M030 製品区分 | H12: 汎用マスタ：品目区分・品目詳細区分 取得予定
B13: 受注区分 | C13: 受注区分名 | E13: 製品区分(大) | F13: 製品区分大名 | H13: 受注区分 | I13: 受注区分名 | J13: 製品区分大 | K13: 製品区分大名 | L13: 品目区分 | M13: 品目区分名 | N13: 品目区分詳細ＣＤ | O13: 標準品目区分詳細名 | P13: 登録画面
H14: 21 | I14: シート商品 | J14: 11 | K14: シート | L14: 1(固定値) | M14: 商品 | N14: 111 | O14: 商品シート | P14: 受注
B15: 10 | C15: 加工製品 | E15: 11 | F15: シート | H15: 21 | I15: シート商品 | J15: 12 | K15: 加工 | L15: 1(固定値) | M15: 商品 | N15: 112 | O15: 商品加工 | P15: 製品マスタ
B16: 11 | C16: 加工商品 | E16: 12 | F16: 加工 | H16: 11 | I16: 加工商品 | J16: 13 | K16: Ｇプリント | L16: 1(固定値) | M16: 商品 | N16: 113 | O16: 商品Ｇプリント | P16: 製品マスタ
B17: 20 | C17: シート製品 | E17: 13 | F17: Ｇプリント | H17: 11 | I17: 加工商品 | J17: 21 | K17: 巻ボール | L17: 1(固定値) | M17: 商品 | N17: 121 | O17: 商品巻ボール | P17: 製品マスタ
B18: 21 | C18: シート商品 | E18: 21 | F18: 巻ボール | H18: 21 | I18: シート商品 | J18: 22 | K18: 片面シート | L18: 1(固定値) | M18: 商品 | N18: 122 | O18: 商品片面シート | P18: 製品マスタ
B19: 30 | C19: 購買品 | E19: 22 | F19: 片面シート | H19: 11 | I19: 加工商品 | J19: 23 | K19: 片面加工 | L19: 1(固定値) | M19: 商品 | N19: 123 | O19: 商品片面加工 | P19: 製品マスタ
B20: 40 | C20: 原紙 | E20: 23 | F20: 片面加工 | H20: 11 | I20: 加工商品 | J20: 31 | K20: プリフル | L20: 1(固定値) | M20: 商品 | N20: 131 | O20: 商品プリフル | P20: 製品マスタ
E21: 31 | F21: プリフル | H21: 11 | I21: 加工商品 | J21: 32 | K21: 刷本支給 | L21: 1(固定値) | M21: 商品 | N21: 132 | O21: 商品刷本支給 | P21: 製品マスタ
E22: 32 | F22: 刷本支給 | H22: 40 | I22: 原紙 | J22: 33 | K22: コートボール | L22: 1(固定値) | M22: 商品 | N22: 133 | O22: 商品コートボール | P22: 品目マスタ | Q22: 諸口品目で事前登録
E23: 33 | F23: コートボール | H23: 40 | I23: 原紙 | J23: 41 | K23: 生原紙 | L23: 1(固定値) | M23: 商品 | N23: 141 | O23: 商品原紙 | P23: 品目マスタ | Q23: 諸口品目で事前登録
E24: 41 | F24: 生原紙 | H24: 40 | I24: 原紙 | J24: 42 | K24: 印刷原紙 | L24: 1(固定値) | M24: 商品 | N24: 142 | O24: 商品印刷原紙 | P24: 品目マスタ | Q24: 諸口品目で事前登録
E25: 42 | F25: 印刷原紙 | H25: 30 | I25: 購買品 | J25: 61 | K25: 版・型 | L25: 1(固定値) | M25: 商品 | N25: 161 | O25: 版型 | P25: 版型マスタ自動
E26: 43 | F26: 巻取り原紙 | H26: 30 | I26: 購買品 | J26: 51 | K26: 外装シート | L26: 1(固定値) | M26: 商品 | N26: 151 | O26: 外装シート | P26: 品目マスタ | Q26: 諸口品目で事前登録
E27: 51 | F27: 外装シート | H27: 30 | I27: 購買品 | J27: 52 | K27: 外装ケース | L27: 1(固定値) | M27: 商品 | N27: 152 | O27: 外装ケース | P27: 品目マスタ | Q27: 諸口品目で事前登録
E28: 52 | F28: 外装ケース | H28: 30 | I28: 購買品 | J28: 71 | K28: 袋 | L28: 1(固定値) | M28: 商品 | N28: 171 | O28: 袋 | P28: 品目マスタ | Q28: 諸口品目で事前登録
E29: 61 | F29: 版・型 | H29: 30 | I29: 購買品 | J29: 83 | K29: モールド | L29: 1(固定値) | M29: 商品 | N29: 183 | O29: モールド | P29: 品目マスタ | Q29: 諸口品目で事前登録
E30: 62 | F30: その他 | H30: 30 | I30: 購買品 | J30: 62 | K30: その他 | L30: 1(固定値) | M30: 商品 | N30: 190 | O30: 商品その他 | P30: 品目マスタ | Q30: 諸口品目で事前登録
E31: 63 | F31: デザイン代 | H31: 20 | I31: シート製品 | J31: 11 | K31: シート | L31: 2(固定値) | M31: 製品 | N31: 211 | O31: シート | P31: 受注
E32: 71 | F32: 袋 | H32: 10 | I32: 加工製品 | J32: 12 | K32: 加工 | L32: 2(固定値) | M32: 製品 | N32: 212 | O32: 加工 | P32: 製品マスタ
E33: 81 | F33: 運賃 | H33: 10 | I33: 加工製品 | J33: 13 | K33: Ｇプリント | L33: 2(固定値) | M33: 製品 | N33: 213 | O33: Ｇプリント | P33: 製品マスタ
E34: 83 | F34: モールド | H34: 10 | I34: 加工製品 | J34: 21 | K34: 巻ボール | L34: 2(固定値) | M34: 製品 | N34: 221 | O34: 巻ボール | P34: 製品マスタ
E35: 91 | F35: 資材料 | H35: 20 | I35: シート製品 | J35: 22 | K35: 片面シート | L35: 2(固定値) | M35: 製品 | N35: 222 | O35: 片面シート | P35: 受注
E36: 92 | F36: 前加工料 | H36: 10 | I36: 加工製品 | J36: 23 | K36: 片面加工 | L36: 2(固定値) | M36: 製品 | N36: 223 | O36: 片面加工 | P36: 製品マスタ
H37: 10 | I37: 加工製品 | J37: 31 | K37: プリフル | L37: 2(固定値) | M37: 製品 | N37: 231 | O37: プリフル | P37: 製品マスタ
H38: 10 | I38: 加工製品 | J38: 32 | K38: 刷本支給 | L38: 2(固定値) | M38: 製品 | N38: 232 | O38: 刷本支給 | P38: 製品マスタ
H39: 40 | I39: 原紙 | J39: 33 | K39: コートボール | L39: 2(固定値) | M39: 製品 | N39: 233 | O39: コートボール製品 | P39: 製品マスタ
H40: 40 | I40: 原紙 | J40: 42 | K40: 印刷原紙 | L40: 2(固定値) | M40: 製品 | N40: 242 | O40: 印刷原紙 | P40: 製品マスタ
B43: 2.最終工程以外の場合
C44: 2-1.工程
C45: 製品加工材料マスタの工程材料区分が１：工程（仕掛品）、２：連産品
C46: 荷姿区分と工程より判断する。荷姿区分の設定は荷姿区分設定参照。
E48: 荷姿区分 | I48: 工程と荷姿区分と品目区分の関係
E49: 荷姿区分 | F49: 荷姿区分名 | I49: 親工程 | J49: 親工程名 | K49: 荷姿区分 | L49: 荷姿区分名 | M49: 品目区分 | N49: 品目区分名 | O49: 品目区分詳細ＣＤ | P49: 標準品目区分詳細名 | Q49: 登録画面
E50: 0：原紙 | F50: 0：原紙 | I50: - | J50: - | K50: 1 | L50: シート | M50: 3(固定値) | N50: 中間品 | O50: 301 | P50: 仕掛シート | Q50: 製品マスタ
E51: 1 | F51: シート | I51: - | J51: - | K51: 2 | L51: コートボール | M51: 3(固定値) | N51: 中間品 | O51: 301 | P51: 仕掛シート | Q51: 製品マスタ
E52: 2 | F52: コートボール | I52: - | J52: - | K52: 3 | L52: 購買品 | M52: 5(固定値) | N52: 資材 | O52: 500 | P52: 消耗品 | Q52: 製品マスタ
E53: 3 | F53: 購買品 | I53: - | J53: - | K53: 5 | L53: 合紙 | M53: 3(固定値) | N53: 中間品 | O53: 301 | P53: 仕掛シート | Q53: 製品マスタ
E54: 4 | F54: 製品区分による | I54: - | J54: - | K54: 6 | L54: ブランクス | M54: 3(固定値) | N54: 中間品 | O54: 302 | P54: ブランクス | Q54: 製品マスタ
E55: 5 | F55: 合紙 | I55: - | J55: - | K55: 8 | L55: グルア後 | M55: 3(固定値) | N55: 中間品 | O55: 303 | P55: グルア | Q55: 製品マスタ
E56: 6 | F56: ブランクス | I56: 0820 | J56: テーパー | K56: - | L56: - | M56: 3(固定値) | N56: 中間品 | O56: 304 | P56: テーパ | Q56: 製品マスタ
E57: 7 | F57: カートン入れ | I57: 0160 | J57: パット | K57: - | L57: - | M57: 3(固定値) | N57: 中間品 | O57: 305 | P57: パット | Q57: 製品マスタ
E58: 8 | F58: グルア後 | I58: 0940 | J58: カートン手配 | M58: 5(固定値) | N58: 資材 | O58: 501 | P58: カートン | Q58: 製品マスタ
E59: 9 | F59: 前工程
C65: 2-2.印刷原紙
C66: 製品加工材料マスタの工程材料区分が4:印刷原紙原紙
M70: 品目区分 | N70: 品目区分名 | O70: 品目区分詳細ＣＤ | P70: 標準品目区分詳細名 | Q70: 登録画面
M71: 6(固定値) | N71: 原料 | O71: 600 | P71: 印刷原紙 | Q71: 製品マスタ（工程付）、原紙マスタ
M72: 6(固定値) | N72: 原料 | O72: 601 | P72: 生原紙 | Q72: 原紙マスタ
M73: 6(固定値) | N73: 原料 | O73: 602 | P73: 支給原紙 | Q73: 原紙マスタ
M74: 6(固定値) | N74: 原料 | O74: 602 | P74: テスト原紙 | Q74: 原紙マスタ
M75: 6(固定値) | N75: 原料 | O75: 603 | P75: コートボール | Q75: 原紙マスタ

Sheet 画面遷移
A1: =表紙!A54 -> Webシステム | K1: 文書名 | U1: モジュールID | Z1: =表紙!$AJ$63 -> MS | AE1: モジュール名 | AJ1: =表紙!$AX$63 -> 見積管理 | AS1: 文書番号 | AZ1: Version | BF1: Rev.
K2: =表紙!O64 -> アドオン設計書 | U2: ｻﾌﾞﾓｼﾞｭｰﾙID | Z2: =表紙!$AJ$64 -> MSBB | AE2: ｻﾌﾞﾓｼﾞｭｰﾙ名 | AJ2: =表紙!$AX$64 -> Webシステム | AS2: =表紙!$BL$64 -> M7-US-1140 | AZ2: =表紙!$BU$64 -> 7.0.2 | BF2: =表紙!$CB$64 -> 8
K3: =RIGHT(CELL("filename",$A$1),LEN(CELL("filename",$A$1))-FIND("]",CELL("filename",$A$1))) -> 画面遷移 | U3: 表題 | Z3: =表紙!$AJ$65 -> - | AE3: =表紙!$AQ$65 -> 製品マスタ連携
A5: ID | D5: 処理名 | Y5: ダブルクリック対象 | AH5: ダブルクリック処理条件
A6: S01 | D6: 販売納期調整登録
B8: 遷移処理
B9: 遷移先画面ＩＤ | I9: MSBBP1230
B10: 遷移先画面名 | I10: 販売納期調整登録
B11: 遷移条件 | I11: 登録後、訂正後、検索後に押下可能
B12: 引継項目・種別 | I12: 遷移元画面項目 | AJ12: 遷移先画面項目
I13: 受注ＮＯ | AJ13: 受注ＮＯ
AJ14: 操作種別：「登録・訂正する」
B15: 遷移後のアクション | I15: 検索
A17: ID | D17: 処理名 | Y17: ダブルクリック対象 | AH17: ダブルクリック処理条件
A18: S02 | D18: 在庫情報選択
B20: 遷移処理
B21: 遷移先画面ＩＤ | I21: MSBEP0500
B22: 遷移先画面名 | I22: 在庫情報選択
B23: 遷移条件 | I23: フォーカス行の品目が在庫品の場合に押下可能。また、打切がオフ、削除行でない、場所が変更可能な場合に押下可能
B24: 引継項目・種別 | I24: 遷移元画面項目 | AJ24: 遷移先画面項目
I25: 品目 | AJ25: 品目
I26: 枝番１ | AJ26: 枝番１
I27: 枝番２ | AJ27: 枝番２
I28: 枝番３ | AJ28: 枝番３
I29: 品名 | AJ29: 品名
I30: 版ＮＯ | AJ30: 版ＮＯ
I31: 格付 | AJ31: 格付
I32: 格付名 | AJ32: 格付名
I33: 総量引当場所Ｇ | AJ33: 総量引当場所Ｇ
I34: 総量引当場所Ｇ名 | AJ34: 総量引当場所Ｇ名
I35: 物流Ｇ | AJ35: 物流Ｇ
I36: 物流Ｇ名 | AJ36: 物流Ｇ名
... I42: 手配ＮＯ４ | AJ42: 手配ＮＯ４
B43: 遷移後のアクション | I43: 検索
B45: 復帰処理
B46: 引継項目 | I46: 遷移元画面項目 | AJ46: 遷移先画面項目
I47: 品目 | AJ47: 品目
I48: 枝番１ | AJ48: 枝番１
I49: 枝番２ | AJ49: 枝番２
I50: 枝番３ | AJ50: 枝番３
I51: 格付 | AJ51: 格付
I52: ロットＮＯ | AJ52: ロットＮＯ
I53: サブロットＮＯ | AJ53: サブロットＮＯ
I54: 版ＮＯ | AJ54: 版ＮＯ
I55: 総量引当場所G | AJ55: 総量引当場所G
I56: 物流Ｇ | AJ56: 物流Ｇ
I57: 場所 | AJ57: 場所
I58: 手配ＮＯ１ | AJ58: 手配ＮＯ１
... I61: 手配ＮＯ４ | AJ61: 手配ＮＯ４
