Workbook
Name Revision: #REF!
Name Version: #REF!
Name Version: #REF!
Name Version: #REF!
Name Version: #REF!
Name Version: #REF!
Name Version: #REF!
Name Version: #REF!
Name Version: #REF!
Name Version: #REF!
Name 発行日: #REF!
Name 文書番号: #REF!
Name 文書番号_カスタマイズ: '[2]表紙（カスタマイズ）'!$U$20
Name 文書名: #REF!
Name 文書名: #REF!
Name 文書名: #REF!
Name 文書名: #REF!
Name 文書名: #REF!
Name 文書名: #REF!
Name 文書名: #REF!
Name 文書名: #REF!
Name 文書名: #REF!
Name 文書名_カスタマイズ: '[2]表紙（カスタマイズ）'!$M$10

Sheet 暫定対応
B2: ■シート商品
B4: ・ | C4: シート加工と同じ動きにする。
C5: ※品目の指定と工程の編集に関する画面の制御が難しいため、客先の結論（なんらか纏めているよう）待ち
B8: ■原紙受注
B10: ・ | C10: 原紙ＣＤ（表）を指定して工程入力が無くても、受注登録を可能にする。 | J10: ※ここも詳しい制御は客先に確認してから決める
C11: ・品目ＣＤの発番：原紙ＣＤ＋印刷ＣＤ＋エンボスＣＤ
C12: 枝番１～３：*
C13: ※マスタ連携時に巾と坪量を決めて、受注明細を更新する。
B15: ・ | C15: 巻きMを自由入力する。
C16: ※業務上の意味：巻取り原紙（原紙ロール）１本の長さ（M）
C17: 巻取り原紙を販売する時に入力される。販売単位：本、受注連携時に、巻きM×数量（本）＝原紙のM数

Sheet 受注パタンの纏め
B2: TOP画面 | G2: 基本情報画面 | J2: 受注入力パタン
B3: 受注区分 | D3: 指定可能品目 | H3: 製品区分
B4: 10 | C4: 加工製品 | D4: 製品マスタ | G4: 指定する製品の製品区分 | J4: 1.加工受注
H5: 12 | I5: 加工
H6: 13 | I6: Ｇプリント
H7: 21 | I7: 巻ボール
H8: 23 | I8: 片面加工
H9: 31 | I9: プリフル
H10: 32 | I10: 刷本支給
B11: 11 | C11: 加工商品 | D11: 製品マスタ | G11: 指定する製品の製品区分 | J11: 1.加工受注
H12: 12 | I12: 加工
H13: 13 | I13: Ｇプリント
H14: 21 | I14: 巻ボール
H15: 23 | I15: 片面加工
H16: 31 | I16: プリフル
H17: 32 | I17: 刷本支給
D18: 品目マスタ | E18: ※検索条件 | J18: ※諸口ＦＬＧで判断
E19: 品目区分 | F19: 1:商品 | G19: 指定する品目の品目詳細区分で判断 | J19: 諸口ＦＬＧ＝0 | K19: 3.商品購買
E20: 品目区分詳細 | F20: 112:商品加工 | H20: 12 | I20: 加工 | J20: 諸口ＦＬＧ＝1 | K20: 4.商品購買（有償支給、諸口）
F21: 113:商品Ｇプリント | H21: 13 | I21: Ｇプリント
F22: 121:商品巻ボール | H22: 21 | I22: 巻ボール
F23: 123:商品片面加工 | H23: 23 | I23: 片面加工
F24: 131:商品プリフル | H24: 31 | I24: プリフル
F25: 132:商品刷本支給 | H25: 32 | I25: 刷本支給
B27: 20 | C27: シート製品 | D27: 画面で採番する | G27: 画面より指定
H28: 11 | I28: シート | J28: 2.シート受注
H29: 22 | I29: 片面シート
B31: 21 | C31: シート商品 | D31: 画面で採番する | G31: 画面より指定
H32: 11 | I32: シート | J32: 2.シート受注
H33: 22 | I33: 片面シート
D35: 品目マスタ | E35: ※検索条件 | J35: ※諸口ＦＬＧで判断
E36: 品目区分 | F36: 1:商品 | G36: 指定する品目の品目詳細区分で判断 | J36: 諸口ＦＬＧ＝0 | K36: 3.商品購買
E37: 品目区分詳細 | F37: 111:商品シート | H37: 11 | I37: シート | J37: 諸口ＦＬＧ＝1 | K37: 4.商品購買（有償支給、諸口）
F38: 122:商品片面シート | H38: 22 | I38: 片面シート
B40: 30 | C40: 購買品 | D40: 品目マスタ | E40: ※検索条件① | G40: 指定する品目の品目詳細区分で判断 | J40: ※諸口ＦＬＧで判断
E41: 品目区分 | F41: 1:商品 | J41: 諸口ＦＬＧ＝0 | K41: 3.商品購買
E42: 品目区分詳細 | F42: 151:外装シート | H42: 51 | I42: 外装シート | J42: 諸口ＦＬＧ＝1 | K42: 4.商品購買（有償支給、諸口）
F43: 152:外装ケース | H43: 52 | I43: 外装ケース
F44: 162:商品その他 | H44: 62 | I44: その他
F45: 171:袋 | H45: 71 | I45: 袋
F46: 180:モールド | H46: 80 | I46: モールド
D48: 品目マスタ（経費品） | G48: 指定する品目の品目詳細区分で判断 | J48: ※画面制御は商品購買（諸口）と同じ
E49: 品目区分 | F49: 9:その他 | K49: 4.商品購買（有償支給、諸口）
E50: 品目区分詳細 | F50: 963:デザイン代 | H50: 63 | I50: デザイン代
F51: 981:運賃 | H51: 81 | I51: 運賃
F52: 991:資材料 | H52: 91 | I52: 資材料
F53: 992:前加工料 | H53: 92 | I53: 前加工料
E54: 諸口品ＦＬＧ | F54: 1:諸口
D55: 品目ＣＤ＝版型ＮＯ
K56: 3.商品購買（版型）
K57: 参照モード（全画面）
B60: 40 | C60: 原紙 | D60: 品目欄入力なし | G60: 原紙マスタ.紙種＝0（原紙）の場合
D61: 原紙（表）に原紙を指定 | H61: 43 | I61: 巻取り原紙 | K61: 5_原紙（原紙売り、輪切り）
G62: 原紙マスタ.紙種≠0（原紙）の場合
H63: 33 | I63: コートボール
D65: 品目マスタ | E65: ※検索条件① | G65: 指定する品目の品目詳細区分で判断 | J65: ※諸口ＦＬＧで判断
E66: 品目区分 | F66: 1:商品 | J66: 諸口ＦＬＧ＝0 | K66: 3.商品購買
E67: 品目区分詳細 | F67: 133:商品コートボール | H67: 33 | I67: コートボール | J67: 諸口ＦＬＧ＝1 | K67: 4.商品購買（有償支給、諸口）
F68: 141:商品原紙 | H68: 41 | I68: 生原紙
F69: 142:商品印刷原紙 | H69: 42 | I69: 印刷原紙
E70: ※検索条件② | J70: ※諸口ＦＬＧで判断
E71: 品目区分 | F71: 2:製品 | G71: 指定する品目の品目詳細区分で判断 | J71: 諸口ＦＬＧ＝0 | K71: 3.商品購買
E72: 品目区分詳細 | F72: 233:コートボール製品 | H72: 33 | I72: コートボール | J72: 諸口ＦＬＧ＝1 | K72: 4.商品購買（有償支給、諸口）
F73: 242:印刷原紙 | H73: 42 | I73: 印刷原紙
E74: ※検索条件③ | J74: ※諸口ＦＬＧで判断
E75: 品目区分 | F75: 6:原料 | G75: 指定する品目の品目詳細区分で判断 | J75: 諸口ＦＬＧ＝0 | K75: 3.商品購買
E76: 品目区分詳細 | F76: 603:コートボール | H76: 33 | I76: コートボール | J76: 諸口ＦＬＧ＝1 | K76: 4.商品購買（有償支給、諸口）
F77: 601:生原紙 | H77: 41 | I77: 生原紙
F78: 602:テスト原紙 | H78: 41 | I78: 生原紙
F79: 600:印刷原紙 | H79: 42 | I79: 印刷原紙

Sheet 原紙
C3: 原紙マスタ

Sheet 汎用マスタ
F1: 必須 | G1: 必須 | H1: 必須 | I1: 必須 | J1: 必須 | K1: 必須 | L1: 必須 | M1: 必須 | N1: 必須 | O1: 必須 | P1: 必須 | Q1: 必須
A2: 一覧に戻る | E2: 論理名 | F2: 汎用分類ＣＤ | G2: キー１ | H2: キー２ | I2: キー３ | J2: キー４ | K2: キー５ | L2: キー６ | M2: キー７ | N2: キー８ | O2: キー９ | P2: キー１０ | Q2: 会社ＣＤ | R2: 文字列１ | S2: 文字列２ | T2: 文字列３ | U2: 文字列４ | V2: 文字列５ | W2: 文字列６ | X2: 文字列７ | Y2: 文字列８ | Z2: 文字列９ | AA2: 文字列１０ | AB2: 文字列１１ | AC2: 文字列１２ | AD2: 文字列１３ | AE2: 文字列１４ | AF2: 文字列１５ | AG2: 文字列１６ | AH2: 文字列１７ | AI2: 文字列１８ | AJ2: 文字列１９ | AK2: 文字列２０ | AL2: 数値１ | AM2: 数値２ | AN2: 数値３ | AO2: 数値４ | AP2: 数値５ | AQ2: 数値６ | AR2: 数値７ | AS2: 数値８ | AT2: 数値９ | AU2: 数値１０ | AV2: 日付１ | AW2: 日付２ | AX2: 日付３ | AY2: 日付４ | AZ2: 日付５ | BA2: 日付６ | BB2: 日付７ | BC2: 日付８ | BD2: 日付９ | BE2: 日付１０ | BF2: フラグ１ | BG2: フラグ２ | BH2: フラグ３ | BI2: フラグ４ | BJ2: フラグ５ | BK2: フラグ６ | BL2: フラグ７ | BM2: フラグ８ | BN2: フラグ９ | BO2: フラグ１０ | BP2: メモ１ | BQ2: メモ２ | BR2: メモ３ | BS2: 論理削除ＦＬＧ | BT2: 論理削除ユーザＩＤ | BU2: 論理削除ユーザ名 | BV2: 論理削除日時 | BW2: 登録ユーザＩＤ | BX2: 登録ユーザ名 | BY2: 登録日時 | BZ2: 登録機能ＩＤ | CA2: 更新カウンタ | CB2: 更新ユーザＩＤ | CC2: 更新ユーザ名 | CD2: 更新日時 | CE2: 更新機能ＩＤ | CF2: 更新リクエストＮＯ
E3: 型 | F3: VARCHAR2 | G3: VARCHAR2 | H3: VARCHAR2 | I3: VARCHAR2 | J3: VARCHAR2 | K3: VARCHAR2 | L3: VARCHAR2 | M3: VARCHAR2 | N3: VARCHAR2 | O3: VARCHAR2 | P3: VARCHAR2 | Q3: VARCHAR2 | R3: VARCHAR2 | S3: VARCHAR2 | T3: VARCHAR2 | U3: VARCHAR2 | V3: VARCHAR2 | W3: VARCHAR2 | X3: VARCHAR2 | Y3: VARCHAR2 | Z3: VARCHAR2 | AA3: VARCHAR2 | AB3: VARCHAR2 | AC3: VARCHAR2 | AD3: VARCHAR2 | AE3: VARCHAR2 | AF3: VARCHAR2 | AG3: VARCHAR2 | AH3: VARCHAR2 | AI3: VARCHAR2 | AJ3: VARCHAR2 | AK3: VARCHAR2 | AL3: NUMBER | AM3: NUMBER | AN3: NUMBER | AO3: NUMBER | AP3: NUMBER | AQ3: NUMBER | AR3: NUMBER | AS3: NUMBER | AT3: NUMBER | AU3: NUMBER | AV3: DATE | AW3: DATE | AX3: DATE | AY3: DATE | AZ3: DATE | BA3: DATE | BB3: DATE | BC3: DATE | BD3: DATE | BE3: DATE | BF3: CHAR | BG3: CHAR | BH3: CHAR | BI3: CHAR | BJ3: CHAR | BK3: CHAR | BL3: CHAR | BM3: CHAR | BN3: CHAR | BO3: CHAR | BP3: VARCHAR2 | BQ3: VARCHAR2 | BR3: VARCHAR2 | BS3: CHAR | BT3: VARCHAR2 | BU3: VARCHAR2 | BV3: TIMESTAMP | BW3: VARCHAR2 | BX3: VARCHAR2 | BY3: TIMESTAMP | BZ3: VARCHAR2 | CA3: NUMBER | CB3: VARCHAR2 | CC3: VARCHAR2 | CD3: TIMESTAMP | CE3: VARCHAR2 | CF3: VARCHAR2
E4: 桁数 | F4: 5 | G4: 20 | H4: 20 | I4: 20 | J4: 20 | K4: 20 | L4: 20 | M4: 20 | N4: 20 | O4: 20 | P4: 20 | Q4: 10 | R4: 100 | S4: 100 | T4: 100 | U4: 100 | V4: 100 | W4: 100 | X4: 100 | Y4: 100 | Z4: 100 | AA4: 100 | AB4: 100 | AC4: 100 | AD4: 100 | AE4: 100 | AF4: 100 | AG4: 100 | AH4: 100 | AI4: 100 | AJ4: 100 | AK4: 100 | AL4: 21,8 | AM4: 21,8 | AN4: 21,8 | AO4: 21,8 | AP4: 21,8 | AQ4: 21,8 | AR4: 21,8 | AS4: 21,8 | AT4: 21,8 | AU4: 21,8 | BF4: 1 | BG4: 1 | BH4: 1 | BI4: 1 | BJ4: 1 | BK4: 1 | BL4: 1 | BM4: 1 | BN4: 1 | BO4: 1 | BP4: 100 | BQ4: 100 | BR4: 100 | BS4: 1 | BT4: 500 | BU4: 100 | BV4: 3 | BW4: 500 | BX4: 100 | BY4: 3 | BZ4: 50 | CA4: 90 | CB4: 500 | CC4: 100 | CD4: 3 | CE4: 50 | CF4: 50
C5: 汎用分類 | D5: 省略可否 | E5: 用途 | F5: GP_GRP_CD | G5: KEY1 | H5: KEY2 | I5: KEY3 | J5: KEY4 | K5: KEY5 | L5: KEY6 | M5: KEY7 | N5: KEY8 | O5: KEY9 | P5: KEY10 | Q5: CO_CD | R5: CHAR1 | S5: CHAR2 | T5: CHAR3 | U5: CHAR4 | V5: CHAR5 | W5: CHAR6 | X5: CHAR7 | Y5: CHAR8 | Z5: CHAR9 | AA5: CHAR10 | AB5: CHAR11 | AC5: CHAR12 | AD5: CHAR13 | AE5: CHAR14 | AF5: CHAR15 | AG5: CHAR16 | AH5: CHAR17 | AI5: CHAR18 | AJ5: CHAR19 | AK5: CHAR20 | AL5: NUM1 | AM5: NUM2 | AN5: NUM3 | AO5: NUM4 | AP5: NUM5 | AQ5: NUM6 | AR5: NUM7 | AS5: NUM8 | AT5: NUM9 | AU5: NUM10 | AV5: DT1 | AW5: DT2 | AX5: DT3 | AY5: DT4 | AZ5: DT5 | BA5: DT6 | BB5: DT7 | BC5: DT8 | BD5: DT9 | BE5: DT10 | BF5: FLG1 | BG5: FLG2 | BH5: FLG3 | BI5: FLG4 | BJ5: FLG5 | BK5: FLG6 | BL5: FLG7 | BM5: FLG8 | BN5: FLG9 | BO5: FLG10 | BP5: MEMO1 | BQ5: MEMO2 | BR5: MEMO3 | BS5: DEL_FLG | BT5: DEL_USR_ID | BU5: DEL_USR_NM | BV5: DEL_TS | BW5: INS_USR_ID | BX5: INS_USR_NM | BY5: INS_TS | BZ5: INS_FUNC_ID | CA5: UPD_CNTR | CB5: UPD_USR_ID | CC5: UPD_USR_NM | CD5: UPD_TS | CE5: UPD_FUNC_ID | CF5: UPD_SRV_REQ_NO
B6: 定義 | C6: WEB受注画面制御 | D6: 省略不可。省略時処理エラー。 | F6: M111 | G6: 受注区分 | H6: 品目区分 | I6: 品目区分詳細 | J6: 諸口ＦＬＧ | L6: 受注区分名 （設定確認要） | M6: 品目区分名 （設定確認要） | N6: 品目区分詳細名 （設定確認要） | O6: 諸口ＦＬＧ （設定確認要） | P6: 表示順 | Q6: CROWN01 | R6: 製品区分 | S6: 受注入力パタン | U6: 製品区分名 | V6: 受注入力パタン名 | BX6: 朱 | BY6: 1/17
B7: データ例 | F7: M111 | G7: 10 | H7: * | I7: * | J7: * | K7: * | L7: 加工製品 | M7: * | N7: * | O7: * | P7: 1 | Q7: J0001 | R7: 12 | S7: 1 | U7: 加工 | V7: 加工品受注（新規入力） | BF7: 0 | BG7: 0 | BH7: 0 | BI7: 0 | BJ7: 0 | BK7: 0 | BL7: 0 | BM7: 0 | BN7: 0 | BO7: 0 | BS7: 0
F8: M111 | G8: 10 | H8: * | I8: * | J8: * | K8: * | L8: 加工製品 | M8: * | N8: * | O8: * | P8: 2 | Q8: J0001 | R8: 13 | S8: 1 | U8: Ｇプリント | V8: 加工品受注（新規入力） | BF8: 0 | BG8: 0 | BH8: 0 | BI8: 0 | BJ8: 0 | BK8: 0 | BL8: 0 | BM8: 0 | BN8: 0 | BO8: 0 | BS8: 0
F9: M111 | G9: 10 | H9: * | I9: * | J9: * | K9: * | L9: 加工製品 | M9: * | N9: * | O9: * | P9: 3 | Q9: J0001 | R9: 21 | S9: 1 | U9: 巻ボール | V9: 加工品受注（新規入力） | BF9: 0 | BG9: 0 | BH9: 0 | BI9: 0 | BJ9: 0 | BK9: 0 | BL9: 0 | BM9: 0 | BN9: 0 | BO9: 0 | BS9: 0
F10: M111 | G10: 10 | H10: * | I10: * | J10: * | K10: * | L10: 加工製品 | M10: * | N10: * | O10: * | P10: 4 | Q10: J0001 | R10: 23 | S10: 1 | U10: 片面加工 | V10: 加工品受注（新規入力） | BF10: 0 | BG10: 0 | BH10: 0 | BI10: 0 | BJ10: 0 | BK10: 0 | BL10: 0 | BM10: 0 | BN10: 0 | BO10: 0 | BS10: 0
F11: M111 | G11: 10 | H11: * | I11: * | J11: * | K11: * | L11: 加工製品 | M11: * | N11: * | O11: * | P11: 5 | Q11: J0001 | R11: 31 | S11: 1 | U11: プリフル | V11: 加工品受注（新規入力） | BF11: 0 | BG11: 0 | BH11: 0 | BI11: 0 | BJ11: 0 | BK11: 0 | BL11: 0 | BM11: 0 | BN11: 0 | BO11: 0 | BS11: 0
F12: M111 | G12: 10 | H12: * | I12: * | J12: * | K12: * | L12: 加工製品 | M12: * | N12: * | O12: * | P12: 6 | Q12: J0001 | R12: 32 | S12: 1 | U12: 刷本支給 | V12: 加工品受注（新規入力） | BF12: 0 | BG12: 0 | BH12: 0 | BI12: 0 | BJ12: 0 | BK12: 0 | BL12: 0 | BM12: 0 | BN12: 0 | BO12: 0 | BS12: 0
F13: M111 | G13: 10 | H13: 2 | I13: 212 | J13: 0 | K13: * | L13: 加工製品 | M13: 製品 | N13: 加工 | O13: * | P13: * | Q13: J0001 | R13: 12 | S13: 3 | U13: 加工 | BF13: 0 | BG13: 0 | BH13: 0 | BI13: 0 | BJ13: 0 | BK13: 0 | BL13: 0 | BM13: 0 | BN13: 0 | BO13: 0 | BS13: 1
F14: M111 | G14: 10 | H14: 2 | I14: 213 | J14: 0 | K14: * | L14: 加工製品 | M14: 製品 | N14: Ｇプリント | O14: * | P14: * | Q14: J0001 | R14: 13 | S14: 3 | U14: Ｇプリント | BF14: 0 | BG14: 0 | BH14: 0 | BI14: 0 | BJ14: 0 | BK14: 0 | BL14: 0 | BM14: 0 | BN14: 0 | BO14: 0 | BS14: 1
F15: M111 | G15: 10 | H15: 2 | I15: 221 | J15: 0 | K15: * | L15: 加工製品 | M15: 製品 | N15: 巻ボール | O15: * | P15: * | Q15: J0001 | R15: 21 | S15: 3 | U15: 巻ボール | BF15: 0 | BG15: 0 | BH15: 0 | BI15: 0 | BJ15: 0 | BK15: 0 | BL15: 0 | BM15: 0 | BN15: 0 | BO15: 0 | BS15: 1
F16: M111 | G16: 10 | H16: 2 | I16: 223 | J16: 0 | K16: * | L16: 加工製品 | M16: 製品 | N16: 片面加工 | O16: * | P16: * | Q16: J0001 | R16: 23 | S16: 3 | U16: 片面加工 | BF16: 0 | BG16: 0 | BH16: 0 | BI16: 0 | BJ16: 0 | BK16: 0 | BL16: 0 | BM16: 0 | BN16: 0 | BO16: 0 | BS16: 1
F17: M111 | G17: 10 | H17: 2 | I17: 231 | J17: 0 | K17: * | L17: 加工製品 | M17: 製品 | N17: プリフル | O17: * | P17: * | Q17: J0001 | R17: 31 | S17: 3 | U17: プリフル | BF17: 0 | BG17: 0 | BH17: 0 | BI17: 0 | BJ17: 0 | BK17: 0 | BL17: 0 | BM17: 0 | BN17: 0 | BO17: 0 | BS17: 1
F18: M111 | G18: 10 | H18: 2 | I18: 232 | J18: 0 | K18: * | L18: 加工製品 | M18: 製品 | N18: 刷本支給 | O18: * | P18: * | Q18: J0001 | R18: 32 | S18: 3 | U18: 刷本支給 | BF18: 0 | BG18: 0 | BH18: 0 | BI18: 0 | BJ18: 0 | BK18: 0 | BL18: 0 | BM18: 0 | BN18: 0 | BO18: 0 | BS18: 1
F19: M111 | G19: 11 | H19: * | I19: * | J19: * | K19: * | L19: 加工製品 | M19: * | N19: * | O19: * | P19: 1 | Q19: J0001 | R19: 12 | S19: 1 | U19: 加工 | V19: 加工品受注（新規入力） | BF19: 0 | BG19: 0 | BH19: 0 | BI19: 0 | BJ19: 0 | BK19: 0 | BL19: 0 | BM19: 0 | BN19: 0 | BO19: 0 | BS19: 0
F20: M111 | G20: 11 | H20: * | I20: * | J20: * | K20: * | L20: 加工製品 | M20: * | N20: * | O20: * | P20: 2 | Q20: J0001 | R20: 13 | S20: 1 | U20: Ｇプリント | V20: 加工品受注（新規入力） | BF20: 0 | BG20: 0 | BH20: 0 | BI20: 0 | BJ20: 0 | BK20: 0 | BL20: 0 | BM20: 0 | BN20: 0 | BO20: 0 | BS20: 0
F21: M111 | G21: 11 | H21: * | I21: * | J21: * | K21: * | L21: 加工製品 | M21: * | N21: * | O21: * | P21: 3 | Q21: J0001 | R21: 21 | S21: 1 | U21: 巻ボール | V21: 加工品受注（新規入力） | BF21: 0 | BG21: 0 | BH21: 0 | BI21: 0 | BJ21: 0 | BK21: 0 | BL21: 0 | BM21: 0 | BN21: 0 | BO21: 0 | BS21: 0
F22: M111 | G22: 11 | H22: * | I22: * | J22: * | K22: * | L22: 加工製品 | M22: * | N22: * | O22: * | P22: 4 | Q22: J0001 | R22: 23 | S22: 1 | U22: 片面加工 | V22: 加工品受注（新規入力） | BF22: 0 | BG22: 0 | BH22: 0 | BI22: 0 | BJ22: 0 | BK22: 0 | BL22: 0 | BM22: 0 | BN22: 0 | BO22: 0 | BS22: 0
F23: M111 | G23: 11 | H23: * | I23: * | J23: * | K23: * | L23: 加工製品 | M23: * | N23: * | O23: * | P23: 5 | Q23: J0001 | R23: 31 | S23: 1 | U23: プリフル | V23: 加工品受注（新規入力） | BF23: 0 | BG23: 0 | BH23: 0 | BI23: 0 | BJ23: 0 | BK23: 0 | BL23: 0 | BM23: 0 | BN23: 0 | BO23: 0 | BS23: 0
F24: M111 | G24: 11 | H24: * | I24: * | J24: * | K24: * | L24: 加工製品 | M24: * | N24: * | O24: * | P24: 6 | Q24: J0001 | R24: 32 | S24: 1 | U24: 刷本支給 | V24: 加工品受注（新規入力） | BF24: 0 | BG24: 0 | BH24: 0 | BI24: 0 | BJ24: 0 | BK24: 0 | BL24: 0 | BM24: 0 | BN24: 0 | BO24: 0 | BS24: 0
F25: M111 | G25: 11 | H25: 1 | I25: 112 | J25: 0 | K25: * | L25: 加工商品 | M25: 商品 | N25: 商品加工 | O25: * | P25: * | Q25: J0001 | R25: 12 | S25: 3 | U25: 加工 | V25: 商品購買 | BF25: 0 | BG25: 0 | BH25: 0 | BI25: 0 | BJ25: 0 | BK25: 0 | BL25: 0 | BM25: 0 | BN25: 0 | BO25: 0 | BS25: 0
F26: M111 | G26: 11 | H26: 1 | I26: 113 | J26: 0 | K26: * | L26: 加工商品 | M26: 商品 | N26: 商品Ｇプリント | O26: * | P26: * | Q26: J0001 | R26: 13 | S26: 3 | U26: Ｇプリント | V26: 商品購買 | BF26: 0 | BG26: 0 | BH26: 0 | BI26: 0 | BJ26: 0 | BK26: 0 | BL26: 0 | BM26: 0 | BN26: 0 | BO26: 0 | BS26: 0
F27: M111 | G27: 11 | H27: 1 | I27: 121 | J27: 0 | K27: * | L27: 加工商品 | M27: 商品 | N27: 商品巻ボール | O27: * | P27: * | Q27: J0001 | R27: 21 | S27: 3 | U27: 巻ボール | V27: 商品購買 | BF27: 0 | BG27: 0 | BH27: 0 | BI27: 0 | BJ27: 0 | BK27: 0 | BL27: 0 | BM27: 0 | BN27: 0 | BO27: 0 | BS27: 0
F28: M111 | G28: 11 | H28: 1 | I28: 123 | J28: 2.シート受注 | K28: * | L28: 加工商品 | M28: 商品 | N28: 商品片面加工 | O28: * | P28: * | Q28: J0001 | R28: 23 | S28: 3 | U28: 片面加工 | V28: 商品購買 | BF28: 0 | BG28: 0 | BH28: 0 | BI28: 0 | BJ28: 0 | BK28: 0 | BL28: 0 | BM28: 0 | BN28: 0 | BO28: 0 | BS28: 0
F29: M111 | G29: 11 | H29: 1 | I29: 131 | J29: 0 | K29: * | L29: 加工商品 | M29: 商品 | N29: 商品プリフル | O29: * | P29: * | Q29: J0001 | R29: 31 | S29: 3 | U29: プリフル | V29: 商品購買 | BF29: 0 | BG29: 0 | BH29: 0 | BI29: 0 | BJ29: 0 | BK29: 0 | BL29: 0 | BM29: 0 | BN29: 0 | BO29: 0 | BS29: 0
F30: M111 | G30: 11 | H30: 1 | I30: 132 | J30: 0 | K30: * | L30: 加工商品 | M30: 商品 | N30: 商品刷本支給 | O30: * | P30: * | Q30: J0001 | R30: 32 | S30: 3 | U30: 刷本支給 | V30: 商品購買 | BF30: 0 | BG30: 0 | BH30: 0 | BI30: 0 | BJ30: 0 | BK30: 0 | BL30: 0 | BM30: 0 | BN30: 0 | BO30: 0 | BS30: 0
F31: M111 | G31: 11 | H31: 1 | I31: 112 | J31: 1 | K31: * | L31: 加工商品 | M31: 商品 | N31: 商品加工 | O31: 諸口 | P31: * | Q31: J0001 | R31: 12 | S31: 4 | U31: 加工 | V31: 商品購買（諸口）、経費品 | BF31: 0 | BG31: 0 | BH31: 0 | BI31: 0 | BJ31: 0 | BK31: 0 | BL31: 0 | BM31: 0 | BN31: 0 | BO31: 0 | BS31: 0
F32: M111 | G32: 11 | H32: 1 | I32: 113 | J32: 1 | K32: * | L32: 加工商品 | M32: 商品 | N32: 商品Ｇプリント | O32: 諸口 | P32: * | Q32: J0001 | R32: 13 | S32: 4 | U32: Ｇプリント | V32: 商品購買（諸口）、経費品 | BF32: 0 | BG32: 0 | BH32: 0 | BI32: 0 | BJ32: 0 | BK32: 0 | BL32: 0 | BM32: 0 | BN32: 0 | BO32: 0 | BS32: 0
F33: M111 | G33: 11 | H33: 1 | I33: 121 | J33: 1 | K33: * | L33: 加工商品 | M33: 商品 | N33: 商品巻ボール | O33: 諸口 | P33: * | Q33: J0001 | R33: 21 | S33: 4 | U33: 巻ボール | V33: 商品購買（諸口）、経費品 | BF33: 0 | BG33: 0 | BH33: 0 | BI33: 0 | BJ33: 0 | BK33: 0 | BL33: 0 | BM33: 0 | BN33: 0 | BO33: 0 | BS33: 0
F34: M111 | G34: 11 | H34: 1 | I34: 123 | J34: 1 | K34: * | L34: 加工商品 | M34: 商品 | N34: 商品片面加工 | O34: 諸口 | P34: * | Q34: J0001 | R34: 23 | S34: 4 | U34: 片面加工 | V34: 商品購買（諸口）、経費品 | BF34: 0 | BG34: 0 | BH34: 0 | BI34: 0 | BJ34: 0 | BK34: 0 | BL34: 0 | BM34: 0 | BN34: 0 | BO34: 0 | BS34: 0
F35: M111 | G35: 11 | H35: 1 | I35: 131 | J35: 1 | K35: * | L35: 加工商品 | M35: 商品 | N35: 商品プリフル | O35: 諸口 | P35: * | Q35: J0001 | R35: 31 | S35: 4 | U35: プリフル | V35: 商品購買（諸口）、経費品 | BF35: 0 | BG35: 0 | BH35: 0 | BI35: 0 | BJ35: 0 | BK35: 0 | BL35: 0 | BM35: 0 | BN35: 0 | BO35: 0 | BS35: 0
F36: M111 | G36: 11 | H36: 1 | I36: 132 | J36: 1 | K36: * | L36: 加工商品 | M36: 商品 | N36: 商品刷本支給 | O36: 諸口 | P36: * | Q36: J0001 | R36: 32 | S36: 4 | U36: 刷本支給 | V36: 商品購買（諸口）、経費品 | BF36: 0 | BG36: 0 | BH36: 0 | BI36: 0 | BJ36: 0 | BK36: 0 | BL36: 0 | BM36: 0 | BN36: 0 | BO36: 0 | BS36: 0
F37: M111 | G37: 20 | H37: * | I37: * | J37: * | K37: * | L37: シート製品 | M37: * | N37: * | O37: * | P37: 1 | Q37: J0001 | R37: 11 | S37: 2 | U37: シート | V37: シート受注（新規入力） | BF37: 0 | BG37: 0 | BH37: 0 | BI37: 0 | BJ37: 0 | BK37: 0 | BL37: 0 | BM37: 0 | BN37: 0 | BO37: 0 | BS37: 0
F38: M111 | G38: 20 | H38: * | I38: * | J38: * | K38: * | L38: シート製品 | M38: * | N38: * | O38: * | P38: 2 | Q38: J0001 | R38: 22 | S38: 2 | U38: 片面シート | V38: シート受注（新規入力） | BF38: 0 | BG38: 0 | BH38: 0 | BI38: 0 | BJ38: 0 | BK38: 0 | BL38: 0 | BM38: 0 | BN38: 0 | BO38: 0 | BS38: 0
F39: M111 | G39: 20 | H39: 2 | I39: 211 | J39: 0 | K39: * | L39: シート製品 | M39: 製品 | N39: シート | O39: * | P39: * | Q39: J0001 | R39: 11 | S39: 2 | U39: シート | V39: シート受注 | BF39: 0 | BG39: 0 | BH39: 0 | BI39: 0 | BJ39: 0 | BK39: 0 | BL39: 0 | BM39: 0 | BN39: 0 | BO39: 0 | BS39: 1
F40: M111 | G40: 20 | H40: 2 | I40: 222 | J40: 0 | K40: * | L40: シート製品 | M40: 製品 | N40: 片面シート | O40: * | P40: * | Q40: J0001 | R40: 22 | S40: 2 | U40: 片面シート | V40: シート受注 | BF40: 0 | BG40: 0 | BH40: 0 | BI40: 0 | BJ40: 0 | BK40: 0 | BL40: 0 | BM40: 0 | BN40: 0 | BO40: 0 | BS40: 1
F41: M111 | G41: 21 | H41: * | I41: * | J41: * | K41: * | L41: シート製品 | M41: * | N41: * | O41: * | P41: 1 | Q41: J0001 | R41: 11 | S41: 2 | U41: シート | V41: シート受注（新規入力） | BF41: 0 | BG41: 0 | BH41: 0 | BI41: 0 | BJ41: 0 | BK41: 0 | BL41: 0 | BM41: 0 | BN41: 0 | BO41: 0 | BS41: 0
F42: M111 | G42: 21 | H42: * | I42: * | J42: * | K42: * | L42: シート製品 | M42: * | N42: * | O42: * | P42: 2 | Q42: J0001 | R42: 22 | S42: 2 | U42: 片面シート | V42: シート受注（新規入力） | BF42: 0 | BG42: 0 | BH42: 0 | BI42: 0 | BJ42: 0 | BK42: 0 | BL42: 0 | BM42: 0 | BN42: 0 | BO42: 0 | BS42: 0
F43: M111 | G43: 21 | H43: 1 | I43: 111 | J43: 0 | K43: * | L43: シート商品 | M43: 商品 | N43: 商品シート | O43: * | P43: * | Q43: J0001 | R43: 11 | S43: 3 | U43: シート | V43: 商品購買 | BF43: 0 | BG43: 0 | BH43: 0 | BI43: 0 | BJ43: 0 | BK43: 0 | BL43: 0 | BM43: 0 | BN43: 0 | BO43: 0 | BS43: 0
F44: M111 | G44: 21 | H44: 1 | I44: 122 | J44: 0 | K44: * | L44: シート商品 | M44: 商品 | N44: 商品片面シート | O44: * | P44: * | Q44: J0001 | R44: 22 | S44: 3 | U44: 片面シート | V44: 商品購買 | BF44: 0 | BG44: 0 | BH44: 0 | BI44: 0 | BJ44: 0 | BK44: 0 | BL44: 0 | BM44: 0 | BN44: 0 | BO44: 0 | BS44: 0
F45: M111 | G45: 21 | H45: 1 | I45: 111 | J45: 0 | K45: * | L45: シート商品 | M45: 商品 | N45: 商品シート | O45: 諸口 | P45: * | Q45: J0001 | R45: 11 | S45: 4 | U45: シート | V45: 商品購買（諸口）、経費品 | BF45: 0 | BG45: 0 | BH45: 0 | BI45: 0 | BJ45: 0 | BK45: 0 | BL45: 0 | BM45: 0 | BN45: 0 | BO45: 0 | BS45: 0
F46: M111 | G46: 21 | H46: 1 | I46: 122 | J46: 0 | K46: * | L46: シート商品 | M46: 商品 | N46: 商品片面シート | O46: 諸口 | P46: * | Q46: J0001 | R46: 22 | S46: 4 | U46: 片面シート | V46: 商品購買（諸口）、経費品 | BF46: 0 | BG46: 0 | BH46: 0 | BI46: 0 | BJ46: 0 | BK46: 0 | BL46: 0 | BM46: 0 | BN46: 0 | BO46: 0 | BS46: 0
F47: M111 | G47: 30 | H47: 1 | I47: 151 | J47: 0 | K47: * | L47: 購買品 | M47: 商品 | N47: 外装シート | O47: * | P47: * | Q47: J0001 | R47: 51 | S47: 3 | U47: 外装シート | V47: 商品購買 | BF47: 0 | BG47: 0 | BH47: 0 | BI47: 0 | BJ47: 0 | BK47: 0 | BL47: 0 | BM47: 0 | BN47: 0 | BO47: 0 | BS47: 0
F48: M111 | G48: 30 | H48: 1 | I48: 152 | J48: 0 | K48: * | L48: 購買品 | M48: 商品 | N48: 外装ケース | O48: * | P48: * | Q48: J0001 | R48: 52 | S48: 3 | U48: 外装ケース | V48: 商品購買 | BF48: 0 | BG48: 0 | BH48: 0 | BI48: 0 | BJ48: 0 | BK48: 0 | BL48: 0 | BM48: 0 | BN48: 0 | BO48: 0 | BS48: 0
F49: M111 | G49: 30 | H49: 1 | I49: 162 | J49: 0 | K49: * | L49: 購買品 | M49: 商品 | N49: 商品その他 | O49: * | P49: * | Q49: J0001 | R49: 62 | S49: 3 | U49: その他 | V49: 商品購買 | BF49: 0 | BG49: 0 | BH49: 0 | BI49: 0 | BJ49: 0 | BK49: 0 | BL49: 0 | BM49: 0 | BN49: 0 | BO49: 0 | BS49: 0
F50: M111 | G50: 30 | H50: 1 | I50: 171 | J50: 0 | K50: * | L50: 購買品 | M50: 商品 | N50: 袋 | O50: * | P50: * | Q50: J0001 | R50: 71 | S50: 3 | U50: 袋 | V50: 商品購買 | BF50: 0 | BG50: 0 | BH50: 0 | BI50: 0 | BJ50: 0 | BK50: 0 | BL50: 0 | BM50: 0 | BN50: 0 | BO50: 0 | BS50: 0
F51: M111 | G51: 30 | H51: 1 | I51: 180 | J51: 0 | K51: * | L51: 購買品 | M51: 商品 | N51: モールド | O51: * | P51: * | Q51: J0001 | R51: 80 | S51: 3 | U51: モールド | V51: 商品購買 | BF51: 0 | BG51: 0 | BH51: 0 | BI51: 0 | BJ51: 0 | BK51: 0 | BL51: 0 | BM51: 0 | BN51: 0 | BO51: 0 | BS51: 0
F52: M111 | G52: 30 | H52: 1 | I52: 151 | J52: 0 | K52: * | L52: 購買品 | M52: 商品 | N52: 外装シート | O52: 諸口 | P52: * | Q52: J0001 | R52: 51 | S52: 4 | U52: 外装シート | V52: 商品購買（諸口）、経費品 | BF52: 0 | BG52: 0 | BH52: 0 | BI52: 0 | BJ52: 0 | BK52: 0 | BL52: 0 | BM52: 0 | BN52: 0 | BO52: 0 | BS52: 0
F53: M111 | G53: 30 | H53: 1 | I53: 152 | J53: 0 | K53: * | L53: 購買品 | M53: 商品 | N53: 外装ケース | O53: 諸口 | P53: * | Q53: J0001 | R53: 52 | S53: 4 | U53: 外装ケース | V53: 商品購買（諸口）、経費品 | BF53: 0 | BG53: 0 | BH53: 0 | BI53: 0 | BJ53: 0 | BK53: 0 | BL53: 0 | BM53: 0 | BN53: 0 | BO53: 0 | BS53: 0
F54: M111 | G54: 30 | H54: 1 | I54: 162 | J54: 0 | K54: * | L54: 購買品 | M54: 商品 | N54: 商品その他 | O54: 諸口 | P54: * | Q54: J0001 | R54: 62 | S54: 4 | U54: その他 | V54: 商品購買（諸口）、経費品 | BF54: 0 | BG54: 0 | BH54: 0 | BI54: 0 | BJ54: 0 | BK54: 0 | BL54: 0 | BM54: 0 | BN54: 0 | BO54: 0 | BS54: 0
F55: M111 | G55: 30 | H55: 1 | I55: 171 | J55: 0 | K55: * | L55: 購買品 | M55: 商品 | N55: 袋 | O55: 諸口 | P55: * | Q55: J0001 | R55: 71 | S55: 4 | U55: 袋 | V55: 商品購買（諸口）、経費品 | BF55: 0 | BG55: 0 | BH55: 0 | BI55: 0 | BJ55: 0 | BK55: 0 | BL55: 0 | BM55: 0 | BN55: 0 | BO55: 0 | BS55: 0
F56: M111 | G56: 30 | H56: 1 | I56: 180 | J56: 0 | K56: 2.シート受注 | L56: 購買品 | M56: 商品 | N56: モールド | O56: 諸口 | P56: * | Q56: J0001 | R56: 80 | S56: 4 | U56: モールド | V56: 商品購買（諸口）、経費品 | BF56: 0 | BG56: 0 | BH56: 0 | BI56: 0 | BJ56: 0 | BK56: 0 | BL56: 0 | BM56: 0 | BN56: 0 | BO56: 0 | BS56: 0
F57: M111 | G57: 30 | H57: 9 | I57: 963 | J57: 1 | K57: * | L57: 購買品 | M57: その他 | N57: デザイン代 | O57: 諸口 | P57: * | Q57: J0001 | R57: 63 | S57: 4 | U57: デザイン代 | V57: 商品購買（諸口）、経費品 | BF57: 0 | BG57: 0 | BH57: 0 | BI57: 0 | BJ57: 0 | BK57: 0 | BL57: 0 | BM57: 0 | BN57: 0 | BO57: 0 | BS57: 0
F58: M111 | G58: 30 | H58: 9 | I58: 981 | J58: 1 | K58: * | L58: 購買品 | M58: その他 | N58: 運賃 | O58: 諸口 | P58: * | Q58: J0001 | R58: 81 | S58: 4 | U58: 運賃 | V58: 商品購買（諸口）、経費品 | BF58: 0 | BG58: 0 | BH58: 0 | BI58: 0 | BJ58: 0 | BK58: 0 | BL58: 0 | BM58: 0 | BN58: 0 | BO58: 0 | BS58: 0
F59: M111 | G59: 30 | H59: 9 | I59: 991 | J59: 1 | K59: * | L59: 購買品 | M59: その他 | N59: 資材料 | O59: 諸口 | P59: * | Q59: J0001 | R59: 91 | S59: 4 | U59: 資材料 | V59: 商品購買（諸口）、経費品 | BF59: 0 | BG59: 0 | BH59: 0 | BI59: 0 | BJ59: 0 | BK59: 0 | BL59: 0 | BM59: 0 | BN59: 0 | BO59: 0 | BS59: 0
F60: M111 | G60: 30 | H60: 9 | I60: 992 | J60: 1 | K60: * | L60: 購買品 | M60: その他 | N60: 前加工料 | O60: 諸口 | P60: * | Q60: J0001 | R60: 92 | S60: 4 | U60: 前加工料 | V60: 商品購買（諸口）、経費品 | BF60: 0 | BG60: 0 | BH60: 0 | BI60: 0 | BJ60: 0 | BK60: 0 | BL60: 0 | BM60: 0 | BN60: 0 | BO60: 0 | BS60: 0
F61: M111 | G61: 40 | H61: 1 | I61: 133 | J61: 0 | K61: 2.シート受注 | L61: 原紙 | M61: 商品 | N61: 商品コートボール | O61: * | P61: * | Q61: J0001 | R61: 33 | S61: 2 | U61: コートボール | V61: シート受注 | BF61: 0 | BG61: 0 | BH61: 0 | BI61: 0 | BJ61: 0 | BK61: 0 | BL61: 0 | BM61: 0 | BN61: 0 | BO61: 0 | BS61: 0
F62: M111 | G62: 40 | H62: 1 | I62: 141 | J62: 0 | K62: * | L62: 原紙 | M62: 商品 | N62: 商品原紙 | O62: * | P62: * | Q62: J0001 | R62: 41 | S62: 2 | U62: 生原紙 | V62: シート受注 | BF62: 0 | BG62: 0 | BH62: 0 | BI62: 0 | BJ62: 0 | BK62: 0 | BL62: 0 | BM62: 0 | BN62: 0 | BO62: 0 | BS62: 0
F63: M111 | G63: 40 | H63: 1 | I63: 142 | J63: 0 | K63: * | L63: 原紙 | M63: 商品 | N63: 商品印刷原紙 | O63: * | P63: * | Q63: J0001 | R63: 42 | S63: 2 | U63: 印刷原紙 | V63: シート受注 | BF63: 0 | BG63: 0 | BH63: 0 | BI63: 0 | BJ63: 0 | BK63: 0 | BL63: 0 | BM63: 0 | BN63: 0 | BO63: 0 | BS63: 0
F64: M111 | G64: 40 | H64: 1 | I64: 133 | J64: 1 | K64: * | L64: 原紙 | M64: 商品 | N64: 商品コートボール | O64: 諸口 | P64: * | Q64: J0001 | R64: 33 | S64: 4 | U64: コートボール | V64: 商品購買（諸口）、経費品 | BF64: 0 | BG64: 0 | BH64: 0 | BI64: 0 | BJ64: 0 | BK64: 0 | BL64: 0 | BM64: 0 | BN64: 0 | BO64: 0 | BS64: 0
F65: M111 | G65: 40 | H65: 1 | I65: 141 | J65: 1 | K65: 3.商品購買 | L65: 原紙 | M65: 商品 | N65: 商品原紙 | O65: 諸口 | P65: * | Q65: J0001 | R65: 41 | S65: 4 | U65: 生原紙 | V65: 商品購買（諸口）、経費品 | BF65: 0 | BG65: 0 | BH65: 0 | BI65: 0 | BJ65: 0 | BK65: 0 | BL65: 0 | BM65: 0 | BN65: 0 | BO65: 0 | BS65: 0
F66: M111 | G66: 40 | H66: 1 | I66: 142 | J66: 1 | K66: * | L66: 原紙 | M66: 商品 | N66: 商品印刷原紙 | O66: 諸口 | P66: * | Q66: J0001 | R66: 42 | S66: 4 | U66: 印刷原紙 | V66: 商品購買（諸口）、経費品 | BF66: 0 | BG66: 0 | BH66: 0 | BI66: 0 | BJ66: 0 | BK66: 0 | BL66: 0 | BM66: 0 | BN66: 0 | BO66: 0 | BS66: 0
F67: M111 | G67: 40 | H67: 2 | I67: 233 | J67: 0 | K67: * | L67: 原紙 | M67: 製品 | N67: コートボール製品 | O67: * | P67: * | Q67: J0001 | R67: 33 | S67: 2 | U67: コートボール | V67: シート受注 | BF67: 0 | BG67: 0 | BH67: 0 | BI67: 0 | BJ67: 0 | BK67: 0 | BL67: 0 | BM67: 0 | BN67: 0 | BO67: 0 | BS67: 0
F68: M111 | G68: 40 | H68: 2 | I68: 242 | J68: 0 | K68: * | L68: 原紙 | M68: 製品 | N68: 印刷原紙 | O68: * | P68: * | Q68: J0001 | R68: 42 | S68: 2 | U68: 印刷原紙 | V68: シート受注 | BF68: 0 | BG68: 0 | BH68: 0 | BI68: 0 | BJ68: 0 | BK68: 0 | BL68: 0 | BM68: 0 | BN68: 0 | BO68: 0 | BS68: 0
F69: M111 | G69: 40 | H69: 2 | I69: 233 | J69: 1 | K69: * | L69: 原紙 | M69: 製品 | N69: コートボール製品 | O69: 諸口 | P69: * | Q69: J0001 | R69: 33 | S69: 4 | U69: コートボール | V69: 商品購買（諸口）、経費品 | BF69: 0 | BG69: 0 | BH69: 0 | BI69: 0 | BJ69: 0 | BK69: 0 | BL69: 0 | BM69: 0 | BN69: 0 | BO69: 0 | BS69: 0
F70: M111 | G70: 40 | H70: 2 | I70: 242 | J70: 1 | K70: * | L70: 原紙 | M70: 製品 | N70: 印刷原紙 | O70: 諸口 | P70: * | Q70: J0001 | R70: 42 | S70: 4 | U70: 印刷原紙 | V70: 商品購買（諸口）、経費品 | BF70: 0 | BG70: 0 | BH70: 0 | BI70: 0 | BJ70: 0 | BK70: 0 | BL70: 0 | BM70: 0 | BN70: 0 | BO70: 0 | BS70: 0
F71: M111 | G71: 40 | H71: 6 | I71: 603 | J71: 0 | K71: * | L71: 原紙 | M71: 原料 | N71: コートボール | O71: * | P71: * | Q71: J0001 | R71: 33 | S71: 3 | U71: コートボール | V71: 商品購買 | BF71: 0 | BG71: 0 | BH71: 0 | BI71: 0 | BJ71: 0 | BK71: 0 | BL71: 0 | BM71: 0 | BN71: 0 | BO71: 0 | BS71: 0
F72: M111 | G72: 40 | H72: 6 | I72: 601 | J72: 0 | K72: * | L72: 原紙 | M72: 原料 | N72: 生原紙 | O72: * | P72: * | Q72: J0001 | R72: 41 | S72: 3 | U72: 生原紙 | V72: 商品購買 | BF72: 0 | BG72: 0 | BH72: 0 | BI72: 0 | BJ72: 0 | BK72: 0 | BL72: 0 | BM72: 0 | BN72: 0 | BO72: 0 | BS72: 0
... F78: M111 | G78: 40 | H78: 6 | I78: 600 | J78: 1 | K78: * | L78: 原紙 | M78: 原料 | N78: 印刷原紙 | O78: 諸口 | P78: * | Q78: J0001 | R78: 42 | S78: 4 | U78: 印刷原紙 | V78: 商品購買（諸口）、経費品 | BF78: 0 | BG78: 0 | BH78: 0 | BI78: 0 | BJ78: 0 | BK78: 0 | BL78: 0 | BM78: 0 | BN78: 0 | BO78: 0 | BS78: 0

Sheet 補足説明資料_受注画面制御
A1: =[3]表紙!A54 -> Webシステム | O1: 文書名 | AC1: モジュールID | AJ1: =[3]表紙!AJ64 -> MSBB | AQ1: モジュール名 | AX1: =[3]表紙!AX64 -> Webシステム | BL1: 文書番号 | BU1: Version | CB1: Rev.
O2: =[3]表紙!O65 -> 表紙 | AC2: サブモジュールID | AJ2: =[3]表紙!AJ65 -> MSBBPA070 | AQ2: サブモジュール名 | AX2: =[3]表紙!AX65 -> 0 | BL2: =[3]表紙!BL65 -> 0 | BU2: =[3]表紙!BU65 -> 0 | CB2: =[3]表紙!CB65 -> 0
O3: =RIGHT(CELL("filename",$A$1),LEN(CELL("filename",$A$1))-FIND("]",CELL("filename",$A$1))) -> 補足説明資料_受注画面制御 | AC3: 表題 | AJ3: =[3]表紙!AJ66 -> 0 | AQ3: =[3]表紙!AQ66 -> 0
AO5: 補足説明
V7: 受注業務パタン | CJ7: V7.0 画面制御の追加 | CV7: V8.0 受注画面制御の詳細化
G8: 画面項目 | V8: 加工受注 | AB8: シート受注 | AH8: 商品購買 | AN8: 版型 | AT8: 有償支給 | AZ8: 経費品 | BF8: 原紙売り（受発注方式） | BL8: 輪切り | CJ8: V7.0 画面制御の追加 | CV8: V8.0 受注画面制御の詳細化
G9: 第1画面（TOP画面） 基本情報 | V9: ○ | AB9: ○ | AH9: ○ | AN9: ● | AT9: ○ | AZ9: ○ | BF9: ○ | BL9: ○ | CJ9: V7.0 画面制御の追加 | CV9: V8.0 受注画面制御の詳細化
G10: 第1画面（TOP画面） 受注明細 | V10: ○ | AB10: - | AH10: - | AN10: - | AT10: - | AZ10: - | BF10: - | BL10: - | CJ10: V7.0 画面制御の追加 | CV10: V8.0 受注画面制御の詳細化
G11: 第2画面（基本情報）基本情報 | V11: 〇 | AB11: 〇 | AH11: 〇 | AN11: ● | AT11: 〇 | AZ11: 〇 | BF11: ○ | BL11: ○ | CJ11: V7.0 画面制御の追加 | CV11: V8.0 受注画面制御の詳細化
G12: 第2画面（基本情報）構成情報 | V12: ● | AB12: 〇 | AH12: - | AN12: ● | AT12: - | AZ12: - | BF12: ○ | BL12: ○ | CJ12: V7.0 画面制御の追加 | CV12: V8.0 受注画面制御の詳細化
G13: 第2画面（基本情報）仕入情報 | V13: 〇 | AB13: 〇 | AH13: 〇 | AN13: ● | AT13: - | AZ13: - | BF13: ○ | BL13: ○ | CJ13: V7.0 画面制御の追加 | CV13: V8.0 受注画面制御の詳細化
G14: 第2画面（基本情報）備考 | V14: 〇 | AB14: 〇 | AH14: 〇 | AN14: ● | AT14: ○ | AZ14: ○ | BF14: ○ | BL14: ○ | CJ14: V7.0 画面制御の追加 | CV14: V8.0 受注画面制御の詳細化
G15: 第3画面（工程情報）工程情報 | V15: ● | AB15: 〇 | AH15: - | AN15: - | AT15: - | AZ15: - | BF15: ○ | BL15: ○ | CJ15: V7.0 画面制御の追加 | CV15: V8.0 受注画面制御の詳細化
G16: ポップアップ（詳細入力画面）基本情報 | V16: ● | AB16: 〇 | AH16: - | AN16: - | AT16: - | AZ16: - | BF16: ○ | BL16: ○ | CJ16: V7.0 画面制御の追加 | CV16: V8.0 受注画面制御の詳細化
G17: ポップアップ（詳細入力画面）外注情報 | V17: ● | AB17: 〇 | AH17: - | AN17: - | AT17: - | AZ17: - | BF17: ○ | BL17: ○ | CJ17: V7.0 画面制御の追加 | CV17: V8.0 受注画面制御の詳細化
G18: ポップアップ（詳細入力画面）工程情報 | V18: ● | AB18: 〇 | AH18: - | AN18: - | AT18: - | AZ18: - | BF18: ○ | BL18: ○ | CJ18: V7.0 画面制御の追加 | CV18: V8.0 受注画面制御の詳細化
G19: ポップアップ（詳細入力画面）作業明細 | V19: ● | AB19: 〇 | AH19: - | AN19: - | AT19: - | AZ19: - | BF19: ○ | BL19: ○ | CJ19: V7.0 画面制御の追加 | CV19: V8.0 受注画面制御の詳細化
... G21: 第4画面（材料設定）材料明細 | V21: ● | AB21: 〇 | AH21: - | AN21: - | AT21: - | AZ21: - | BF21: ○ | BL21: ○ | CJ21: V7.0 画面制御の追加 | CV21: V8.0 受注画面制御の詳細化
CJ22: V7.0 画面制御の追加 | CV22: V8.0 受注画面制御の詳細化
G23: ※注釈 | CJ23: V7.0 画面制御の追加 | CV23: V8.0 受注画面制御の詳細化
H24: 〇：編集可能 | CJ24: V7.0 画面制御の追加 | CV24: V8.0 受注画面制御の詳細化
H25: ●：参照のみ | CJ25: V7.0 画面制御の追加 | CV25: V8.0 受注画面制御の詳細化
H26: -：非表示 | CJ26: V7.0 画面制御の追加 | CV26: V8.0 受注画面制御の詳細化
CJ27: V7.0 画面制御の追加 | CV27: V8.0 受注画面制御の詳細化
G28: 受注区分、製品区分の組合せがどの受注業務パタンにあたるかは「受発注パタン詳細」シート参照 | CJ28: V7.0 画面制御の追加 | CV28: V8.0 受注画面制御の詳細化
CJ29: V7.0 画面制御の追加 | CV29: V8.0 受注画面制御の詳細化
CV30: V8.0 受注画面制御の詳細化
CV31: V8.0 受注画面制御の詳細化
CV32: V8.0 受注画面制御の詳細化
CV33: V8.0 受注画面制御の詳細化
CV34: V8.0 受注画面制御の詳細化
CV35: V8.0 受注画面制御の詳細化
CV36: V8.0 受注画面制御の詳細化
CV37: V8.0 受注画面制御の詳細化
CV38: V8.0 受注画面制御の詳細化
CV39: V8.0 受注画面制御の詳細化
CV40: V8.0 受注画面制御の詳細化
CV41: V8.0 受注画面制御の詳細化
... CV184: V8.0 受注画面制御の詳細化

Sheet 1_加工受注
A3: 画面イメージ
B5: ≫凡例
Q6: ・・・ | S6: ボタン
C7: 見積計算書№ | Q7: ・・・ | S7: 検索項目(検索画面表示選択)
C8: 品名 | Q8: ・・・ | S8: 入力項目
C9: 得意先 | Q9: ・・・ | S9: 表示項目(得意先名称、原紙名等)
C10: 操作種別 | I10: ●登録 | M10: ○訂正 | Q10: ・・・ | S10: 選択項目(一つのみ選択可能)
C11: 受注区分 | Q11: ・・・ | S11: 選択項目(一つのみ選択可能)
C12: 作業順 | I12: ☑AAA | M12: ☑BBB | Q12: ・・・ | S12: 選択項目(複数選択可能)
B15: 〇加工品受注初期表示
D16: ログイン営業担当の部門が初期設定
C21: TOP画面
D23: 操作種別 | J23: ●登録 | N23: ○訂正 | R23: ○削除 | V23: ○参照 | FT23: 2022/10/29 落合 記載箇所が不明 | GG23: MDSOL回答 2022/10/31 手配NOの表示条件に追加しました。 2段表示は難しいとのことです。 | HI23: 2022/11/01 落合 問題なし
D24: 受注区分 | S24: 得意先 | AO24: 手配NO | BK24: ←「訂正」「削除」「参照」の時、初期フォーカス
D27: 受注部門 | J27: XXXXXX | O27: 名古屋営業 | AD27: 受注日 | AO27: 受注区分
D28: 得意先 | AD28: 客先納期 | AO28: 数量 | FE28: 2022/10/29 落合 記載箇所が不明 | FR28: MDSOL回答 2022/10/31 WEB受注一覧照会の設計書に追記しました。 | GN28: 2022/11/01 落合 問題なし
FU29: 2022/10/29 落合 入力中の受注を除いて既に超えている場合です。 | GQ29: MDSOL回答 2022/10/31 石田 承知しました。処理概要に得意先指定時（TOP画面、基本画面）を記載致しました。 | HY29: 2022/11/01 落合 問題なし
D30: 注文書No | W30: 先方担当 | AO30: 宛名 | BC30: 様 | EY30: 2022/10/29 落合 問題なし
D31: 運送会社 | W31: 出荷日時 | FD31: 2022/11/01 落合 問題なし
D33: 売価区分
D35: 受注明細
D36: 製品CD | J36: (件名:オートフィルタ) | AC36: ← ｾｯﾄ品目指定することで、以下の一覧に部材品目表示
D39: № | F39: 手配NO1 | I39: 手配NO2 | L39: 手配NO3 | O39: 製品CD/品目CD | T39: CP品名1 | Y39: CP品名2 | AB39: 単位 | AD39: 数量 | AG39: 特値 | AJ39: 個別単価 | AM39: ｾｯﾄ単価 | AP39: 客先納期 | AT39: 手配区分 | AW39: 納品先 | BA39: 納品先名 | BE39: 物流グループ | BH39: 預り売上 | BL39: 売上理由 | BP39: 受注№/受注明細№
E40: 1 | AG40: □ | BI40: □
E41: 2 | AG41: □ | BI41: □
E42: 3 | AG42: □ | BI42: □ | FD42: MDSOL回答 2022/10/31 コピー行追加で納期を変更した場合は、手配NOが同一となるため、まとめ期間内ならまとまります。行追加の場合は分割されます。 | GV42: 2022/11/01 落合 問題なし
F44: ※メニュー「シート受注入力」を選択した場合は、第２画面からスタート
F45: ※メニュー「購買品受注入力」を選択した場合は、第２画面からスタート。 工程情報登録はなし。 入力項目の追加あり。
B52: 〇受注基本情報を入力
C54: TOP画面
D56: 操作種別 | J56: ●登録 | N56: ○訂正 | R56: ○削除 | V56: ○参照
D57: 受注区分 | S57: 得意先 | AO57: 手配NO | BK57: ←「訂正」「削除」「参照」の時、初期フォーカス
D60: 受注部門 | J60: XXXXXX | O60: 名古屋営業 | AD60: 受注日 | AH60: 44622 | AO60: 受注区分 | AS60: 21：加工商品
D61: 得意先 | J61: XXXXXXX | Q61: 得意先A | AD61: 客先納期 | AH61: 44628 | AO61: 数量 | AS61: 5000
D63: 注文書No | J63: XXXXXXXXXXX | W63: 先方担当 | AC63: 田中 | AO63: 宛名 | AS63: 得意先A 営業部 田中 | BC63: 様
D64: 運送会社 | J64: XXXXXXX | O64: コダマ名古屋 | W64: 出荷日時 | AC64: 44627 | AH64: 0.5
D66: 売価区分 | J66: 単品売り
D68: 受注明細
D69: 製品CD | J69: 123456789010000 | Q69: セット品 | AC69: ← ｾｯﾄ品目指定することで、以下の一覧に部材品目表示
D72: № | F72: 手配NO1 | I72: 手配NO2 | L72: 手配NO3 | O72: 製品CD/品目CD | T72: CP品名1 | Y72: CP品名2 | AB72: 単位 | AD72: 数量 | AG72: 特値 | AJ72: 個別単価 | AM72: ｾｯﾄ単価 | AP72: 客先納期 | AT72: 手配区分 | AW72: 納品先 | BA72: 納品先名 | BE72: 物流グループ | BH72: 預り売上 | BL72: 売上理由 | BP72: 受注№/受注明細№
E73: 1 | O73: 123456789010001 | T73: CP品名 | Y73: 身 | AB73: 個 | AD73: 5000 | AG73: □ | AJ73: 100 | AP73: 44628 | AT73: 購買依頼 | BI73: □
E74: 2 | O74: 123456789010002 | T74: CP品名 | Y74: 蓋 | AB74: 個 | AD74: 5000 | AG74: □ | AJ74: 100 | AM74: 0 | AP74: 44628 | AT74: 購買依頼 | BI74: □
E75: 3 | O75: 123456789010003 | T75: CP品名 | Y75: 仕切り | AB75: 個 | AD75: 10000 | AG75: □ | AJ75: 50 | AM75: 0 | AP75: 44628 | AT75: 購買依頼 | BI75: □
B86: 〇第２画面初期表示
C87: 製品マスタと第1画面のインプットから初期表示
C88: 第２画面 | H88: ※部材の種類分、第２画面が連続して表示される
D89: 基本情報
D91: 納品先 | H91: XXXXXXX | O91: 手配区分 | T91: 購買依頼 | AA91: 預り売上 □ | AE91: 3000 | AJ91: 出荷日時 | AM91: 44627 | AR91: 0.5
D93: 売上WG | H93: 30 名古屋 | O93: 受注区分 | T93: 21：加工商品 | AC93: 製品区分 | AE93: 大 | AF93: 12 | AL93: 中 | AS93: 小
D94: 手配NO | O94: 案件NO | T94: XXXXXXXXX-XXX
D95: 得意先 | H95: XXXXXXX | O95: 得意先A | X95: 客先納期 | AB95: 44628
D96: 製品CD/品目CD | H96: 123456789010001 | O96: 顧客品名1 | S96: 顧客品名 | AI96: 顧客品名2 | AM96: 身
D97: 版型NO | O97: CP品名1 | S97: CP品名 | AI97: CP品名2 | AM97: 身
D98: 顧客注文№ | H98: XXXXXXXXXXX | O98: 顧客品番
D99: FSC製品区分 | O99: 食品安全
D101: 予備 | H101: 納入予備 | O101: 営業サンプル | Z101: 定数出荷 | AM101: 不適合手配NO
D103: 売上可否 | H103: 可
D105: 構成情報
D106: シート 段 | J106: E | O106: 原紙 | Z106: 印刷 | AI106: エンボス | AT106: メーカ
F107: 表 | J107: ECBAF | O107: コードボール270（Fﾐｯｸｽ） | Z107: 0000 | AI107: 00
F108: 中 | J108: EOO1R | O108: 中芯（Fリサイクル） | Z108: 0000 | AI108: 00
F109: 裏 | J109: E0928 | O109: 09ｺﾝﾗｲﾅｰ(Fﾐｯｸｽ 撥水（B1）) | Z109: 9507 | AI109: 00
D110: FSC受注区分
D111: 枚葉印刷 | J111: オフセット
D112: 刃渡り（mm) | J112: 巾 | L112: 790 | P112: 流れ | R112: 990 | V112: 咥え | Z112: 前後 | AB112: 10 | AF112: 左右 | AH112: 10
D113: シート寸法 | J113: 巾 | L113: 800 | P113: 流れ | R113: 1000 | U113: ※(抜き無し見積もり：刃渡り寸法が無いので、シート寸法を入力する。)
D114: 売上巾 | J114: 巾 | L114: 800
D115: 最終機械工程 | J115: グルア
D116: 数量 | J116: 5000 | P116: 数量単位 | W116: 枚 | Z116: 単価 | AF116: 100 | AI116: セット単価 | AT116: 単価単位 | BB116: 枚 | BE116: 特値 □
D118: 仕入情報
D119: 発注先 | J119: XXXXXX | P119: 発注先 | Z119: 発注単位 | AF119: 枚 | AI119: 発注単価 | AQ119: 90 | AT119: 単価単位 | BB119: 枚 | CL119: REV9.0 原紙売りとそれ以外の画面項目制御
D121: 備考
D122: 印刷備考 | J122: FSC管理NO・1614 | AD122: 製造備考 | AJ122: ｹﾞ7ｺｰﾄﾞ（文昌堂）支給 ｼｮｳﾜﾄﾞｳﾍ/4
D123: 納入備考 | J123: ｹﾞ7ｺｰﾄﾞ（文昌堂）支給 ｼｮｳﾜﾄﾞｳﾍ/4 | AD123: 伝票備考
D124: 出荷備考１ | J124: FSC.1614 オ＝ト | AD124: 出荷備考２ | AJ124: ｼｮｳﾜﾄﾞｳ/7 ﾓﾁｺﾐ ｶｰﾄﾝ/11
D125: 再製造備考 | Z125: 40byte
B135: 〇第3画面初期表示
C136: ３ページ目：工程情報画面
C137: 参照のみ
D138: 製品CD | G138: 123456789010001 | N138: 得意先 | X138: 顧客品名 | BI138: 出荷日時 | BL138: 2023/3/7 12:00
D139: ← 画面固定 →
D140: 工程 | F140: 工程名 | I140: 作業 | O140: WG | Q140: 号機／発注先 | V140: 号機 変更 不可 | X140: CP 配送 | AB140: 加工予定日 | AF140: 仕様／工程備考 | BH140: 版型 | BL140: 消耗品 | BP140: 外注費 | BT140: 製造設定 | BZ140: △
AB141: 加工予定日 | AF141: 仕様1 | AJ141: 仕様2 | AN141: 仕様3 | AR141: 仕様4 | AV141: 仕様5 | AZ141: 仕様6 | BD141: 仕様7 | BH141: 版型№ | BL141: 消耗品 | BP141: 仕入単価 | BT141: ﾛｽ率 (%) | BV141: 台数 (枚) | BX141: LT (日)
AF142: 工程備考１ | AV142: 工程備考２ | BP142: 指値(本支店)
D143: 0020 | F143: 輪転（グラビア）1 | I143: 00201 | K143: （輪転）グラビア1 | O143: 30 | Q143: 名古屋 輪転グラビア1号機 | V143: □ | X143: 移送 | AF143: 印刷CD | AJ143: 印刷回数 | AN143: 色数 | AR143: ﾆｽ区分 | AV143: ﾏｰｸ断裁
AF144: 9507 | AJ144: 1 | AN144: 3 | AR144: 1
AF145: 工程備考AAA | AV145: 工程備考BBB
D146: 0110 | F146: 片面コルゲータ | I146: 01101 | K146: 貼合 | O146: 30 | Q146: 小牧工場 片面コルゲータ | V146: □ | X146: □ | AB146: 44990 | AJ146: 全判巾 | AN146: 全判流れ | AR146: 巾変更 | BX146: 1
AJ147: 1350 | AN147: 814 | AR147: 1:不可
I149: 01102 | K149: コルスリ | AF149: 表巾 | AJ149: ｽﾘｯﾀｰ巾1 | AN149: ｽﾘｯﾀｰ流れ1 | AR149: ｽﾘｯﾀｰ巾2 | AV149: ｽﾘｯﾀｰ流れ2 | AZ149: コルスリ | BD149: 割り数
AJ150: 644 | AN150: 814 | AZ150: 3:化粧裁 | BD150: 2
AF151: 工程備考AAA | AV151: 工程備考BBB
D152: 0200 | F152: コートボール手配（表） | I152: 02001 | K152: ｺｰﾄﾎﾞｰﾙ手配 | O152: 40 | Q152: 外注：昭和堂 | V152: □ | X152: □ | Z152: □ | AF152: 巾 | AJ152: 流れ | AN152: 目なり | AR152: 連量 | AV152: ＠ | AZ152: 単位 | BD152: 特スキ
AF153: 650 | AJ153: 950 | AN153: 1.縦目 | AR153: 165 | AV153: 145 | AZ153: kg
I155: 02002 | K155: ｺｰﾄﾎﾞｰﾙ断裁 | AF155: 巾 | AJ155: 流れ
AF156: 650 | AJ156: 820
D158: 0440 | F158: 刷版手配(表) | I158: 04401 | K158: 刷版手配(表) | O158: 40 | Q158: 外注：昭和堂 | V158: □ | X158: □ | Z158: □ | AF158: 寸法 1.K | AJ158: 版作成 | AN158: 面付数 | AR158: 版数 | AV158: 抜きｽﾞﾚ防止ﾏｰｸ | AZ158: 面付番号 | BD158: 混入防止ﾏｰｸ
AJ159: 0:ﾌｨﾙﾑ 1:ＣＴＰ | AV159: 1.要 2.不可 | AZ159: 1.要 2.不可 | BD159: 1.要 2.不可
D161: 0450 | F161: オフセット印刷1 | I161: 04501 | K161: 製品情報 | O161: 40 | Q161: 外注：昭和堂 | V161: □ | X161: □ | Z161: □ | AF161: 原稿 | AJ161: ｸﾚｰﾑ情報 | AN161: ｸﾚｰﾑ対象工程
AF162: 0.ﾅｼ 1.原稿袋 2.図面ｼｽﾃﾑ | AJ162: 0.ﾅｼ 1.ｱﾘ | AN162: 1.ＡＬＬ 2.備考欄
...

Sheet 2_シート受注
A3: 画面イメージ
B5: ≫凡例
Q6: ・・・ | S6: ボタン
C7: 見積計算書№ | Q7: ・・・ | S7: 検索項目(検索画面表示選択)
C8: 品名 | Q8: ・・・ | S8: 入力項目
C9: 得意先 | Q9: ・・・ | S9: 表示項目(得意先名称、原紙名等)
C10: 操作種別 | I10: ●登録 | M10: ○訂正 | Q10: ・・・ | S10: 選択項目(一つのみ選択可能)
C11: 受注区分 | Q11: ・・・ | S11: 選択項目(一つのみ選択可能)
C12: 作業順 | I12: ☑AAA | M12: ☑BBB | Q12: ・・・ | S12: 選択項目(複数選択可能)
B15: 〇シート受注初期表示
D16: ログイン営業担当の部門が初期設定
C21: TOP画面
D23: 操作種別 | J23: ●登録 | N23: ○訂正 | R23: ○削除 | V23: ○参照 | FT23: 2022/10/29 落合 記載箇所が不明 | GG23: MDSOL回答 2022/10/31 手配NOの表示条件に追加しました。 2段表示は難しいとのことです。 | HI23: 2022/11/01 落合 問題なし
D24: 受注区分 | S24: 得意先 | AO24: 手配NO | BK24: ←「訂正」「削除」「参照」の時、初期フォーカス
D27: 受注部門 | J27: XXXXXX | O27: 名古屋営業 | AD27: 受注日 | AO27: 受注区分
D28: 得意先 | AD28: 客先納期 | AO28: 数量 | FE28: 2022/10/29 落合 記載箇所が不明 | FR28: MDSOL回答 2022/10/31 WEB受注一覧照会の設計書に追記しました。 | GN28: 2022/11/01 落合 問題なし
FU29: 2022/10/29 落合 入力中の受注を除いて既に超えている場合です。 | GQ29: MDSOL回答 2022/10/31 石田 承知しました。処理概要に得意先指定時（TOP画面、基本画面）を記載致しました。 | HY29: 2022/11/01 落合 問題なし
D30: 注文書No | W30: 先方担当 | AO30: 宛名 | BC30: 様 | EY30: 2022/10/29 落合 問題なし
D31: 運送会社 | W31: 出荷日時 | FD31: 2022/11/01 落合 問題なし
D33: 売価区分
D35: 受注明細
D36: 製品CD | J36: (件名:オートフィルタ) | AC36: ← ｾｯﾄ品目指定することで、以下の一覧に部材品目表示
D39: № | F39: 手配NO1 | I39: 手配NO2 | L39: 手配NO3 | O39: 製品CD/品目CD | T39: CP品名1 | Y39: CP品名2 | AB39: 単位 | AD39: 数量 | AG39: 特値 | AJ39: 個別単価 | AM39: ｾｯﾄ単価 | AP39: 客先納期 | AT39: 手配区分 | AW39: 納品先 | BA39: 納品先名 | BE39: 物流グループ | BH39: 預り売上 | BL39: 売上理由 | BP39: 受注№/受注明細№
E40: 1 | AG40: □ | BI40: □
E41: 2 | AG41: □ | BI41: □
E42: 3 | AG42: □ | BI42: □ | FD42: MDSOL回答 2022/10/31 コピー行追加で納期を変更した場合は、手配NOが同一となるため、まとめ期間内ならまとまります。行追加の場合は分割されます。 | GV42: 2022/11/01 落合 問題なし
F44: ※メニュー「シート受注入力」を選択した場合は、第２画面からスタート
F45: ※メニュー「購買品受注入力」を選択した場合は、第２画面からスタート。 工程情報登録はなし。 入力項目の追加あり。
B52: 〇受注基本情報を入力
C54: TOP画面
D56: 操作種別 | J56: ●登録 | N56: ○訂正 | R56: ○削除 | V56: ○参照
D57: 受注区分 | S57: 得意先 | AO57: 手配NO | BK57: ←「訂正」「削除」「参照」の時、初期フォーカス
D60: 受注部門 | J60: XXXXXX | O60: 名古屋営業 | AD60: 受注日 | AH60: 44622 | AO60: 受注区分 | AS60: 11：シート商品
D61: 得意先 | J61: XXXXXXX | Q61: 得意先A | AD61: 客先納期 | AH61: 44628 | AO61: 数量 | AS61: 5000
D63: 注文書No | J63: XXXXXXXXXXX | W63: 先方担当 | AC63: 田中 | AO63: 宛名 | AS63: 得意先A 営業部 田中 | BC63: 様
D64: 運送会社 | J64: XXXXXXX | O64: コダマ名古屋 | W64: 出荷日時 | AC64: 44627 | AH64: 0.5
D66: 売価区分 | J66: 単品売り
B78: 〇第２画面初期表示
C79: 第1画面のインプットから初期表示
C80: 第２画面
D81: 基本情報
D83: 納品先 | H83: XXXXXXX | O83: 手配区分 | T83: 購買依頼 | AA83: 預り売上 □ | AJ83: 出荷日時 | AM83: 44627 | AR83: 0.5
D85: 売上WG | H85: 30 名古屋 | O85: 受注区分 | T85: 11：シート商品 | AC85: 製品区分 | AE85: 大 | AF85: 11 | AL85: 中 | AS85: 小
D86: 手配NO | O86: 案件NO | T86: XXXXXXXXX-XXX
D87: 得意先 | H87: XXXXXXX | O87: 得意先A | X87: 客先納期 | AB87: 44628
D88: 製品CD/品目CD | H88: XXXXXXXXXXX | O88: 顧客品名1 | AI88: 顧客品名2
D89: 版型NO | O89: CP品名1 | AI89: CP品名2
D90: 顧客注文№ | H90: XXXXXXXXXXX | O90: 顧客品番
D91: FSC製品区分 | O91: 食品安全
D93: 予備 | H93: 納入予備 | O93: 営業サンプル | Z93: 定数出荷 | AM93: 不適合手配NO
D95: 売上可否 | H95: 可
D97: 構成情報
D98: シート 段 | O98: 原紙 | Z98: 印刷 | AI98: エンボス | AT98: メーカ
F99: 表
F100: 中
F101: 裏
D102: FSC受注区分
D103: 枚葉印刷
D104: 刃渡り（mm) | J104: 巾 | P104: 流れ | V104: 咥え | Z104: 前後 | AF104: 左右
D105: シート寸法 | J105: 巾 | P105: 流れ | U105: ※(抜き無し見積もり：刃渡り寸法が無いので、シート寸法を入力する。)
D106: 売上巾 | J106: 巾
D107: 最終機械工程
D108: 数量 | J108: 5000 | P108: 数量単位 | W108: 枚 | Z108: 単価 | AI108: セット単価 | AT108: 単価単位 | BE108: 特値 □
D110: 仕入情報
D111: 発注先 | Z111: 発注単位 | AI111: 発注単価 | AT111: 単価単位 | CL111: REV9.0 原紙売りとそれ以外の画面項目制御
D113: 備考
D114: 印刷備考 | AD114: 製造備考
D115: 納入備考 | AD115: 伝票備考
D116: 出荷備考１ | AD116: 出荷備考２
D117: 再製造備考
B137: 〇第２画面インプット
C138: 第1画面のインプットから初期表示
C139: 第２画面
D140: 基本情報
D142: 納品先 | H142: XXXXXXX | O142: 手配区分 | T142: 購買依頼 | AA142: 預り売上 □ | AE142: 3000 | AJ142: 出荷日時 | AM142: 44627 | AR142: 0.5
D144: 売上WG | H144: 30 名古屋 | O144: 受注区分 | T144: 21：加工商品 | AC144: 製品区分 | AE144: 大 | AF144: 12 | AL144: 中 | AS144: 小
D145: 手配NO | O145: 案件NO | T145: XXXXXXXXX-XXX
D146: 得意先 | H146: XXXXXXX | O146: 得意先A | X146: 客先納期 | AB146: 44628
D147: 製品CD/品目CD | H147: XXXXXXXXXXX | O147: 顧客品名1 | S147: 顧客品名 | AI147: 顧客品名2 | AM147: 身
D148: 版型NO | O148: CP品名1 | S148: CP品名 | AI148: CP品名2 | AM148: 身
D149: 顧客注文№ | H149: XXXXXXXXXXX | O149: 顧客品番
D150: FSC製品区分 | O150: 食品安全
D152: 予備 | H152: 納入予備 | O152: 営業サンプル | Z152: 定数出荷 | AM152: 不適合手配NO
D154: 売上可否 | H154: 可
D156: 構成情報
D157: シート 段 | J157: E | O157: 原紙 | Z157: 印刷 | AI157: エンボス | AT157: メーカ
F158: 表 | J158: ECBAF | O158: コードボール270（Fﾐｯｸｽ） | Z158: 0000 | AI158: 00
F159: 中 | J159: EOO1R | O159: 中芯（Fリサイクル） | Z159: 0000 | AI159: 00
F160: 裏 | J160: E928 | O160: 09ｺﾝﾗｲﾅｰ(Fﾐｯｸｽ 撥水（B1）) | Z160: 9507 | AI160: 00
D161: FSC受注区分
D162: 枚葉印刷 | J162: オフセット
D163: 刃渡り（mm) | J163: 巾 | L163: 790 | P163: 流れ | R163: 990 | V163: 咥え | Z163: 前後 | AB163: 10 | AF163: 左右 | AH163: 10
D164: シート寸法 | J164: 巾 | L164: 800 | P164: 流れ | R164: 1000 | U164: ※(抜き無し見積もり：刃渡り寸法が無いので、シート寸法を入力する。)
D165: 売上巾 | J165: 巾 | L165: 800
D166: 最終機械工程 | J166: グルア
D167: 数量 | J167: 5000 | P167: 数量単位 | W167: 枚 | Z167: 単価 | AF167: 100 | AI167: セット単価 | AT167: 単価単位 | BB167: 枚 | BE167: 特値 □
D169: 仕入情報
D170: 発注先 | J170: XXXXXX | P170: 発注先 | Z170: 発注単位 | AF170: 枚 | AI170: 発注単価 | AQ170: 90 | AT170: 単価単位 | BB170: 枚 | CL170: REV9.0 原紙売りとそれ以外の画面項目制御
D172: 備考
D173: 印刷備考 | J173: FSC管理NO・1614 | AD173: 製造備考 | AJ173: ｹﾞ7ｺｰﾄﾞ（文昌堂）支給 ｼｮｳﾜﾄﾞｳﾍ/4
...

Sheet 3_商品購買
A3: 画面イメージ
B5: ≫凡例
Q6: ・・・ | S6: ボタン
C7: 見積計算書№ | Q7: ・・・ | S7: 検索項目(検索画面表示選択)
C8: 品名 | Q8: ・・・ | S8: 入力項目
C9: 得意先 | Q9: ・・・ | S9: 表示項目(得意先名称、原紙名等)
C10: 操作種別 | I10: ●登録 | M10: ○訂正 | Q10: ・・・ | S10: 選択項目(一つのみ選択可能)
C11: 受注区分 | Q11: ・・・ | S11: 選択項目(一つのみ選択可能)
C12: 作業順 | I12: ☑AAA | M12: ☑BBB | Q12: ・・・ | S12: 選択項目(複数選択可能)
B15: 〇商品購買初期表示
D16: ログイン営業担当の部門が初期設定
C21: TOP画面
D23: 操作種別 | J23: ●登録 | N23: ○訂正 | R23: ○削除 | V23: ○参照 | FT23: 2022/10/29 落合 記載箇所が不明 | GG23: MDSOL回答 2022/10/31 手配NOの表示条件に追加しました。 2段表示は難しいとのことです。 | HI23: 2022/11/01 落合 問題なし
D24: 受注区分 | S24: 得意先 | AO24: 手配NO | BK24: ←「訂正」「削除」「参照」の時、初期フォーカス
D27: 受注部門 | J27: XXXXXX | O27: 名古屋営業 | AD27: 受注日 | AO27: 受注区分
D28: 得意先 | AD28: 客先納期 | AO28: 数量 | FE28: 2022/10/29 落合 記載箇所が不明 | FR28: MDSOL回答 2022/10/31 WEB受注一覧照会の設計書に追記しました。 | GN28: 2022/11/01 落合 問題なし
FU29: 2022/10/29 落合 入力中の受注を除いて既に超えている場合です。 | GQ29: MDSOL回答 2022/10/31 石田 承知しました。処理概要に得意先指定時（TOP画面、基本画面）を記載致しました。 | HY29: 2022/11/01 落合 問題なし
D30: 注文書No | W30: 先方担当 | AO30: 宛名 | BC30: 様 | EY30: 2022/10/29 落合 問題なし
D31: 運送会社 | W31: 出荷日時 | FD31: 2022/11/01 落合 問題なし
D33: 売価区分
D35: 受注明細
D36: 製品CD | J36: (件名:オートフィルタ) | AC36: ← ｾｯﾄ品目指定することで、以下の一覧に部材品目表示
D39: № | F39: 手配NO1 | I39: 手配NO2 | L39: 手配NO3 | O39: 製品CD/品目CD | T39: CP品名1 | Y39: CP品名2 | AB39: 単位 | AD39: 数量 | AG39: 特値 | AJ39: 個別単価 | AM39: ｾｯﾄ単価 | AP39: 客先納期 | AT39: 手配区分 | AW39: 納品先 | BA39: 納品先名 | BE39: 物流グループ | BH39: 預り売上 | BL39: 売上理由 | BP39: 受注№/受注明細№
E40: 1 | AG40: □ | BI40: □
E41: 2 | AG41: □ | BI41: □
E42: 3 | AG42: □ | BI42: □ | FD42: MDSOL回答 2022/10/31 コピー行追加で納期を変更した場合は、手配NOが同一となるため、まとめ期間内ならまとまります。行追加の場合は分割されます。 | GV42: 2022/11/01 落合 問題なし
F44: ※メニュー「シート受注入力」を選択した場合は、第２画面からスタート
F45: ※メニュー「購買品受注入力」を選択した場合は、第２画面からスタート。 工程情報登録はなし。 入力項目の追加あり。
B52: 〇受注基本情報を入力
C54: TOP画面
D56: 操作種別 | J56: ●登録 | N56: ○訂正 | R56: ○削除 | V56: ○参照
D57: 受注区分 | S57: 得意先 | AO57: 手配NO | BK57: ←「訂正」「削除」「参照」の時、初期フォーカス
D60: 受注部門 | J60: XXXXXX | O60: 名古屋営業 | AD60: 受注日 | AH60: 44622 | AO60: 受注区分 | AS60: 30：購買品
D61: 得意先 | J61: XXXXXXX | Q61: 得意先A | AD61: 客先納期 | AH61: 44628 | AO61: 数量 | AS61: 5000
D63: 注文書No | J63: XXXXXXXXXXX | W63: 先方担当 | AC63: 田中 | AO63: 宛名 | AS63: 得意先A 営業部 田中 | BC63: 様
D64: 運送会社 | J64: XXXXXXX | O64: コダマ名古屋 | W64: 出荷日時 | AC64: 44627 | AH64: 0.5
D66: 売価区分 | J66: 単品売り
B78: 〇第２画面初期表示
C79: 第1画面のインプットから初期表示
C80: 第２画面
D81: 基本情報
D83: 納品先 | H83: XXXXXXX | O83: 手配区分 | T83: 購買依頼 | AA83: 預り売上 □ | AJ83: 出荷日時 | AM83: 44627 | AR83: 0.5
D85: 売上WG | H85: 30 名古屋 | O85: 受注区分 | T85: 30:購買品 | AC85: 製品区分 | AE85: 大 | AL85: 中 | AS85: 小
D86: 手配NO | O86: 案件NO | T86: XXXXXXXXX-XXX
D87: 得意先 | H87: XXXXXXX | O87: 得意先A | X87: 客先納期 | AB87: 44628
D88: 製品CD/品目CD | H88: XXXXXXXX | O88: 顧客品名1 | AI88: 顧客品名2
D89: 版型NO | O89: CP品名1 | AI89: CP品名2
D90: 顧客注文№ | H90: XXXXXXXXXXX | O90: 顧客品番
D91: FSC製品区分 | O91: 食品安全
D93: 予備 | H93: 納入予備 | O93: 営業サンプル | Z93: 定数出荷 | AM93: 不適合手配NO
D95: 売上可否 | H95: 可
D97: 構成情報
D98: シート 段 | O98: 原紙 | Z98: 印刷 | AI98: エンボス | AT98: メーカ
F99: 表
F100: 中
F101: 裏
D102: FSC受注区分
D103: 枚葉印刷
D104: 刃渡り（mm) | J104: 巾 | P104: 流れ | V104: 咥え | Z104: 前後 | AF104: 左右
D105: シート寸法 | J105: 巾 | P105: 流れ | U105: ※(抜き無し見積もり：刃渡り寸法が無いので、シート寸法を入力する。)
D106: 売上巾 | J106: 巾
D107: 最終機械工程
D108: 数量 | P108: 数量単位 | Z108: 単価 | AI108: セット単価 | AT108: 単価単位 | BE108: 特値 □
D110: 仕入情報
D111: 発注先 | Z111: 発注単位 | AI111: 発注単価 | AT111: 単価単位 | CL111: REV9.0 原紙売りとそれ以外の画面項目制御
D113: 備考
D114: 印刷備考 | AD114: 製造備考
D115: 納入備考 | AD115: 伝票備考
D116: 出荷備考１ | AD116: 出荷備考２
D117: 再製造備考
B139: 〇第２画面インプット
C140: 第1画面のインプットから初期表示
C141: 第２画面
D142: 基本情報
D144: 納品先 | H144: XXXXXXX | O144: 手配区分 | T144: 購買依頼 | AA144: 預り売上 □ | AE144: 2000 | AJ144: 出荷日時 | AM144: 44627 | AR144: 0.5
D146: 売上WG | H146: 30 名古屋 | O146: 受注区分 | T146: 30:購買品 | AC146: 製品区分 | AE146: 大 | AF146: 51：外装シート | AL146: 中 | AS146: 小
D147: 手配NO | O147: 案件NO | T147: XXXXXXXXX-XXX
D148: 得意先 | H148: XXXXXXX | O148: 得意先A | X148: 客先納期 | AB148: 44628
D149: 製品CD/品目CD | H149: XXXXXXXXXXX | O149: 顧客品名1 | S149: 顧客品名 | AI149: 顧客品名2 | AM149: 身
D150: 版型NO | O150: CP品名1 | S150: CP品名 | AI150: CP品名2 | AM150: 身
D151: 顧客注文№ | H151: XXXXXXXXXXX | O151: 顧客品番
D152: FSC製品区分 | O152: 食品安全
D154: 予備 | H154: 納入予備 | O154: 営業サンプル | Z154: 定数出荷 | AM154: 不適合手配NO
D156: 売上可否 | H156: 可
D158: 構成情報
D159: シート 段 | O159: 原紙 | Z159: 印刷 | AI159: エンボス | AT159: メーカ
F160: 表
F161: 中
F162: 裏
D163: FSC受注区分
D164: 枚葉印刷
D165: 刃渡り（mm) | J165: 巾 | P165: 流れ | V165: 咥え | Z165: 前後 | AF165: 左右
D166: シート寸法 | J166: 巾 | P166: 流れ | U166: ※(抜き無し見積もり：刃渡り寸法が無いので、シート寸法を入力する。)
D167: 売上巾 | J167: 巾
D168: 最終機械工程
D169: 数量 | J169: 5000 | P169: 数量単位 | W169: 枚 | Z169: 単価 | AF169: 100 | AI169: セット単価 | AT169: 単価単位 | BB169: 枚 | BE169: 特値 □
D171: 仕入情報
D172: 発注先 | J172: XXXXXX | P172: 発注先 | Z172: 発注単位 | AF172: 枚 | AI172: 発注単価 | AQ172: 90 | AT172: 単価単位 | BB172: 枚 | CL172: REV9.0 原紙売りとそれ以外の画面項目制御
D174: 備考
D175: 印刷備考 | J175: FSC管理NO・1614 | AD175: 製造備考 | AJ175: ｹﾞ7ｺｰﾄﾞ（文昌堂）支給 ｼｮｳﾜﾄﾞｳﾍ/4
...

Sheet 3_商品購買（版型）
A3: 画面イメージ
B5: ≫凡例
Q6: ・・・ | S6: ボタン
C7: 見積計算書№ | Q7: ・・・ | S7: 検索項目(検索画面表示選択)
C8: 品名 | Q8: ・・・ | S8: 入力項目
C9: 得意先 | Q9: ・・・ | S9: 表示項目(得意先名称、原紙名等)
C10: 操作種別 | I10: ●登録 | M10: ○訂正 | Q10: ・・・ | S10: 選択項目(一つのみ選択可能)
C11: 受注区分 | Q11: ・・・ | S11: 選択項目(一つのみ選択可能)
C12: 作業順 | I12: ☑AAA | M12: ☑BBB | Q12: ・・・ | S12: 選択項目(複数選択可能)
B15: 〇版型受注表示
D16: ログイン営業担当の部門が初期設定
C21: TOP画面
D23: 操作種別 | J23: ●登録 | N23: ○訂正 | R23: ○削除 | V23: ○参照 | FT23: 2022/10/29 落合 記載箇所が不明 | GG23: MDSOL回答 2022/10/31 手配NOの表示条件に追加しました。 2段表示は難しいとのことです。 | HI23: 2022/11/01 落合 問題なし
D24: 受注区分 | S24: 得意先 | AO24: 手配NO | BK24: ←「訂正」「削除」「参照」の時、初期フォーカス
D27: 受注部門 | J27: XXXXXX | O27: 名古屋営業 | AD27: 受注日 | AO27: 受注区分
D28: 得意先 | AD28: 客先納期 | AO28: 数量 | FE28: 2022/10/29 落合 記載箇所が不明 | FR28: MDSOL回答 2022/10/31 WEB受注一覧照会の設計書に追記しました。 | GN28: 2022/11/01 落合 問題なし
FU29: 2022/10/29 落合 入力中の受注を除いて既に超えている場合です。 | GQ29: MDSOL回答 2022/10/31 石田 承知しました。処理概要に得意先指定時（TOP画面、基本画面）を記載致しました。 | HY29: 2022/11/01 落合 問題なし
D30: 注文書No | W30: 先方担当 | AO30: 宛名 | BC30: 様 | EY30: 2022/10/29 落合 問題なし
D31: 運送会社 | W31: 出荷日時 | FD31: 2022/11/01 落合 問題なし
D33: 売価区分
D35: 受注明細
D36: 製品CD | J36: (件名:オートフィルタ) | AC36: ← ｾｯﾄ品目指定することで、以下の一覧に部材品目表示
D39: № | F39: 手配NO1 | I39: 手配NO2 | L39: 手配NO3 | O39: 製品CD/品目CD | T39: CP品名1 | Y39: CP品名2 | AB39: 単位 | AD39: 数量 | AG39: 特値 | AJ39: 個別単価 | AM39: ｾｯﾄ単価 | AP39: 客先納期 | AT39: 手配区分 | AW39: 納品先 | BA39: 納品先名 | BE39: 物流グループ | BH39: 預り売上 | BL39: 売上理由 | BP39: 受注№/受注明細№
E40: 1 | AG40: □ | BI40: □
E41: 2 | AG41: □ | BI41: □
E42: 3 | AG42: □ | BI42: □ | FD42: MDSOL回答 2022/10/31 コピー行追加で納期を変更した場合は、手配NOが同一となるため、まとめ期間内ならまとまります。行追加の場合は分割されます。 | GV42: 2022/11/01 落合 問題なし
F44: ※メニュー「シート受注入力」を選択した場合は、第２画面からスタート
F45: ※メニュー「購買品受注入力」を選択した場合は、第２画面からスタート。 工程情報登録はなし。 入力項目の追加あり。
B52: 〇参照モードにして手配NOを入力し検索する
C54: TOP画面
D56: 操作種別 | J56: ○登録 | N56: ○訂正 | R56: ○削除 | V56: ●参照
D57: 受注区分 | S57: 得意先 | AO57: 手配NO | AR57: XXXXXXXXXX | BK57: ←「訂正」「削除」「参照」の時、初期フォーカス
D60: 受注部門 | J60: XXXXXX | O60: 名古屋営業 | AD60: 受注日 | AH60: 44622 | AO60: 受注区分 | AS60: 30：購買品
D61: 得意先 | J61: XXXXXXX | Q61: 得意先A | AD61: 客先納期 | AH61: 44628 | AO61: 数量 | AS61: 1
D63: 注文書No | J63: XXXXXXXXXXX | W63: 先方担当 | AC63: 田中 | AO63: 宛名 | AS63: 得意先A 営業部 田中 | BC63: 様
D64: 運送会社 | J64: XXXXXXX | O64: コダマ名古屋 | W64: 出荷日時 | AC64: 44627 | AH64: 0.5
D66: 売価区分 | J66: 単品売り
B79: 〇第２画面初期表示
C80: 第1画面のインプットから初期表示
C81: 第２画面
D82: 基本情報
D84: 納品先 | H84: XXXXXXX | O84: 手配区分 | T84: 購買依頼 | AA84: 預り売上 □ | AE84: 1 | AJ84: 出荷日時 | AM84: 44627 | AR84: 0.5
D86: 売上WG | H86: 30 名古屋 | O86: 受注区分 | T86: 30：商品購買 | AC86: 製品区分 | AE86: 大 | AF86: 61：版型 | AL86: 中 | AS86: 小
D87: 手配NO | O87: 案件NO | T87: XXXXXXXXX-XXX
D88: 得意先 | H88: XXXXXXX | O88: 得意先A | X88: 客先納期 | AB88: 44628
D89: 製品CD/品目CD | H89: H1234567 | O89: 顧客品名1 | S89: 顧客品名 | AI89: 顧客品名2 | AM89: 身
D90: 版型NO | O90: CP品名1 | S90: CP品名 | AI90: CP品名2 | AM90: 身
D91: 顧客注文№ | H91: XXXXXXXXXXX | O91: 顧客品番
D92: FSC製品区分 | O92: 食品安全
D94: 予備 | H94: 納入予備 | O94: 営業サンプル | Z94: 定数出荷 | AM94: 不適合手配NO
D96: 売上可否 | H96: 可
D98: 構成情報
D99: シート 段 | O99: 原紙 | Z99: 印刷 | AI99: エンボス | AT99: メーカ
F100: 表
F101: 中
F102: 裏
D103: FSC受注区分
D104: 枚葉印刷
D105: 刃渡り（mm) | J105: 巾 | P105: 流れ | V105: 咥え | Z105: 前後 | AF105: 左右
D106: シート寸法 | J106: 巾 | P106: 流れ | U106: ※(抜き無し見積もり：刃渡り寸法が無いので、シート寸法を入力する。)
D107: 売上巾 | J107: 巾
D108: 最終機械工程
D109: 数量 | J109: 1 | P109: 数量単位 | W109: 個 | Z109: 単価 | AF109: 100 | AI109: セット単価 | AT109: 単価単位 | BB109: 個 | BE109: 特値 □
D111: 仕入情報
D112: 発注先 | J112: XXXXXX | P112: 発注先 | Z112: 発注単位 | AF112: 個 | AI112: 発注単価 | AQ112: 90 | AT112: 単価単位 | BB112: 個 | CL112: REV9.0 原紙売りとそれ以外の画面項目制御
D114: 備考
D115: 印刷備考 | J115: FSC管理NO・1614 | AD115: 製造備考 | AJ115: ｹﾞ7ｺｰﾄﾞ（文昌堂）支給 ｼｮｳﾜﾄﾞｳﾍ/4
D116: 納入備考 | J116: ｹﾞ7ｺｰﾄﾞ（文昌堂）支給 ｼｮｳﾜﾄﾞｳﾍ/4 | AD116: 伝票備考
D117: 出荷備考１ | J117: FSC.1614 オ＝ト | AD117: 出荷備考２ | AJ117: ｼｮｳﾜﾄﾞｳ/7 ﾓﾁｺﾐ ｶｰﾄﾝ/11
D118: 再製造備考 | Z118: 40byte

Sheet 4_商品購買（有償支給）
A3: 画面イメージ
B5: ≫凡例
Q6: ・・・ | S6: ボタン
C7: 見積計算書№ | Q7: ・・・ | S7: 検索項目(検索画面表示選択)
C8: 品名 | Q8: ・・・ | S8: 入力項目
C9: 得意先 | Q9: ・・・ | S9: 表示項目(得意先名称、原紙名等)
C10: 操作種別 | I10: ●登録 | M10: ○訂正 | Q10: ・・・ | S10: 選択項目(一つのみ選択可能)
C11: 受注区分 | Q11: ・・・ | S11: 選択項目(一つのみ選択可能)
C12: 作業順 | I12: ☑AAA | M12: ☑BBB | Q12: ・・・ | S12: 選択項目(複数選択可能)
B15: 〇有償支給初期表示
D16: ログイン営業担当の部門が初期設定
C21: TOP画面
D23: 操作種別 | J23: ●登録 | N23: ○訂正 | R23: ○削除 | V23: ○参照 | FT23: 2022/10/29 落合 記載箇所が不明 | GG23: MDSOL回答 2022/10/31 手配NOの表示条件に追加しました。 2段表示は難しいとのことです。 | HI23: 2022/11/01 落合 問題なし
D24: 受注区分 | S24: 得意先 | AO24: 手配NO | BK24: ←「訂正」「削除」「参照」の時、初期フォーカス
D27: 受注部門 | J27: XXXXXX | O27: 名古屋営業 | AD27: 受注日 | AO27: 受注区分
D28: 得意先 | AD28: 客先納期 | AO28: 数量 | FE28: 2022/10/29 落合 記載箇所が不明 | FR28: MDSOL回答 2022/10/31 WEB受注一覧照会の設計書に追記しました。 | GN28: 2022/11/01 落合 問題なし
FU29: 2022/10/29 落合 入力中の受注を除いて既に超えている場合です。 | GQ29: MDSOL回答 2022/10/31 石田 承知しました。処理概要に得意先指定時（TOP画面、基本画面）を記載致しました。 | HY29: 2022/11/01 落合 問題なし
D30: 注文書No | W30: 先方担当 | AO30: 宛名 | BC30: 様 | EY30: 2022/10/29 落合 問題なし
D31: 運送会社 | W31: 出荷日時 | FD31: 2022/11/01 落合 問題なし
D33: 売価区分
D35: 受注明細
D36: 製品CD | J36: (件名:オートフィルタ) | AC36: ← ｾｯﾄ品目指定することで、以下の一覧に部材品目表示
D39: № | F39: 手配NO1 | I39: 手配NO2 | L39: 手配NO3 | O39: 製品CD/品目CD | T39: CP品名1 | Y39: CP品名2 | AB39: 単位 | AD39: 数量 | AG39: 特値 | AJ39: 個別単価 | AM39: ｾｯﾄ単価 | AP39: 客先納期 | AT39: 手配区分 | AW39: 納品先 | BA39: 納品先名 | BE39: 物流グループ | BH39: 預り売上 | BL39: 売上理由 | BP39: 受注№/受注明細№
E40: 1 | AG40: □ | BI40: □
E41: 2 | AG41: □ | BI41: □
E42: 3 | AG42: □ | BI42: □ | FD42: MDSOL回答 2022/10/31 コピー行追加で納期を変更した場合は、手配NOが同一となるため、まとめ期間内ならまとまります。行追加の場合は分割されます。 | GV42: 2022/11/01 落合 問題なし
F44: ※メニュー「シート受注入力」を選択した場合は、第２画面からスタート
F45: ※メニュー「購買品受注入力」を選択した場合は、第２画面からスタート。 工程情報登録はなし。 入力項目の追加あり。
B52: 〇受注基本情報を入力
C54: TOP画面
D56: 操作種別 | J56: ●登録 | N56: ○訂正 | R56: ○削除 | V56: ○参照
D57: 受注区分 | S57: 得意先 | AO57: 手配NO | BK57: ←「訂正」「削除」「参照」の時、初期フォーカス
D60: 受注部門 | J60: XXXXXX | O60: 名古屋営業 | AD60: 受注日 | AH60: 44622 | AO60: 受注区分 | AS60: 30：購買品
D61: 得意先 | J61: XXXXXXX | Q61: 得意先A | AD61: 客先納期 | AH61: 44628 | AO61: 数量 | AS61: 1
D63: 注文書No | J63: XXXXXXXXXXX | W63: 先方担当 | AC63: 田中 | AO63: 宛名 | AS63: 得意先A 営業部 田中 | BC63: 様
D64: 運送会社 | J64: XXXXXXX | O64: コダマ名古屋 | W64: 出荷日時 | AC64: 44627 | AH64: 0.5
D66: 売価区分 | J66: 単品売り
B78: 〇第２画面初期表示
C79: 第1画面のインプットから初期表示
C80: 第２画面
D81: 基本情報
D83: 納品先 | H83: XXXXXXX | O83: 手配区分 | T83: 購買依頼 | AA83: 預り売上 □ | AJ83: 出荷日時 | AM83: 44627 | AR83: 0.5
D85: 売上WG | H85: 30 名古屋 | O85: 受注区分 | T85: 30：購買品 | AC85: 製品区分 | AE85: 大 | AL85: 中 | AS85: 小
D86: 手配NO | O86: 案件NO | T86: XXXXXXXXX-XXX
D87: 得意先 | H87: XXXXXXX | O87: 得意先A | X87: 客先納期 | AB87: 44628
D88: 製品CD/品目CD | H88: XXXXXXXXXXX | O88: 顧客品名1 | AI88: 顧客品名2
D89: 版型NO | O89: CP品名1 | AI89: CP品名2
D90: 顧客注文№ | H90: XXXXXXXXXXX | O90: 顧客品番
D91: FSC製品区分 | O91: 食品安全
D93: 予備 | H93: 納入予備 | O93: 営業サンプル | Z93: 定数出荷 | AM93: 不適合手配NO
D95: 売上可否 | H95: 可
D97: 構成情報
D98: シート 段 | O98: 原紙 | Z98: 印刷 | AI98: エンボス | AT98: メーカ
F99: 表
F100: 中
F101: 裏
D102: FSC受注区分
D103: 枚葉印刷
D104: 刃渡り（mm) | J104: 巾 | P104: 流れ | V104: 咥え | Z104: 前後 | AF104: 左右
D105: シート寸法 | J105: 巾 | P105: 流れ | U105: ※(抜き無し見積もり：刃渡り寸法が無いので、シート寸法を入力する。)
D106: 売上巾 | J106: 巾
D107: 最終機械工程
D108: 数量 | J108: 1 | P108: 数量単位 | Z108: 単価 | AI108: セット単価 | AT108: 単価単位 | BE108: 特値 □
D110: 仕入情報
D111: 発注先 | Z111: 発注単位 | AI111: 発注単価 | AT111: 単価単位 | CL111: REV9.0 原紙売りとそれ以外の画面項目制御
D113: 備考
D114: 印刷備考 | AD114: 製造備考
D115: 納入備考 | AD115: 伝票備考
D116: 出荷備考１ | AD116: 出荷備考２
D117: 再製造備考
B139: 〇第２画面インプット
C140: 第1画面のインプットから初期表示
C141: 第２画面
D142: 基本情報
D144: 納品先 | H144: XXXXXXX | O144: 手配区分 | T144: 在庫引当 | AA144: 預り売上 □ | AJ144: 出荷日時 | AM144: 44627 | AR144: 0.5
D146: 売上WG | H146: 30 名古屋 | O146: 受注区分 | T146: 30：商品購買 | AC146: 製品区分 | AE146: 大 | AF146: 62：その他 | AL146: 中 | AS146: 小
D147: 手配NO | O147: 案件NO | T147: XXXXXXXXX-XXX
D148: 得意先 | H148: XXXXXXX | O148: 得意先A | X148: 客先納期 | AB148: 44628
D149: 製品CD/品目CD | H149: XXXXXXXX | O149: 顧客品名1 | S149: 顧客品名 | AI149: 顧客品名2 | AM149: 身
D150: 版型NO | O150: CP品名1 | S150: CP品名 | AI150: CP品名2 | AM150: 身
D151: 顧客注文№ | H151: XXXXXXXXXXX | O151: 顧客品番
D152: FSC製品区分 | O152: 食品安全
D154: 予備 | H154: 納入予備 | O154: 営業サンプル | Z154: 定数出荷 | AM154: 不適合手配NO
D156: 売上可否 | H156: 可
D158: 構成情報
D159: シート 段 | O159: 原紙 | Z159: 印刷 | AI159: エンボス | AT159: メーカ
F160: 表
F161: 中
F162: 裏
D163: FSC受注区分
D164: 枚葉印刷
D165: 刃渡り（mm) | J165: 巾 | P165: 流れ | V165: 咥え | Z165: 前後 | AF165: 左右
D166: シート寸法 | J166: 巾 | P166: 流れ | U166: ※(抜き無し見積もり：刃渡り寸法が無いので、シート寸法を入力する。)
D167: 売上巾 | J167: 巾
D168: 最終機械工程
D169: 数量 | J169: 1 | P169: 数量単位 | W169: 個 | Z169: 単価 | AD169: 50000 | AI169: セット単価 | AT169: 単価単位 | BB169: 個 | BE169: 特値 □
D171: 仕入情報
D172: 発注先 | Z172: 発注単位 | AI172: 発注単価 | AT172: 単価単位 | CL172: REV9.0 原紙売りとそれ以外の画面項目制御
D174: 備考
D175: 印刷備考 | AD175: 製造備考
...

Sheet 4_商品購買（諸口）
A3: 画面イメージ
B5: ≫凡例
Q6: ・・・ | S6: ボタン
C7: 見積計算書№ | Q7: ・・・ | S7: 検索項目(検索画面表示選択)
C8: 品名 | Q8: ・・・ | S8: 入力項目
C9: 得意先 | Q9: ・・・ | S9: 表示項目(得意先名称、原紙名等)
C10: 操作種別 | I10: ●登録 | M10: ○訂正 | Q10: ・・・ | S10: 選択項目(一つのみ選択可能)
C11: 受注区分 | Q11: ・・・ | S11: 選択項目(一つのみ選択可能)
C12: 作業順 | I12: ☑AAA | M12: ☑BBB | Q12: ・・・ | S12: 選択項目(複数選択可能)
B15: 〇経費品初期表示
D16: ログイン営業担当の部門が初期設定
C21: TOP画面
D23: 操作種別 | J23: ●登録 | N23: ○訂正 | R23: ○削除 | V23: ○参照 | FT23: 2022/10/29 落合 記載箇所が不明 | GG23: MDSOL回答 2022/10/31 手配NOの表示条件に追加しました。 2段表示は難しいとのことです。 | HI23: 2022/11/01 落合 問題なし
D24: 受注区分 | S24: 得意先 | AO24: 手配NO | BK24: ←「訂正」「削除」「参照」の時、初期フォーカス
D27: 受注部門 | J27: XXXXXX | O27: 名古屋営業 | AD27: 受注日 | AO27: 受注区分
D28: 得意先 | AD28: 客先納期 | AO28: 数量 | FE28: 2022/10/29 落合 記載箇所が不明 | FR28: MDSOL回答 2022/10/31 WEB受注一覧照会の設計書に追記しました。 | GN28: 2022/11/01 落合 問題なし
FU29: 2022/10/29 落合 入力中の受注を除いて既に超えている場合です。 | GQ29: MDSOL回答 2022/10/31 石田 承知しました。処理概要に得意先指定時（TOP画面、基本画面）を記載致しました。 | HY29: 2022/11/01 落合 問題なし
D30: 注文書No | W30: 先方担当 | AO30: 宛名 | BC30: 様 | EY30: 2022/10/29 落合 問題なし
D31: 運送会社 | W31: 出荷日時 | FD31: 2022/11/01 落合 問題なし
D33: 売価区分
D35: 受注明細
D36: 製品CD | J36: (件名:オートフィルタ) | AC36: ← ｾｯﾄ品目指定することで、以下の一覧に部材品目表示
D39: № | F39: 手配NO1 | I39: 手配NO2 | L39: 手配NO3 | O39: 製品CD/品目CD | T39: CP品名1 | Y39: CP品名2 | AB39: 単位 | AD39: 数量 | AG39: 特値 | AJ39: 個別単価 | AM39: ｾｯﾄ単価 | AP39: 客先納期 | AT39: 手配区分 | AW39: 納品先 | BA39: 納品先名 | BE39: 物流グループ | BH39: 預り売上 | BL39: 売上理由 | BP39: 受注№/受注明細№
E40: 1 | AG40: □ | BI40: □
E41: 2 | AG41: □ | BI41: □
E42: 3 | AG42: □ | BI42: □ | FD42: MDSOL回答 2022/10/31 コピー行追加で納期を変更した場合は、手配NOが同一となるため、まとめ期間内ならまとまります。行追加の場合は分割されます。 | GV42: 2022/11/01 落合 問題なし
F44: ※メニュー「シート受注入力」を選択した場合は、第２画面からスタート
F45: ※メニュー「購買品受注入力」を選択した場合は、第２画面からスタート。 工程情報登録はなし。 入力項目の追加あり。
B52: 〇受注基本情報を入力
C54: TOP画面
D56: 操作種別 | J56: ●登録 | N56: ○訂正 | R56: ○削除 | V56: ○参照
D57: 受注区分 | S57: 得意先 | AO57: 手配NO | BK57: ←「訂正」「削除」「参照」の時、初期フォーカス
D60: 受注部門 | J60: XXXXXX | O60: 名古屋営業 | AD60: 受注日 | AH60: 44622 | AO60: 受注区分 | AS60: 30：購買品
D61: 得意先 | J61: XXXXXXX | Q61: 得意先A | AD61: 客先納期 | AH61: 44628 | AO61: 数量 | AS61: 1
D63: 注文書No | J63: XXXXXXXXXXX | W63: 先方担当 | AC63: 田中 | AO63: 宛名 | AS63: 得意先A 営業部 田中 | BC63: 様
D64: 運送会社 | J64: XXXXXXX | O64: コダマ名古屋 | W64: 出荷日時 | AC64: 44627 | AH64: 0.5
D66: 売価区分 | J66: 単品売り
B78: 〇第２画面初期表示
C79: 第1画面のインプットから初期表示
C80: 第２画面
D81: 基本情報
D83: 納品先 | H83: XXXXXXX | O83: 手配区分 | T83: 購買依頼 | AA83: 預り売上 □ | AJ83: 出荷日時 | AM83: 44627 | AR83: 0.5
D85: 売上WG | H85: 30 名古屋 | O85: 受注区分 | T85: 30：購買品 | AC85: 製品区分 | AE85: 大 | AL85: 中 | AS85: 小
D86: 手配NO | O86: 案件NO | T86: XXXXXXXXX-XXX
D87: 得意先 | H87: XXXXXXX | O87: 得意先A | X87: 客先納期 | AB87: 44628
D88: 製品CD/品目CD | H88: XXXXXXX | O88: 顧客品名1 | AI88: 顧客品名2
D89: 版型NO | O89: CP品名1 | AI89: CP品名2
D90: 顧客注文№ | H90: XXXXXXXXXXX | O90: 顧客品番
D91: FSC製品区分 | O91: 食品安全
D93: 予備 | H93: 納入予備 | O93: 営業サンプル | Z93: 定数出荷 | AM93: 不適合手配NO
D95: 売上可否 | H95: 可
D97: 構成情報
D98: シート 段 | O98: 原紙 | Z98: 印刷 | AI98: エンボス | AT98: メーカ
F99: 表
F100: 中
F101: 裏
D102: FSC受注区分
D103: 枚葉印刷
D104: 刃渡り（mm) | J104: 巾 | P104: 流れ | V104: 咥え | Z104: 前後 | AF104: 左右
D105: シート寸法 | J105: 巾 | P105: 流れ | U105: ※(抜き無し見積もり：刃渡り寸法が無いので、シート寸法を入力する。)
D106: 売上巾 | J106: 巾
D107: 最終機械工程
D108: 数量 | P108: 数量単位 | Z108: 単価 | AI108: セット単価 | AT108: 単価単位 | BE108: 特値 □
D110: 仕入情報
D111: 発注先 | Z111: 発注単位 | AI111: 発注単価 | AT111: 単価単位 | CL111: REV9.0 原紙売りとそれ以外の画面項目制御
D113: 備考
D114: 印刷備考 | AD114: 製造備考
D115: 納入備考 | AD115: 伝票備考
D116: 出荷備考１ | AD116: 出荷備考２
D117: 再製造備考
B139: 〇第２画面インプット
C140: 第1画面のインプットから初期表示
C141: 第２画面
D142: 基本情報
D144: 納品先 | H144: XXXXXXX | O144: 手配区分 | T144: 在庫引当 | AA144: 預り売上 □ | AJ144: 出荷日時 | AM144: 44627 | AR144: 0.5
D146: 売上WG | H146: 30 名古屋 | O146: 受注区分 | T146: 30：商品購買 | AC146: 製品区分 | AE146: 大 | AF146: 62：その他 | AL146: 中 | AS146: 小
D147: 手配NO | O147: 案件NO | T147: XXXXXXXXX-XXX
D148: 得意先 | H148: XXXXXXX | O148: 得意先A | X148: 客先納期 | AB148: 44628
D149: 製品CD/品目CD | H149: XXXXXXXX | O149: 顧客品名1 | S149: 顧客品名 | AI149: 顧客品名2 | AM149: 身
D150: 版型NO | O150: CP品名1 | S150: CP品名 | AI150: CP品名2 | AM150: 身
D151: 顧客注文№ | H151: XXXXXXXXXXX | O151: 顧客品番
D152: FSC製品区分 | O152: 食品安全
D154: 予備 | H154: 納入予備 | O154: 営業サンプル | Z154: 定数出荷 | AM154: 不適合手配NO
D156: 売上可否 | H156: 可
D158: 構成情報
D159: シート 段 | O159: 原紙 | Z159: 印刷 | AI159: エンボス | AT159: メーカ
F160: 表
F161: 中
F162: 裏
D163: FSC受注区分
D164: 枚葉印刷
D165: 刃渡り（mm) | J165: 巾 | P165: 流れ | V165: 咥え | Z165: 前後 | AF165: 左右
D166: シート寸法 | J166: 巾 | P166: 流れ | U166: ※(抜き無し見積もり：刃渡り寸法が無いので、シート寸法を入力する。)
D167: 売上巾 | J167: 巾
D168: 最終機械工程
D169: 数量 | J169: 1 | P169: 数量単位 | W169: 個 | Z169: 単価 | AD169: 50000 | AI169: セット単価 | AT169: 単価単位 | BB169: 個 | BE169: 特値 □
D171: 仕入情報
D172: 発注先 | Z172: 発注単位 | AI172: 発注単価 | AT172: 単価単位 | CL172: V09 原紙売りとそれ以外の画面項目制御
D174: 備考
D175: 印刷備考 | AD175: 製造備考
...

Sheet 5_原紙（原紙売り）
A3: 画面イメージ
B5: ≫凡例
Q6: ・・・ | S6: ボタン
C7: 見積計算書№ | Q7: ・・・ | S7: 検索項目(検索画面表示選択)
C8: 品名 | Q8: ・・・ | S8: 入力項目
C9: 得意先 | Q9: ・・・ | S9: 表示項目(得意先名称、原紙名等)
C10: 操作種別 | I10: ●登録 | M10: ○訂正 | Q10: ・・・ | S10: 選択項目(一つのみ選択可能)
C11: 受注区分 | Q11: ・・・ | S11: 選択項目(一つのみ選択可能)
C12: 作業順 | I12: ☑AAA | M12: ☑BBB | Q12: ・・・ | S12: 選択項目(複数選択可能)
B15: 〇原紙売り初期表示
D16: ログイン営業担当の部門が初期設定
C21: TOP画面
D23: 操作種別 | J23: ●登録 | N23: ○訂正 | R23: ○削除 | V23: ○参照 | FT23: 2022/10/29 落合 記載箇所が不明 | GG23: MDSOL回答 2022/10/31 手配NOの表示条件に追加しました。 2段表示は難しいとのことです。 | HI23: 2022/11/01 落合 問題なし
D24: 受注区分 | S24: 得意先 | AO24: 手配NO | BK24: ←「訂正」「削除」「参照」の時、初期フォーカス
D27: 受注部門 | J27: XXXXXX | O27: 名古屋営業 | AD27: 受注日 | AO27: 受注区分
D28: 得意先 | AD28: 客先納期 | AO28: 数量 | FE28: 2022/10/29 落合 記載箇所が不明 | FR28: MDSOL回答 2022/10/31 WEB受注一覧照会の設計書に追記しました。 | GN28: 2022/11/01 落合 問題なし
FU29: 2022/10/29 落合 入力中の受注を除いて既に超えている場合です。 | GQ29: MDSOL回答 2022/10/31 石田 承知しました。処理概要に得意先指定時（TOP画面、基本画面）を記載致しました。 | HY29: 2022/11/01 落合 問題なし
D30: 注文書No | W30: 先方担当 | AO30: 宛名 | BC30: 様 | EY30: 2022/10/29 落合 問題なし
D31: 運送会社 | W31: 出荷日時 | FD31: 2022/11/01 落合 問題なし
D33: 売価区分
D35: 受注明細
D36: 製品CD | J36: (件名:オートフィルタ) | AC36: ← ｾｯﾄ品目指定することで、以下の一覧に部材品目表示
D39: № | F39: 手配NO1 | I39: 手配NO2 | L39: 手配NO3 | O39: 製品CD/品目CD | T39: CP品名1 | Y39: CP品名2 | AB39: 単位 | AD39: 数量 | AG39: 特値 | AJ39: 個別単価 | AM39: ｾｯﾄ単価 | AP39: 客先納期 | AT39: 手配区分 | AW39: 納品先 | BA39: 納品先名 | BE39: 物流グループ | BH39: 預り売上 | BL39: 売上理由 | BP39: 受注№/受注明細№
E40: 1 | AG40: □ | BI40: □
E41: 2 | AG41: □ | BI41: □
E42: 3 | AG42: □ | BI42: □ | FD42: MDSOL回答 2022/10/31 コピー行追加で納期を変更した場合は、手配NOが同一となるため、まとめ期間内ならまとまります。行追加の場合は分割されます。 | GV42: 2022/11/01 落合 問題なし
F44: ※メニュー「シート受注入力」を選択した場合は、第２画面からスタート
F45: ※メニュー「購買品受注入力」を選択した場合は、第２画面からスタート。 工程情報登録はなし。 入力項目の追加あり。
B52: 〇受注基本情報を入力
C54: TOP画面
D56: 操作種別 | J56: ●登録 | N56: ○訂正 | R56: ○削除 | V56: ○参照
D57: 受注区分 | S57: 得意先 | AO57: 手配NO | BK57: ←「訂正」「削除」「参照」の時、初期フォーカス
D60: 受注部門 | J60: XXXXXX | O60: 名古屋営業 | AD60: 受注日 | AH60: 44622 | AO60: 受注区分 | AS60: 40：原紙
D61: 得意先 | J61: XXXXXXX | Q61: 得意先A | AD61: 客先納期 | AH61: 44628 | AO61: 数量 | AS61: 1000
D63: 注文書No | J63: XXXXXXXXXXX | W63: 先方担当 | AC63: 田中 | AO63: 宛名 | AS63: 得意先A 営業部 田中 | BC63: 様
D64: 運送会社 | J64: XXXXXXX | O64: コダマ名古屋 | W64: 出荷日時 | AC64: 44627 | AH64: 0.5
D66: 売価区分 | J66: 単品売り
B78: 〇第２画面初期表示
C79: 第1画面のインプットから初期表示
C80: 第２画面
D81: 基本情報
D83: 納品先 | H83: XXXXXXX | O83: 手配区分 | T83: 購買依頼 | AA83: 預り売上 □ | AJ83: 出荷日時 | AM83: 44627 | AR83: 0.5
D85: 売上WG | H85: 30 名古屋 | O85: 受注区分 | T85: 40:原紙 | AC85: 製品区分 | AE85: 大 | AL85: 中 | AS85: 小
D86: 手配NO | O86: 案件NO
D87: 得意先 | H87: XXXXXXX | O87: 得意先A | X87: 客先納期 | AB87: 44628
D88: 製品CD/品目CD | H88: 123456789010001 | O88: 顧客品名1 | AI88: 顧客品名2
D89: 版型NO | O89: CP品名1 | AI89: CP品名2
D90: 顧客注文№ | H90: XXXXXXXXXXX | O90: 顧客品番
D91: FSC製品区分 | O91: 食品安全
D93: 予備 | H93: 納入予備 | O93: 営業サンプル | Z93: 定数出荷 | AM93: 不適合手配NO
D95: 売上可否 | H95: 可
D97: 構成情報
D98: シート 段 | O98: 原紙 | Z98: 印刷 | AI98: エンボス | AT98: メーカ
F99: 表
F100: 中
F101: 裏
D102: FSC受注区分
D103: 寸法 | J103: 巾 | P103: 巻きM | CL103: REV9.0 原紙売りとそれ以外の画面項目制御
D104: 売上巾 | J104: 巾 | CL104: REV9.0 原紙売りとそれ以外の画面項目制御
D105: 最終機械工程
D106: 数量 | P106: 数量単位 | Z106: 単価 | AI106: セット単価 | AT106: 単価単位 | BE106: 特値 □
D108: 仕入情報
D109: 発注先 | Z109: 発注単位 | AI109: 発注単価 | AT109: 単価単位 | CL109: REV9.0 原紙売りとそれ以外の画面項目制御
D111: 備考
D112: 印刷備考 | AD112: 製造備考
D113: 納入備考 | AD113: 伝票備考
D114: 出荷備考１ | AD114: 出荷備考２
D115: 再製造備考
B137: 〇第２画面インプット
C139: 第２画面
D140: 基本情報
D142: 納品先 | H142: XXXXXXX | O142: 手配区分 | T142: 購買依頼 | AA142: 預り売上 □ | AE142: 3000 | AJ142: 出荷日時 | AM142: 44627 | AR142: 0.5
D144: 売上WG | H144: 30 名古屋 | O144: 受注区分 | T144: 40:原紙 | AC144: 製品区分 | AE144: 大 | AL144: 中 | AS144: 小
D145: 手配NO | O145: 案件NO
D146: 得意先 | H146: XXXXXXX | O146: 得意先A | X146: 客先納期 | AB146: 44628
D147: 製品CD/品目CD | O147: 顧客品名1 | S147: 顧客品名 | AI147: 顧客品名2 | AM147: 身
D148: 版型NO | O148: CP品名1 | S148: CP品名 | AI148: CP品名2 | AM148: 身
D149: 顧客注文№ | H149: XXXXXXXXXXX | O149: 顧客品番
D150: FSC製品区分 | O150: 食品安全
D152: 予備 | H152: 納入予備 | O152: 営業サンプル | Z152: 定数出荷 | AM152: 不適合手配NO
D154: 売上可否 | H154: 可
D156: 構成情報
D157: シート 段 | O157: 原紙 | Z157: 印刷 | AI157: エンボス | AT157: メーカ
F158: 表 | J158: GCBAF | O158: コードボール270（Fﾐｯｸｽ） | Z158: 0000 | AI158: 00
F159: 中
F160: 裏
D161: FSC受注区分
D162: 寸法 | J162: 巾 | L162: 650 | P162: 巻きM | R162: 1000 | CL162: REV9.0 原紙売りとそれ以外の画面項目制御
D163: 売上巾 | J163: 巾 | L163: 650 | CL163: REV9.0 原紙売りとそれ以外の画面項目制御
D164: 最終機械工程
D165: 数量 | J165: 1000 | P165: 数量単位 | W165: 本 | Z165: 単価 | AD165: 100 | AI165: セット単価 | AT165: 単価単位 | BB165: M | BE165: 特値 □
D167: 仕入情報
D168: 発注先 | J168: XXXXXX | P168: 発注先 | Z168: 発注単位 | AF168: 本 | AI168: 発注単価 | AT168: 単価単位 | BB168: M | CL168: REV9.0 原紙売りとそれ以外の画面項目制御
D170: 備考
D171: 印刷備考 | J171: FSC管理NO・1614 | AD171: 製造備考 | AJ171: ｹﾞ7ｺｰﾄﾞ（文昌堂）支給 ｼｮｳﾜﾄﾞｳﾍ/4
D172: 納入備考 | J172: ｹﾞ7ｺｰﾄﾞ（文昌堂）支給 ｼｮｳﾜﾄﾞｳﾍ/4 | AD172: 伝票備考
D173: 出荷備考１ | J173: FSC.1614 オ＝ト | AD173: 出荷備考２ | AJ173: ｼｮｳﾜﾄﾞｳ/7 ﾓﾁｺﾐ ｶｰﾄﾝ/11
D174: 再製造備考 | Z174: 40byte
B186: 〇第3画面初期表示
C187: ３ページ目：工程情報画面
...

Sheet 5_原紙（輪切り）
A3: 画面イメージ
B5: ≫凡例
Q6: ・・・ | S6: ボタン
C7: 見積計算書№ | Q7: ・・・ | S7: 検索項目(検索画面表示選択)
C8: 品名 | Q8: ・・・ | S8: 入力項目
C9: 得意先 | Q9: ・・・ | S9: 表示項目(得意先名称、原紙名等)
C10: 操作種別 | I10: ●登録 | M10: ○訂正 | Q10: ・・・ | S10: 選択項目(一つのみ選択可能)
C11: 受注区分 | Q11: ・・・ | S11: 選択項目(一つのみ選択可能)
C12: 作業順 | I12: ☑AAA | M12: ☑BBB | Q12: ・・・ | S12: 選択項目(複数選択可能)
B15: 〇原紙売り初期表示
D16: ログイン営業担当の部門が初期設定
C21: TOP画面
D23: 操作種別 | J23: ●登録 | N23: ○訂正 | R23: ○削除 | V23: ○参照 | FT23: 2022/10/29 落合 記載箇所が不明 | GG23: MDSOL回答 2022/10/31 手配NOの表示条件に追加しました。 2段表示は難しいとのことです。 | HI23: 2022/11/01 落合 問題なし
D24: 受注区分 | S24: 得意先 | AO24: 手配NO | BK24: ←「訂正」「削除」「参照」の時、初期フォーカス
D27: 受注部門 | J27: XXXXXX | O27: 名古屋営業 | AD27: 受注日 | AO27: 受注区分
D28: 得意先 | AD28: 客先納期 | AO28: 数量 | FE28: 2022/10/29 落合 記載箇所が不明 | FR28: MDSOL回答 2022/10/31 WEB受注一覧照会の設計書に追記しました。 | GN28: 2022/11/01 落合 問題なし
FU29: 2022/10/29 落合 入力中の受注を除いて既に超えている場合です。 | GQ29: MDSOL回答 2022/10/31 石田 承知しました。処理概要に得意先指定時（TOP画面、基本画面）を記載致しました。 | HY29: 2022/11/01 落合 問題なし
D30: 注文書No | W30: 先方担当 | AO30: 宛名 | BC30: 様 | EY30: 2022/10/29 落合 問題なし
D31: 運送会社 | W31: 出荷日時 | FD31: 2022/11/01 落合 問題なし
D33: 売価区分
D35: 受注明細
D36: 製品CD | J36: (件名:オートフィルタ) | AC36: ← ｾｯﾄ品目指定することで、以下の一覧に部材品目表示
D39: № | F39: 手配NO1 | I39: 手配NO2 | L39: 手配NO3 | O39: 製品CD/品目CD | T39: CP品名1 | Y39: CP品名2 | AB39: 単位 | AD39: 数量 | AG39: 特値 | AJ39: 個別単価 | AM39: ｾｯﾄ単価 | AP39: 客先納期 | AT39: 手配区分 | AW39: 納品先 | BA39: 納品先名 | BE39: 物流グループ | BH39: 預り売上 | BL39: 売上理由 | BP39: 受注№/受注明細№
E40: 1 | AG40: □ | BI40: □
E41: 2 | AG41: □ | BI41: □
E42: 3 | AG42: □ | BI42: □ | FD42: MDSOL回答 2022/10/31 コピー行追加で納期を変更した場合は、手配NOが同一となるため、まとめ期間内ならまとまります。行追加の場合は分割されます。 | GV42: 2022/11/01 落合 問題なし
F44: ※メニュー「シート受注入力」を選択した場合は、第２画面からスタート
F45: ※メニュー「購買品受注入力」を選択した場合は、第２画面からスタート。 工程情報登録はなし。 入力項目の追加あり。
B52: 〇受注基本情報を入力
C54: TOP画面
D56: 操作種別 | J56: ●登録 | N56: ○訂正 | R56: ○削除 | V56: ○参照
D57: 受注区分 | S57: 得意先 | AO57: 手配NO | BK57: ←「訂正」「削除」「参照」の時、初期フォーカス
D60: 受注部門 | J60: XXXXXX | O60: 名古屋営業 | AD60: 受注日 | AH60: 44622 | AO60: 受注区分 | AS60: 40：原紙
D61: 得意先 | J61: XXXXXXX | Q61: 得意先A | AD61: 客先納期 | AH61: 44628 | AO61: 数量 | AS61: 3
D63: 注文書No | J63: XXXXXXXXXXX | W63: 先方担当 | AC63: 田中 | AO63: 宛名 | AS63: 得意先A 営業部 田中 | BC63: 様
D64: 運送会社 | J64: XXXXXXX | O64: コダマ名古屋 | W64: 出荷日時 | AC64: 44627 | AH64: 0.5
D66: 売価区分 | J66: 単品売り
B78: 〇第２画面初期表示
C79: 第1画面のインプットから初期表示
C80: 第２画面
D81: 基本情報
D83: 納品先 | H83: XXXXXXX | O83: 手配区分 | T83: 購買依頼 | AA83: 預り売上 □ | AJ83: 出荷日時 | AM83: 44627 | AR83: 0.5
D85: 売上WG | H85: 30 名古屋 | O85: 受注区分 | T85: 40:原紙 | AC85: 製品区分 | AE85: 大 | AL85: 中 | AS85: 小
D86: 手配NO | O86: 案件NO
D87: 得意先 | H87: XXXXXXX | O87: 得意先A | X87: 客先納期 | AB87: 44628
D88: 製品CD/品目CD | H88: 123456789010001 | O88: 顧客品名1 | AI88: 顧客品名2
D89: 版型NO | O89: CP品名1 | AI89: CP品名2
D90: 顧客注文№ | H90: XXXXXXXXXXX | O90: 顧客品番
D91: FSC製品区分 | O91: 食品安全
D93: 予備 | H93: 納入予備 | O93: 営業サンプル | Z93: 定数出荷 | AM93: 不適合手配NO
D95: 売上可否 | H95: 可
D97: 構成情報
D98: シート 段 | O98: 原紙 | Z98: 印刷 | AI98: エンボス | AT98: メーカ
F99: 表
F100: 中
F101: 裏
D102: FSC受注区分
D103: 寸法 | J103: 巾 | P103: 巻きM | CL103: REV9.0 原紙売りとそれ以外の画面項目制御
D104: 売上巾 | J104: 巾 | CL104: REV9.0 原紙売りとそれ以外の画面項目制御
D105: 最終機械工程
D106: 数量 | P106: 数量単位 | Z106: 単価 | AI106: セット単価 | AT106: 単価単位 | BE106: 特値 □
D108: 仕入情報
D109: 発注先 | Z109: 発注単位 | AI109: 発注単価 | AT109: 単価単位 | CL109: REV9.0 原紙売りとそれ以外の画面項目制御
D111: 備考
D112: 印刷備考 | AD112: 製造備考
D113: 納入備考 | AD113: 伝票備考
D114: 出荷備考１ | AD114: 出荷備考２
D115: 再製造備考
B137: 〇第２画面インプット
C139: 第２画面
D140: 基本情報
D142: 納品先 | H142: XXXXXXX | O142: 手配区分 | T142: 購買依頼 | AA142: 預り売上 □ | AE142: 3000 | AJ142: 出荷日時 | AM142: 44627 | AR142: 0.5
D144: 売上WG | H144: 30 名古屋 | O144: 受注区分 | T144: 40:原紙 | AC144: 製品区分 | AE144: 大 | AF144: 43:巻き取り原紙 | AL144: 中 | AS144: 小
D145: 手配NO | O145: 案件NO
D146: 得意先 | H146: XXXXXXX | O146: 得意先A | X146: 客先納期 | AB146: 44628
D147: 製品CD/品目CD | H147: XXXXXXXXXXX | O147: 顧客品名1 | S147: 顧客品名 | AI147: 顧客品名2
D148: 版型NO | O148: CP品名1 | S148: CP品名 | AI148: CP品名2
D149: 顧客注文№ | H149: XXXXXXXXXXX | O149: 顧客品番
D150: FSC製品区分 | O150: 食品安全
D152: 予備 | H152: 納入予備 | O152: 営業サンプル | Z152: 定数出荷 | AM152: 不適合手配NO
D154: 売上可否 | H154: 可
D156: 構成情報
D157: シート 段 | O157: 原紙 | Z157: 印刷 | AI157: エンボス | AT157: メーカ
F158: 表 | J158: E0928 | O158: 原紙XXXX | Z158: 0000 | AI158: 00
F159: 中
F160: 裏
D161: FSC受注区分
D162: 寸法 | J162: 巾 | L162: 400 | P162: 巻きM | R162: 1000 | CL162: REV9.0 原紙売りとそれ以外の画面項目制御
D163: 売上巾 | J163: 巾 | L163: 650 | CL163: REV9.0 原紙売りとそれ以外の画面項目制御
D164: 最終機械工程 | J164: 輪切り
D165: 数量 | J165: 1 | P165: 数量単位 | W165: 本 | Z165: 単価 | AD165: 100 | AI165: セット単価 | AT165: 単価単位 | BB165: M | BE165: 特値 □
D167: 仕入情報
D168: 発注先 | J168: XXXXXX | P168: 発注先 | Z168: 発注単位 | AF168: 本 | AI168: 発注単価 | AT168: 単価単位 | BB168: M | CL168: REV9.0 原紙売りとそれ以外の画面項目制御
D170: 備考
D171: 印刷備考 | J171: FSC管理NO・1614 | AD171: 製造備考 | AJ171: ｹﾞ7ｺｰﾄﾞ（文昌堂）支給 ｼｮｳﾜﾄﾞｳﾍ/4
D172: 納入備考 | J172: ｹﾞ7ｺｰﾄﾞ（文昌堂）支給 ｼｮｳﾜﾄﾞｳﾍ/4 | AD172: 伝票備考
D173: 出荷備考１ | J173: FSC.1614 オ＝ト | AD173: 出荷備考２ | AJ173: ｼｮｳﾜﾄﾞｳ/7 ﾓﾁｺﾐ ｶｰﾄﾝ/11
D174: 再製造備考 | Z174: 40byte
B186: 〇第3画面初期表示
C187: ３ページ目：工程情報画面
...

Sheet ｜➡参考

Sheet 受注⇒MCの集约
A1: 受注区分 | B1: 受注区分名 | C1: 製品区分大 | D1: 製品区分大名 | E1: 品目区分 | F1: 品目区分名 | G1: 品目区分詳細ＣＤ | H1: 標準品目区分詳細名 | I1: 品目系マスタ登録元 | J1: 製品受注パタン | K1: 受注業務パタン | O1: オーダ区分
A3: 10 | B3: 加工製品 | C3: 12 | D3: 加工 | E3: 2 | F3: 製品 | G3: 212 | H3: 加工 | I3: 製品マスタ | J3: CPで取り扱いがある（品目登録済） | K3: 加工品受注 | M3: =IF(N3<>N2, "1","") -> 1 | N3: =A3&C3&E3&G3&I3&J3&K3 -> 10122212製品マスタCPで取り扱いがある（品目登録済）加工品受注 | O3: 内製
A4: 10 | B4: 加工製品 | C4: 12 | D4: 加工 | E4: 2 | F4: 製品 | G4: 212 | H4: 加工 | I4: 製品マスタ | J4: CPで取り扱いがある（品目登録済） | K4: 加工品受注 | M4: =IF(N4<>N3, "1","") | N4: =A4&C4&E4&G4&I4&J4&K4 -> 10122212製品マスタCPで取り扱いがある（品目登録済）加工品受注 | O4: 内製
A5: 10 | B5: 加工製品 | C5: 12 | D5: 加工 | E5: 2 | F5: 製品 | G5: 212 | H5: 加工 | I5: 製品マスタ | J5: CPで取り扱いがある（品目登録済） | K5: 加工品受注 | M5: =IF(N5<>N4, "1","") | N5: =A5&C5&E5&G5&I5&J5&K5 -> 10122212製品マスタCPで取り扱いがある（品目登録済）加工品受注 | O5: 内製
A6: 10 | B6: 加工製品 | C6: 12 | D6: 加工 | E6: 2 | F6: 製品 | G6: 212 | H6: 加工 | I6: 製品マスタ | J6: CPで取り扱いがある（品目登録済） | K6: 加工品受注 | M6: =IF(N6<>N5, "1","") | N6: =A6&C6&E6&G6&I6&J6&K6 -> 10122212製品マスタCPで取り扱いがある（品目登録済）加工品受注 | O6: 外注
A7: 10 | B7: 加工製品 | C7: 12 | D7: 加工 | E7: 2 | F7: 製品 | G7: 212 | H7: 加工 | I7: 製品マスタ | J7: CPで取り扱いがある（品目登録済） | K7: 加工品受注 | M7: =IF(N7<>N6, "1","") | N7: =A7&C7&E7&G7&I7&J7&K7 -> 10122212製品マスタCPで取り扱いがある（品目登録済）加工品受注 | O7: 外注
A8: 10 | B8: 加工製品 | C8: 12 | D8: 加工 | E8: 2 | F8: 製品 | G8: 212 | H8: 加工 | I8: 製品マスタ | J8: CPで取り扱いがある（品目登録済） | K8: 加工品受注 | M8: =IF(N8<>N7, "1","") | N8: =A8&C8&E8&G8&I8&J8&K8 -> 10122212製品マスタCPで取り扱いがある（品目登録済）加工品受注 | O8: WG間転送
A9: 10 | B9: 加工製品 | C9: 13 | D9: Ｇプリント | E9: 2 | F9: 製品 | G9: 213 | H9: Ｇプリント | I9: 製品マスタ | J9: CPで取り扱いがある（品目登録済） | K9: 加工品受注 | M9: =IF(N9<>N8, "1","") -> 1 | N9: =A9&C9&E9&G9&I9&J9&K9 -> 10132213製品マスタCPで取り扱いがある（品目登録済）加工品受注 | O9: 内製
A10: 10 | B10: 加工製品 | C10: 13 | D10: Ｇプリント | E10: 2 | F10: 製品 | G10: 213 | H10: Ｇプリント | I10: 製品マスタ | J10: CPで取り扱いがある（品目登録済） | K10: 加工品受注 | M10: =IF(N10<>N9, "1","") | N10: =A10&C10&E10&G10&I10&J10&K10 -> 10132213製品マスタCPで取り扱いがある（品目登録済）加工品受注 | O10: 内製
A11: 10 | B11: 加工製品 | C11: 13 | D11: Ｇプリント | E11: 2 | F11: 製品 | G11: 213 | H11: Ｇプリント | I11: 製品マスタ | J11: CPで取り扱いがある（品目登録済） | K11: 加工品受注 | M11: =IF(N11<>N10, "1","") | N11: =A11&C11&E11&G11&I11&J11&K11 -> 10132213製品マスタCPで取り扱いがある（品目登録済）加工品受注 | O11: 内製
A12: 10 | B12: 加工製品 | C12: 13 | D12: Ｇプリント | E12: 2 | F12: 製品 | G12: 213 | H12: Ｇプリント | I12: 製品マスタ | J12: CPで取り扱いがある（品目登録済） | K12: 加工品受注 | M12: =IF(N12<>N11, "1","") | N12: =A12&C12&E12&G12&I12&J12&K12 -> 10132213製品マスタCPで取り扱いがある（品目登録済）加工品受注 | O12: 外注
A13: 10 | B13: 加工製品 | C13: 13 | D13: Ｇプリント | E13: 2 | F13: 製品 | G13: 213 | H13: Ｇプリント | I13: 製品マスタ | J13: CPで取り扱いがある（品目登録済） | K13: 加工品受注 | M13: =IF(N13<>N12, "1","") | N13: =A13&C13&E13&G13&I13&J13&K13 -> 10132213製品マスタCPで取り扱いがある（品目登録済）加工品受注 | O13: 外注
A14: 10 | B14: 加工製品 | C14: 13 | D14: Ｇプリント | E14: 2 | F14: 製品 | G14: 213 | H14: Ｇプリント | I14: 製品マスタ | J14: CPで取り扱いがある（品目登録済） | K14: 加工品受注 | M14: =IF(N14<>N13, "1","") | N14: =A14&C14&E14&G14&I14&J14&K14 -> 10132213製品マスタCPで取り扱いがある（品目登録済）加工品受注 | O14: WG間転送
... A90: 21 | B90: シート商品 | C90: 22 | D90: 片面シート | E90: 1 | F90: 商品 | G90: 122 | H90: 商品片面シート | I90: 品目マスタ | J90: CPで取り扱いが無い（諸口品目） | K90: 商品購買 | M90: =IF(N90<>N89, "1","") | N90: =A90&C90&E90&G90&I90&J90&K90 -> 21221122品目マスタCPで取り扱いが無い（諸口品目）商品購買 | O90: 購買
A91: 30 | B91: 購買品 | C91: 51 | D91: 外装シート | E91: 1 | F91: 商品 | G91: 151 | H91: 外装シート | I91: 品目マスタ | J91: CPで取り扱いが無い（諸口品目） | K91: 商品購買 | M91: =IF(N91<>N90, "1","") -> 1 | N91: =A91&C91&E91&G91&I91&J91&K91 -> 30511151品目マスタCPで取り扱いが無い（諸口品目）商品購買 | O91: 購買
A92: 30 | B92: 購買品 | C92: 51 | D92: 外装シート | E92: 1 | F92: 商品 | G92: 151 | H92: 外装シート | I92: 品目マスタ | J92: CPで取り扱いが無い（諸口品目） | K92: 商品購買 | M92: =IF(N92<>N91, "1","") | N92: =A92&C92&E92&G92&I92&J92&K92 -> 30511151品目マスタCPで取り扱いが無い（諸口品目）商品購買 | O92: 購買
A93: 30 | B93: 購買品 | C93: 52 | D93: 外装ケース | E93: 1 | F93: 商品 | G93: 152 | H93: 外装ケース | I93: 品目マスタ | J93: CPで取り扱いが無い（諸口品目） | K93: 商品購買 | M93: =IF(N93<>N92, "1","") -> 1 | N93: =A93&C93&E93&G93&I93&J93&K93 -> 30521152品目マスタCPで取り扱いが無い（諸口品目）商品購買 | O93: 購買
A94: 30 | B94: 購買品 | C94: 52 | D94: 外装ケース | E94: 1 | F94: 商品 | G94: 152 | H94: 外装ケース | I94: 品目マスタ | J94: CPで取り扱いが無い（諸口品目） | K94: 商品購買 | M94: =IF(N94<>N93, "1","") | N94: =A94&C94&E94&G94&I94&J94&K94 -> 30521152品目マスタCPで取り扱いが無い（諸口品目）商品購買 | O94: 購買
A95: 30 | B95: 購買品 | C95: 62 | D95: その他 | E95: 1 | F95: 商品 | G95: 162 | H95: 商品その他 | I95: 品目マスタ | J95: CPで取り扱いが無い（諸口品目） | K95: 商品購買 | M95: =IF(N95<>N94, "1","") -> 1 | N95: =A95&C95&E95&G95&I95&J95&K95 -> 30621162品目マスタCPで取り扱いが無い（諸口品目）商品購買 | O95: 購買
A96: 30 | B96: 購買品 | C96: 62 | D96: その他 | E96: 1 | F96: 商品 | G96: 162 | H96: 商品その他 | I96: 品目マスタ | J96: CPで取り扱いが無い（諸口品目） | K96: 商品購買 | M96: =IF(N96<>N95, "1","") | N96: =A96&C96&E96&G96&I96&J96&K96 -> 30621162品目マスタCPで取り扱いが無い（諸口品目）商品購買 | O96: 購買
A97: 30 | B97: 購買品 | C97: 63 | D97: デザイン代 | E97: 9 | F97: その他 | G97: 963 | H97: デザイン代 | I97: 品目マスタ | J97: CPで取り扱いが無い（諸口品目） | K97: 経費受注 | M97: =IF(N97<>N96, "1","") -> 1 | N97: =A97&C97&E97&G97&I97&J97&K97 -> 30639963品目マスタCPで取り扱いが無い（諸口品目）経費受注 | O97: -
A98: 30 | B98: 購買品 | C98: 71 | D98: 袋 | E98: 1 | F98: 商品 | G98: 171 | H98: 袋 | I98: 品目マスタ | J98: CPで取り扱いが無い（諸口品目） | K98: 商品購買 | M98: =IF(N98<>N97, "1","") -> 1 | N98: =A98&C98&E98&G98&I98&J98&K98 -> 30711171品目マスタCPで取り扱いが無い（諸口品目）商品購買 | O98: 購買
A99: 30 | B99: 購買品 | C99: 71 | D99: 袋 | E99: 1 | F99: 商品 | G99: 171 | H99: 袋 | I99: 品目マスタ | J99: CPで取り扱いが無い（諸口品目） | K99: 商品購買 | M99: =IF(N99<>N98, "1","") | N99: =A99&C99&E99&G99&I99&J99&K99 -> 30711171品目マスタCPで取り扱いが無い（諸口品目）商品購買 | O99: 購買
A100: 30 | B100: 購買品 | C100: 81 | D100: 運賃 | E100: 9 | F100: その他 | G100: 981 | H100: 運賃 | I100: 品目マスタ | J100: CPで取り扱いが無い（諸口品目） | K100: 経費受注 | M100: =IF(N100<>N99, "1","") -> 1 | N100: =A100&C100&E100&G100&I100&J100&K100 -> 30819981品目マスタCPで取り扱いが無い（諸口品目）経費受注 | O100: -
A101: 30 | B101: 購買品 | C101: 91 | D101: 資材料 | E101: 9 | F101: その他 | G101: 991 | H101: 資材料 | I101: 品目マスタ | J101: CPで取り扱いが無い（諸口品目） | K101: 経費受注 | M101: =IF(N101<>N100, "1","") -> 1 | N101: =A101&C101&E101&G101&I101&J101&K101 -> 30919991品目マスタCPで取り扱いが無い（諸口品目）経費受注 | O101: -
A102: 30 | B102: 購買品 | C102: 92 | D102: 前加工料 | E102: 9 | F102: その他 | G102: 992 | H102: 前加工料 | I102: 品目マスタ | J102: CPで取り扱いが無い（諸口品目） | K102: 経費受注 | M102: =IF(N102<>N101, "1","") -> 1 | N102: =A102&C102&E102&G102&I102&J102&K102 -> 30929992品目マスタCPで取り扱いが無い（諸口品目）経費受注 | O102: -
A103: 30 | B103: 購買品 | C103: 80 | D103: モールド | E103: 1 | F103: 商品 | G103: 180 | H103: モールド | I103: 品目マスタ | J103: CPで取り扱いが無い（諸口品目） | K103: 商品購買 | M103: =IF(N103<>N102, "1","") -> 1 | N103: =A103&C103&E103&G103&I103&J103&K103 -> 30801180品目マスタCPで取り扱いが無い（諸口品目）商品購買 | O103: 購買
A104: 30 | B104: 購買品 | C104: 80 | D104: モールド | E104: 1 | F104: 商品 | G104: 180 | H104: モールド | I104: 品目マスタ | J104: CPで取り扱いが無い（諸口品目） | K104: 商品購買 | M104: =IF(N104<>N103, "1","") | N104: =A104&C104&E104&G104&I104&J104&K104 -> 30801180品目マスタCPで取り扱いが無い（諸口品目）商品購買 | O104: 購買
A105: 40 | B105: 原紙 | C105: 33 | D105: コートボール | E105: 1 | F105: 商品 | G105: 133 | H105: 商品コートボール | I105: 製品マスタ | J105: CPで取り扱いがある（品目登録済） | K105: 加工品受注 | M105: =IF(N105<>N104, "1","") -> 1 | N105: =A105&C105&E105&G105&I105&J105&K105 -> 40331133製品マスタCPで取り扱いがある（品目登録済）加工品受注 | O105: 外注
A106: 40 | B106: 原紙 | C106: 33 | D106: コートボール | E106: 1 | F106: 商品 | G106: 133 | H106: 商品コートボール | I106: 製品マスタ | J106: CPで取り扱いがある（品目登録済） | K106: 加工品受注 | M106: =IF(N106<>N105, "1","") | N106: =A106&C106&E106&G106&I106&J106&K106 -> 40331133製品マスタCPで取り扱いがある（品目登録済）加工品受注 | O106: 外注
A107: 40 | B107: 原紙 | C107: 33 | D107: コートボール | E107: 1 | F107: 商品 | G107: 133 | H107: 商品コートボール | I107: 製品マスタ | J107: CPで取り扱いがある（品目登録済） | K107: 加工品受注 | M107: =IF(N107<>N106, "1","") | N107: =A107&C107&E107&G107&I107&J107&K107 -> 40331133製品マスタCPで取り扱いがある（品目登録済）加工品受注 | O107: WG間転送
A108: 40 | B108: 原紙 | C108: 33 | D108: コートボール | E108: 1 | F108: 商品 | G108: 133 | H108: 商品コートボール | I108: 品目マスタ | J108: CPで取り扱いが無い（諸口品目） | K108: 商品購買 | M108: =IF(N108<>N107, "1","") -> 1 | N108: =A108&C108&E108&G108&I108&J108&K108 -> 40331133品目マスタCPで取り扱いが無い（諸口品目）商品購買 | O108: 購買
A109: 40 | B109: 原紙 | C109: 33 | D109: コートボール | E109: 1 | F109: 商品 | G109: 133 | H109: 商品コートボール | I109: 品目マスタ | J109: CPで取り扱いが無い（諸口品目） | K109: 商品購買 | M109: =IF(N109<>N108, "1","") | N109: =A109&C109&E109&G109&I109&J109&K109 -> 40331133品目マスタCPで取り扱いが無い（諸口品目）商品購買 | O109: 購買
A110: 40 | B110: 原紙 | C110: 33 | D110: コートボール | E110: 2 | F110: 製品 | G110: 233 | H110: コートボール製品 | I110: 製品マスタ | J110: CPで取り扱いがある（品目登録済） | K110: 加工品受注 | M110: =IF(N110<>N109, "1","") -> 1 | N110: =A110&C110&E110&G110&I110&J110&K110 -> 40332233製品マスタCPで取り扱いがある（品目登録済）加工品受注 | O110: 内製
A111: 40 | B111: 原紙 | C111: 33 | D111: コートボール | E111: 2 | F111: 製品 | G111: 233 | H111: コートボール製品 | I111: 製品マスタ | J111: CPで取り扱いがある（品目登録済） | K111: 加工品受注 | M111: =IF(N111<>N110, "1","") | N111: =A111&C111&E111&G111&I111&J111&K111 -> 40332233製品マスタCPで取り扱いがある（品目登録済）加工品受注 | O111: 内製
A112: 40 | B112: 原紙 | C112: 33 | D112: コートボール | E112: 2 | F112: 製品 | G112: 233 | H112: コートボール製品 | I112: 製品マスタ | J112: CPで取り扱いがある（品目登録済） | K112: 加工品受注 | M112: =IF(N112<>N111, "1","") | N112: =A112&C112&E112&G112&I112&J112&K112 -> 40332233製品マスタCPで取り扱いがある（品目登録済）加工品受注 | O112: 内製
A113: 40 | B113: 原紙 | C113: 33 | D113: コートボール | E113: 2 | F113: 製品 | G113: 233 | H113: コートボール製品 | I113: 製品マスタ | J113: CPで取り扱いがある（品目登録済） | K113: 加工品受注 | M113: =IF(N113<>N112, "1","") | N113: =A113&C113&E113&G113&I113&J113&K113 -> 40332233製品マスタCPで取り扱いがある（品目登録済）加工品受注 | O113: 外注
A114: 40 | B114: 原紙 | C114: 33 | D114: コートボール | E114: 2 | F114: 製品 | G114: 233 | H114: コートボール製品 | I114: 製品マスタ | J114: CPで取り扱いがある（品目登録済） | K114: 加工品受注 | M114: =IF(N114<>N113, "1","") | N114: =A114&C114&E114&G114&I114&J114&K114 -> 40332233製品マスタCPで取り扱いがある（品目登録済）加工品受注 | O114: 外注
A115: 40 | B115: 原紙 | C115: 33 | D115: コートボール | E115: 2 | F115: 製品 | G115: 233 | H115: コートボール製品 | I115: 製品マスタ | J115: CPで取り扱いがある（品目登録済） | K115: 加工品受注 | M115: =IF(N115<>N114, "1","") | N115: =A115&C115&E115&G115&I115&J115&K115 -> 40332233製品マスタCPで取り扱いがある（品目登録済）加工品受注 | O115: WG間転送
A116: 40 | B116: 原紙 | C116: 33 | D116: コートボール | E116: 6 | F116: 原料 | G116: 603 | H116: コートボール | I116: WEB受注 | J116: CPで取り扱いがある（品目登録済） | K116: 原紙売り（受発注方式） | M116: =IF(N116<>N115, "1","") -> 1 | N116: =A116&C116&E116&G116&I116&J116&K116 -> 40336603WEB受注CPで取り扱いがある（品目登録済）原紙売り（受発注方式） | O116: 本支店売買（受発注）
A117: 40 | B117: 原紙 | C117: 33 | D117: コートボール | E117: 6 | F117: 原料 | G117: 603 | H117: コートボール | I117: WEB受注 | J117: CPで取り扱いがある（品目登録済） | K117: 原紙売り（受発注方式） | M117: =IF(N117<>N116, "1","") | N117: =A117&C117&E117&G117&I117&J117&K117 -> 40336603WEB受注CPで取り扱いがある（品目登録済）原紙売り（受発注方式） | O117: 本支店売買（受発注）
A118: 40 | B118: 原紙 | C118: 33 | D118: コートボール | E118: 6 | F118: 原料 | G118: 603 | H118: コートボール | I118: WEB受注 | J118: CPで取り扱いがある（品目登録済） | K118: 原紙売り（受発注方式） | M118: =IF(N118<>N117, "1","") | N118: =A118&C118&E118&G118&I118&J118&K118 -> 40336603WEB受注CPで取り扱いがある（品目登録済）原紙売り（受発注方式） | O118: 本支店売買（受発注）
A119: 40 | B119: 原紙 | C119: 33 | D119: コートボール | E119: 6 | F119: 原料 | G119: 603 | H119: コートボール | I119: 原紙マスタ | J119: CPで取り扱いがある（品目登録済） | K119: 商品購買 | M119: =IF(N119<>N118, "1","") -> 1 | N119: =A119&C119&E119&G119&I119&J119&K119 -> 40336603原紙マスタCPで取り扱いがある（品目登録済）商品購買 | O119: 購買
A120: 40 | B120: 原紙 | C120: 33 | D120: コートボール | E120: 6 | F120: 原料 | G120: 603 | H120: コートボール | I120: 原紙マスタ | J120: CPで取り扱いがある（品目登録済） | K120: 商品購買 | M120: =IF(N120<>N119, "1","") | N120: =A120&C120&E120&G120&I120&J120&K120 -> 40336603原紙マスタCPで取り扱いがある（品目登録済）商品購買 | O120: 購買
A121: 40 | B121: 原紙 | C121: 41 | D121: 生原紙 | E121: 1 | F121: 商品 | G121: 141 | H121: 商品原紙 | I121: 品目マスタ | J121: CPで取り扱いが無い（諸口品目） | K121: 商品購買 | M121: =IF(N121<>N120, "1","") -> 1 | N121: =A121&C121&E121&G121&I121&J121&K121 -> 40411141品目マスタCPで取り扱いが無い（諸口品目）商品購買 | O121: 購買
A122: 40 | B122: 原紙 | C122: 41 | D122: 生原紙 | E122: 1 | F122: 商品 | G122: 141 | H122: 商品原紙 | I122: 品目マスタ | J122: CPで取り扱いが無い（諸口品目） | K122: 商品購買 | M122: =IF(N122<>N121, "1","") | N122: =A122&C122&E122&G122&I122&J122&K122 -> 40411141品目マスタCPで取り扱いが無い（諸口品目）商品購買 | O122: 購買
A123: 40 | B123: 原紙 | C123: 41 | D123: 生原紙 | E123: 6 | F123: 原料 | G123: 601 | H123: 生原紙 | I123: WEB受注 | J123: CPで取り扱いがある（品目登録済） | K123: 原紙売り（受発注方式） | M123: =IF(N123<>N122, "1","") -> 1 | N123: =A123&C123&E123&G123&I123&J123&K123 -> 40416601WEB受注CPで取り扱いがある（品目登録済）原紙売り（受発注方式） | O123: 本支店売買（受発注）
A124: 40 | B124: 原紙 | C124: 41 | D124: 生原紙 | E124: 6 | F124: 原料 | G124: 601 | H124: 生原紙 | I124: WEB受注 | J124: CPで取り扱いがある（品目登録済） | K124: 原紙売り（受発注方式） | M124: =IF(N124<>N123, "1","") | N124: =A124&C124&E124&G124&I124&J124&K124 -> 40416601WEB受注CPで取り扱いがある（品目登録済）原紙売り（受発注方式） | O124: 本支店売買（受発注）
A125: 40 | B125: 原紙 | C125: 41 | D125: 生原紙 | E125: 6 | F125: 原料 | G125: 601 | H125: 生原紙 | I125: WEB受注 | J125: CPで取り扱いがある（品目登録済） | K125: 原紙売り（受発注方式） | M125: =IF(N125<>N124, "1","") | N125: =A125&C125&E125&G125&I125&J125&K125 -> 40416601WEB受注CPで取り扱いがある（品目登録済）原紙売り（受発注方式） | O125: 本支店売買（受発注）
A126: 40 | B126: 原紙 | C126: 41 | D126: 生原紙 | E126: 6 | F126: 原料 | G126: 601 | H126: 生原紙 | I126: 原紙マスタ | J126: CPで取り扱いがある（品目登録済） | K126: 商品購買 | M126: =IF(N126<>N125, "1","") -> 1 | N126: =A126&C126&E126&G126&I126&J126&K126 -> 40416601原紙マスタCPで取り扱いがある（品目登録済）商品購買 | O126: 購買
A127: 40 | B127: 原紙 | C127: 41 | D127: 生原紙 | E127: 6 | F127: 原料 | G127: 601 | H127: 生原紙 | I127: 原紙マスタ | J127: CPで取り扱いがある（品目登録済） | K127: 商品購買 | M127: =IF(N127<>N126, "1","") | N127: =A127&C127&E127&G127&I127&J127&K127 -> 40416601原紙マスタCPで取り扱いがある（品目登録済）商品購買 | O127: 購買
A128: 40 | B128: 原紙 | C128: 41 | D128: 生原紙 | E128: 6 | F128: 原料 | G128: 601 | H128: 生原紙 | I128: 原紙マスタ | J128: CPで取り扱いがある（品目登録済） | K128: 商品購買 | M128: =IF(N128<>N127, "1","") | N128: =A128&C128&E128&G128&I128&J128&K128 -> 40416601原紙マスタCPで取り扱いがある（品目登録済）商品購買 | O128: 購買
A129: 40 | B129: 原紙 | C129: 41 | D129: 生原紙 | E129: 6 | F129: 原料 | G129: 602 | H129: テスト原紙 | I129: WEB受注 | J129: CPで取り扱いがある（品目登録済） | K129: 原紙売り（受発注方式） | M129: =IF(N129<>N128, "1","") -> 1 | N129: =A129&C129&E129&G129&I129&J129&K129 -> 40416602WEB受注CPで取り扱いがある（品目登録済）原紙売り（受発注方式） | O129: 本支店売買（受発注）
A130: 40 | B130: 原紙 | C130: 41 | D130: 生原紙 | E130: 6 | F130: 原料 | G130: 602 | H130: テスト原紙 | I130: 原紙マスタ | J130: CPで取り扱いがある（品目登録済） | K130: 商品購買 | M130: =IF(N130<>N129, "1","") -> 1 | N130: =A130&C130&E130&G130&I130&J130&K130 -> 40416602原紙マスタCPで取り扱いがある（品目登録済）商品購買 | O130: 購買
A131: 40 | B131: 原紙 | C131: 42 | D131: 印刷原紙 | E131: 1 | F131: 商品 | G131: 142 | H131: 商品印刷原紙 | I131: 製品マスタ | J131: CPで取り扱いがある（品目登録済） | K131: 加工品受注 | M131: =IF(N131<>N130, "1","") -> 1 | N131: =A131&C131&E131&G131&I131&J131&K131 -> 40421142製品マスタCPで取り扱いがある（品目登録済）加工品受注 | O131: 外注
A132: 40 | B132: 原紙 | C132: 42 | D132: 印刷原紙 | E132: 1 | F132: 商品 | G132: 142 | H132: 商品印刷原紙 | I132: 製品マスタ | J132: CPで取り扱いがある（品目登録済） | K132: 加工品受注 | M132: =IF(N132<>N131, "1","") | N132: =A132&C132&E132&G132&I132&J132&K132 -> 40421142製品マスタCPで取り扱いがある（品目登録済）加工品受注 | O132: 外注
A133: 40 | B133: 原紙 | C133: 42 | D133: 印刷原紙 | E133: 1 | F133: 商品 | G133: 142 | H133: 商品印刷原紙 | I133: 製品マスタ | J133: CPで取り扱いがある（品目登録済） | K133: 加工品受注 | M133: =IF(N133<>N132, "1","") | N133: =A133&C133&E133&G133&I133&J133&K133 -> 40421142製品マスタCPで取り扱いがある（品目登録済）加工品受注 | O133: WG間転送
A134: 40 | B134: 原紙 | C134: 42 | D134: 印刷原紙 | E134: 1 | F134: 商品 | G134: 142 | H134: 商品印刷原紙 | I134: 品目マスタ | J134: CPで取り扱いが無い（諸口品目） | K134: 商品購買 | M134: =IF(N134<>N133, "1","") -> 1 | N134: =A134&C134&E134&G134&I134&J134&K134 -> 40421142品目マスタCPで取り扱いが無い（諸口品目）商品購買 | O134: 購買
A135: 40 | B135: 原紙 | C135: 42 | D135: 印刷原紙 | E135: 1 | F135: 商品 | G135: 142 | H135: 商品印刷原紙 | I135: 品目マスタ | J135: CPで取り扱いが無い（諸口品目） | K135: 商品購買 | M135: =IF(N135<>N134, "1","") | N135: =A135&C135&E135&G135&I135&J135&K135 -> 40421142品目マスタCPで取り扱いが無い（諸口品目）商品購買 | O135: 購買
A136: 40 | B136: 原紙 | C136: 42 | D136: 印刷原紙 | E136: 2 | F136: 製品 | G136: 242 | H136: 印刷原紙 | I136: 製品マスタ | J136: CPで取り扱いがある（品目登録済） | K136: 加工品受注 | M136: =IF(N136<>N135, "1","") -> 1 | N136: =A136&C136&E136&G136&I136&J136&K136 -> 40422242製品マスタCPで取り扱いがある（品目登録済）加工品受注 | O136: 内製
A137: 40 | B137: 原紙 | C137: 42 | D137: 印刷原紙 | E137: 2 | F137: 製品 | G137: 242 | H137: 印刷原紙 | I137: 製品マスタ | J137: CPで取り扱いがある（品目登録済） | K137: 加工品受注 | M137: =IF(N137<>N136, "1","") | N137: =A137&C137&E137&G137&I137&J137&K137 -> 40422242製品マスタCPで取り扱いがある（品目登録済）加工品受注 | O137: 内製
A138: 40 | B138: 原紙 | C138: 42 | D138: 印刷原紙 | E138: 2 | F138: 製品 | G138: 242 | H138: 印刷原紙 | I138: 製品マスタ | J138: CPで取り扱いがある（品目登録済） | K138: 加工品受注 | M138: =IF(N138<>N137, "1","") | N138: =A138&C138&E138&G138&I138&J138&K138 -> 40422242製品マスタCPで取り扱いがある（品目登録済）加工品受注 | O138: 内製
A139: 40 | B139: 原紙 | C139: 42 | D139: 印刷原紙 | E139: 2 | F139: 製品 | G139: 242 | H139: 印刷原紙 | I139: 製品マスタ | J139: CPで取り扱いがある（品目登録済） | K139: 加工品受注 | M139: =IF(N139<>N138, "1","") | N139: =A139&C139&E139&G139&I139&J139&K139 -> 40422242製品マスタCPで取り扱いがある（品目登録済）加工品受注 | O139: 外注
A140: 40 | B140: 原紙 | C140: 42 | D140: 印刷原紙 | E140: 2 | F140: 製品 | G140: 242 | H140: 印刷原紙 | I140: 製品マスタ | J140: CPで取り扱いがある（品目登録済） | K140: 加工品受注 | M140: =IF(N140<>N139, "1","") | N140: =A140&C140&E140&G140&I140&J140&K140 -> 40422242製品マスタCPで取り扱いがある（品目登録済）加工品受注 | O140: 外注
A141: 40 | B141: 原紙 | C141: 42 | D141: 印刷原紙 | E141: 2 | F141: 製品 | G141: 242 | H141: 印刷原紙 | I141: 製品マスタ | J141: CPで取り扱いがある（品目登録済） | K141: 加工品受注 | M141: =IF(N141<>N140, "1","") | N141: =A141&C141&E141&G141&I141&J141&K141 -> 40422242製品マスタCPで取り扱いがある（品目登録済）加工品受注 | O141: WG間転送
A142: 40 | B142: 原紙 | C142: 42 | D142: 印刷原紙 | E142: 6 | F142: 原料 | G142: 600 | H142: 印刷原紙 | I142: WEB受注 | J142: CPで取り扱いがある（品目登録済） | K142: 原紙売り（受発注方式） | M142: =IF(N142<>N141, "1","") -> 1 | N142: =A142&C142&E142&G142&I142&J142&K142 -> 40426600WEB受注CPで取り扱いがある（品目登録済）原紙売り（受発注方式） | O142: 本支店売買（受発注）
... A147: 40 | B147: 原紙 | C147: 42 | D147: 印刷原紙 | E147: 6 | F147: 原料 | G147: 600 | H147: 印刷原紙 | I147: 原紙マスタ | J147: CPで取り扱いがある（品目登録済） | K147: 商品購買 | M147: =IF(N147<>N146, "1","") | N147: =A147&C147&E147&G147&I147&J147&K147 -> 40426600原紙マスタCPで取り扱いがある（品目登録済）商品購買 | O147: 購買

Sheet 画面制御（試し）
B1: TOP画面
E2: 基本情報 | F2: 受注明細
B3: 受注区分 | D3: 補足 | E3: 全項目 | F3: セット品CDの指定 | G3: 明細行数 | H3: 製品CD | I3: 品目CD | J3: CP品名1 | K3: CP品名2 | L3: 単位 | M3: 数量 | N3: 特値 | O3: 個別単価 | P3: ｾｯﾄ単価 | Q3: 客先納期 | R3: 手配区分 | S3: 納品先 | T3: 納品先名 | U3: 物流グループ | V3: 預り売上 | W3: 売上理由 | X3: 受注№/受注明細№
B4: 10 | C4: 加工製品 | D4: 段ボール受注 | E4: 既存仕様 | G4: 制限なし | H4: 行別選択するか、セット品に含まれる製品 | J4: 次画面入力値 | K4: 次画面入力値 | L4: 製品マスタ | M4: 既存仕様 | N4: 既存仕様 | O4: 既存仕様 | P4: 既存仕様 | Q4: 既存仕様 | R4: 既存仕様 | S4: 既存仕様 | T4: 既存仕様 | U4: 既存仕様 | V4: 既存仕様 | W4: 既存仕様 | X4: 既存仕様
B5: 11 | C5: 加工商品 | D5: 段ボール受注 | E5: 既存仕様 | G5: 制限なし | H5: 行別選択するか、セット品に含まれる製品 | J5: 次画面入力値 | K5: 次画面入力値 | L5: 製品マスタ | M5: 既存仕様 | N5: 既存仕様 | O5: 既存仕様 | P5: 既存仕様 | Q5: 既存仕様 | R5: 既存仕様 | S5: 既存仕様 | T5: 既存仕様 | U5: 既存仕様 | V5: 既存仕様 | W5: 既存仕様 | X5: 既存仕様
B6: 20 | C6: シート製品 | D6: シート受注 | E6: 既存仕様 | F6: 入力不可 | G6: 1行のみ | H6: 保存時採番 | J6: 次画面入力値 | K6: 次画面入力値 | L6: 次画面入力値 | M6: 製品と同じ | N6: 製品と同じ | O6: 製品と同じ | P6: 製品と同じ | Q6: 製品と同じ | R6: 製品と同じ | S6: 製品と同じ | T6: 製品と同じ | U6: 製品と同じ | V6: 製品と同じ | W6: 製品と同じ | X6: 製品と同じ
B7: 21 | C7: シート商品 | D7: シート受注 | E7: 既存仕様 | F7: 入力不可 | G7: 1行のみ | H7: 保存時採番 | J7: 次画面入力値 | K7: 次画面入力値 | L7: 次画面入力値 | M7: 製品と同じ | N7: 製品と同じ | O7: 製品と同じ | P7: 製品と同じ | Q7: 製品と同じ | R7: 製品と同じ | S7: 製品と同じ | T7: 製品と同じ | U7: 製品と同じ | V7: 製品と同じ | W7: 製品と同じ | X7: 製品と同じ
B8: 30 | C8: 購買品 | D8: 経費受注 | E8: 既存仕様 | F8: 入力不可 | G8: 1行のみ | J8: 次画面入力値 | K8: 次画面入力値 | L8: 次画面入力値 | M8: 製品と同じ | N8: 製品と同じ | O8: 製品と同じ | P8: 製品と同じ | Q8: 製品と同じ | R8: 製品と同じ | S8: 製品と同じ | T8: 製品と同じ | U8: 製品と同じ | V8: 製品と同じ | W8: 製品と同じ | X8: 製品と同じ
B9: 40 | C9: 原紙 | D9: 通常受注 （生原紙、加工原紙、印刷原紙） | E9: 既存仕様 | F9: 入力不可 | G9: 1行のみ | J9: 次画面入力値 | K9: 次画面入力値 | L9: 次画面入力値 | M9: 製品と同じ | N9: 製品と同じ | O9: 製品と同じ | P9: 製品と同じ | Q9: 製品と同じ | R9: 製品と同じ | S9: 製品と同じ | T9: 製品と同じ | U9: 製品と同じ | V9: 製品と同じ | W9: 製品と同じ | X9: 製品と同じ
B11: 基本情報画面
E12: 基本情報 | L12: 構成情報 | M12: 仕入情報 | N12: 備考
B13: 受注区分 | D13: 補足 | E13: 製品区分 | H13: 預り売上 | I13: 納入予備 | J13: 営業サンプル | K13: 定数出荷 | L13: 全項目 | M13: 全項目 | N13: 全項目
B14: 10 | C14: 加工製品 | D14: 段ボール受注
B15: 11 | C15: 加工商品 | D15: 段ボール受注
B16: 20 | C16: シート製品 | D16: シート受注
B17: 21 | C17: シート商品 | D17: シート受注
B18: 30 | C18: 購買品 | D18: 経費受注 （運賃、保管料など） | H18: 入力不可 | I18: 入力不可 | J18: 入力不可 | K18: 入力不可 | L18: 入力不可 | M18: 入力不可 | N18: 入力不可
B19: 30 | C19: 購買品 | D19: 通常受注 （経費品以外のMC品目）
B20: 30 | C20: 購買品 | D20: 通常受注 （版型）
B21: 40 | C21: 原紙 | D21: 通常受注 （生原紙、加工原紙、印刷原紙）
B24: 工程情報画面
E25: 工程情報
B26: 受注区分 | D26: 補足 | E26: 全項目
B27: 10 | C27: 加工製品 | D27: 段ボール受注
B28: 11 | C28: 加工商品 | D28: 段ボール受注
B29: 20 | C29: シート製品 | D29: シート受注
B30: 21 | C30: シート商品 | D30: シート受注
B31: 30 | C31: 購買品 | D31: 経費受注 （運賃、保管料など） | E31: 入力不可
B32: 30 | C32: 購買品 | D32: 通常受注 （経費品以外のMC品目） | E32: 入力不可
B33: 30 | C33: 購買品 | D33: 通常受注 （版型） | E33: 入力不可
B34: 40 | C34: 原紙 | D34: 通常受注 （生原紙、加工原紙、印刷原紙）
B36: ポップアップ画面（詳細入力）
E37: 基本情報 | F37: 外注情報 | G37: 工程情報 | H37: 作業明細 | I37: 連産品明細
B38: 受注区分 | D38: 補足 | E38: 全項目 | F38: 全項目 | G38: 全項目 | H38: 全項目 | I38: 全項目
B39: 10 | C39: 加工製品 | D39: 段ボール受注
B40: 11 | C40: 加工商品 | D40: 段ボール受注
B41: 20 | C41: シート製品 | D41: シート受注
B42: 21 | C42: シート商品 | D42: シート受注
B43: 30 | C43: 購買品 | D43: 経費受注 （運賃、保管料など） | E43: 入力不可 | F43: 入力不可 | G43: 入力不可 | H43: 入力不可 | I43: 入力不可
B44: 30 | C44: 購買品 | D44: 通常受注 （経費品以外のMC品目） | E44: 入力不可 | F44: 入力不可 | G44: 入力不可 | H44: 入力不可 | I44: 入力不可
B45: 30 | C45: 購買品 | D45: 通常受注 （版型） | E45: 入力不可 | F45: 入力不可 | G45: 入力不可 | H45: 入力不可 | I45: 入力不可
B46: 40 | C46: 原紙 | D46: 通常受注 （生原紙、加工原紙、印刷原紙）
B48: 材料設定画面
E49: 材料明細
B50: 受注区分 | D50: 補足 | E50: 全項目
B51: 10 | C51: 加工製品 | D51: 段ボール受注
B52: 11 | C52: 加工商品 | D52: 段ボール受注
B53: 20 | C53: シート製品 | D53: シート受注
B54: 21 | C54: シート商品 | D54: シート受注
B55: 30 | C55: 購買品 | D55: 経費受注 （運賃、保管料など） | E55: 入力不可
B56: 30 | C56: 購買品 | D56: 通常受注 （経費品以外のMC品目） | E56: 入力不可
B57: 30 | C57: 購買品 | D57: 通常受注 （版型） | E57: 入力不可
B58: 40 | C58: 原紙 | D58: 通常受注 （生原紙、加工原紙、印刷原紙）
C62: 参考
F64: 第1画面 （TOP画面） | H64: 第2画面 （基本情報） | L64: 第3画面 （工程情報） | M64: ポップアップ （詳細入力画面） | R64: 第4画面 （材料設定）
E65: 画面項目 | F65: 基本情報 | G65: 受注明細 | H65: 基本情報 | I65: 構成情報 | J65: 仕入情報 | K65: 備考 | L65: 工程情報 | M65: 基本情報 | N65: 外注情報 | O65: 工程情報 | P65: 作業明細 | Q65: 連産品明細 | R65: 材料明細
D66: 受注業務パタン | E66: 加工受注 | F66: ○ | G66: ○ | H66: 〇 | I66: ● | J66: 〇 | K66: 〇 | L66: ● | M66: ● | N66: ● | O66: ● | P66: ● | Q66: ● | R66: ●
E67: シート受注 | F67: ○ | G67: - | H67: 〇 | I67: 〇 | J67: 〇 | K67: 〇 | L67: 〇 | M67: 〇 | N67: 〇 | O67: 〇 | P67: 〇 | Q67: - | R67: 〇
E68: 商品購買 | F68: ○ | G68: - | H68: 〇 | I68: - | J68: 〇 | K68: 〇 | L68: - | M68: - | N68: - | O68: - | P68: - | Q68: - | R68: -
E69: 版型 | F69: ● | G69: - | H69: ● | I69: ● | J69: ● | K69: ● | L69: - | M69: - | N69: - | O69: - | P69: - | Q69: - | R69: -
E70: 有償支給 | F70: ○ | G70: - | H70: 〇 | I70: - | J70: - | K70: ○ | L70: - | M70: - | N70: - | O70: - | P70: - | Q70: - | R70: -
E71: 経費品 | F71: ○ | G71: - | H71: 〇 | I71: - | J71: - | K71: ○ | L71: - | M71: - | N71: - | O71: - | P71: - | Q71: - | R71: -
E72: 原紙売り（受発注方式） | F72: ○ | G72: - | H72: ○ | I72: ○ | J72: ○ | K72: ○ | L72: ○ | M72: ○ | N72: ○ | O72: ○ | P72: ○ | Q72: - | R72: ○
E73: 輪切り | F73: ○ | G73: - | H73: ○ | I73: ○ | J73: ○ | K73: ○ | L73: ○ | M73: ○ | N73: ○ | O73: ○ | P73: ○ | Q73: - | R73: ○

Sheet 纏め（試し）
E1: 受注区分・製品区分の組合せ
B2: 受注区分 | C2: 受注区分名 | E2: 受注区分 | F2: 受注区分名 | G2: 製品区分 大 | H2: 製品区分名 大 | J2: 製品区分 | L2: 受注品目 | M2: 製品区分 大 | N2: 製品区分名 大 | O2: 製品 | Q2: 商品
O3: 内製 | P3: 外注 | R3: 本支店売買 | S3: 通常 | T3: 諸口
B4: 10 | C4: 加工製品 | E4: 10 | F4: 加工製品 | G4: 12 | H4: 加工 | J4: 12:加工 | L4: 段ボール（加工品） | M4: 12 | N4: 加工 | O4: 〇 | P4: 〇 | S4: >外注< | T4: 〇 （MC品目マスタ）
B5: 11 | C5: 加工商品 | E5: 10 | F5: 加工製品 | G5: 13 | H5: Ｇプリント | J5: 13:Ｇプリント | M5: 13 | N5: Ｇプリント | O5: 〇 | P5: 〇 | S5: >外注< | T5: 〇 （MC品目マスタ）
B6: 20 | C6: シート製品 | E6: 10 | F6: 加工製品 | G6: 21 | H6: 巻ボール | J6: 21:巻ボール | M6: 21 | N6: 巻ボール | O6: 〇 | P6: 〇 | S6: >外注< | T6: 〇 （MC品目マスタ）
B7: 21 | C7: シート商品 | E7: 10 | F7: 加工製品 | G7: 23 | H7: 片面加工 | J7: 23:片面加工 | M7: 23 | N7: 片面加工 | O7: 〇 | P7: 〇 | S7: >外注< | T7: 〇 （MC品目マスタ）
B8: 30 | C8: 購買品 | E8: 10 | F8: 加工製品 | G8: 31 | H8: プリフル | J8: 31:プリフル | M8: 31 | N8: プリフル | O8: 〇 | P8: 〇 | S8: >外注< | T8: 〇 （MC品目マスタ）
B9: 40 | C9: 原紙 | E9: 10 | F9: 加工製品 | G9: 32 | H9: 刷本支給 | J9: 32:刷本支給 | M9: 32 | N9: 刷本支給 | O9: 〇 | P9: 〇 | S9: >外注< | T9: 〇 （MC品目マスタ）
E10: 11 | F10: 加工商品 | G10: 12 | H10: 加工 | J10: 12:加工 | L10: シート | M10: 11 | N10: シート | O10: 〇 （WEB受注画面採番） | P10: 〇 （WEB受注画面採番） | S10: >外注< | T10: 〇 （MC品目マスタ）
E11: 11 | F11: 加工商品 | G11: 13 | H11: Ｇプリント | J11: 13:Ｇプリント | M11: 22 | N11: 片面シート | O11: 〇 （WEB受注画面採番） | P11: 〇 （WEB受注画面採番） | S11: >外注< | T11: 〇 （MC品目マスタ）
E12: 11 | F12: 加工商品 | G12: 21 | H12: 巻ボール | J12: 21:巻ボール | L12: 原紙 | M12: 33 | N12: コートボール | O12: 〇 （MC品目マスタ、製品マスタ採番済） | P12: 〇 （MC品目マスタ、製品マスタ採番済） | R12: 〇 （WEB受注画面採番） | S12: 〇 （原紙マスタ） | T12: 〇 （MC品目マスタ）
E13: 11 | F13: 加工商品 | G13: 23 | H13: 片面加工 | J13: 23:片面加工 | M13: 41 | N13: 生原紙 | R13: 〇 （WEB受注画面採番） | S13: 〇 （原紙マスタ） | T13: 〇 （MC品目マスタ）
E14: 11 | F14: 加工商品 | G14: 31 | H14: プリフル | J14: 31:プリフル | M14: 42 | N14: 印刷原紙 | O14: 〇 （MC品目マスタ、製品マスタ採番済） | P14: 〇 （MC品目マスタ、製品マスタ採番済） | R14: 〇 （WEB受注画面採番） | S14: 〇 （原紙マスタ） | T14: 〇 （MC品目マスタ）
E15: 11 | F15: 加工商品 | G15: 32 | H15: 刷本支給 | J15: 32:刷本支給 | M15: 43 | N15: 巻取り原紙 | O15: － | P15: － | R15: ー | S15: ー | T15: － | U15: ※受注なし
E16: 20 | F16: シート製品 | G16: 11 | H16: シート | J16: 11:シート | L16: 購買品 | M16: 51 | N16: 外装シート | T16: 〇 （MC品目マスタ）
E17: 20 | F17: シート製品 | G17: 22 | H17: 片面シート | J17: 22:片面シート | M17: 52 | N17: 外装ケース | T17: 〇 （MC品目マスタ）
E18: 21 | F18: シート商品 | G18: 11 | H18: シート | J18: 11:シート | M18: 61 | N18: 版・型 | T18: 〇 （MC品目マスタ）
E19: 21 | F19: シート商品 | G19: 22 | H19: 片面シート | J19: 22:片面シート | M19: 62 | N19: その他 | T19: 〇 （MC品目マスタ）
E20: 30 | F20: 購買品 | G20: 51 | H20: 外装シート | J20: 51:外装シート | M20: 63 | N20: デザイン代 | T20: 〇 （MC品目マスタ） | U20: ※発注無し
E21: 30 | F21: 購買品 | G21: 52 | H21: 外装ケース | J21: 52:外装ケース | M21: 71 | N21: 袋 | T21: 〇 （MC品目マスタ） | U21: ※発注無し
E22: 30 | F22: 購買品 | G22: 62 | H22: その他 | J22: 62:その他 | M22: 81 | N22: 運賃 | T22: 〇 （MC品目マスタ） | U22: ※発注無し
E23: 30 | F23: 購買品 | G23: 63 | H23: デザイン代 | J23: 63:デザイン代 | M23: 91 | N23: 資材料 | T23: 〇 （MC品目マスタ） | U23: ※発注無し
E24: 30 | F24: 購買品 | G24: 71 | H24: 袋 | J24: 71:袋 | M24: 92 | N24: 前加工料 | T24: 〇 （MC品目マスタ） | U24: ※発注無し
E25: 30 | F25: 購買品 | G25: 80 | H25: モールド | J25: 80:モールド
E26: 30 | F26: 購買品 | G26: 81 | H26: 運賃 | J26: 81:運賃
E27: 30 | F27: 購買品 | G27: 91 | H27: 資材料 | J27: 91:資材料
E28: 30 | F28: 購買品 | G28: 92 | H28: 前加工料 | J28: 92:前加工料
E29: 40 | F29: 原紙 | G29: 33 | H29: コートボール | J29: 33:コートボール
E30: 40 | F30: 原紙 | G30: 41 | H30: 生原紙 | J30: 41:生原紙
E31: 40 | F31: 原紙 | G31: 42 | H31: 印刷原紙 | J31: 42:印刷原紙

Sheet 受注業務パタン
Q2: 受注業務パタン
B3: 画面項目 | Q3: 加工受注 | W3: シート受注 | AC3: 商品購買 | AI3: 版型 | AO3: 有償支給 | AU3: 経費品 | BA3: 原紙売り（受発注方式） | BG3: 輪切り
B4: 第1画面（TOP画面） 基本情報 | Q4: ○ | W4: ○ | AC4: ○ | AI4: ● | AO4: ○ | AU4: ○ | BA4: ○ | BG4: ○
B5: 第1画面（TOP画面） 受注明細 | Q5: ○ | W5: - | AC5: - | AI5: - | AO5: - | AU5: - | BA5: - | BG5: -
B6: 第2画面（基本情報）基本情報 | Q6: 〇 | W6: 〇 | AC6: 〇 | AI6: ● | AO6: 〇 | AU6: 〇 | BA6: ○ | BG6: ○
B7: 第2画面（基本情報）構成情報 | Q7: ● | W7: 〇 | AC7: - | AI7: ● | AO7: - | AU7: - | BA7: ○ | BG7: ○
B8: 第2画面（基本情報）仕入情報 | Q8: 〇 | W8: 〇 | AC8: 〇 | AI8: ● | AO8: - | AU8: - | BA8: ○ | BG8: ○
B9: 第2画面（基本情報）備考 | Q9: 〇 | W9: 〇 | AC9: 〇 | AI9: ● | AO9: ○ | AU9: ○ | BA9: ○ | BG9: ○
B10: 第3画面（工程情報）工程情報 | Q10: ● | W10: 〇 | AC10: - | AI10: - | AO10: - | AU10: - | BA10: ○ | BG10: ○
B11: ポップアップ（詳細入力画面）基本情報 | Q11: ● | W11: 〇 | AC11: - | AI11: - | AO11: - | AU11: - | BA11: ○ | BG11: ○
B12: ポップアップ（詳細入力画面）外注情報 | Q12: ● | W12: 〇 | AC12: - | AI12: - | AO12: - | AU12: - | BA12: ○ | BG12: ○
B13: ポップアップ（詳細入力画面）工程情報 | Q13: ● | W13: 〇 | AC13: - | AI13: - | AO13: - | AU13: - | BA13: ○ | BG13: ○
B14: ポップアップ（詳細入力画面）作業明細 | Q14: ● | W14: 〇 | AC14: - | AI14: - | AO14: - | AU14: - | BA14: ○ | BG14: ○
... B16: 第4画面（材料設定）材料明細 | Q16: ● | W16: 〇 | AC16: - | AI16: - | AO16: - | AU16: - | BA16: ○ | BG16: ○
B18: ※注釈
C19: 〇：編集可能
C20: ●：参照のみ
C21: -：非表示
B23: 受注区分、製品区分の組合せがどの受注業務パタンにあたるかは「受発注パタン詳細」シート参照

Sheet 受注⇒MC
A1: No | B1: 元No | C1: 受注区分 | D1: 受注区分名 | E1: 製品区分大 | F1: 製品区分大名 | G1: 品目区分 | H1: 品目区分名 | I1: 品目区分詳細ＣＤ | J1: 標準品目区分詳細名 | K1: オーダ区分 | L1: 品目系マスタ登録元 | M1: 製品受注パタン | N1: 受注業務パタン | O1: マスタ登録先 | AC1: 発注先の登録 | AD1: 単位の登録 | AE1: 発注単価の登録先 | AF1: 巻きｍの登録先 | AT1: 「注文書の出力」シート参照 | AW1: V7.0 画面制御の追加
O2: 品目マスタ（共通） | P2: 品目マスタ（会社） | Q2: 品目詳細マスタ | R2: 品目単位マスタ | S2: 品目格納先マスタ | T2: BOMマスタ | U2: 品目工程マスタ | V2: 工程工数マスタ | W2: 得意先販売単価マスタ | X2: 加工単価マスタ | Y2: 購買単価マスタ | Z2: （アドオン）原紙マスタ | AA2: （アドオン）事業所別原紙巾マスタ | AB2: （アドオン）原紙単価マスタ | AG2: 発注予定発生元 | AH2: オーダ発生元 | AI2: 品目CD | AJ2: 枝番１ | AK2: 枝番２ | AL2: 枝番３ | AM2: 単価単位取得 | AN2: 単価取得 | AO2: 巻きｍ取得 | AP2: 発注単位取得 | AQ2: 工程仕様取得 | AR2: 単価算出 | AS2: 重量算出 | AT2: 出力注文書 | AU2: 発注/製造あり | AW2: V7.0 画面制御の追加
A3: 1 | B3: 1 | C3: 21 | D3: シート商品 | E3: 11 | F3: シート | G3: 1 | H3: 商品 | I3: 111 | J3: 商品シート | K3: 外注 | L3: WEB受注 | M3: CPで取り扱いがある（品目登録済） | N3: シート受注 | O3: ○ | P3: ○ | Q3: ○ | S3: △ | T3: ○ | AC3: WEB受注 | AD3: WEB受注 | AE3: WEB受注 | AF3: - | AG3: MRP | AH3: MRP | AI3: 製品コード(11桁) | AJ3: 連番4桁 | AM3: NULL | AN3: 加工単価マスタ | AO3: NULL | AP3: 発注予定 | AQ3: 〇 | AR3: 〇：加工単価より取得 | AS3: 〇 | AT3: 加工発注書 | AU3: 〇 | AW3: V7.0 画面制御の追加
C4: 21 | D4: シート商品 | E4: 11 | F4: シート | G4: 1 | H4: 商品 | I4: 111 | J4: 商品シート | K4: 外注 | L4: WEB受注 | M4: CPで取り扱いがある（品目登録済） | N4: シート受注 | O4: ○ | P4: ○ | Q4: ○ | S4: △ | T4: ○ | AC4: WEB受注 | AD4: WEB受注 | AE4: WEB受注 | AF4: - | AG4: 受注 | AH4: - | AI4: 製品コード(11桁) | AJ4: 連番4桁 | AM4: NULL | AN4: 受注 | AO4: NULL | AP4: 受注 | AQ4: 〇 | AR4: 〇：受注明細より取得 | AS4: 〇 | AT4: 加工発注書 | AU4: 〇 | AW4: V7.0 画面制御の追加
A5: 2 | B5: 2 | C5: 21 | D5: シート商品 | E5: 11 | F5: シート | G5: 1 | H5: 商品 | I5: 111 | J5: 商品シート | K5: 購買 | L5: 品目マスタ | M5: CPで取り扱いが無い（諸口品目） | N5: 商品購買 | O5: ○ | P5: ○ | Q5: ○ | AC5: WEB受注 | AD5: WEB受注 | AE5: WEB受注 | AF5: - | AG5: MRP | AH5: MRP | AI5: 諸口品目 | AM5: NULL | AN5: NULL | AO5: NULL | AP5: 発注予定 | AQ5: ×：仕様が取得できない | AR5: ×：諸口品のため購買単価マスタがない | AS5: - | AT5: 加工発注書 | AU5: 〇 | AW5: V7.0 画面制御の追加
C6: 21 | D6: シート商品 | E6: 11 | F6: シート | G6: 1 | H6: 商品 | I6: 111 | J6: 商品シート | K6: 購買 | L6: 品目マスタ | M6: CPで取り扱いが無い（諸口品目） | N6: 商品購買 | O6: ○ | P6: ○ | Q6: ○ | AC6: WEB受注 | AD6: WEB受注 | AE6: WEB受注 | AF6: - | AG6: 受注 | AH6: - | AI6: 諸口品目 | AM6: NULL | AN6: 受注 | AO6: NULL | AP6: 受注 | AQ6: ×：仕様が取得できない | AR6: 〇：受注明細より取得 | AS6: - | AT6: 加工発注書 | AU6: 〇 | AW6: V7.0 画面制御の追加
A7: 3 | B7: 3 | C7: 21 | D7: シート商品 | E7: 11 | F7: シート | G7: 1 | H7: 商品 | I7: 111 | J7: 商品シート | K7: WG間転送 | L7: WEB受注 | M7: CPで取り扱いがある（品目登録済） | N7: シート受注 | O7: ○ | P7: ○ | Q7: ○ | S7: △ | T7: ○ | AC7: - | AD7: - | AE7: - | AF7: - | AG7: MRP | AH7: MRP | AI7: 製品コード(11桁) | AJ7: 連番4桁 | AM7: - | AN7: - | AO7: - | AP7: - | AQ7: - | AR7: - | AS7: - | AT7: - | AU7: 〇 | AW7: V7.0 画面制御の追加
A8: 4 | B8: 4 | C8: 11 | D8: 加工商品 | E8: 12 | F8: 加工 | G8: 1 | H8: 商品 | I8: 112 | J8: 商品加工 | K8: 外注 | L8: 製品マスタ | M8: CPで取り扱いがある（品目登録済） | N8: 加工品受注 | O8: ○ | P8: ○ | Q8: ○ | S8: △ | T8: ○ | W8: ○ | X8: △ | AC8: 製品マスタ→WEB受注 | AD8: WEB受注 | AE8: WEB受注 | AF8: - | AG8: MRP | AH8: MRP | AI8: 製品コード(11桁) | AJ8: 連番4桁 | AM8: NULL | AN8: 加工単価マスタ | AO8: NULL | AP8: 発注予定 | AQ8: 〇 | AR8: 〇：加工単価より取得 | AS8: 〇 | AT8: 加工発注書 | AU8: 〇 | AW8: V7.0 画面制御の追加
C9: 11 | D9: 加工商品 | E9: 12 | F9: 加工 | G9: 1 | H9: 商品 | I9: 112 | J9: 商品加工 | K9: 外注 | L9: 製品マスタ | M9: CPで取り扱いがある（品目登録済） | N9: 加工品受注 | O9: ○ | P9: ○ | Q9: ○ | S9: △ | T9: ○ | W9: ○ | X9: △ | AC9: 製品マスタ→WEB受注 | AD9: WEB受注 | AE9: WEB受注 | AF9: - | AG9: 受注 | AH9: - | AI9: 製品コード(11桁) | AJ9: 連番4桁 | AM9: NULL | AN9: 受注 | AO9: NULL | AP9: 受注 | AQ9: 〇 | AR9: 〇：受注明細より取得 | AS9: 〇 | AT9: 加工発注書 | AU9: 〇 | AW9: V7.0 画面制御の追加
A10: 5 | B10: 5 | C10: 11 | D10: 加工商品 | E10: 12 | F10: 加工 | G10: 1 | H10: 商品 | I10: 112 | J10: 商品加工 | K10: 購買 | L10: 品目マスタ | M10: CPで取り扱いが無い（諸口品目） | N10: 商品購買 | O10: ○ | P10: ○ | Q10: ○ | AC10: WEB受注 | AD10: WEB受注 | AE10: WEB受注 | AF10: - | AG10: MRP | AH10: MRP | AI10: 諸口品目 | AM10: NULL | AN10: NULL | AO10: NULL | AP10: 発注予定 | AQ10: ×：仕様が取得できない | AR10: ×：諸口品のため購買単価マスタがない | AS10: - | AT10: 加工発注書 | AU10: 〇 | AW10: V7.0 画面制御の追加
C11: 11 | D11: 加工商品 | E11: 12 | F11: 加工 | G11: 1 | H11: 商品 | I11: 112 | J11: 商品加工 | K11: 購買 | L11: 品目マスタ | M11: CPで取り扱いが無い（諸口品目） | N11: 商品購買 | O11: ○ | P11: ○ | Q11: ○ | AC11: WEB受注 | AD11: WEB受注 | AE11: WEB受注 | AF11: - | AG11: 受注 | AH11: - | AI11: 諸口品目 | AM11: NULL | AN11: 受注 | AO11: NULL | AP11: 受注 | AQ11: ×：仕様が取得できない | AR11: 〇：受注明細より取得 | AS11: - | AT11: 加工発注書 | AU11: 〇 | AW11: V7.0 画面制御の追加
A12: 6 | B12: 6 | C12: 11 | D12: 加工商品 | E12: 12 | F12: 加工 | G12: 1 | H12: 商品 | I12: 112 | J12: 商品加工 | K12: WG間転送 | L12: 製品マスタ | M12: CPで取り扱いがある（品目登録済） | N12: 加工品受注 | O12: ○ | P12: ○ | Q12: ○ | S12: △ | T12: ○ | W12: ○ | AC12: - | AD12: - | AE12: - | AF12: - | AG12: MRP | AH12: MRP | AI12: 製品コード(11桁) | AJ12: 連番4桁 | AM12: - | AN12: - | AO12: - | AP12: - | AQ12: - | AR12: - | AS12: - | AT12: - | AU12: 〇 | AW12: V7.0 画面制御の追加
A13: 7 | B13: 7 | C13: 11 | D13: 加工商品 | E13: 13 | F13: Ｇプリント | G13: 1 | H13: 商品 | I13: 113 | J13: 商品Ｇプリント | K13: 外注 | L13: 製品マスタ | M13: CPで取り扱いがある（品目登録済） | N13: 加工品受注 | O13: ○ | P13: ○ | Q13: ○ | S13: △ | T13: ○ | W13: ○ | X13: △ | AC13: 製品マスタ→WEB受注 | AD13: 製品マスタ→WEB受注 | AE13: 加工単価→WEB受注 | AF13: - | AG13: MRP | AH13: MRP | AI13: 製品コード(11桁) | AJ13: 連番4桁 | AM13: NULL | AN13: 加工単価マスタ | AO13: NULL | AP13: 発注予定 | AQ13: 〇 | AR13: 〇：加工単価より取得 | AS13: 〇 | AT13: 加工発注書 | AU13: 〇 | AW13: V7.0 画面制御の追加
C14: 11 | D14: 加工商品 | E14: 13 | F14: Ｇプリント | G14: 1 | H14: 商品 | I14: 113 | J14: 商品Ｇプリント | K14: 外注 | L14: 製品マスタ | M14: CPで取り扱いがある（品目登録済） | N14: 加工品受注 | O14: ○ | P14: ○ | Q14: ○ | S14: △ | T14: ○ | W14: ○ | X14: △ | AC14: 製品マスタ→WEB受注 | AD14: 製品マスタ→WEB受注 | AE14: 加工単価→WEB受注 | AF14: - | AG14: 受注 | AH14: - | AI14: 製品コード(11桁) | AJ14: 連番4桁 | AM14: NULL | AN14: 受注 | AO14: NULL | AP14: 受注 | AQ14: 〇 | AR14: 〇：受注明細より取得 | AS14: 〇 | AT14: 加工発注書 | AU14: 〇 | AW14: V7.0 画面制御の追加
A15: 8 | B15: 8 | C15: 11 | D15: 加工商品 | E15: 13 | F15: Ｇプリント | G15: 1 | H15: 商品 | I15: 113 | J15: 商品Ｇプリント | K15: 購買 | L15: 品目マスタ | M15: CPで取り扱いが無い（諸口品目） | N15: 商品購買 | O15: ○ | P15: ○ | Q15: ○ | AC15: WEB受注 | AD15: WEB受注 | AE15: WEB受注 | AF15: - | AG15: MRP | AH15: MRP | AI15: 諸口品目 | AM15: NULL | AN15: NULL | AO15: NULL | AP15: 発注予定 | AQ15: ×：仕様が取得できない | AR15: ×：諸口品のため購買単価マスタがない | AS15: - | AT15: 加工発注書 | AU15: 〇 | AW15: V7.0 画面制御の追加
C16: 11 | D16: 加工商品 | E16: 13 | F16: Ｇプリント | G16: 1 | H16: 商品 | I16: 113 | J16: 商品Ｇプリント | K16: 購買 | L16: 品目マスタ | M16: CPで取り扱いが無い（諸口品目） | N16: 商品購買 | O16: ○ | P16: ○ | Q16: ○ | AC16: WEB受注 | AD16: WEB受注 | AE16: WEB受注 | AF16: - | AG16: 受注 | AH16: - | AI16: 諸口品目 | AM16: NULL | AN16: 受注 | AO16: NULL | AP16: 受注 | AQ16: ×：仕様が取得できない | AR16: 〇：受注明細より取得 | AS16: - | AT16: 加工発注書 | AU16: 〇 | AW16: V7.0 画面制御の追加
A17: 9 | B17: 9 | C17: 11 | D17: 加工商品 | E17: 13 | F17: Ｇプリント | G17: 1 | H17: 商品 | I17: 113 | J17: 商品Ｇプリント | K17: WG間転送 | L17: 製品マスタ | M17: CPで取り扱いがある（品目登録済） | N17: 加工品受注 | O17: ○ | P17: ○ | Q17: ○ | S17: △ | T17: ○ | W17: ○ | AC17: - | AD17: - | AE17: - | AF17: - | AG17: MRP | AH17: MRP | AI17: 製品コード(11桁) | AJ17: 連番4桁 | AM17: - | AN17: - | AO17: - | AP17: - | AQ17: - | AR17: - | AS17: - | AT17: - | AU17: 〇 | AW17: V7.0 画面制御の追加
A18: 10 | B18: 10 | C18: 11 | D18: 加工商品 | E18: 21 | F18: 巻ボール | G18: 1 | H18: 商品 | I18: 121 | J18: 商品巻ボール | K18: 外注 | L18: 製品マスタ | M18: CPで取り扱いがある（品目登録済） | N18: 加工品受注 | O18: ○ | P18: ○ | Q18: ○ | S18: △ | T18: ○ | W18: ○ | X18: △ | AC18: 製品マスタ→WEB受注 | AD18: 製品マスタ→WEB受注 | AE18: 加工単価→WEB受注 | AF18: WEB受注 | AG18: MRP | AH18: MRP | AI18: 製品コード(11桁) | AJ18: 連番4桁 | AM18: NULL | AN18: 加工単価マスタ | AO18: NULL | AP18: 発注予定 | AQ18: 〇 | AR18: 〇：加工単価より取得 | AS18: 〇 | AT18: 加工発注書 | AU18: 〇 | AW18: V7.0 画面制御の追加
C19: 11 | D19: 加工商品 | E19: 21 | F19: 巻ボール | G19: 1 | H19: 商品 | I19: 121 | J19: 商品巻ボール | K19: 外注 | L19: 製品マスタ | M19: CPで取り扱いがある（品目登録済） | N19: 加工品受注 | O19: ○ | P19: ○ | Q19: ○ | S19: △ | T19: ○ | W19: ○ | X19: △ | AC19: 製品マスタ→WEB受注 | AD19: 製品マスタ→WEB受注 | AE19: 加工単価→WEB受注 | AF19: WEB受注 | AG19: 受注 | AH19: - | AI19: 製品コード(11桁) | AJ19: 連番4桁 | AM19: NULL | AN19: 受注 | AO19: NULL | AP19: 受注 | AQ19: 〇 | AR19: 〇：受注明細より取得 | AS19: 〇 | AT19: 加工発注書 | AU19: 〇 | AW19: V7.0 画面制御の追加
A20: 11 | B20: 11 | C20: 11 | D20: 加工商品 | E20: 21 | F20: 巻ボール | G20: 1 | H20: 商品 | I20: 121 | J20: 商品巻ボール | K20: 購買 | L20: 品目マスタ | M20: CPで取り扱いが無い（諸口品目） | N20: 商品購買 | O20: ○ | P20: ○ | Q20: ○ | R20: ○ | AC20: WEB受注 | AD20: WEB受注 | AE20: WEB受注 | AF20: - | AG20: MRP | AH20: MRP | AI20: 諸口品目 | AM20: NULL | AN20: NULL | AO20: NULL | AP20: 発注予定 | AQ20: ×：仕様が取得できない | AR20: ×：諸口品のため購買単価マスタがない | AS20: - | AT20: 加工発注書 | AU20: 〇 | AW20: V7.0 画面制御の追加
C21: 11 | D21: 加工商品 | E21: 21 | F21: 巻ボール | G21: 1 | H21: 商品 | I21: 121 | J21: 商品巻ボール | K21: 購買 | L21: 品目マスタ | M21: CPで取り扱いが無い（諸口品目） | N21: 商品購買 | O21: ○ | P21: ○ | Q21: ○ | R21: ○ | AC21: WEB受注 | AD21: WEB受注 | AE21: WEB受注 | AF21: - | AG21: 受注 | AH21: - | AI21: 諸口品目 | AM21: NULL | AN21: 受注 | AO21: NULL | AP21: 受注 | AQ21: ×：仕様が取得できない | AR21: 〇：受注明細より取得 | AS21: - | AT21: 加工発注書 | AU21: 〇 | AW21: V7.0 画面制御の追加
A22: 12 | B22: 12 | C22: 11 | D22: 加工商品 | E22: 21 | F22: 巻ボール | G22: 1 | H22: 商品 | I22: 121 | J22: 商品巻ボール | K22: WG間転送 | L22: 製品マスタ | M22: CPで取り扱いがある（品目登録済） | N22: 加工品受注 | O22: ○ | P22: ○ | Q22: ○ | S22: △ | T22: ○ | W22: ○ | AC22: - | AD22: - | AE22: - | AF22: - | AG22: MRP | AH22: MRP | AI22: 製品コード(11桁) | AJ22: 連番4桁 | AM22: - | AN22: - | AO22: - | AP22: - | AQ22: - | AR22: - | AS22: - | AT22: - | AU22: 〇 | AW22: V7.0 画面制御の追加
A23: 13 | B23: 13 | C23: 21 | D23: シート商品 | E23: 22 | F23: 片面シート | G23: 1 | H23: 商品 | I23: 122 | J23: 商品片面シート | K23: 外注 | L23: WEB受注 | M23: CPで取り扱いがある（品目登録済） | N23: シート受注 | O23: ○ | P23: ○ | Q23: ○ | S23: △ | T23: ○ | AC23: WEB受注 | AD23: WEB受注 | AE23: WEB受注 | AF23: - | AG23: MRP | AH23: MRP | AI23: 製品コード(11桁) | AJ23: 連番4桁 | AM23: NULL | AN23: 加工単価マスタ | AO23: NULL | AP23: 発注予定 | AQ23: 〇 | AR23: 〇：加工単価より取得 | AS23: 〇 | AT23: 加工発注書 | AU23: 〇 | AW23: V7.0 画面制御の追加
C24: 21 | D24: シート商品 | E24: 22 | F24: 片面シート | G24: 1 | H24: 商品 | I24: 122 | J24: 商品片面シート | K24: 外注 | L24: WEB受注 | M24: CPで取り扱いがある（品目登録済） | N24: シート受注 | O24: ○ | P24: ○ | Q24: ○ | S24: △ | T24: ○ | AC24: WEB受注 | AD24: WEB受注 | AE24: WEB受注 | AF24: - | AG24: 受注 | AH24: - | AI24: 製品コード(11桁) | AJ24: 連番4桁 | AM24: NULL | AN24: 受注 | AO24: NULL | AP24: 受注 | AQ24: 〇 | AR24: 〇：受注明細より取得 | AS24: 〇 | AT24: 加工発注書 | AU24: 〇 | AW24: V7.0 画面制御の追加
A25: 14 | B25: 14 | C25: 21 | D25: シート商品 | E25: 22 | F25: 片面シート | G25: 1 | H25: 商品 | I25: 122 | J25: 商品片面シート | K25: 購買 | L25: 品目マスタ | M25: CPで取り扱いが無い（諸口品目） | N25: 商品購買 | O25: ○ | P25: ○ | Q25: ○ | AC25: WEB受注 | AD25: WEB受注 | AE25: WEB受注 | AF25: - | AG25: MRP | AH25: MRP | AI25: 諸口品目 | AM25: NULL | AN25: NULL | AO25: NULL | AP25: 発注予定 | AQ25: ×：仕様が取得できない | AR25: ×：諸口品のため購買単価マスタがない | AS25: - | AT25: 加工発注書 | AU25: 〇 | AW25: V7.0 画面制御の追加
C26: 21 | D26: シート商品 | E26: 22 | F26: 片面シート | G26: 1 | H26: 商品 | I26: 122 | J26: 商品片面シート | K26: 購買 | L26: 品目マスタ | M26: CPで取り扱いが無い（諸口品目） | N26: 商品購買 | O26: ○ | P26: ○ | Q26: ○ | AC26: WEB受注 | AD26: WEB受注 | AE26: WEB受注 | AF26: - | AG26: 受注 | AH26: - | AI26: 諸口品目 | AM26: NULL | AN26: 受注 | AO26: NULL | AP26: 受注 | AQ26: ×：仕様が取得できない | AR26: 〇：受注明細より取得 | AS26: - | AT26: 加工発注書 | AU26: 〇 | AW26: V7.0 画面制御の追加
A27: 15 | B27: 15 | C27: 21 | D27: シート商品 | E27: 22 | F27: 片面シート | G27: 1 | H27: 商品 | I27: 122 | J27: 商品片面シート | K27: WG間転送 | L27: WEB受注 | M27: CPで取り扱いがある（品目登録済） | N27: シート受注 | O27: ○ | P27: ○ | Q27: ○ | S27: △ | T27: ○ | AC27: - | AD27: - | AE27: - | AF27: - | AG27: MRP | AH27: MRP | AI27: 製品コード(11桁) | AJ27: 連番4桁 | AM27: - | AN27: - | AO27: - | AP27: - | AQ27: - | AR27: - | AS27: - | AT27: - | AU27: 〇 | AW27: V7.0 画面制御の追加
A28: 16 | B28: 16 | C28: 11 | D28: 加工商品 | E28: 23 | F28: 片面加工 | G28: 1 | H28: 商品 | I28: 123 | J28: 商品片面加工 | K28: 外注 | L28: 製品マスタ | M28: CPで取り扱いがある（品目登録済） | N28: 加工品受注 | O28: ○ | P28: ○ | Q28: ○ | S28: △ | T28: ○ | W28: ○ | X28: △ | AC28: 製品マスタ→WEB受注 | AD28: 製品マスタ→WEB受注 | AE28: 加工単価→WEB受注 | AF28: - | AG28: MRP | AH28: MRP | AI28: 製品コード(11桁) | AJ28: 連番4桁 | AM28: NULL | AN28: 加工単価マスタ | AO28: NULL | AP28: 発注予定 | AQ28: 〇 | AR28: 〇：加工単価より取得 | AS28: 〇 | AT28: 加工発注書 | AU28: 〇 | AW28: V7.0 画面制御の追加
C29: 11 | D29: 加工商品 | E29: 23 | F29: 片面加工 | G29: 1 | H29: 商品 | I29: 123 | J29: 商品片面加工 | K29: 外注 | L29: 製品マスタ | M29: CPで取り扱いがある（品目登録済） | N29: 加工品受注 | O29: ○ | P29: ○ | Q29: ○ | S29: △ | T29: ○ | W29: ○ | X29: △ | AC29: 製品マスタ→WEB受注 | AD29: 製品マスタ→WEB受注 | AE29: 加工単価→WEB受注 | AF29: - | AG29: 受注 | AH29: - | AI29: 製品コード(11桁) | AJ29: 連番4桁 | AM29: NULL | AN29: 受注 | AO29: NULL | AP29: 受注 | AQ29: 〇 | AR29: 〇：受注明細より取得 | AS29: 〇 | AT29: 加工発注書 | AU29: 〇 | AW29: V7.0 画面制御の追加
A30: 17 | B30: 17 | C30: 11 | D30: 加工商品 | E30: 23 | F30: 片面加工 | G30: 1 | H30: 商品 | I30: 123 | J30: 商品片面加工 | K30: 購買 | L30: 品目マスタ | M30: CPで取り扱いが無い（諸口品目） | N30: 商品購買 | O30: ○ | P30: ○ | Q30: ○ | AC30: WEB受注 | AD30: WEB受注 | AE30: WEB受注 | AF30: - | AG30: MRP | AH30: MRP | AI30: 諸口品目 | AM30: NULL | AN30: NULL | AO30: NULL | AP30: 発注予定 | AQ30: ×：仕様が取得できない | AR30: ×：諸口品のため購買単価マスタがない | AS30: - | AT30: 加工発注書 | AU30: 〇 | AW30: V7.0 画面制御の追加
C31: 11 | D31: 加工商品 | E31: 23 | F31: 片面加工 | G31: 1 | H31: 商品 | I31: 123 | J31: 商品片面加工 | K31: 購買 | L31: 品目マスタ | M31: CPで取り扱いが無い（諸口品目） | N31: 商品購買 | O31: ○ | P31: ○ | Q31: ○ | AC31: WEB受注 | AD31: WEB受注 | AE31: WEB受注 | AF31: - | AG31: 受注 | AH31: - | AI31: 諸口品目 | AM31: NULL | AN31: 受注 | AO31: NULL | AP31: 受注 | AQ31: ×：仕様が取得できない | AR31: 〇：受注明細より取得 | AS31: - | AT31: 加工発注書 | AU31: 〇 | AW31: V7.0 画面制御の追加
A32: 18 | B32: 18 | C32: 11 | D32: 加工商品 | E32: 23 | F32: 片面加工 | G32: 1 | H32: 商品 | I32: 123 | J32: 商品片面加工 | K32: WG間転送 | L32: 製品マスタ | M32: CPで取り扱いがある（品目登録済） | N32: 加工品受注 | O32: ○ | P32: ○ | Q32: ○ | S32: △ | T32: ○ | W32: ○ | AC32: - | AD32: - | AE32: - | AF32: - | AG32: MRP | AH32: MRP | AI32: 製品コード(11桁) | AJ32: 連番4桁 | AM32: - | AN32: - | AO32: - | AP32: - | AQ32: - | AR32: - | AS32: - | AT32: - | AU32: 〇 | AW32: V7.0 画面制御の追加
A33: 19 | B33: 19 | C33: 11 | D33: 加工商品 | E33: 31 | F33: プリフル | G33: 1 | H33: 商品 | I33: 131 | J33: 商品プリフル | K33: 外注 | L33: 製品マスタ | M33: CPで取り扱いがある（品目登録済） | N33: 加工品受注 | O33: ○ | P33: ○ | Q33: ○ | S33: △ | T33: ○ | W33: ○ | X33: △ | AC33: 製品マスタ→WEB受注 | AD33: 製品マスタ→WEB受注 | AE33: 加工単価→WEB受注 | AF33: - | AG33: MRP | AH33: MRP | AI33: 製品コード(11桁) | AJ33: 連番4桁 | AM33: NULL | AN33: 加工単価マスタ | AO33: NULL | AP33: 発注予定 | AQ33: 〇 | AR33: 〇：加工単価より取得 | AS33: 〇 | AT33: 加工発注書 | AU33: 〇 | AW33: V7.0 画面制御の追加
C34: 11 | D34: 加工商品 | E34: 31 | F34: プリフル | G34: 1 | H34: 商品 | I34: 131 | J34: 商品プリフル | K34: 外注 | L34: 製品マスタ | M34: CPで取り扱いがある（品目登録済） | N34: 加工品受注 | O34: ○ | P34: ○ | Q34: ○ | S34: △ | T34: ○ | W34: ○ | X34: △ | AC34: 製品マスタ→WEB受注 | AD34: 製品マスタ→WEB受注 | AE34: 加工単価→WEB受注 | AF34: - | AG34: 受注 | AH34: - | AI34: 製品コード(11桁) | AJ34: 連番4桁 | AM34: NULL | AN34: 受注 | AO34: NULL | AP34: 受注 | AQ34: 〇 | AR34: 〇：受注明細より取得 | AS34: 〇 | AT34: 加工発注書 | AU34: 〇 | AW34: V7.0 画面制御の追加
A35: 20 | B35: 20 | C35: 11 | D35: 加工商品 | E35: 31 | F35: プリフル | G35: 1 | H35: 商品 | I35: 131 | J35: 商品プリフル | K35: 購買 | L35: 品目マスタ | M35: CPで取り扱いが無い（諸口品目） | N35: 商品購買 | O35: ○ | P35: ○ | Q35: ○ | AC35: WEB受注 | AD35: WEB受注 | AE35: WEB受注 | AF35: - | AG35: MRP | AH35: MRP | AI35: 諸口品目 | AM35: NULL | AN35: NULL | AO35: NULL | AP35: 発注予定 | AQ35: ×：仕様が取得できない | AR35: ×：諸口品のため購買単価マスタがない | AS35: - | AT35: 加工発注書 | AU35: 〇 | AW35: V7.0 画面制御の追加
C36: 11 | D36: 加工商品 | E36: 31 | F36: プリフル | G36: 1 | H36: 商品 | I36: 131 | J36: 商品プリフル | K36: 購買 | L36: 品目マスタ | M36: CPで取り扱いが無い（諸口品目） | N36: 商品購買 | O36: ○ | P36: ○ | Q36: ○ | AC36: WEB受注 | AD36: WEB受注 | AE36: WEB受注 | AF36: - | AG36: 受注 | AH36: - | AI36: 諸口品目 | AM36: NULL | AN36: 受注 | AO36: NULL | AP36: 受注 | AQ36: ×：仕様が取得できない | AR36: 〇：受注明細より取得 | AS36: - | AT36: 加工発注書 | AU36: 〇 | AW36: V7.0 画面制御の追加
A37: 21 | B37: 21 | C37: 11 | D37: 加工商品 | E37: 31 | F37: プリフル | G37: 1 | H37: 商品 | I37: 131 | J37: 商品プリフル | K37: WG間転送 | L37: 製品マスタ | M37: CPで取り扱いがある（品目登録済） | N37: 加工品受注 | O37: ○ | P37: ○ | Q37: ○ | S37: △ | T37: ○ | W37: ○ | AC37: - | AD37: - | AE37: - | AF37: - | AG37: MRP | AH37: MRP | AI37: 製品コード(11桁) | AJ37: 連番4桁 | AM37: - | AN37: - | AO37: - | AP37: - | AQ37: - | AR37: - | AS37: - | AT37: - | AU37: 〇 | AW37: V7.0 画面制御の追加
A38: 22 | B38: 22 | C38: 11 | D38: 加工商品 | E38: 32 | F38: 刷本支給 | G38: 1 | H38: 商品 | I38: 132 | J38: 商品刷本支給 | K38: 外注 | L38: 製品マスタ | M38: CPで取り扱いがある（品目登録済） | N38: 加工品受注 | O38: ○ | P38: ○ | Q38: ○ | S38: △ | T38: ○ | W38: ○ | X38: △ | AC38: 製品マスタ→WEB受注 | AD38: 製品マスタ→WEB受注 | AE38: 加工単価→WEB受注 | AF38: - | AG38: MRP | AH38: MRP | AI38: 製品コード(11桁) | AJ38: 連番4桁 | AM38: NULL | AN38: 加工単価マスタ | AO38: NULL | AP38: 発注予定 | AQ38: 〇 | AR38: 〇：加工単価より取得 | AS38: 〇 | AT38: 加工発注書 | AU38: 〇 | AW38: V7.0 画面制御の追加
C39: 11 | D39: 加工商品 | E39: 32 | F39: 刷本支給 | G39: 1 | H39: 商品 | I39: 132 | J39: 商品刷本支給 | K39: 外注 | L39: 製品マスタ | M39: CPで取り扱いがある（品目登録済） | N39: 加工品受注 | O39: ○ | P39: ○ | Q39: ○ | S39: △ | T39: ○ | W39: ○ | X39: △ | AC39: 製品マスタ→WEB受注 | AD39: 製品マスタ→WEB受注 | AE39: 加工単価→WEB受注 | AF39: - | AG39: 受注 | AH39: - | AI39: 製品コード(11桁) | AJ39: 連番4桁 | AM39: NULL | AN39: 受注 | AO39: NULL | AP39: 受注 | AQ39: 〇 | AR39: 〇：受注明細より取得 | AS39: 〇 | AT39: 加工発注書 | AU39: 〇 | AW39: V7.0 画面制御の追加
A40: 23 | B40: 23 | C40: 11 | D40: 加工商品 | E40: 32 | F40: 刷本支給 | G40: 1 | H40: 商品 | I40: 132 | J40: 商品刷本支給 | K40: 購買 | L40: 品目マスタ | M40: CPで取り扱いが無い（諸口品目） | N40: 商品購買 | O40: ○ | P40: ○ | Q40: ○ | AC40: WEB受注 | AD40: WEB受注 | AE40: WEB受注 | AF40: - | AG40: MRP | AH40: MRP | AI40: 諸口品目 | AM40: NULL | AN40: NULL | AO40: NULL | AP40: 発注予定 | AQ40: ×：仕様が取得できない | AR40: ×：諸口品のため購買単価マスタがない | AS40: - | AT40: 加工発注書 | AU40: 〇 | AW40: V7.0 画面制御の追加
C41: 11 | D41: 加工商品 | E41: 32 | F41: 刷本支給 | G41: 1 | H41: 商品 | I41: 132 | J41: 商品刷本支給 | K41: 購買 | L41: 品目マスタ | M41: CPで取り扱いが無い（諸口品目） | N41: 商品購買 | O41: ○ | P41: ○ | Q41: ○ | AC41: WEB受注 | AD41: WEB受注 | AE41: WEB受注 | AF41: - | AG41: 受注 | AH41: - | AI41: 諸口品目 | AM41: NULL | AN41: 受注 | AO41: NULL | AP41: 受注 | AQ41: ×：仕様が取得できない | AR41: 〇：受注明細より取得 | AS41: - | AT41: 加工発注書 | AU41: 〇 | AW41: V7.0 画面制御の追加
A42: 24 | B42: 24 | C42: 11 | D42: 加工商品 | E42: 32 | F42: 刷本支給 | G42: 1 | H42: 商品 | I42: 132 | J42: 商品刷本支給 | K42: WG間転送 | L42: 製品マスタ | M42: CPで取り扱いがある（品目登録済） | N42: 加工品受注 | O42: ○ | P42: ○ | Q42: ○ | S42: △ | W42: ○ | AC42: - | AD42: - | AE42: - | AF42: - | AG42: MRP | AH42: MRP | AI42: 製品コード(11桁) | AJ42: 連番4桁 | AM42: - | AN42: - | AO42: - | AP42: - | AQ42: - | AR42: - | AS42: - | AT42: - | AU42: 〇 | AW42: V7.0 画面制御の追加
A43: 25 | B43: 25 | C43: 40 | D43: 原紙 | E43: 33 | F43: コートボール | G43: 1 | H43: 商品 | I43: 133 | J43: 商品コートボール | K43: 購買 | L43: 品目マスタ | M43: CPで取り扱いが無い（諸口品目） | N43: 商品購買 | O43: ○ | P43: ○ | Q43: ○ | R43: ○ | AC43: WEB受注 | AD43: WEB受注 | AE43: WEB受注 | AF43: - | AG43: MRP | AH43: MRP | AI43: 製品コード(11桁) | AJ43: 連番4桁 | AM43: 原紙単価 | AN43: 原紙単価 | AO43: NULL | AP43: 発注予定 | AQ43: ×：寸法が取得できない | AR43: ×：寸法の取得ができない？ | AS43: ×：寸法(巾・流れ)、坪量が取得できない | AT43: 加工発注書 | AU43: 〇 | AW43: V7.0 画面制御の追加
C44: 40 | D44: 原紙 | E44: 33 | F44: コートボール | G44: 1 | H44: 商品 | I44: 133 | J44: 商品コートボール | K44: 購買 | L44: 品目マスタ | M44: CPで取り扱いが無い（諸口品目） | N44: 商品購買 | O44: ○ | P44: ○ | Q44: ○ | R44: ○ | AC44: WEB受注 | AD44: WEB受注 | AE44: WEB受注 | AF44: - | AG44: 受注 | AH44: - | AI44: 製品コード(11桁) | AJ44: 連番4桁 | AM44: 受注 | AN44: 受注 | AO44: NULL | AP44: 受注 | AQ44: ×：寸法が取得できない | AR44: ×：各項目を受注明細より取得するが、単価単位によっては(kgや㎡など)算出不可 | AS44: ×：寸法(巾・流れ)、坪量が取得できない | AT44: 加工発注書 | AU44: 〇 | AW44: V7.0 画面制御の追加
A45: 26 | B45: 26 | C45: 40 | D45: 原紙 | E45: 33 | F45: コートボール | G45: 1 | H45: 商品 | I45: 133 | J45: 商品コートボール | K45: 外注 | L45: 製品マスタ | M45: CPで取り扱いがある（品目登録済） | N45: 加工品受注 | O45: ○ | P45: ○ | Q45: ○ | R45: ○ | T45: 〇 | W45: ○ | X45: △ | AC45: 製品マスタ→WEB受注 | AD45: 製品マスタ→WEB受注 | AE45: 加工単価→WEB受注 | AF45: - | AG45: MRP | AH45: MRP | AI45: 諸口品目 | AM45: NULL | AN45: NULL | AO45: NULL | AP45: 発注予定 | AQ45: ×：寸法が取得できない | AR45: ×：諸口品のため加工単価が存在しない | AS45: ×：寸法(巾・流れ)、坪量が取得できない | AT45: 加工発注書 | AU45: 〇 | AW45: V7.0 画面制御の追加
C46: 40 | D46: 原紙 | E46: 33 | F46: コートボール | G46: 1 | H46: 商品 | I46: 133 | J46: 商品コートボール | K46: 外注 | L46: 製品マスタ | M46: CPで取り扱いがある（品目登録済） | N46: 加工品受注 | O46: ○ | P46: ○ | Q46: ○ | R46: ○ | T46: 〇 | W46: ○ | X46: △ | AC46: 製品マスタ→WEB受注 | AD46: 製品マスタ→WEB受注 | AE46: 加工単価→WEB受注 | AF46: - | AG46: 受注 | AH46: - | AI46: 諸口品目 | AM46: 受注 | AN46: 受注 | AO46: NULL | AP46: 受注 | AQ46: ×：寸法が取得できない | AR46: 〇：受注明細より取得 | AS46: ×：寸法(巾・流れ)、坪量が取得できない | AT46: 加工発注書 | AU46: 〇 | AW46: V7.0 画面制御の追加
A47: 27 | B47: 27 | C47: 40 | D47: 原紙 | E47: 33 | F47: コートボール | G47: 1 | H47: 商品 | I47: 133 | J47: 商品コートボール | K47: WG間転送 | L47: 製品マスタ | M47: CPで取り扱いがある（品目登録済） | N47: 加工品受注 | O47: ○ | P47: ○ | Q47: ○ | R47: ○ | S47: △ | T47: ○ | W47: ○ | AC47: - | AD47: - | AE47: - | AF47: - | AG47: MRP | AH47: MRP | AI47: 製品コード(11桁) | AJ47: 連番4桁 | AM47: - | AN47: - | AO47: - | AP47: - | AQ47: - | AR47: - | AS47: - | AT47: - | AU47: 〇 | AW47: V7.0 画面制御の追加
A48: 28 | B48: 28 | C48: 40 | D48: 原紙 | E48: 41 | F48: 生原紙 | G48: 1 | H48: 商品 | I48: 141 | J48: 商品原紙 | K48: 購買 | L48: 品目マスタ | M48: CPで取り扱いが無い（諸口品目） | N48: 商品購買 | O48: ○ | P48: ○ | Q48: ○ | R48: ○ | AC48: WEB受注 | AD48: WEB受注 | AE48: WEB受注 | AF48: - | AG48: MRP | AH48: MRP | AI48: 諸口品目 | AM48: NULL | AN48: NULL | AO48: 単価単位マスタ | AP48: 発注予定 | AQ48: ×：仕様が取得できない | AR48: ×：諸口品のため購買単価マスタがない | AS48: - | AT48: 加工発注書 | AU48: 〇 | AW48: V7.0 画面制御の追加
C49: 40 | D49: 原紙 | E49: 41 | F49: 生原紙 | G49: 1 | H49: 商品 | I49: 141 | J49: 商品原紙 | K49: 購買 | L49: 品目マスタ | M49: CPで取り扱いが無い（諸口品目） | N49: 商品購買 | O49: ○ | P49: ○ | Q49: ○ | R49: ○ | AC49: WEB受注 | AD49: WEB受注 | AE49: WEB受注 | AF49: - | AG49: 受注 | AH49: - | AI49: 諸口品目 | AM49: 受注 | AN49: 受注 | AO49: 受注 | AP49: 受注 | AQ49: ×：仕様が取得できない | AR49: 〇：受注明細より取得 | AS49: - | AT49: 加工発注書 | AU49: 〇 | AW49: V7.0 画面制御の追加
A50: 29 | B50: 29 | C50: 40 | D50: 原紙 | E50: 42 | F50: 印刷原紙 | G50: 1 | H50: 商品 | I50: 142 | J50: 商品印刷原紙 | K50: 購買 | L50: 品目マスタ | M50: CPで取り扱いが無い（諸口品目） | N50: 商品購買 | O50: ○ | P50: ○ | Q50: ○ | R50: ○ | AC50: WEB受注 | AD50: WEB受注 | AE50: WEB受注 | AF50: - | AG50: MRP | AH50: MRP | AI50: 諸口品目 | AM50: NULL | AN50: NULL | AO50: 単価単位マスタ | AP50: 発注予定 | AQ50: ×：仕様が取得できない | AR50: ×：諸口品のため購買単価マスタがない | AS50: - | AT50: 加工発注書 | AU50: 〇 | AW50: V7.0 画面制御の追加
C51: 40 | D51: 原紙 | E51: 42 | F51: 印刷原紙 | G51: 1 | H51: 商品 | I51: 142 | J51: 商品印刷原紙 | K51: 購買 | L51: 品目マスタ | M51: CPで取り扱いが無い（諸口品目） | N51: 商品購買 | O51: ○ | P51: ○ | Q51: ○ | R51: ○ | AC51: WEB受注 | AD51: WEB受注 | AE51: WEB受注 | AF51: - | AG51: 受注 | AH51: - | AI51: 諸口品目 | AM51: 受注 | AN51: 受注 | AO51: 受注 | AP51: 受注 | AQ51: ×：仕様が取得できない | AR51: 〇：受注明細より取得 | AS51: - | AT51: 加工発注書 | AU51: 〇 | AW51: V7.0 画面制御の追加
A52: 30 | B52: 30 | C52: 40 | D52: 原紙 | E52: 42 | F52: 印刷原紙 | G52: 1 | H52: 商品 | I52: 142 | J52: 商品印刷原紙 | K52: 外注 | L52: 製品マスタ | M52: CPで取り扱いがある（品目登録済） | N52: 加工品受注 | O52: ○ | P52: ○ | Q52: ○ | R52: ○ | S52: △ | T52: ○ | W52: ○ | X52: △ | Z52: △ | AA52: △ | AC52: 製品マスタ→WEB受注 | AD52: 製品マスタ→WEB受注 | AE52: 加工単価→WEB受注 | AF52: - | AG52: MRP | AH52: MRP | AI52: 製品コード(11桁) | AJ52: 連番4桁 | AM52: NULL | AN52: 加工単価マスタ | AO52: 品目単位 | AP52: 発注予定 | AQ52: 〇 | AR52: 〇：加工単価より取得 | AS52: ×：寸法(巾)、坪量が取得できない | AT52: 加工発注書 | AU52: 〇 | AW52: V7.0 画面制御の追加
C53: 40 | D53: 原紙 | E53: 42 | F53: 印刷原紙 | G53: 1 | H53: 商品 | I53: 142 | J53: 商品印刷原紙 | K53: 外注 | L53: 製品マスタ | M53: CPで取り扱いがある（品目登録済） | N53: 加工品受注 | O53: ○ | P53: ○ | Q53: ○ | R53: ○ | S53: △ | T53: ○ | W53: ○ | X53: △ | Z53: △ | AA53: △ | AC53: 製品マスタ→WEB受注 | AD53: 製品マスタ→WEB受注 | AE53: 加工単価→WEB受注 | AF53: - | AG53: 受注 | AH53: - | AI53: 製品コード(11桁) | AJ53: 連番4桁 | AM53: NULL | AN53: 受注 | AO53: NULL | AP53: 受注 | AQ53: 〇 | AR53: 〇：受注明細より取得 | AS53: ×：寸法(巾)、坪量が取得できない | AT53: 加工発注書 | AU53: 〇 | AW53: V7.0 画面制御の追加
A54: 31 | B54: 31 | C54: 40 | D54: 原紙 | E54: 42 | F54: 印刷原紙 | G54: 1 | H54: 商品 | I54: 142 | J54: 商品印刷原紙 | K54: WG間転送 | L54: 製品マスタ | M54: CPで取り扱いがある（品目登録済） | N54: 加工品受注 | O54: ○ | P54: ○ | Q54: ○ | R54: ○ | S54: △ | T54: ○ | W54: ○ | AC54: - | AD54: - | AE54: - | AF54: - | AG54: MRP | AH54: MRP | AI54: 製品コード(11桁) | AJ54: 連番4桁 | AM54: - | AN54: - | AO54: - | AP54: - | AQ54: - | AR54: - | AS54: - | AT54: - | AU54: 〇 | AW54: V7.0 画面制御の追加
A55: 32 | B55: 33 | C55: 30 | D55: 購買品 | E55: 51 | F55: 外装シート | G55: 1 | H55: 商品 | I55: 151 | J55: 外装シート | K55: 購買 | L55: 品目マスタ | M55: CPで取り扱いが無い（諸口品目） | N55: 商品購買 | O55: ○ | P55: ○ | Q55: ○ | AC55: WEB受注 | AD55: WEB受注 | AE55: WEB受注 | AF55: - | AG55: MRP | AH55: MRP | AI55: 諸口品目 | AM55: NULL | AN55: NULL | AO55: NULL | AP55: 発注予定 | AQ55: ×：仕様が取得できない | AR55: ×：諸口品のため購買単価マスタがない | AS55: - | AT55: 不明(おそらく発注書) | AU55: 〇 | AW55: V7.0 画面制御の追加
C56: 30 | D56: 購買品 | E56: 51 | F56: 外装シート | G56: 1 | H56: 商品 | I56: 151 | J56: 外装シート | K56: 購買 | L56: 品目マスタ | M56: CPで取り扱いが無い（諸口品目） | N56: 商品購買 | O56: ○ | P56: ○ | Q56: ○ | AC56: WEB受注 | AD56: WEB受注 | AE56: WEB受注 | AF56: - | AG56: 受注 | AH56: - | AI56: 諸口品目 | AM56: NULL | AN56: 受注 | AO56: NULL | AP56: 受注 | AQ56: ×：仕様が取得できない | AR56: 〇：受注明細より取得 | AS56: - | AT56: 不明(おそらく発注書) | AU56: 〇 | AW56: V7.0 画面制御の追加
A57: 33 | B57: 34 | C57: 30 | D57: 購買品 | E57: 52 | F57: 外装ケース | G57: 1 | H57: 商品 | I57: 152 | J57: 外装ケース | K57: 購買 | L57: 品目マスタ | M57: CPで取り扱いが無い（諸口品目） | N57: 商品購買 | O57: ○ | P57: ○ | Q57: ○ | AC57: WEB受注 | AD57: WEB受注 | AE57: WEB受注 | AF57: - | AG57: MRP | AH57: MRP | AI57: 諸口品目 | AM57: NULL | AN57: NULL | AO57: NULL | AP57: 発注予定 | AQ57: ×：仕様が取得できない | AR57: ×：諸口品のため購買単価マスタがない | AS57: - | AT57: 発注書 | AU57: 〇 | AW57: V7.0 画面制御の追加
C58: 30 | D58: 購買品 | E58: 52 | F58: 外装ケース | G58: 1 | H58: 商品 | I58: 152 | J58: 外装ケース | K58: 購買 | L58: 品目マスタ | M58: CPで取り扱いが無い（諸口品目） | N58: 商品購買 | O58: ○ | P58: ○ | Q58: ○ | AC58: WEB受注 | AD58: WEB受注 | AE58: WEB受注 | AF58: - | AG58: 受注 | AH58: - | AI58: 諸口品目 | AM58: NULL | AN58: 受注 | AO58: NULL | AP58: 受注 | AQ58: ×：仕様が取得できない | AR58: 〇：受注明細より取得 | AS58: - | AT58: 発注書 | AU58: 〇 | AW58: V7.0 画面制御の追加
A59: 34 | B59: 35 | C59: 30 | D59: 購買品 | E59: 71 | F59: 袋 | G59: 1 | H59: 商品 | I59: 171 | J59: 袋 | K59: 購買 | L59: 品目マスタ | M59: CPで取り扱いが無い（諸口品目） | N59: 商品購買 | O59: ○ | P59: ○ | Q59: ○ | AC59: WEB受注 | AD59: WEB受注 | AE59: WEB受注 | AF59: - | AG59: MRP | AH59: MRP | AI59: 諸口品目 | AM59: NULL | AN59: NULL | AO59: NULL | AP59: 発注予定 | AQ59: ×：仕様が取得できない | AR59: ×：諸口品のため購買単価マスタがない | AS59: - | AT59: 発注書 | AU59: 〇 | AW59: V7.0 画面制御の追加
C60: 30 | D60: 購買品 | E60: 71 | F60: 袋 | G60: 1 | H60: 商品 | I60: 171 | J60: 袋 | K60: 購買 | L60: 品目マスタ | M60: CPで取り扱いが無い（諸口品目） | N60: 商品購買 | O60: ○ | P60: ○ | Q60: ○ | AC60: WEB受注 | AD60: WEB受注 | AE60: WEB受注 | AF60: - | AG60: 受注 | AH60: - | AI60: 諸口品目 | AM60: NULL | AN60: 受注 | AO60: NULL | AP60: 受注 | AQ60: ×：仕様が取得できない | AR60: 〇：受注明細より取得 | AS60: - | AT60: 発注書 | AU60: 〇 | AW60: V7.0 画面制御の追加
A61: 35 | B61: 36 | C61: 30 | D61: 購買品 | E61: 80 | F61: モールド | G61: 1 | H61: 商品 | I61: 180 | J61: モールド | K61: 購買 | L61: 品目マスタ | M61: CPで取り扱いが無い（諸口品目） | N61: 商品購買 | O61: ○ | P61: ○ | Q61: ○ | AC61: WEB受注 | AD61: WEB受注 | AE61: WEB受注 | AF61: - | AG61: MRP | AH61: MRP | AI61: 諸口品目 | AM61: NULL | AN61: NULL | AO61: NULL | AP61: 発注予定 | AQ61: ×：仕様が取得できない | AR61: ×：諸口品のため購買単価マスタがない | AS61: - | AT61: 発注書 | AU61: 〇 | AW61: V7.0 画面制御の追加
C62: 30 | D62: 購買品 | E62: 80 | F62: モールド | G62: 1 | H62: 商品 | I62: 180 | J62: モールド | K62: 購買 | L62: 品目マスタ | M62: CPで取り扱いが無い（諸口品目） | N62: 商品購買 | O62: ○ | P62: ○ | Q62: ○ | AC62: WEB受注 | AD62: WEB受注 | AE62: WEB受注 | AF62: - | AG62: 受注 | AH62: - | AI62: 諸口品目 | AM62: NULL | AN62: 受注 | AO62: NULL | AP62: 受注 | AQ62: ×：仕様が取得できない | AR62: 〇：受注明細より取得 | AS62: - | AT62: 発注書 | AU62: 〇 | AW62: V7.0 画面制御の追加
A63: 36 | B63: 37 | C63: 30 | D63: 購買品 | E63: 62 | F63: その他 | G63: 1 | H63: 商品 | I63: 162 | J63: 商品その他 | K63: 購買 | L63: 品目マスタ | M63: CPで取り扱いが無い（諸口品目） | N63: 商品購買 | O63: ○ | P63: ○ | Q63: ○ | AC63: WEB受注 | AD63: WEB受注 | AE63: WEB受注 | AF63: - | AG63: MRP | AH63: MRP | AI63: 諸口品目 | AM63: NULL | AN63: NULL | AO63: NULL | AP63: 発注予定 | AQ63: ×：仕様が取得できない | AR63: ×：諸口品のため購買単価マスタがない | AS63: - | AT63: 発注書 | AU63: 〇 | AW63: V7.0 画面制御の追加
C64: 30 | D64: 購買品 | E64: 62 | F64: その他 | G64: 1 | H64: 商品 | I64: 162 | J64: 商品その他 | K64: 購買 | L64: 品目マスタ | M64: CPで取り扱いが無い（諸口品目） | N64: 商品購買 | O64: ○ | P64: ○ | Q64: ○ | AC64: WEB受注 | AD64: WEB受注 | AE64: WEB受注 | AF64: - | AG64: 受注 | AH64: - | AI64: 諸口品目 | AM64: NULL | AN64: 受注 | AO64: NULL | AP64: 受注 | AQ64: ×：仕様が取得できない | AR64: 〇：受注明細より取得 | AS64: - | AT64: 発注書 | AU64: 〇 | AW64: V7.0 画面制御の追加
A65: 37 | B65: 38 | C65: 20 | D65: シート製品 | E65: 11 | F65: シート | G65: 2 | H65: 製品 | I65: 211 | J65: シート | K65: 内製 | L65: WEB受注 | M65: CPで取り扱いがある（品目登録済） | N65: シート受注 | O65: ○ | P65: ○ | Q65: ○ | S65: △ | T65: ○ | U65: ○ | V65: ○ | AC65: - | AD65: - | AE65: - | AF65: - | AG65: MRP | AH65: MRP | AI65: 製品コード(11桁) | AJ65: 連番4桁 | AM65: - | AN65: - | AO65: - | AP65: - | AQ65: 〇 | AR65: - | AS65: - | AT65: - | AU65: 〇 | AW65: V7.0 画面制御の追加
C66: 20 | D66: シート製品 | E66: 11 | F66: シート | G66: 2 | H66: 製品 | I66: 211 | J66: シート | K66: 内製 | L66: WEB受注 | M66: CPで取り扱いがある（品目登録済） | N66: シート受注 | O66: ○ | P66: ○ | Q66: ○ | S66: △ | T66: ○ | U66: ○ | V66: ○ | AC66: - | AD66: - | AE66: - | AF66: - | AG66: 発注点 | AH66: MRP | AI66: 製品コード(11桁) | AJ66: 連番4桁 | AM66: - | AN66: - | AO66: - | AP66: - | AQ66: 〇 | AR66: - | AS66: - | AT66: - | AU66: 〇 | AW66: V7.0 画面制御の追加
C67: 20 | D67: シート製品 | E67: 11 | F67: シート | G67: 2 | H67: 製品 | I67: 211 | J67: シート | K67: 内製 | L67: WEB受注 | M67: CPで取り扱いがある（品目登録済） | N67: シート受注 | O67: ○ | P67: ○ | Q67: ○ | S67: △ | T67: ○ | U67: ○ | V67: ○ | AC67: - | AD67: - | AE67: - | AF67: - | AG67: 受注 | AH67: MRP | AI67: 製品コード(11桁) | AJ67: 連番4桁 | AM67: - | AN67: - | AO67: - | AP67: - | AQ67: 〇 | AR67: - | AS67: - | AT67: - | AU67: 〇 | AW67: V7.0 画面制御の追加
A68: 38 | B68: 39 | C68: 20 | D68: シート製品 | E68: 11 | F68: シート | G68: 2 | H68: 製品 | I68: 211 | J68: シート | K68: 外注 | L68: WEB受注 | M68: CPで取り扱いがある（品目登録済） | N68: シート受注 | O68: ○ | P68: ○ | Q68: ○ | S68: △ | T68: ○ | AC68: WEB受注 | AD68: WEB受注 | AE68: WEB受注 | AF68: - | AG68: MRP | AH68: MRP | AI68: 製品コード(11桁) | AJ68: 連番4桁 | AM68: NULL | AN68: 加工単価マスタ | AO68: NULL | AP68: 発注予定 | AQ68: 〇 | AR68: 〇：加工単価より取得 | AS68: 〇 | AT68: 加工発注書 | AU68: 〇 | AW68: V7.0 画面制御の追加
C69: 20 | D69: シート製品 | E69: 11 | F69: シート | G69: 2 | H69: 製品 | I69: 211 | J69: シート | K69: 外注 | L69: WEB受注 | M69: CPで取り扱いがある（品目登録済） | N69: シート受注 | O69: ○ | P69: ○ | Q69: ○ | S69: △ | T69: ○ | AC69: WEB受注 | AD69: WEB受注 | AE69: WEB受注 | AF69: - | AG69: 受注 | AH69: - | AI69: 製品コード(11桁) | AJ69: 連番4桁 | AM69: NULL | AN69: 受注 | AO69: NULL | AP69: 受注 | AQ69: 〇 | AR69: 〇：受注明細より取得 | AS69: 〇 | AT69: 加工発注書 | AU69: 〇 | AW69: V7.0 画面制御の追加
A70: 39 | B70: 40 | C70: 20 | D70: シート製品 | E70: 11 | F70: シート | G70: 2 | H70: 製品 | I70: 211 | J70: シート | K70: WG間転送 | L70: WEB受注 | M70: CPで取り扱いがある（品目登録済） | N70: シート受注 | O70: ○ | P70: ○ | Q70: ○ | S70: △ | T70: ○ | U70: ○ | V70: ○ | AC70: - | AD70: - | AE70: - | AF70: - | AG70: MRP | AH70: MRP | AI70: 製品コード(11桁) | AJ70: 連番4桁 | AM70: - | AN70: - | AO70: - | AP70: - | AQ70: - | AR70: - | AS70: - | AT70: - | AU70: 〇 | AW70: V7.0 画面制御の追加
A71: 40 | B71: 41 | C71: 10 | D71: 加工製品 | E71: 12 | F71: 加工 | G71: 2 | H71: 製品 | I71: 212 | J71: 加工 | K71: 内製 | L71: 製品マスタ | M71: CPで取り扱いがある（品目登録済） | N71: 加工品受注 | O71: ○ | P71: ○ | Q71: ○ | S71: △ | T71: ○ | U71: ○ | V71: ○ | W71: ○ | AC71: - | AD71: - | AE71: - | AF71: - | AG71: MRP | AH71: MRP | AI71: 製品コード(11桁) | AJ71: 連番4桁 | AM71: - | AN71: - | AO71: - | AP71: - | AQ71: 〇 | AR71: - | AS71: - | AT71: - | AU71: 〇 | AW71: V7.0 画面制御の追加
C72: 10 | D72: 加工製品 | E72: 12 | F72: 加工 | G72: 2 | H72: 製品 | I72: 212 | J72: 加工 | K72: 内製 | L72: 製品マスタ | M72: CPで取り扱いがある（品目登録済） | N72: 加工品受注 | O72: ○ | P72: ○ | Q72: ○ | S72: △ | T72: ○ | U72: ○ | V72: ○ | W72: ○ | AC72: - | AD72: - | AE72: - | AF72: - | AG72: 発注点 | AH72: MRP | AI72: 製品コード(11桁) | AJ72: 連番4桁 | AM72: - | AN72: - | AO72: - | AP72: - | AQ72: 〇 | AR72: - | AS72: - | AT72: - | AU72: 〇 | AW72: V7.0 画面制御の追加
C73: 10 | D73: 加工製品 | E73: 12 | F73: 加工 | G73: 2 | H73: 製品 | I73: 212 | J73: 加工 | K73: 内製 | L73: 製品マスタ | M73: CPで取り扱いがある（品目登録済） | N73: 加工品受注 | O73: ○ | P73: ○ | Q73: ○ | S73: △ | T73: ○ | U73: ○ | V73: ○ | W73: ○ | AC73: - | AD73: - | AE73: - | AF73: - | AG73: 受注 | AH73: MRP | AI73: 製品コード(11桁) | AJ73: 連番4桁 | AM73: - | AN73: - | AO73: - | AP73: - | AQ73: 〇 | AR73: - | AS73: - | AT73: - | AU73: 〇 | AW73: V7.0 画面制御の追加
A74: 41 | B74: 42 | C74: 10 | D74: 加工製品 | E74: 12 | F74: 加工 | G74: 2 | H74: 製品 | I74: 212 | J74: 加工 | K74: 外注 | L74: 製品マスタ | M74: CPで取り扱いがある（品目登録済） | N74: 加工品受注 | O74: ○ | P74: ○ | Q74: ○ | S74: △ | T74: ○ | W74: ○ | X74: △ | AC74: 製品マスタ→WEB受注 | AD74: 製品マスタ→WEB受注 | AE74: 加工単価→WEB受注 | AF74: - | AG74: MRP | AH74: MRP | AI74: 製品コード(11桁) | AJ74: 連番4桁 | AM74: NULL | AN74: 加工単価マスタ | AO74: NULL | AP74: 発注予定 | AQ74: 〇 | AR74: 〇：加工単価より取得 | AS74: 〇 | AT74: 加工発注書 | AU74: 〇 | AW74: V7.0 画面制御の追加
C75: 10 | D75: 加工製品 | E75: 12 | F75: 加工 | G75: 2 | H75: 製品 | I75: 212 | J75: 加工 | K75: 外注 | L75: 製品マスタ | M75: CPで取り扱いがある（品目登録済） | N75: 加工品受注 | O75: ○ | P75: ○ | Q75: ○ | S75: △ | T75: ○ | W75: ○ | X75: △ | AC75: 製品マスタ→WEB受注 | AD75: 製品マスタ→WEB受注 | AE75: 加工単価→WEB受注 | AF75: - | AG75: 受注 | AH75: - | AI75: 製品コード(11桁) | AJ75: 連番4桁 | AM75: NULL | AN75: 受注 | AO75: NULL | AP75: 受注 | AQ75: 〇 | AR75: 〇：受注明細より取得 | AS75: 〇 | AT75: 加工発注書 | AU75: 〇 | AW75: V7.0 画面制御の追加
A76: 42 | B76: 43 | C76: 10 | D76: 加工製品 | E76: 12 | F76: 加工 | G76: 2 | H76: 製品 | I76: 212 | J76: 加工 | K76: WG間転送 | L76: 製品マスタ | M76: CPで取り扱いがある（品目登録済） | N76: 加工品受注 | O76: ○ | P76: ○ | Q76: ○ | S76: △ | T76: ○ | U76: ○ | V76: ○ | W76: ○ | AC76: - | AD76: - | AE76: - | AF76: - | AG76: MRP | AH76: MRP | AI76: 製品コード(11桁) | AJ76: 連番4桁 | AM76: - | AN76: - | AO76: - | AP76: - | AQ76: - | AR76: - | AS76: - | AT76: - | AU76: 〇 | AW76: V7.0 画面制御の追加
A77: 43 | B77: 44 | C77: 10 | D77: 加工製品 | E77: 13 | F77: Ｇプリント | G77: 2 | H77: 製品 | I77: 213 | J77: Ｇプリント | K77: 内製 | L77: 製品マスタ | M77: CPで取り扱いがある（品目登録済） | N77: 加工品受注 | O77: ○ | P77: ○ | Q77: ○ | S77: △ | T77: ○ | U77: ○ | V77: ○ | W77: ○ | AC77: - | AD77: - | AE77: - | AF77: - | AG77: MRP | AH77: MRP | AI77: 製品コード(11桁) | AJ77: 連番4桁 | AM77: - | AN77: - | AO77: - | AP77: - | AQ77: 〇 | AR77: - | AS77: - | AT77: - | AU77: 〇 | AW77: V7.0 画面制御の追加
C78: 10 | D78: 加工製品 | E78: 13 | F78: Ｇプリント | G78: 2 | H78: 製品 | I78: 213 | J78: Ｇプリント | K78: 内製 | L78: 製品マスタ | M78: CPで取り扱いがある（品目登録済） | N78: 加工品受注 | O78: ○ | P78: ○ | Q78: ○ | S78: △ | T78: ○ | U78: ○ | V78: ○ | W78: ○ | AC78: - | AD78: - | AE78: - | AF78: - | AG78: 発注点 | AH78: MRP | AI78: 製品コード(11桁) | AJ78: 連番4桁 | AM78: - | AN78: - | AO78: - | AP78: - | AQ78: 〇 | AR78: - | AS78: - | AT78: - | AU78: 〇 | AW78: V7.0 画面制御の追加
C79: 10 | D79: 加工製品 | E79: 13 | F79: Ｇプリント | G79: 2 | H79: 製品 | I79: 213 | J79: Ｇプリント | K79: 内製 | L79: 製品マスタ | M79: CPで取り扱いがある（品目登録済） | N79: 加工品受注 | O79: ○ | P79: ○ | Q79: ○ | S79: △ | T79: ○ | U79: ○ | V79: ○ | W79: ○ | AC79: - | AD79: - | AE79: - | AF79: - | AG79: 受注 | AH79: MRP | AI79: 製品コード(11桁) | AJ79: 連番4桁 | AM79: - | AN79: - | AO79: - | AP79: - | AQ79: 〇 | AR79: - | AS79: - | AT79: - | AU79: 〇 | AW79: V7.0 画面制御の追加
A80: 44 | B80: 45 | C80: 10 | D80: 加工製品 | E80: 13 | F80: Ｇプリント | G80: 2 | H80: 製品 | I80: 213 | J80: Ｇプリント | K80: 外注 | L80: 製品マスタ | M80: CPで取り扱いがある（品目登録済） | N80: 加工品受注 | O80: ○ | P80: ○ | Q80: ○ | S80: △ | T80: ○ | W80: ○ | X80: △ | AC80: 製品マスタ→WEB受注 | AD80: 製品マスタ→WEB受注 | AE80: 加工単価→WEB受注 | AF80: - | AG80: MRP | AH80: MRP | AI80: 製品コード(11桁) | AJ80: 連番4桁 | AM80: NULL | AN80: 加工単価マスタ | AO80: NULL | AP80: 発注予定 | AQ80: 〇 | AR80: 〇：加工単価より取得 | AS80: 〇 | AT80: 加工発注書 | AU80: 〇 | AW80: V7.0 画面制御の追加
C81: 10 | D81: 加工製品 | E81: 13 | F81: Ｇプリント | G81: 2 | H81: 製品 | I81: 213 | J81: Ｇプリント | K81: 外注 | L81: 製品マスタ | M81: CPで取り扱いがある（品目登録済） | N81: 加工品受注 | O81: ○ | P81: ○ | Q81: ○ | S81: △ | T81: ○ | W81: ○ | X81: △ | AC81: 製品マスタ→WEB受注 | AD81: 製品マスタ→WEB受注 | AE81: 加工単価→WEB受注 | AF81: - | AG81: 受注 | AH81: - | AI81: 製品コード(11桁) | AJ81: 連番4桁 | AM81: NULL | AN81: 受注 | AO81: NULL | AP81: 受注 | AQ81: 〇 | AR81: 〇：受注明細より取得 | AS81: 〇 | AT81: 加工発注書 | AU81: 〇 | AW81: V7.0 画面制御の追加
A82: 45 | B82: 46 | C82: 10 | D82: 加工製品 | E82: 13 | F82: Ｇプリント | G82: 2 | H82: 製品 | I82: 213 | J82: Ｇプリント | K82: WG間転送 | L82: 製品マスタ | M82: CPで取り扱いがある（品目登録済） | N82: 加工品受注 | O82: ○ | P82: ○ | Q82: ○ | S82: △ | T82: ○ | U82: ○ | V82: ○ | W82: ○ | AC82: - | AD82: - | AE82: - | AF82: - | AG82: MRP | AH82: MRP | AI82: 製品コード(11桁) | AJ82: 連番4桁 | AM82: - | AN82: - | AO82: - | AP82: - | AQ82: - | AR82: - | AS82: - | AT82: - | AU82: 〇 | AW82: V7.0 画面制御の追加
A83: 46 | B83: 47 | C83: 10 | D83: 加工製品 | E83: 21 | F83: 巻ボール | G83: 2 | H83: 製品 | I83: 221 | J83: 巻ボール | K83: 内製 | L83: 製品マスタ | M83: CPで取り扱いがある（品目登録済） | N83: 加工品受注 | O83: ○ | P83: ○ | Q83: ○ | S83: △ | T83: ○ | U83: ○ | V83: ○ | W83: ○ | AC83: - | AD83: - | AE83: - | AF83: - | AG83: MRP | AH83: MRP | AI83: 製品コード(11桁) | AJ83: 連番4桁 | AM83: - | AN83: - | AO83: - | AP83: - | AQ83: 〇 | AR83: - | AS83: - | AT83: - | AU83: 〇 | AW83: V7.0 画面制御の追加
C84: 10 | D84: 加工製品 | E84: 21 | F84: 巻ボール | G84: 2 | H84: 製品 | I84: 221 | J84: 巻ボール | K84: 内製 | L84: 製品マスタ | M84: CPで取り扱いがある（品目登録済） | N84: 加工品受注 | O84: ○ | P84: ○ | Q84: ○ | S84: △ | T84: ○ | U84: ○ | V84: ○ | W84: ○ | AC84: - | AD84: - | AE84: - | AF84: - | AG84: 発注点 | AH84: MRP | AI84: 製品コード(11桁) | AJ84: 連番4桁 | AM84: - | AN84: - | AO84: - | AP84: - | AQ84: 〇 | AR84: - | AS84: - | AT84: - | AU84: 〇 | AW84: V7.0 画面制御の追加
C85: 10 | D85: 加工製品 | E85: 21 | F85: 巻ボール | G85: 2 | H85: 製品 | I85: 221 | J85: 巻ボール | K85: 内製 | L85: 製品マスタ | M85: CPで取り扱いがある（品目登録済） | N85: 加工品受注 | O85: ○ | P85: ○ | Q85: ○ | S85: △ | T85: ○ | U85: ○ | V85: ○ | W85: ○ | AC85: - | AD85: - | AE85: - | AF85: - | AG85: 受注 | AH85: MRP | AI85: 製品コード(11桁) | AJ85: 連番4桁 | AM85: - | AN85: - | AO85: - | AP85: - | AQ85: 〇 | AR85: - | AS85: - | AT85: - | AU85: 〇 | AW85: V7.0 画面制御の追加
A86: 47 | B86: 48 | C86: 10 | D86: 加工製品 | E86: 21 | F86: 巻ボール | G86: 2 | H86: 製品 | I86: 221 | J86: 巻ボール | K86: 外注 | L86: 製品マスタ | M86: CPで取り扱いがある（品目登録済） | N86: 加工品受注 | O86: ○ | P86: ○ | Q86: ○ | S86: △ | T86: ○ | W86: ○ | X86: △ | AC86: 製品マスタ→WEB受注 | AD86: 製品マスタ→WEB受注 | AE86: 加工単価→WEB受注 | AF86: WEB受注 | AG86: MRP | AH86: MRP | AI86: 製品コード(11桁) | AJ86: 連番4桁 | AM86: NULL | AN86: 加工単価マスタ | AO86: NULL | AP86: 発注予定 | AQ86: 〇 | AR86: 〇：加工単価より取得 | AS86: 〇 | AT86: 加工発注書 | AU86: 〇 | AW86: V7.0 画面制御の追加
C87: 10 | D87: 加工製品 | E87: 21 | F87: 巻ボール | G87: 2 | H87: 製品 | I87: 221 | J87: 巻ボール | K87: 外注 | L87: 製品マスタ | M87: CPで取り扱いがある（品目登録済） | N87: 加工品受注 | O87: ○ | P87: ○ | Q87: ○ | S87: △ | T87: ○ | W87: ○ | X87: △ | AC87: 製品マスタ→WEB受注 | AD87: 製品マスタ→WEB受注 | AE87: 加工単価→WEB受注 | AF87: WEB受注 | AG87: 受注 | AH87: - | AI87: 製品コード(11桁) | AJ87: 連番4桁 | AM87: NULL | AN87: 受注 | AO87: NULL | AP87: 受注 | AQ87: 〇 | AR87: 〇：受注明細より取得 | AS87: 〇 | AT87: 加工発注書 | AU87: 〇 | AW87: V7.0 画面制御の追加
A88: 48 | B88: 49 | C88: 10 | D88: 加工製品 | E88: 21 | F88: 巻ボール | G88: 2 | H88: 製品 | I88: 221 | J88: 巻ボール | K88: WG間転送 | L88: 製品マスタ | M88: CPで取り扱いがある（品目登録済） | N88: 加工品受注 | O88: ○ | P88: ○ | Q88: ○ | S88: △ | T88: ○ | U88: ○ | V88: ○ | W88: ○ | AC88: - | AD88: - | AE88: - | AF88: - | AG88: MRP | AH88: MRP | AI88: 製品コード(11桁) | AJ88: 連番4桁 | AM88: - | AN88: - | AO88: - | AP88: - | AQ88: - | AR88: - | AS88: - | AT88: - | AU88: 〇 | AW88: V7.0 画面制御の追加
A89: 49 | B89: 50 | C89: 20 | D89: シート製品 | E89: 22 | F89: 片面シート | G89: 2 | H89: 製品 | I89: 222 | J89: 片面シート | K89: 内製 | L89: WEB受注 | M89: CPで取り扱いがある（品目登録済） | N89: シート受注 | O89: ○ | P89: ○ | Q89: ○ | S89: △ | T89: ○ | U89: ○ | V89: ○ | AC89: - | AD89: - | AE89: - | AF89: - | AG89: MRP | AH89: MRP | AI89: 製品コード(11桁) | AJ89: 連番4桁 | AM89: - | AN89: - | AO89: - | AP89: - | AQ89: 〇 | AR89: - | AS89: - | AT89: - | AU89: 〇 | AW89: V7.0 画面制御の追加
C90: 20 | D90: シート製品 | E90: 22 | F90: 片面シート | G90: 2 | H90: 製品 | I90: 222 | J90: 片面シート | K90: 内製 | L90: WEB受注 | M90: CPで取り扱いがある（品目登録済） | N90: シート受注 | O90: ○ | P90: ○ | Q90: ○ | S90: △ | T90: ○ | U90: ○ | V90: ○ | AC90: - | AD90: - | AE90: - | AF90: - | AG90: 発注点 | AH90: MRP | AI90: 製品コード(11桁) | AJ90: 連番4桁 | AM90: - | AN90: - | AO90: - | AP90: - | AQ90: 〇 | AR90: - | AS90: - | AT90: - | AU90: 〇 | AW90: V7.0 画面制御の追加
C91: 20 | D91: シート製品 | E91: 22 | F91: 片面シート | G91: 2 | H91: 製品 | I91: 222 | J91: 片面シート | K91: 内製 | L91: WEB受注 | M91: CPで取り扱いがある（品目登録済） | N91: シート受注 | O91: ○ | P91: ○ | Q91: ○ | S91: △ | T91: ○ | U91: ○ | V91: ○ | AC91: - | AD91: - | AE91: - | AF91: - | AG91: 受注 | AH91: MRP | AI91: 製品コード(11桁) | AJ91: 連番4桁 | AM91: - | AN91: - | AO91: - | AP91: - | AQ91: 〇 | AR91: - | AS91: - | AT91: - | AU91: 〇 | AW91: V7.0 画面制御の追加
A92: 50 | B92: 51 | C92: 20 | D92: シート製品 | E92: 22 | F92: 片面シート | G92: 2 | H92: 製品 | I92: 222 | J92: 片面シート | K92: 外注 | L92: WEB受注 | M92: CPで取り扱いがある（品目登録済） | N92: シート受注 | O92: ○ | P92: ○ | Q92: ○ | S92: △ | T92: ○ | AC92: WEB受注 | AD92: WEB受注 | AE92: WEB受注 | AF92: - | AG92: MRP | AH92: MRP | AI92: 製品コード(11桁) | AJ92: 連番4桁 | AM92: NULL | AN92: 加工単価マスタ | AO92: NULL | AP92: 発注予定 | AQ92: 〇 | AR92: 〇：加工単価より取得 | AS92: 〇 | AT92: 加工発注書 | AU92: 〇 | AW92: V7.0 画面制御の追加
B93: 51 | C93: 20 | D93: シート製品 | E93: 22 | F93: 片面シート | G93: 2 | H93: 製品 | I93: 222 | J93: 片面シート | K93: 外注 | L93: WEB受注 | M93: CPで取り扱いがある（品目登録済） | N93: シート受注 | O93: ○ | P93: ○ | Q93: ○ | S93: △ | T93: ○ | AC93: WEB受注 | AD93: WEB受注 | AE93: WEB受注 | AF93: - | AG93: 受注 | AH93: - | AI93: 製品コード(11桁) | AJ93: 連番4桁 | AM93: NULL | AN93: 受注 | AO93: NULL | AP93: 受注 | AQ93: 〇 | AR93: 〇：受注明細より取得 | AS93: 〇 | AT93: 加工発注書 | AU93: 〇 | AW93: V7.0 画面制御の追加
A94: 51 | B94: 52 | C94: 20 | D94: シート製品 | E94: 22 | F94: 片面シート | G94: 2 | H94: 製品 | I94: 222 | J94: 片面シート | K94: WG間転送 | L94: WEB受注 | M94: CPで取り扱いがある（品目登録済） | N94: シート受注 | O94: ○ | P94: ○ | Q94: ○ | S94: △ | T94: ○ | U94: ○ | V94: ○ | AC94: - | AD94: - | AE94: - | AF94: - | AG94: MRP | AH94: MRP | AI94: 製品コード(11桁) | AJ94: 連番4桁 | AM94: - | AN94: - | AO94: - | AP94: - | AQ94: - | AR94: - | AS94: - | AT94: - | AU94: 〇 | AW94: V7.0 画面制御の追加
A95: 52 | B95: 53 | C95: 10 | D95: 加工製品 | E95: 23 | F95: 片面加工 | G95: 2 | H95: 製品 | I95: 223 | J95: 片面加工 | K95: 内製 | L95: 製品マスタ | M95: CPで取り扱いがある（品目登録済） | N95: 加工品受注 | O95: ○ | P95: ○ | Q95: ○ | S95: △ | T95: ○ | U95: ○ | V95: ○ | W95: ○ | AC95: - | AD95: - | AE95: - | AF95: - | AG95: MRP | AH95: MRP | AI95: 製品コード(11桁) | AJ95: 連番4桁 | AM95: - | AN95: - | AO95: - | AP95: - | AQ95: 〇 | AR95: - | AS95: - | AT95: - | AU95: 〇 | AW95: V7.0 画面制御の追加
C96: 10 | D96: 加工製品 | E96: 23 | F96: 片面加工 | G96: 2 | H96: 製品 | I96: 223 | J96: 片面加工 | K96: 内製 | L96: 製品マスタ | M96: CPで取り扱いがある（品目登録済） | N96: 加工品受注 | O96: ○ | P96: ○ | Q96: ○ | S96: △ | T96: ○ | U96: ○ | V96: ○ | W96: ○ | AC96: - | AD96: - | AE96: - | AF96: - | AG96: 発注点 | AH96: MRP | AI96: 製品コード(11桁) | AJ96: 連番4桁 | AM96: - | AN96: - | AO96: - | AP96: - | AQ96: 〇 | AR96: - | AS96: - | AT96: - | AU96: 〇 | AW96: V7.0 画面制御の追加
C97: 10 | D97: 加工製品 | E97: 23 | F97: 片面加工 | G97: 2 | H97: 製品 | I97: 223 | J97: 片面加工 | K97: 内製 | L97: 製品マスタ | M97: CPで取り扱いがある（品目登録済） | N97: 加工品受注 | O97: ○ | P97: ○ | Q97: ○ | S97: △ | T97: ○ | U97: ○ | V97: ○ | W97: ○ | AC97: - | AD97: - | AE97: - | AF97: - | AG97: 受注 | AH97: MRP | AI97: 製品コード(11桁) | AJ97: 連番4桁 | AM97: - | AN97: - | AO97: - | AP97: - | AQ97: 〇 | AR97: - | AS97: - | AT97: - | AU97: 〇 | AW97: V7.0 画面制御の追加
A98: 53 | B98: 54 | C98: 10 | D98: 加工製品 | E98: 23 | F98: 片面加工 | G98: 2 | H98: 製品 | I98: 223 | J98: 片面加工 | K98: 外注 | L98: 製品マスタ | M98: CPで取り扱いがある（品目登録済） | N98: 加工品受注 | O98: ○ | P98: ○ | Q98: ○ | S98: △ | T98: ○ | W98: ○ | X98: △ | AC98: 製品マスタ→WEB受注 | AD98: 製品マスタ→WEB受注 | AE98: 加工単価→WEB受注 | AF98: - | AG98: MRP | AH98: MRP | AI98: 製品コード(11桁) | AJ98: 連番4桁 | AM98: NULL | AN98: 加工単価マスタ | AO98: NULL | AP98: 発注予定 | AQ98: 〇 | AR98: 〇：加工単価より取得 | AS98: 〇 | AT98: 加工発注書 | AU98: 〇 | AW98: V7.0 画面制御の追加
C99: 10 | D99: 加工製品 | E99: 23 | F99: 片面加工 | G99: 2 | H99: 製品 | I99: 223 | J99: 片面加工 | K99: 外注 | L99: 製品マスタ | M99: CPで取り扱いがある（品目登録済） | N99: 加工品受注 | O99: ○ | P99: ○ | Q99: ○ | S99: △ | T99: ○ | W99: ○ | X99: △ | AC99: 製品マスタ→WEB受注 | AD99: 製品マスタ→WEB受注 | AE99: 加工単価→WEB受注 | AF99: - | AG99: 受注 | AH99: - | AI99: 製品コード(11桁) | AJ99: 連番4桁 | AM99: NULL | AN99: 受注 | AO99: NULL | AP99: 受注 | AQ99: 〇 | AR99: 〇：受注明細より取得 | AS99: 〇 | AT99: 加工発注書 | AU99: 〇 | AW99: V7.0 画面制御の追加
A100: 54 | B100: 55 | C100: 10 | D100: 加工製品 | E100: 23 | F100: 片面加工 | G100: 2 | H100: 製品 | I100: 223 | J100: 片面加工 | K100: WG間転送 | L100: 製品マスタ | M100: CPで取り扱いがある（品目登録済） | N100: 加工品受注 | O100: ○ | P100: ○ | Q100: ○ | S100: △ | T100: ○ | U100: ○ | V100: ○ | W100: ○ | AC100: - | AD100: - | AE100: - | AF100: - | AG100: MRP | AH100: MRP | AI100: 製品コード(11桁) | AJ100: 連番4桁 | AM100: - | AN100: - | AO100: - | AP100: - | AQ100: - | AR100: - | AS100: - | AT100: - | AU100: 〇 | AW100: V7.0 画面制御の追加
...
