Workbook
Name Rev.: [2]表紙!$U$22
Name Rev.: 表紙!$U$22
Name Revision: #REF!
Name Ver.: #REF!
Name Ver.: 表紙!$AE$26
Name Version: #REF!
Name Version: #REF!
Name ご確認者: #REF!
Name ご確認者: 表紙!$AG$40
Name ご確認日: #REF!
Name ご確認日: 表紙!$AG$42
Name サブシステム名: #REF!
Name サブシステム名: 表紙!$U$28
Name システム名: #REF!
Name システム名: 表紙!$U$26
Name プロジェクト名: #REF!
Name プロジェクト名: 表紙!$U$18
Name 開発区分: #REF!
Name 開発区分: 表紙!$U$36
Name 機能ＩＤ: #REF!
Name 機能ＩＤ: 表紙!$U$32
Name 機能区分: #REF!
Name 機能区分: 表紙!$U$34
Name 機能名称: #REF!
Name 機能名称: 表紙!$U$30
Name 顧客名: #REF!
Name 顧客名: 表紙!$U$16
Name 最終更新者: #REF!
Name 最終更新者: 表紙!$AB$40
Name 最終更新日: #REF!
Name 最終更新日: 表紙!$AB$42
Name 作成者: #REF!
Name 作成者: 表紙!$W$40
Name 作成日: #REF!
Name 作成日: 表紙!$W$42
Name 章: #REF!
Name 章: 表紙!$M$10
Name 発行日: #REF!
Name 文書番号: #REF!
Name 文書番号_カスタマイズ: '[3]表紙（カスタマイズ）'!$U$20
Name 文書名: #REF!
Name 文書名: 表紙!$M$10
Name 文書名: #REF!
Name 文書名_カスタマイズ: '[3]表紙（カスタマイズ）'!$M$10

Sheet 目次
A1: アドオン設計書作成ガイド
C3: ■アドオン設計と成果物について
D4: ・システム設計フェーズとソフトウェア設計フェーズでアドオンの処理仕様を定義する
D5: ・システム設計フェーズとソフトウェア設計フェーズの成果物がアドオン設計書であり、ソフトウェア製作フェーズのインプットとなる
C7: ■各設計フェーズ毎のアドオン設計書作成範囲
D8: ・システム設計フェーズ：他機能との関連を定義するとともに、画面や帳票、ファイル入出力を中心とした外部入出力の設計を行う
D9: ・ソフトウェア設計フェーズ：内部処理を中心とした設計を行う
U11: ◎ | W11: … | X11: システム設計フェーズで作成
U12: ○ | W12: … | X12: システム設計フェーズで基本仕様を定義して、ソフトウェア設計フェーズで詳細化する
U13: △ | W13: … | X13: 必要に応じて（例えば標準仕様から変更がない場合は不要）
U14: ‐ | W14: … | X14: 不要
W15: … | X15: ソフトウェア設計フェーズで作成
D17: 各設計書と作成対象シートのマトリックス | S17: ※カスタマイズ：標準機能に機能を追加する アドオン：新規で機能を開発する
D18: EXCELシート | N18: 画面設計書 | W18: バッチ設計書 | AF18: 帳票設計書 | AO18: ＢＩ設計書 | AT18: .Net設計書 | BB18: EXCELシート | BL18: WebDB設計書 | BR18: 帳票設計書 | BX18: 汎用申請設計書
N19: カスタマイズ | S19: アドオン | W19: カスタマイズ | AB19: アドオン | AF19: カスタマイズ | AK19: アドオン | AO19: アドオン | AT19: アドオン | BL19: アドオン | BR19: アドオン | BX19: アドオン
D20: 概要 | N20: ◎ | O20: ※1 | S20: ◎ | W20: ◎ | X20: ※1 | AB20: ◎ | AF20: ◎ | AG20: ※1 | AK20: ◎ | AO20: ◎ | AT20: ◎ | BB20: 機能概要 | BL20: ◎ | BR20: ◎ | BX20: ◎
D21: レイアウト | N21: ◎ | O21: ※2 | S21: ◎ | W21: ‐ | AB21: ‐ | AF21: ◎ | AG21: ※2 | AK21: ◎ | AO21: ◎ | AT21: ◎ | BB21: アプリケーションフロー | BL21: ◎ | BR21: ー | BX21: ◎
D22: 項目説明 | N22: △ | S22: ○ | W22: ‐ | AB22: ‐ | AF22: △ | AK22: ○ | AO22: ○ | AT22: ○ | BB22: データベース設定 | BL22: ◎ | BR22: ー | BX22: ◎
D23: 引数説明 | N23: ‐ | S23: ‐ | W23: △ | AB23: ◎ | AF23: ‐ | AK23: ‐ | AO23: ‐ | AT23: ◎ | BB23: フィールド設定 | BL23: ◎ | BR23: ー | BX23: ◎
D24: 処理概要 | N24: ◎ | S24: ◎ | W24: ◎ | AB24: ◎ | AF24: ◎ | AK24: ◎ | AO24: ◎ | AT24: ◎ | BB24: 一覧表示画面設定 | BL24: ◎ | BR24: ー | BX24: ◎
D25: 処理詳細 | BB25: 表示編集画面設定 | BL25: ◎ | BR25: ー | BX25: ◎
D26: 処理・サービス関連図 | N26: △ | S26: ◎ | W26: △ | AB26: ◎ | AF26: ‐ | AK26: ‐ | AO26: ‐ | AT26: ◎ | BB26: 明細画面設定 | BL26: △ | BN26: ※3 | BR26: ー | BX26: △ | BZ26: ※3
D27: 検索入出力仕様 | N27: △ | S27: ○ | W27: △ | AB27: ○ | AF27: ‐ | AK27: ‐ | AO27: ‐ | AT27: ○ | BB27: 集計表示設定 | BL27: △ | BN27: ※4 | BR27: ー | BX27: △ | BZ27: ※4
D28: 更新入出力仕様 | N28: △ | S28: ○ | W28: △ | AB28: ○ | AF28: ‐ | AK28: ‐ | AO28: ‐ | AT28: ○ | BB28: 絞り込み条件設定 | BL28: △ | BN28: ※5 | BR28: ー | BX28: △ | BZ28: ※5
D29: ファイル入出力仕様 | N29: △ | S29: △ | W29: ‐ | AB29: ‐ | AF29: ‐ | AK29: ‐ | AO29: ‐ | AT29: △ | BB29: その他設定 | BR29: ー
D30: 画面遷移 | N30: △ | S30: ◎ | W30: ‐ | AB30: ‐ | AF30: ‐ | AK30: ‐ | AO30: ‐ | AT30: ◎ | BB30: 帳票イメージ | BL30: ー | BR30: ◎ | BX30: ー
D31: メッセージ一覧 | N31: △ | S31: △ | W31: △ | AB31: △ | AF31: ‐ | AK31: ‐ | AO31: ‐ | AT31: △ | BB31: 項目設計 | BL31: ー | BR31: ◎ | BX31: ー
D32: 補足説明 | N32: △ | S32: △ | W32: △ | AB32: △ | AF32: △ | AK32: △ | AO32: △ | AT32: △ | BB32: 補足説明 | BL32: △ | BR32: △ | BX32: △
D33: サービス呼出編集仕様 | N33: - | S33: - | W33: - | AB33: - | AF33: - | AK33: - | AO33: - | AT33: - | BB33: 補足説明(詳細)
D35: ※1 | G35: 別シートでカスタマイズ内容を記載する | BB35: ※3 | BE35: 単票画面は記載しない
D36: ※2 | G36: 吹き出しでカスタマイズ内容を記載する | BB36: ※4 | BE36: 集計・グラフ機能を使用する場合に記載する
BB37: ※5 | BE37: 共通設定のみ記載する(個別設定は、記載しない)

Sheet 表紙
AW2: サブモジュール
AW3: MA_マスタ管理
AW4: MB_業務共通
AW5: MG_原価管理
AW6: MSBA_需給管理
M7: 基本設計 | AW7: MSBB_販売管理
AW8: MSBC_生産管理
AW9: MSBD_購買管理
M10: アドオン設計書 | AW10: MSBE_在庫物流管理
AW11: MSBF_品質管理
AW12: MSBG_債権管理
AW13: MSBH_債務管理
AW14: MSBI_締処理
AW15: MSUA_リスト・入力補助
M16: 顧客 | U16: 株式会社クラウン・パッケージ | AW16: PF_ESBアダプタ
M18: プロジェクト名 | U18: 基幹システム刷新PJ | AW18: 機能区分
AW19: 画面
M20: 文書番号 | AW20: 帳票
AW21: バッチ
M22: Ｒｅｖ． | U22: {=MAX(_xlfn.NUMBERVALUE(改訂!A7:E56))} -> 7 | AW22: マスタ
M24: 機密性区分 | U24: 取扱注意（Ｃ） | AW24: 開発区分
AW25: カスタマイズ
M26: システム名 | U26: mcframe7 | AC26: Ver. | AE26: 7.0.2 | AW26: アドオン
AW27: －
M28: サブモジュール | U28: MSBB_販売管理
M30: 機能名 | U30: =M50 -> Web受注入力
M32: 機能ID | U32: =G50 -> MSBBPA070
M34: 機能区分 | U34: 画面
M36: 開発区分 | U36: アドオン
W39: 作成 | AB39: 最終更新 | AG39: ご確認
W40: MDSOL | AB40: =改訂!AZ2 -> MDSOL 石田
W42: 44846 | AB42: =改訂!BJ2 -> 44965
A48: 文書番号 | G48: 画面ID | M48: 画面名 | V48: Version | AB48: Revision
A50: M7-US-1140 | G50: MSBBPA070 | M50: Web受注入力 | V50: 1.0.0 | AB50: r01.00
A53: 共通（元データ）
A54: Webシステム | K54: 文書名 | U54: モジュールID | Z54: MS | AE54: モジュール名 | AJ54: 見積管理 | AS54: 文書番号 | AZ54: Version | BF54: Rev.
K55: 画面説明書 | U55: ｻﾌﾞﾓｼﾞｭｰﾙID | Z55: MSBB | AE55: ｻﾌﾞﾓｼﾞｭｰﾙ名 | AJ55: Webシステム | AS55: M7-US-1140 | AZ55: 1.0.0 | BF55: r00.00
K56: 表紙 | U56: 表題 | Z56: MSBBPA070 | AE56: Web受注入力
A57: 共通（リンク用）
A58: =A54 -> Webシステム | K58: 文書名 | U58: モジュールID | Z58: =Z54 -> MS | AE58: モジュール名 | AJ58: =AJ54 -> 見積管理 | AS58: 文書番号 | AZ58: Version | BF58: Rev.
K59: =文書名 -> アドオン設計書 | U59: ｻﾌﾞﾓｼﾞｭｰﾙID | Z59: =Z55 -> MSBB | AE59: ｻﾌﾞﾓｼﾞｭｰﾙ名 | AJ59: =AJ55 -> Webシステム | AS59: =AS55 -> M7-US-1140 | AZ59: =AZ55 -> 1.0.0 | BF59: =BF55 -> r00.00
K60: =RIGHT(CELL("filename",$A$1),LEN(CELL("filename",$A$1))-FIND("]",CELL("filename",$A$1))) -> 表紙 | U60: 表題 | Z60: =Z56 -> MSBBPA070 | AE60: =AE56 -> Web受注入力
A62: 概要シート用
A63: =A58 -> Webシステム | O63: 文書名 | AC63: モジュールID | AJ63: =Z58 -> MS | AQ63: モジュール名 | AX63: =AJ58 -> 見積管理 | BL63: 文書番号 | BU63: Version | CB63: Rev.
O64: =K59 -> アドオン設計書 | AC64: サブモジュールID | AJ64: =Z59 -> MSBB | AQ64: サブモジュール名 | AX64: =AJ59 -> Webシステム | BL64: =AS59 -> M7-US-1140 | BU64: 7.0.2 | CB64: =改訂!BP2 -> 7
O65: =RIGHT(CELL("filename",$A$1),LEN(CELL("filename",$A$1))-FIND("]",CELL("filename",$A$1))) -> 表紙 | AC65: 表題 | AJ65: =Z60 -> MSBBPA070 | AQ65: =AE60 -> Web受注入力

Sheet 改訂
A1: 第7章 | K1: 改訂 | AU1: 作成者 | AZ1: MDSOL | BE1: 作成日 | BJ1: =表紙!W42 -> 44846 | BP1: Rev.
AU2: 修正者 | AZ2: =BM18 -> MDSOL 石田 | BE2: 改訂日 | BJ2: =MAX(改訂!BM7:BQ58) -> 44965 | BP2: {=MAX(_xlfn.NUMBERVALUE(改訂!A7:E56))} -> 7
A5: Rev. | F5: 改定内容 | BC5: 頁 | BM5: 変更日 変更者 | BR5: 確認日 確認者
A7: 1 | F7: 新規作成 | BM7: 44865
BM8: MDSOL
A9: 2 | F9: 仕様連絡書：RCS-1062に伴う下記改定を実施 案件NOをDBの項目は、案件NO(親)＋案件NO(子)＋案件NO(部材)に分割する ※画面項目は、1つとする | BC9: 項目説明、更新入出力仕様 | BM9: 44894 | BR9: 44895
BM10: MDSOL | BR10: MDSOL 奥本
A11: 2 | F11: 仕様連絡書：RCS-1062に伴う下記改定を実施 FSC製品区分に統合(FSC認証製品＝FSC製品区分) | BC11: レイアウト、項目説明、検索入出力仕様、更新入出力仕様、ファイル入出力仕様 | BM11: 44894 | BR11: 44895
BM12: MDSOL | BR12: MDSOL 奥本
A13: 2 | F13: 仕様連絡書：RCS-1062に伴う下記改定を実施 高品質→高管理、各画面から項目削除、DB項目としては残す | BC13: 更新入出力仕様 | BM13: 44896 | BR13: 44896
BM14: MDSOL | BR14: MDSOL 奥本
A15: 3 | F15: 仕様連絡書：RCS-1073に伴う下記改定を実施 購買品受注の時に、発注単価が必要 | BC15: レイアウト、項目説明、検索入出力仕様、更新入出力仕様 | BM15: 44909 | BR15: 44909
BM16: MDSOL 石田 | BR16: MDSOL 奥本
A17: 3 | F17: 仕様連絡書：RCS-1073に伴う下記改定を実施 過去受注をコピーした時に、セットしたくない項目がある | BC17: 処理概要 | BM17: 44909 | BR17: 44909
BM18: MDSOL 石田 | BR18: MDSOL 奥本
A19: 4 | F19: 仕様連絡書：RCS-1158に伴う下記改定を実施 WEB受注明細、mcf受注明細の関係を明記。 | BC19: 概要、補足説明資料 | BM19: 44937 | BR19: 44939
BM20: MDSOL 石田 | BR20: MDSOL 奥本
A21: 4 | F21: 仕様連絡書：RCS-1158に伴う下記改定を実施 預り売上数の項目追加と入力チェック | BC21: 処理概要、レイアウト、項目説明、処理概要、検索入出力仕様、更新入出力仕様、メッセージ一覧 | BM21: 44937 | BR21: 44939
BM22: MDSOL 石田 | BR22: MDSOL 奥本
A23: 4 | F23: 仕様連絡書：RCS-1158に伴う下記改定を実施 仕掛チェックの追加 | BC23: 処理概要、補足説明資料_仕掛チェック | BM23: 44937 | BR23: 44939
BM24: MDSOL 石田 | BR24: MDSOL 奥本
A25: 4 | F25: 仕様連絡書：RCS-1158に伴う下記改定を実施 行コピーの有効条件追加 | BC25: 処理概要 | BM25: 44937 | BR25: 44939
BM26: MDSOL 石田 | BR26: MDSOL 奥本
A27: 4 | F27: メッセージ一覧にメッセージを追加する。 | BC27: メッセージ一覧 | BM27: 44909
BM28: TBK徐
A29: 4 | F29: 処理詳細の追加 | BC29: 処理詳細 | BM29: 44909
BM30: TBK徐
A31: 4 | F31: メッセージ一覧の採番 | BC31: メッセージ一覧 | BM31: 44931
BM32: TBK徐
A33: 5 | F33: 仕様連絡書：RCS-1115に伴う下記改定を実施 項目説明に画面レイアウト項目の不足分を追加 | BC33: 項目説明 | BM33: 44959 | BR33: 44960
BM34: MDSOL 石田 | BR34: MDSOL 奥本
A35: 5 | F35: 仕様連絡書：RCS-1115に伴う下記改定を実施 処理概要とメッセージ一覧の紐づけ見直し | BC35: 処理概要 | BM35: 44959 | BR35: 44960
BM36: MDSOL 石田 | BR36: MDSOL 奥本
A37: 5 | F37: 仕様連絡書：RCS-1115に伴う下記改定を実施 処理・サービス関連図のテーブル名修正 | BC37: 処理・サービス関連図 検索入出力仕様 | BM37: 44959 | BR37: 44960
BM38: MDSOL 石田 | BR38: MDSOL 奥本
A39: 6 | F39: シ設計集中見直し（RCS-1229）:参照元_見積計算書ＮＯ 項目削除／項目見直し(見積計算書ＮＯ) | BC39: 更新入出力仕様 | BM39: 44964 | BR39: 44964
BM40: MDSOL野村 | BR40: MDSOL 奥本
A41: 6 | F41: シ設計集中見直し（RCS-1229）:製品CD桁数見直し(15桁に変更) | BC41: 項目説明 | BM41: 44964 | BR41: 44965
BM42: MDSOL野村 | BR42: MDSOL 奥本
A43: 7 | F43: シ設計集中見直し（RCS-1229）:受注画面表示制御の追加 | BC43: レイアウト、処理概要、 補足説明資料_受注画面制御、受発注パタン詳細 | BM43: 44965 | BR43: 44966
BM44: MDSOL石田 | BR44: MDSOL 奥本

Sheet 概要
A1: =表紙!A54 -> Webシステム | O1: 文書名 | AC1: モジュールID | AJ1: =表紙!AJ63 -> MS | AQ1: モジュール名 | AX1: =表紙!AX63 -> 見積管理 | BL1: 文書番号 | BU1: Version | CB1: Rev.
O2: =表紙!O64 -> アドオン設計書 | AC2: サブモジュールID | AJ2: =表紙!AJ64 -> MSBB | AQ2: サブモジュール名 | AX2: =表紙!AX64 -> Webシステム | BL2: =表紙!BL64 -> M7-US-1140 | BU2: =表紙!BU64 -> 7.0.2 | CB2: =表紙!CB64 -> 7
O3: =RIGHT(CELL("filename",$A$1),LEN(CELL("filename",$A$1))-FIND("]",CELL("filename",$A$1))) -> 概要 | AC3: 表題 | AJ3: =表紙!AJ65 -> MSBBPA070 | AQ3: =表紙!AQ65 -> Web受注入力
AO5: 概要
B7: 【業務要件】
C8: カスタマイズ | G8: 内容
C9: No.
C10: 4 | G10: 見積WEBシステムを構築する。
G11: 見積Webシステム：主要機能 ①見積(見積計算書)入力・発行②御見積書入力・発行③見積確定④受注入力⑤受注一覧(単価訂正)⑥製品マスタ⑦得意先マスタ⑧シート単価マスタ
C12: 126 | G12: 売上計算方法がmcframe7の数量＊単価ではなく数量＊単価＊寸法など異なっている。現行の売上計算方法をmcframe7で実現する。
G13: 既存単価とは別に単価項目を追加しユーザーはそこに単価を登録する。
G14: 売上計算方法の計算根拠項目を追加し売上計算を行い1数量辺りの単価をmcframe既存単価に自動設定して金額を合わせる。
C15: 146 | G15: 当初想定は、1画面で明細形式での画面構成を想定していたが、製品マスタと同等のテーブル構造を持ち、受注入力でも工程仕様画面を表示(仕様の変更可はシート受注のみ)するように変更する
B19: 【説明】
C20: 製品マスタ、過去受注より受注入力を行う。
B22: 【目的】
C23: ・受注を登録・訂正・参照する。
B25: 【オペレーション一覧】
C26: WEB受注の登録・更新処理を行う
C27: WEB受注の検索・照会処理を行う
B30: 【SQLID一覧】
C31: なし
B33: 【ソート順】
C34: なし
B36: 【データアクセスコントロール】
C37: 拠点による制御
C38: ※詳細は、【MSBBPA000】_共通設計書_アドオン(Webシステム共通仕様)にて定義
B40: 【自由記述】
C41: 前提条件として予備、サンプル、預かりは本体のWEB受注明細に含まれ独立したWEB受注明細としては持たない。mcframe受注明細では独立し本体の受注明細とは分割する。 | CJ41: REV4.0 WEB受注明細、mcf受注明細の関係を明記
C42: 詳細は「補足説明資料」シート参照。 | CJ42: REV4.0 WEB受注明細、mcf受注明細の関係を明記

Sheet 概要 (セッション用)
A1: =表紙!A54 -> Webシステム | O1: 文書名 | AC1: モジュールID | AJ1: =表紙!AJ63 -> MS | AQ1: モジュール名 | AX1: =表紙!AX63 -> 見積管理 | BL1: 文書番号 | BU1: Version | CB1: Rev.
O2: =表紙!O64 -> アドオン設計書 | AC2: サブモジュールID | AJ2: =表紙!AJ64 -> MSBB | AQ2: サブモジュール名 | AX2: =表紙!AX64 -> Webシステム | BL2: =表紙!BL64 -> M7-US-1140 | BU2: =表紙!BU64 -> 7.0.2 | CB2: =表紙!CB64 -> 7
O3: =RIGHT(CELL("filename",$A$1),LEN(CELL("filename",$A$1))-FIND("]",CELL("filename",$A$1))) -> 概要 (セッション用) | AC3: 表題 | AJ3: =表紙!AJ65 -> MSBBPA070 | AQ3: =表紙!AQ65 -> Web受注入力
AO5: 概要

Sheet WEBテーブル関連図
A1: =表紙!A54 -> Webシステム | O1: 文書名 | AC1: モジュールID | AJ1: =表紙!AJ63 -> MS | AQ1: モジュール名 | AX1: =表紙!AX63 -> 見積管理 | BL1: 文書番号 | BU1: Version | CB1: Rev.
O2: =表紙!O64 -> アドオン設計書 | AC2: サブモジュールID | AJ2: =表紙!AJ64 -> MSBB | AQ2: サブモジュール名 | AX2: =表紙!AX64 -> Webシステム | BL2: =表紙!BL64 -> M7-US-1140 | BU2: =表紙!BU64 -> 7.0.2 | CB2: =表紙!CB64 -> 7
O3: =RIGHT(CELL("filename",$A$1),LEN(CELL("filename",$A$1))-FIND("]",CELL("filename",$A$1))) -> WEBテーブル関連図 | AC3: 表題 | AJ3: =表紙!AJ65 -> MSBBPA070 | AQ3: =表紙!AQ65 -> Web受注入力
AO5: WEBテーブル関連図

Sheet レイアウト
A1: =表紙!A54 -> Webシステム | K1: 文書名 | U1: モジュールID | Z1: =表紙!$AJ$63 -> MS | AE1: モジュール名 | AJ1: =表紙!$AX$63 -> 見積管理 | AS1: 文書番号 | AZ1: Version | BF1: Rev.
K2: =表紙!O64 -> アドオン設計書 | U2: ｻﾌﾞﾓｼﾞｭｰﾙID | Z2: =表紙!$AJ$64 -> MSBB | AE2: ｻﾌﾞﾓｼﾞｭｰﾙ名 | AJ2: =表紙!$AX$64 -> Webシステム | AS2: =表紙!$BL$64 -> M7-US-1140 | AZ2: =表紙!$BU$64 -> 7.0.2 | BF2: =表紙!$CB$64 -> 7
K3: =RIGHT(CELL("filename",$A$1),LEN(CELL("filename",$A$1))-FIND("]",CELL("filename",$A$1))) -> レイアウト | U3: 表題 | Z3: =表紙!$AJ$65 -> MSBBPA070 | AE3: =表紙!$AQ$65 -> Web受注入力
A5: 画面イメージ
B7: ≫凡例
Q8: ・・・ | S8: ボタン
C9: 見積計算書№ | Q9: ・・・ | S9: 検索項目(検索画面表示選択)
C10: 品名 | Q10: ・・・ | S10: 入力項目
C11: 得意先 | Q11: ・・・ | S11: 表示項目(得意先名称、原紙名等)
C12: 操作種別 | I12: ●登録 | M12: ○訂正 | Q12: ・・・ | S12: 選択項目(一つのみ選択可能)
C13: 受注区分 | Q13: ・・・ | S13: 選択項目(一つのみ選択可能)
C14: 作業順 | I14: ☑AAA | M14: ☑BBB | Q14: ・・・ | S14: 選択項目(複数選択可能)
C23: TOP画面
BZ24: CP指摘 2022/10/02 落合 コピーの操作種別が必要か疑問。 登録で手配№を指定されたらコピーで良いように思うが？ | DJ24: MDSOL回答 石田 2022/10/27 コピーの操作種別をなくしました。 | EE24: 2022/10/29 落合 問題なし
D25: 操作種別 | J25: ●登録 | N25: ○訂正 | R25: ○削除 | V25: ○参照 | BZ25: CP指摘 2022/10/02 落合 手配№オートコンプリート。 得意先指定がある事を条件に過去3か月の受注を対象に検索をかける。 表示項目（品名１・２、段 構成名 シート寸法）2段表示が可能か確認願います。 | EG25: MDSOL回答 石田 2022/10/27 共通ロジック（【MSBBPACOM】_共通設計書_アドオン(Web共通ロジック)）_の方で記載致しました。 | FT25: 2022/10/29 落合 記載箇所が不明 | GG25: MDSOL回答 2022/10/31 手配NOの表示条件に追加しました。 2段表示は難しいとのことです。 | HI25: 2022/11/01 落合 問題なし
D26: 受注区分 | S26: 得意先 | AO26: 手配NO | BK26: ←「訂正」「削除」「参照」の時、初期フォーカス | CA26: 品名もしくはシート寸法でほぼ検索可能な想定
BZ27: CP指摘 2022/9/30 落合 製品区分（大）は第2画面へ移動。 代わりに得意先を製品区分（大）の位置に移動 | DQ27: MDSOL回答 石田 2022/10/27 対応しました | EF27: 2022/10/29 落合 問題なし
BZ28: 部材ごとに製品区分が変わる為
D29: 受注部門 | AD29: 受注日 | AO29: 受注区分 | BZ29: 製品区分の吹き出しに記載の画面遷移は、受注区分にて判断する
D30: 得意先 | AD30: 客先納期 | AO30: 数量 | BZ30: CP指摘 2022/10/02 落合 受注一覧照会を開いたときに、受注区分・得意先CD・受注日（当日から6か月の範囲）で | DQ30: MDSOL回答 石田 2022/10/27 共通ロジック（【MSBBPACOM】_共通設計書_アドオン(Web共通ロジック)）_の方で記載致しました。 | FE30: 2022/10/29 落合 記載箇所が不明 | FR30: MDSOL回答 2022/10/31 WEB受注一覧照会の設計書に追記しました。 | GN30: 2022/11/01 落合 問題なし
BZ31: CP指摘 2022/9/30 落合 得意先指定時、与信限度額超えていたらアラート「与信限度額を超えています。受注継続するか要確認！」 | DQ31: MDSOL回答 石田 2022/10/27 金額が未定のため、登録時では駄目でしょうか？登録時には与信チェックを入れています。取引先指定のタイミングの場合は既に与信限度額を超えている場合になります。 | FU31: 2022/10/29 落合 入力中の受注を除いて既に超えている場合です。 | GQ31: MDSOL回答 2022/10/31 石田 承知しました。処理概要に得意先指定時（TOP画面、基本画面）を記載致しました。 | HY31: 2022/11/01 落合 問題なし
D32: 注文書No | W32: 先方担当 | AO32: 宛名 | BC32: 様 | BZ32: CP指摘 2022/10/27 落合 出荷日時ですが、1時間刻みの時間指定＋昼積み＋夜積みになっていると思いますが、出荷予定の時間にセットすることで可能でしょうか？ | DQ32: MDSOL回答 石田 2022/10/28 可能です。昼積みと夜積みについては00：00：00でそれ以外は時間を設定します。 | EY32: 2022/10/29 落合 問題なし
D33: 運送会社 | W33: 出荷日時 | BZ33: CP指摘 2022/9/30 落合 得意先のオートコンプリート表示項目（管轄拠点・得意先CD・得意先名・住所１・２・電話番号） | DQ33: MDSOL回答 石田 2022/10/27 共通ロジック（【MSBBPACOM】_共通設計書_アドオン(Web共通ロジック)）_の方で記載致しました。 | FD33: 2022/11/01 落合 問題なし
D35: 売価区分 | BZ35: CP指摘 2022/9/30 落合 客納期が標準リードタイムを下回っているときアラート「納期まで製造必要日数を下回っています。要調整！」 | DQ35: MDSOL回答 石田 2022/10/27 処理概要に記載致しました。 | EJ35: 2022/10/29 落合 問題なし
BZ36: CP指摘 2022/9/30 落合 客納期・出荷日が非稼働日の時アラート「客納期が非稼働日です。」「出荷日が非稼働日です。」 | DQ36: MDSOL回答 石田 2022/10/27 処理概要に記載致しました。 | EJ36: 2022/10/29 落合 問題なし
D37: 受注明細
D38: 製品CD | J38: (件名:オートフィルタ) | AC38: ← ｾｯﾄ品目指定することで、以下の一覧に部材品目表示
D41: № | F41: 手配NO1 | I41: 手配NO2 | L41: 手配NO3 | O41: 製品CD/品目CD | T41: CP品名1 | Y41: CP品名2 | AB41: 単位 | AD41: 数量 | AG41: 特値 | AJ41: 個別単価 | AM41: ｾｯﾄ単価 | AP41: 客先納期 | AT41: 手配区分 | AW41: 納品先 | BA41: 納品先名 | BE41: 物流グループ | BH41: 預り売上 | BL41: 売上理由 | BP41: 受注№/受注明細№
E42: 1 | I42: 得意先CD | L42: 案件№ | T42: 味比べ3P箱 身 | AG42: □ | BI42: □
E43: 2 | I43: 得意先CD | L43: 案件№ | T43: 味比べ3P箱 蓋 | AG43: □ | BI43: □ | BZ43: CP指摘 2022/9/30 落合 受注明細単位の納期が必要。預かり売上する為に分割したときに、売上日を指定するため。 製造前に納期を分けた時に、製造予定が分割される懸念がある。 | DQ43: MDSOL回答 石田 2022/10/27 対応しました | EG43: 2022/11/01 落合 問題なし
E44: 3 | I44: 得意先CD | L44: 案件№ | T44: 味比べ3P箱 仕切り | AG44: □ | AT44: 仕入直送 | BI44: □ | DQ44: CP指摘 2022/10/29 落合 受注時に納期分割して登録した場合は、生産予定が分割される認識ですが合っていますか？ | FD44: MDSOL回答 2022/10/31 コピー行追加で納期を変更した場合は、手配NOが同一となるため、まとめ期間内ならまとまります。行追加の場合は分割されます。 | GV44: 2022/11/01 落合 問題なし
F46: ※メニュー「シート受注入力」を選択した場合は、第２画面からスタート
F47: ※メニュー「購買品受注入力」を選択した場合は、第２画面からスタート。 工程情報登録はなし。 入力項目の追加あり。
C53: 第２画面 | H53: ※部材の種類分、第２画面が連続して表示される
D54: 基本情報
D56: 納品先 | O56: 手配区分 | AA56: 預り売上 □ | AJ56: 出荷日時
D58: 売上WG | H58: 30 名古屋 | O58: 受注区分 | AC58: 製品区分 | AE58: 大 | AL58: 中 | AS58: 小 | BZ58: CP指摘 2022/10/27 落合 手配№２の表示は不要（得意先CDと同じため） 手配№３は見出しを「案件NO」にする | DH58: MDSOL回答 石田 2022/10/28 修正しました | DX58: 2022/10/29 落合 問題なし
D59: 手配NO | O59: 案件NO
D60: 得意先 | X60: 客先納期 | BZ60: CP指摘 2022/09/30 落合 購買品受注入力の時に、製品CD・版型№の入力が必要 | DA60: MDSOL回答 石田 2022/10/27 追加致しました | DR60: 2022/10/29 落合 問題なし
D61: 製品CD/品目CD | O61: 顧客品名1 | AI61: 顧客品名2 | CF61: 未入力時アラート表示 「未入力」
D62: 版型NO | O62: CP品名1 | AI62: CP品名2
D63: 顧客注文№ | O63: 顧客品番
D64: FSC製品区分 | O64: 食品安全 | BZ64: Rev2.0 項目統合(FSC認証製品＝FSC製品区分)
CM65: Rev4.0 預り売上数項目の追加
D66: 予備 | H66: 納入予備 | O66: 営業サンプル | Z66: 定数出荷 | AM66: 不適合手配NO
BZ67: CP指摘 2022/10/02 落合 商品・購買品受注の時に、発注先が必要 | DA67: MDSOL回答 石田 2022/10/27 追加致しました | DR67: 2022/10/29 落合 問題なし
D68: 売上可否 | H68: 区分値：可、不可、商品込、社内
D70: 構成情報
D71: シート 段 | J71: E | O71: 原紙 | Z71: 印刷 | AI71: エンボス | AT71: メーカ
F72: 表 | J72: ECBAF | O72: コードボール270（Fﾐｯｸｽ） | Z72: 0000 | AI72: 00
F73: 中 | J73: EOO1R | O73: 中芯（Fリサイクル） | Z73: 0000 | AI73: 00 | CM73: V7.0 受注画面制御
F74: 裏 | J74: E928 | O74: 09ｺﾝﾗｲﾅｰ(Fﾐｯｸｽ 撥水（B1）) | Z74: 9507 | AI74: 00
D75: FSC受注区分
D76: 枚葉印刷 | J76: オフセット
D77: 刃渡り（mm) | J77: 巾 | P77: 流れ | V77: 咥え | Z77: 前後 | AF77: 左右 | BZ77: CP指摘 2022/10/02 落合 売上巾が必要。 売上時の平米計算も売上巾にて行う。 | DO77: MDSOL回答 石田 2022/10/27 追加致しました | EE77: 2022/10/29 落合 問題なし
D78: シート寸法 | J78: 巾 | P78: 流れ | U78: ※(抜き無し見積もり：刃渡り寸法が無いので、シート寸法を入力する。) | BZ78: CP指摘 2022/9/30 落合 単位と数量の位置を逆にする。 単価と単価単位も位置を逆にする。 | DO78: MDSOL回答 石田 2022/10/27 対応致しました | EE78: 2022/10/29 落合 問題なし
D79: 売上巾 | J79: 巾 | BZ79: CP指摘 2022/9/30 落合 セット単価も入力欄。 売価区分＝セットでかつ親部材の時のみ入力可とする。 子の場合はゼロ。 | DO79: MDSOL回答 石田 2022/10/27 対応致しました | EE79: 2022/10/29 落合 問題なし
D80: 最終機械工程 | J80: グルア | BZ80: CP指摘 2022/9/30 落合 備考の表示順を上から印刷備考・製造備考・納入備考・伝票備考・出荷備考１・出荷備考２・再製造備考の順に変更 | DO80: MDSOL回答 石田 2022/10/27 対応致しました | EE80: 2022/10/29 落合 問題なし
D81: 数量 | P81: 数量単位 | Z81: 単価 | AI81: セット単価 | AT81: 単価単位 | BE81: 特値 □
D83: 仕入情報 | CM83: V7.0 受注画面制御
D84: 巻きM | P84: 発注単位 | Z84: 発注単価 | AI84: 発注先
CL85: REV3.0 発注単価の追加
D86: 備考
D87: 印刷備考 | J87: FSC管理NO・1614 | AD87: 製造備考 | AJ87: ｹﾞ7ｺｰﾄﾞ（文昌堂）支給 ｼｮｳﾜﾄﾞｳﾍ/4
D88: 納入備考 | J88: ｹﾞ7ｺｰﾄﾞ（文昌堂）支給 ｼｮｳﾜﾄﾞｳﾍ/4 | AD88: 伝票備考
D89: 出荷備考１ | J89: FSC.1614 オ＝ト | AD89: 出荷備考２ | AJ89: ｼｮｳﾜﾄﾞｳ/7 ﾓﾁｺﾐ ｶｰﾄﾝ/11
D90: 再製造備考 | Z90: 40byte
C98: ３ページ目：工程情報画面
D99: 製品CD | G99: 5372700017001 | N99: 得意先 | X99: 顧客品名 | BI99: 出荷日時 | BL99: 2022/8/30 12:00
D100: ← 画面固定 →
D101: 工程 | F101: 工程名 | I101: 作業 | O101: WG | Q101: 号機／発注先 | V101: 号機 変更 不可 | X101: CP 配送 | AB101: 加工予定日 | AF101: 仕様／工程備考 | BH101: 版型 | BL101: 消耗品 | BP101: 外注費 | BT101: 製造設定 | BZ101: △
AB102: 加工予定日 | AF102: 仕様1 | AJ102: 仕様2 | AN102: 仕様3 | AR102: 仕様4 | AV102: 仕様5 | AZ102: 仕様6 | BD102: 仕様7 | BH102: 版型№ | BL102: 消耗品 | BP102: 仕入単価 | BT102: ﾛｽ率 (%) | BV102: 台数 (枚) | BX102: LT (日)
AF103: 工程備考１ | AV103: 工程備考２ | BP103: 指値(本支店)
D104: 0020 | F104: 輪転（グラビア）1 | I104: 00201 | K104: （輪転）グラビア1 | O104: 30 | Q104: 名古屋 輪転グラビア1号機 | V104: □ | X104: 移送 | AF104: 印刷CD | AJ104: 印刷回数 | AN104: 色数 | AR104: ﾆｽ区分 | AV104: ﾏｰｸ断裁 | CL104: MDSOL回答 2022/11/11 石田 会議を受けてCP配送区分をフラグ→リストボックスとして項目定義、レイアウト変更しました。設定処理は共通処理として処理概要に呼び出しを記載しました。材料設定で後工程が決まる部分があり登録時の設定は材料設定が確定したタイミングです。
AF105: 9507 | AJ105: 1 | AN105: 3 | AR105: 1
AF106: 工程備考AAA | AV106: 工程備考BBB
D107: 0110 | F107: 片面コルゲータ | I107: 01101 | K107: 貼合 | O107: 30 | Q107: 小牧工場 片面コルゲータ | V107: □ | X107: □ | AB107: 44801 | AJ107: 全判巾 | AN107: 全判流れ | AR107: 巾変更 | BX107: 1
AJ108: 1350 | AN108: 814 | AR108: 1:不可
I110: 01102 | K110: コルスリ | AF110: 表巾 | AJ110: ｽﾘｯﾀｰ巾1 | AN110: ｽﾘｯﾀｰ流れ1 | AR110: ｽﾘｯﾀｰ巾2 | AV110: ｽﾘｯﾀｰ流れ2 | AZ110: コルスリ | BD110: 割り数
AJ111: 644 | AN111: 814 | AZ111: 3:化粧裁 | BD111: 2
AF112: 工程備考AAA | AV112: 工程備考BBB
D113: 0200 | F113: コートボール手配（表） | I113: 02001 | K113: ｺｰﾄﾎﾞｰﾙ手配 | O113: 40 | Q113: 外注：昭和堂 | V113: □ | X113: □ | Z113: □ | AF113: 巾 | AJ113: 流れ | AN113: 目なり | AR113: 連量 | AV113: ＠ | AZ113: 単位 | BD113: 特スキ
AF114: 650 | AJ114: 950 | AN114: 1.縦目 | AR114: 165 | AV114: 145 | AZ114: kg
I116: 02002 | K116: ｺｰﾄﾎﾞｰﾙ断裁 | AF116: 巾 | AJ116: 流れ
AF117: 650 | AJ117: 820
D119: 0440 | F119: 刷版手配(表) | I119: 04401 | K119: 刷版手配(表) | O119: 40 | Q119: 外注：昭和堂 | V119: □ | X119: □ | Z119: □ | AF119: 寸法 1.K | AJ119: 版作成 | AN119: 面付数 | AR119: 版数 | AV119: 抜きｽﾞﾚ防止ﾏｰｸ | AZ119: 面付番号 | BD119: 混入防止ﾏｰｸ
AJ120: 0:ﾌｨﾙﾑ 1:ＣＴＰ | AV120: 1.要 2.不可 | AZ120: 1.要 2.不可 | BD120: 1.要 2.不可
D122: 0450 | F122: オフセット印刷1 | I122: 04501 | K122: 製品情報 | O122: 40 | Q122: 外注：昭和堂 | V122: □ | X122: □ | Z122: □ | AF122: 原稿 | AJ122: ｸﾚｰﾑ情報 | AN122: ｸﾚｰﾑ対象工程
AF123: 0.ﾅｼ 1.原稿袋 2.図面ｼｽﾃﾑ | AJ123: 0.ﾅｼ 1.ｱﾘ | AN123: 1.ＡＬＬ 2.備考欄
I125: 04502 | K125: オフセット印刷 | AF125: 色数 | AJ125: 色数割増 | AN125: 特色数 | AR125: ｲﾝｷ区分 | AV125: 針先
AF126: 1 | AR126: 3.ＵＶ | AV126: 1.突
I128: 04503 | K128: ニス | AF128: 壺ﾆｽ | AJ128: ｺｰﾀｰﾆｽ | AN128: ｽﾎﾟｯﾄ
AF129: 5:UVOP | AJ129: 4.UVｸﾘｱ | AN129: 2.ｱｸｱｴﾝﾎﾞｽ
D131: 0550 | F131: 合紙 | I131: 05501 | K131: 合紙 | O131: 40 | Q131: 九州 合紙G | V131: □ | X131: □ | Z131: □ | AF131: 貼り方 | AJ131: 糊
AF132: 1.片面 | AJ132: 0.合紙糊
D134: 0600 | F134: トムソン | I134: 06001 | K134: 新版ゴムづけ | O134: 40 | Q134: 九州 抜き１３ | V134: □ | AB134: 44802 | BX134: 1
I137: 06002 | K137: トムソン | AF137: 附数 | AJ137: 個数 | AN137: 刃渡1 / シート巾側 | AR137: 刃渡2 / シート流れ側 | AV137: 面切 | AZ137: 穴数 | BD137: 抜
AF138: 1 | AJ138: 1 | AN138: 616 | AR138: 787 | AV138: 1.アリ | BD138: 2.裏
D140: 0800 | F140: グルア | I140: 08001 | K140: グルア（1） | O140: 40 | Q140: 九州 グルア30 | V140: □ | AB140: 44803 | AF140: 形式 | AJ140: 縦 | AN140: 横 | AR140: 仮折 | AV140: 連結数 | AZ140: 箱の高さ | BD140: 貼り方 | BX140: 0
AF141: 6.サイド貼り | AJ141: 616 | AN141: 787 | AR141: 1する | AZ141: 85
...

Sheet レイアウト(CP案_0518)
A1: =表紙!A54 -> Webシステム | K1: 文書名 | U1: モジュールID | Z1: =表紙!$AJ$63 -> MS | AE1: モジュール名 | AJ1: =表紙!$AX$63 -> 見積管理 | AS1: 文書番号 | AZ1: Version | BF1: Rev.
K2: =表紙!O64 -> アドオン設計書 | U2: ｻﾌﾞﾓｼﾞｭｰﾙID | Z2: =表紙!$AJ$64 -> MSBB | AE2: ｻﾌﾞﾓｼﾞｭｰﾙ名 | AJ2: =表紙!$AX$64 -> Webシステム | AS2: =表紙!$BL$64 -> M7-US-1140 | AZ2: =表紙!$BU$64 -> 7.0.2 | BF2: =表紙!$CB$64 -> 7
K3: =RIGHT(CELL("filename",$A$1),LEN(CELL("filename",$A$1))-FIND("]",CELL("filename",$A$1))) -> レイアウト(CP案_0518) | U3: 表題 | Z3: =表紙!$AJ$65 -> MSBBPA070 | AE3: =表紙!$AQ$65 -> Web受注入力
A5: 画面イメージ
B7: ≫凡例
Q8: ・・・ | S8: ボタン
C9: 見積計算書№ | Q9: ・・・ | S9: 検索項目(検索画面表示選択)
C10: 品名 | Q10: ・・・ | S10: 入力項目
C11: 得意先 | Q11: ・・・ | S11: 表示項目(得意先名称、原紙名等)
C12: 操作種別 | I12: ●登録 | M12: ○訂正 | Q12: ・・・ | S12: 選択項目(一つのみ選択可能)
C13: 受注区分 | Q13: ・・・ | S13: 選択項目(一つのみ選択可能)
C14: 作業順 | I14: ☑AAA | M14: ☑BBB | Q14: ・・・ | S14: 選択項目(複数選択可能)
C16: 第1画面
D21: 操作種別 | J21: ●登録 | N21: ○訂正 | R21: ○削除 | V21: ○参照
D23: 受注部門 | AD23: 受注日
D24: 得意先 | AD24: 客納期 | AO24: 数量
D26: 注文書No | W26: 先方担当 | AO26: 宛名 | BB26: 様
D27: 運送会社 | W27: 出荷時間
D29: 手配NO | AD29: ← 「登録」時、コピー元手配№。 「訂正」「削除」「参照」の時、初期フォーカス
D31: 受注明細
D32: 製品CD | J32: (件名:オートフィルタ) | AC32: ← ｾｯﾄ品目指定することで、以下の一覧に部材品目表示
D34: № | F34: 手配NO1 | J34: 手配NO2 | N34: 手配NO3 | R34: 製品CD | Z34: 製品名 | AJ34: 単位 | AN34: 数量 | AS34: 特値 | AV34: 単価 | AZ34: 金額 | BD34: 手配区分 | BH34: 納入先 | BL34: 納入先名 | BP34: 物流グループ | BT34: 預り売上 | BX34: 売上理由 | CB34: 受注明細№
E35: 1 | J35: 得意先CD | N35: 案件№ | Z35: 味比べ3P箱 身 | AS35: □ | BU35: □
E36: 2 | J36: 得意先CD | N36: 案件№ | Z36: 味比べ3P箱 身 | AS36: □ | BU36: □ | BX36: 製造予備
E37: 3 | J37: 得意先CD | N37: 案件№ | Z37: 味比べ3P箱 蓋 | AS37: □ | BU37: □
E38: 4 | J38: 得意先CD | N38: 案件№ | Z38: 味比べ3P箱 仕切り | AS38: □ | BD38: 仕入直送 | BU38: □
F40: ※メニュー「シート受注入力」を選択した場合は、第２画面からスタート
F41: ※メニュー「購買品受注入力」を選択した場合は、第２画面からスタート。 工程情報登録はなし。 入力項目の追加あり。
C46: 第２画面 | H46: ※部材の種類分、第２画面が連続して表示される
D47: 基本情報
F48: 手配NO | O48: 得意先 | AI48: 客納期 | AS48: 数量 | BC48: 単位
F49: 製品CD | O49: 顧客品名
O50: CP品名1 | AI50: CP品名2
F51: 顧客注文№ | O51: 顧客品番
F52: FSC認証 | O52: 食品安全
D54: 予備 | H54: 納入予備 | P54: 製造予備 | X54: 営業サンプル
D55: 備考
D60: ↓ 段・原紙構成・寸法などは、全て工程情報として入力を行う。 工程画面にて工程に対して材料指定を行う。 作業順別の材料指定は不可。 工程の下にツリービューにて材料をぶら下げる
BQ93: 第３画面 ロット別単価設定画面へ

Sheet レイアウト旧
A1: =表紙!A54 -> Webシステム | K1: 文書名 | U1: モジュールID | Z1: =表紙!$AJ$63 -> MS | AE1: モジュール名 | AJ1: =表紙!$AX$63 -> 見積管理 | AS1: 文書番号 | AZ1: Version | BF1: Rev.
K2: =表紙!O64 -> アドオン設計書 | U2: ｻﾌﾞﾓｼﾞｭｰﾙID | Z2: =表紙!$AJ$64 -> MSBB | AE2: ｻﾌﾞﾓｼﾞｭｰﾙ名 | AJ2: =表紙!$AX$64 -> Webシステム | AS2: =表紙!$BL$64 -> M7-US-1140 | AZ2: =表紙!$BU$64 -> 7.0.2 | BF2: =表紙!$CB$64 -> 7
K3: =RIGHT(CELL("filename",$A$1),LEN(CELL("filename",$A$1))-FIND("]",CELL("filename",$A$1))) -> レイアウト旧 | U3: 表題 | Z3: =表紙!$AJ$65 -> MSBBPA070 | AE3: =表紙!$AQ$65 -> Web受注入力
A5: 画面イメージ
B7: ≫凡例
Q8: ・・・ | S8: ボタン
C9: 見積計算書№ | Q9: ・・・ | S9: 検索項目(検索画面表示選択)
C10: 品名 | Q10: ・・・ | S10: 入力項目
C11: 得意先 | Q11: ・・・ | S11: 表示項目(得意先名称、原紙名等)
C12: 操作種別 | I12: ●登録 | M12: ○訂正 | Q12: ・・・ | S12: 選択項目(一つのみ選択可能)
C13: 受注区分 | Q13: ・・・ | S13: 選択項目(一つのみ選択可能)
C14: 作業順 | I14: ☑AAA | M14: ☑BBB | Q14: ・・・ | S14: 選択項目(複数選択可能)
C16: TOP画面
D21: 操作種別 | J21: ●登録 | N21: ○訂正 | R21: ○削除 | V21: ○参照 | Z21: ○コピー
D23: 製品CD | J23: (件名:オートフィルタ) | AD23: 手配NO | BE23: 得意先
D25: ↑新規時 有効 | AD25: ↑訂正、削除、参照時 有効
D29: 基本情報
D31: 案件№ | AD31: 受注№
D33: 受注部門 | V33: 最終製造部門 | AN33: シート部門
D34: 受注日 | V34: 運送会社 | AN34: 夜積区分 | AX34: (1:夜、0:昼)
D36: 得意先 | J36: (得意先名:オートフィルタ) | AH36: 先方担当
AH37: 宛名 | AX37: 様
D39: 注文書No
D45: 受注明細
D47: № | F47: 受注明細№ | N47: 製品CD | V47: 製品名 | AF47: 単位 | AJ47: 数量 | AN47: 平米 | AS47: 特値 | AV47: 単価 | AZ47: 金額 | BD47: 手配NO1 | BH47: 手配NO2 | BL47: 手配NO3 | BP47: 手配区分 | BT47: 納入先 | BX47: 納入先名 | CB47: 物流グループ | CF47: 預り売上 | CJ47: 売上理由
E48: 1 | V48: 味比べ3P箱 身 | AS48: □ | CG48: □
E49: 2 | V49: 味比べ3P箱 身 | AS49: □ | CG49: □ | CJ49: 製造予備
E50: 3 | V50: 味比べ3P箱 蓋 | AS50: □ | CG50: □
E51: 4 | V51: 味比べ3P箱 仕切り | AS51: □ | BP51: 仕入直送 | CG51: □
D57: 基本情報
D60: シート 段 | V60: メーカー
D61: 構成 | F61: 表 | J61: C5R | O61: Ｃ５（Ｆリサイクル）
F62: 中 | J62: 001R | O62: 中芯（Ｆリサイクル)
F63: 裏 | J63: C5R | O63: Ｃ５（Ｆリサイクル）
D65: 33:コート | J65: 表幅 | M65: 幅 | Q65: 流れ | V65: コルスリ | AA65: 割数 | AE65: 断裁区分
D66: シート寸法 | P66: × | V66: 4 | X66: 化半 | AH66: (1:外注)
D67: スリッター | P67: ×
D69: 予備必要 | J69: 納入予備 | S69: 製造予備 | AB69: 営業サンプル
D71: 定数出荷 | N71: (1:定数出荷)
D73: 貼合日 | P73: 課長立会有無 | AA73: コルゲータ反転有無 | AN73: エッジプレス | AX73: 協力会社指示 | BJ73: シート荷姿指示 | BU73: 協力会社指示
D76: 印刷備考 | AD76: 製造備考
D77: 横持備考 | AD77: 納入備考
D78: 配車備考 | AD78: 伝票備考
D80: 号機指定
D82: 不適合受注NO

Sheet レイアウト (シート)
A1: =表紙!A54 -> Webシステム | K1: 文書名 | U1: モジュールID | Z1: =表紙!$AJ$63 -> MS | AE1: モジュール名 | AJ1: =表紙!$AX$63 -> 見積管理 | AS1: 文書番号 | AZ1: Version | BF1: Rev.
K2: =表紙!O64 -> アドオン設計書 | U2: ｻﾌﾞﾓｼﾞｭｰﾙID | Z2: =表紙!$AJ$64 -> MSBB | AE2: ｻﾌﾞﾓｼﾞｭｰﾙ名 | AJ2: =表紙!$AX$64 -> Webシステム | AS2: =表紙!$BL$64 -> M7-US-1140 | AZ2: =表紙!$BU$64 -> 7.0.2 | BF2: =表紙!$CB$64 -> 7
K3: =RIGHT(CELL("filename",$A$1),LEN(CELL("filename",$A$1))-FIND("]",CELL("filename",$A$1))) -> レイアウト (シート) | U3: 表題 | Z3: =表紙!$AJ$65 -> MSBBPA070 | AE3: =表紙!$AQ$65 -> Web受注入力
A5: 画面イメージ
B7: ≫凡例
Q8: ・・・ | S8: ボタン
C9: 見積計算書№ | Q9: ・・・ | S9: 検索項目(検索画面表示選択)
C10: 品名 | Q10: ・・・ | S10: 入力項目
C11: 得意先 | Q11: ・・・ | S11: 表示項目(得意先名称、原紙名等)
C12: 操作種別 | I12: ●登録 | M12: ○訂正 | Q12: ・・・ | S12: 選択項目(一つのみ選択可能)
C13: 受注区分 | Q13: ・・・ | S13: 選択項目(一つのみ選択可能)
C14: 作業順 | I14: ☑AAA | M14: ☑BBB | Q14: ・・・ | S14: 選択項目(複数選択可能)
C16: TOP画面
D21: 操作種別 | J21: ●登録 | N21: ○訂正 | R21: ○削除 | V21: ○参照 | Z21: ○コピー
D23: 製品CD | J23: (件名:オートフィルタ) | AD23: 手配NO | BE23: 得意先
D25: ↑新規時 有効 | AD25: ↑訂正、削除、参照時 有効
D31: 基本情報
D33: 案件№
D35: 受注部門 | V35: 最終製造部門 | AN35: シート部門
D36: 受注日 | V36: 運送会社 | AN36: 夜積区分 | AX36: (1:夜、0:昼)
D38: 得意先 | J38: (得意先名:オートフィルタ) | AH38: 先方担当
AH39: 宛名 | AX39: 様
D41: 注文書No
D52: 受注明細
D54: № | F54: 製品CD | N54: 製品名 | X54: 単位 | AB54: 数量 | AF54: 平米 | AK54: 特値 | AN54: 単価 | AR54: 金額 | AV54: 手配NO1 | AZ54: 手配NO2 | BD54: 手配NO3 | BH54: 手配区分 | BL54: 納入先 | BP54: 納入先名 | BT54: 物流グループ | BX54: 預り売上 | CB54: 売上理由
E55: 1 | N55: シート | AK55: □ | BY55: □
E56: 2 | N56: シート | AK56: □ | AN56: 0 | BY56: □ | CB56: 納入予備
D61: 基本情報
D63: 受注区分 | J63: 1 | L63: 製品 | T63: 製品区分 | Z63: 11:シート
D65: 客品名 | AD65: 客先品番
D66: CP品名 | AD66: 部材名 | AU66: JANコード
D68: シート 段 | V68: メーカー
D69: 構成 | F69: 表 | J69: C5R | O69: Ｃ５（Ｆリサイクル）
F70: 中 | J70: 001R | O70: 中芯（Ｆリサイクル)
F71: 裏 | J71: C5R | O71: Ｃ５（Ｆリサイクル）
J73: 表幅 | M73: 幅 | Q73: 流れ | V73: コルスリ | AA73: 割数 | AE73: 断裁区分 | AM73: スコアラ寸法
D74: シート寸法 | P74: × | V74: 4 | X74: 化半 | AH74: (1:外注) | AP74: ＋ | AT74: ＋ | AX74: ＋ | BB74: ＋
D75: 受注寸法１ | P75: ×
D76: 受注寸法２ | P76: × | V76: 売上巾
D78: 予備必要 | J78: 納入予備 | S78: 製造予備 | AB78: 営業サンプル
D80: 定数出荷 | N80: (1:定数出荷)
D82: 貼合日 | P82: 課長立会有無 | AA82: コルゲータ反転有無 | AN82: エッジプレス | AX82: 協力会社指示 | BJ82: シート荷姿指示 | BU82: 協力会社指示
D85: 印刷備考 | AD85: 製造備考
D86: 横持備考 | AD86: 納入備考
D87: 配車備考 | AD87: 伝票備考
D89: 号機指定

Sheet レイアウト (商品購買) 
A1: =表紙!A54 -> Webシステム | K1: 文書名 | U1: モジュールID | Z1: =表紙!$AJ$63 -> MS | AE1: モジュール名 | AJ1: =表紙!$AX$63 -> 見積管理 | AS1: 文書番号 | AZ1: Version | BF1: Rev.
K2: =表紙!O64 -> アドオン設計書 | U2: ｻﾌﾞﾓｼﾞｭｰﾙID | Z2: =表紙!$AJ$64 -> MSBB | AE2: ｻﾌﾞﾓｼﾞｭｰﾙ名 | AJ2: =表紙!$AX$64 -> Webシステム | AS2: =表紙!$BL$64 -> M7-US-1140 | AZ2: =表紙!$BU$64 -> 7.0.2 | BF2: =表紙!$CB$64 -> 7
K3: =RIGHT(CELL("filename",$A$1),LEN(CELL("filename",$A$1))-FIND("]",CELL("filename",$A$1))) -> レイアウト (商品購買) | U3: 表題 | Z3: =表紙!$AJ$65 -> MSBBPA070 | AE3: =表紙!$AQ$65 -> Web受注入力
A5: 画面イメージ
B7: ≫凡例
Q8: ・・・ | S8: ボタン
C9: 見積計算書№ | Q9: ・・・ | S9: 検索項目(検索画面表示選択)
C10: 品名 | Q10: ・・・ | S10: 入力項目
C11: 得意先 | Q11: ・・・ | S11: 表示項目(得意先名称、原紙名等)
C12: 操作種別 | I12: ●登録 | M12: ○訂正 | Q12: ・・・ | S12: 選択項目(一つのみ選択可能)
C13: 受注区分 | Q13: ・・・ | S13: 選択項目(一つのみ選択可能)
C14: 作業順 | I14: ☑AAA | M14: ☑BBB | Q14: ・・・ | S14: 選択項目(複数選択可能)
C16: TOP画面
D21: 操作種別 | J21: ●登録 | N21: ○訂正 | R21: ○削除 | V21: ○参照 | Z21: ○コピー
D23: 製品CD | J23: (件名:オートフィルタ) | AD23: 手配NO | BE23: 得意先
D25: ↑新規時 有効 | AD25: ↑訂正、削除、参照時 有効
D31: 基本情報
D33: 案件№
D35: 受注部門 | V35: 最終製造部門 | AN35: シート部門
D36: 受注日 | V36: 運送会社 | AN36: 夜積区分 | AX36: (1:夜、0:昼)
D38: 得意先 | J38: (得意先名:オートフィルタ) | AH38: 先方担当
AH39: 宛名 | AX39: 様
D41: 注文書No
D52: 受注明細
D54: № | F54: 製品CD | N54: 製品名 | X54: 単位 | AB54: 数量 | AF54: 平米 | AK54: 特値 | AN54: 単価 | AR54: 金額 | AV54: 手配NO1 | AZ54: 手配NO2 | BD54: 手配NO3 | BH54: 手配区分 | BL54: 発注先 | BP54: 発注先名 | BT54: 納入先 | BX54: 納入先名 | CB54: 物流グループ | CF54: 預り売上 | CJ54: 売上理由
E55: 1 | N55: 商品 | AK55: □ | CG55: □
D61: 基本情報
D63: 客品名 | AD63: 客先品番
D64: CP品名 | AD64: 部材名 | AU64: JANコード
D66: 版型NO
D68: シート 段 | V68: メーカー
D69: 構成 | F69: 表 | J69: C5R | O69: Ｃ５（Ｆリサイクル）
F70: 中 | J70: 001R | O70: 中芯（Ｆリサイクル)
F71: 裏 | J71: C5R | O71: Ｃ５（Ｆリサイクル）
J73: 表幅 | M73: 幅 | Q73: 流れ | V73: コルスリ | AA73: 割数 | AE73: 断裁区分
D74: シート寸法 | P74: × | V74: 4 | X74: 化半 | AH74: (1:外注)
D75: スリッター | P75: ×
D77: 予備必要 | J77: 納入予備 | S77: 製造予備 | AB77: 営業サンプル
D79: 定数出荷 | N79: (1:定数出荷)
D81: 貼合日 | P81: 課長立会有無 | AA81: コルゲータ反転有無 | AN81: エッジプレス | AX81: 協力会社指示 | BJ81: シート荷姿指示 | BU81: 協力会社指示
D83: 印刷備考 | AD83: 製造備考
D84: 横持備考 | AD84: 納入備考
D85: 配車備考 | AD85: 伝票備考
D87: 号機指定

Sheet レイアウト_bk01
A1: =表紙!A54 -> Webシステム | K1: 文書名 | U1: モジュールID | Z1: =表紙!$AJ$63 -> MS | AE1: モジュール名 | AJ1: =表紙!$AX$63 -> 見積管理 | AS1: 文書番号 | AZ1: Version | BF1: Rev.
K2: =表紙!O64 -> アドオン設計書 | U2: ｻﾌﾞﾓｼﾞｭｰﾙID | Z2: =表紙!$AJ$64 -> MSBB | AE2: ｻﾌﾞﾓｼﾞｭｰﾙ名 | AJ2: =表紙!$AX$64 -> Webシステム | AS2: =表紙!$BL$64 -> M7-US-1140 | AZ2: =表紙!$BU$64 -> 7.0.2 | BF2: =表紙!$CB$64 -> 7
K3: =RIGHT(CELL("filename",$A$1),LEN(CELL("filename",$A$1))-FIND("]",CELL("filename",$A$1))) -> レイアウト_bk01 | U3: 表題 | Z3: =表紙!$AJ$65 -> MSBBPA070 | AE3: =表紙!$AQ$65 -> Web受注入力
A5: 画面イメージ
B7: ≫凡例
Q8: ・・・ | S8: ボタン
C9: 見積計算書№ | Q9: ・・・ | S9: 検索項目(検索画面表示選択)
C10: 品名 | Q10: ・・・ | S10: 入力項目
C11: 得意先 | Q11: ・・・ | S11: 表示項目(得意先名称、原紙名等)
C12: 操作種別 | I12: ●登録 | M12: ○訂正 | Q12: ・・・ | S12: 選択項目(一つのみ選択可能)
C13: 受注区分 | Q13: ・・・ | S13: 選択項目(一つのみ選択可能)
C14: 作業順 | I14: ☑AAA | M14: ☑BBB | Q14: ・・・ | S14: 選択項目(複数選択可能)
C21: 第1画面
D23: 操作種別 | J23: ●登録 | N23: ○訂正 | R23: ○削除 | V23: ○参照 | Z23: ○コピー
AO24: 手配NO | BK24: ← 「コピー」時、元手配№。 「訂正」「削除」「参照」の時、初期フォーカス
D27: 受注部門 | AD27: 受注日 | AO27: 受注区分
D28: 得意先 | AD28: 客納納期 | AO28: 数量
D30: 注文書No | W30: 先方担当 | AO30: 宛名 | BC30: 様
D31: 運送会社 | W31: 出荷時間
D33: 売価区分
D35: 受注明細
D36: 製品CD | J36: (件名:オートフィルタ) | AC36: ← ｾｯﾄ品目指定することで、以下の一覧に部材品目表示
D39: № | F39: 手配NO1 | I39: 手配NO2 | L39: 手配NO3 | O39: 製品CD/品目CD | T39: 製品名 | AB39: 単位 | AD39: 数量 | AG39: 特値 | AJ39: 個別単価 | AM39: ｾｯﾄ単価 | AP39: 金額 | AT39: 手配区分 | AW39: 納品先 | BA39: 納品先名 | BE39: 物流グループ | BH39: 預り売上 | BL39: 売上理由 | BP39: 受注№/受注明細№
E40: 1 | I40: 得意先CD | L40: 案件№ | T40: 味比べ3P箱 身 | AG40: □ | BI40: □
E41: 3 | I41: 得意先CD | L41: 案件№ | T41: 味比べ3P箱 蓋 | AG41: □ | BI41: □
E42: 4 | I42: 得意先CD | L42: 案件№ | T42: 味比べ3P箱 仕切り | AG42: □ | AT42: 仕入直送 | BI42: □
F44: ※メニュー「シート受注入力」を選択した場合は、第２画面からスタート
F45: ※メニュー「購買品受注入力」を選択した場合は、第２画面からスタート。 工程情報登録はなし。 入力項目の追加あり。
C53: 第２画面 | H53: ※部材の種類分、第２画面が連続して表示される
D54: 基本情報
F56: 受注区分 | Q56: 製品区分 | S56: 大 | Z56: 中 | AG56: 小
F57: 手配NO | O57: 得意先 | AI57: 客納納期 | AS57: 数量 | BC57: 単位
F58: 製品CD | O58: 顧客品名
O59: CP品名1 | AI59: CP品名2
F60: 顧客注文№ | O60: 顧客品番
F61: FSC認証 | O61: 食品安全
D64: 予備 | H64: 納入予備 | P64: 製造予備 | X64: 営業サンプル
D67: 定数出荷 | P67: 号機指定 | AC67: 不適合受注NO
D69: 売上可否
D71: 構成情報
D72: シート 段 | J72: E | O72: 原紙 | AC72: 印刷 | AQ72: エンボス
F73: 表 | J73: (原紙名:ｵｰﾄﾌｨﾙﾀ) | AC73: (印刷名:ｵｰﾄﾌｨﾙﾀ) | AQ73: (エンボス名:ｵｰﾄﾌｨﾙﾀ)
F74: 中 | J74: (原紙名:ｵｰﾄﾌｨﾙﾀ) | AC74: (印刷名:ｵｰﾄﾌｨﾙﾀ) | AQ74: (エンボス名:ｵｰﾄﾌｨﾙﾀ)
F75: 裏 | J75: (原紙名:ｵｰﾄﾌｨﾙﾀ) | AC75: (印刷名:ｵｰﾄﾌｨﾙﾀ) | AQ75: (エンボス名:ｵｰﾄﾌｨﾙﾀ)
D76: FSC受注区分
D77: 枚葉印刷 | J77: オフセット
D78: 刃渡り（mm) | J78: 巾 | P78: 流れ | V78: 咥え | Z78: 前後 | AF78: 左右
D79: シート寸法 | J79: 巾 | P79: 流れ | U79: ※(抜き無し見積もり：刃渡り寸法が無いので、シート寸法を入力する。)
D80: 最終機械工程 | J80: グルア
D81: 単価 | P81: 特値 □
D83: 備考
D84: コルゲータ | J84: 40byte | AD84: コルゲータ以降 | AJ84: 40byte
D85: 印刷備考 | J85: 40byte | AD85: グルア以降 | AJ85: 40byte
D86: 伝票備考 | J86: 40byte | AD86: 納入備考 | AJ86: 40byte
D87: 出荷備考 | J87: 40byte | AD87: 横持備考 | AJ87: 40byte
C95: ３ページ目：工程情報画面
D96: 製品CD | G96: 5372700017001 | N96: 得意先 | X96: 顧客品名
D97: ← 画面固定 →
D98: 工順 | E98: 工程 | G98: 工程名 | J98: 作業 | O98: WG | Q98: 号機／発注先 | V98: 仕様／工程備考 | AX98: 版型 | BB98: 外注費 | BF98: 製造設定 | BL98: △
V99: 仕様1 | Z99: 仕様2 | AD99: 仕様3 | AH99: 仕様4 | AL99: 仕様5 | AP99: 仕様6 | AT99: 仕様7 | AX99: 版型№ | BB99: 仕入単価 | BF99: ﾛｽ率 (%) | BH99: 台数 (枚) | BJ99: LT
V100: 工程備考１ | AL100: 工程備考２ | BJ100: (日)
D101: 10 | E101: 0110 | G101: 片面コルゲータ | J101: 1 | K101: 貼合 | O101: 10 | Q101: 5362：●●工業 | Z101: 全判巾 | AD101: 全判流れ | BB101: 500 | BF101: 1 | BH101: 5
J104: 2 | K104: コルスリ | V104: 表巾 | Z104: ｽﾘｯﾀｰ1巾 | AD104: ｽﾘｯﾀｰ1流れ | AH104: ｽﾘｯﾀｰ2巾 | AL104: ｽﾘｯﾀｰ2流れ | AP104: ｺﾙｽﾘ | AT104: 割り数
J107: 引当 | K107: 連絡 | V107: 材料 | AB107: 受給区分・単価 | AH107: 支給区分・単価 | AN107: 材料 | AT107: 受給区分・単価 | AZ107: 支給区分・単価 | BF107: 入庫先
V108: 表 | AB108: 有・無 | AH108: 有・無 | AT108: 有・無 | AZ108: 有・無 | BF108: 名古屋合紙置き場
V109: 中 | AB109: 有・無 | AH109: 有・無 | AT109: 有・無 | AZ109: 有・無
AB110: 有・無 | AH110: 有・無 | AT110: 有・無 | AZ110: 有・無
D111: 20 | E111: 0200 | G111: ｺｰﾄﾎﾞｰﾙ手配（表） | J111: 1 | K111: ｺｰﾄﾎﾞｰﾙ手配 | V111: 巾 | Z111: 流れ | AD111: 目なり | AH111: 連量 | AL111: 単価 | AP111: 単位 | AT111: 得スキ
J114: 2 | K114: ｺｰﾄﾎﾞｰﾙ断裁 | V114: 巾 | Z114: 流れ | AD114: 裁ち数
J117: 引当 | K117: 連絡 | V117: 材料 | AB117: 受給区分・単価 | AH117: 支給区分・単価 | AN117: 材料 | AT117: 受給区分・単価 | AZ117: 支給区分・単価 | BF117: 入庫先
V118: コートボール | AB118: 有・無 | AH118: 有・無 | AT118: 有・無 | AZ118: 有・無
AB119: 有・無 | AH119: 有・無 | AT119: 有・無 | AZ119: 有・無
AB120: 有・無 | AH120: 有・無 | AT120: 有・無 | AZ120: 有・無
D121: 40 | E121: 0450 | G121: オフセット印刷1 | J121: 1 | K121: 刷版手配 | V121: 寸法 | Z121: 版作成 | AD121: 面付数 | AH121: 版数 | AL121: 抜きｽﾞﾚ | AP121: 面付番号 | AT121: 混入防止
J124: 2 | K124: 印刷 | V124: 色数 | Z124: 色数割増 | AD124: 壺ニス | AH124: コーターニス | AL124: スポット | AP124: インキ区分 | AT124: 針先
J127: 3 | K127: ニス | V127: 壺ﾆｽ | Z127: ｺｰﾀｰﾆｽ | AD127: ｽﾎﾟｯﾄ
J130: 引当 | K130: 連絡 | V130: 材料 | AB130: 受給区分・単価 | AH130: 支給区分・単価 | AN130: 材料 | AT130: 受給区分・単価 | AZ130: 支給区分・単価 | BF130: 入庫先
V131: 0200:ｺｰﾄﾎﾞｰﾙ手配（表） | AB131: 有・無 | AH131: 有・無 | AT131: 有・無 | AZ131: 有・無
V132: アルミ板 | AB132: 有・無 | AH132: 有・無 | AT132: 有・無 | AZ132: 有・無
AB133: 有・無 | AH133: 有・無 | AT133: 有・無 | AZ133: 有・無
D134: 50 | E134: 0550 | G134: 合紙 | J134: 1 | K134: 合紙 | O134: 10 | V134: 合紙 | Z134: 合紙糊
J137: 引当 | K137: 連絡 | V137: 材料 | AB137: 受給区分・単価 | AH137: 支給区分・単価 | AN137: 材料 | AT137: 受給区分・単価 | AZ137: 支給区分・単価 | BF137: 入庫先
V138: 0110:片面コルゲータ | AB138: 有・無 | AH138: 有・無 | AT138: 有・無 | AZ138: 有・無
V139: 0450:オフセット印刷1 | AB139: 有・無 | AH139: 有・無 | AT139: 有・無 | AZ139: 有・無
AB140: 有・無 | AH140: 有・無 | AT140: 有・無 | AZ140: 有・無
D141: 60 | E141: 0600 | G141: トムソン | J141: 1 | K141: トムソン | O141: 10 | V141: 付け数 | Z141: 個数 | AD141: 刃渡り1 | AH141: 刃渡り2 | AL141: 面切 | AP141: 穴数 | AT141: 抜き方向
V142: 2 | Z142: 4
J144: 引当 | K144: 連絡 | V144: 材料 | AB144: 受給区分・単価 | AH144: 支給区分・単価 | AN144: 材料 | AT144: 受給区分・単価 | AZ144: 支給区分・単価 | BF144: 入庫先
V145: 0550:合紙 | AB145: 有・無 | AH145: 有・無 | AT145: 有・無 | AZ145: 有・無
AB146: 有・無 | AH146: 有・無 | AT146: 有・無 | AZ146: 有・無
AB147: 有・無 | AH147: 有・無 | AT147: 有・無 | AZ147: 有・無
D148: 70 | E148: 0800 | G148: グルア | J148: 1 | K148: グルア（1） | O148: 10 | V148: 形式 | Z148: 縦 | AD148: 横 | AH148: 仮折 | AL148: 連結数 | AP148: 箱の高さ | AT148: 貼り方
V149: 1 | AD149: 1
J151: 引当 | K151: 連絡 | V151: 材料 | AB151: 受給区分・単価 | AH151: 支給区分・単価 | AN151: 材料 | AT151: 受給区分・単価 | AZ151: 支給区分・単価 | BF151: 入庫先
V152: 0600:トムソン | AB152: 有・無 | AH152: 有・無 | AT152: 有・無 | AZ152: 有・無
V153: AAAAAAAAA1 | AB153: 有・無 | AH153: 有・無 | AT153: 有・無 | AZ153: 有・無
V154: BBBBBBBBB1 | AB154: 有・無 | AH154: 有・無 | AT154: 有・無 | AZ154: 有・無 | BL154: ▽
D160: 製品CD | G160: 5372700017001 | N160: 得意先 | X160: 顧客品名
D161: ← 画面固定 →
D162: 工順 | E162: 工程 | G162: 工程名 | J162: 作業 | O162: WG | Q162: 号機／発注先 | V162: 仕様／工程備考 | AX162: 版型 | BB162: 外注費 | BF162: 製造設定 | BL162: △
...

Sheet レイアウト (プリフル入力)
A1: =表紙!A54 -> Webシステム | K1: 文書名 | U1: モジュールID | Z1: =表紙!$AJ$63 -> MS | AE1: モジュール名 | AJ1: =表紙!$AX$63 -> 見積管理 | AS1: 文書番号 | AZ1: Version | BF1: Rev.
K2: =表紙!O64 -> アドオン設計書 | U2: ｻﾌﾞﾓｼﾞｭｰﾙID | Z2: =表紙!$AJ$64 -> MSBB | AE2: ｻﾌﾞﾓｼﾞｭｰﾙ名 | AJ2: =表紙!$AX$64 -> Webシステム | AS2: =表紙!$BL$64 -> M7-US-1140 | AZ2: =表紙!$BU$64 -> 7.0.2 | BF2: =表紙!$CB$64 -> 7
K3: =RIGHT(CELL("filename",$A$1),LEN(CELL("filename",$A$1))-FIND("]",CELL("filename",$A$1))) -> レイアウト (プリフル入力) | U3: 表題 | Z3: =表紙!$AJ$65 -> MSBBPA070 | AE3: =表紙!$AQ$65 -> Web受注入力
A5: 画面イメージ
B7: ≫凡例
Q8: ・・・ | S8: ボタン
C9: 見積計算書№ | Q9: ・・・ | S9: 検索項目(検索画面表示選択)
C10: 品名 | Q10: ・・・ | S10: 入力項目
C11: 得意先 | Q11: ・・・ | S11: 表示項目(得意先名称、原紙名等)
C12: 操作種別 | I12: ●登録 | M12: ○訂正 | Q12: ・・・ | S12: 選択項目(一つのみ選択可能)
C13: 受注区分 | Q13: ・・・ | S13: 選択項目(一つのみ選択可能)
C14: 作業順 | I14: ☑AAA | M14: ☑BBB | Q14: ・・・ | S14: 選択項目(複数選択可能)
C21: 第1画面 | CL21: 在庫情報
D23: 操作種別 | J23: ●登録 | N23: ○訂正 | R23: ○削除 | V23: ○参照 | Z23: ○コピー
AO24: 手配NO | BK24: ← 「コピー」時、元手配№。 「訂正」「削除」「参照」の時、初期フォーカス | CM24: ワーキンググループ
CM26: 品目CD
D27: 受注部門 | J27: 9110 | O27: 九州営業 | AD27: 受注日 | AH27: 2022/7/15 | AO27: 受注区分 | AS27: 製品
D28: 得意先 | J28: 095439 | Q28: 福岡パッケージ | AD28: 客納納期 | AH28: 2022/7/31 | AO28: 数量 | AS28: 5000 | CM28: 手配NO
D30: 注文書No | J30: 328-133-01-1 | W30: 先方担当 | AO30: 宛名 | BC30: 様
D31: 運送会社 | W31: 出荷時間
CL32: ワーキンググループＣＤ | CM32: ワーキンググループ名 | CN32: 品目ＣＤ | CO32: 枝番１ | CP32: 枝番２ | CQ32: 枝番３ | CR32: 品名 | CS32: 在庫数量 | CT32: 入庫予定数量 | CU32: 引当数量 | CV32: 保留数量 | CW32: 引当可能数量 | CX32: 場所ＣＤ | CY32: 場所名 | CZ32: 棚・ラインＣＤ | DA32: 棚・ライン名 | DB32: 棚・ライン無 | DC32: 物流グループＣＤ | DD32: 物流グループ名 | DE32: 手配ＮＯ１ | DF32: 手配ＮＯ２ | DG32: 手配ＮＯ３
D33: 売価区分 | J33: 単品売り | CL33: 30 | CM33: 名古屋 | CN33: 00221088 | CO33: 01 | CS33: 500 | CT33: 300 | CU33: 300 | CV33: 0 | CW33: 500
CL34: 30 | CM34: 名古屋 | CN34: 00221088 | CO34: 01 | CS34: 200 | CT34: 0 | CU34: 0 | CV34: 0 | CW34: 200
D35: 受注明細
D36: 製品CD | J36: (件名:オートフィルタ) | AC36: ← ｾｯﾄ品目指定することで、以下の一覧に部材品目表示
D39: № | F39: 手配NO1 | I39: 手配NO2 | L39: 手配NO3 | O39: 製品CD/品目CD | T39: 製品名 | AB39: 単位 | AD39: 数量 | AG39: 特値 | AJ39: 個別単価 | AM39: ｾｯﾄ単価 | AP39: 金額 | AT39: 手配区分 | AW39: 客先納期 | BA39: 納品先 | BE39: 納品先名 | BI39: 物流グループ | BL39: 預り売上 | BP39: 売上理由 | BT39: 受注№/受注明細№
E40: 1 | I40: 095439 | L40: 00001 | O40: 0022108801 | T40: もつ鍋化粧箱（海千様） 身 | AB40: 個 | AD40: 5000 | AG40: □ | AJ40: 114 | AT40: 在庫引当 | AW40: 2022/7/31 | BA40: 094258 | BE40: アスパック | BM40: □
E41: 2 | AG41: □ | BM41: □
E42: 3 | AG42: □ | BM42: □
C51: 第２画面 | H51: ※部材の種類分、第２画面が連続して表示される
D52: 基本情報
F54: 受注区分 | H54: 製品 | Q54: 製品区分 | S54: 大 | T54: 31プリフル | Z54: 中 | AG54: 小
F55: 手配NO | H55: 000001:095439:00001 | O55: 得意先 | S55: 95439 | W55: 福岡パッケージ | AI55: 客納納期 | AM55: 2022/07/31 | AS55: 数量 | AV55: 5,000 | BC55: 単位 | BE55: 個
F56: 製品CD | H56: 0022108801 | O56: 顧客品名
O57: CP品名1 | S57: もつ鍋化粧箱（海千様） | AI57: CP品名2
F58: 顧客注文№ | H58: 328-133-01-1 | O58: 顧客品番
F59: FSC認証 | O59: 食品安全
D62: 予備 | H62: 納入予備 | P62: 製造予備 | T62: 80 | X62: 営業サンプル
D65: 定数出荷 | P65: 号機指定 | AC65: 不適合受注NO
D67: 売上可否
D69: 構成情報
D70: シート 段 | J70: E | O70: 原紙 | Z70: 印刷 | AI70: エンボス | AT70: メーカ
F71: 表 | J71: ECBAF | O71: コードボール270（Fﾐｯｸｽ） | Z71: 0000 | AI71: 00
F72: 中 | J72: EOO1R | O72: 中芯（Fリサイクル） | Z72: 0000 | AI72: 00
F73: 裏 | J73: E928 | O73: 09ｺﾝﾗｲﾅｰ(Fﾐｯｸｽ 撥水（B1）) | Z73: 9507 | AI73: 00
D74: FSC受注区分
D75: 枚葉印刷 | J75: オフセット
D76: 刃渡り（mm) | J76: 巾 | L76: 1350 | P76: 流れ | R76: 814 | V76: 咥え | Z76: 前後 | AF76: 左右
D77: シート寸法 | J77: 巾 | M77: 644 | P77: 流れ | S77: 814 | U77: ※(抜き無し見積もり：刃渡り寸法が無いので、シート寸法を入力する。)
D78: 最終機械工程 | J78: グルア
D79: 単価 | J79: 114.00／個 | P79: 特値 □
D81: 備考
D82: 印刷備考 | J82: FSC管理NO・1614 | AD82: 製造備考 | AJ82: ｹﾞ7ｺｰﾄﾞ（文昌堂）支給 ｼｮｳﾜﾄﾞｳﾍ/4
D83: 伝票備考 | J83: FSC.1614 オ＝ト | AD83: 納入備考 | AJ83: ｼｮｳﾜﾄﾞｳ/7 ﾓﾁｺﾐ ｶｰﾄﾝ/11
D84: 出荷備考１ | Z84: 40byte | AD84: 出荷備考２ | AZ84: 40byte
C93: ３ページ目：工程情報画面
D94: 製品CD | G94: 0022108801 | N94: 得意先 | Q94: 95439 | X94: 顧客品名 | AD94: 福岡パッケージ
D95: ← 画面固定 →
D96: 工順 | E96: 工程 | G96: 工程名 | J96: 作業 | O96: WG | Q96: 号機／発注先 | V96: 仕様／工程備考 | AX96: 版型 | BB96: 外注費 | BF96: 製造設定 | BL96: △
V97: 仕様1 | Z97: 仕様2 | AD97: 仕様3 | AH97: 仕様4 | AL97: 仕様5 | AP97: 仕様6 | AT97: 仕様7 | AX97: 版型№ | BB97: 仕入単価 | BF97: ﾛｽ率 (%) | BH97: 台数 (枚) | BJ97: LT
V98: 工程備考１ | AL98: 工程備考２ | BJ98: (日)
D99: 10 | E99: 0020 | G99: 輪転（グラビア）1 | J99: 00201 | K99: （輪転）グラビア1 | O99: 30 | Q99: 名古屋 輪転グラビア1号機 | V99: 印刷CD | Z99: 印刷回数 | AD99: 色数 | AH99: ﾆｽ区分 | AL99: ﾏｰｸ断裁
V100: 9507 | Z100: 1 | AD100: 3 | AH100: 1
J102: 引当 | K102: 連絡 | V102: 材料 | AL102: 受給区分 | AT102: 受給単価 | BB102: 入庫先
V103: E09289507：09ｺﾝﾗｲﾅｰ(Fﾐｯｸｽ 撥水（B1）)
D106: 20 | E106: 0040 | G106: エンボス1 | J106: 00401 | K106: （輪転）エンボス1 | O106: 30 | Q106: 外注：岐阜事業所 | V106: エンボスCD | Z106: エンボスの深さ | AD106: 水有り（加湿）
V107: IB | Z107: 1：スーパー | AD107: 1：加湿要
J109: 引当 | K109: 連絡 | V109: 材料 | AL109: 受給区分 | AT109: 受給単価 | BB109: 入庫先
V110: 0020：輪転（グラビア）１
D113: 30 | E113: 0110 | G113: 片面コルゲータ | J113: 01101 | K113: 貼合 | O113: 30 | Q113: 小牧工場 片面コルゲータ | Z113: 全判巾 | AD113: 全判流れ | AH113: 巾変更
Z114: 1350 | AD114: 814 | AH114: 1:不可
J116: 01102 | K116: コルスリ | V116: 表巾 | Z116: ｽﾘｯﾀｰ巾1 | AD116: ｽﾘｯﾀｰ流れ1 | AH116: ｽﾘｯﾀｰ巾2 | AL116: ｽﾘｯﾀｰ流れ2 | AP116: コルスリ | AT116: 割り数
Z117: 644 | AD117: 814 | AP117: 3:化粧裁 | AT117: 2
J119: 引当 | K119: 連絡 | V119: 材料 | AL119: 受給区分 | AT119: 受給単価 | BB119: 入庫先
V120: 0040：エンボス１
V121: E001R：中芯（Fリサイクル）
D123: 40 | E123: 0170 | G123: 反転機 | J123: 01701 | K123: 反転機 | O123: 30 | Q123: 名古屋 反転機 | Z123: 方向
Z124: 1.裏上一方
J126: 引当 | K126: 連絡 | V126: 材料 | AL126: 受給区分 | AT126: 受給単価 | BB126: 入庫先
V127: 0110：片面コルゲータ
D130: 50 | E130: 0190 | G130: パイルターナー | J130: 01901 | K130: パイルターナー | O130: 30 | Q130: 名古屋 ターナー1号機 | V130: ﾊﾟｲﾙ
V131: 1.アリ
J133: 引当 | K133: 連絡 | V133: 材料 | AL133: 受給区分 | AT133: 受給単価 | BB133: 入庫先
V134: 0170：反転機
D137: 60 | E137: 0200 | G137: コートボール手配（表） | J137: 02001 | K137: ｺｰﾄﾎﾞｰﾙ手配 | O137: 40 | Q137: 外注：昭和堂 | V137: 巾 | Z137: 流れ | AD137: 目なり | AH137: 連量 | AL137: ＠ | AP137: 単位 | AT137: 特スキ
V138: 650 | Z138: 950 | AD138: 1.縦目 | AH138: 165 | AL138: 145 | AP138: kg
J140: 02002 | K140: ｺｰﾄﾎﾞｰﾙ断裁 | V140: 巾 | Z140: 流れ
V141: 650 | Z141: 820
J143: 引当 | K143: 連絡 | V143: 材料 | AL143: 受給区分 | AT143: 受給単価 | BB143: 入庫先
V144: ECBAF：コートボール270（Fﾐｯｸｽ）
D147: 70 | E147: 0440 | G147: 刷版手配(表) | J147: 04401 | K147: 刷版手配(表) | O147: 40 | Q147: 外注：昭和堂 | V147: 寸法 1.K | Z147: 版作成 | AD147: 面付数 | AH147: 版数 | AL147: 抜きｽﾞﾚ防止ﾏｰｸ | AP147: 面付番号 | AT147: 混入防止ﾏｰｸ
Z148: 0:ﾌｨﾙﾑ 1:ＣＴＰ | AL148: 1.要 2.不可 | AP148: 1.要 2.不可 | AT148: 1.要 2.不可
J150: 引当 | K150: 連絡 | V150: 材料 | AL150: 受給区分 | AT150: 受給単価 | BB150: 入庫先
D154: 80 | E154: 0450 | G154: オフセット印刷1 | J154: 04501 | K154: 製品情報 | O154: 40 | Q154: 外注：昭和堂 | V154: 原稿 | Z154: ｸﾚｰﾑ情報 | AD154: ｸﾚｰﾑ対象工程
V155: 0.ﾅｼ 1.原稿袋 2.図面ｼｽﾃﾑ | Z155: 0.ﾅｼ 1.ｱﾘ | AD155: 1.ＡＬＬ 2.備考欄
J157: 04502 | K157: オフセット印刷 | V157: 色数 | Z157: 色数割増 | AD157: 特色数 | AH157: ｲﾝｷ区分 | AL157: 針先
V158: 1 | AH158: 3.ＵＶ | AL158: 1.突
J160: 04503 | K160: ニス | V160: 壺ﾆｽ | Z160: ｺｰﾀｰﾆｽ | AD160: ｽﾎﾟｯﾄ
V161: 5:UVOP | Z161: 4.UVｸﾘｱ | AD161: 2.ｱｸｱｴﾝﾎﾞｽ
J163: 引当 | K163: 連絡 | V163: 材料 | AL163: 受給区分 | AT163: 受給単価 | BB163: 入庫先
...

Sheet Popupレイアウト
A1: =表紙!A54 -> Webシステム | K1: 文書名 | U1: モジュールID | Z1: =表紙!$AJ$63 -> MS | AE1: モジュール名 | AJ1: =表紙!$AX$63 -> 見積管理 | AS1: 文書番号 | AZ1: Version | BF1: Rev.
K2: =表紙!O64 -> アドオン設計書 | U2: ｻﾌﾞﾓｼﾞｭｰﾙID | Z2: =表紙!$AJ$64 -> MSBB | AE2: ｻﾌﾞﾓｼﾞｭｰﾙ名 | AJ2: =表紙!$AX$64 -> Webシステム | AS2: =表紙!$BL$64 -> M7-US-1140 | AZ2: =表紙!$BU$64 -> 7.0.2 | BF2: =表紙!$CB$64 -> 7
K3: =RIGHT(CELL("filename",$A$1),LEN(CELL("filename",$A$1))-FIND("]",CELL("filename",$A$1))) -> Popupレイアウト | U3: 表題 | Z3: =表紙!$AJ$65 -> MSBBPA070 | AE3: =表紙!$AQ$65 -> Web受注入力
A5: 画面イメージ
C9: 加工品の場合
CF11: CP指摘 2022/09/30 落合 シート受注用の工程選択ポップアップ画面イメージが必要 | DH11: MDSOL回答 石田 2022/10/27 対応致しました。
D12: 製品CD | G12: 0022108801 | N12: 得意先 | Q12: 095439 | AA12: 顧客品名 | AG12: もつ鍋化粧箱（海千様） | CF12: 対象工程のみに絞り込みされること | DI12: 工程一覧でシートの工程のみ選択できるように記載しております。
D13: 工程 | G13: 0110:片面コルゲータ | DH13: CP指摘 2022/10/29 落合 指摘内容は、製品マスタと同じ、工程選択のポップアップが必要という内容です。 | ER13: MDSOL回答 2022/10/31 | FC13: 承知しました。
ER14: 2022/11/01 落合 未対応
D15: WG／号機／発注先 | L15: 10 | P15: 5362：●●工業 | Z15: 号機変更不可 | AI15: □ | AK15: CP配送区分 | ER15: MDSOL回答 2022/11/04
ES16: 本シートの46行目より、シートの場合を記述足しております。
D17: ﾁｪｯｸ | F17: 作業 | N17: 仕様 | AP17: 版型 | AV17: 消耗品 | ES17: レイアウト シートには以下記述を記載しております。
N18: 仕様1 | R18: 仕様2 | V18: 仕様3 | Z18: 仕様4 | AD18: 仕様5 | AH18: 仕様6 | AL18: 仕様7 | ET18: ３ページ目：工程情報画面
N19: 工程備考１ | AD19: 工程備考２ | ET19: シート受注時のみ編集可能 工程選択は汎用マスタ.工程マスタのシート受注使用フラグが設定されているもののみ表示
D20: ☑ | F20: 1 | H20: 貼合 | R20: 全判巾 | V20: 全判流れ | Z20: 巾変更 | ET20: 行挿入・行削除ボタンは、シート受注時のみ表示
Z21: 1:不可 | ER21: 2022/11/07 落合
N22: 工程備考AAA | AD22: 工程備考BBB | ES22: 工程追加方法のイメージが大きく違っていたようです。
D23: ☑ | F23: 2 | H23: コルスリ | N23: 表巾 | R23: ｽﾘｯﾀｰ1巾 | V23: ｽﾘｯﾀｰ1流れ | Z23: ｽﾘｯﾀｰ2巾 | AD23: ｽﾘｯﾀｰ2流れ | AH23: ｺﾙｽﾘ | AL23: 割り数 | ES23: 以下の手順で良かったでしょうか？
ES24: １．工程情報画面の「行挿入」で空白行が出来る
N25: 工程備考AAA | AD25: 工程備考123456 | ES25: ２．「詳細入力」ボタン押下により、ポップアップ表示される
ES26: ３．工程を選択する
D27: 製造 | AD27: 外注 | AL27: 本支店 | ES27: ４．仕様を入力して「工程へ反映」で追加される
D28: ﾛｽ率(%) | I28: 10 | M28: 台数(枚) | Q28: 10 | U28: LT(日) | Y28: 10 | AD28: 仕入単価 | AH28: 2000 | AL28: 指値 | AP28: 1000 | ES28: 工程を選択するときに、工程の一覧表示はないのでしょうか？
ER29: MDSOL回答 2022/11/08 工程追加の手順は下記を想定しています。
ES30: １．工程情報画面の「行挿入」で空白行が出来る
D31: 入庫先 | H31: 名古屋合紙置き場 | ES31: ２．工程情報画面で工程を選択する(コンボボックスより選択)
ES32: ３．「詳細入力」ボタン押下により、ポップアップ表示される ※対象工程
D33: № | F33: 連産品 | P33: 数量比率 | S33: 次工程 | ES33: ４．作業選択、仕様を入力して「工程へ反映」で追加される
E34: 1 | F34: 連産品① | P34: 4 | ES34: 工程の一覧表示から選択するオペレーションでなく、上記手順１・２をする手順を想定しています。
E35: 2 | F35: 連産品② | P35: 2 | ER35: 2022/11/09 落合 問題ありませんが、POPUP内で工程を選択した方がユーザーにとっては使いやすいように思います。
E36: 3 | EX36: 工程と工程仕様はセットなので、入力する画面が分かれるのは違和感があります。
E37: 4 | EX37: POPUP内の工程表示がコンボボックスになっており、選択した工程の作業に切り替わるでは難しいでしょうか？
E38: 5 | ES38: MDSOL回答 2022/11/10
E39: 6 | ET39: 工程変更分の情報を保持・反映する必要が有り、難易度・作業ボリュームが変わるため、今回はこの形で進めさせてください。
ET40: ※上記を修正する場合、製品マスタも同修正が必要になるかと思います。
ER42: 2022/11/10 落合 打ち合わせ内でお伝えした通り、1工程ごとにポップアップを確定するという方法であれば可能と思います。
EX43: 再度ご確認をお願い致します。
ER45: MDSOL回答 2022/11/11
C46: シートの場合 | ET46: 開発元に確認中のためお待ちください。
D47: 製品CD | G47: 0022108801 | N47: 得意先 | Q47: 095439 | AA47: 顧客品名 | AG47: もつ鍋化粧箱（海千様）
D48: 工程 | G48: 0110:片面コルゲータ
D50: WG／号機／発注先 | L50: 10 | P50: 5362：●●工業 | Z50: 号機変更不可 | AI50: □ | AK50: CP配送区分
D52: ﾁｪｯｸ | F52: 作業 | N52: 仕様 | AP52: 版型 | AV52: 消耗品
N53: 仕様1 | R53: 仕様2 | V53: 仕様3 | Z53: 仕様4 | AD53: 仕様5 | AH53: 仕様6 | AL53: 仕様7
N54: 工程備考１ | AD54: 工程備考２
D55: ☑ | F55: 1 | H55: 貼合 | R55: 全判巾 | V55: 全判流れ | Z55: 巾変更
Z56: 1:不可
N57: 工程備考AAA | AD57: 工程備考BBB
D58: ☑ | F58: 2 | H58: コルスリ | N58: 表巾 | R58: ｽﾘｯﾀｰ1巾 | V58: ｽﾘｯﾀｰ1流れ | Z58: ｽﾘｯﾀｰ2巾 | AD58: ｽﾘｯﾀｰ2流れ | AH58: ｺﾙｽﾘ | AL58: 割り数
N60: 工程備考AAA | AD60: 工程備考123456
D62: 製造 | AD62: 外注 | AL62: 本支店
D63: ﾛｽ率(%) | I63: 10 | M63: 台数(枚) | Q63: 10 | U63: LT(日) | Y63: 10 | AD63: 仕入単価 | AH63: 2000 | AL63: 指値 | AP63: 1000
D66: 入庫先 | H66: 名古屋合紙置き場

Sheet 現行画面
A1: =表紙!A54 -> Webシステム | K1: 文書名 | U1: モジュールID | Z1: =表紙!$AJ$63 -> MS | AE1: モジュール名 | AJ1: =表紙!$AX$63 -> 見積管理 | AS1: 文書番号 | AZ1: Version | BF1: Rev.
K2: =表紙!O64 -> アドオン設計書 | U2: ｻﾌﾞﾓｼﾞｭｰﾙID | Z2: =表紙!$AJ$64 -> MSBB | AE2: ｻﾌﾞﾓｼﾞｭｰﾙ名 | AJ2: =表紙!$AX$64 -> Webシステム | AS2: =表紙!$BL$64 -> M7-US-1140 | AZ2: =表紙!$BU$64 -> 7.0.2 | BF2: =表紙!$CB$64 -> 7
K3: =RIGHT(CELL("filename",$A$1),LEN(CELL("filename",$A$1))-FIND("]",CELL("filename",$A$1))) -> 現行画面 | U3: 表題 | Z3: =表紙!$AJ$65 -> MSBBPA070 | AE3: =表紙!$AQ$65 -> Web受注入力
A5: 画面イメージ

Sheet 項目説明
A1: =表紙!A54 -> Webシステム | K1: 文書名 | U1: モジュールID | Z1: =表紙!$AJ$63 -> MS | AE1: モジュール名 | AJ1: =表紙!$AX$63 -> 見積管理 | AS1: 文書番号 | AZ1: Version | BF1: Rev.
K2: =表紙!O64 -> アドオン設計書 | U2: ｻﾌﾞﾓｼﾞｭｰﾙID | Z2: =表紙!$AJ$64 -> MSBB | AE2: ｻﾌﾞﾓｼﾞｭｰﾙ名 | AJ2: =表紙!$AX$64 -> Webシステム | AS2: =表紙!$BL$64 -> M7-US-1140 | AZ2: =表紙!$BU$64 -> 7.0.2 | BF2: =表紙!$CB$64 -> 7
K3: =RIGHT(CELL("filename",$A$1),LEN(CELL("filename",$A$1))-FIND("]",CELL("filename",$A$1))) -> 項目説明 | U3: 表題 | Z3: =表紙!$AJ$65 -> MSBBPA070 | AE3: =表紙!$AQ$65 -> Web受注入力
A5: 第1画面（TOP画面）
B6: 操作種別 | N6: 説明 | BE6: Ｗ | BF6: 型 | BG6: 参 | BH6: 必 | BI6: 入 | BJ6: 非 | BK6: 検 | BN6: 操作種別 | BY6: 最大入力文字数 | CK6: DB文字数 | CS6: mcframe項目名 | DB6: mcframeDB文字数
A7: ● | B7: 登録 | M7: 新規登録するモード。初期状態 | BE7: R | BN7: 登録
A8: ● | B8: 訂正 | M8: 訂正するモード | BE8: R | BN8: 訂正
A9: ● | B9: 削除 | M9: 削除するモード | BE9: R | BN9: 削除
A10: ● | B10: 参照 | M10: 参照するモード | BE10: R | BN10: 参照
B11: 検索 | N11: 説明 | BE11: Ｗ | BF11: 型 | BG11: 参 | BH11: 必 | BI11: 入 | BJ11: 非 | BK11: 検 | BN11: 検索 | BY11: 最大入力文字数 | CK11: DB文字数 | CS11: mcframe項目名 | DB11: mcframeDB文字数
A12: 〇 | B12: 受注区分 | M12: 【MSBBPACOM】_共通設計書_アドオン(共通ロジック)にて定義 | BE12: C | BF12: S | BH12: 必 | BN12: 受注区分
A13: 〇 | B13: 得意先 | M13: 【MSBBPACOM】_共通設計書_アドオン(共通ロジック)にて定義 | BE13: C | BF13: S | BH13: 必 | BN13: 製品区分(大)
A14: 〇 | B14: 手配NO | M14: 「登録」時、元手配№。 「訂正」「削除」「参照」の時、初期フォーカス 【MSBBPACOM】_共通設計書_アドオン(共通ロジック)にて定義 | BE14: A | BF14: S | BK14: 検 | BN14: 手配NO
B15: 基本情報 | N15: 説明 | BE15: Ｗ | BF15: 型 | BG15: 参 | BH15: 必 | BI15: 入 | BJ15: 非 | BK15: 検 | BN15: 基本情報 | BY15: 最大入力文字数 | CK15: DB文字数 | CS15: mcframe項目名 | DB15: mcframeDB文字数
A16: ● | B16: 受注部門 | M16: 受注部門を設定する※【MSBBPACOM】_共通設計書_アドオン(共通ロジック)にて定義 | BE16: C | BF16: S | BH16: 必 | BK16: 検 | BN16: 受注部門
A17: ● | B17: 受注日 | M17: 受注日を設定する | BE17: カ | BF17: D | BH17: 必 | BN17: 受注日
A18: ● | B18: 受注区分 | M18: 加工製品、加工商品、シート製品、購買品、原紙 ※【MSBBPACOM】_共通設計書_アドオン(共通ロジック)にて定義 | BE18: C | BF18: S | BN18: 受注区分
A19: ● | B19: 得意先 | M19: 得意先CDを設定する※【MSBBPACOM】_共通設計書_アドオン(共通ロジック)にて定義 | BE19: A | BF19: S | BH19: 必 | BK19: 検 | BN19: 得意先
A20: ● | B20: 客先納期 | M20: 客先納期を設定する | BE20: カ | BF20: D | BH20: 必 | BN20: 客先納期
A21: ● | B21: 数量 | M21: 受注数量を設定する | BE21: T | BF21: N | BN21: 数量 | BY21: 10,2 | CK21: 21,8 | DB21: 21,8
A22: ● | B22: 注文書No | M22: 顧客の注文書番号 | BE22: T | BF22: S | BN22: 注文書No | BY22: 20文字 | CK22: 20文字 | CS22: 得意先注文明細ＮＯ | DB22: 20文字
A23: ● | B23: 先方担当 | M23: 顧客の担当者 | BE23: T | BF23: S | BN23: 先方担当
A24: ● | B24: 宛名 | M24: 宛名 | BE24: T | BF24: S | BN24: 宛名
A25: ● | B25: 運送会社 | M25: 運送会社を設定する※【MSBBPACOM】_共通設計書_アドオン(共通ロジック)にて定義 | BE25: C | BF25: S | BK25: 検 | BN25: 運送会社
A26: ● | B26: 出荷日時 | M26: 出荷日を設定する※M：日付時分（フォーマットが「YYYY/MM/DD 」のデータ） | BE26: カ | BF26: D | BN26: 出荷日
A27: ● | B27: 出荷条件 | M27: 昼積み、夜積み、時間指定を設定する※【MSBBPACOM】_共通設計書_アドオン(共通ロジック)にて定義 | BE27: C | BF27: S | BN27: 出荷条件
A28: ● | B28: 売価区分 | M28: 売価区分を設定する※【MSBBPACOM】_共通設計書_アドオン(共通ロジック)にて定義 | BE28: C | BF28: S | BN28: 売価区分
B29: 検索(受注明細) | N29: 説明 | BE29: Ｗ | BF29: 型 | BG29: 参 | BH29: 必 | BI29: 入 | BJ29: 非 | BK29: 検 | BN29: 検索(受注明細) | BY29: 最大入力文字数 | CK29: DB文字数 | CS29: mcframe項目名 | DB29: mcframeDB文字数
A30: ● | B30: 製品CD | M30: ｾｯﾄ品目指定することで、以下の一覧に部材品目表示※【MSBBPACOM】_共通設計書_アドオン(共通ロジック)にて定義 | BE30: A | BF30: S | BK30: 検 | BN30: 製品CD
B31: 受注明細 | N31: 説明 | BE31: Ｗ | BF31: 型 | BG31: 参 | BH31: 必 | BI31: 入 | BJ31: 非 | BK31: 検 | BN31: 受注明細 | BY31: 最大入力文字数 | CK31: DB文字数 | CS31: mcframe項目名 | DB31: mcframeDB文字数
B32: № | M32: 行番号 | BF32: N | BN32: №
B33: 手配NO | M33: 自動設定 連番※【MSBBPACOM】_共通設計書_アドオン(共通ロジック)にて定義 | BF33: S | BN33: 手配NO | BY33: 8文字 | CK33: 15文字 | CS33: 手配NO1 | DB33: 15文字
A34: ● | B34: 製品CD/品目CD | M34: 製品CD OR 経費品目を設定する。購買受注の際に必須※【MSBBPACOM】_共通設計書_アドオン(共通ロジック)にて定義 | BE34: A | BF34: S | BN34: 製品CD/品目CD | BY34: 15文字 | CK34: 15文字 | DY34: Rev6.0 製品CD桁数見直し(15桁に変更)
B35: CP品名1 | M35: CP品名1を設定する。 | BF35: S | BN35: CP品名1
B36: CP品名2 | M36: CP品名2を設定する。 | BF36: S | BN36: CP品名2
A37: ● | B37: 数量 | M37: 数量を設定する | BE37: T | BF37: N | BN37: 数量 | BY37: 10,2 | CK37: 21,8 | CS37: 受注明細.取引単位数量 | DB37: 21,8
A38: ● | B38: 単位 | M38: 数量単位を設定する | BE38: C | BF38: S | BN38: 単位
B39: 特値 | M39: 単価が特値かどうか設定する | BE39: チ | BF39: F | BN39: 特値
A40: ● | B40: 個別単価 | M40: 個別の単価 | BE40: T | BF40: N | BN40: 個別単価 | BY40: 10,2 | CK40: 21,8 | CS40: 受注明細.単価 | DB40: 21,8
A41: ● | B41: ｾｯﾄ単価 | M41: セット売りでの単価。売価区分＝セットでかつ親部材の時のみ入力可とする。 子の場合はゼロ。 | BE41: T | BF41: N | BN41: ｾｯﾄ単価 | BY41: 10,2 | CK41: 21,8 | CS41: 受注明細.単価 | DB41: 21,8
A42: ● | B42: 単価単位 | M42: 単価単位 | BE42: T | BF42: N | BN42: 単価単位
A43: ● | B43: 客先納期 | M43: 客先納期を設定する。部材毎に編集可能。 | BE43: D | BN43: 客先納期
A44: ● | B44: 手配区分 | M44: 手配区分（在庫引当、手配依頼、仕入直送）※【MSBBPACOM】_共通設計書_アドオン(共通ロジック)にて定義 | BE44: カ | BF44: D | BH44: 必 | BN44: 手配区分
A45: ● | B45: 納品先 | M45: 納品先を設定する※【MSBBPACOM】_共通設計書_アドオン(共通ロジック)にて定義 | BE45: A | BF45: S | BK45: 検 | BN45: 納品先
B46: 納品先名 | M46: 納品先の名称 | BF46: S | BN46: 納品先名
B47: 物流グループ | M47: 物流グループを設定する | BF47: S | BN47: 物流グループ
A48: ● | B48: 預り売上 | M48: 預り売上（在庫がクラウンにある状態で売上する）の場合設定する。 | BE48: チ | BF48: F | BN48: 預り売上
B49: 売上理由 | M49: 0円時必須 | BE49: C | BF49: S | BN49: 売上理由
B50: 受注№/受注明細№ | M50: Webの主キー情報 | BF50: S | BN50: 受注№/受注明細№
B51: フッター | N51: 説明 | BE51: Ｗ | BF51: 型 | BG51: 参 | BH51: 必 | BI51: 入 | BJ51: 非 | BK51: 検 | BN51: フッター | BY51: 最大入力文字数 | CK51: DB文字数 | CS51: mcframe項目名 | DB51: mcframeDB文字数
B52: クリア | M52: 画面を初期化する | BE52: B | BN52: クリア
B53: 行コピー | M53: 受注明細(部材)選択行の下に行を複製追加する。手配NOは変更なしで預り売上の切替ができる。 | BE53: B | BN53: 行コピー
B54: 行追加 | M54: 受注明細(部材)選択行の下に行を追加する | BE54: B | BN54: 行追加
B55: 行削除 | M55: 受注明細(部材)選択行を削除する | BE55: B | BN55: 行削除
B56: ▲ | M56: 選択行を1行上に移動 | BE56: B | BN56: ▲
B57: ▼ | M57: 選択行を1行下に移動 | BE57: B | BN57: ▼
B58: 受注伝票 | M58: 受注伝票を出力する | BE58: B | BN58: 受注伝票
B59: 次画面 | M59: 第２画面へ遷移する | BE59: B | BN59: 次画面
A61: 第２画面(基本情報)
B62: 基本情報 | N62: 説明 | BE62: Ｗ | BF62: 型 | BG62: 参 | BH62: 必 | BI62: 入 | BJ62: 非 | BK62: 検 | BN62: 基本情報 | BY62: 最大入力文字数 | CK62: DB文字数 | CS62: mcframe項目名 | DB62: mcframeDB文字数
B63: 納品先 | M63: 納品先を設定する※シートの場合は納品先が入力できる※【MSBBPACOM】_共通設計書_アドオン(共通ロジック)にて定義 | BE63: A | BF63: S | BN63: 納品先
B64: 手配区分 | M64: 手配区分（在庫引当、手配依頼、仕入直送）※【MSBBPACOM】_共通設計書_アドオン(共通ロジック)にて定義 | BE64: C | BF64: S | BN64: 手配区分
B65: 預り売上 | M65: 預り売上（在庫がクラウンにある状態で売上する）の場合設定する。 | BF65: S | BN65: 預り売上
A66: ● | B66: 預り売上数 | M66: 預り売上数を設定する。 | BE66: T | BF66: S | BN66: 預り売上数 | BY66: 10,2 | CK66: 21,8 | CS66: 受注明細.取引単位数量 | DB66: 21,8 | DY66: Rev4.0 預り売上数の項目追加
A67: ● | B67: 出荷日時 | M67: 出荷日を設定する※M：日付時分（フォーマットが「YYYY/MM/DD 」のデータ） | BE67: カ | BF67: D | BN67: 出荷日
A68: ● | B68: 出荷条件 | M68: 昼積み、夜積み、時間指定を設定する※【MSBBPACOM】_共通設計書_アドオン(共通ロジック)にて定義 | BE68: C | BF68: S | BN68: 出荷条件
B69: 売上WG | M69: 売上担当のWGを設定する※【MSBBPACOM】_共通設計書_アドオン(共通ロジック)にて定義 | BE69: C | BF69: S | BN69: 売上WG | DY69: Rev5.0 売上WGの項目説明追加
B70: 受注区分 | M70: 受注区分を設定する※【MSBBPACOM】_共通設計書_アドオン(共通ロジック)にて定義 | BE70: C | BF70: S | BN70: 受注区分
B71: 製品区分_大 | M71: 製品区分_大を設定する。※【MSBBPACOM】_共通設計書_アドオン(共通ロジック)にて定義 | BE71: C | BF71: S | BN71: 製品区分_大
B72: 製品区分_中 | M72: 工程決定後に製品区分中を設定する※【MSBBPACOM】_共通設計書_アドオン(共通ロジック)にて定義 | BE72: C | BF72: S | BN72: 製品区分_中
B73: 製品区分_小 | M73: 工程決定後に製品区分小を設定する※【MSBBPACOM】_共通設計書_アドオン(共通ロジック)にて定義 | BE73: C | BF73: S | BN73: 製品区分_小
B74: 手配NO | M74: 手配NO１~３ 自動設定※【MSBBPACOM】_共通設計書_アドオン(共通ロジック)にて定義 | BF74: S | BN74: 手配NO
B75: 案件NO | M75: 案件NOを設定する。※【MSBBPACOM】_共通設計書_アドオン(共通ロジック)にて定義。入力・表示形式は、[案件№(親)-案件№(子)-案件№(部材)] ※案件№(親)＋’－’＋案件№(子)+’－’＋案件№(部材)でセットする | BF75: S | BN75: 案件NO(親) | BY75: 7文字 | CK75: 15文字 | CS75: 手配NO3 | DB75: 15文字 | DZ75: Rev2.0 説明変更 Rev5.0 レイアウトにあわせ位置変更
B76: 得意先 | M76: 得意先CD※【MSBBPACOM】_共通設計書_アドオン(共通ロジック)にて定義 | BE76: A | BF76: S | BN76: 得意先
B77: 得意先名 | M77: 得意先名称 | BF77: S | BN77: 得意先名
B78: 客先納期 | M78: 顧客の納期 | BF78: D | BN78: 客先納期
B79: 製品CD/品目CD | M79: 製品CD OR 経費品目を設定する※【MSBBPACOM】_共通設計書_アドオン(共通ロジック)にて定義 | BF79: S | BN79: 製品CD/品目CD
B80: 版型NO | M80: 購買受注時、版型NOを必須で指定する※【MSBBPACOM】_共通設計書_アドオン(共通ロジック)にて定義 | BF80: S | BN80: 版型NO
A81: ● | B81: 顧客品名１ | M81: 顧客呼称の品名１ | BF81: S | BN81: 顧客品名１ | BY81: 32文字 | CK81: 80文字 | CS81: 品目マスタ.品目別名３ | DB81: 100文字
A82: ● | B82: 顧客品名２ | M82: 顧客呼称の品名２ | BF82: S | BN82: 顧客品名２ | BY82: 12文字 | CK82: 80文字 | CS82: 品目マスタ.品目別名4 | DB82: 100文字
A83: ● | B83: CP品名1 | M83: CP呼称の品名１ | BF83: S | BN83: CP品名1 | BY83: 32文字 | CK83: 80文字 | CS83: 品目マスタ.品目別名1 | DB83: 100文字
A84: ● | B84: CP品名2 | M84: CP呼称の品名２ | BF84: S | BN84: CP品名2 | BY84: 12文字 | CK84: 80文字 | CS84: 品目マスタ.品目別名2 | DB84: 100文字
A85: ● | B85: 顧客注文№ | M85: 顧客の注文番号 | BF85: S | BN85: 顧客注文№
A86: ● | B86: 顧客品番 | M86: 顧客での品番 | BF86: S | BN86: 顧客品番
B87: FSC製品区分 | M87: FSC製品区分製品かどうか※【MSBBPACOM】_共通設計書_アドオン(共通ロジック)にて定義 | BF87: S | BN87: FSC製品区分 | DY87: Rev2.0 項目統合(FSC認証製品＝FSC製品区分)
B88: 食品安全 | M88: 1:FSSC22000※【MSBBPACOM】_共通設計書_アドオン(共通ロジック)にて定義 | BF88: S | BN88: 食品安全
A89: ● | B89: 納入予備 | M89: 納入時の予備 | BE89: T | BF89: S | BN89: 納入予備 | BY89: 10,2 | CK89: 21,8 | CS89: 受注明細.取引単位数量 | DB89: 21,8
A90: ● | B90: 営業サンプル | M90: 営業用のサンプル数 | BE90: T | BF90: S | BN90: 営業サンプル | BY90: 10,2 | CK90: 21,8 | CS90: 受注明細.取引単位数量 | DB90: 21,8
A91: ● | B91: 定数出荷 | M91: 定数での出荷が求めらるかどうか。※【MSBBPACOM】_共通設計書_アドオン(共通ロジック)にて定義 | BE91: T | BF91: N | BN91: 定数出荷
A92: ● | B92: 不適合手配NO | M92: 不適合があった手配NOを指定する。※【MSBBPACOM】_共通設計書_アドオン(共通ロジック)にて定義 | BE92: A | BF92: S | BK92: 検 | BN92: 不適合手配NO
A93: ● | B93: 売上可否 | M93: 売上できるかどうか（区分値：可、不可、商品込、社内）※【MSBBPACOM】_共通設計書_アドオン(共通ロジック)にて定義 | BE93: C | BF93: S | BN93: 売上可否
B94: 構成情報 | N94: 説明 | BE94: Ｗ | BF94: 型 | BG94: 参 | BH94: 必 | BI94: 入 | BJ94: 非 | BK94: 検 | BN94: 構成情報 | BY94: 最大入力文字数 | CK94: DB文字数 | CS94: mcframe項目名 | DB94: mcframeDB文字数
A95: ● | B95: シート段 | M95: B段、5号段、E段、F段、G段 段ボールの厚みの規格 【MSBBPACOM】_共通設計書_アドオン(共通ロジック)にて定義 | BE95: C | BF95: S | BH95: 必 | BN95: シート段
A96: ● | B96: 原紙コード(表) | M96: 表原紙の原紙コード 【MSBBPACOM】_共通設計書_アドオン(共通ロジック)にて定義 | BE96: A | BF96: S | BK96: 検 | BN96: 原紙コード(表)
A97: ● | B97: 印刷コード(表) | M97: 表原紙の印刷コード 【MSBBPACOM】_共通設計書_アドオン(共通ロジック)にて定義 | BE97: A | BF97: S | BK97: 検 | BN97: 印刷コード(表)
A98: ● | B98: エンボスコード(表) | M98: 表原紙のエンボスコード 【MSBBPACOM】_共通設計書_アドオン(共通ロジック)にて定義 | BE98: A | BF98: S | BK98: 検 | BN98: エンボスコード(表)
A99: ● | B99: メーカ（表） | M99: 表原紙のメーカーコード 【MSBBPACOM】_共通設計書_アドオン(共通ロジック)にて定義 | BE99: A | BF99: S | BK99: 検 | BN99: メーカ（表）
A100: ● | B100: 原紙コード(中) | M100: 中原紙の原紙コード 【MSBBPACOM】_共通設計書_アドオン(共通ロジック)にて定義 | BE100: A | BF100: S | BK100: 検 | BN100: 原紙コード(中)
A101: ● | B101: 印刷コード(中) | M101: 中原紙の印刷コード 【MSBBPACOM】_共通設計書_アドオン(共通ロジック)にて定義 | BE101: A | BF101: S | BK101: 検 | BN101: 印刷コード(中)
A102: ● | B102: エンボスコード(中) | M102: 中原紙のエンボスコード 【MSBBPACOM】_共通設計書_アドオン(共通ロジック)にて定義 | BE102: A | BF102: S | BK102: 検 | BN102: エンボスコード(中)
...

Sheet 引数説明
A1: =表紙!A54 -> Webシステム | K1: 文書名 | U1: モジュールID | Z1: =表紙!$AJ$63 -> MS | AE1: モジュール名 | AJ1: =表紙!$AX$63 -> 見積管理 | AS1: 文書番号 | AZ1: Version | BF1: Rev.
K2: =表紙!O64 -> アドオン設計書 | U2: ｻﾌﾞﾓｼﾞｭｰﾙID | Z2: =表紙!$AJ$64 -> MSBB | AE2: ｻﾌﾞﾓｼﾞｭｰﾙ名 | AJ2: =表紙!$AX$64 -> Webシステム | AS2: =表紙!$BL$64 -> M7-US-1140 | AZ2: =表紙!$BU$64 -> 7.0.2 | BF2: =表紙!$CB$64 -> 7
K3: =RIGHT(CELL("filename",$A$1),LEN(CELL("filename",$A$1))-FIND("]",CELL("filename",$A$1))) -> 引数説明 | U3: 表題 | Z3: =表紙!$AJ$65 -> MSBBPA070 | AE3: =表紙!$AQ$65 -> Web受注入力
B5: オペレーションＩＤ/名称：SloRecvIfImp_Upd01/取込
A6: 必 | B6: 項目名 | N6: 説明 | AS6: 未設定時の振る舞い
B7: 得意先ＣＤ | M7: 受注受信ＩＦの検索条件

Sheet 画面遷移
A1: =表紙!A54 -> Webシステム | K1: 文書名 | U1: モジュールID | Z1: =表紙!$AJ$63 -> MS | AE1: モジュール名 | AJ1: =表紙!$AX$63 -> 見積管理 | AS1: 文書番号 | AZ1: Version | BF1: Rev.
K2: =表紙!O64 -> アドオン設計書 | U2: ｻﾌﾞﾓｼﾞｭｰﾙID | Z2: =表紙!$AJ$64 -> MSBB | AE2: ｻﾌﾞﾓｼﾞｭｰﾙ名 | AJ2: =表紙!$AX$64 -> Webシステム | AS2: =表紙!$BL$64 -> M7-US-1140 | AZ2: =表紙!$BU$64 -> 7.0.2 | BF2: =表紙!$CB$64 -> 7
K3: =RIGHT(CELL("filename",$A$1),LEN(CELL("filename",$A$1))-FIND("]",CELL("filename",$A$1))) -> 画面遷移 | U3: 表題 | Z3: =表紙!$AJ$65 -> MSBBPA070 | AE3: =表紙!$AQ$65 -> Web受注入力
A5: ID | D5: 処理名 | Y5: ダブルクリック対象 | AH5: ダブルクリック処理条件
A6: S01 | D6: Web受注一覧照会から本画面遷移
B8: 遷移処理
B9: 遷移元画面ＩＤ | I9: MSBBPA080
B10: 遷移元画面名 | I10: Web受注一覧照会
B11: 遷移先画面ＩＤ | I11: MSBBPA070
B12: 遷移先画面名 | I12: Web受注入力
B13: 遷移条件 | I13: Web受注一覧照会画面の一覧表示部データから一つのみ選択の後、選択ボタンをクリックします
B14: 引継項目・種別 | I14: 遷移元画面項目 | AJ14: 遷移先画面項目
I15: WEB受注NO | AJ15: WEB受注NO
I16: WEB受注明細NO | AJ16: WEB受注明細NO
B18: 遷移後のアクション | I18: 操作種別が「参照」をします
B19: 備考
A21: ID | D21: 処理名
A22: S02 | D22: メニューから本画面遷移
B24: 遷移処理
B25: 遷移元画面ＩＤ | I25: なし
B26: 遷移元画面名 | I26: メニュー
B27: 遷移先画面ＩＤ | I27: MSBBPA070
B28: 遷移先画面名 | I28: Web受注入力
B29: 遷移条件 | I29: なし
B30: 引継項目・種別 | I30: 遷移元画面項目 | AJ30: 遷移先画面項目
I31: メンニュー一覧のkey | AJ31: なし
B34: 遷移後のアクション | I34: 画面を初期化して、操作種別が「登録」をします
B35: 備考

Sheet 処理概要
A1: =表紙!A54 -> Webシステム | K1: 文書名 | U1: モジュールID | Z1: =表紙!$AJ$63 -> MS | AE1: モジュール名 | AJ1: =表紙!$AX$63 -> 見積管理 | AS1: 文書番号 | AZ1: Version | BF1: Rev.
K2: =表紙!O64 -> アドオン設計書 | U2: ｻﾌﾞﾓｼﾞｭｰﾙID | Z2: =表紙!$AJ$64 -> MSBB | AE2: ｻﾌﾞﾓｼﾞｭｰﾙ名 | AJ2: =表紙!$AX$64 -> Webシステム | AS2: =表紙!$BL$64 -> M7-US-1140 | AZ2: =表紙!$BU$64 -> 7.0.2 | BF2: =表紙!$CB$64 -> 7
K3: =RIGHT(CELL("filename",$A$1),LEN(CELL("filename",$A$1))-FIND("]",CELL("filename",$A$1))) -> 処理概要 | U3: 表題 | Z3: =表紙!$AJ$65 -> MSBBPA070 | AE3: =表紙!$AQ$65 -> Web受注入力
A5: No | B5: 入力 | J5: 処理 | BD5: 出力
A6: ０ | B6: 構成・工程編集可の判定処理
J7: １．構成・工程編集可の判定処理は以下の形で判定する。 | BM7: REV7.0 受注画面制御の追加
N8: 補足受注画面制御で構成・工程が編集可となっている受注区分、製品区分、品目採番の組合せの場合 | BM8: REV7.0 受注画面制御の追加
O9: 構成・工程編集可 | BM9: REV7.0 受注画面制御の追加
N10: それ以外の場合 | BM10: REV7.0 受注画面制御の追加
O11: 構成・工程編集不可 | BM11: REV7.0 受注画面制御の追加
K12: 以後、設計書内では構成・工程編集可の場合、構成・工程編集可以外の場合と記する。 | BM12: REV7.0 受注画面制御の追加
BM13: REV7.0 受注画面制御の追加
A14: 1 | B14: 検索（手配NO）
J15: １．検索処理
K16: 検索入出力仕様に従い検索を行う | BD16: 検索入出力仕様２
N17: 検索条件
N18: 項目名 | W18: 設定値
N19: 手配NO１ | W19: 画面.手配NO１
N20: 手配NO２ | W20: 画面.手配NO２
N21: 手配NO３ | W21: 画面.手配NO３
K23: 登録モードで検索した場合、参照モード→登録モードに切り替えた場合に以下項目をクリアする。 | BM23: REV3.0 過去受注をコピーした時に、セットしたくない項目がある
K24: 受注日・客納期・出荷時間・個別単価・セット単価・得値区分・金額・預り売上・預り理由・顧客注文№・不適合受注№・再製造備考 | BM24: REV3.0 過去受注をコピーした時に、セットしたくない項目がある
A26: ２ | B26: 検索（製品CD）
J28: １．検索処理
K29: 検索入出力仕様に従い検索を行う
BD30: 検索入出力仕様1
N31: 検索条件
N32: 項目名 | W32: 設定値
N33: 製品CD | W33: 画面.製品CD
L34: OR | N34: セット品CD | W34: 画面.製品CD
A36: ３ | B36: 受注区分変更処理
J38: １．受注区分変更処理
K39: 受注区分が変更された場合以下処理を行う。
K40: 1-1)受注区分が加工製品、加工商品、原紙の場合 | BM40: REV4.0 行コピーの有効条件追加
L41: 受注明細欄を表示する | BM41: REV4.0 行コピーの有効条件追加
L42: 行コピーを無効にする。 | BM42: REV4.0 行コピーの有効条件追加
L43: 1-1-1)受注区分：原紙の場合 | BM43: REV4.0 行コピーの有効条件追加
M44: 行コピーを有効にする。 | BM44: REV4.0 行コピーの有効条件追加
K45: 1-2)受注区分がそれ以外
L46: 受注明細欄を非表示にする
A47: ４ | B47: クリアボタン押下
J48: １）クリア処理
L49: 一覧や入力項目の内容をクリアし、種別選択をした状態へ戻す。
A51: ５ | B51: 行コピーボタン押下
J52: １）一覧の選択行＋１の番号で一覧に選択行の挿入を行う。
A54: ６ | B54: 行追加ボタン押下
J55: １）一覧の選択行＋１の番号で一覧に空行の挿入を行う。
A57: ７ | B57: 行削除ボタン押下
J58: １）一覧の選択行を削除する
A60: ８ | B60: △ボタン押下
J61: １）一覧の選択行を上の行と入れ替える。1行目の場合は何もしない。
A63: ９ | B63: ▽ボタン押下
J64: １）一覧の選択行を下の行と入れ替える。1行目の場合は何もしない。
A66: 10 | B66: 次画面（TOP画面）
J68: 0．遷移前処理
L69: 0-1)客先納期チェック
M70: 構成・工程編集可以外の場合 | BM70: REV7.0 受注画面制御の追加
N71: 製品CDで製品加工工程マスタ.LTを取得しレコード分を合計＝合計LT
N72: 客先納期日-受注日＜合計LTであればエラーとする。 | BD72: メッセージ一覧.1
L73: 0-2)画面情報を配列に保持する。
J75: １．遷移処理
L76: 新規の場合、TOP画面の情報と製品基本マスタを検索する。 | BD76: 検索入出力仕様3
L77: 新規以外の場合、受注明細を検索する。 | BD77: 検索入出力仕様6
L78: 基本情報画面へ遷移を行う
A80: １１ | B80: 次画面（基本情報）
J82: 0．遷移前処理
L83: 0-1)客先納期チェック
M84: 構成・工程編集可以外の場合 | BM84: REV7.0 受注画面制御の追加
N85: 客先納期日-受注日＜受注加工.標準LT合計であればエラーとする。 | BD85: メッセージ一覧.1
L86: ０-2）画面情報を配列に保持する
J88: １．遷移処理
L89: 1-1)新規の場合、製品加工工程マスタを検索する。 | BD89: 検索入出力仕様4
L90: 1-2)新規以外の場合、受注加工工程を検索する。 | BD90: 検索入出力仕様7
L91: 1-3)加工予定日の算出処理
M92: 工程の並びの降順に、出荷日時よりLT(日）の値を営業日として工程順に減算した日付を加工用予定日にセットする。
M93: 営業日→実日数の換算はmcframe7の拠点（WG）別カレンダマスタを元に計算する。
L94: WGは最終工程のWGとする。
L95: 工程情報画面へ遷移を行う
A98: １２ | B98: 戻るボタン押下（基本情報、工程情報、材料設定）
J99: ０）画面入力情報を配列に保持する。
J100: １）前画面へ戻る。
A102: １３ | B102: 工程挿入（工程情報）
J103: １）選択工程の一行下に工程行を追加する
A105: １４ | B105: 工程削除（工程情報）
J106: １）選択工程を削除する
A108: １５ | B108: 詳細入力（工程情報）
J109: １）選択工程の情報をPOPUP画面へ設定する。
K110: 1-1)工程がトムソンの場合、連産品表を表示する
K111: 1-2)それ以外の場合、連産品表を非表示にする
A113: １６ | B113: 作業挿入（POPUP）
J114: １）選択作業の一行下に作業行を追加する
A116: １７ | B116: 作業削除（POPUP）
J117: １）選択作業を削除する
A119: １８ | B119: 行挿入（POPUP）
J120: １）選択行の一行下に行を追加する
A122: １９ | B122: 行削除（POPUP）
J123: １）選択行を削除する
A125: ２０ | B125: 工程仕様変更時
J126: １）割り数設定
K127: 仕様に割り数がある場合、（全判巾÷ｽﾘｯﾀｰ巾）×（全判流れ÷ｽﾘｯﾀｰ流れ）＝割り数として割り数に値を自動設定する。
...

Sheet 処理詳細
A1: =表紙!A54 -> Webシステム | K1: 文書名 | U1: モジュールID | Z1: =表紙!$AJ$63 -> MS | AE1: モジュール名 | AJ1: =表紙!$AX$63 -> 見積管理 | AS1: 文書番号 | AZ1: Version | BF1: Rev.
K2: =表紙!O64 -> アドオン設計書 | U2: ｻﾌﾞﾓｼﾞｭｰﾙID | Z2: =表紙!$AJ$64 -> MSBB | AE2: ｻﾌﾞﾓｼﾞｭｰﾙ名 | AJ2: =表紙!$AX$64 -> Webシステム | AS2: =表紙!$BL$64 -> M7-US-1140 | AZ2: =表紙!$BU$64 -> 7.0.2 | BF2: =表紙!$CB$64 -> 7
K3: =RIGHT(CELL("filename",$A$1),LEN(CELL("filename",$A$1))-FIND("]",CELL("filename",$A$1))) -> 処理詳細 | U3: 表題 | Z3: =表紙!$AJ$65 -> MSBBPA070 | AE3: =表紙!$AQ$65 -> Web受注入力
A5: No | B5: 入力 | J5: 処理 | BD5: 出力
A6: 0 | B6: 構成・工程編集可の判定処理
J7: 0．構成・工程編集可の判定処理は以下の形で判定する。
N8: 補足受注画面制御で構成・工程が編集可となっている受注区分、製品区分、品目採番の組合せの場合
O9: 構成・工程編集可
N10: それ以外の場合
O11: 構成・工程編集不可
K12: 以後、設計書内では構成・工程編集可の場合、構成・工程編集可以外の場合と記する。
K14: ※ | L14: ファンクション作成、画面項目入力し、調用する。
A16: １ | B16: 初期表示 | J16: TOP画面
J17: 1.1 | L17: 遷移元メニューから
L18: 操作種別 | P18: ： | Q18: 「登録」を設定する
L19: その他 | P19: ： | Q19: 活性とする、各項目のクリア処理と初期値設定を行う
J21: 1.2 | L21: 遷移元【MSBBPA080】_Web受注一覧照会から
L22: 操作種別 | P22: ： | Q22: 「参照」を設定する
L23: 操作種別以外、全画面が非活性とする
A25: 2 | B25: 画面操作 | J25: TOP画面
J26: 2.1 | L26: 操作種別ボタンの制御処理
K27: 2.1.1 | N27: [操作種別]ラジオが「登録」の場合、
N28: 受注区分、得意先、手配NOは編集不可、 受注伝票ボタンが非活性を設定する。その以外、編集可、ボタンが活性を設定する。
N30: 参照モード→登録モードに切り替えた場合に以下項目をクリアする。
N31: 受注日・客納期・出荷時間・個別単価・セット単価・得値区分・金額・預り売上・預り理由・顧客注文№・不適合受注№・再製造備考
K33: 2.1.2 | N33: [操作種別]が「訂正」の場合、
N34: 受注伝票発行ボタンが非活性を設定する。その以外、編集可、ボタンが活性を設定する。
K36: 2.1.3 | N36: [操作種別]が「削除」の場合、
N37: 受注区分、得意先、手配NOは編集可、次画面ボタン、登録ボタンが活性を設定する。その以外、編集不可、ボタンが非活性を設定する。
K39: 2.1.4 | N39: [操作種別]が「参照」の場合、
N40: 受注区分、得意先、手配NOは編集可、次画面ボタン、受注伝票ボタンが活性を設定する。その以外、編集不可、ボタンが非活性を設定する。
N42: ※操作種別切り替え処理は、以下の通りです。
N53: ※ | O53: 手配NOが「訂正」「削除」「参照」の時、初期フォーカスを設定する。
J55: 2.2 | L55: 受注区分変更処理
L56: 受注区分が変更された場合以下処理を行う。
L58: 2.2.1 | N58: 受注区分が加工製品、加工商品、原紙の場合
N59: 基本情報.受注明細欄を表示する
N60: 行コピーを無効にする。
N61: 1-1-1)受注区分：原紙の場合
O62: 行コピーを有効にする。
L64: 2.2.2 | N64: 受注区分がそれ以外
N65: 基本情報.受注明細欄を非表示にする
J67: 2.3 | L67: 工程仕様変更時
L68: 割り数設定
L69: 仕様に割り数がある場合、（全判巾÷ｽﾘｯﾀｰ巾）×（全判流れ÷ｽﾘｯﾀｰ流れ）＝割り数として割り数に値を自動設定する。
L70: ない場合は何もしない。
J72: 2.4 | L72: 得意先指定時（TOP画面、基本画面）
L73: 2.4.1 | N73: 得意先を指定した場合、以下処理を実行する。
N74: 1) | O74: 与信限度額チェック
O75: 得意先の与信管理先から与信残高を取得する。（mcf受注入力の与信残高取得処理を実行）
O76: 与信残高が既に超過している場合メッセージを表示する。 | BD76: メッセージNo.2
J78: 2.5 | L78: 受注パタンでの処理
M79: 購買品・商品(構成無し)の場合、第２画面までの入力となる
J81: 2.6 | M81: シートの場合
N82: 製品マスタと同様に３ページ目：工程情報画面以降の入力が可能となります。
M83: シート以外の場合
N84: 製品マスタの情報から変更不可。
M85: ※工程備考のみ入力可能
J87: 2.7 | L87: 下記の編集ボタンは、シート受注のみ使用可能と設定
L88: ※ | M88: シート受注以外、工程、作業、材料情報は製品マスタから引き継ぐ情報を、常に参照モードにする。
M89: ・ | N89: 工程挿入（工程情報）
M90: ・ | N90: 工程削除（工程情報）
M91: ・ | N91: 作業挿入（POPUP）
M92: ・ | N92: 作業削除（POPUP）、
M93: ・ | N93: 行挿入（POPUP）
M94: ・ | N94: 行削除（POPUP）
M95: ・ | N95: 行挿入（材料設定） | Y95: 共通処理（CP配送区分設定処理）を実行する。
M96: ・ | N96: 行削除（材料設定）
A98: 3 | B98: 検索 | J98: TOP画面
J99: 3.1 | L99: コンボボックスの初期化
L100: 【定数マスタ】のタイプによって、取得したデータを画面の毎コンボボックスに設定する
L101: 以下コンボボックスについて、【MSBBPACOM】_共通設計書_アドオン(Webシステム共通仕様)の「処理詳細(共通検索)」シート」を参照する。 | R101: 加工製品、加工商品、シート製品、購買品、原紙を設定する。（定数マスタが設定する。）
L102: ※ | M102: シート受注の場合、製品マスタ画面と同様な仕様で実装
M103: ・ | N103: 受注区分 | AH103: ・ | AI103: 売価区分
M104: ・ | N104: 製品区分(大) | AH104: ・ | AI104: 親子区分
M105: ・ | N105: 製品区分(中) | AH105: ・ | AI105: FSC製品区分(認証製品)
M106: ・ | N106: 製品区分(小) | AH106: ・ | AI106: FSC材質区分
M107: ・ | N107: シート段 | AH107: ・ | AI107: 製品用途
M108: ・ | N108: 枚葉印刷 | AH108: ・ | AI108: 機密情報
M109: ・ | N109: 最終機械工程 | AH109: ・ | AI109: 品質区分
M110: ・ | N110: 製品形状 | AH110: ・ | AI110: 奪取区分
M111: ・ | N111: 物流区分 | AH111: ・ | AI111: TKP折れシワ基準
M112: ・ | N112: AD（形状） | AH112: ・ | AI112: 食品安全
M113: ・ | N113: Mチェン | AH113: ・ | AI113: 容リ支払
M114: ・ | N114: 重要度(重要区分) | AH114: ・ | AI114: 識別表示
... M120: ・ | N120: 出荷条件 | AH120: ・ | AI120: 運賃請求
M122: 購買品受注の時に、発注単価が入力必須を設定する、発注単価以外の項目、レイアウトシート参照する。
M124: ※ | N124: シートかどうかの判定処理は以下の形で判定する。
N125: 受注区分：シート製品の場合 → シート
R126: それ以外の場合 → シート以外
L128: 出荷条件コンボボックスの初期化
R129: 昼積み、夜積み、時間指定を設定する。（定数マスタが設定する。）
L131: 売価区分コンボボックスの初期化
R132: 汎用マスタの売価区分を設定する。
J134: 3.2 | L134: 得意先の検索ボタン処理
L135: 取引先マスタ検索のポップアップ画面へを遷移して、抽出条件＜取引先コード＞あるいは、＜取引先名＞をもとに結果を表示したところ、
L136: 選択結果(1行)を遷移元画面（本画面の得意先コード、得意先名を設定）に返す
M138: ※ | N138: 得意先検索_SQLリソースの検索仕様
N139: 【MSBBPACOM】_共通設計書_アドオン(Web共通ロジック)の「処理詳細(共通検索)」シート」を参照する。
J141: 3.3 | L141: 手配NOの検索ボタン処理
...

Sheet 画面項目制御
B2: 第1画面（TOP画面）
J3: 操作種別 | O3: 登録 | R3: 訂正 | U3: 削除 | X3: 参照 | AA3: 登録後 | AD3: 削除後 | AH3: R | AJ3: 有効(必須)
B4: 画面項目 | AA4: 訂正後 | AH4: E | AJ4: 有効
B5: 検索 | G5: 受注区分 | O5: R | R5: R | U5: R | X5: R | AA5: R | AD5: R | AH5: RO | AJ5: 読取のみ
G6: 得意先 | O6: R | R6: R | U6: R | X6: R | AA6: R | AD6: R | AH6: D | AJ6: 無効
G7: 手配NO | O7: E | R7: E | U7: E | X7: E | AA7: E | AD7: E | AH7: I | AJ7: 非表示
B8: 基本情報 | G8: 受注部門 | O8: R | R8: R | U8: RO | X8: RO | AA8: RO | AD8: RO
G9: 受注日 | O9: R | R9: R | U9: RO | X9: RO | AA9: RO | AD9: RO
G10: 受注区分 | O10: E | R10: E | U10: RO | X10: RO | AA10: RO | AD10: RO
G11: 得意先 | O11: R | R11: R | U11: RO | X11: RO | AA11: RO | AD11: RO
G12: 客先納期 | O12: R | R12: R | U12: RO | X12: RO | AA12: RO | AD12: RO
G13: 数量 | O13: E | R13: E | U13: RO | X13: RO | AA13: RO | AD13: RO
G14: 注文書No | O14: E | R14: E | U14: RO | X14: RO | AA14: RO | AD14: RO
G15: 先方担当 | O15: E | R15: E | U15: RO | X15: RO | AA15: RO | AD15: RO
G16: 宛名 | O16: E | R16: E | U16: RO | X16: RO | AA16: RO | AD16: RO
G17: 運送会社 | O17: E | R17: E | U17: RO | X17: RO | AA17: RO | AD17: RO
G18: 出荷日時 | O18: E | R18: E | U18: RO | X18: RO | AA18: RO | AD18: RO
G19: 出荷条件 | O19: E | R19: E | U19: RO | X19: RO | AA19: RO | AD19: RO
G20: 売価区分 | O20: E | R20: E | U20: RO | X20: RO | AA20: RO | AD20: RO
B21: 検索(受注明細) | G21: 製品CD | O21: E | R21: E | U21: D | X21: D | AA21: D | AD21: D
B22: 受注明細 | G22: № | O22: RO | R22: RO | U22: RO | X22: RO | AA22: RO | AD22: RO
G23: 手配NO | O23: RO | R23: RO | U23: RO | X23: RO | AA23: RO | AD23: RO
G24: 案件NO | O24: RO | R24: RO | U24: RO | X24: RO | AA24: RO | AD24: RO
G25: 製品CD/品目CD | O25: E/R | R25: E/R | U25: RO | X25: RO | AA25: RO | AD25: RO
G26: CP品名1 | O26: RO | R26: RO | U26: RO | X26: RO | AA26: RO | AD26: RO
G27: CP品名2 | O27: RO | R27: RO | U27: RO | X27: RO | AA27: RO | AD27: RO
G28: 数量 | O28: E | R28: E | U28: RO | X28: RO | AA28: RO | AD28: RO
G29: 単位 | O29: E | R29: E | U29: RO | X29: RO | AA29: RO | AD29: RO
G30: 特値 | O30: RO | R30: RO | U30: RO | X30: RO | AA30: RO | AD30: RO
G31: 個別単価 | O31: E | R31: E | U31: RO | X31: RO | AA31: RO | AD31: RO
G32: ｾｯﾄ単価 | O32: E | R32: E | U32: RO | X32: RO | AA32: RO | AD32: RO
G33: 単価単位 | O33: E | R33: E | U33: RO | X33: RO | AA33: RO | AD33: RO
G34: 客先納期 | O34: E | R34: E | U34: RO | X34: RO | AA34: RO | AD34: RO
... G41: 受注№/受注明細№ | O41: RO | R41: RO | U41: RO | X41: RO | AA41: RO | AD41: RO
B42: フッター | G42: クリア | O42: E | R42: E | U42: RO | X42: RO | AA42: RO | AD42: RO
G43: 行コピー | O43: E | R43: E | U43: RO | X43: RO | AA43: RO | AD43: RO
G44: 行追加 | O44: E | R44: E | U44: RO | X44: RO | AA44: RO | AD44: RO
G45: 行削除 | O45: E | R45: RO | U45: RO | X45: RO | AA45: RO | AD45: RO
G46: ▲ | O46: E | R46: E | U46: RO | X46: RO | AA46: RO | AD46: RO
G47: ▼ | O47: E | R47: E | U47: RO | X47: RO | AA47: RO | AD47: RO
G48: 受注伝票 | O48: E | R48: E | U48: RO | X48: E | AA48: E | AD48: RO
G49: 次画面 | O49: E | R49: E | U49: E | X49: E | AA49: RO | AD49: RO
B53: 第２画面(基本情報)
J54: 操作種別 | O54: 登録 | R54: 訂正 | U54: 削除 | X54: 参照
B55: 画面項目
B56: 基本情報 | G56: 納品先 | O56: RO | R56: RO | U56: RO | X56: RO
G57: 手配区分 | O57: RO | R57: RO | U57: RO | X57: RO
G58: 預り売上 | O58: RO | R58: RO | U58: RO | X58: RO
G59: 出荷日時 | O59: E | R59: E | U59: RO | X59: RO
G60: 出荷条件 | O60: E | R60: E | U60: RO | X60: RO
G61: 受注区分 | O61: RO | R61: RO | U61: RO | X61: RO
G62: 製品区分_大 | O62: RO | R62: RO | U62: RO | X62: RO
G63: 製品区分_中 | O63: RO | R63: RO | U63: RO | X63: RO
G64: 製品区分_小 | O64: RO | R64: RO | U64: RO | X64: RO
G65: 手配NO | O65: RO | R65: RO | U65: RO | X65: RO
G66: 得意先 | O66: RO | R66: RO | U66: RO | X66: RO
G67: 得意先名 | O67: RO | R67: RO | U67: RO | X67: RO
G68: 客先納期 | O68: RO | R68: RO | U68: RO | X68: RO
... G83: 売上可否 | O83: E | R83: E | U83: RO | X83: RO
B84: 構成情報 | G84: シート段 | O84: R | R84: R | U84: RO | X84: RO
G85: 原紙コード(表) | O85: E | R85: E | U85: RO | X85: RO
G86: 印刷コード(表) | O86: E | R86: E | U86: RO | X86: RO
G87: エンボスコード(表) | O87: E | R87: E | U87: RO | X87: RO
G88: メーカ（表） | O88: E | R88: E | U88: RO | X88: RO
G89: 原紙コード(中) | O89: E | R89: E | U89: RO | X89: RO
G90: 印刷コード(中) | O90: E | R90: E | U90: RO | X90: RO
G91: エンボスコード(中) | O91: E | R91: E | U91: RO | X91: RO
G92: メーカ（中） | O92: E | R92: E | U92: RO | X92: RO
G93: 原紙コード(裏) | O93: E | R93: E | U93: RO | X93: RO
G94: 印刷コード(裏) | O94: E | R94: E | U94: RO | X94: RO
G95: エンボスコード(裏) | O95: E | R95: E | U95: RO | X95: RO
G96: メーカ（裏） | O96: E | R96: E | U96: RO | X96: RO
... G112: 特値 | O112: E | R112: E | U112: RO | X112: RO
B113: 仕入情報 | G113: 巻きM | O113: E | R113: E | U113: RO | X113: RO
G114: 単価単位 | O114: E | R114: E | U114: RO | X114: RO
G115: 発注単価 | O115: E | R115: E | U115: RO | X115: RO
G116: 発注先 | O116: E | R116: E | U116: RO | X116: RO
G117: 発注先名 | O117: RO | R117: RO | U117: RO | X117: RO
B118: 備考 | G118: 印刷備考 | O118: E | R118: E | U118: RO | X118: RO
G119: 製造備考 | O119: E | R119: E | U119: RO | X119: RO
G120: 再製造備考 | O120: E | R120: E | U120: RO | X120: RO
G121: 伝票備考 | O121: E | R121: E | U121: RO | X121: RO
G122: 納入備考 | O122: E | R122: E | U122: RO | X122: RO
G123: 出荷備考１ | O123: E | R123: E | U123: RO | X123: RO
G124: 出荷備考２ | O124: E | R124: E | U124: RO | X124: RO
B125: フッター | G125: 戻る | O125: E | R125: E | U125: E | X125: E
G126: 受注伝票 | O126: E | R126: E | U126: D | X126: E
G127: 次画面 | O127: E | R127: E | U127: E | X127: E
B131: 第３画面(工程情報)
J132: 操作種別 | O132: 登録 | R132: 訂正 | U132: 削除 | X132: 参照
B133: 画面項目
B134: ヘッダー | G134: 製品CD | O134: RO | R134: RO | U134: RO | X134: RO
G135: 得意先 | O135: RO | R135: RO | U135: RO | X135: RO
G136: 顧客品名 | O136: RO | R136: RO | U136: RO | X136: RO
G137: 出荷日時 | O137: RO | R137: RO | U137: RO | X137: RO
B138: 工程情報 | G138: 工程 | O138: RO | R138: RO | U138: RO | X138: RO
G139: 工程名 | O139: RO | R139: RO | U139: RO | X139: RO
G140: 作業 | O140: RO | R140: RO | U140: RO | X140: RO
G141: 作業名 | O141: RO | R141: RO | U141: RO | X141: RO
G142: WG | O142: RO | R142: RO | U142: RO | X142: RO
...

Sheet 処理・サービス関連図
A1: =表紙!A54 -> Webシステム | K1: 文書名 | U1: モジュールID | Z1: =表紙!$AJ$63 -> MS | AE1: モジュール名 | AJ1: =表紙!$AX$63 -> 見積管理 | AS1: 文書番号 | AZ1: Version | BF1: Rev.
K2: =表紙!O64 -> アドオン設計書 | U2: ｻﾌﾞﾓｼﾞｭｰﾙID | Z2: =表紙!$AJ$64 -> MSBB | AE2: ｻﾌﾞﾓｼﾞｭｰﾙ名 | AJ2: =表紙!$AX$64 -> Webシステム | AS2: =表紙!$BL$64 -> M7-US-1140 | AZ2: =表紙!$BU$64 -> 7.0.2 | BF2: =表紙!$CB$64 -> 7
K3: =RIGHT(CELL("filename",$A$1),LEN(CELL("filename",$A$1))-FIND("]",CELL("filename",$A$1))) -> 処理・サービス関連図 | U3: 表題 | Z3: =表紙!$AJ$65 -> MSBBPA070 | AE3: =表紙!$AQ$65 -> Web受注入力
C7: 検索処理
BM9: REV5.0 製品基本マスタ重複削除
C26: 更新処理
C36: ファイル出力処理
C46: シート受注、原紙工程ありの場合
C51: ファイル出力処理
BM58: REV5.0 品目単位マスタ追加

Sheet 検索入出力仕様
A1: =表紙!A54 -> Webシステム | K1: 文書名 | U1: モジュールID | Z1: =表紙!$AJ$63 -> MS | AE1: モジュール名 | AJ1: =表紙!$AX$63 -> 見積管理 | AS1: 文書番号 | AZ1: Version | BF1: Rev.
K2: =表紙!O64 -> アドオン設計書 | U2: ｻﾌﾞﾓｼﾞｭｰﾙID | Z2: =表紙!$AJ$64 -> MSBB | AE2: ｻﾌﾞﾓｼﾞｭｰﾙ名 | AJ2: =表紙!$AX$64 -> Webシステム | AS2: =表紙!$BL$64 -> M7-US-1140 | AZ2: =表紙!$BU$64 -> 7.0.2 | BF2: =表紙!$CB$64 -> 7
K3: =RIGHT(CELL("filename",$A$1),LEN(CELL("filename",$A$1))-FIND("]",CELL("filename",$A$1))) -> 検索入出力仕様 | U3: 表題 | Z3: =表紙!$AJ$65 -> MSBBPA070 | AE3: =表紙!$AQ$65 -> Web受注入力
A5: No | G5: 1 | S5: ボタン | Z5: 製品CD | AH5: 備考 | AK5: セット製品CD選択時の部材一覧へのセット処理
A6: 処理分類 | E6: 検索 | S6: ソート順
A7: No | C7: 転送先 | V7: 転送元 | AQ7: 説明
C8: 種 | D8: オブジェクト | K8: 項目名 | V8: 種 | W8: オブジェクト | AF8: 項目名
C9: 画 | D9: 第1画面 | G9: 部材一覧 | K9: 製品CD | V9: T | W9: 製品基本マスタ | AF9: 製品コード | BM9: REV5.0 製品マスタ → 製品基本マスタ
C10: 画 | D10: 第1画面 | G10: 部材一覧 | K10: 製品名 | V10: T | W10: 製品基本マスタ | AF10: 顧客品名 | BM10: REV5.0 製品マスタ → 製品基本マスタ
C11: 画 | D11: 第1画面 | G11: 部材一覧 | K11: 単位 | V11: T | W11: 製品基本マスタ | AF11: 数量単位 | BM11: REV5.0 製品マスタ → 製品基本マスタ
C12: 画 | D12: 第1画面 | G12: 部材一覧 | K12: 個別単価 | V12: T | W12: 製品基本マスタ | AF12: 現_セット単価 | BM12: REV5.0 製品マスタ → 製品基本マスタ
C13: 画 | D13: 第1画面 | G13: 部材一覧 | K13: ｾｯﾄ単価 | V13: T | W13: 製品基本マスタ | AF13: 現_個別単価 | BM13: REV5.0 製品マスタ → 製品基本マスタ
A15: No | G15: 2 | S15: ボタン | Z15: 手配NO | AH15: 備考 | AK15: 登録、訂正・削除・参照時の画面セット処理
A16: 処理分類 | E16: 検索 | S16: ソート順
A17: No | C17: 転送先 | V17: 転送元 | AQ17: 説明
C18: 種 | D18: オブジェクト | K18: 項目名 | V18: 種 | W18: オブジェクト | AF18: 項目名
C19: 画 | D19: 第1画面 | G19: 基本情報 | K19: 受注部門 | V19: T | W19: 受注 | AF19: 受注部門
C20: 画 | D20: 第1画面 | G20: 基本情報 | K20: 受注日 | V20: T | W20: 受注 | AF20: 受注日
C21: 画 | D21: 第1画面 | G21: 基本情報 | K21: 受注区分 | V21: T | W21: 受注 | AF21: 受注区分
C22: 画 | D22: 第1画面 | G22: 基本情報 | K22: 得意先 | V22: T | W22: 受注 | AF22: 得意先
C23: 画 | D23: 第1画面 | G23: 基本情報 | K23: 客納納期 | V23: T | W23: 受注 | AF23: 客納納期
C24: 画 | D24: 第1画面 | G24: 基本情報 | K24: 数量 | V24: T | W24: 受注 | AF24: 数量
C25: 画 | D25: 第1画面 | G25: 基本情報 | K25: 注文書No | V25: T | W25: 受注 | AF25: 注文書No
C26: 画 | D26: 第1画面 | G26: 基本情報 | K26: 先方担当 | V26: T | W26: 受注 | AF26: 先方担当
C27: 画 | D27: 第1画面 | G27: 基本情報 | K27: 宛名 | V27: T | W27: 受注 | AF27: 宛名
C28: 画 | D28: 第1画面 | G28: 基本情報 | K28: 運送会社 | V28: T | W28: 受注 | AF28: 運送会社
C29: 画 | D29: 第1画面 | G29: 基本情報 | K29: 出荷時間 | V29: T | W29: 受注 | AF29: 出荷時間
C30: 画 | D30: 第1画面 | G30: 基本情報 | K30: 出荷条件 | V30: T | W30: 受注 | AF30: 出荷条件
... C50: 画 | D50: 第1画面 | G50: 部材一覧 | K50: 受注№/受注明細№ | V50: T | W50: 受注明細 | AF50: 受注№ || 受注明細№
A53: No | G53: 3 | S53: ボタン | AH53: 備考
A54: 処理分類 | E54: 検索(製品基本マスタ) | S54: ソート順
A55: No | C55: 転送先 | V55: 転送元 | AQ55: 説明
C56: 種 | D56: オブジェクト | K56: 項目名 | V56: 種 | W56: オブジェクト | AF56: 項目名
A57: 1 | C57: 画 | D57: ２ページ目：基本情報画面 | K57: 納品先 | V57: 画 | W57: 第1画面 部材一覧
A58: 2 | C58: 画 | D58: ２ページ目：基本情報画面 | K58: 手配区分 | V58: 画 | W58: 第1画面 部材一覧 | AF58: 手配区分
A59: 3 | C59: 画 | D59: ２ページ目：基本情報画面 | K59: 預り売上 | V59: 画 | W59: 第1画面 部材一覧 | AF59: 預り売上
A60: 4 | C60: 画 | D60: ２ページ目：基本情報画面 | K60: 受注区分 | V60: 画 | W60: 第1画面 部材一覧 | AF60: 受注区分
A61: 5 | C61: 画 | D61: ２ページ目：基本情報画面 | K61: 製品区分_大 | V61: 画 | W61: 第1画面 部材一覧 | AF61: 製品区分_大
A62: 6 | C62: 画 | D62: ２ページ目：基本情報画面 | K62: 製品区分_中 | V62: 画 | W62: 第1画面 部材一覧 | AF62: 製品区分_中
A63: 7 | C63: 画 | D63: ２ページ目：基本情報画面 | K63: 製品区分_小 | V63: 画 | W63: 第1画面 部材一覧 | AF63: 製品区分_小
A64: 8 | C64: 画 | D64: ２ページ目：基本情報画面 | K64: 手配NO | V64: 画 | W64: 第1画面 部材一覧 | AF64: 手配NO
A65: 9 | C65: 画 | D65: ２ページ目：基本情報画面 | K65: 得意先 | V65: 画 | W65: 第1画面 部材一覧 | AF65: 得意先
A66: 10 | C66: 画 | D66: ２ページ目：基本情報画面 | K66: 得意先名 | V66: 画 | W66: 第1画面 部材一覧 | AF66: 得意先名
A67: 11 | C67: 画 | D67: ２ページ目：基本情報画面 | K67: 客先納期 | V67: 画 | W67: 第1画面 部材一覧 | AF67: 客先納期
A68: 12 | C68: 画 | D68: ２ページ目：基本情報画面 | K68: 製品CD | V68: T | W68: 製品基本マスタ | AF68: 製品CD
A69: 13 | C69: 画 | D69: ２ページ目：基本情報画面 | K69: 顧客品名１ | V69: T | W69: 製品基本マスタ | AF69: 顧客品名１
... A74: 18 | C74: 画 | D74: ２ページ目：基本情報画面 | K74: 顧客品番 | V74: T | W74: 製品基本マスタ | AF74: 顧客品番
A75: 19 | C75: 画 | D75: ２ページ目：基本情報画面 | K75: FSC製品区分 | V75: T | W75: 製品基本マスタ | AF75: FSC製品区分 | BM75: Rev2.0 項目統合(FSC認証製品＝FSC製品区分)
A76: 20 | C76: 画 | D76: ２ページ目：基本情報画面 | K76: 食品安全 | V76: T | W76: 製品基本マスタ | AF76: 食品安全
A77: 21 | C77: 画 | D77: ２ページ目：基本情報画面 | K77: 納入予備 | V77: T | W77: 製品基本マスタ | AF77: 納入予備
A78: 22 | C78: 画 | D78: ２ページ目：基本情報画面 | K78: 営業サンプル | V78: T | W78: 製品基本マスタ | AF78: 営業サンプル
A79: 23 | C79: 画 | D79: ２ページ目：基本情報画面 | K79: 定数出荷 | V79: T | W79: 製品基本マスタ | AF79: 定数出荷
A80: 24 | C80: 画 | D80: ２ページ目：基本情報画面 | K80: 不適合手配NO | V80: T | AQ80: NULL
A81: 25 | C81: 画 | D81: ２ページ目：基本情報画面 | K81: 売上可否 | V81: T | W81: 製品基本マスタ | AF81: 売上可否
A82: 26 | C82: 画 | D82: ２ページ目：基本情報画面 | K82: シート段 | V82: T | W82: 製品基本マスタ | AF82: シート段
A83: 27 | C83: 画 | D83: ２ページ目：基本情報画面 | K83: 原紙コード(表) | V83: T | W83: 製品基本マスタ | AF83: 原紙コード(表)
A84: 28 | C84: 画 | D84: ２ページ目：基本情報画面 | K84: 印刷コード(表) | V84: T | W84: 製品基本マスタ | AF84: 印刷コード(表)
A85: 29 | C85: 画 | D85: ２ページ目：基本情報画面 | K85: エンボスコード(表) | V85: T | W85: 製品基本マスタ | AF85: エンボスコード(表)
A86: 30 | C86: 画 | D86: ２ページ目：基本情報画面 | K86: メーカ（表） | V86: T | W86: 製品基本マスタ | AF86: メーカ（表）
A87: 31 | C87: 画 | D87: ２ページ目：基本情報画面 | K87: 原紙コード(中) | V87: T | W87: 製品基本マスタ | AF87: 原紙コード(中)
A88: 32 | C88: 画 | D88: ２ページ目：基本情報画面 | K88: 印刷コード(中) | V88: T | W88: 製品基本マスタ | AF88: 印刷コード(中)
A89: 33 | C89: 画 | D89: ２ページ目：基本情報画面 | K89: エンボスコード(中) | V89: T | W89: 製品基本マスタ | AF89: エンボスコード(中)
A90: 34 | C90: 画 | D90: ２ページ目：基本情報画面 | K90: メーカ（中） | V90: T | W90: 製品基本マスタ | AF90: メーカ（中）
A91: 35 | C91: 画 | D91: ２ページ目：基本情報画面 | K91: 原紙コード(裏) | V91: T | W91: 製品基本マスタ | AF91: 原紙コード(裏)
A92: 36 | C92: 画 | D92: ２ページ目：基本情報画面 | K92: 印刷コード(裏) | V92: T | W92: 製品基本マスタ | AF92: 印刷コード(裏)
... A104: 48 | C104: 画 | D104: ２ページ目：基本情報画面 | K104: 数量 | V104: T | W104: 製品基本マスタ | AF104: 数量
A105: 49 | C105: 画 | D105: ２ページ目：基本情報画面 | K105: 数量単位 | V105: T | AQ105: NULL
A106: 50 | C106: 画 | D106: ２ページ目：基本情報画面 | K106: 単価 | V106: T | W106: 製品基本マスタ | AF106: 単価
A107: 51 | C107: 画 | D107: ２ページ目：基本情報画面 | K107: セット単価 | V107: T | W107: 製品基本マスタ | AF107: セット単価
A108: 52 | C108: 画 | D108: ２ページ目：基本情報画面 | K108: 単価単位 | V108: T | AQ108: NULL
A109: 53 | C109: 画 | D109: ２ページ目：基本情報画面 | K109: 特値 | V109: T | AQ109: NULL
A110: 54 | C110: 画 | D110: ２ページ目：基本情報画面 | K110: 印刷備考 | V110: T | W110: 製品基本マスタ | AF110: 印刷備考
A111: 55 | C111: 画 | D111: ２ページ目：基本情報画面 | K111: 製造備考 | V111: T | W111: 製品基本マスタ | AF111: 製造備考
A112: 56 | C112: 画 | D112: ２ページ目：基本情報画面 | K112: 再製造備考 | V112: T | W112: 製品基本マスタ | AF112: 再製造備考
A113: 57 | C113: 画 | D113: ２ページ目：基本情報画面 | K113: 伝票備考 | V113: T | W113: 製品基本マスタ | AF113: 伝票備考
A114: 58 | C114: 画 | D114: ２ページ目：基本情報画面 | K114: 納入備考 | V114: T | W114: 製品基本マスタ | AF114: 納入備考
A115: 59 | C115: 画 | D115: ２ページ目：基本情報画面 | K115: 出荷備考１ | V115: T | W115: 製品基本マスタ | AF115: 出荷備考１
A116: 60 | C116: 画 | D116: ２ページ目：基本情報画面 | K116: 出荷備考２ | V116: T | W116: 製品基本マスタ | AF116: 出荷備考２
A117: 58 | C117: 画 | D117: ２ページ目：基本情報画面 | K117: 巻きM | V117: T | AQ117: NULL
A118: 59 | C118: 画 | D118: ２ページ目：基本情報画面 | K118: 売上巾 | V118: T | AQ118: NULL
A119: 60 | C119: 画 | D119: ２ページ目：基本情報画面 | K119: 発注先 | V119: T | AQ119: NULL
A120: 61 | C120: 画 | D120: ２ページ目：基本情報画面 | K120: 発注単価 | V120: T | AQ120: NULL | BM120: REV3.0 発注単価の追加
A121: 62 | C121: 画 | D121: ２ページ目：基本情報画面 | K121: 発注単位 | V121: T | AQ121: NULL
A122: 63 | C122: 画 | D122: ２ページ目：基本情報画面 | K122: 預り売上数 | V122: T | AQ122: NULL | BM122: REV4.0 預り売上数の追加
A123: No | G123: 4 | S123: ボタン | AH123: 備考
A124: 処理分類 | E124: 検索(製品加工工程マスタ) | S124: ソート順
A125: No | C125: 転送先 | V125: 転送元 | AQ125: 説明
C126: 種 | D126: オブジェクト | K126: 項目名 | V126: 種 | W126: オブジェクト | AF126: 項目名
A127: 1 | C127: 画 | D127: ３ページ目：工程情報画面 | K127: 工程 | V127: T | W127: 製品加工工程マスタ | AF127: 工程
A128: 2 | C128: 画 | D128: ３ページ目：工程情報画面 | K128: 工程名 | V128: T | W128: 製品加工工程マスタ | AF128: 工程名
A129: 3 | C129: 画 | D129: ３ページ目：工程情報画面 | K129: 作業 | V129: T | W129: 製品加工工程マスタ | AF129: 作業
A130: 4 | C130: 画 | D130: ３ページ目：工程情報画面 | K130: 作業名 | V130: T | W130: 製品加工工程マスタ | AF130: 作業名
A131: 5 | C131: 画 | D131: ３ページ目：工程情報画面 | K131: WG | V131: T | W131: 製品加工工程マスタ | AF131: WG
A132: 6 | C132: 画 | D132: ３ページ目：工程情報画面 | K132: 号機/発注先 | V132: T | W132: 製品加工工程マスタ | AF132: 号機/発注先
A133: 7 | C133: 画 | D133: ３ページ目：工程情報画面 | K133: 号機指定 | V133: T | W133: 製品加工工程マスタ | AF133: 号機指定
A134: 8 | C134: 画 | D134: ３ページ目：工程情報画面 | K134: CP配送区分 | V134: T | W134: 製品加工工程マスタ | AF134: CP配送区分
A135: 9 | C135: 画 | D135: ３ページ目：工程情報画面 | K135: 仕様１名称 | V135: T | W135: 製品加工工程マスタ | AF135: 仕様１名称
A136: 10 | C136: 画 | D136: ３ページ目：工程情報画面 | K136: 仕様１値 | V136: T | W136: 製品加工工程マスタ | AF136: 仕様１値
A137: 11 | C137: 画 | D137: ３ページ目：工程情報画面 | K137: 仕様２名称 | V137: T | W137: 製品加工工程マスタ | AF137: 仕様２名称
A138: 12 | C138: 画 | D138: ３ページ目：工程情報画面 | K138: 仕様２値 | V138: T | W138: 製品加工工程マスタ | AF138: 仕様２値
...

Sheet 更新入出力仕様
A1: =表紙!A54 -> Webシステム | K1: 文書名 | U1: モジュールID | Z1: =表紙!$AJ$63 -> MS | AE1: モジュール名 | AJ1: =表紙!$AX$63 -> 見積管理 | AS1: 文書番号 | AZ1: Version | BF1: Rev.
K2: =表紙!O64 -> アドオン設計書 | U2: ｻﾌﾞﾓｼﾞｭｰﾙID | Z2: =表紙!$AJ$64 -> MSBB | AE2: ｻﾌﾞﾓｼﾞｭｰﾙ名 | AJ2: =表紙!$AX$64 -> Webシステム | AS2: =表紙!$BL$64 -> M7-US-1140 | AZ2: =表紙!$BU$64 -> 7.0.2 | BF2: =表紙!$CB$64 -> 7
K3: =RIGHT(CELL("filename",$A$1),LEN(CELL("filename",$A$1))-FIND("]",CELL("filename",$A$1))) -> 更新入出力仕様 | U3: 表題 | Z3: =表紙!$AJ$65 -> MSBBPA070 | AE3: =表紙!$AQ$65 -> Web受注入力
A5: No | G5: 1 | S5: ロジック名称 | Z5: 受注更新処理 | AH5: 備考
A6: 処理分類 | E6: 追加
A7: No | C7: 転送先 | V7: 転送元 | AQ7: 説明
C8: 種 | D8: オブジェクト | K8: 項目名 | V8: 種 | W8: オブジェクト | AF8: 項目名
A9: 1 | C9: T | D9: 受注 | K9: Web受注NO | V9: 画 | AQ9: シーケンスにより自動採番
A10: 2 | C10: T | D10: 受注 | K10: 得意先コード | V10: 画 | W10: 第1画面 | AA10: 基本情報 | AF10: 得意先コード
A11: 3 | C11: T | D11: 受注 | K11: 受注区分 | V11: 画 | W11: 第1画面 | AA11: 基本情報 | AF11: 受注区分
A12: 4 | C12: T | D12: 受注 | K12: 受注部門 | V12: 画 | W12: 第1画面 | AA12: 基本情報 | AF12: 受注部門
A13: 5 | C13: T | D13: 受注 | K13: 受注日 | V13: 画 | W13: 第1画面 | AA13: 基本情報 | AF13: 受注日
A14: 6 | C14: T | D14: 受注 | K14: 客納納期 | V14: 画 | W14: 第1画面 | AA14: 基本情報 | AF14: 客納納期
A15: 7 | C15: T | D15: 受注 | K15: 数量 | V15: 画 | W15: 第1画面 | AA15: 基本情報 | AF15: 数量
A16: 8 | C16: T | D16: 受注 | K16: 注文書NO | V16: 画 | W16: 第1画面 | AA16: 基本情報 | AF16: 注文書NO
A17: 9 | C17: T | D17: 受注 | K17: 先方担当 | V17: 画 | W17: 第1画面 | AA17: 基本情報 | AF17: 先方担当
A18: 10 | C18: T | D18: 受注 | K18: 宛名 | V18: 画 | W18: 第1画面 | AA18: 基本情報 | AF18: 宛名
A19: 11 | C19: T | D19: 受注 | K19: 運送会社 | V19: 画 | W19: 第1画面 | AA19: 基本情報 | AF19: 運送会社
A20: 12 | C20: T | D20: 受注 | K20: 出荷日時 | V20: 画 | W20: 第1画面 | AA20: 基本情報 | AF20: 出荷日時
A21: 13 | C21: T | D21: 受注 | K21: 売価区分 | V21: 画 | W21: 第1画面 | AA21: 基本情報 | AF21: 売価区分
A22: 14 | C22: T | D22: 受注 | K22: 受注ＮＯ | V22: 画 | AQ22: 承認済 | AU22: 新規：* 更新：変更しない
A23: 15 | C23: T | D23: 受注 | K23: ステータス | V23: 画 | AQ23: 承認固定 | AU23: 新規：0 更新：変更しない
A24: 16 | C24: T | D24: 受注 | K24: mcframe7転送FLG | V24: 画 | AQ24: FALSE固定
A25: 17
A26: 18
A27: No | G27: 2 | H27: 受注明細追加更新 | S27: ロジック名称 | AH27: 備考
A28: 処理分類 | E28: 追加・更新
A29: No | C29: 転送先 | V29: 転送元 | AQ29: 説明
C30: 種 | D30: オブジェクト | K30: 項目名 | V30: 種 | W30: オブジェクト | AF30: 項目名
A31: 1 | C31: T | D31: 受注明細 | K31: Web受注NO | V31: T | W31: 受注 | AF31: Web受注NO
A32: 2 | C32: T | D32: 受注明細 | K32: Web受注明細NO | AF32: 明細行 | AQ32: WEB受注NO＋明細行
A33: 3 | C33: T | D33: 受注明細 | K33: 手配ＮＯ１ | AQ33: シーケンスにより自動採番
A34: 4 | C34: T | D34: 受注明細 | K34: 手配ＮＯ２ | W34: 1ページ目：得意先コード | AF34: 得意先コード
A35: 5 | C35: T | D35: 受注明細 | K35: 手配ＮＯ３ | W35: 製品基本マスタ | AF35: 案件NO(親) | BN35: Rev2.0 変更
A36: 6 | C36: T | D36: 受注明細 | K36: 手配ＮＯ４ | AQ36: NULL
A37: 7 | C37: T | D37: 受注明細 | K37: 製品コード | V37: 画 | W37: 2ページ目：基本情報画面 | AF37: 製品コード
A38: 8 | C38: T | D38: 受注明細 | K38: 品目コード | V38: 画 | W38: 2ページ目：基本情報画面 | AF38: 品目コード
A39: 9 | C39: T | D39: 受注明細 | K39: 枝番１ | V39: 画 | W39: 2ページ目：基本情報画面 | AF39: 枝番１
A40: 10 | C40: T | D40: 受注明細 | K40: 枝番２ | V40: 画 | W40: 2ページ目：基本情報画面 | AF40: 枝番２
A41: 11 | C41: T | D41: 受注明細 | K41: 枝番３ | V41: 画 | W41: 2ページ目：基本情報画面 | AF41: 枝番３
A42: 12 | C42: T | D42: 受注明細 | K42: 製品区分_大 | V42: 画 | W42: 2ページ目：基本情報画面 | AF42: 製品区分_大
A43: 13 | C43: T | D43: 受注明細 | K43: 製品区分_中 | V43: 画 | W43: 2ページ目：基本情報画面 | AF43: 製品区分_中
A44: 14 | C44: T | D44: 受注明細 | K44: 製品区分_小 | V44: 画 | W44: 2ページ目：基本情報画面 | AF44: 製品区分_小
A45: 15 | C45: T | D45: 受注明細 | K45: 顧客品名１ | V45: 画 | W45: 2ページ目：基本情報画面 | AF45: 顧客品名１
A46: 16 | C46: T | D46: 受注明細 | K46: 顧客品名２ | V46: 画 | W46: 2ページ目：基本情報画面 | AF46: 顧客品名２
A47: 17 | C47: T | D47: 受注明細 | K47: 顧客品番 | V47: 画 | W47: 2ページ目：基本情報画面 | AF47: 顧客品番
A48: 18 | C48: T | D48: 受注明細 | K48: CP品名1 | V48: 画 | W48: 2ページ目：基本情報画面 | AF48: CP品名1
... A63: 33 | C63: T | D63: 受注明細 | K63: 出荷検査 | V63: 画 | W63: 2ページ目：基本情報画面 | AF63: 出荷検査
A64: 34 | C64: T | D64: 受注明細 | K64: FSC製品区分 | V64: 画 | W64: 2ページ目：基本情報画面 | AF64: FSC製品区分 | BM64: Rev2.0 項目削除(FSC認証製品＝FSC製品区分)
A65: 35 | C65: T | D65: 受注明細 | K65: 食品安全 | V65: 画 | W65: 2ページ目：基本情報画面 | AF65: 食品安全
A66: 36 | C66: T | D66: 受注明細 | K66: 定数出荷 | V66: 画 | W66: 2ページ目：基本情報画面 | AF66: 定数出荷
A67: 37 | C67: T | D67: 受注明細 | K67: 納入予備 | V67: 画 | W67: 2ページ目：基本情報画面 | AF67: 納入予備
A68: 38 | C68: T | D68: 受注明細 | K68: 営業サンプル | V68: 画 | W68: 2ページ目：基本情報画面 | AF68: 営業サンプル
A69: 39 | C69: T | D69: 受注明細 | K69: 売上可否 | V69: 画 | W69: 2ページ目：基本情報画面 | AF69: 売上可否
A70: 40 | C70: T | D70: 受注明細 | K70: 段 | V70: 画 | W70: 2ページ目：基本情報画面 | AF70: 段
A71: 41 | C71: T | D71: 受注明細 | K71: 原紙コード(表) | V71: 画 | W71: 2ページ目：基本情報画面 | AF71: 原紙コード(表)
A72: 42 | C72: T | D72: 受注明細 | K72: 印刷コード(表) | V72: 画 | W72: 2ページ目：基本情報画面 | AF72: 印刷コード(表)
A73: 43 | C73: T | D73: 受注明細 | K73: エンボスコード(表) | V73: 画 | W73: 2ページ目：基本情報画面 | AF73: エンボスコード(表)
A74: 44 | C74: T | D74: 受注明細 | K74: メーカコード(表) | V74: 画 | W74: 2ページ目：基本情報画面 | AF74: メーカコード(表)
A75: 45 | C75: T | D75: 受注明細 | K75: 原紙コード(中) | V75: 画 | W75: 2ページ目：基本情報画面 | AF75: 原紙コード(中)
A76: 46 | C76: T | D76: 受注明細 | K76: 印刷コード(中) | V76: 画 | W76: 2ページ目：基本情報画面 | AF76: 印刷コード(中)
... A102: 79 | C102: T | D102: 受注明細 | K102: 巻きM | V102: 画 | W102: 2ページ目：基本情報画面 | AF102: 巻きM
A103: 80 | C103: T | D103: 受注明細 | K103: 発注単価 | V103: 画 | W103: 2ページ目：基本情報画面 | AF103: 発注単価 | BN103: REV3.0 発注単価の追加
A104: 81 | C104: T | D104: 受注明細 | K104: 発注単位 | V104: 画 | W104: 2ページ目：基本情報画面 | AF104: 発注単位
A105: 82 | C105: T | D105: 受注明細 | K105: 案件NO(親)、(子)、(部材) | V105: T | W105: 製品基本マスタ | AF105: 案件NO(親)、(子)、(部材) | AQ105: 案件NO(親)、(子)、(部材)に分割して登録する | BN105: Rev2.0 変更
A106: 83 | C106: T | D106: 受注明細 | K106: 御見積書NO | V106: T | W106: 製品基本マスタ | AF106: 御見積書NO
A107: 84 | C107: T | D107: 受注明細 | K107: 見積計算書NO | V107: T | W107: 製品基本マスタ | AF107: 見積計算書NO
A108: 85 | C108: T | D108: 受注明細 | K108: 参照元_見積計算書NO | V108: T | W108: 製品基本マスタ | AF108: 参照元_見積計算書NO | BN108: Rev6.0 見積計算書ＮＯ項目 重複削除
A109: 86 | C109: T | D109: 受注明細 | K109: セット部品CD | V109: T | W109: 製品基本マスタ | AF109: セット部品CD
A110: 87 | C110: T | D110: 受注明細 | K110: セット品名 | V110: T | W110: 製品基本マスタ | AF110: セット品名
A111: 88 | C111: T | D111: 受注明細 | K111: 親子区分 | V111: T | W111: 製品基本マスタ | AF111: 親子区分
A112: 89 | C112: T | D112: 受注明細 | K112: JANCD | V112: T | W112: 製品基本マスタ | AF112: JANCD
A113: 90 | C113: T | D113: 受注明細 | K113: 受注区分 | V113: T | W113: 製品基本マスタ | AF113: 受注区分
A114: 91 | C114: T | D114: 受注明細 | K114: セット比率 | V114: T | W114: 製品基本マスタ | AF114: セット比率
A115: 92 | C115: T | D115: 受注明細 | K115: 製品用途 | V115: T | W115: 製品基本マスタ | AF115: 製品用途
A116: 93 | C116: T | D116: 受注明細 | K116: 物流区分 | V116: T | W116: 製品基本マスタ | AF116: 物流区分
A117: 94 | C117: T | D117: 受注明細 | K117: 機密情報 | V117: T | W117: 製品基本マスタ | AF117: 機密情報
A118: 95 | C118: T | D118: 受注明細 | K118: 奪取区分 | V118: T | W118: 製品基本マスタ | AF118: 奪取区分
A119: 96 | C119: T | D119: 受注明細 | K119: 重要区分 | V119: T | W119: 製品基本マスタ | AF119: 重要区分
A120: 97 | C120: T | D120: 受注明細 | K120: Mチェン | V120: T | W120: 製品基本マスタ | AF120: Mチェン
A121: 98 | C121: T | D121: 受注明細 | K121: 品質区分 | V121: T | W121: 製品基本マスタ | AF121: 品質区分
A122: 99 | C122: T | D122: 受注明細 | K122: 高品質 | V122: T | W122: 製品基本マスタ | AF122: 高品質 | BN122: Rev2.0 項目削除(高品質 項目削除)
A123: 100 | C123: T | D123: 受注明細 | K123: 製品形状 | V123: T | W123: 製品基本マスタ | AF123: 製品形状
A124: 101 | C124: T | D124: 受注明細 | K124: ユネスコマーク | V124: T | W124: 製品基本マスタ | AF124: ユネスコマーク
A125: 102 | C125: T | D125: 受注明細 | K125: 折鶴マーク | V125: T | W125: 製品基本マスタ | AF125: 折鶴マーク
A126: 103 | C126: T | D126: 受注明細 | K126: 4M契約 | V126: T | W126: 製品基本マスタ | AF126: 4M契約
A127: 104 | C127: T | D127: 受注明細 | K127: TKP折れシワ基準 | V127: T | W127: 製品基本マスタ | AF127: TKP折れシワ基準
A128: 105 | C128: T | D128: 受注明細 | K128: 容リ支払 | V128: T | W128: 製品基本マスタ | AF128: 容リ支払
A129: 106 | C129: T | D129: 受注明細 | K129: FSC材質区分 | V129: T | W129: 製品基本マスタ | AF129: FSC材質区分
A130: 107 | C130: T | D130: 受注明細 | K130: FSC管理NO | V130: T | W130: 製品基本マスタ | AF130: FSC管理NO
A131: 108 | C131: T | D131: 受注明細 | K131: FSC製品区分 | V131: T | W131: 製品基本マスタ | AF131: FSC製品区分
A132: 109 | C132: T | D132: 受注明細 | K132: 紙使用量ｇ | V132: T | W132: 製品基本マスタ | AF132: 紙使用量ｇ
A133: 110 | C133: T | D133: 受注明細 | K133: プラ使用量ｇ | V133: T | W133: 製品基本マスタ | AF133: プラ使用量ｇ
A134: 111 | C134: T | D134: 受注明細 | K134: ガラス使用量ｇ | V134: T | W134: 製品基本マスタ | AF134: ガラス使用量ｇ
... A141: 118 | C141: T | D141: 受注明細 | K141: 運賃請求 | V141: T | W141: 製品基本マスタ | AF141: 運賃請求
A142: 119 | C142: T | D142: 受注明細 | K142: 受注ＮＯ | V142: T | W142: 受注明細 | AF142: 受注ＮＯ | AQ142: 新規はNULL
A143: 120 | C143: T | D143: 受注明細 | K143: 受注明細ＮＯ | V143: T | W143: 受注明細 | AF143: 受注明細ＮＯ | AQ143: 新規はNULL
A144: 121 | C144: T | D144: 受注明細 | K144: ステータス | AQ144: 承認済 | AT144: 新規：0 更新：変更しない
A145: 122 | C145: T | D145: 受注明細 | K145: ワークフロー承認FLG | AQ145: 承認固定 | AT145: 新規：0 更新：単価変更場合、0を設定する。
A146: 123 | C146: T | D146: 受注明細 | K146: mcframe7転送FLG | AQ146: FALSE固定
...

Sheet テーブル項目_受注
A1: =表紙!A54 -> Webシステム | K1: 文書名 | U1: モジュールID | Z1: =表紙!$AJ$63 -> MS | AE1: モジュール名 | AJ1: =表紙!$AX$63 -> 見積管理 | AS1: 文書番号 | AZ1: Version | BF1: Rev.
K2: =表紙!O64 -> アドオン設計書 | U2: ｻﾌﾞﾓｼﾞｭｰﾙID | Z2: =表紙!$AJ$64 -> MSBB | AE2: ｻﾌﾞﾓｼﾞｭｰﾙ名 | AJ2: =表紙!$AX$64 -> Webシステム | AS2: =表紙!$BL$64 -> M7-US-1140 | AZ2: =表紙!$BU$64 -> 7.0.2 | BF2: =表紙!$CB$64 -> 7
K3: =RIGHT(CELL("filename",$A$1),LEN(CELL("filename",$A$1))-FIND("]",CELL("filename",$A$1))) -> テーブル項目_受注 | U3: 表題 | Z3: =表紙!$AJ$65 -> MSBBPA070 | AE3: =表紙!$AQ$65 -> Web受注入力
A5: テーブル名 | O5: 日本語名 | AE5: 種別
O6: 受注 | AE6: アドオン(新規)
A8: 主キー | D8: 項目名 | O8: 日本語名 | AE8: 型 | AG8: 桁 | AI8: Null | AK8: 説明 | BL8: 値の制限 | BM8: 設定仕様 | BN8: 未設定時の振る舞い | BO8: 受注画面
A9: 〇 | O9: Web受注NO | AE9: N | AI9: N
O10: 得意先コード | AE10: C | AI10: N | BL10: 得意先マスタ(mcframe7)
O11: 受注区分 | AE11: C | AI11: N | AK11: 受注区分：加工製品、加工商品、シート製品、購買品 | BL11: 汎用マスタ(mcframe7)
O12: 受注部門 | AE12: C | BL12: 部門マスタ(mcframe7)
O13: 受注日 | AE13: D
O14: 客納納期 | AE14: D
O15: 数量 | AE15: N
O16: 注文書NO | AE16: C
O17: 先方担当 | AE17: C
O18: 宛名 | AE18: C
O19: 運送会社 | AE19: C
O20: 出荷日時 | AE20: C
O21: 売価区分 | AE21: C | AK21: 売価区分：個別単価、セット単価
O22: 受注ＮＯ | AK22: mcframe7側の連携キー
O23: ステータス | AE23: N | AI23: N | AK23: 0:未転送、9:mcframe7転送済
O24: mcframe7転送FLG | AE24: F | AI24: N | AK24: mcframe7転送を示すフラグ
D25: MEMO1 | O25: メモ１ | AE25: C | AG25: 100 | AI25: Y
D26: MEMO2 | O26: メモ２ | AE26: C | AG26: 100 | AI26: Y
D27: MEMO3 | O27: メモ３ | AE27: C | AG27: 100 | AI27: Y
D28: DEL_FLG | O28: 論理削除ＦＬＧ | AE28: F | AI28: N | AK28: 論理削除を示すフラグ
D29: DEL_USR_ID | O29: 論理削除ユーザＩＤ | AE29: C | AG29: 500 | AI29: Y
D30: DEL_USR_NM | O30: 論理削除ユーザ名 | AE30: C | AG30: 100 | AI30: Y
D31: DEL_TS | O31: 論理削除日時 | AE31: TS | AG31: 0 | AI31: Y
D32: INS_USR_ID | O32: 登録ユーザＩＤ | AE32: C | AG32: 500 | AI32: Y
D33: INS_USR_NM | O33: 登録ユーザ名 | AE33: C | AG33: 100 | AI33: Y
D34: INS_TS | O34: 登録日時 | AE34: TS | AG34: 0 | AI34: Y
D35: INS_FUNC_ID | O35: 登録機能ＩＤ | AE35: C | AG35: 50 | AI35: Y
D36: UPD_CNTR | O36: 更新カウンタ | AE36: N | AG36: 9,0 | AI36: Y
D37: UPD_USR_ID | O37: 更新ユーザＩＤ | AE37: C | AG37: 500 | AI37: Y
D38: UPD_USR_NM | O38: 更新ユーザ名 | AE38: C | AG38: 100 | AI38: Y
D39: UPD_TS | O39: 更新日時 | AE39: TS | AG39: 0 | AI39: Y
D40: UPD_FUNC_ID | O40: 更新機能ＩＤ | AE40: C | AG40: 50 | AI40: Y
D41: UPD_SRV_REQ_NO | O41: 更新リクエストＮＯ | AE41: C | AG41: 50 | AI41: Y

Sheet テーブル項目_受注明細
A1: =表紙!A54 -> Webシステム | K1: 文書名 | U1: モジュールID | Z1: =表紙!$AJ$63 -> MS | AE1: モジュール名 | AJ1: =表紙!$AX$63 -> 見積管理 | AS1: 文書番号 | AZ1: Version | BF1: Rev.
K2: =表紙!O64 -> アドオン設計書 | U2: ｻﾌﾞﾓｼﾞｭｰﾙID | Z2: =表紙!$AJ$64 -> MSBB | AE2: ｻﾌﾞﾓｼﾞｭｰﾙ名 | AJ2: =表紙!$AX$64 -> Webシステム | AS2: =表紙!$BL$64 -> M7-US-1140 | AZ2: =表紙!$BU$64 -> 7.0.2 | BF2: =表紙!$CB$64 -> 7
K3: =RIGHT(CELL("filename",$A$1),LEN(CELL("filename",$A$1))-FIND("]",CELL("filename",$A$1))) -> テーブル項目_受注明細 | U3: 表題 | Z3: =表紙!$AJ$65 -> MSBBPA070 | AE3: =表紙!$AQ$65 -> Web受注入力
A5: テーブル名 | O5: 日本語名 | AE5: 種別
O6: 受注明細 | AE6: アドオン(新規)
A8: 主キー | D8: 項目名 | O8: 日本語名 | AE8: 型 | AG8: 桁 | AI8: Null | AK8: 説明 | BL8: 値の制限 | BM8: 設定仕様 | BN8: 未設定時の振る舞い | BO8: 受注画面
A9: 〇 | O9: Web受注NO | AE9: N | AI9: N
A10: 〇 | O10: Web受注明細NO | AE10: N | AI10: N
O11: 手配ＮＯ１ | AE11: C | AI11: Y
O12: 手配ＮＯ２ | AE12: C | AI12: Y
O13: 手配ＮＯ３ | AE13: C | AI13: Y
O14: 手配ＮＯ４ | AE14: C | AI14: Y
O15: 製品コード | AE15: C | AI15: N | BL15: 製品マスタ
O16: 品目コード | AE16: C | AI16: N | AK16: mcframe7連携用 | BL16: システム自動 | BO16: 画面表示無し
O17: 枝番１ | AE17: C | AI17: N | AK17: mcframe7連携用 | AR17: 部材一覧の行番(00) | BL17: システム自動 | BO17: 画面表示無し
O18: 枝番２ | AE18: C | AI18: N | AK18: mcframe7連携用 | BL18: システム自動 | BO18: 画面表示無し
O19: 枝番３ | AE19: C | AI19: N | AK19: mcframe7連携用 | BL19: システム自動 | BO19: 画面表示無し
O20: 製品区分_大 | AE20: C | AI20: N
O21: 製品区分_中 | AE21: C | AI21: N
O22: 製品区分_小 | AE22: C | AI22: N
O23: 顧客品名１ | AE23: C | AI23: Y
O24: 顧客品名２ | AE24: C | AI24: Y
O25: 顧客品番 | AE25: C | AI25: Y
O26: CP品名1 | AE26: C | AI26: Y
O27: CP品名2 | AE27: C | AI27: Y
O28: 数量単位 | AE28: C | AI28: N
O29: 数量 | AE29: N | AI29: N
O30: 特値FLG | AE30: C | AI30: N
O31: 単価単位
O32: セット単価 | AE32: N | AI32: N
O33: 個別単価 | AE33: N | AI33: N
O34: 金額 | AE34: N | AI34: N
O35: 納品先コード | AE35: C | AI35: N | BL35: 納品先マスタ(mcframe7)
O36: 客先納期 | AE36: D | AI36: N
O37: 物流グループ | AE37: C | AI37: N | BL37: 物流グループマスタ(mcframe7)
O38: 手配区分 | AE38: C | AI38: N | AK38: 選択項目は、汎用マスタで管理
O39: 預り売上FLG | AE39: C | AI39: N
O40: 売上理由 | AE40: C
O41: 出荷検査 | AE41: C | AL41: 〃
O42: FSC認証製品 | AE42: C | AL42: 〃
O43: 食品安全 | AE43: C | AL43: 〃
O44: 定数出荷 | AE44: C
O45: 納入予備 | AE45: N
O46: 営業サンプル | AE46: N
O47: 売上可否 | AE47: C | AK47: 選択項目は、汎用マスタで管理
O48: 段 | AE48: C | AI48: Y | BO48: ２ページ目：基本情報画面 | BP48: 〇
O49: 原紙コード(表) | AE49: C | AI49: Y | BL49: 原紙マスタ | BO49: ２ページ目：基本情報画面 | BP49: 〇
O50: 印刷コード(表) | AE50: C | AI50: Y | BL50: 汎用マスタ(印刷マスタ) | BO50: ２ページ目：基本情報画面 | BP50: 〇
O51: エンボスコード(表) | AE51: C | AI51: Y | BL51: 汎用マスタ(エンボスマスタ) | BO51: ２ページ目：基本情報画面 | BP51: 〇
O52: メーカコード(表) | AE52: C | AI52: Y | BL52: 汎用マスタ(エンボスマスタ) | BO52: ２ページ目：基本情報画面 | BP52: 〇
O53: 原紙コード(中) | AE53: C | AI53: Y | BL53: 原紙マスタ | BO53: ２ページ目：基本情報画面 | BP53: 〇
O54: 印刷コード(中) | AE54: C | AI54: Y | BL54: 汎用マスタ(印刷マスタ) | BO54: ２ページ目：基本情報画面 | BP54: 〇
O55: エンボスコード(中) | AE55: C | AI55: Y | BL55: 汎用マスタ(エンボスマスタ) | BO55: ２ページ目：基本情報画面 | BP55: 〇
O56: メーカーコード(中) | AE56: C | AI56: Y | BL56: 汎用マスタ(エンボスマスタ) | BO56: ２ページ目：基本情報画面 | BP56: 〇
O57: 原紙コード(裏) | AE57: C | AI57: Y | BL57: 原紙マスタ | BO57: ２ページ目：基本情報画面 | BP57: 〇
O58: 印刷コード(裏) | AE58: C | AI58: Y | BL58: 汎用マスタ(印刷マスタ) | BO58: ２ページ目：基本情報画面 | BP58: 〇
O59: エンボスコード(裏) | AE59: C | AI59: Y | BL59: 汎用マスタ(エンボスマスタ) | BO59: ２ページ目：基本情報画面 | BP59: 〇
O60: メーカーコード(裏) | AE60: C | AI60: Y | BL60: 汎用マスタ(エンボスマスタ) | BO60: ２ページ目：基本情報画面 | BP60: 〇
O61: 枚葉印刷 | AE61: C | AI61: Y | BO61: ２ページ目：基本情報画面 | BP61: 〇
O62: 刃渡り_巾 | AE62: N | AI62: Y | AK62: 単位:mm | BO62: ２ページ目：基本情報画面 | BP62: 〇
O63: 刃渡り_流れ | AE63: N | AI63: Y | AK63: 単位:mm | BO63: ２ページ目：基本情報画面 | BP63: 〇
O64: 咥え_前後 | AE64: N | AI64: Y | AK64: 単位:mm | BO64: ２ページ目：基本情報画面 | BP64: 〇
O65: 咥え_左右 | AE65: N | AI65: Y | AK65: 単位:mm | BO65: ２ページ目：基本情報画面 | BP65: 〇
O66: シート寸法_巾 | AE66: N | AI66: Y | AK66: 単位:mm | BO66: ２ページ目：基本情報画面 | BP66: 〇
O67: シート寸法_流れ | AE67: N | AI67: Y | AK67: 単位:mm | BO67: ２ページ目：基本情報画面 | BP67: 〇
O68: 売上巾 | AE68: N | AI68: Y | AK68: 単位:mm
O69: 最終機械工程 | AE69: C | AI69: Y | BO69: ２ページ目：基本情報画面 | BP69: 〇
O70: FSC受注区分 | AE70: C | AI70: Y | AK70: 選択項目は、汎用マスタで管理
O71: 印刷備考 | AE71: C | AI71: Y | BO71: ２ページ目：基本情報画面 | BP71: 〇
O72: 製造備考 | AE72: C | AI72: Y | BO72: ２ページ目：基本情報画面 | BP72: 〇
O73: 伝票備考 | AE73: C | AI73: Y | BO73: ２ページ目：基本情報画面 | BP73: 〇
O74: 納入備考 | AE74: C | AI74: Y | BO74: ２ページ目：基本情報画面 | BP74: 〇
O75: 出荷備考１ | AE75: C | AI75: Y | BO75: ２ページ目：基本情報画面 | BP75: 〇
O76: 出荷備考２ | AE76: C | AI76: Y | BO76: ２ページ目：基本情報画面 | BP76: 〇
O77: 再製造備考 | AE77: C | AI77: Y | BO77: ２ページ目：基本情報画面 | BP77: 〇
O78: 不適合手配NO | AE78: C | AI78: Y | BO78: ２ページ目：基本情報画面 | BP78: 〇
O79: 発注先 | AE79: C | AI79: Y | BO79: ２ページ目：基本情報画面 | BP79: 〇
O80: 巻きM | AE80: N | AI80: Y | BO80: ２ページ目：基本情報画面 | BP80: 〇
O81: 案件NO | AE81: C | AI81: Y
O82: 御見積書NO | AE82: C | AI82: Y
O83: 見積計算書NO | AE83: C | AI83: Y
O84: 参照元_見積計算書NO | AE84: C | AI84: Y
O85: セット部品CD | AE85: C | AI85: N
O86: セット品名 | AE86: C | AI86: Y
O87: 親子区分 | AE87: C | AI87: N
O88: JANCD | AE88: C | AI88: Y
O89: 受注区分 | AE89: N | AI89: N
O90: セット比率 | AE90: C | AI90: Y
O91: 製品用途 | AE91: C | AI91: Y
O92: 物流区分 | AE92: C | AI92: Y
... O114: デザイン提案NO | AE114: C | AI114: Y
O115: 売価区分 | AE115: C | AI115: N | AK115: 1:ｾｯﾄｳﾘ2:ﾀﾝﾋﾟﾝｳﾘ3:ｱｿｰﾄ
O116: 購買品の発注先 | AE116: C | AI116: Y | AK116: 商品のみ登録可
O117: 運賃請求 | AE117: C | AI117: N | AK117: 0:込み、1:別途
O118: 受注ＮＯ | AK118: mcframe7側の連携キー
O119: 受注明細ＮＯ | AK119: mcframe7側の連携キー
O120: ステータス | AE120: N | AI120: N | AK120: 0:未転送、9:mcframe7転送済
O121: mcframe7転送FLG | AE121: F | AI121: N | AK121: mcframe7転送を示すフラグ
D122: MEMO1 | O122: メモ１ | AE122: C | AG122: 100 | AI122: Y
D123: MEMO2 | O123: メモ２ | AE123: C | AG123: 100 | AI123: Y
...

Sheet テーブル項目_受注加工工程
A1: =表紙!A54 -> Webシステム | K1: 文書名 | U1: モジュールID | Z1: =表紙!$AJ$63 -> MS | AE1: モジュール名 | AJ1: =表紙!$AX$63 -> 見積管理 | AS1: 文書番号 | AZ1: Version | BF1: Rev.
K2: =表紙!O64 -> アドオン設計書 | U2: ｻﾌﾞﾓｼﾞｭｰﾙID | Z2: =表紙!$AJ$64 -> MSBB | AE2: ｻﾌﾞﾓｼﾞｭｰﾙ名 | AJ2: =表紙!$AX$64 -> Webシステム | AS2: =表紙!$BL$64 -> M7-US-1140 | AZ2: =表紙!$BU$64 -> 7.0.2 | BF2: =表紙!$CB$64 -> 7
K3: =RIGHT(CELL("filename",$A$1),LEN(CELL("filename",$A$1))-FIND("]",CELL("filename",$A$1))) -> テーブル項目_受注加工工程 | U3: 表題 | Z3: =表紙!$AJ$65 -> MSBBPA070 | AE3: =表紙!$AQ$65 -> Web受注入力
A5: テーブル名 | O5: 日本語名 | AE5: 種別
O6: 受注加工工程 | AE6: アドオン(新規)
A8: 主キー | D8: 項目名 | O8: 日本語名 | AE8: 型 | AG8: 桁 | AI8: Null | AK8: 説明 | BL8: 値の制限 | BM8: 設定仕様 | BN8: 未設定時の振る舞い | BO8: 受注画面
A9: 〇 | O9: Web受注NO | AE9: N | AI9: N
A10: 〇 | O10: Web受注明細NO | AE10: N | AI10: N
A11: 〇 | O11: 製品コード | AE11: C | AI11: N | AK11: 製品コードを自動採番する。 コード体系参照。 | BO11: １ページ目：メンテ対象選択画面
A12: 〇 | O12: 作業コード | AE12: C | AI12: N | AK12: mcの工程コードに当たる。製品マスタで設定 | BL12: 作業マスタ(条件=作業CD) | BO12: ３ページ目：工程情報画面 | BP12: 〇
O13: 工程コード | AE13: C | AI13: N | AK13: mcの品目コードに当たる。製品マスタで設定
O14: TOP品目コード | AE14: C | AI14: N | AK14: 製品の品目CD
O15: TOP品目_枝番1 | AE15: C | AI15: N | AK15: 製品の品目枝番１
O16: TOP品目_枝番2 | AE16: C | AI16: N | AK16: 製品の品目枝番２
O17: TOP品目_枝番3 | AE17: C | AI17: N | AK17: 製品の品目枝番３
O18: 品目コード | AE18: C | AI18: N | AK18: 工程の品目CD
O19: 枝番1 | AE19: C | AI19: N | AK19: 工程の品目枝番１
O20: 枝番2 | AE20: C | AI20: N | AK20: 工程の品目枝番２
O21: 枝番3 | AE21: C | AI21: N | AK21: 工程の品目枝番３
O22: ワーキンググループＣＤ | AE22: C | AG22: 10 | AI22: Y | AK22: 号機・発注先に紐づくワーキンググループCD | BO22: ３ページ目：工程情報画面 | BP22: 〇
O23: 号機・発注先 | AE23: C | AI23: Y | AK23: 作業場所として号機か発注先が入る | BL23: 取引先マスタ、場所マスタ | BO23: ３ページ目：工程情報画面 | BP23: △ | BQ23: 発注先時は、引き継ぐ
O24: 号機指定 | AE24: F | AI24: N | AK24: 号機・発注先が固定かどうか | BO24: ３ページ目：工程情報画面
O25: CP配送区分 | AE25: C | AI25: Y | AK25: 引取出荷、移送、売上出荷、WG間依頼 | BO25: ３ページ目：工程情報画面
O26: 工程仕様01 | AE26: C | AI26: Y | AK26: 作業の仕様情報が入る | BL26: 汎用マスタ(工程仕様) | BO26: ３ページ目：工程情報画面 | BP26: 〇
O27: 工程仕様02 | AE27: C | AI27: Y | AK27: 作業の仕様情報が入る | BL27: 汎用マスタ(工程仕様) | BO27: ３ページ目：工程情報画面 | BP27: 〇
O28: 工程仕様03 | AE28: C | AI28: Y | AK28: 作業の仕様情報が入る | BL28: 汎用マスタ(工程仕様) | BO28: ３ページ目：工程情報画面 | BP28: 〇
O29: 工程仕様04 | AE29: C | AI29: Y | AK29: 作業の仕様情報が入る | BL29: 汎用マスタ(工程仕様) | BO29: ３ページ目：工程情報画面 | BP29: 〇
O30: 工程仕様05 | AE30: C | AI30: Y | AK30: 作業の仕様情報が入る | BL30: 汎用マスタ(工程仕様) | BO30: ３ページ目：工程情報画面 | BP30: 〇
O31: 工程仕様06 | AE31: C | AI31: Y | AK31: 作業の仕様情報が入る | BL31: 汎用マスタ(工程仕様) | BO31: ３ページ目：工程情報画面 | BP31: 〇
O32: 工程仕様07 | AE32: C | AI32: Y | AK32: 作業の仕様情報が入る | BL32: 汎用マスタ(工程仕様) | BO32: ３ページ目：工程情報画面 | BP32: 〇
O33: 工程仕様08 | AE33: C | AI33: Y | AK33: 作業の仕様情報が入る | BL33: 汎用マスタ(工程仕様) | BO33: ３ページ目：工程情報画面 | BP33: 〇
O34: 工程仕様09 | AE34: C | AI34: Y | AK34: 作業の仕様情報が入る | BL34: 汎用マスタ(工程仕様) | BO34: ３ページ目：工程情報画面 | BP34: 〇
O35: 工程仕様10 | AE35: C | AI35: Y | AK35: 作業の仕様情報が入る | BL35: 汎用マスタ(工程仕様) | BO35: ３ページ目：工程情報画面 | BP35: 〇
O36: 数量単位 | AE36: N | AI36: Y | AK36: 仕様設定された単位を転記する
O37: 版型NO１ | AE37: C | AI37: Y | AK37: 工程で使用する版型 | BO37: ３ページ目：工程情報画面
O38: 版型NO２ | AE38: C | AI38: Y | AK38: 工程で使用する版型 | BO38: ３ページ目：工程情報画面
O39: 版型NO３ | AE39: C | AI39: Y | AK39: 工程で使用する版型 | BO39: ３ページ目：工程情報画面
O40: 消耗品１ | AE40: C | AI40: Y | AK40: 工程で使用する消耗品 | BO40: ３ページ目：工程情報画面
O41: 消耗品２ | AE41: C | AI41: Y | AK41: 工程で使用する消耗品 | BO41: ３ページ目：工程情報画面
O42: 消耗品３ | AE42: C | AI42: Y | AK42: 工程で使用する消耗品 | BO42: ３ページ目：工程情報画面
O43: 仕入単価 | AE43: N | AI43: Y | AK43: 工程の仕入単価 | BO43: ３ページ目：工程情報画面
O44: 指値（本支店） | AE44: N | AI44: Y | AK44: 工程の本支店指値
O45: ロス率 | AE45: N | AI45: N | AK45: 工程のロス率 | BO45: ３ページ目：工程情報画面
O46: 台数 | AE46: N | AI46: N | AK46: 工程の台数（固定使用数） | BO46: ３ページ目：工程情報画面
O47: LT | AE47: N | AI47: N | AK47: 工程のLT | BO47: ３ページ目：工程情報画面
O48: 入庫先 | AE48: C | AI48: Y | AK48: 工程の入庫先
O49: 並び順 | AE49: N | AI49: N | AK49: 画面の並び順、システム自動採番 | BO49: ３ページ目：工程情報画面
O50: 製造順優先項目１ | AE50: C | AI50: Y | AK50: 段：アルファベット順
O51: 製造順優先項目２ | AE51: C | AI51: Y | AK51: アドオン設計書作成ガイド
O52: 製造順優先項目３ | AE52: C | AI52: Y | AK52: 裏原紙 材料コード(原紙コード)順
O53: 製造順優先項目４ | AE53: C | AI53: Y | AK53: 印刷有無：無し → 有り順
O54: 製造順優先項目５ | AE54: C | AI54: Y | AK54: 表原紙 メーカー順：メーカー指定の場合メーカーＣＤ、無い場合 Null
O55: 製造順優先項目６ | AE55: C | AI55: Y | AK55: アドオン設計書作成ガイド
O56: 製造順優先項目７ | AE56: C | AI56: Y | AK56: 全判の流れ：大から小順
O57: 製造順優先項目８ | AE57: C | AI57: Y | AK57: コルスリ区分：有→無し順
D58: MEMO1 | O58: メモ１ | AE58: C | AG58: 100 | AI58: Y
D59: MEMO2 | O59: メモ２ | AE59: C | AG59: 100 | AI59: Y
D60: MEMO3 | O60: メモ３ | AE60: C | AG60: 100 | AI60: Y
D61: DEL_FLG | O61: 論理削除ＦＬＧ | AE61: F | AI61: N | AK61: 論理削除を示すフラグ
D62: DEL_USR_ID | O62: 論理削除ユーザＩＤ | AE62: C | AG62: 500 | AI62: Y
D63: DEL_USR_NM | O63: 論理削除ユーザ名 | AE63: C | AG63: 100 | AI63: Y
D64: DEL_TS | O64: 論理削除日時 | AE64: TS | AG64: 0 | AI64: Y
D65: INS_USR_ID | O65: 登録ユーザＩＤ | AE65: C | AG65: 500 | AI65: Y
D66: INS_USR_NM | O66: 登録ユーザ名 | AE66: C | AG66: 100 | AI66: Y
D67: INS_TS | O67: 登録日時 | AE67: TS | AG67: 0 | AI67: Y
D68: INS_FUNC_ID | O68: 登録機能ＩＤ | AE68: C | AG68: 50 | AI68: Y
D69: UPD_CNTR | O69: 更新カウンタ | AE69: N | AG69: 9,0 | AI69: Y
D70: UPD_USR_ID | O70: 更新ユーザＩＤ | AE70: C | AG70: 500 | AI70: Y
D71: UPD_USR_NM | O71: 更新ユーザ名 | AE71: C | AG71: 100 | AI71: Y
D72: UPD_TS | O72: 更新日時 | AE72: TS | AG72: 0 | AI72: Y
D73: UPD_FUNC_ID | O73: 更新機能ＩＤ | AE73: C | AG73: 50 | AI73: Y
D74: UPD_SRV_REQ_NO | O74: 更新リクエストＮＯ | AE74: C | AG74: 50 | AI74: Y

Sheet テーブル項目_受注工程備考
A1: =表紙!A54 -> Webシステム | K1: 文書名 | U1: モジュールID | Z1: =表紙!$AJ$63 -> MS | AE1: モジュール名 | AJ1: =表紙!$AX$63 -> 見積管理 | AS1: 文書番号 | AZ1: Version | BF1: Rev.
K2: =表紙!O64 -> アドオン設計書 | U2: ｻﾌﾞﾓｼﾞｭｰﾙID | Z2: =表紙!$AJ$64 -> MSBB | AE2: ｻﾌﾞﾓｼﾞｭｰﾙ名 | AJ2: =表紙!$AX$64 -> Webシステム | AS2: =表紙!$BL$64 -> M7-US-1140 | AZ2: =表紙!$BU$64 -> 7.0.2 | BF2: =表紙!$CB$64 -> 7
K3: =RIGHT(CELL("filename",$A$1),LEN(CELL("filename",$A$1))-FIND("]",CELL("filename",$A$1))) -> テーブル項目_受注工程備考 | U3: 表題 | Z3: =表紙!$AJ$65 -> MSBBPA070 | AE3: =表紙!$AQ$65 -> Web受注入力
A5: テーブル名 | O5: 日本語名 | AE5: 種別
O6: 受注工程備考 | AE6: アドオン(新規)
A8: 主キー | D8: 項目名 | O8: 日本語名 | AE8: 型 | AG8: 桁 | AI8: Null | AK8: 説明 | BL8: 値の制限 | BM8: 設定仕様 | BN8: 未設定時の振る舞い | BO8: 受注画面
A9: 〇 | O9: Web受注NO | AE9: N | AI9: N
A10: 〇 | O10: Web受注明細NO | AE10: N | AI10: N
A11: 〇 | O11: 製品コード | AE11: C | AI11: N | AK11: 製品コードを自動採番する。 コード体系参照。 | BO11: １ページ目：メンテ対象選択画面
A12: 〇 | O12: 作業コード | AE12: C | AI12: N | AK12: mcの工程コードに当たる。製品マスタで設定 | BL12: 作業マスタ(条件=作業CD) | BO12: ３ページ目：工程情報画面 | BP12: 〇
O13: 工程備考1 | AE13: C | AI13: Y | AK13: 工程に関する備考情報 | BO13: ３ページ目：工程情報画面 | BP13: 〇
O14: 工程備考2 | AE14: C | AI14: Y | AK14: 工程に関する備考情報 | BO14: ３ページ目：工程情報画面 | BP14: 〇
D15: MEMO1 | O15: メモ１ | AE15: C | AG15: 100 | AI15: Y
D16: MEMO2 | O16: メモ２ | AE16: C | AG16: 100 | AI16: Y
D17: MEMO3 | O17: メモ３ | AE17: C | AG17: 100 | AI17: Y
D18: DEL_FLG | O18: 論理削除ＦＬＧ | AE18: F | AI18: N | AK18: 論理削除を示すフラグ
D19: DEL_USR_ID | O19: 論理削除ユーザＩＤ | AE19: C | AG19: 500 | AI19: Y
D20: DEL_USR_NM | O20: 論理削除ユーザ名 | AE20: C | AG20: 100 | AI20: Y
D21: DEL_TS | O21: 論理削除日時 | AE21: TS | AG21: 0 | AI21: Y
D22: INS_USR_ID | O22: 登録ユーザＩＤ | AE22: C | AG22: 500 | AI22: Y
D23: INS_USR_NM | O23: 登録ユーザ名 | AE23: C | AG23: 100 | AI23: Y
D24: INS_TS | O24: 登録日時 | AE24: TS | AG24: 0 | AI24: Y
D25: INS_FUNC_ID | O25: 登録機能ＩＤ | AE25: C | AG25: 50 | AI25: Y
D26: UPD_CNTR | O26: 更新カウンタ | AE26: N | AG26: 9,0 | AI26: Y
D27: UPD_USR_ID | O27: 更新ユーザＩＤ | AE27: C | AG27: 500 | AI27: Y
D28: UPD_USR_NM | O28: 更新ユーザ名 | AE28: C | AG28: 100 | AI28: Y
D29: UPD_TS | O29: 更新日時 | AE29: TS | AG29: 0 | AI29: Y
D30: UPD_FUNC_ID | O30: 更新機能ＩＤ | AE30: C | AG30: 50 | AI30: Y
D31: UPD_SRV_REQ_NO | O31: 更新リクエストＮＯ | AE31: C | AG31: 50 | AI31: Y

Sheet テーブル項目_受注加工材料
A1: =表紙!A54 -> Webシステム | K1: 文書名 | U1: モジュールID | Z1: =表紙!$AJ$63 -> MS | AE1: モジュール名 | AJ1: =表紙!$AX$63 -> 見積管理 | AS1: 文書番号 | AZ1: Version | BF1: Rev.
K2: =表紙!O64 -> アドオン設計書 | U2: ｻﾌﾞﾓｼﾞｭｰﾙID | Z2: =表紙!$AJ$64 -> MSBB | AE2: ｻﾌﾞﾓｼﾞｭｰﾙ名 | AJ2: =表紙!$AX$64 -> Webシステム | AS2: =表紙!$BL$64 -> M7-US-1140 | AZ2: =表紙!$BU$64 -> 7.0.2 | BF2: =表紙!$CB$64 -> 7
K3: =RIGHT(CELL("filename",$A$1),LEN(CELL("filename",$A$1))-FIND("]",CELL("filename",$A$1))) -> テーブル項目_受注加工材料 | U3: 表題 | Z3: =表紙!$AJ$65 -> MSBBPA070 | AE3: =表紙!$AQ$65 -> Web受注入力
A5: テーブル名 | O5: 日本語名 | AE5: 種別
O6: 受注加工材料 | AE6: アドオン(新規)
A8: 主キー | D8: 項目名 | O8: 日本語名 | AE8: 型 | AG8: 桁 | AI8: Null | AK8: 説明 | BL8: 値の制限 | BM8: 設定仕様 | BN8: 未設定時の振る舞い | BO8: 製品マスタ画面
A9: 〇 | O9: Web受注NO | AE9: C | AI9: N | BO9: １ページ目：メンテ対象選択画面
A10: 〇 | O10: Web受注明細NO | AE10: C | AI10: N | BO10: ３ページ目：工程情報画面
A11: 〇 | O11: 製品コード | AE11: C | AI11: N | BO11: ３ページ目：工程情報画面
A12: 〇 | O12: 工程コード | AE12: C | AI12: N | BO12: ３ページ目：工程情報画面
A13: 〇 | O13: 材料CD | AE13: C | AI13: N | BO13: ３ページ目：工程情報画面
O14: 工程材料区分 | AE14: C | AI14: N | AK14: 1:仕掛品(工程コード)、2:連産品、3:原料、４：印刷原紙 | BO14: ３ページ目：工程情報画面
O15: 品目ＣＤ | AE15: C | AI15: N | AK15: 材料区分：3:品目マスタ時に値格納 | BL15: 品目マスタ | BO15: ３ページ目：工程情報画面
O16: 枝番１ | AE16: C | AI16: N | AK16: 材料区分：3:品目マスタ時に値格納 | BL16: 品目マスタ | BO16: ３ページ目：工程情報画面
O17: 枝番２ | AE17: C | AI17: N | AK17: 材料区分：3:品目マスタ時に値格納 | BL17: 品目マスタ | BO17: ３ページ目：工程情報画面
O18: 枝番３ | AE18: C | AI18: N | AK18: 材料区分：3:品目マスタ時に値格納 | BL18: 品目マスタ | BO18: ３ページ目：工程情報画面
O19: 受給区分 | AE19: C | AI19: N | AK19: 無償支給、有償支給 | BO19: ３ページ目：工程情報画面
O20: 受給単価 | AE20: N | AI20: N | BO20: ３ページ目：工程情報画面
O21: 並び順 | AE21: N | AI21: N | AK21: 画面の並び順、システム自動採番 | AW21: 例 | AX21: 材料1 | BA21: → | BC21: 材料2 | BO21: ３ページ目：工程情報画面
AX22: 材料3 | BA22: → | BC22: 材料4
AX23: 材料5 | BA23: → | BC23: 材料6
D24: MEMO1 | O24: メモ１ | AE24: C | AG24: 100 | AI24: Y
D25: MEMO2 | O25: メモ２ | AE25: C | AG25: 100 | AI25: Y
D26: MEMO3 | O26: メモ３ | AE26: C | AG26: 100 | AI26: Y
D27: DEL_FLG | O27: 論理削除ＦＬＧ | AE27: F | AI27: N | AK27: 論理削除を示すフラグ
D28: DEL_USR_ID | O28: 論理削除ユーザＩＤ | AE28: C | AG28: 500 | AI28: Y
D29: DEL_USR_NM | O29: 論理削除ユーザ名 | AE29: C | AG29: 100 | AI29: Y
D30: DEL_TS | O30: 論理削除日時 | AE30: TS | AG30: 0 | AI30: Y
D31: INS_USR_ID | O31: 登録ユーザＩＤ | AE31: C | AG31: 500 | AI31: Y
D32: INS_USR_NM | O32: 登録ユーザ名 | AE32: C | AG32: 100 | AI32: Y
D33: INS_TS | O33: 登録日時 | AE33: TS | AG33: 0 | AI33: Y
D34: INS_FUNC_ID | O34: 登録機能ＩＤ | AE34: C | AG34: 50 | AI34: Y
D35: UPD_CNTR | O35: 更新カウンタ | AE35: N | AG35: 9,0 | AI35: Y
D36: UPD_USR_ID | O36: 更新ユーザＩＤ | AE36: C | AG36: 500 | AI36: Y
D37: UPD_USR_NM | O37: 更新ユーザ名 | AE37: C | AG37: 100 | AI37: Y
D38: UPD_TS | O38: 更新日時 | AE38: TS | AG38: 0 | AI38: Y
D39: UPD_FUNC_ID | O39: 更新機能ＩＤ | AE39: C | AG39: 50 | AI39: Y
D40: UPD_SRV_REQ_NO | O40: 更新リクエストＮＯ | AE40: C | AG40: 50 | AI40: Y

Sheet メッセージ一覧
A1: =表紙!A54 -> Webシステム | K1: 文書名 | U1: モジュールID | Z1: =表紙!$AJ$63 -> MS | AE1: モジュール名 | AJ1: =表紙!$AX$63 -> 見積管理 | AS1: 文書番号 | AZ1: Version | BF1: Rev.
K2: =表紙!O64 -> アドオン設計書 | U2: ｻﾌﾞﾓｼﾞｭｰﾙID | Z2: =表紙!$AJ$64 -> MSBB | AE2: ｻﾌﾞﾓｼﾞｭｰﾙ名 | AJ2: =表紙!$AX$64 -> Webシステム | AS2: =表紙!$BL$64 -> M7-US-1140 | AZ2: =表紙!$BU$64 -> 7.0.2 | BF2: =表紙!$CB$64 -> 7
K3: =RIGHT(CELL("filename",$A$1),LEN(CELL("filename",$A$1))-FIND("]",CELL("filename",$A$1))) -> メッセージ一覧 | U3: 表題 | Z3: =表紙!$AJ$65 -> MSBBPA070 | AE3: =表紙!$AQ$65 -> Web受注入力
B6: =RIGHT(CELL("filename",B6),LEN(CELL("filename",B6))-FIND("]",CELL("filename",B6))) -> メッセージ一覧
A8: No | C8: 新/変 | E8: 種別 | G8: メッセージ内容 | AQ8: 備考（パラメータ等） | BG8: メッセージID
A9: 1 | C9: 新 | E9: W | G9: 納期まで製造必要日数を下回っています。要調整！
A10: 2 | C10: 新 | E10: W | G10: 与信限度額を超えています。受注継続するか要確認！
A11: 3 | C11: 新 | E11: W | G11: ｛パラメータ.日付｝が非稼働日です。 | AQ11: 日付
A12: 4 | C12: 新 | E12: W | G12: 該当受注明細は既に｛パラメータ.ステータス｝のため、数量の変更ができません。 | AQ12: ステータス（出荷済、売上済）
A13: 5 | C13: 新 | E13: W | G13: 預り売上数：{パラメータ.預り売上数}が受注残数：{パラメータ.受注残数}を超えています。 預り売上数は、受注残数以下の数量にしてください。 | AQ13: 預り売上数、受注残数 | BM13: REV4.0 預り売上数の項目追加と入力チェック
A14: 6 | C14: 新 | E14: W | G14: 既に生産予定を組んでいるため、変更できません。
A15: 7 | C15: 新 | E15: W | G15: 既に指図済みのため、変更できません。
A16: 8 | C16: 新 | E16: I | G16: 検索結果がありません。 | BG16: E10008
A17: 9 | C17: 新 | E17: W | G17: 更新対象が、他の処理によって更新されています。最新情報を取得してください。 | BG17: W10002
A18: 10 | C18: 新 | E18: W

Sheet 補足説明資料
A1: =表紙!A54 -> Webシステム | O1: 文書名 | AC1: モジュールID | AJ1: =表紙!AJ64 -> MSBB | AQ1: モジュール名 | AX1: =表紙!AX64 -> Webシステム | BL1: 文書番号 | BU1: Version | CB1: Rev.
O2: =表紙!O65 -> 表紙 | AC2: サブモジュールID | AJ2: =表紙!AJ65 -> MSBBPA070 | AQ2: サブモジュール名 | AX2: =表紙!AX65 -> 0 | BL2: =表紙!BL65 -> 0 | BU2: =表紙!BU65 -> 0 | CB2: =表紙!CB65 -> 0
O3: =RIGHT(CELL("filename",$A$1),LEN(CELL("filename",$A$1))-FIND("]",CELL("filename",$A$1))) -> 補足説明資料 | AC3: 表題 | AJ3: =表紙!AJ66 -> 0 | AQ3: =表紙!AQ66 -> 0
AO5: 補足説明
CJ7: REV4.0 WEB受注明細、mcf受注明細の関係を明記
CJ8: REV4.0 WEB受注明細、mcf受注明細の関係を明記
CJ9: REV4.0 WEB受注明細、mcf受注明細の関係を明記
CJ10: REV4.0 WEB受注明細、mcf受注明細の関係を明記
CJ11: REV4.0 WEB受注明細、mcf受注明細の関係を明記
CJ12: REV4.0 WEB受注明細、mcf受注明細の関係を明記
CJ13: REV4.0 WEB受注明細、mcf受注明細の関係を明記
CJ14: REV4.0 WEB受注明細、mcf受注明細の関係を明記
CJ15: REV4.0 WEB受注明細、mcf受注明細の関係を明記
CJ16: REV4.0 WEB受注明細、mcf受注明細の関係を明記
CJ17: REV4.0 WEB受注明細、mcf受注明細の関係を明記
CJ18: REV4.0 WEB受注明細、mcf受注明細の関係を明記
... CJ36: REV4.0 WEB受注明細、mcf受注明細の関係を明記
C37: 本体数量が0で営業サンプルや予備数のみの受注は発生しない | CJ37: REV4.0 WEB受注明細、mcf受注明細の関係を明記
CJ38: REV4.0 WEB受注明細、mcf受注明細の関係を明記
CJ39: REV4.0 WEB受注明細、mcf受注明細の関係を明記
CJ40: REV4.0 WEB受注明細、mcf受注明細の関係を明記
CJ41: REV4.0 WEB受注明細、mcf受注明細の関係を明記
CJ42: REV4.0 WEB受注明細、mcf受注明細の関係を明記
CJ43: REV4.0 WEB受注明細、mcf受注明細の関係を明記
CJ44: REV4.0 WEB受注明細、mcf受注明細の関係を明記
CJ45: REV4.0 WEB受注明細、mcf受注明細の関係を明記
CJ46: REV4.0 WEB受注明細、mcf受注明細の関係を明記
C47: 様々な更新パタンに対応して更新を行う | CJ47: REV4.0 WEB受注明細、mcf受注明細の関係を明記
CJ48: REV4.0 WEB受注明細、mcf受注明細の関係を明記
CJ49: REV4.0 WEB受注明細、mcf受注明細の関係を明記
CJ50: REV4.0 WEB受注明細、mcf受注明細の関係を明記
CJ51: REV4.0 WEB受注明細、mcf受注明細の関係を明記
CJ52: REV4.0 WEB受注明細、mcf受注明細の関係を明記
CJ53: REV4.0 WEB受注明細、mcf受注明細の関係を明記
CJ54: REV4.0 WEB受注明細、mcf受注明細の関係を明記
CJ55: REV4.0 WEB受注明細、mcf受注明細の関係を明記
CJ56: REV4.0 WEB受注明細、mcf受注明細の関係を明記
CJ57: REV4.0 WEB受注明細、mcf受注明細の関係を明記
CJ58: REV4.0 WEB受注明細、mcf受注明細の関係を明記
CJ59: REV4.0 WEB受注明細、mcf受注明細の関係を明記
... CJ75: REV4.0 WEB受注明細、mcf受注明細の関係を明記

Sheet 補足説明資料_仕掛チェック
A1: =表紙!A54 -> Webシステム | O1: 文書名 | AC1: モジュールID | AJ1: =表紙!AJ64 -> MSBB | AQ1: モジュール名 | AX1: =表紙!AX64 -> Webシステム | BL1: 文書番号 | BU1: Version | CB1: Rev.
O2: =表紙!O65 -> 表紙 | AC2: サブモジュールID | AJ2: =表紙!AJ65 -> MSBBPA070 | AQ2: サブモジュール名 | AX2: =表紙!AX65 -> 0 | BL2: =表紙!BL65 -> 0 | BU2: =表紙!BU65 -> 0 | CB2: =表紙!CB65 -> 0
O3: =RIGHT(CELL("filename",$A$1),LEN(CELL("filename",$A$1))-FIND("]",CELL("filename",$A$1))) -> 補足説明資料_仕掛チェック | AC3: 表題 | AJ3: =表紙!AJ66 -> 0 | AQ3: =表紙!AQ66 -> 0
AO5: 補足説明
D7: 仕掛チェック仕様 | CJ7: REV4.0 WEB受注明細、mcf受注明細の関係を明記
D8: № | F8: 生産予定状況 | R8: 出荷・売上状況 | AD8: WEB受注更新可否 | AJ8: 備考１ | CJ8: REV4.0 WEB受注明細、mcf受注明細の関係を明記
D9: 1 | F9: 未登録 | AD9: 更新可能 | AJ9: - | CJ9: REV4.0 WEB受注明細、mcf受注明細の関係を明記
D10: 2 | F10: オーダ全て未確定 | AD10: 更新可能 | AJ10: - | CJ10: REV4.0 WEB受注明細、mcf受注明細の関係を明記
D11: 3 | F11: 保存or確定あり | AD11: 更新不可 | AJ11: メッセージ一覧.NO5表示 | CJ11: REV4.0 WEB受注明細、mcf受注明細の関係を明記
D12: 4 | F12: 一部工程が指図済み | AD12: 更新不可 | AJ12: メッセージ一覧.NO5表示 | CJ12: REV4.0 WEB受注明細、mcf受注明細の関係を明記
D13: 5 | F13: 一部工程が製造完了 | AD13: 更新不可 | AJ13: メッセージ一覧.NO5表示 | CJ13: REV4.0 WEB受注明細、mcf受注明細の関係を明記
D14: 6 | F14: 全て完了 | AD14: 更新不可 | AJ14: メッセージ一覧.NO5表示 | CJ14: REV4.0 WEB受注明細、mcf受注明細の関係を明記
D15: 7 | F15: - | R15: 一部出荷指図済み | AD15: 更新不可 | AJ15: メッセージ一覧.NO4表示 | CJ15: REV4.0 WEB受注明細、mcf受注明細の関係を明記
D16: 8 | F16: - | R16: 一部出荷実績済み | AD16: 更新不可 | AJ16: メッセージ一覧.NO4表示 | CJ16: REV4.0 WEB受注明細、mcf受注明細の関係を明記
D17: 9 | F17: - | R17: 一部売上実績済み | AD17: 更新不可 | AJ17: メッセージ一覧.NO4表示 | CJ17: REV4.0 WEB受注明細、mcf受注明細の関係を明記
CJ18: REV4.0 WEB受注明細、mcf受注明細の関係を明記
CJ19: REV4.0 WEB受注明細、mcf受注明細の関係を明記
CJ20: REV4.0 WEB受注明細、mcf受注明細の関係を明記
CJ21: REV4.0 WEB受注明細、mcf受注明細の関係を明記
CJ22: REV4.0 WEB受注明細、mcf受注明細の関係を明記
CJ23: REV4.0 WEB受注明細、mcf受注明細の関係を明記
CJ24: REV4.0 WEB受注明細、mcf受注明細の関係を明記
CJ25: REV4.0 WEB受注明細、mcf受注明細の関係を明記
CJ26: REV4.0 WEB受注明細、mcf受注明細の関係を明記
CJ27: REV4.0 WEB受注明細、mcf受注明細の関係を明記
CJ28: REV4.0 WEB受注明細、mcf受注明細の関係を明記
CJ29: REV4.0 WEB受注明細、mcf受注明細の関係を明記
... CJ33: REV4.0 WEB受注明細、mcf受注明細の関係を明記

Sheet 補足説明資料_受注画面制御
A1: =表紙!A54 -> Webシステム | O1: 文書名 | AC1: モジュールID | AJ1: =表紙!AJ64 -> MSBB | AQ1: モジュール名 | AX1: =表紙!AX64 -> Webシステム | BL1: 文書番号 | BU1: Version | CB1: Rev.
O2: =表紙!O65 -> 表紙 | AC2: サブモジュールID | AJ2: =表紙!AJ65 -> MSBBPA070 | AQ2: サブモジュール名 | AX2: =表紙!AX65 -> 0 | BL2: =表紙!BL65 -> 0 | BU2: =表紙!BU65 -> 0 | CB2: =表紙!CB65 -> 0
O3: =RIGHT(CELL("filename",$A$1),LEN(CELL("filename",$A$1))-FIND("]",CELL("filename",$A$1))) -> 補足説明資料_受注画面制御 | AC3: 表題 | AJ3: =表紙!AJ66 -> 0 | AQ3: =表紙!AQ66 -> 0
AO5: 補足説明
V7: 受注業務パタン | CJ7: V7.0 画面制御の追加
G8: 画面項目 | V8: 加工受注 | AB8: シート受注 | AH8: 商品購買 | AN8: 版型 | AT8: 有償支給 | AZ8: 経費品 | BF8: 原紙売り（受発注方式） | BL8: 輪切り | CJ8: V7.0 画面制御の追加
G9: 第1画面（TOP画面） 基本情報 | V9: ○ | AB9: ○ | AH9: ○ | AN9: ● | AT9: ○ | AZ9: ○ | BF9: ○ | BL9: ○ | CJ9: V7.0 画面制御の追加
G10: 第1画面（TOP画面） 受注明細 | V10: ○ | AB10: - | AH10: - | AN10: - | AT10: - | AZ10: - | BF10: - | BL10: - | CJ10: V7.0 画面制御の追加
G11: 第2画面（基本情報）基本情報 | V11: 〇 | AB11: 〇 | AH11: 〇 | AN11: ● | AT11: 〇 | AZ11: 〇 | BF11: ○ | BL11: ○ | CJ11: V7.0 画面制御の追加
G12: 第2画面（基本情報）構成情報 | V12: ● | AB12: 〇 | AH12: - | AN12: ● | AT12: - | AZ12: - | BF12: ○ | BL12: ○ | CJ12: V7.0 画面制御の追加
G13: 第2画面（基本情報）仕入情報 | V13: 〇 | AB13: 〇 | AH13: 〇 | AN13: ● | AT13: - | AZ13: - | BF13: ○ | BL13: ○ | CJ13: V7.0 画面制御の追加
G14: 第2画面（基本情報）備考 | V14: 〇 | AB14: 〇 | AH14: 〇 | AN14: ● | AT14: ○ | AZ14: ○ | BF14: ○ | BL14: ○ | CJ14: V7.0 画面制御の追加
G15: 第3画面（工程情報）工程情報 | V15: ● | AB15: 〇 | AH15: - | AN15: - | AT15: - | AZ15: - | BF15: ○ | BL15: ○ | CJ15: V7.0 画面制御の追加
G16: ポップアップ（詳細入力画面）基本情報 | V16: ● | AB16: 〇 | AH16: - | AN16: - | AT16: - | AZ16: - | BF16: ○ | BL16: ○ | CJ16: V7.0 画面制御の追加
G17: ポップアップ（詳細入力画面）外注情報 | V17: ● | AB17: 〇 | AH17: - | AN17: - | AT17: - | AZ17: - | BF17: ○ | BL17: ○ | CJ17: V7.0 画面制御の追加
G18: ポップアップ（詳細入力画面）工程情報 | V18: ● | AB18: 〇 | AH18: - | AN18: - | AT18: - | AZ18: - | BF18: ○ | BL18: ○ | CJ18: V7.0 画面制御の追加
G19: ポップアップ（詳細入力画面）作業明細 | V19: ● | AB19: 〇 | AH19: - | AN19: - | AT19: - | AZ19: - | BF19: ○ | BL19: ○ | CJ19: V7.0 画面制御の追加
... G21: 第4画面（材料設定）材料明細 | V21: ● | AB21: 〇 | AH21: - | AN21: - | AT21: - | AZ21: - | BF21: ○ | BL21: ○ | CJ21: V7.0 画面制御の追加
CJ22: V7.0 画面制御の追加
G23: ※注釈 | CJ23: V7.0 画面制御の追加
H24: 〇：編集可能 | CJ24: V7.0 画面制御の追加
H25: ●：参照のみ | CJ25: V7.0 画面制御の追加
H26: -：非表示 | CJ26: V7.0 画面制御の追加
CJ27: V7.0 画面制御の追加
G28: 受注区分、製品区分の組合せがどの受注業務パタンにあたるかは「受発注パタン詳細」シート参照 | CJ28: V7.0 画面制御の追加
CJ29: V7.0 画面制御の追加

Sheet 受発注パタン詳細
AQ2: -：取得の必要なし | AR2: -：算出の必要なし | AS2: -：算出の必要なし
AG3: MRP | AQ3: 〇：取得可能 | AR3: 〇：算出可能 | AS3: 〇：算出可能
AG4: 受注：手配区分で仕入直送、 | AQ4: ×：取得不可 取得できないことでの問題点を記載 | AR4: ×：算出不可 算出できない理由を記載 | AS4: ×：算出不可 算出できない理由を記載
AG5: 発注点
A6: No | B6: 元No | C6: 受注区分 | D6: 受注区分名 | E6: 製品区分大 | F6: 製品区分大名 | G6: 品目区分 | H6: 品目区分名 | I6: 品目区分詳細ＣＤ | J6: 標準品目区分詳細名 | K6: オーダ区分 | L6: 品目系マスタ登録元 | M6: 製品受注パタン | N6: 受注業務パタン | O6: マスタ登録先 | AC6: 発注先の登録 | AD6: 単位の登録 | AE6: 発注単価の登録先 | AF6: 巻きｍの登録先 | AT6: 「注文書の出力」シート参照 | AW6: V7.0 画面制御の追加
O7: 品目マスタ（共通） | P7: 品目マスタ（会社） | Q7: 品目詳細マスタ | R7: 品目単位マスタ | S7: 品目格納先マスタ | T7: BOMマスタ | U7: 品目工程マスタ | V7: 工程工数マスタ | W7: 得意先販売単価マスタ | X7: 加工単価マスタ | Y7: 購買単価マスタ | Z7: （アドオン）原紙マスタ | AA7: （アドオン）事業所別原紙巾マスタ | AB7: （アドオン）原紙単価マスタ | AG7: 発注予定発生元 | AH7: オーダ発生元 | AI7: 品目CD | AJ7: 枝番１ | AK7: 枝番２ | AL7: 枝番３ | AM7: 単価単位取得 | AN7: 単価取得 | AO7: 巻きｍ取得 | AP7: 発注単位取得 | AQ7: 工程仕様取得 | AR7: 単価算出 | AS7: 重量算出 | AT7: 出力注文書 | AU7: 発注/製造あり | AW7: V7.0 画面制御の追加
A8: 1 | B8: 1 | C8: 21 | D8: シート商品 | E8: 11 | F8: シート | G8: 1(固定値) | H8: 商品 | I8: 111 | J8: 商品シート | K8: 外注 | L8: WEB受注 | M8: CPで取り扱いがある（品目登録済） | N8: シート受注 | O8: ○ | P8: ○ | Q8: ○ | S8: △ | T8: ○ | AC8: WEB受注 | AD8: WEB受注 | AE8: WEB受注 | AF8: - | AG8: MRP | AH8: MRP | AI8: 製品コード(11桁) | AJ8: 連番4桁 | AM8: NULL | AN8: 加工単価マスタ | AO8: NULL | AP8: 発注予定 | AQ8: 〇 | AR8: 〇：加工単価より取得 | AS8: 〇 | AT8: 加工発注書 | AU8: 〇 | AW8: V7.0 画面制御の追加
C9: 21 | D9: シート商品 | E9: 11 | F9: シート | G9: 1(固定値) | H9: 商品 | I9: 111 | J9: 商品シート | K9: 外注 | L9: WEB受注 | M9: CPで取り扱いがある（品目登録済） | N9: シート受注 | O9: ○ | P9: ○ | Q9: ○ | S9: △ | T9: ○ | AC9: WEB受注 | AD9: WEB受注 | AE9: WEB受注 | AF9: - | AG9: 受注 | AH9: - | AI9: 製品コード(11桁) | AJ9: 連番4桁 | AM9: NULL | AN9: 受注 | AO9: NULL | AP9: 受注 | AQ9: 〇 | AR9: 〇：受注明細より取得 | AS9: 〇 | AT9: 加工発注書 | AU9: 〇 | AW9: V7.0 画面制御の追加
A10: 2 | B10: 2 | C10: 21 | D10: シート商品 | E10: 11 | F10: シート | G10: 1(固定値) | H10: 商品 | I10: 111 | J10: 商品シート | K10: 購買 | L10: 品目マスタ | M10: CPで取り扱いが無い（諸口品目） | N10: 商品購買 | O10: ○ | P10: ○ | Q10: ○ | AC10: WEB受注 | AD10: WEB受注 | AE10: WEB受注 | AF10: - | AG10: MRP | AH10: MRP | AI10: 諸口品目 | AM10: NULL | AN10: NULL | AO10: NULL | AP10: 発注予定 | AQ10: ×：仕様が取得できない | AR10: ×：諸口品のため購買単価マスタがない | AS10: - | AT10: 加工発注書 | AU10: 〇 | AW10: V7.0 画面制御の追加
C11: 21 | D11: シート商品 | E11: 11 | F11: シート | G11: 1(固定値) | H11: 商品 | I11: 111 | J11: 商品シート | K11: 購買 | L11: 品目マスタ | M11: CPで取り扱いが無い（諸口品目） | N11: 商品購買 | O11: ○ | P11: ○ | Q11: ○ | AC11: WEB受注 | AD11: WEB受注 | AE11: WEB受注 | AF11: - | AG11: 受注 | AH11: - | AI11: 諸口品目 | AM11: NULL | AN11: 受注 | AO11: NULL | AP11: 受注 | AQ11: ×：仕様が取得できない | AR11: 〇：受注明細より取得 | AS11: - | AT11: 加工発注書 | AU11: 〇 | AW11: V7.0 画面制御の追加
A12: 3 | B12: 3 | C12: 21 | D12: シート商品 | E12: 11 | F12: シート | G12: 1(固定値) | H12: 商品 | I12: 111 | J12: 商品シート | K12: WG間転送 | L12: WEB受注 | M12: CPで取り扱いがある（品目登録済） | N12: シート受注 | O12: ○ | P12: ○ | Q12: ○ | S12: △ | T12: ○ | AC12: - | AD12: - | AE12: - | AF12: - | AG12: MRP | AH12: MRP | AI12: 製品コード(11桁) | AJ12: 連番4桁 | AM12: - | AN12: - | AO12: - | AP12: - | AQ12: - | AR12: - | AS12: - | AT12: - | AU12: 〇 | AW12: V7.0 画面制御の追加
A13: 4 | B13: 4 | C13: 21 | D13: 加工商品 | E13: 12 | F13: 加工 | G13: 1(固定値) | H13: 商品 | I13: 112 | J13: 商品加工 | K13: 外注 | L13: 製品マスタ | M13: CPで取り扱いがある（品目登録済） | N13: 加工品受注 | O13: ○ | P13: ○ | Q13: ○ | S13: △ | T13: ○ | W13: ○ | X13: △ | AC13: 製品マスタ→WEB受注 | AD13: WEB受注 | AE13: WEB受注 | AF13: - | AG13: MRP | AH13: MRP | AI13: 製品コード(11桁) | AJ13: 連番4桁 | AM13: NULL | AN13: 加工単価マスタ | AO13: NULL | AP13: 発注予定 | AQ13: 〇 | AR13: 〇：加工単価より取得 | AS13: 〇 | AT13: 加工発注書 | AU13: 〇 | AW13: V7.0 画面制御の追加
C14: 21 | D14: 加工商品 | E14: 12 | F14: 加工 | G14: 1(固定値) | H14: 商品 | I14: 112 | J14: 商品加工 | K14: 外注 | L14: 製品マスタ | M14: CPで取り扱いがある（品目登録済） | N14: 加工品受注 | O14: ○ | P14: ○ | Q14: ○ | S14: △ | T14: ○ | W14: ○ | X14: △ | AC14: 製品マスタ→WEB受注 | AD14: WEB受注 | AE14: WEB受注 | AF14: - | AG14: 受注 | AH14: - | AI14: 製品コード(11桁) | AJ14: 連番4桁 | AM14: NULL | AN14: 受注 | AO14: NULL | AP14: 受注 | AQ14: 〇 | AR14: 〇：受注明細より取得 | AS14: 〇 | AT14: 加工発注書 | AU14: 〇 | AW14: V7.0 画面制御の追加
A15: 5 | B15: 5 | C15: 21 | D15: 加工商品 | E15: 12 | F15: 加工 | G15: 1(固定値) | H15: 商品 | I15: 112 | J15: 商品加工 | K15: 購買 | L15: 品目マスタ | M15: CPで取り扱いが無い（諸口品目） | N15: 商品購買 | O15: ○ | P15: ○ | Q15: ○ | AC15: WEB受注 | AD15: WEB受注 | AE15: WEB受注 | AF15: - | AG15: MRP | AH15: MRP | AI15: 諸口品目 | AM15: NULL | AN15: NULL | AO15: NULL | AP15: 発注予定 | AQ15: ×：仕様が取得できない | AR15: ×：諸口品のため購買単価マスタがない | AS15: - | AT15: 加工発注書 | AU15: 〇 | AW15: V7.0 画面制御の追加
C16: 21 | D16: 加工商品 | E16: 12 | F16: 加工 | G16: 1(固定値) | H16: 商品 | I16: 112 | J16: 商品加工 | K16: 購買 | L16: 品目マスタ | M16: CPで取り扱いが無い（諸口品目） | N16: 商品購買 | O16: ○ | P16: ○ | Q16: ○ | AC16: WEB受注 | AD16: WEB受注 | AE16: WEB受注 | AF16: - | AG16: 受注 | AH16: - | AI16: 諸口品目 | AM16: NULL | AN16: 受注 | AO16: NULL | AP16: 受注 | AQ16: ×：仕様が取得できない | AR16: 〇：受注明細より取得 | AS16: - | AT16: 加工発注書 | AU16: 〇 | AW16: V7.0 画面制御の追加
A17: 6 | B17: 6 | C17: 21 | D17: 加工商品 | E17: 12 | F17: 加工 | G17: 1(固定値) | H17: 商品 | I17: 112 | J17: 商品加工 | K17: WG間転送 | L17: 製品マスタ | M17: CPで取り扱いがある（品目登録済） | N17: 加工品受注 | O17: ○ | P17: ○ | Q17: ○ | S17: △ | T17: ○ | W17: ○ | AC17: - | AD17: - | AE17: - | AF17: - | AG17: MRP | AH17: MRP | AI17: 製品コード(11桁) | AJ17: 連番4桁 | AM17: - | AN17: - | AO17: - | AP17: - | AQ17: - | AR17: - | AS17: - | AT17: - | AU17: 〇 | AW17: V7.0 画面制御の追加
A18: 7 | B18: 7 | C18: 11 | D18: 加工商品 | E18: 13 | F18: Ｇプリント | G18: 1(固定値) | H18: 商品 | I18: 113 | J18: 商品Ｇプリント | K18: 外注 | L18: 製品マスタ | M18: CPで取り扱いがある（品目登録済） | N18: 加工品受注 | O18: ○ | P18: ○ | Q18: ○ | S18: △ | T18: ○ | W18: ○ | X18: △ | AC18: 製品マスタ→WEB受注 | AD18: 製品マスタ→WEB受注 | AE18: 加工単価→WEB受注 | AF18: - | AG18: MRP | AH18: MRP | AI18: 製品コード(11桁) | AJ18: 連番4桁 | AM18: NULL | AN18: 加工単価マスタ | AO18: NULL | AP18: 発注予定 | AQ18: 〇 | AR18: 〇：加工単価より取得 | AS18: 〇 | AT18: 加工発注書 | AU18: 〇 | AW18: V7.0 画面制御の追加
C19: 11 | D19: 加工商品 | E19: 13 | F19: Ｇプリント | G19: 1(固定値) | H19: 商品 | I19: 113 | J19: 商品Ｇプリント | K19: 外注 | L19: 製品マスタ | M19: CPで取り扱いがある（品目登録済） | N19: 加工品受注 | O19: ○ | P19: ○ | Q19: ○ | S19: △ | T19: ○ | W19: ○ | X19: △ | AC19: 製品マスタ→WEB受注 | AD19: 製品マスタ→WEB受注 | AE19: 加工単価→WEB受注 | AF19: - | AG19: 受注 | AH19: - | AI19: 製品コード(11桁) | AJ19: 連番4桁 | AM19: NULL | AN19: 受注 | AO19: NULL | AP19: 受注 | AQ19: 〇 | AR19: 〇：受注明細より取得 | AS19: 〇 | AT19: 加工発注書 | AU19: 〇 | AW19: V7.0 画面制御の追加
A20: 8 | B20: 8 | C20: 11 | D20: 加工商品 | E20: 13 | F20: Ｇプリント | G20: 1(固定値) | H20: 商品 | I20: 113 | J20: 商品Ｇプリント | K20: 購買 | L20: 品目マスタ | M20: CPで取り扱いが無い（諸口品目） | N20: 商品購買 | O20: ○ | P20: ○ | Q20: ○ | AC20: WEB受注 | AD20: WEB受注 | AE20: WEB受注 | AF20: - | AG20: MRP | AH20: MRP | AI20: 諸口品目 | AM20: NULL | AN20: NULL | AO20: NULL | AP20: 発注予定 | AQ20: ×：仕様が取得できない | AR20: ×：諸口品のため購買単価マスタがない | AS20: - | AT20: 加工発注書 | AU20: 〇 | AW20: V7.0 画面制御の追加
C21: 11 | D21: 加工商品 | E21: 13 | F21: Ｇプリント | G21: 1(固定値) | H21: 商品 | I21: 113 | J21: 商品Ｇプリント | K21: 購買 | L21: 品目マスタ | M21: CPで取り扱いが無い（諸口品目） | N21: 商品購買 | O21: ○ | P21: ○ | Q21: ○ | AC21: WEB受注 | AD21: WEB受注 | AE21: WEB受注 | AF21: - | AG21: 受注 | AH21: - | AI21: 諸口品目 | AM21: NULL | AN21: 受注 | AO21: NULL | AP21: 受注 | AQ21: ×：仕様が取得できない | AR21: 〇：受注明細より取得 | AS21: - | AT21: 加工発注書 | AU21: 〇 | AW21: V7.0 画面制御の追加
A22: 9 | B22: 9 | C22: 11 | D22: 加工商品 | E22: 13 | F22: Ｇプリント | G22: 1(固定値) | H22: 商品 | I22: 113 | J22: 商品Ｇプリント | K22: WG間転送 | L22: 製品マスタ | M22: CPで取り扱いがある（品目登録済） | N22: 加工品受注 | O22: ○ | P22: ○ | Q22: ○ | S22: △ | T22: ○ | W22: ○ | AC22: - | AD22: - | AE22: - | AF22: - | AG22: MRP | AH22: MRP | AI22: 製品コード(11桁) | AJ22: 連番4桁 | AM22: - | AN22: - | AO22: - | AP22: - | AQ22: - | AR22: - | AS22: - | AT22: - | AU22: 〇 | AW22: V7.0 画面制御の追加
A23: 10 | B23: 10 | C23: 11 | D23: 加工商品 | E23: 21 | F23: 巻ボール | G23: 1(固定値) | H23: 商品 | I23: 121 | J23: 商品巻ボール | K23: 外注 | L23: 製品マスタ | M23: CPで取り扱いがある（品目登録済） | N23: 加工品受注 | O23: ○ | P23: ○ | Q23: ○ | S23: △ | T23: ○ | W23: ○ | X23: △ | AC23: 製品マスタ→WEB受注 | AD23: 製品マスタ→WEB受注 | AE23: 加工単価→WEB受注 | AF23: WEB受注 | AG23: MRP | AH23: MRP | AI23: 製品コード(11桁) | AJ23: 連番4桁 | AM23: NULL | AN23: 加工単価マスタ | AO23: NULL | AP23: 発注予定 | AQ23: 〇 | AR23: 〇：加工単価より取得 | AS23: 〇 | AT23: 加工発注書 | AU23: 〇 | AW23: V7.0 画面制御の追加
C24: 11 | D24: 加工商品 | E24: 21 | F24: 巻ボール | G24: 1(固定値) | H24: 商品 | I24: 121 | J24: 商品巻ボール | K24: 外注 | L24: 製品マスタ | M24: CPで取り扱いがある（品目登録済） | N24: 加工品受注 | O24: ○ | P24: ○ | Q24: ○ | S24: △ | T24: ○ | W24: ○ | X24: △ | AC24: 製品マスタ→WEB受注 | AD24: 製品マスタ→WEB受注 | AE24: 加工単価→WEB受注 | AF24: WEB受注 | AG24: 受注 | AH24: - | AI24: 製品コード(11桁) | AJ24: 連番4桁 | AM24: NULL | AN24: 受注 | AO24: NULL | AP24: 受注 | AQ24: 〇 | AR24: 〇：受注明細より取得 | AS24: 〇 | AT24: 加工発注書 | AU24: 〇 | AW24: V7.0 画面制御の追加
A25: 11 | B25: 11 | C25: 11 | D25: 加工商品 | E25: 21 | F25: 巻ボール | G25: 1(固定値) | H25: 商品 | I25: 121 | J25: 商品巻ボール | K25: 購買 | L25: 品目マスタ | M25: CPで取り扱いが無い（諸口品目） | N25: 商品購買 | O25: ○ | P25: ○ | Q25: ○ | R25: ○ | AC25: WEB受注 | AD25: WEB受注 | AE25: WEB受注 | AF25: - | AG25: MRP | AH25: MRP | AI25: 諸口品目 | AM25: NULL | AN25: NULL | AO25: NULL | AP25: 発注予定 | AQ25: ×：仕様が取得できない | AR25: ×：諸口品のため購買単価マスタがない | AS25: - | AT25: 加工発注書 | AU25: 〇 | AW25: V7.0 画面制御の追加
C26: 11 | D26: 加工商品 | E26: 21 | F26: 巻ボール | G26: 1(固定値) | H26: 商品 | I26: 121 | J26: 商品巻ボール | K26: 購買 | L26: 品目マスタ | M26: CPで取り扱いが無い（諸口品目） | N26: 商品購買 | O26: ○ | P26: ○ | Q26: ○ | R26: ○ | AC26: WEB受注 | AD26: WEB受注 | AE26: WEB受注 | AF26: - | AG26: 受注 | AH26: - | AI26: 諸口品目 | AM26: NULL | AN26: 受注 | AO26: NULL | AP26: 受注 | AQ26: ×：仕様が取得できない | AR26: 〇：受注明細より取得 | AS26: - | AT26: 加工発注書 | AU26: 〇 | AW26: V7.0 画面制御の追加
A27: 12 | B27: 12 | C27: 11 | D27: 加工商品 | E27: 21 | F27: 巻ボール | G27: 1(固定値) | H27: 商品 | I27: 121 | J27: 商品巻ボール | K27: WG間転送 | L27: 製品マスタ | M27: CPで取り扱いがある（品目登録済） | N27: 加工品受注 | O27: ○ | P27: ○ | Q27: ○ | S27: △ | T27: ○ | W27: ○ | AC27: - | AD27: - | AE27: - | AF27: - | AG27: MRP | AH27: MRP | AI27: 製品コード(11桁) | AJ27: 連番4桁 | AM27: - | AN27: - | AO27: - | AP27: - | AQ27: - | AR27: - | AS27: - | AT27: - | AU27: 〇 | AW27: V7.0 画面制御の追加
A28: 13 | B28: 13 | C28: 21 | D28: シート商品 | E28: 22 | F28: 片面シート | G28: 1(固定値) | H28: 商品 | I28: 122 | J28: 商品片面シート | K28: 外注 | L28: WEB受注 | M28: CPで取り扱いがある（品目登録済） | N28: シート受注 | O28: ○ | P28: ○ | Q28: ○ | S28: △ | T28: ○ | AC28: WEB受注 | AD28: WEB受注 | AE28: WEB受注 | AF28: - | AG28: MRP | AH28: MRP | AI28: 製品コード(11桁) | AJ28: 連番4桁 | AM28: NULL | AN28: 加工単価マスタ | AO28: NULL | AP28: 発注予定 | AQ28: 〇 | AR28: 〇：加工単価より取得 | AS28: 〇 | AT28: 加工発注書 | AU28: 〇 | AW28: V7.0 画面制御の追加
C29: 21 | D29: シート商品 | E29: 22 | F29: 片面シート | G29: 1(固定値) | H29: 商品 | I29: 122 | J29: 商品片面シート | K29: 外注 | L29: WEB受注 | M29: CPで取り扱いがある（品目登録済） | N29: シート受注 | O29: ○ | P29: ○ | Q29: ○ | S29: △ | T29: ○ | AC29: WEB受注 | AD29: WEB受注 | AE29: WEB受注 | AF29: - | AG29: 受注 | AH29: - | AI29: 製品コード(11桁) | AJ29: 連番4桁 | AM29: NULL | AN29: 受注 | AO29: NULL | AP29: 受注 | AQ29: 〇 | AR29: 〇：受注明細より取得 | AS29: 〇 | AT29: 加工発注書 | AU29: 〇 | AW29: V7.0 画面制御の追加
A30: 14 | B30: 14 | C30: 21 | D30: シート商品 | E30: 22 | F30: 片面シート | G30: 1(固定値) | H30: 商品 | I30: 122 | J30: 商品片面シート | K30: 購買 | L30: 品目マスタ | M30: CPで取り扱いが無い（諸口品目） | N30: 商品購買 | O30: ○ | P30: ○ | Q30: ○ | AC30: WEB受注 | AD30: WEB受注 | AE30: WEB受注 | AF30: - | AG30: MRP | AH30: MRP | AI30: 諸口品目 | AM30: NULL | AN30: NULL | AO30: NULL | AP30: 発注予定 | AQ30: ×：仕様が取得できない | AR30: ×：諸口品のため購買単価マスタがない | AS30: - | AT30: 加工発注書 | AU30: 〇 | AW30: V7.0 画面制御の追加
C31: 21 | D31: シート商品 | E31: 22 | F31: 片面シート | G31: 1(固定値) | H31: 商品 | I31: 122 | J31: 商品片面シート | K31: 購買 | L31: 品目マスタ | M31: CPで取り扱いが無い（諸口品目） | N31: 商品購買 | O31: ○ | P31: ○ | Q31: ○ | AC31: WEB受注 | AD31: WEB受注 | AE31: WEB受注 | AF31: - | AG31: 受注 | AH31: - | AI31: 諸口品目 | AM31: NULL | AN31: 受注 | AO31: NULL | AP31: 受注 | AQ31: ×：仕様が取得できない | AR31: 〇：受注明細より取得 | AS31: - | AT31: 加工発注書 | AU31: 〇 | AW31: V7.0 画面制御の追加
A32: 15 | B32: 15 | C32: 21 | D32: シート商品 | E32: 22 | F32: 片面シート | G32: 1(固定値) | H32: 商品 | I32: 122 | J32: 商品片面シート | K32: WG間転送 | L32: WEB受注 | M32: CPで取り扱いがある（品目登録済） | N32: シート受注 | O32: ○ | P32: ○ | Q32: ○ | S32: △ | T32: ○ | AC32: - | AD32: - | AE32: - | AF32: - | AG32: MRP | AH32: MRP | AI32: 製品コード(11桁) | AJ32: 連番4桁 | AM32: - | AN32: - | AO32: - | AP32: - | AQ32: - | AR32: - | AS32: - | AT32: - | AU32: 〇 | AW32: V7.0 画面制御の追加
A33: 16 | B33: 16 | C33: 11 | D33: 加工商品 | E33: 23 | F33: 片面加工 | G33: 1(固定値) | H33: 商品 | I33: 123 | J33: 商品片面加工 | K33: 外注 | L33: 製品マスタ | M33: CPで取り扱いがある（品目登録済） | N33: 加工品受注 | O33: ○ | P33: ○ | Q33: ○ | S33: △ | T33: ○ | W33: ○ | X33: △ | AC33: 製品マスタ→WEB受注 | AD33: 製品マスタ→WEB受注 | AE33: 加工単価→WEB受注 | AF33: - | AG33: MRP | AH33: MRP | AI33: 製品コード(11桁) | AJ33: 連番4桁 | AM33: NULL | AN33: 加工単価マスタ | AO33: NULL | AP33: 発注予定 | AQ33: 〇 | AR33: 〇：加工単価より取得 | AS33: 〇 | AT33: 加工発注書 | AU33: 〇 | AW33: V7.0 画面制御の追加
C34: 11 | D34: 加工商品 | E34: 23 | F34: 片面加工 | G34: 1(固定値) | H34: 商品 | I34: 123 | J34: 商品片面加工 | K34: 外注 | L34: 製品マスタ | M34: CPで取り扱いがある（品目登録済） | N34: 加工品受注 | O34: ○ | P34: ○ | Q34: ○ | S34: △ | T34: ○ | W34: ○ | X34: △ | AC34: 製品マスタ→WEB受注 | AD34: 製品マスタ→WEB受注 | AE34: 加工単価→WEB受注 | AF34: - | AG34: 受注 | AH34: - | AI34: 製品コード(11桁) | AJ34: 連番4桁 | AM34: NULL | AN34: 受注 | AO34: NULL | AP34: 受注 | AQ34: 〇 | AR34: 〇：受注明細より取得 | AS34: 〇 | AT34: 加工発注書 | AU34: 〇 | AW34: V7.0 画面制御の追加
A35: 17 | B35: 17 | C35: 11 | D35: 加工商品 | E35: 23 | F35: 片面加工 | G35: 1(固定値) | H35: 商品 | I35: 123 | J35: 商品片面加工 | K35: 購買 | L35: 品目マスタ | M35: CPで取り扱いが無い（諸口品目） | N35: 商品購買 | O35: ○ | P35: ○ | Q35: ○ | AC35: WEB受注 | AD35: WEB受注 | AE35: WEB受注 | AF35: - | AG35: MRP | AH35: MRP | AI35: 諸口品目 | AM35: NULL | AN35: NULL | AO35: NULL | AP35: 発注予定 | AQ35: ×：仕様が取得できない | AR35: ×：諸口品のため購買単価マスタがない | AS35: - | AT35: 加工発注書 | AU35: 〇 | AW35: V7.0 画面制御の追加
C36: 11 | D36: 加工商品 | E36: 23 | F36: 片面加工 | G36: 1(固定値) | H36: 商品 | I36: 123 | J36: 商品片面加工 | K36: 購買 | L36: 品目マスタ | M36: CPで取り扱いが無い（諸口品目） | N36: 商品購買 | O36: ○ | P36: ○ | Q36: ○ | AC36: WEB受注 | AD36: WEB受注 | AE36: WEB受注 | AF36: - | AG36: 受注 | AH36: - | AI36: 諸口品目 | AM36: NULL | AN36: 受注 | AO36: NULL | AP36: 受注 | AQ36: ×：仕様が取得できない | AR36: 〇：受注明細より取得 | AS36: - | AT36: 加工発注書 | AU36: 〇 | AW36: V7.0 画面制御の追加
A37: 18 | B37: 18 | C37: 11 | D37: 加工商品 | E37: 23 | F37: 片面加工 | G37: 1(固定値) | H37: 商品 | I37: 123 | J37: 商品片面加工 | K37: WG間転送 | L37: 製品マスタ | M37: CPで取り扱いがある（品目登録済） | N37: 加工品受注 | O37: ○ | P37: ○ | Q37: ○ | S37: △ | T37: ○ | W37: ○ | AC37: - | AD37: - | AE37: - | AF37: - | AG37: MRP | AH37: MRP | AI37: 製品コード(11桁) | AJ37: 連番4桁 | AM37: - | AN37: - | AO37: - | AP37: - | AQ37: - | AR37: - | AS37: - | AT37: - | AU37: 〇 | AW37: V7.0 画面制御の追加
A38: 19 | B38: 19 | C38: 11 | D38: 加工商品 | E38: 31 | F38: プリフル | G38: 1(固定値) | H38: 商品 | I38: 131 | J38: 商品プリフル | K38: 外注 | L38: 製品マスタ | M38: CPで取り扱いがある（品目登録済） | N38: 加工品受注 | O38: ○ | P38: ○ | Q38: ○ | S38: △ | T38: ○ | W38: ○ | X38: △ | AC38: 製品マスタ→WEB受注 | AD38: 製品マスタ→WEB受注 | AE38: 加工単価→WEB受注 | AF38: - | AG38: MRP | AH38: MRP | AI38: 製品コード(11桁) | AJ38: 連番4桁 | AM38: NULL | AN38: 加工単価マスタ | AO38: NULL | AP38: 発注予定 | AQ38: 〇 | AR38: 〇：加工単価より取得 | AS38: 〇 | AT38: 加工発注書 | AU38: 〇 | AW38: V7.0 画面制御の追加
C39: 11 | D39: 加工商品 | E39: 31 | F39: プリフル | G39: 1(固定値) | H39: 商品 | I39: 131 | J39: 商品プリフル | K39: 外注 | L39: 製品マスタ | M39: CPで取り扱いがある（品目登録済） | N39: 加工品受注 | O39: ○ | P39: ○ | Q39: ○ | S39: △ | T39: ○ | W39: ○ | X39: △ | AC39: 製品マスタ→WEB受注 | AD39: 製品マスタ→WEB受注 | AE39: 加工単価→WEB受注 | AF39: - | AG39: 受注 | AH39: - | AI39: 製品コード(11桁) | AJ39: 連番4桁 | AM39: NULL | AN39: 受注 | AO39: NULL | AP39: 受注 | AQ39: 〇 | AR39: 〇：受注明細より取得 | AS39: 〇 | AT39: 加工発注書 | AU39: 〇 | AW39: V7.0 画面制御の追加
A40: 20 | B40: 20 | C40: 11 | D40: 加工商品 | E40: 31 | F40: プリフル | G40: 1(固定値) | H40: 商品 | I40: 131 | J40: 商品プリフル | K40: 購買 | L40: 品目マスタ | M40: CPで取り扱いが無い（諸口品目） | N40: 商品購買 | O40: ○ | P40: ○ | Q40: ○ | AC40: WEB受注 | AD40: WEB受注 | AE40: WEB受注 | AF40: - | AG40: MRP | AH40: MRP | AI40: 諸口品目 | AM40: NULL | AN40: NULL | AO40: NULL | AP40: 発注予定 | AQ40: ×：仕様が取得できない | AR40: ×：諸口品のため購買単価マスタがない | AS40: - | AT40: 加工発注書 | AU40: 〇 | AW40: V7.0 画面制御の追加
C41: 11 | D41: 加工商品 | E41: 31 | F41: プリフル | G41: 1(固定値) | H41: 商品 | I41: 131 | J41: 商品プリフル | K41: 購買 | L41: 品目マスタ | M41: CPで取り扱いが無い（諸口品目） | N41: 商品購買 | O41: ○ | P41: ○ | Q41: ○ | AC41: WEB受注 | AD41: WEB受注 | AE41: WEB受注 | AF41: - | AG41: 受注 | AH41: - | AI41: 諸口品目 | AM41: NULL | AN41: 受注 | AO41: NULL | AP41: 受注 | AQ41: ×：仕様が取得できない | AR41: 〇：受注明細より取得 | AS41: - | AT41: 加工発注書 | AU41: 〇 | AW41: V7.0 画面制御の追加
A42: 21 | B42: 21 | C42: 11 | D42: 加工商品 | E42: 31 | F42: プリフル | G42: 1(固定値) | H42: 商品 | I42: 131 | J42: 商品プリフル | K42: WG間転送 | L42: 製品マスタ | M42: CPで取り扱いがある（品目登録済） | N42: 加工品受注 | O42: ○ | P42: ○ | Q42: ○ | S42: △ | T42: ○ | W42: ○ | AC42: - | AD42: - | AE42: - | AF42: - | AG42: MRP | AH42: MRP | AI42: 製品コード(11桁) | AJ42: 連番4桁 | AM42: - | AN42: - | AO42: - | AP42: - | AQ42: - | AR42: - | AS42: - | AT42: - | AU42: 〇 | AW42: V7.0 画面制御の追加
A43: 22 | B43: 22 | C43: 11 | D43: 加工商品 | E43: 32 | F43: 刷本支給 | G43: 1(固定値) | H43: 商品 | I43: 132 | J43: 商品刷本支給 | K43: 外注 | L43: 製品マスタ | M43: CPで取り扱いがある（品目登録済） | N43: 加工品受注 | O43: ○ | P43: ○ | Q43: ○ | S43: △ | T43: ○ | W43: ○ | X43: △ | AC43: 製品マスタ→WEB受注 | AD43: 製品マスタ→WEB受注 | AE43: 加工単価→WEB受注 | AF43: - | AG43: MRP | AH43: MRP | AI43: 製品コード(11桁) | AJ43: 連番4桁 | AM43: NULL | AN43: 加工単価マスタ | AO43: NULL | AP43: 発注予定 | AQ43: 〇 | AR43: 〇：加工単価より取得 | AS43: 〇 | AT43: 加工発注書 | AU43: 〇 | AW43: V7.0 画面制御の追加
C44: 11 | D44: 加工商品 | E44: 32 | F44: 刷本支給 | G44: 1(固定値) | H44: 商品 | I44: 132 | J44: 商品刷本支給 | K44: 外注 | L44: 製品マスタ | M44: CPで取り扱いがある（品目登録済） | N44: 加工品受注 | O44: ○ | P44: ○ | Q44: ○ | S44: △ | T44: ○ | W44: ○ | X44: △ | AC44: 製品マスタ→WEB受注 | AD44: 製品マスタ→WEB受注 | AE44: 加工単価→WEB受注 | AF44: - | AG44: 受注 | AH44: - | AI44: 製品コード(11桁) | AJ44: 連番4桁 | AM44: NULL | AN44: 受注 | AO44: NULL | AP44: 受注 | AQ44: 〇 | AR44: 〇：受注明細より取得 | AS44: 〇 | AT44: 加工発注書 | AU44: 〇 | AW44: V7.0 画面制御の追加
A45: 23 | B45: 23 | C45: 11 | D45: 加工商品 | E45: 32 | F45: 刷本支給 | G45: 1(固定値) | H45: 商品 | I45: 132 | J45: 商品刷本支給 | K45: 購買 | L45: 品目マスタ | M45: CPで取り扱いが無い（諸口品目） | N45: 商品購買 | O45: ○ | P45: ○ | Q45: ○ | AC45: WEB受注 | AD45: WEB受注 | AE45: WEB受注 | AF45: - | AG45: MRP | AH45: MRP | AI45: 諸口品目 | AM45: NULL | AN45: NULL | AO45: NULL | AP45: 発注予定 | AQ45: ×：仕様が取得できない | AR45: ×：諸口品のため購買単価マスタがない | AS45: - | AT45: 加工発注書 | AU45: 〇 | AW45: V7.0 画面制御の追加
C46: 11 | D46: 加工商品 | E46: 32 | F46: 刷本支給 | G46: 1(固定値) | H46: 商品 | I46: 132 | J46: 商品刷本支給 | K46: 購買 | L46: 品目マスタ | M46: CPで取り扱いが無い（諸口品目） | N46: 商品購買 | O46: ○ | P46: ○ | Q46: ○ | AC46: WEB受注 | AD46: WEB受注 | AE46: WEB受注 | AF46: - | AG46: 受注 | AH46: - | AI46: 諸口品目 | AM46: NULL | AN46: 受注 | AO46: NULL | AP46: 受注 | AQ46: ×：仕様が取得できない | AR46: 〇：受注明細より取得 | AS46: - | AT46: 加工発注書 | AU46: 〇 | AW46: V7.0 画面制御の追加
A47: 24 | B47: 24 | C47: 11 | D47: 加工商品 | E47: 32 | F47: 刷本支給 | G47: 1(固定値) | H47: 商品 | I47: 132 | J47: 商品刷本支給 | K47: WG間転送 | L47: 製品マスタ | M47: CPで取り扱いがある（品目登録済） | N47: 加工品受注 | O47: ○ | P47: ○ | Q47: ○ | S47: △ | W47: ○ | AC47: - | AD47: - | AE47: - | AF47: - | AG47: MRP | AH47: MRP | AI47: 製品コード(11桁) | AJ47: 連番4桁 | AM47: - | AN47: - | AO47: - | AP47: - | AQ47: - | AR47: - | AS47: - | AT47: - | AU47: 〇 | AW47: V7.0 画面制御の追加
A48: 25 | B48: 25 | C48: 40 | D48: 原紙 | E48: 33 | F48: コートボール | G48: 1(固定値) | H48: 商品 | I48: 133 | J48: 商品コートボール | K48: 購買 | L48: 品目マスタ | M48: CPで取り扱いが無い（諸口品目） | N48: 商品購買 | O48: ○ | P48: ○ | Q48: ○ | R48: ○ | AC48: WEB受注 | AD48: WEB受注 | AE48: WEB受注 | AF48: - | AG48: MRP | AH48: MRP | AI48: 製品コード(11桁) | AJ48: 連番4桁 | AM48: 原紙単価 | AN48: 原紙単価 | AO48: NULL | AP48: 発注予定 | AQ48: ×：寸法が取得できない | AR48: ×：寸法の取得ができない？ | AS48: ×：寸法(巾・流れ)、坪量が取得できない | AT48: 加工発注書 | AU48: 〇 | AW48: V7.0 画面制御の追加
C49: 40 | D49: 原紙 | E49: 33 | F49: コートボール | G49: 1(固定値) | H49: 商品 | I49: 133 | J49: 商品コートボール | K49: 購買 | L49: 品目マスタ | M49: CPで取り扱いが無い（諸口品目） | N49: 商品購買 | O49: ○ | P49: ○ | Q49: ○ | R49: ○ | AC49: WEB受注 | AD49: WEB受注 | AE49: WEB受注 | AF49: - | AG49: 受注 | AH49: - | AI49: 製品コード(11桁) | AJ49: 連番4桁 | AM49: 受注 | AN49: 受注 | AO49: NULL | AP49: 受注 | AQ49: ×：寸法が取得できない | AR49: ×：各項目を受注明細より取得するが、単価単位によっては(kgや㎡など)算出不可 | AS49: ×：寸法(巾・流れ)、坪量が取得できない | AT49: 加工発注書 | AU49: 〇 | AW49: V7.0 画面制御の追加
A50: 26 | B50: 26 | C50: 40 | D50: 原紙 | E50: 33 | F50: コートボール | G50: 1(固定値) | H50: 商品 | I50: 133 | J50: 商品コートボール | K50: 外注 | L50: 製品マスタ | M50: CPで取り扱いがある（品目登録済） | N50: 加工品受注 | O50: ○ | P50: ○ | Q50: ○ | R50: ○ | T50: 〇 | W50: ○ | X50: △ | AC50: 製品マスタ→WEB受注 | AD50: 製品マスタ→WEB受注 | AE50: 加工単価→WEB受注 | AF50: - | AG50: MRP | AH50: MRP | AI50: 諸口品目 | AM50: NULL | AN50: NULL | AO50: NULL | AP50: 発注予定 | AQ50: ×：寸法が取得できない | AR50: ×：諸口品のため加工単価が存在しない | AS50: ×：寸法(巾・流れ)、坪量が取得できない | AT50: 加工発注書 | AU50: 〇 | AW50: V7.0 画面制御の追加
C51: 40 | D51: 原紙 | E51: 33 | F51: コートボール | G51: 1(固定値) | H51: 商品 | I51: 133 | J51: 商品コートボール | K51: 外注 | L51: 製品マスタ | M51: CPで取り扱いがある（品目登録済） | N51: 加工品受注 | O51: ○ | P51: ○ | Q51: ○ | R51: ○ | T51: 〇 | W51: ○ | X51: △ | AC51: 製品マスタ→WEB受注 | AD51: 製品マスタ→WEB受注 | AE51: 加工単価→WEB受注 | AF51: - | AG51: 受注 | AH51: - | AI51: 諸口品目 | AM51: 受注 | AN51: 受注 | AO51: NULL | AP51: 受注 | AQ51: ×：寸法が取得できない | AR51: 〇：受注明細より取得 | AS51: ×：寸法(巾・流れ)、坪量が取得できない | AT51: 加工発注書 | AU51: 〇 | AW51: V7.0 画面制御の追加
A52: 27 | B52: 27 | C52: 40 | D52: 原紙 | E52: 33 | F52: コートボール | G52: 1(固定値) | H52: 商品 | I52: 133 | J52: 商品コートボール | K52: WG間転送 | L52: 製品マスタ | M52: CPで取り扱いがある（品目登録済） | N52: 加工品受注 | O52: ○ | P52: ○ | Q52: ○ | R52: ○ | S52: △ | T52: ○ | W52: ○ | AC52: - | AD52: - | AE52: - | AF52: - | AG52: MRP | AH52: MRP | AI52: 製品コード(11桁) | AJ52: 連番4桁 | AM52: - | AN52: - | AO52: - | AP52: - | AQ52: - | AR52: - | AS52: - | AT52: - | AU52: 〇 | AW52: V7.0 画面制御の追加
A53: 28 | B53: 28 | C53: 40 | D53: 原紙 | E53: 41 | F53: 生原紙 | G53: 1(固定値) | H53: 商品 | I53: 141 | J53: 商品原紙 | K53: 購買 | L53: 品目マスタ | M53: CPで取り扱いが無い（諸口品目） | N53: 商品購買 | O53: ○ | P53: ○ | Q53: ○ | R53: ○ | AC53: WEB受注 | AD53: WEB受注 | AE53: WEB受注 | AF53: - | AG53: MRP | AH53: MRP | AI53: 諸口品目 | AM53: NULL | AN53: NULL | AO53: 単価単位マスタ | AP53: 発注予定 | AQ53: ×：仕様が取得できない | AR53: ×：諸口品のため購買単価マスタがない | AS53: - | AT53: 加工発注書 | AU53: 〇 | AW53: V7.0 画面制御の追加
C54: 40 | D54: 原紙 | E54: 41 | F54: 生原紙 | G54: 1(固定値) | H54: 商品 | I54: 141 | J54: 商品原紙 | K54: 購買 | L54: 品目マスタ | M54: CPで取り扱いが無い（諸口品目） | N54: 商品購買 | O54: ○ | P54: ○ | Q54: ○ | R54: ○ | AC54: WEB受注 | AD54: WEB受注 | AE54: WEB受注 | AF54: - | AG54: 受注 | AH54: - | AI54: 諸口品目 | AM54: 受注 | AN54: 受注 | AO54: 受注 | AP54: 受注 | AQ54: ×：仕様が取得できない | AR54: 〇：受注明細より取得 | AS54: - | AT54: 加工発注書 | AU54: 〇 | AW54: V7.0 画面制御の追加
A55: 29 | B55: 29 | C55: 40 | D55: 原紙 | E55: 42 | F55: 印刷原紙 | G55: 1(固定値) | H55: 商品 | I55: 142 | J55: 商品印刷原紙 | K55: 購買 | L55: 品目マスタ | M55: CPで取り扱いが無い（諸口品目） | N55: 商品購買 | O55: ○ | P55: ○ | Q55: ○ | R55: ○ | AC55: WEB受注 | AD55: WEB受注 | AE55: WEB受注 | AF55: - | AG55: MRP | AH55: MRP | AI55: 諸口品目 | AM55: NULL | AN55: NULL | AO55: 単価単位マスタ | AP55: 発注予定 | AQ55: ×：仕様が取得できない | AR55: ×：諸口品のため購買単価マスタがない | AS55: - | AT55: 加工発注書 | AU55: 〇 | AW55: V7.0 画面制御の追加
C56: 40 | D56: 原紙 | E56: 42 | F56: 印刷原紙 | G56: 1(固定値) | H56: 商品 | I56: 142 | J56: 商品印刷原紙 | K56: 購買 | L56: 品目マスタ | M56: CPで取り扱いが無い（諸口品目） | N56: 商品購買 | O56: ○ | P56: ○ | Q56: ○ | R56: ○ | AC56: WEB受注 | AD56: WEB受注 | AE56: WEB受注 | AF56: - | AG56: 受注 | AH56: - | AI56: 諸口品目 | AM56: 受注 | AN56: 受注 | AO56: 受注 | AP56: 受注 | AQ56: ×：仕様が取得できない | AR56: 〇：受注明細より取得 | AS56: - | AT56: 加工発注書 | AU56: 〇 | AW56: V7.0 画面制御の追加
A57: 30 | B57: 30 | C57: 40 | D57: 原紙 | E57: 42 | F57: 印刷原紙 | G57: 1(固定値) | H57: 商品 | I57: 142 | J57: 商品印刷原紙 | K57: 外注 | L57: 製品マスタ | M57: CPで取り扱いがある（品目登録済） | N57: 加工品受注 | O57: ○ | P57: ○ | Q57: ○ | R57: ○ | S57: △ | T57: ○ | W57: ○ | X57: △ | Z57: △ | AA57: △ | AC57: 製品マスタ→WEB受注 | AD57: 製品マスタ→WEB受注 | AE57: 加工単価→WEB受注 | AF57: - | AG57: MRP | AH57: MRP | AI57: 製品コード(11桁) | AJ57: 連番4桁 | AM57: NULL | AN57: 加工単価マスタ | AO57: 品目単位 | AP57: 発注予定 | AQ57: 〇 | AR57: 〇：加工単価より取得 | AS57: ×：寸法(巾)、坪量が取得できない | AT57: 加工発注書 | AU57: 〇 | AW57: V7.0 画面制御の追加
C58: 40 | D58: 原紙 | E58: 42 | F58: 印刷原紙 | G58: 1(固定値) | H58: 商品 | I58: 142 | J58: 商品印刷原紙 | K58: 外注 | L58: 製品マスタ | M58: CPで取り扱いがある（品目登録済） | N58: 加工品受注 | O58: ○ | P58: ○ | Q58: ○ | R58: ○ | S58: △ | T58: ○ | W58: ○ | X58: △ | Z58: △ | AA58: △ | AC58: 製品マスタ→WEB受注 | AD58: 製品マスタ→WEB受注 | AE58: 加工単価→WEB受注 | AF58: - | AG58: 受注 | AH58: - | AI58: 製品コード(11桁) | AJ58: 連番4桁 | AM58: NULL | AN58: 受注 | AO58: NULL | AP58: 受注 | AQ58: 〇 | AR58: 〇：受注明細より取得 | AS58: ×：寸法(巾)、坪量が取得できない | AT58: 加工発注書 | AU58: 〇 | AW58: V7.0 画面制御の追加
A59: 31 | B59: 31 | C59: 40 | D59: 原紙 | E59: 42 | F59: 印刷原紙 | G59: 1(固定値) | H59: 商品 | I59: 142 | J59: 商品印刷原紙 | K59: WG間転送 | L59: 製品マスタ | M59: CPで取り扱いがある（品目登録済） | N59: 加工品受注 | O59: ○ | P59: ○ | Q59: ○ | R59: ○ | S59: △ | T59: ○ | W59: ○ | AC59: - | AD59: - | AE59: - | AF59: - | AG59: MRP | AH59: MRP | AI59: 製品コード(11桁) | AJ59: 連番4桁 | AM59: - | AN59: - | AO59: - | AP59: - | AQ59: - | AR59: - | AS59: - | AT59: - | AU59: 〇 | AW59: V7.0 画面制御の追加
A60: 32 | B60: 33 | C60: 30 | D60: 購買品 | E60: 51 | F60: 外装シート | G60: 1(固定値) | H60: 商品 | I60: 151 | J60: 外装シート | K60: 購買 | L60: 品目マスタ | M60: CPで取り扱いが無い（諸口品目） | N60: 商品購買 | O60: ○ | P60: ○ | Q60: ○ | AC60: WEB受注 | AD60: WEB受注 | AE60: WEB受注 | AF60: - | AG60: MRP | AH60: MRP | AI60: 諸口品目 | AM60: NULL | AN60: NULL | AO60: NULL | AP60: 発注予定 | AQ60: ×：仕様が取得できない | AR60: ×：諸口品のため購買単価マスタがない | AS60: - | AT60: 不明(おそらく発注書) | AU60: 〇 | AW60: V7.0 画面制御の追加
C61: 30 | D61: 購買品 | E61: 51 | F61: 外装シート | G61: 1(固定値) | H61: 商品 | I61: 151 | J61: 外装シート | K61: 購買 | L61: 品目マスタ | M61: CPで取り扱いが無い（諸口品目） | N61: 商品購買 | O61: ○ | P61: ○ | Q61: ○ | AC61: WEB受注 | AD61: WEB受注 | AE61: WEB受注 | AF61: - | AG61: 受注 | AH61: - | AI61: 諸口品目 | AM61: NULL | AN61: 受注 | AO61: NULL | AP61: 受注 | AQ61: ×：仕様が取得できない | AR61: 〇：受注明細より取得 | AS61: - | AT61: 不明(おそらく発注書) | AU61: 〇 | AW61: V7.0 画面制御の追加
A62: 33 | B62: 34 | C62: 30 | D62: 購買品 | E62: 52 | F62: 外装ケース | G62: 1(固定値) | H62: 商品 | I62: 152 | J62: 外装ケース | K62: 購買 | L62: 品目マスタ | M62: CPで取り扱いが無い（諸口品目） | N62: 商品購買 | O62: ○ | P62: ○ | Q62: ○ | AC62: WEB受注 | AD62: WEB受注 | AE62: WEB受注 | AF62: - | AG62: MRP | AH62: MRP | AI62: 諸口品目 | AM62: NULL | AN62: NULL | AO62: NULL | AP62: 発注予定 | AQ62: ×：仕様が取得できない | AR62: ×：諸口品のため購買単価マスタがない | AS62: - | AT62: 発注書 | AU62: 〇 | AW62: V7.0 画面制御の追加
C63: 30 | D63: 購買品 | E63: 52 | F63: 外装ケース | G63: 1(固定値) | H63: 商品 | I63: 152 | J63: 外装ケース | K63: 購買 | L63: 品目マスタ | M63: CPで取り扱いが無い（諸口品目） | N63: 商品購買 | O63: ○ | P63: ○ | Q63: ○ | AC63: WEB受注 | AD63: WEB受注 | AE63: WEB受注 | AF63: - | AG63: 受注 | AH63: - | AI63: 諸口品目 | AM63: NULL | AN63: 受注 | AO63: NULL | AP63: 受注 | AQ63: ×：仕様が取得できない | AR63: 〇：受注明細より取得 | AS63: - | AT63: 発注書 | AU63: 〇 | AW63: V7.0 画面制御の追加
A64: 34 | B64: 35 | C64: 30 | D64: 購買品 | E64: 71 | F64: 袋 | G64: 1(固定値) | H64: 商品 | I64: 171 | J64: 袋 | K64: 購買 | L64: 品目マスタ | M64: CPで取り扱いが無い（諸口品目） | N64: 商品購買 | O64: ○ | P64: ○ | Q64: ○ | AC64: WEB受注 | AD64: WEB受注 | AE64: WEB受注 | AF64: - | AG64: MRP | AH64: MRP | AI64: 諸口品目 | AM64: NULL | AN64: NULL | AO64: NULL | AP64: 発注予定 | AQ64: ×：仕様が取得できない | AR64: ×：諸口品のため購買単価マスタがない | AS64: - | AT64: 発注書 | AU64: 〇 | AW64: V7.0 画面制御の追加
C65: 30 | D65: 購買品 | E65: 71 | F65: 袋 | G65: 1(固定値) | H65: 商品 | I65: 171 | J65: 袋 | K65: 購買 | L65: 品目マスタ | M65: CPで取り扱いが無い（諸口品目） | N65: 商品購買 | O65: ○ | P65: ○ | Q65: ○ | AC65: WEB受注 | AD65: WEB受注 | AE65: WEB受注 | AF65: - | AG65: 受注 | AH65: - | AI65: 諸口品目 | AM65: NULL | AN65: 受注 | AO65: NULL | AP65: 受注 | AQ65: ×：仕様が取得できない | AR65: 〇：受注明細より取得 | AS65: - | AT65: 発注書 | AU65: 〇 | AW65: V7.0 画面制御の追加
A66: 35 | B66: 36 | C66: 30 | D66: 購買品 | E66: 80 | F66: モールド | G66: 1(固定値) | H66: 商品 | I66: 180 | J66: モールド | K66: 購買 | L66: 品目マスタ | M66: CPで取り扱いが無い（諸口品目） | N66: 商品購買 | O66: ○ | P66: ○ | Q66: ○ | AC66: WEB受注 | AD66: WEB受注 | AE66: WEB受注 | AF66: - | AG66: MRP | AH66: MRP | AI66: 諸口品目 | AM66: NULL | AN66: NULL | AO66: NULL | AP66: 発注予定 | AQ66: ×：仕様が取得できない | AR66: ×：諸口品のため購買単価マスタがない | AS66: - | AT66: 発注書 | AU66: 〇 | AW66: V7.0 画面制御の追加
C67: 30 | D67: 購買品 | E67: 80 | F67: モールド | G67: 1(固定値) | H67: 商品 | I67: 180 | J67: モールド | K67: 購買 | L67: 品目マスタ | M67: CPで取り扱いが無い（諸口品目） | N67: 商品購買 | O67: ○ | P67: ○ | Q67: ○ | AC67: WEB受注 | AD67: WEB受注 | AE67: WEB受注 | AF67: - | AG67: 受注 | AH67: - | AI67: 諸口品目 | AM67: NULL | AN67: 受注 | AO67: NULL | AP67: 受注 | AQ67: ×：仕様が取得できない | AR67: 〇：受注明細より取得 | AS67: - | AT67: 発注書 | AU67: 〇 | AW67: V7.0 画面制御の追加
A68: 36 | B68: 37 | C68: 30 | D68: 購買品 | E68: 62 | F68: その他 | G68: 1(固定値) | H68: 商品 | I68: 162 | J68: 商品その他 | K68: 購買 | L68: 品目マスタ | M68: CPで取り扱いが無い（諸口品目） | N68: 商品購買 | O68: ○ | P68: ○ | Q68: ○ | AC68: WEB受注 | AD68: WEB受注 | AE68: WEB受注 | AF68: - | AG68: MRP | AH68: MRP | AI68: 諸口品目 | AM68: NULL | AN68: NULL | AO68: NULL | AP68: 発注予定 | AQ68: ×：仕様が取得できない | AR68: ×：諸口品のため購買単価マスタがない | AS68: - | AT68: 発注書 | AU68: 〇 | AW68: V7.0 画面制御の追加
C69: 30 | D69: 購買品 | E69: 62 | F69: その他 | G69: 1(固定値) | H69: 商品 | I69: 162 | J69: 商品その他 | K69: 購買 | L69: 品目マスタ | M69: CPで取り扱いが無い（諸口品目） | N69: 商品購買 | O69: ○ | P69: ○ | Q69: ○ | AC69: WEB受注 | AD69: WEB受注 | AE69: WEB受注 | AF69: - | AG69: 受注 | AH69: - | AI69: 諸口品目 | AM69: NULL | AN69: 受注 | AO69: NULL | AP69: 受注 | AQ69: ×：仕様が取得できない | AR69: 〇：受注明細より取得 | AS69: - | AT69: 発注書 | AU69: 〇 | AW69: V7.0 画面制御の追加
A70: 37 | B70: 38 | C70: 20 | D70: シート製品 | E70: 11 | F70: シート | G70: 2(固定値) | H70: 製品 | I70: 211 | J70: シート | K70: 内製 | L70: WEB受注 | M70: CPで取り扱いがある（品目登録済） | N70: シート受注 | O70: ○ | P70: ○ | Q70: ○ | S70: △ | T70: ○ | U70: ○ | V70: ○ | AC70: - | AD70: - | AE70: - | AF70: - | AG70: MRP | AH70: MRP | AI70: 製品コード(11桁) | AJ70: 連番4桁 | AM70: - | AN70: - | AO70: - | AP70: - | AQ70: 〇 | AR70: - | AS70: - | AT70: - | AU70: 〇 | AW70: V7.0 画面制御の追加
C71: 20 | D71: シート製品 | E71: 11 | F71: シート | G71: 2(固定値) | H71: 製品 | I71: 211 | J71: シート | K71: 内製 | L71: WEB受注 | M71: CPで取り扱いがある（品目登録済） | N71: シート受注 | O71: ○ | P71: ○ | Q71: ○ | S71: △ | T71: ○ | U71: ○ | V71: ○ | AC71: - | AD71: - | AE71: - | AF71: - | AG71: 発注点 | AH71: MRP | AI71: 製品コード(11桁) | AJ71: 連番4桁 | AM71: - | AN71: - | AO71: - | AP71: - | AQ71: 〇 | AR71: - | AS71: - | AT71: - | AU71: 〇 | AW71: V7.0 画面制御の追加
C72: 20 | D72: シート製品 | E72: 11 | F72: シート | G72: 2(固定値) | H72: 製品 | I72: 211 | J72: シート | K72: 内製 | L72: WEB受注 | M72: CPで取り扱いがある（品目登録済） | N72: シート受注 | O72: ○ | P72: ○ | Q72: ○ | S72: △ | T72: ○ | U72: ○ | V72: ○ | AC72: - | AD72: - | AE72: - | AF72: - | AG72: 受注 | AH72: MRP | AI72: 製品コード(11桁) | AJ72: 連番4桁 | AM72: - | AN72: - | AO72: - | AP72: - | AQ72: 〇 | AR72: - | AS72: - | AT72: - | AU72: 〇 | AW72: V7.0 画面制御の追加
A73: 38 | B73: 39 | C73: 20 | D73: シート製品 | E73: 11 | F73: シート | G73: 2(固定値) | H73: 製品 | I73: 211 | J73: シート | K73: 外注 | L73: WEB受注 | M73: CPで取り扱いがある（品目登録済） | N73: シート受注 | O73: ○ | P73: ○ | Q73: ○ | S73: △ | T73: ○ | AC73: WEB受注 | AD73: WEB受注 | AE73: WEB受注 | AF73: - | AG73: MRP | AH73: MRP | AI73: 製品コード(11桁) | AJ73: 連番4桁 | AM73: NULL | AN73: 加工単価マスタ | AO73: NULL | AP73: 発注予定 | AQ73: 〇 | AR73: 〇：加工単価より取得 | AS73: 〇 | AT73: 加工発注書 | AU73: 〇 | AW73: V7.0 画面制御の追加
C74: 20 | D74: シート製品 | E74: 11 | F74: シート | G74: 2(固定値) | H74: 製品 | I74: 211 | J74: シート | K74: 外注 | L74: WEB受注 | M74: CPで取り扱いがある（品目登録済） | N74: シート受注 | O74: ○ | P74: ○ | Q74: ○ | S74: △ | T74: ○ | AC74: WEB受注 | AD74: WEB受注 | AE74: WEB受注 | AF74: - | AG74: 受注 | AH74: - | AI74: 製品コード(11桁) | AJ74: 連番4桁 | AM74: NULL | AN74: 受注 | AO74: NULL | AP74: 受注 | AQ74: 〇 | AR74: 〇：受注明細より取得 | AS74: 〇 | AT74: 加工発注書 | AU74: 〇 | AW74: V7.0 画面制御の追加
A75: 39 | B75: 40 | C75: 20 | D75: シート製品 | E75: 11 | F75: シート | G75: 2(固定値) | H75: 製品 | I75: 211 | J75: シート | K75: WG間転送 | L75: WEB受注 | M75: CPで取り扱いがある（品目登録済） | N75: シート受注 | O75: ○ | P75: ○ | Q75: ○ | S75: △ | T75: ○ | U75: ○ | V75: ○ | AC75: - | AD75: - | AE75: - | AF75: - | AG75: MRP | AH75: MRP | AI75: 製品コード(11桁) | AJ75: 連番4桁 | AM75: - | AN75: - | AO75: - | AP75: - | AQ75: - | AR75: - | AS75: - | AT75: - | AU75: 〇 | AW75: V7.0 画面制御の追加
A76: 40 | B76: 41 | C76: 10 | D76: 加工製品 | E76: 12 | F76: 加工 | G76: 2(固定値) | H76: 製品 | I76: 212 | J76: 加工 | K76: 内製 | L76: 製品マスタ | M76: CPで取り扱いがある（品目登録済） | N76: 加工品受注 | O76: ○ | P76: ○ | Q76: ○ | S76: △ | T76: ○ | U76: ○ | V76: ○ | W76: ○ | AC76: - | AD76: - | AE76: - | AF76: - | AG76: MRP | AH76: MRP | AI76: 製品コード(11桁) | AJ76: 連番4桁 | AM76: - | AN76: - | AO76: - | AP76: - | AQ76: 〇 | AR76: - | AS76: - | AT76: - | AU76: 〇 | AW76: V7.0 画面制御の追加
C77: 10 | D77: 加工製品 | E77: 12 | F77: 加工 | G77: 2(固定値) | H77: 製品 | I77: 212 | J77: 加工 | K77: 内製 | L77: 製品マスタ | M77: CPで取り扱いがある（品目登録済） | N77: 加工品受注 | O77: ○ | P77: ○ | Q77: ○ | S77: △ | T77: ○ | U77: ○ | V77: ○ | W77: ○ | AC77: - | AD77: - | AE77: - | AF77: - | AG77: 発注点 | AH77: MRP | AI77: 製品コード(11桁) | AJ77: 連番4桁 | AM77: - | AN77: - | AO77: - | AP77: - | AQ77: 〇 | AR77: - | AS77: - | AT77: - | AU77: 〇 | AW77: V7.0 画面制御の追加
C78: 10 | D78: 加工製品 | E78: 12 | F78: 加工 | G78: 2(固定値) | H78: 製品 | I78: 212 | J78: 加工 | K78: 内製 | L78: 製品マスタ | M78: CPで取り扱いがある（品目登録済） | N78: 加工品受注 | O78: ○ | P78: ○ | Q78: ○ | S78: △ | T78: ○ | U78: ○ | V78: ○ | W78: ○ | AC78: - | AD78: - | AE78: - | AF78: - | AG78: 受注 | AH78: MRP | AI78: 製品コード(11桁) | AJ78: 連番4桁 | AM78: - | AN78: - | AO78: - | AP78: - | AQ78: 〇 | AR78: - | AS78: - | AT78: - | AU78: 〇 | AW78: V7.0 画面制御の追加
A79: 41 | B79: 42 | C79: 10 | D79: 加工製品 | E79: 12 | F79: 加工 | G79: 2(固定値) | H79: 製品 | I79: 212 | J79: 加工 | K79: 外注 | L79: 製品マスタ | M79: CPで取り扱いがある（品目登録済） | N79: 加工品受注 | O79: ○ | P79: ○ | Q79: ○ | S79: △ | T79: ○ | W79: ○ | X79: △ | AC79: 製品マスタ→WEB受注 | AD79: 製品マスタ→WEB受注 | AE79: 加工単価→WEB受注 | AF79: - | AG79: MRP | AH79: MRP | AI79: 製品コード(11桁) | AJ79: 連番4桁 | AM79: NULL | AN79: 加工単価マスタ | AO79: NULL | AP79: 発注予定 | AQ79: 〇 | AR79: 〇：加工単価より取得 | AS79: 〇 | AT79: 加工発注書 | AU79: 〇 | AW79: V7.0 画面制御の追加
C80: 10 | D80: 加工製品 | E80: 12 | F80: 加工 | G80: 2(固定値) | H80: 製品 | I80: 212 | J80: 加工 | K80: 外注 | L80: 製品マスタ | M80: CPで取り扱いがある（品目登録済） | N80: 加工品受注 | O80: ○ | P80: ○ | Q80: ○ | S80: △ | T80: ○ | W80: ○ | X80: △ | AC80: 製品マスタ→WEB受注 | AD80: 製品マスタ→WEB受注 | AE80: 加工単価→WEB受注 | AF80: - | AG80: 受注 | AH80: - | AI80: 製品コード(11桁) | AJ80: 連番4桁 | AM80: NULL | AN80: 受注 | AO80: NULL | AP80: 受注 | AQ80: 〇 | AR80: 〇：受注明細より取得 | AS80: 〇 | AT80: 加工発注書 | AU80: 〇 | AW80: V7.0 画面制御の追加
A81: 42 | B81: 43 | C81: 10 | D81: 加工製品 | E81: 12 | F81: 加工 | G81: 2(固定値) | H81: 製品 | I81: 212 | J81: 加工 | K81: WG間転送 | L81: 製品マスタ | M81: CPで取り扱いがある（品目登録済） | N81: 加工品受注 | O81: ○ | P81: ○ | Q81: ○ | S81: △ | T81: ○ | U81: ○ | V81: ○ | W81: ○ | AC81: - | AD81: - | AE81: - | AF81: - | AG81: MRP | AH81: MRP | AI81: 製品コード(11桁) | AJ81: 連番4桁 | AM81: - | AN81: - | AO81: - | AP81: - | AQ81: - | AR81: - | AS81: - | AT81: - | AU81: 〇 | AW81: V7.0 画面制御の追加
A82: 43 | B82: 44 | C82: 10 | D82: 加工製品 | E82: 13 | F82: Ｇプリント | G82: 2(固定値) | H82: 製品 | I82: 213 | J82: Ｇプリント | K82: 内製 | L82: 製品マスタ | M82: CPで取り扱いがある（品目登録済） | N82: 加工品受注 | O82: ○ | P82: ○ | Q82: ○ | S82: △ | T82: ○ | U82: ○ | V82: ○ | W82: ○ | AC82: - | AD82: - | AE82: - | AF82: - | AG82: MRP | AH82: MRP | AI82: 製品コード(11桁) | AJ82: 連番4桁 | AM82: - | AN82: - | AO82: - | AP82: - | AQ82: 〇 | AR82: - | AS82: - | AT82: - | AU82: 〇 | AW82: V7.0 画面制御の追加
C83: 10 | D83: 加工製品 | E83: 13 | F83: Ｇプリント | G83: 2(固定値) | H83: 製品 | I83: 213 | J83: Ｇプリント | K83: 内製 | L83: 製品マスタ | M83: CPで取り扱いがある（品目登録済） | N83: 加工品受注 | O83: ○ | P83: ○ | Q83: ○ | S83: △ | T83: ○ | U83: ○ | V83: ○ | W83: ○ | AC83: - | AD83: - | AE83: - | AF83: - | AG83: 発注点 | AH83: MRP | AI83: 製品コード(11桁) | AJ83: 連番4桁 | AM83: - | AN83: - | AO83: - | AP83: - | AQ83: 〇 | AR83: - | AS83: - | AT83: - | AU83: 〇 | AW83: V7.0 画面制御の追加
C84: 10 | D84: 加工製品 | E84: 13 | F84: Ｇプリント | G84: 2(固定値) | H84: 製品 | I84: 213 | J84: Ｇプリント | K84: 内製 | L84: 製品マスタ | M84: CPで取り扱いがある（品目登録済） | N84: 加工品受注 | O84: ○ | P84: ○ | Q84: ○ | S84: △ | T84: ○ | U84: ○ | V84: ○ | W84: ○ | AC84: - | AD84: - | AE84: - | AF84: - | AG84: 受注 | AH84: MRP | AI84: 製品コード(11桁) | AJ84: 連番4桁 | AM84: - | AN84: - | AO84: - | AP84: - | AQ84: 〇 | AR84: - | AS84: - | AT84: - | AU84: 〇 | AW84: V7.0 画面制御の追加
A85: 44 | B85: 45 | C85: 10 | D85: 加工製品 | E85: 13 | F85: Ｇプリント | G85: 2(固定値) | H85: 製品 | I85: 213 | J85: Ｇプリント | K85: 外注 | L85: 製品マスタ | M85: CPで取り扱いがある（品目登録済） | N85: 加工品受注 | O85: ○ | P85: ○ | Q85: ○ | S85: △ | T85: ○ | W85: ○ | X85: △ | AC85: 製品マスタ→WEB受注 | AD85: 製品マスタ→WEB受注 | AE85: 加工単価→WEB受注 | AF85: - | AG85: MRP | AH85: MRP | AI85: 製品コード(11桁) | AJ85: 連番4桁 | AM85: NULL | AN85: 加工単価マスタ | AO85: NULL | AP85: 発注予定 | AQ85: 〇 | AR85: 〇：加工単価より取得 | AS85: 〇 | AT85: 加工発注書 | AU85: 〇 | AW85: V7.0 画面制御の追加
C86: 10 | D86: 加工製品 | E86: 13 | F86: Ｇプリント | G86: 2(固定値) | H86: 製品 | I86: 213 | J86: Ｇプリント | K86: 外注 | L86: 製品マスタ | M86: CPで取り扱いがある（品目登録済） | N86: 加工品受注 | O86: ○ | P86: ○ | Q86: ○ | S86: △ | T86: ○ | W86: ○ | X86: △ | AC86: 製品マスタ→WEB受注 | AD86: 製品マスタ→WEB受注 | AE86: 加工単価→WEB受注 | AF86: - | AG86: 受注 | AH86: - | AI86: 製品コード(11桁) | AJ86: 連番4桁 | AM86: NULL | AN86: 受注 | AO86: NULL | AP86: 受注 | AQ86: 〇 | AR86: 〇：受注明細より取得 | AS86: 〇 | AT86: 加工発注書 | AU86: 〇 | AW86: V7.0 画面制御の追加
A87: 45 | B87: 46 | C87: 10 | D87: 加工製品 | E87: 13 | F87: Ｇプリント | G87: 2(固定値) | H87: 製品 | I87: 213 | J87: Ｇプリント | K87: WG間転送 | L87: 製品マスタ | M87: CPで取り扱いがある（品目登録済） | N87: 加工品受注 | O87: ○ | P87: ○ | Q87: ○ | S87: △ | T87: ○ | U87: ○ | V87: ○ | W87: ○ | AC87: - | AD87: - | AE87: - | AF87: - | AG87: MRP | AH87: MRP | AI87: 製品コード(11桁) | AJ87: 連番4桁 | AM87: - | AN87: - | AO87: - | AP87: - | AQ87: - | AR87: - | AS87: - | AT87: - | AU87: 〇 | AW87: V7.0 画面制御の追加
A88: 46 | B88: 47 | C88: 10 | D88: 加工製品 | E88: 21 | F88: 巻ボール | G88: 2(固定値) | H88: 製品 | I88: 221 | J88: 巻ボール | K88: 内製 | L88: 製品マスタ | M88: CPで取り扱いがある（品目登録済） | N88: 加工品受注 | O88: ○ | P88: ○ | Q88: ○ | S88: △ | T88: ○ | U88: ○ | V88: ○ | W88: ○ | AC88: - | AD88: - | AE88: - | AF88: - | AG88: MRP | AH88: MRP | AI88: 製品コード(11桁) | AJ88: 連番4桁 | AM88: - | AN88: - | AO88: - | AP88: - | AQ88: 〇 | AR88: - | AS88: - | AT88: - | AU88: 〇 | AW88: V7.0 画面制御の追加
C89: 10 | D89: 加工製品 | E89: 21 | F89: 巻ボール | G89: 2(固定値) | H89: 製品 | I89: 221 | J89: 巻ボール | K89: 内製 | L89: 製品マスタ | M89: CPで取り扱いがある（品目登録済） | N89: 加工品受注 | O89: ○ | P89: ○ | Q89: ○ | S89: △ | T89: ○ | U89: ○ | V89: ○ | W89: ○ | AC89: - | AD89: - | AE89: - | AF89: - | AG89: 発注点 | AH89: MRP | AI89: 製品コード(11桁) | AJ89: 連番4桁 | AM89: - | AN89: - | AO89: - | AP89: - | AQ89: 〇 | AR89: - | AS89: - | AT89: - | AU89: 〇 | AW89: V7.0 画面制御の追加
C90: 10 | D90: 加工製品 | E90: 21 | F90: 巻ボール | G90: 2(固定値) | H90: 製品 | I90: 221 | J90: 巻ボール | K90: 内製 | L90: 製品マスタ | M90: CPで取り扱いがある（品目登録済） | N90: 加工品受注 | O90: ○ | P90: ○ | Q90: ○ | S90: △ | T90: ○ | U90: ○ | V90: ○ | W90: ○ | AC90: - | AD90: - | AE90: - | AF90: - | AG90: 受注 | AH90: MRP | AI90: 製品コード(11桁) | AJ90: 連番4桁 | AM90: - | AN90: - | AO90: - | AP90: - | AQ90: 〇 | AR90: - | AS90: - | AT90: - | AU90: 〇 | AW90: V7.0 画面制御の追加
A91: 47 | B91: 48 | C91: 10 | D91: 加工製品 | E91: 21 | F91: 巻ボール | G91: 2(固定値) | H91: 製品 | I91: 221 | J91: 巻ボール | K91: 外注 | L91: 製品マスタ | M91: CPで取り扱いがある（品目登録済） | N91: 加工品受注 | O91: ○ | P91: ○ | Q91: ○ | S91: △ | T91: ○ | W91: ○ | X91: △ | AC91: 製品マスタ→WEB受注 | AD91: 製品マスタ→WEB受注 | AE91: 加工単価→WEB受注 | AF91: WEB受注 | AG91: MRP | AH91: MRP | AI91: 製品コード(11桁) | AJ91: 連番4桁 | AM91: NULL | AN91: 加工単価マスタ | AO91: NULL | AP91: 発注予定 | AQ91: 〇 | AR91: 〇：加工単価より取得 | AS91: 〇 | AT91: 加工発注書 | AU91: 〇 | AW91: V7.0 画面制御の追加
C92: 10 | D92: 加工製品 | E92: 21 | F92: 巻ボール | G92: 2(固定値) | H92: 製品 | I92: 221 | J92: 巻ボール | K92: 外注 | L92: 製品マスタ | M92: CPで取り扱いがある（品目登録済） | N92: 加工品受注 | O92: ○ | P92: ○ | Q92: ○ | S92: △ | T92: ○ | W92: ○ | X92: △ | AC92: 製品マスタ→WEB受注 | AD92: 製品マスタ→WEB受注 | AE92: 加工単価→WEB受注 | AF92: WEB受注 | AG92: 受注 | AH92: - | AI92: 製品コード(11桁) | AJ92: 連番4桁 | AM92: NULL | AN92: 受注 | AO92: NULL | AP92: 受注 | AQ92: 〇 | AR92: 〇：受注明細より取得 | AS92: 〇 | AT92: 加工発注書 | AU92: 〇 | AW92: V7.0 画面制御の追加
A93: 48 | B93: 49 | C93: 10 | D93: 加工製品 | E93: 21 | F93: 巻ボール | G93: 2(固定値) | H93: 製品 | I93: 221 | J93: 巻ボール | K93: WG間転送 | L93: 製品マスタ | M93: CPで取り扱いがある（品目登録済） | N93: 加工品受注 | O93: ○ | P93: ○ | Q93: ○ | S93: △ | T93: ○ | U93: ○ | V93: ○ | W93: ○ | AC93: - | AD93: - | AE93: - | AF93: - | AG93: MRP | AH93: MRP | AI93: 製品コード(11桁) | AJ93: 連番4桁 | AM93: - | AN93: - | AO93: - | AP93: - | AQ93: - | AR93: - | AS93: - | AT93: - | AU93: 〇 | AW93: V7.0 画面制御の追加
A94: 49 | B94: 50 | C94: 20 | D94: シート製品 | E94: 22 | F94: 片面シート | G94: 2(固定値) | H94: 製品 | I94: 222 | J94: 片面シート | K94: 内製 | L94: WEB受注 | M94: CPで取り扱いがある（品目登録済） | N94: シート受注 | O94: ○ | P94: ○ | Q94: ○ | S94: △ | T94: ○ | U94: ○ | V94: ○ | AC94: - | AD94: - | AE94: - | AF94: - | AG94: MRP | AH94: MRP | AI94: 製品コード(11桁) | AJ94: 連番4桁 | AM94: - | AN94: - | AO94: - | AP94: - | AQ94: 〇 | AR94: - | AS94: - | AT94: - | AU94: 〇 | AW94: V7.0 画面制御の追加
C95: 20 | D95: シート製品 | E95: 22 | F95: 片面シート | G95: 2(固定値) | H95: 製品 | I95: 222 | J95: 片面シート | K95: 内製 | L95: WEB受注 | M95: CPで取り扱いがある（品目登録済） | N95: シート受注 | O95: ○ | P95: ○ | Q95: ○ | S95: △ | T95: ○ | U95: ○ | V95: ○ | AC95: - | AD95: - | AE95: - | AF95: - | AG95: 発注点 | AH95: MRP | AI95: 製品コード(11桁) | AJ95: 連番4桁 | AM95: - | AN95: - | AO95: - | AP95: - | AQ95: 〇 | AR95: - | AS95: - | AT95: - | AU95: 〇 | AW95: V7.0 画面制御の追加
C96: 20 | D96: シート製品 | E96: 22 | F96: 片面シート | G96: 2(固定値) | H96: 製品 | I96: 222 | J96: 片面シート | K96: 内製 | L96: WEB受注 | M96: CPで取り扱いがある（品目登録済） | N96: シート受注 | O96: ○ | P96: ○ | Q96: ○ | S96: △ | T96: ○ | U96: ○ | V96: ○ | AC96: - | AD96: - | AE96: - | AF96: - | AG96: 受注 | AH96: MRP | AI96: 製品コード(11桁) | AJ96: 連番4桁 | AM96: - | AN96: - | AO96: - | AP96: - | AQ96: 〇 | AR96: - | AS96: - | AT96: - | AU96: 〇 | AW96: V7.0 画面制御の追加
A97: 50 | B97: 51 | C97: 20 | D97: シート製品 | E97: 22 | F97: 片面シート | G97: 2(固定値) | H97: 製品 | I97: 222 | J97: 片面シート | K97: 外注 | L97: WEB受注 | M97: CPで取り扱いがある（品目登録済） | N97: シート受注 | O97: ○ | P97: ○ | Q97: ○ | S97: △ | T97: ○ | AC97: WEB受注 | AD97: WEB受注 | AE97: WEB受注 | AF97: - | AG97: MRP | AH97: MRP | AI97: 製品コード(11桁) | AJ97: 連番4桁 | AM97: NULL | AN97: 加工単価マスタ | AO97: NULL | AP97: 発注予定 | AQ97: 〇 | AR97: 〇：加工単価より取得 | AS97: 〇 | AT97: 加工発注書 | AU97: 〇 | AW97: V7.0 画面制御の追加
B98: 51 | C98: 20 | D98: シート製品 | E98: 22 | F98: 片面シート | G98: 2(固定値) | H98: 製品 | I98: 222 | J98: 片面シート | K98: 外注 | L98: WEB受注 | M98: CPで取り扱いがある（品目登録済） | N98: シート受注 | O98: ○ | P98: ○ | Q98: ○ | S98: △ | T98: ○ | AC98: WEB受注 | AD98: WEB受注 | AE98: WEB受注 | AF98: - | AG98: 受注 | AH98: - | AI98: 製品コード(11桁) | AJ98: 連番4桁 | AM98: NULL | AN98: 受注 | AO98: NULL | AP98: 受注 | AQ98: 〇 | AR98: 〇：受注明細より取得 | AS98: 〇 | AT98: 加工発注書 | AU98: 〇 | AW98: V7.0 画面制御の追加
A99: 51 | B99: 52 | C99: 20 | D99: シート製品 | E99: 22 | F99: 片面シート | G99: 2(固定値) | H99: 製品 | I99: 222 | J99: 片面シート | K99: WG間転送 | L99: WEB受注 | M99: CPで取り扱いがある（品目登録済） | N99: シート受注 | O99: ○ | P99: ○ | Q99: ○ | S99: △ | T99: ○ | U99: ○ | V99: ○ | AC99: - | AD99: - | AE99: - | AF99: - | AG99: MRP | AH99: MRP | AI99: 製品コード(11桁) | AJ99: 連番4桁 | AM99: - | AN99: - | AO99: - | AP99: - | AQ99: - | AR99: - | AS99: - | AT99: - | AU99: 〇 | AW99: V7.0 画面制御の追加
A100: 52 | B100: 53 | C100: 10 | D100: 加工製品 | E100: 23 | F100: 片面加工 | G100: 2(固定値) | H100: 製品 | I100: 223 | J100: 片面加工 | K100: 内製 | L100: 製品マスタ | M100: CPで取り扱いがある（品目登録済） | N100: 加工品受注 | O100: ○ | P100: ○ | Q100: ○ | S100: △ | T100: ○ | U100: ○ | V100: ○ | W100: ○ | AC100: - | AD100: - | AE100: - | AF100: - | AG100: MRP | AH100: MRP | AI100: 製品コード(11桁) | AJ100: 連番4桁 | AM100: - | AN100: - | AO100: - | AP100: - | AQ100: 〇 | AR100: - | AS100: - | AT100: - | AU100: 〇 | AW100: V7.0 画面制御の追加
C101: 10 | D101: 加工製品 | E101: 23 | F101: 片面加工 | G101: 2(固定値) | H101: 製品 | I101: 223 | J101: 片面加工 | K101: 内製 | L101: 製品マスタ | M101: CPで取り扱いがある（品目登録済） | N101: 加工品受注 | O101: ○ | P101: ○ | Q101: ○ | S101: △ | T101: ○ | U101: ○ | V101: ○ | W101: ○ | AC101: - | AD101: - | AE101: - | AF101: - | AG101: 発注点 | AH101: MRP | AI101: 製品コード(11桁) | AJ101: 連番4桁 | AM101: - | AN101: - | AO101: - | AP101: - | AQ101: 〇 | AR101: - | AS101: - | AT101: - | AU101: 〇 | AW101: V7.0 画面制御の追加
...

Sheet mcframe7受注
A1: テーブル名 | C1: 別名 | E1: 日本語名 | H1: 排他 | I1: 履歴 | J1: VIEW | K1: MULTI | L1: DBC | M1: Mod.ID | N1: クラス名 | O1: Pj.Id | P1: SuperClassPj.Id | Q1: SuperListClass | R1: SuperDMLClass | S1: SuperRowClass
A2: * | B2: MST_SLO_ALL | E2: 受注ヘッダ | H2: * | I2: * | J2: *
B3: 【説明】
B4: 受注のヘッダ情報を格納する。
A8: レベル | B8: 項目名 | C8: Ref. | D8: メタ | E8: 型 | F8: 桁 | G8: Null | H8: Def. | I8: 履歴 | J8: VIEW | K8: MULTI | L8: DBC | M8: 参 | N8: 表別名/参照先 | O8: INNERROW | P8: 日本語 | Q8: 説明 | R8: フルネーム | S8: 値の制限 | T8: Rev. | U8: 設定仕様 | V8: 未設定時の振る舞い
A9: 0 | B9: SLO_NO | D9: #MA.SLO_NO | E9: C | F9: 15 | G9: N | P9: 受注ＮＯ | Q9: 受注を特定する番号 発番業務区分により発番する
A10: 0 | B10: CO_CD | D10: #MA.CO_CD | E10: C | F10: 10 | G10: N | J10: N | P10: 会社ＣＤ | Q10: 会社を表す一意のＣＤ
A12: 1 | B12: SLO_REV | D12: #MA.SLIP_REV | E12: N | F12: 4,0 | G12: N | P12: 受注改訂番号 | Q12: 受注のリビジョン
A13: 1 | B13: TRD_CD | D13: #MA.TRD_CD | E13: C | F13: 4 | G13: N | P13: 取引ＣＤ | Q13: 取引を識別する取引ＣＤ 取引パタン区分が売上、出荷の取引ＣＤが設定できる。
A14: 1 | B14: TRD_PTN_TYP | D14: #MA.TRD_PTN_TYP | E14: C | F14: 4 | G14: N | P14: 取引パタン区分 | Q14: 取引のパターンを定義する区分
A15: 1 | B15: SLO_DT | D15: #MA.DT | E15: D | G15: N | P15: 受注日 | Q15: 受注が成約した日。（受注を登録した日ではない。）
A16: 1 | B16: SLO_TYP | D16: #MS.SLO_TYP | E16: C | F16: 1 | G16: N | P16: 受注区分 | Q16: 仮受注または本受注を指定する。仮受注の場合は、在庫引当、手配依頼はできるが、出荷ができなくなる。
A17: 1 | B17: CST_CD | D17: #MA.BP_CD | E17: C | F17: 20 | G17: N | P17: 得意先ＣＤ | Q17: 得意先ＣＤ
A18: 1 | B18: CST_PO_NO | D18: #MA.CST_PO_NO | E18: C | F18: 20 | G18: Y | P18: 得意先注文ＮＯ | Q18: 得意先の注文ＮＯ
A19: 1 | B19: CST_PO_REV | D19: #MA.SLIP_REV | E19: N | F19: 4,0 | G19: Y | P19: 得意先注文改訂番号 | Q19: 得意先の注文改訂番号 EDI納期回答する際に、回答送信データに設定する。古い注文データに対して回答していないかを発注者側で判断するための項目。EDI対象であっても、発注者側で設定してこないこともあるので、得意先注文NOを設定時でも改訂番号は必須としていない。
A20: 1 | B20: TRD_CUR_CD | D20: #MA.CUR_CD | E20: C | F20: 3 | G20: Y | P20: 取引通貨ＣＤ | Q20: 取引通貨
A21: 1 | B21: XRATE_INPT_FLG | D21: #MA.FLG | E21: F | G21: N | P21: 為替レート指定ＦＬＧ | Q21: 為替レートを指定した場合に「1」が設定される
A22: 1 | B22: XRATE | D22: #MA.MONEY | E22: N | F22: 21,8 | G22: Y | P22: 為替レート | Q22: 為替レート
A23: 1 | B23: PTAX_XRATE_INPT_FLG | D23: #MA.FLG | E23: F | G23: N | P23: 納税為替レート指定ＦＬＧ | Q23: 納税為替レートを指定した場合に「1」が設定される
A24: 1 | B24: PTAX_XRATE | D24: #MA.MONEY | E24: N | F24: 21,8 | G24: Y | P24: 納税為替レート | Q24: 納税為替レート
A25: 1 | B25: SLS_USR_CD | D25: #MA.USR_CD | E25: C | F25: 500 | G25: Y | P25: 売上担当者ＣＤ | Q25: 得意先の担当者 売上担当者の位置づけ
A26: 1 | B26: SLS_DPT_CD | D26: #MA.DPT_CD | E26: C | F26: 20 | G26: N | P26: 売上部門ＣＤ | Q26: 得意先の担当部門 売上担当部門の位置づけ
A27: 1 | B27: WG_CD | D27: #MA.WG_CD | E27: C | F27: 10 | G27: N | P27: ワーキンググループＣＤ | Q27: 売上部門が属するワーキンググループ
A28: 1 | B28: IV_NO | D28: #MA.IV_NO | E28: C | F28: 15 | G28: Y | P28: インボイスＮＯ | Q28: インボイス取引の場合に、受注登録時にインボイスＮＯを決定する場合に設定する。インボイスに引き継がれる。 発番業務区分により発番するが、手入力での指定も可能。
A29: 1 | B29: TTERM_CD1 | D29: #MA.TTERM_CD | E29: C | F29: 5 | G29: Y | P29: 取引条件ＣＤ１ | Q29: 取引条件ＣＤ１
A30: 1 | B30: TTERM_RMRKS1 | D30: #MS.TTERM_RMRKS1 | E30: C | F30: 100 | G30: Y | P30: 取引条件備考１ | Q30: 取引条件備考１
A31: 1 | B31: TTERM_CD2 | D31: #MA.TTERM_CD | E31: C | F31: 5 | G31: Y | P31: 取引条件ＣＤ２ | Q31: 取引条件ＣＤ２
A32: 1 | B32: TTERM_RMRKS2 | D32: #MS.TTERM_RMRKS2 | E32: C | F32: 100 | G32: Y | P32: 取引条件備考２ | Q32: 取引条件備考２
A33: 1 | B33: TTERM_CD3 | D33: #MA.TTERM_CD | E33: C | F33: 5 | G33: Y | P33: 取引条件ＣＤ３ | Q33: 取引条件ＣＤ３
A34: 1 | B34: TTERM_RMRKS3 | D34: #MS.TTERM_RMRKS3 | E34: C | F34: 100 | G34: Y | P34: 取引条件備考３ | Q34: 取引条件備考３
A35: 1 | B35: TRNSPT_CD | D35: #MA.TRNSPT_CD | E35: C | F35: 5 | G35: Y | P35: 輸送方法ＣＤ | Q35: インボイス用項目。インボイスに引き継がれる。
A36: 1 | B36: VSSL_FLGHT | D36: #MA.VSSL_FLGHT | E36: C | F36: 40 | G36: Y | P36: 船名／便名 | Q36: インボイス用項目。インボイスに引き継がれる。
A37: 1 | B37: LOAD_PORT_CD | D37: #MA.PORT_CD | E37: C | F37: 5 | G37: Y | P37: 船積港ＣＤ | Q37: インボイス用項目。インボイスに引き継がれる。
A38: 1 | B38: ETD_DT | D38: #MA.DT | E38: D | G38: Y | P38: 船積予定日 | Q38: インボイス用項目。インボイスに引き継がれる。
A39: 1 | B39: DSCHRG_PORT_CD | D39: #MA.PORT_CD | E39: C | F39: 5 | G39: Y | P39: 船卸港ＣＤ | Q39: インボイス用項目。インボイスに引き継がれる。
A40: 1 | B40: ETA_DT | D40: #MA.DT | E40: D | G40: Y | P40: 船卸予定日 | Q40: インボイス用項目。インボイスに引き継がれる。
A41: 1 | B41: VIA_PORT_CD | D41: #MA.PORT_CD | E41: C | F41: 5 | G41: Y | P41: 経由地ＣＤ | Q41: インボイス用項目。インボイスに引き継がれる。
A42: 1 | B42: VIA_SCHD_DT | D42: #MA.DT | E42: D | G42: Y | P42: 経由予定日 | Q42: インボイス用項目。インボイスに引き継がれる。
A43: 1 | B43: ASSORT_TYP | D43: #MS.SHIP_ASSORT_TYP | E43: C | F43: 1 | G43: N | P43: 品揃区分 | Q43: 「品揃する」が指定された場合、明細単位の出荷が不可になり、全明細まとめて出荷指図しないとエラーとなる。 出荷指図対象外の場合は、出荷実績もしくは売上実績で、全明細の実績をまとめて登録しないとエラーとなる。
A44: 1 | B44: SLS_BASIS_TYP | D44: #MA.SLS_BASIS_TYP | E44: C | F44: 1 | G44: Y | P44: 売上計上区分 | Q44: 売上に関わる取引の場合、売上のタイミングを指定する 「出荷基準」の場合、出荷と同時に売上計上する 「検収基準」の場合、出荷後に得意先からの検収を受けて売上を計上する 「着荷基準」の場合、納品先へ届いた日に売上を計上する
A45: 1 | B45: AR_DPT_CD | D45: #MA.DPT_CD | E45: C | F45: 20 | G45: Y | P45: 債権部門ＣＤ | Q45: 債権残高を管理する部門 取引先マスタの債権部門区分に応じてデフォルト値が画面に表示される。
A46: 1 | B46: WRK_NO | D46: #MA.WRK_NO | E46: C | F46: 15 | G46: Y | P46: 案件ＮＯ | Q46: 案件ＮＯ
A47: 1 | B47: RCPT_DT | D47: #MA.DT | E47: D | G47: Y | P47: 受付日 | Q47: 受注を受け付けた日 受注管理項目
A48: 1 | B48: RCPT_USR_CD | D48: #MA.USR_CD | E48: C | F48: 500 | G48: Y | P48: 受付担当者ＣＤ | Q48: 受注を受け付けた担当者 受注管理項目
A49: 1 | B49: TRD_RMRKS | D49: #MA.TRD_RMRKS | E49: C | F49: 100 | G49: Y | P49: 取引備考 | Q49: 納品書に出力される備考
A50: 1 | B50: INTR_RMRKS | D50: #MS.SLO_INTR_RMRKS | E50: C | F50: 100 | G50: Y | P50: 内部備考 | Q50: 受注管理のための備考 以降の処理へは引き継がれない
A51: 1 | B51: CST_PO_RMRKS | D51: #MS.CST_PO_RMRKS | E51: C | F51: 100 | G51: Y | P51: 得意先注文備考 | Q51: 得意先の注文備考
A52: 1 | B52: QTN_NO | D52: #MA.QTN_NO | E52: C | F52: 15 | G52: Y | P52: 見積ＮＯ | Q52: 見積引継ぎを行った場合の見積レコードの見積ＮＯ
A53: 1 | B53: QTN_REV | D53: #MA.SLIP_REV | E53: N | F53: 4,0 | G53: Y | P53: 見積改訂番号 | Q53: 見積引継ぎを行った場合の見積レコードの見積改訂番号
A54: 1 | B54: ADV_SHIP_CTRL_TYP | D54: #MS.ADV_SHIP_CTRL_TYP | E54: C | F54: 1 | G54: Y | P54: 前受金出荷制御区分 | Q54: 前受金を入金するまで、出荷できないように制御するための区分
A55: 1 | B55: ADV_BILL_AMT | D55: #MA.MONEY | E55: N | F55: 21,8 | G55: Y | P55: 前受金請求額 | Q55: 前受金の請求額（取引通貨） 前受金出荷制御区分が設定されている場合に、設定可能
A56: 1 | B56: ADV_RCV_AMT | D56: #MA.MONEY | E56: N | F56: 21,8 | G56: Y | P56: 前受金入金額 | Q56: 前受金の入金額（取引通貨） 前受金出荷制御区分が「出荷不可」の場合、入金額が請求額に達するまで出荷ができない。 前受金入金で対応する受注ＮＯを入力して登録すると更新される。
A57: 1 | B57: SUB_CHAR1 | D57: #MS.SLO_SUB_CHAR1 | E57: C | F57: 20 | G57: Y | P57: 予備１ | Q57: 予備１
A58: 1 | B58: SUB_CHAR2 | D58: #MS.SLO_SUB_CHAR2 | E58: C | F58: 20 | G58: Y | P58: 予備２ | Q58: 予備２
A59: 1 | B59: SUB_CHAR3 | D59: #MS.SLO_SUB_CHAR3 | E59: C | F59: 20 | G59: Y | P59: 予備３ | Q59: 予備３
A60: 1 | B60: APRV_FLG | D60: #MA.FLG | E60: F | G60: N | H60: '0' | P60: 承認対象ＦＬＧ | Q60: 承認対象であるか（「0:承認対象外」、「1：承認対象」） 承認モジュールを実行し、戻り値の承認対象ＦＬＧを設定する
A61: 1 | B61: APRV_NO | D61: #MA.APRV_NO | E61: C | F61: 15 | G61: Y | P61: 承認ＮＯ | Q61: 承認対象外の場合はNULLとなる 承認モジュールを実行し、戻り値の承認ＮＯを設定する
A62: 1 | B62: APRV_STS_TYP | D62: #MA.APRV_STS_TYP | E62: C | F62: 1 | G62: Y | P62: 承認状況区分 | Q62: 承認対象外の場合はNULLとなる 承認モジュールを実行し、戻り値の承認状況区分を設定する 承認モジュールで承認、却下、承認取消、却下取消した際に承認状況区分を反映する。
A63: 1 | B63: EDI_FLG | D63: #MA.FLG | E63: F | G63: N | H63: '0' | P63: ＥＤＩ ＦＬＧ | Q63: 不使用項目
A64: 1 | B64: CAN_FLG | D64: #MA.FLG | E64: F | G64: N | H64: '0' | P64: 取消ＦＬＧ | Q64: 受注の取消を表すフラグ。受注を取り消すと「１」になる
A65: 1 | B65: CAN_RSN_CD | D65: #MS.SLO_RSN_CD | E65: C | F65: 10 | G65: Y | P65: 取消理由ＣＤ | Q65: 受注の取消理由を設定する。 受注を取り消す場合のみデータに設定される
A66: 1 | B66: CAN_RMRKS | D66: #MS.SLO_CAN_RMRKS | E66: C | F66: 100 | G66: Y | P66: 取消備考 | Q66: 受注の取消の備考を設定する。 受注を取り消す場合のみデータに設定される
A67: 1 | B67: CRED_UPD_AMT | D67: #MA.MONEY | E67: N | F67: 21,8 | G67: Y | P67: 与信更新金額 | Q67: 不使用項目
A68: 88 | B68: $EDI_SUB_COLS$
A69: 88 | B69: $EXCTRL_COLS$
A72: INDEX | C72: SLO_DT, CO_CD
A73: INDEX | C73: CST_CD, CO_CD
A74: INDEX | C74: CST_PO_NO, CO_CD
A75: INDEX | C75: SLS_USR_CD, CO_CD
A76: INDEX | C76: SLS_DPT_CD, CO_CD
A77: INDEX | C77: WRK_NO, CO_CD
A78: INDEX | C78: RCPT_DT, CO_CD
A84: テーブル名 | C84: 別名 | E84: 日本語名 | H84: 排他 | I84: 履歴 | J84: VIEW | K84: MULTI | L84: DBC | M84: Mod.ID | N84: クラス名 | O84: Pj.Id | P84: SuperClassPj.Id | Q84: SuperListClass | R84: SuperDMLClass | S84: SuperRowClass
A85: * | B85: MST_SLO_P_ALL | E85: 受注ヘッダ（改訂履歴） | H85: * | I85: * | J85: *
B86: 【説明】
B87: 受注ヘッダの改訂履歴を保持する。
A91: レベル | B91: 項目名 | C91: Ref. | D91: メタ | E91: 型 | F91: 桁 | G91: Null | H91: Def. | I91: 履歴 | J91: VIEW | K91: MULTI | L91: DBC | M91: 参 | N91: 表別名/参照先 | O91: INNERROW | P91: 日本語 | Q91: 説明 | R91: フルネーム | S91: 値の制限 | T91: Rev. | U91: 設定仕様 | V91: 未設定時の振る舞い
A92: 0 | B92: SLO_NO | D92: #MA.SLO_NO | E92: C | F92: 15 | G92: N | P92: 受注ＮＯ
A93: 0 | B93: CO_CD | D93: #MA.CO_CD | E93: C | F93: 10 | G93: N | J93: N | P93: 会社ＣＤ
A95: 0 | B95: SLO_REV | D95: #MA.SLIP_REV | E95: N | F95: 4,0 | G95: N | P95: 受注改訂番号
A96: 1 | B96: TRD_CD | D96: #MA.TRD_CD | E96: C | F96: 4 | G96: N | P96: 取引ＣＤ
A97: 1 | B97: TRD_PTN_TYP | D97: #MA.TRD_PTN_TYP | E97: C | F97: 4 | G97: N | P97: 取引パタン区分
A98: 1 | B98: SLO_DT | D98: #MA.DT | E98: D | G98: N | P98: 受注日
A99: 1 | B99: SLO_TYP | D99: #MS.SLO_TYP | E99: C | F99: 1 | G99: N | P99: 受注区分
A100: 1 | B100: CST_CD | D100: #MA.BP_CD | E100: C | F100: 20 | G100: N | P100: 得意先ＣＤ
A101: 1 | B101: CST_PO_NO | D101: #MA.CST_PO_NO | E101: C | F101: 20 | G101: Y | P101: 得意先注文ＮＯ
A102: 1 | B102: CST_PO_REV | D102: #MA.SLIP_REV | E102: N | F102: 4,0 | G102: Y | P102: 得意先注文改訂番号
A103: 1 | B103: TRD_CUR_CD | D103: #MA.CUR_CD | E103: C | F103: 3 | G103: Y | P103: 取引通貨ＣＤ
A104: 1 | B104: XRATE_INPT_FLG | D104: #MA.FLG | E104: F | G104: N | P104: 為替レート指定ＦＬＧ
A105: 1 | B105: XRATE | D105: #MA.MONEY | E105: N | F105: 21,8 | G105: Y | P105: 為替レート
A106: 1 | B106: PTAX_XRATE_INPT_FLG | D106: #MA.FLG | E106: F | G106: N | P106: 納税為替レート指定ＦＬＧ
A107: 1 | B107: PTAX_XRATE | D107: #MA.MONEY | E107: N | F107: 21,8 | G107: Y | P107: 納税為替レート
A108: 1 | B108: SLS_USR_CD | D108: #MA.USR_CD | E108: C | F108: 500 | G108: Y | P108: 売上担当者ＣＤ
A109: 1 | B109: SLS_DPT_CD | D109: #MA.DPT_CD | E109: C | F109: 20 | G109: N | P109: 売上部門ＣＤ
A110: 1 | B110: WG_CD | D110: #MA.WG_CD | E110: C | F110: 10 | G110: N | P110: ワーキンググループＣＤ
A111: 1 | B111: IV_NO | D111: #MA.IV_NO | E111: C | F111: 15 | G111: Y | P111: インボイスＮＯ
A112: 1 | B112: TTERM_CD1 | D112: #MA.TTERM_CD | E112: C | F112: 5 | G112: Y | P112: 取引条件ＣＤ１
A113: 1 | B113: TTERM_RMRKS1 | D113: #MS.TTERM_RMRKS1 | E113: C | F113: 100 | G113: Y | P113: 取引条件備考１
A114: 1 | B114: TTERM_CD2 | D114: #MA.TTERM_CD | E114: C | F114: 5 | G114: Y | P114: 取引条件ＣＤ２
A115: 1 | B115: TTERM_RMRKS2 | D115: #MS.TTERM_RMRKS2 | E115: C | F115: 100 | G115: Y | P115: 取引条件備考２
...

Sheet 2-1-1. ファイルフォーマット（注文）
A1: mcframe 7 | I1: 文書名 | T1: モジュールID | AB1: MS | AF1: モジュール名 | AN1: ＳＣＭ | AW1: 文書番号 | BC1: Version | BG1: Rev.
I2: バッチ説明書 | T2: サブモジュールID | AB2: MSLA | AF2: サブモジュール名 | AN2: SCM Link | AW2: M7-US-1311 | BC2: 7.0.1 | BG2: r01.01
T3: 表題 | AB3: =MID(CELL("filename",$A$1),FIND("]",CELL("filename",$A$1))+1,31) -> 2-1-1. ファイルフォーマット（注文）
B6: 2. EDIインターフェース
C8: 2-1. 注文
D10: =RIGHT(CELL("filename",D10),LEN(CELL("filename",D10))-FIND("]",CELL("filename",D10))) -> 2-1-1. ファイルフォーマット（注文）
B12: ファイル | BD12: 送信 （購買） | BG12: 受信 （販売）
B13: 項目名 | K13: 日本語名 | T13: 型 | U13: 桁 | W13: 説明 | BD13: 新規 | BE13: 更新 | BF13: 削除 | BG13: 新規 | BH13: 更新 | BI13: 削除
B14: data_lno | K14: データ行ＮＯ | T14: N | U14: 15,0 | W14: 注文情報のデータを一意に特定する番号。過去に送信したすべての注文情報も含めて一意となる番号を発番する | BD14: ◎ | BE14: ◎ | BF14: ◎ | BG14: ◎ | BH14: ◎ | BI14: ◎
B15: data_no | K15: データＮＯ | T15: N | U15: 15,0 | W15: 送信の順序を識別する番号 この番号が大きいほど後から送信されたデータとなる。1回の送信で複数明細が送信される場合、全明細で同じ値となる | BD15: ◎ | BE15: ◎ | BF15: ◎ | BG15: ◎ | BH15: ◎ | BI15: ◎
B16: trd_typ_cd | K16: 取引種別ＣＤ | T16: C | U16: 5 | W16: 取引の種別を識別するＣＤ。定数値：001 | BD16: ◎ | BE16: ◎ | BF16: ◎
B17: data_make_dt | K17: 送信元レコード作成日時 | T17: D | W17: 送信元のシステムがインターフェースデータを作成した日時 形式：yyyy/MM/dd hh:mm:ss | BD17: ◎ | BE17: ◎ | BF17: ◎ | BG17: ◎ | BH17: ◎ | BI17: ◎
B18: data_crud_typ | K18: データ更新区分 | T18: C | U18: 1 | W18: 当該の明細が新規、更新、削除のどれであるかを表す 1：新規、2：更新、3：削除 | BD18: ◎ | BE18: ◎ | BF18: ◎ | BG18: ◎ | BH18: ◎ | BI18: ◎
B19: po_crud_typ | K19: 発注更新区分 | T19: C | U19: 1 | W19: 対応する発注のヘッダ（注文書）が新規、更新、削除のどれであるかを表す 1：新規、2：更新、3：削除 | BD19: ◎ | BE19: ◎ | BF19: ◎
B20: po_no | K20: 発注ＮＯ | T20: C | U20: 20 | W20: 発注のヘッダ（注文書）を識別する番号 | BD20: ◎ | BE20: ◎ | BF20: ◎ | BG20: ◎ | BH20: ◎ | BI20: ◎
B21: po_rev | K21: 発注改訂番号 | T21: N | U21: 4,0 | W21: 発注の改訂番号 | BD21: ◎ | BE21: ◎ | BF21: ◎ | BG21: ○ | BH21: ○ | BI21: ○
B22: po_d_no | K22: 発注明細ＮＯ | T22: C | U22: 20 | W22: 発注の明細を識別する番号 ※受信側では、明細の特定は発注ＮＯ + 発注明細ＮＯで行う。注文明細ごとの管理をしないシステムとの連携の場合はNULLにすることも可能 | BD22: ◎ | BE22: ◎ | BF22: ◎ | BG22: ○ | BH22: ○ | BI22: ○
B23: po_co_cd | K23: 発注者ＣＤ | T23: C | U23: 500 | W23: 発注者のコード 送信するデータには自社の「会社ＣＤ」が設定される | BD23: ◎ | BE23: ◎ | BF23: ◎ | BG23: ◎ | BH23: ◎ | BI23: ◎
B24: po_co_nm | K24: 発注者名 | T24: C | U24: 100 | W24: 発注者の名称 | BD24: ◎ | BE24: ◎ | BF24: ◎ | BG24: △ | BH24: △ | BI24: △
B25: po_co_cntry_cd | K25: 発注者国ＣＤ | T25: C | U25: 500 | W25: 発注者の国コード | BD25: ◎ | BE25: ◎ | BF25: ◎
B26: slo_co_cd | K26: 受注者ＣＤ | T26: C | U26: 500 | W26: 受注者コード 送信するデータには「発注先ＣＤ」が設定される | BD26: ◎ | BE26: ◎ | BF26: ◎ | BG26: △ | BH26: △ | BI26: △
B27: slo_co_nm | K27: 受注者名 | T27: C | U27: 100 | W27: 受注者の名称 | BD27: ◎ | BE27: ◎ | BF27: ◎ | BG27: △ | BH27: △ | BI27: △
B28: slo_co_cntry_cd | K28: 受注者国ＣＤ | T28: C | U28: 500 | W28: 受注者の国コード | BD28: ◎ | BE28: ◎ | BF28: ◎
B29: po_dt | K29: 注文日 | T29: D | W29: 発注を行った日 形式：yyyy/MM/dd | BD29: ◎ | BE29: ◎ | BF29: ◎ | BG29: △ | BH29: △ | BI29: △
B30: upd_po_print_schd_dt | K30: 変更注文書発行予定日 | T30: D | W30: 仮単価の明細を含む注文書を発行する場合、本単価に変更して正式注文書を発行する予定の日付 形式：yyyy/MM/dd | BD30: ○ | BE30: ○ | BF30: ○
B31: crct_rsn_nm | K31: 訂正理由 | T31: C | U31: 100 | W31: 注文を訂正、削除した場合の理由 | BD31: ○ | BE31: ○ | BF31: ○
B32: crct_rsn_rmrks | K32: 訂正理由備考 | T32: C | U32: 100 | W32: 注文を訂正、削除した場合の備考 | BD32: ○ | BE32: ○ | BF32: ○
B33: po_print_txt | K33: 注文書表示テキスト | T33: C | U33: 1000 | W33: 注文書に表示する文言（取引条件等） | BD33: ○ | BE33: ○ | BF33: ○
B34: po_print_rmrks | K34: 注文書備考 | T34: C | U34: 100 | W34: 注文書の備考 | BD34: ○ | BE34: ○ | BF34: ○ | BG34: ○ | BH34: ○ | BI34: ○
B35: po_print_d_rmrks | K35: 注文明細備考 | T35: C | U35: 100 | W35: 注文書の明細備考 | BD35: ○ | BE35: ○ | BF35: ○ | BG35: ○ | BH35: ○ | BI35: ○
B36: purc_dpt_cd | K36: 購買部門ＣＤ | T36: C | U36: 500 | W36: 発注を行った部門コード | BD36: ◎ | BE36: ◎ | BF36: ◎
B37: purc_dpt_nm | K37: 購買部門名 | T37: C | U37: 100 | W37: 発注を行った部門名 | BD37: ◎ | BE37: ◎ | BF37: ◎
B38: purc_usr_cd | K38: 購買担当者ＣＤ | T38: C | U38: 500 | W38: 発注を行った担当者コード | BD38: ○ | BE38: ○ | BF38: ○
B39: purc_usr_nm | K39: 購買担当者名 | T39: C | U39: 100 | W39: 発注を行った担当者名 | BD39: ○ | BE39: ○ | BF39: ○
B40: po_co_itm_cd | K40: 発注者品目ＣＤ | T40: C | U40: 500 | W40: 発注者の品目コード | BD40: ◎ | BE40: ◎ | BF40: ◎ | BG40: ◎ | BH40: ◎ | BI40: ○
B41: po_co_itm_sub1 | K41: 発注者枝番１ | T41: C | U41: 5 | W41: 発注者の品目の枝番１ | BD41: ○ | BE41: ○ | BF41: ○ | BG41: ○ | BH41: ○ | BI41: ○
B42: po_co_itm_sub2 | K42: 発注者枝番２ | T42: C | U42: 5 | W42: 発注者の品目の枝番２ | BD42: ○ | BE42: ○ | BF42: ○ | BG42: ○ | BH42: ○ | BI42: ○
B43: po_co_itm_sub3 | K43: 発注者枝番３ | T43: C | U43: 5 | W43: 発注者の品目の枝番３ | BD43: ○ | BE43: ○ | BF43: ○ | BG43: ○ | BH43: ○ | BI43: ○
B44: po_co_itm_nm | K44: 発注者品名 | T44: C | U44: 100 | W44: 発注者の品名 | BD44: ◎ | BE44: ◎ | BF44: ◎ | BG44: ○ | BH44: ○ | BI44: ○
B45: po_co_iv_itm_nm | K45: 発注者インボイス表記品名 | T45: C | U45: 100 | W45: 発注者が輸入時に使用する品名。インボイス取引でない場合は「発注者品名」と同じ値が設定される | BD45: ◎ | BE45: ◎ | BF45: ◎
B46: po_co_sundry_itm_flg | K46: 発注者諸口品ＦＬＧ | T46: C | U46: 1 | W46: 発注者の品目コードが諸口品であるかを表す 0:諸口品でない 1:諸口品 | BD46: ○ | BE46: ○ | BF46: ○
B47: dest_cd1 | K47: 仕向先ＣＤ１ | T47: C | U47: 500 | W47: 仕向先のコード１ | BG47: ○ | BH47: ○ | BI47: ○
B48: dest_nm1 | K48: 仕向先名１ | T48: C | U48: 100 | W48: 仕向先の名称１ | BG48: △ | BH48: △ | BI48: △
B49: dest_cd2 | K49: 仕向先ＣＤ２ | T49: C | U49: 500 | W49: 仕向先のコード２ 仕向先１が設定されている場合に設定可能 | BG49: ○ | BH49: ○ | BI49: ○
B50: dest_nm2 | K50: 仕向先名２ | T50: C | U50: 100 | W50: 仕向先の名称２ | BG50: △ | BH50: △ | BI50: △
B51: dest_cd3 | K51: 仕向先ＣＤ３ | T51: C | U51: 500 | W51: 仕向先のコード３ 仕向先３が設定されている場合に設定可能 | BG51: ○ | BH51: ○ | BI51: ○
B52: dest_nm3 | K52: 仕向先名３ | T52: C | U52: 100 | W52: 仕向先の名称３ | BG52: △ | BH52: △ | BI52: △
B53: outsrc_flg | K53: 外注ＦＬＧ | T53: C | U53: 1 | W53: 外注品の発注であるかを表す 0:購入品 1:外注品 | BD53: ○ | BE53: ○ | BF53: ○
B54: drct_dlv_flg | K54: 直送ＦＬＧ | T54: C | U54: 1 | W54: 直送の発注であるかを表す 0:自社に納品（直送以外） 1:仕入直送あるいは直送支給 | BD54: ○ | BE54: ○ | BF54: ○
B55: purc_id_typ | K55: 購買識別区分 | T55: C | U55: 1 | W55: 注文の種類を表す 1:通常購買 2:無償受給 3:有償受給 4:ＶＭＩのどれに該当するのかを識別する区分 その他：1と同じ ※受信側では「2:無償受給」「3:有償受給」のデータは取り込めず、エラーとなる | BD55: ◎ | BE55: ◎ | BF55: ◎ | BG55: ○ | BH55: ○ | BI55: ○
B56: sls_cststk_flg | K56: 預り売上ＦＬＧ | T56: C | U56: 1 | W56: 出荷するよりも前に売上することを表すＦＬＧ | BG56: ○ | BH56: ○ | BI56: ○
B57: slo_typ | K57: 受注区分 | T57: C | U57: 1 | W57: 本受注あるいは仮受注のどちらであるかを表す 1:仮受注 2:本受注 その他：2と同じ | BG57: ○ | BH57: ○ | BI57: ○
B58: sls_dpt_cd | K58: 売上部門ＣＤ | T58: C | U58: 500 | W58: 受注者の担当部門コード ▽取込時のデータ補完 ・未設定 かつ データ更新区分が「新規」の場合、下記の順で補完する ①売上担当者ＣＤが設定されている場合、担当者権限マスタの主部門と同じとみなす ②売上担当者ＣＤが設定されてない場合、得意先担当マスタの部門ＣＤと同じとみなす ③得意先担当マスタに担当者が設定されている場合、担当者ＣＤに紐付く担当者権限マスタの主部門と同じとみなす ・未設定 かつ データ更新区分が「更新」の場合、下記の順で補完する ①売上担当者ＣＤが変更されてない場合、受注ヘッダの売上部門ＣＤと同じとみなす ②新規と同じ | BG58: ○ | BH58: ○ | BI58: ○
B59: sls_dpt_nm | K59: 売上部門名 | T59: C | U59: 100 | W59: 受注者の担当部門名 | BG59: △ | BH59: △ | BI59: △
B60: sls_usr_cd | K60: 売上担当者ＣＤ | T60: C | U60: 500 | W60: 受注者の担当者コード ▽取込時のデータ補完 ・未設定 かつ データ更新区分が「新規」の場合、得意先担当マスタの担当者ＣＤと同じとみなす ・未設定 かつ データ更新区分が「更新」の場合、受注ヘッダの売上担当者ＣＤと同じとみなす | BG60: ○ | BH60: ○ | BI60: ○
B61: sls_usr_nm | K61: 売上担当者名 | T61: C | U61: 100 | W61: 受注者の担当者名 | BG61: △ | BH61: △ | BI61: △
B62: in_to_id_typ | K62: 納入先識別区分 | T62: C | U62: 1 | W62: 納入先を識別する区分 当該レコードの「IN_TO_ID_CD」など納入先の項目に、「納品先」あるいは「場所」のどちらの情報が設定されているのかを識別する 1:納品先 2:場所 | BD62: ◎ | BE62: ◎ | BF62: ◎
B63: in_to_id_cd | K63: 納入先識別ＣＤ | T63: C | U63: 500 | W63: 納入先のコード 納入先識別区分が「納品先」：納品先のコード 納入先識別区分が「場所」：納入場所のコード | BD63: ◎ | BE63: ◎ | BF63: ◎ | BG63: ◎ | BH63: ◎ | BI63: ○
B64: in_to_nm | K64: 納入先名 | T64: C | U64: 100 | W64: 納入先の名称 ▽取込時のデータ補完 未設定 かつ 納品先の納品先諸口ＦＬＧがオフの場合、取引先マスタの取引先名と同じとみなす | BD64: ◎ | BE64: ◎ | BF64: ◎ | BG64: ○ | BH64: ○ | BI64: ○
B65: in_to_zip_cd | K65: 納入先郵便番号 | T65: C | U65: 10 | W65: 納入先の郵便番号 ▽取込時のデータ補完 未設定 かつ 納品先の納品先諸口ＦＬＧがオフの場合、取引先マスタの郵便番号名と同じとみなす | BD65: ○ | BE65: ○ | BF65: ○ | BG65: ○ | BH65: ○ | BI65: ○
B66: in_to_addr1 | K66: 納入先住所１ | T66: C | U66: 40 | W66: 納入先の住所１ ▽取込時のデータ補完 未設定 かつ 納品先の納品先諸口ＦＬＧがオフの場合、取引先マスタの住所１と同じとみなす | BD66: ◎ | BE66: ◎ | BF66: ◎ | BG66: ○ | BH66: ○ | BI66: ○
B67: in_to_addr2 | K67: 納入先住所２ | T67: C | U67: 40 | W67: 納入先の住所２ ▽取込時のデータ補完 未設定 かつ 納品先の納品先諸口ＦＬＧがオフの場合、取引先マスタの住所２と同じとみなす | BD67: ○ | BE67: ○ | BF67: ○ | BG67: ○ | BH67: ○ | BI67: ○
B68: in_to_addr3 | K68: 納入先住所３ | T68: C | U68: 40 | W68: 納入先の住所３ ▽取込時のデータ補完 未設定 かつ 納品先の納品先諸口ＦＬＧがオフの場合、取引先マスタの住所３と同じとみなす | BD68: ○ | BE68: ○ | BF68: ○ | BG68: ○ | BH68: ○ | BI68: ○
B69: in_to_addr4 | K69: 納入先住所４ | T69: C | U69: 40 | W69: 納入先の住所４ ▽取込時のデータ補完 未設定 かつ 納品先の納品先諸口ＦＬＧがオフの場合、取引先マスタの住所４と同じとみなす | BD69: ○ | BE69: ○ | BF69: ○ | BG69: ○ | BH69: ○ | BI69: ○
B70: in_to_cntct_dpt | K70: 納入先担当部署 | T70: C | U70: 100 | W70: 納入先の担当部署納入先識別区分が「場所」の場合は設定されない ▽取込時のデータ補完 未設定 かつ 納品先の納品先諸口ＦＬＧがオフの場合、取引先マスタの納品先部署と同じとみなす | BD70: ○ | BE70: ○ | BF70: ○ | BG70: ○ | BH70: ○ | BI70: ○
B71: in_to_cntct_psn | K71: 納入先担当者 | T71: C | U71: 100 | W71: 納入先の担当者納入先識別区分が「場所」の場合は設定されない ▽取込時のデータ補完 未設定 かつ 納品先の納品先諸口ＦＬＧがオフの場合、取引先マスタの納品先担当者と同じとみなす | BD71: ○ | BE71: ○ | BF71: ○ | BG71: ○ | BH71: ○ | BI71: ○
B72: in_to_tel | K72: 納入先ＴＥＬ | T72: C | U72: 30 | W72: 納入先の電話番号 ▽取込時のデータ補完 未設定 かつ 納品先の納品先諸口ＦＬＧがオフの場合、取引先マスタのＴＥＬと同じとみなす | BD72: ○ | BE72: ○ | BF72: ○ | BG72: ○ | BH72: ○ | BI72: ○
B73: in_to_fax | K73: 納入先ＦＡＸ | T73: C | U73: 30 | W73: 納入先のＦＡＸ ▽取込時のデータ補完 未設定 かつ 納品先の納品先諸口ＦＬＧがオフの場合、取引先マスタのＦＡＸと同じとみなす | BD73: ○ | BE73: ○ | BF73: ○ | BG73: ○ | BH73: ○ | BI73: ○
B74: in_to_sundry_flg | K74: 納入先諸口ＦＬＧ | T74: C | U74: 1 | W74: 納入先識別区分が「納品先」：納品先が諸口の場合は「1」、それ以外は「0」 納入先識別区分が「場所」：「0」 | BD74: ○ | BE74: ○ | BF74: ○
B75: in_to_cntry_cd | K75: 納入先国ＣＤ | T75: C | U75: 500 | W75: 納入先の国コード | BD75: ○ | BE75: ○ | BF75: ○ | BG75: ○ | BH75: ○ | BI75: ○
B76: site_cd | K76: 工場・物流倉庫ＣＤ | T76: C | U76: 500 | W76: 納入先識別区分が「場所」の場合は設定される 納入場所の属する工場・物流倉庫のコード | BD76: ○ | BE76: ○ | BF76: ○
B77: site_nm | K77: 工場・物流倉庫名 | T77: C | U77: 100 | W77: 工場・物流倉庫名 | BD77: ○ | BE77: ○ | BF77: ○
B78: drct_dlv_bp_cd | K78: 直送発注先ＣＤ | T78: C | U78: 500 | W78: 直送支給の場合は設定される 支給先のコード | BD78: ○ | BE78: ○ | BF78: ○
B79: drct_dlv_bp_nm | K79: 直送発注先名 | T79: C | U79: 100 | W79: 直送支給の場合は設定される 支給先の名称 | BD79: ○ | BE79: ○ | BF79: ○
B80: drct_dlv_cntry_cd | K80: 直送発注先国ＣＤ | T80: C | U80: 500 | W80: 直送支給の場合は設定される 支給先の国コード | BD80: ○ | BE80: ○ | BF80: ○
B81: tdlv_cd | K81: 配送先ＣＤ | T81: C | U81: 500 | W81: 配送先のコード ▽取込時のデータ補完 ・未設定 かつ データ更新区分が「新規」 かつ 納品先の配送先必須ＦＬＧがオンの場合、物流制御マスタの標準配送先ＣＤと同じとみなす ・未設定 かつ データ更新区分が「更新」 かつ 納品先の配送先必須ＦＬＧがオンの場合、下記の順で補完する ①売上部門のワーキンググループ かつ 納品先 かつ 品目が変更されてない場合、受注明細の配送先ＣＤと同じとみなす ②新規と同じ | BD81: ○ | BE81: ○ | BF81: ○ | BG81: ○ | BH81: ○ | BI81: ○
B82: tdlv_nm | K82: 配送先名 | T82: C | U82: 100 | W82: 配送先の名称 ▽取込時のデータ補完 ・未設定 かつ データ更新区分が「新規」 かつ 配送先の納品先諸口ＦＬＧがオフの場合、取引先マスタの取引先名と同じとみなす ・未設定 かつ データ更新区分が「更新」 かつ 配送先の納品先諸口ＦＬＧがオフの場合、下記の順で補完する ①配送先が変更されてない場合、受注明細の配送先名と同じとみなす ②新規と同じ | BD82: ○ | BE82: ○ | BF82: ○ | BG82: ○ | BH82: ○ | BI82: ○
B83: tdlv_zip_cd | K83: 配送先郵便番号 | T83: C | U83: 10 | W83: 配送先の郵便番号 ▽取込時のデータ補完 ・未設定 かつ データ更新区分が「新規」 かつ 配送先の納品先諸口ＦＬＧがオフの場合、取引先マスタの郵便番号と同じとみなす ・未設定 かつ データ更新区分が「更新」 かつ 配送先の納品先諸口ＦＬＧがオフの場合、下記の順で補完する ①配送先が変更されてない場合、受注明細の配送先郵便番号と同じとみなす ②新規と同じ | BD83: ○ | BE83: ○ | BF83: ○ | BG83: ○ | BH83: ○ | BI83: ○
B84: tdlv_addr1 | K84: 配送先住所１ | T84: C | U84: 40 | W84: 配送先の住所１ ▽取込時のデータ補完 ・未設定 かつ データ更新区分が「新規」 かつ 配送先の納品先諸口ＦＬＧがオフの場合、取引先マスタの住所１と同じとみなす ・未設定 かつ データ更新区分が「更新」 かつ 配送先の納品先諸口ＦＬＧがオフの場合、下記の順で補完する ①配送先が変更されてない場合、受注明細の配送先住所１と同じとみなす ②新規と同じ | BD84: ○ | BE84: ○ | BF84: ○ | BG84: ○ | BH84: ○ | BI84: ○
B85: tdlv_addr2 | K85: 配送先住所２ | T85: C | U85: 40 | W85: 配送先の住所２ ▽取込時のデータ補完 ・未設定 かつ データ更新区分が「新規」 かつ 配送先の納品先諸口ＦＬＧがオフの場合、取引先マスタの住所２と同じとみなす ・未設定 かつ データ更新区分が「更新」 かつ 配送先の納品先諸口ＦＬＧがオフの場合、下記の順で補完する ①配送先が変更されてない場合、受注明細の配送先住所２と同じとみなす ②新規と同じ | BD85: ○ | BE85: ○ | BF85: ○ | BG85: ○ | BH85: ○ | BI85: ○
B86: tdlv_addr3 | K86: 配送先住所３ | T86: C | U86: 40 | W86: 配送先の住所３ ▽取込時のデータ補完 ・未設定 かつ データ更新区分が「新規」 かつ 配送先の納品先諸口ＦＬＧがオフの場合、取引先マスタの住所３と同じとみなす ・未設定 かつ データ更新区分が「更新」 かつ 配送先の納品先諸口ＦＬＧがオフの場合、下記の順で補完する ①配送先が変更されてない場合、受注明細の配送先住所３と同じとみなす ②新規と同じ | BD86: ○ | BE86: ○ | BF86: ○ | BG86: ○ | BH86: ○ | BI86: ○
B87: tdlv_addr4 | K87: 配送先住所４ | T87: C | U87: 40 | W87: 配送先の住所４ ▽取込時のデータ補完 ・未設定 かつ データ更新区分が「新規」 かつ 配送先の納品先諸口ＦＬＧがオフの場合、取引先マスタの住所４と同じとみなす ・未設定 かつ データ更新区分が「更新」 かつ 配送先の納品先諸口ＦＬＧがオフの場合、下記の順で補完する ①配送先が変更されてない場合、受注明細の配送先住所４と同じとみなす ②新規と同じ | BD87: ○ | BE87: ○ | BF87: ○ | BG87: ○ | BH87: ○ | BI87: ○
B88: tdlv_cntct_dpt | K88: 配送先担当部署 | T88: C | U88: 100 | W88: 配送先の担当部署 ▽取込時のデータ補完 ・未設定 かつ データ更新区分が「新規」 かつ 配送先の納品先諸口ＦＬＧがオフの場合、取引先マスタの納品先部署と同じとみなす ・未設定 かつ データ更新区分が「更新」 かつ 配送先の納品先諸口ＦＬＧがオフの場合、下記の順で補完する ①配送先が変更されてない場合、受注明細の配送先郵便番号と同じとみなす ②新規と同じ | BD88: ○ | BE88: ○ | BF88: ○ | BG88: ○ | BH88: ○ | BI88: ○
B89: tdlv_cntct_psn | K89: 配送先担当者 | T89: C | U89: 100 | W89: 配送先の担当者 ▽取込時のデータ補完 ・未設定 かつ データ更新区分が「新規」 かつ 配送先の納品先諸口ＦＬＧがオフの場合、取引先マスタの納品先担当者と同じとみなす ・未設定 かつ データ更新区分が「更新」 かつ 配送先の納品先諸口ＦＬＧがオフの場合、下記の順で補完する ①配送先が変更されてない場合、受注明細の配送先担当者と同じとみなす ②新規と同じ | BD89: ○ | BE89: ○ | BF89: ○ | BG89: ○ | BH89: ○ | BI89: ○
B90: tdlv_tel | K90: 配送先ＴＥＬ | T90: C | U90: 30 | W90: 配送先の電話番号 ▽取込時のデータ補完 ・未設定 かつ データ更新区分が「新規」 かつ 配送先の納品先諸口ＦＬＧがオフの場合、取引先マスタのＴＥＬと同じとみなす ・未設定 かつ データ更新区分が「更新」 かつ 配送先の納品先諸口ＦＬＧがオフの場合、下記の順で補完する ①配送先が変更されてない場合、受注明細の配送先ＴＥＬと同じとみなす ②新規と同じ | BD90: ○ | BE90: ○ | BF90: ○ | BG90: ○ | BH90: ○ | BI90: ○
B91: tdlv_fax | K91: 配送先ＦＡＸ | T91: C | U91: 30 | W91: 配送先のＦＡＸ ▽取込時のデータ補完 ・未設定 かつ データ更新区分が「新規」 かつ 配送先の納品先諸口ＦＬＧがオフの場合、取引先マスタのＦＡＸと同じとみなす ・未設定 かつ データ更新区分が「更新」 かつ 配送先の納品先諸口ＦＬＧがオフの場合、下記の順で補完する ①配送先が変更されてない場合、受注明細の配送先ＦＡＸと同じとみなす ②新規と同じ | BD91: ○ | BE91: ○ | BF91: ○ | BG91: ○ | BH91: ○ | BI91: ○
B92: tdlv_sundry_flg | K92: 配送先諸口ＦＬＧ | T92: C | U92: 1 | W92: 配送先が諸口であるかを表す 0:諸口でない 1:諸口 | BD92: ○ | BE92: ○ | BF92: ○
B93: tdlv_cntry_cd | K93: 配送先国ＣＤ | T93: C | U93: 500 | W93: 配送先の国コード | BD93: ○ | BE93: ○ | BF93: ○ | BG93: ○ | BH93: ○ | BI93: ○
B94: dlv_slip_rmrks | K94: 納品書備考 | T94: C | U94: 100 | W94: 納品書に出力される備考 ▽取込時のデータ補完 未設定 かつ データ更新区分が「更新」 かつ 受注ヘッダの取引備考と同じとみなす | BD94: ○ | BE94: ○ | BF94: ○ | BG94: ○ | BH94: ○ | BI94: ○
B95: dlv_slip_d_rmrks | K95: 納品書明細備考 | T95: C | U95: 100 | W95: 納品書の明細に出力される備考 ▽取込時のデータ補完 未設定 かつ データ更新区分が「更新」 かつ 受注明細の取引明細備考と同じとみなす | BD95: ○ | BE95: ○ | BF95: ○ | BG95: ○ | BH95: ○ | BI95: ○
B96: dlv_day_week_typ | K96: 着曜日 | T96: C | U96: 1 | W96: 納入を希望する曜日 2：月曜日 3：火曜日 4：水曜日 5：木曜日 6：金曜日 7：土曜日 1：日曜日 | BG96: ○ | BH96: ○ | BI96: ○
B97: pri_prnt_typ | K97: 価格印字区分 | T97: C | U97: 1 | W97: 納品書に価格を印字するかどうかを表す区分 0:価格を印字しない 1:価格を印字する 上記以外：指定なし（受信側ではマスタから決定する） ▽取込時のデータ補完 ・未設定 かつ データ更新区分が「新規」の場合、取引先マスタ（納品先）の価格印字ＦＬＧと同じとみなす ・未設定 かつ データ更新区分が「更新」の場合、下記の順で補完する ①納品先ＣＤが変更されてない場合、受注明細の価格印字ＦＬＧと同じとみなす ②新規と同じ | BD97: ◎ | BE97: ◎ | BF97: ◎ | BG97: ○ | BH97: ○ | BI97: ○
B98: wrk_no | K98: 案件ＮＯ | T98: C | U98: 500 | W98: 案件ＮＯ 発注者のどの案件の注文かを表す | BD98: ○ | BE98: ○ | BF98: ○ | BG98: ○ | BH98: ○ | BI98: ○
B99: wrk_nm | K99: 案件名 | T99: C | U99: 100 | W99: 案件名 | BD99: ○ | BE99: ○ | BF99: ○ | BG99: △ | BH99: △ | BI99: △
B100: tterm_cd1 | K100: 取引条件ＣＤ１ | T100: C | U100: 500 | W100: 取引条件コード１ インボイス取引ではインコタームズを想定 ▽取込時のデータ補完 未設定 かつ データ更新区分が「新規」の場合、取引先マスタの得意先取引条件ＣＤ１と同じとみなす | BD100: ○ | BE100: ○ | BF100: ○ | BG100: ○ | BH100: ○ | BI100: ○
B101: tterm_nm1 | K101: 取引条件名１ | T101: C | U101: 100 | W101: 取引条件名１ | BD101: ○ | BE101: ○ | BF101: ○ | BG101: △ | BH101: △ | BI101: △
B102: tterm_rmrks1 | K102: 取引条件備考１ | T102: C | U102: 100 | W102: 取引条件コード１の備考 | BD102: ○ | BE102: ○ | BF102: ○ | BG102: ○ | BH102: ○ | BI102: ○
B103: tterm_cd2 | K103: 取引条件ＣＤ２ | T103: C | U103: 500 | W103: 取引条件コード２ インボイス取引では受渡場所を想定 ▽取込時のデータ補完 未設定 かつ データ更新区分が「新規」の場合、取引先マスタの得意先取引条件ＣＤ２と同じとみなす | BD103: ○ | BE103: ○ | BF103: ○ | BG103: ○ | BH103: ○ | BI103: ○
B104: tterm_nm2 | K104: 取引条件名２ | T104: C | U104: 100 | W104: 取引条件名２ | BD104: ○ | BE104: ○ | BF104: ○ | BG104: △ | BH104: △ | BI104: △
B105: tterm_rmrks2 | K105: 取引条件備考２ | T105: C | U105: 100 | W105: 取引条件コード２の備考 | BD105: ○ | BE105: ○ | BF105: ○ | BG105: ○ | BH105: ○ | BI105: ○
...

Sheet 2-1-8. 受信ＩＦ確認（注文）
A1: mcframe 7 | I1: 文書名 | T1: モジュールID | AB1: MS | AF1: モジュール名 | AN1: ＳＣＭ | AW1: 文書番号 | BC1: Version | BG1: Rev.
I2: バッチ説明書 | T2: サブモジュールID | AB2: MSLA | AF2: サブモジュール名 | AN2: SCM Link | AW2: M7-US-1311 | BC2: 7.0.1 | BG2: r01.01
T3: 表題 | AB3: =MID(CELL("filename",$A$1),FIND("]",CELL("filename",$A$1))+1,31) -> 2-1-8. 受信ＩＦ確認（注文）
B6: 2. EDIインターフェース
C8: 2-1. 注文
D10: =RIGHT(CELL("filename",D10),LEN(CELL("filename",D10))-FIND("]",CELL("filename",D10))) -> 2-1-8. 受信ＩＦ確認（注文）
B12: 基本情報
B13: ビュー | M13: MST_SLO_RECV_IF
B14: ビュー日本語名 | M14: 受注受信ＩＦ
B15: 更新 | M15: 可能
B16: 新規登録・ファイル入力 | M16: 可能
B17: データ取込 | M17: 可能
B18: ソート順 | M18: データＮＯ、データ行ＮＯ
B20: 画面遷移
B21: 遷移先画面ＩＤ | M21: なし
B22: 遷移先画面名
B23: 遷移条件
B24: 自動検索
B25: 遷移元項目 | AF25: 遷移先項目
B31: 検索項目
C32: 項目名 | S32: 初期値 | AA32: 備考
B33: ● | C33: データ行ＮＯ
B34: ● | C34: データＮＯ
B35: ● | C35: データ更新区分
C36: データ更新区分名
B37: ● | C37: ＰＧ実行状況区分
C38: ＰＧ実行状況区分名
B39: ● | C39: 外部システムＣＤ
B40: ● | C40: 外部システムデータＮＯ
B41: ● | C41: 外部システムデータ行ＮＯ
B42: ● | C42: 送信元レコード作成日時ＦＲＯＭ
B43: ● | C43: 送信元レコード作成日時ＴＯ
B44: ● | C44: 取込対象ＦＬＧ true | S44: オフ
B45: ● | C45: 取込対象ＦＬＧ false | S45: オフ
B46: ● | C46: 取込対象ＦＬＧ 両方 | S46: オン
B47: ● | C47: 得意先注文ＮＯ
B48: ● | C48: 得意先注文明細ＮＯ
B49: ● | C49: 得意先ＣＤ
B50: ● | C50: 注文日ＦＲＯＭ
B51: ● | C51: 注文日ＴＯ
B52: ● | C52: ログＮＯ
B53: ● | C53: ログサブキー１
B54: ● | C54: ログサブキー２
B55: ● | C55: 登録日時ＦＲＯＭ
B56: ● | C56: 登録日時ＴＯ
B57: ● | C57: 更新日時ＦＲＯＭ
B58: ● | C58: 更新日時ＴＯ
... B60: ● | C60: 送受信状況区分
C61: 送受信状況区分名
B63: 明細項目
C64: 項目名 | S64: フォーマット | AA64: 必 | AB64: 可 | AC64: 参 | AD64: 継 | AE64: 備考
B65: ● | C65: 選択 | AC65: ●
C66: データ行ＮＯ | AC66: ●
C67: データＮＯ | AC67: ●
C68: ＰＧ実行状況区分 | AC68: ●
C69: ＰＧ実行状況区分名 | AC69: ●
C70: 送受信状況区分 | AC70: ●
C71: 送受信状況区分名 | AC71: ●
B72: ● | C72: データ更新区分 | AA72: ● | AB72: ● | AD72: ●
C73: データ更新区分名 | AC73: ● | AD73: ●
B74: ● | C74: 外部システムＣＤ | AA74: ● | AB74: ● | AD74: ●
B75: ● | C75: 外部システムデータＮＯ | AA75: ● | AB75: ● | AD75: ●
B76: ● | C76: 外部システムデータ行ＮＯ | AA76: ● | AB76: ● | AD76: ●
B77: ● | C77: 送信元レコード作成日時 | S77: YMDHMS | AB77: ● | AD77: ●
B78: ● | C78: 取込対象ＦＬＧ | AB78: ● | AD78: ●
B79: ● | C79: 受信日 | S79: YMD | AB79: ● | AD79: ●
B80: ● | C80: 得意先注文ＮＯ | AB80: ● | AD80: ●
B81: ● | C81: 得意先注文改訂番号 | AB81: ● | AD81: ●
B82: ● | C82: 得意先注文明細ＮＯ | AB82: ● | AD82: ●
B83: ● | C83: 得意先ＣＤ | AB83: ● | AD83: ●
B84: ● | C84: ＩＦ得意先ＣＤ | AB84: ● | AD84: ●
B85: ● | C85: ＩＦ得意先名 | AB85: ● | AD85: ●
B86: ● | C86: 仕向先ＣＤ１ | AB86: ● | AD86: ●
B87: ● | C87: ＩＦ仕向先ＣＤ１ | AB87: ● | AD87: ●
B88: ● | C88: ＩＦ仕向先名１ | AB88: ● | AD88: ●
B89: ● | C89: 仕向先ＣＤ２ | AB89: ● | AD89: ●
B90: ● | C90: ＩＦ仕向先ＣＤ２ | AB90: ● | AD90: ●
B91: ● | C91: ＩＦ仕向先名２ | AB91: ● | AD91: ●
... B94: ● | C94: ＩＦ仕向先名３ | AB94: ● | AD94: ●
B95: ● | C95: 注文日 | S95: YMD | AB95: ● | AD95: ●
B96: ● | C96: 購買識別区分 | AB96: ● | AD96: ●
B97: ● | C97: 預り売上ＦＬＧ | AB97: ● | AD97: ●
B98: ● | C98: 受注区分 | AB98: ● | AD98: ●
B99: ● | C99: 取引通貨ＣＤ | AB99: ● | AD99: ●
B100: ● | C100: ＩＦ取引通貨ＣＤ | AB100: ● | AD100: ●
B101: ● | C101: 売上部門ＣＤ | AB101: ● | AD101: ●
B102: ● | C102: ＩＦ売上部門ＣＤ | AB102: ● | AD102: ●
B103: ● | C103: ＩＦ売上部門名 | AB103: ● | AD103: ●
B104: ● | C104: 売上担当者ＣＤ | AB104: ● | AD104: ●
B105: ● | C105: ＩＦ売上担当者ＣＤ | AB105: ● | AD105: ●
B106: ● | C106: ＩＦ売上担当者名 | AB106: ● | AD106: ●
B107: ● | C107: 納品先ＣＤ | AB107: ● | AD107: ●
... B209: ● | C209: サブロットＮＯ | AB209: ● | AD209: ●
B210: ● | C210: 納入希望日時 | S210: YMDHM | AB210: ● | AD210: ●
B211: ● | C211: 検収予定日 | S211: YMD | AB211: ● | AD211: ●
B212: ● | C212: メーカＣＤ | AB212: ● | AD212: ●
B213: ● | C213: ＩＦメーカＣＤ | AB213: ● | AD213: ●
B214: ● | C214: ＩＦメーカ名 | AB214: ● | AD214: ●
B215: ● | C215: 取引備考 | AB215: ● | AD215: ●
B216: ● | C216: 取引明細備考 | AB216: ● | AD216: ●
...

Sheet |→現行テーブル

Sheet 受注基本ファイル
A1: テーブル情報
B2: システム名 | E2: 作成者 | F2: HW59 | L2: SELECT * FROM CPOKD9.FJJ01P
B3: サブシステム名 | E3: 作成日 | F3: 2019/8/19 | L3: WHERE JAJNO IN (21080679,21080678,21080681,21080683,21080686,21080687)
B4: スキーマ名 | C4: CPOKD9 | E4: 更新日 | L4: FETCH FIRST 30 ROWS ONLY
B5: 論理テーブル名 | C5: 受注基本ファイル | E5: RDBMS | F5: DB2 for IBM i 07.02.0000 OS/400 V7R2M0
B6: 物理テーブル名 | C6: FJJ01P | H6: ="SELECT * FROM " & C4 & "." & C6 -> SELECT * FROM CPOKD9.FJJ01P
B7: 備考 | H7: FETCH FIRST 30 ROWS ONLY
B8: キー：受注No 受注基本ファイルに有償の判断をする項目はもっていません。有償支給シート受注入力画面の得意先が外注先となっているのみで判断
H9: CPOKD9.FJJ01P
BJ10: =BH14/1000*BI14/1000*BJ14 -> 423.555 | BT10: =BR14/1000*BS14/1000*BT14 -> 405.1179
A12: カラム情報 | I12: 活動区分 | J12: 受注№ | K12: 受注№(親) | L12: 製造指令回数 | M12: 部門(受注) | N12: 部門(責任) | O12: 受注区分 | P12: 製品区分 | Q12: 受注日 | R12: 納期(客先) | S12: 納期時刻 | T12: 得意先ｺｰﾄﾞ | U12: 納入先ｺｰﾄﾞ | V12: 品名1 | W12: 品名2 | X12: 注文№ | Y12: 段 | Z12: 原紙ｺｰﾄﾞ(表) | AA12: 印刷ｺｰﾄﾞ(表) | AB12: ｴﾝﾎﾞｽｺｰﾄﾞ(表) | AC12: 坪量(表) | AD12: 材料区分(表) | AE12: 原紙区分(表) | AF12: 原紙小区分(表) | AG12: 印刷区分(表) | AH12: ｴﾝﾎﾞｽ区分(表) | AI12: 原紙ｺｰﾄﾞ(中) | AJ12: 印刷ｺｰﾄﾞ(中) | AK12: ｴﾝﾎﾞｽｺｰﾄﾞ(中) | AL12: 坪量(中) | AM12: 材料区分(中) | AN12: 原紙区分(中) | AO12: 原紙小区分(中) | AP12: 印刷区分(中) | AQ12: ｴﾝﾎﾞｽ区分(中) | AR12: 原紙ｺｰﾄﾞ(裏) | AS12: 印刷ｺｰﾄﾞ(裏) | AT12: ｴﾝﾎﾞｽｺｰﾄﾞ(裏) | AU12: 坪量(裏) | AV12: 材料区分(裏) | AW12: 原紙区分(裏) | AX12: 原紙小区分(裏) | AY12: 印刷区分(裏) | AZ12: ｴﾝﾎﾞｽ区分(裏) | BA12: ﾊﾟﾋﾟｴ区分 | BB12: ﾊﾟﾋﾟｴ区分(表) | BC12: ﾊﾟﾋﾟｴ区分(中) | BD12: ﾊﾟﾋﾟｴ区分(裏) | BE12: ﾒｰｶｰｺｰﾄﾞ(表) | BF12: ﾒｰｶｰｺｰﾄﾞ(中) | BG12: ﾒｰｶｰｺｰﾄﾞ(裏) | BH12: 巾(全判) | BI12: 流れ(全判) | BJ12: 数量(全判) | BK12: 巾(ｽﾘｯﾀｰ1) | BL12: 流れ(ｽﾘｯﾀｰ1) | BM12: 数量(ｽﾘｯﾀｰ1) | BN12: 巾(ｽﾘｯﾀｰ2) | BO12: 流れ(ｽﾘｯﾀｰ2) | BP12: 数量(ｽﾘｯﾀｰ2) | BQ12: 巾(表ﾗｲﾅｰ) | BR12: 巾(受注) | BS12: 流れ(受注) | BT12: 数量(受注) | BU12: 数量単位 | BV12: ｺﾙｽﾘ区分 | BW12: 枚/ｼｰﾄ(割数) | BX12: 断裁区分 | BY12: 備考(伝票備考) | BZ12: 備考(製造) | CA12: 備考(納入) | CB12: 売上単価 | CC12: 単価単位 | CD12: 特値区分 | CE12: 後処理区分 | CF12: 受注入力者 | CG12: WS-ID(受注入力) | CH12: 受注入力日付 | CI12: 受注入力時間 | CJ12: 最終更新日付 | CK12: 最終更新時刻 | CL12: ｼｰﾄ加工区分 | CM12: 両面・片面区分 | CN12: 担当者ｺｰﾄﾞ | CO12: 受注 | CP12: 受注金額 | CQ12: 原材料費 | CR12: 標準原価金額 | CS12: 付数 | CT12: 通し | CU12: 製品ｺｰﾄﾞ(ｾｯﾄ) | CV12: 製品ｺｰﾄﾞ(部品) | CW12: 数量(ｾｯﾄ) | CX12: 数量(部品) | CY12: ｼｰﾄ単価 | CZ12: 売上単価(ｾｯﾄ) | DA12: 売上単価(個別) | DB12: 売価区分 | DC12: ｾｯﾄ比率 | DD12: 製品用途区分 | DE12: 納期(ｼｰﾄ) | DF12: 納期(生産予定表) | DG12: 印刷有無区分 | DH12: 印刷指示ﾌﾗｸﾞ | DI12: 印刷指示ﾌﾗｸﾞ(表) | DJ12: 印刷指示ﾌﾗｸﾞ(中) | DK12: 印刷指示ﾌﾗｸﾞ(裏) | DL12: 納期(印刷・表) | DM12: 納期(印刷・中) | DN12: 納期(印刷・裏) | DO12: 原紙場所(表) | DP12: 原紙場所(中) | DQ12: 原紙場所(裏) | DR12: 印刷実績日(表) | DS12: 印刷実績日(中) | DT12: 印刷実績日(裏) | DU12: 製造指示ﾌﾗｸﾞ | DV12: 製造予定日 | DW12: 製造実績日 | DX12: 製造良品数量(累積) | DY12: 製造不良数量(累積) | DZ12: ｽﾘｯﾀｰ実績日 | EA12: ｽﾘｯﾀｰ良品数量(累積) | EB12: ｽﾘｯﾀｰ不良数量(累積) | EC12: 発注表出力ﾌﾗｸﾞ | ED12: 発注表出力日付 | EE12: 発注表出力時刻 | EF12: 配車指示回数 | EG12: 納入先ｺｰﾄﾞ(最終) | EH12: 在庫区分 | EI12: 納入日(最新) | EJ12: 出荷数量(最新) | EK12: 出荷数量(累計) | EL12: 出荷完了区分 | EM12: 売上日付(最新) | EN12: 売上完了区分 | EO12: 売上単価(最新) | EP12: 巾(売上) | EQ12: 流れ(売上) | ER12: 巾(実寸法) | ES12: 売上数量(最新) | ET12: 売上数量(累計) | EU12: 売上金額(最新) | EV12: 売上金額(累計) | EW12: 棚卸日(最新) | EX12: 製造完了日(加工実績) | EY12: 製造完了数(加工実績) | EZ12: 製造完了日(仕入) | FA12: 製造完了数(仕入) | FB12: 製造完了Ｆ(加工実績) | FC12: 仕入日(最新) | FD12: 仕入実数量(累積) | FE12: 仕入数量(累積) | FF12: 係数(流れ) | FG12: 係数(数量) | FH12: 受注計算処理区分 | FI12: 受注№(加工) | FJ12: 完了数 | FK12: ｼｰﾄ納期時刻 | FL12: 見積シート単価 | FM12: 見積シート金額 | FN12: 見積加工金額 | FO12: 見積管理％ | FP12: 見積管理金額 | FQ12: 見積横持単価 | FR12: 見積横持金額 | FS12: 見積合計金額 | FT12: 見積単価 | FU12: 再製造フラグ | FV12: 製造幅変更不可ﾌﾗｸﾞ | FW12: 版№ | FX12: 号機 | FY12: 当月減耗累計数 | FZ12: 棚番号 | GA12: ｴｯﾁﾞﾌﾟﾚｽ | GB12: 検査区分 | GC12: 数量(予備) | GD12: 初回区分 | GE12: 割増売上(最低) | GF12: 売上割増金額(印刷) | GG12: 売上割増金額(コル) | GH12: 売上日付(最低割増) | GI12: ﾘｽﾄ出力区分 | GJ12: 客先品番 | GK12: 客先品名 | GL12: 製造摘要 | GM12: 納入摘要 | GN12: 出荷日 | GO12: 予定日計算区分 | GP12: 製造開始予定時刻 | GQ12: 発注単価 | GR12: 運賃請求区分 | GS12: 納品伝票区分 | GT12: 売上伝票区分 | GU12: 納入先宛名 | GV12: ﾊﾟｲﾙﾀｰﾅｰ | GW12: 請求表示加工見積 | GX12: 配送区分 | GY12: 仕入金額(部門間) | GZ12: 在庫場所区分 | HA12: 備考(配車) | HB12: 備考(シート横持 | HC12: 印刷指示№(表) | HD12: 印刷指示№(中) | HE12: 印刷指示№(裏) | HF12: 仕入先ｺｰﾄﾞ | HG12: 運送仕入先ｺｰﾄﾞ | HH12: 夜積区分 | HI12: 数量(ｴｲｷﾞｮｳｻﾝﾌﾟﾙ) | HJ12: 売上可否区分 | HK12: 納入先ｺｰﾄﾞｺﾝﾊﾞｰﾀｰ | HL12: ｺﾝﾊﾞｰﾀｰ (略) | HM12: パレット梱包Ｆ | HN12: 発注№ | HO12: 発注№ | HP12: 発注№ | HQ12: 担当者名客先 | HR12: 奪取区分 | HS12: 備考(印刷) | HT12: 数量(顧客) | HU12: 定数出荷区分 | HV12: ミスクレーム受注№ | HW12: 再製造受注備考 | HX12: 不適合社内・社外 | HY12: 数量(発注) | HZ12: FSC製品区分 | IA12: 部門(シート) | IB12: 印刷部門(表) | IC12: 印刷部門(中) | ID12: 印刷部門(裏) | IE12: 付加価値区分 | IF12: スコアラ１ | IG12: スコアラ２ | IH12: スコアラ３ | II12: スコアラ４ | IJ12: スコアラ５ | IK12: 食品安全規格
A13: No | B13: 論理名 | C13: 物理名 | D13: データ型 | E13: Not Null | F13: デフォルト | G13: 備考 | I13: JAKATU | J13: JAJNO | K13: JAJNOO | L13: JAKAI | M13: JAVMJ | N13: JAVMM | O13: JAJUK | P13: JASHK | Q13: JAJDT | R13: JANOKT | S13: JANOKJ | T13: JATKC | U13: JANNC | V13: JAHIN1 | W13: JAHIN2 | X13: JACHN | Y13: JADAN | Z13: JAGSC1 | AA13: JAPRC1 | AB13: JAEBC1 | AC13: JATUB1 | AD13: JAZRK1 | AE13: JAGSK1 | AF13: JAGLK1 | AG13: JAPRK1 | AH13: JAEBK1 | AI13: JAGSC2 | AJ13: JAPRC2 | AK13: JAEBC2 | AL13: JATUB2 | AM13: JAZRK2 | AN13: JAGSK2 | AO13: JAGLK2 | AP13: JAPRK2 | AQ13: JAEBK2 | AR13: JAGSC3 | AS13: JAPRC3 | AT13: JAEBC3 | AU13: JATUB3 | AV13: JAZRK3 | AW13: JAGSK3 | AX13: JAGLK3 | AY13: JAPRK3 | AZ13: JAEBK3 | BA13: JAPPE | BB13: JAPPE1 | BC13: JAPPE2 | BD13: JAPPE3 | BE13: JAMKC1 | BF13: JAMKC2 | BG13: JAMKC3 | BH13: JAHAB1 | BI13: JANGR1 | BJ13: JASRY1 | BK13: JAHAB2 | BL13: JANGR2 | BM13: JASRY2 | BN13: JAHAB3 | BO13: JANGR3 | BP13: JASRY3 | BQ13: JAHAB4 | BR13: JAHABJ | BS13: JANGRJ | BT13: JASRYJ | BU13: JASTK | BV13: JAKOK | BW13: JAMIS | BX13: JADSK | BY13: JABIKB | BZ13: JABIKS | CA13: JABIKN | CB13: JAUTN | CC13: JATTK | CD13: JATNK | CE13: JAATK | CF13: JAJTN | CG13: JAWIDJ | CH13: JAJTD | CI13: JAJNT | CJ13: JALDT | CK13: JALTM | CL13: JASKK | CM13: JAROK | CN13: JATNC | CO13: JAJMM | CP13: JAJKG | CQ13: JAGZA | CR13: JAGKG | CS13: JATKE | CT13: JATOS | CU13: JASHC1 | CV13: JASHC2 | CW13: JASRY4 | CX13: JASRY5 | CY13: JASTT | CZ13: JAUTNS | DA13: JAUTNP | DB13: JABKK | DC13: JAHIR | DD13: JAYOK | DE13: JANOKS | DF13: JANOKY | DG13: JAPUM | DH13: JAPSF | DI13: JAPSF1 | DJ13: JAPSF2 | DK13: JAPSF3 | DL13: JANOK1 | DM13: JANOK2 | DN13: JANOK3 | DO13: JAGSB1 | DP13: JAGSB2 | DQ13: JAGSB3 | DR13: JAPZD1 | DS13: JAPZD2 | DT13: JAPZD3 | DU13: JASSF | DV13: JASYD | DW13: JASZD | DX13: JASGSR | DY13: JASBSR | DZ13: JASRD | EA13: JASRGR | EB13: JASRBR | EC13: JAHTF | ED13: JAHTD | EE13: JAHTT | EF13: JAHSK | EG13: JANNCL | EH13: JAZIK | EI13: JASDTN | EJ13: JASSUN | EK13: JASSUR | EL13: JAHPK | EM13: JAUDTN | EN13: JAUPK | EO13: JAUTNN | EP13: JAHABU | EQ13: JANGRU | ER13: JAHABZ | ES13: JAUSUN | ET13: JAUSUR | EU13: JAUKGN | EV13: JAUKGR | EW13: JATODN | EX13: JAMPDK | EY13: JAMPSK | EZ13: JAMPDI | FA13: JAMPSI | FB13: JAKZPF | FC13: JASIDN | FD13: JAIZSR | FE13: JAISUR | FF13: JAKEI | FG13: JAKEIS | FH13: JACPK | FI13: JAJNOK | FJ13: JAKNS | FK13: JANKSJ | FL13: JAMMST | FM13: JAMMSG | FN13: JAMMKG | FO13: JAMMKP | FP13: JAMMKH | FQ13: JAMMYT | FR13: JAMMYG | FS13: JAMMTG | FT13: JAMMTT | FU13: JARPT | FV13: JASHHF | FW13: JAHAN | FX13: JAGOK | FY13: JAGMSR | FZ13: JATNNO | GA13: JAEGPS | GB13: JAKSKB | GC13: JASRYY | GD13: JAHKB | GE13: JAHSKP | GF13: JAURWP | GG13: JAURWC | GH13: JAUDTP | GI13: JALST | GJ13: JACHNO | GK13: JACHNM | GL13: JASTKY | GM13: JANTKY | GN13: JASKDT | GO13: JAYKKB | GP13: JASJIY | GQ13: JAHTNK | GR13: JAUCSK | GS13: JANDPK | GT13: JAUDPK | GU13: JAATNM | GV13: JAPILE | GW13: JAKMSH | GX13: JAHSKB | GY13: JASKGV | GZ13: JAZIBK | HA13: JABIKH | HB13: JABIKY | HC13: JAPSN1 | HD13: JAPSN2 | HE13: JAPSN3 | HF13: JASRC | HG13: JASRCU | HH13: JAYZK | HI13: JASRYE | HJ13: JAURKH | HK13: JATKCC | HL13: JATKRC | HM13: JAPKF | HN13: JAHTN1 | HO13: JAHTN2 | HP13: JAHTN3 | HQ13: JATNNK | HR13: JADSKB | HS13: JABIKP | HT13: JASRYC | HU13: JATEIS | HV13: JAJNOC | HW13: JABIKJ | HX13: JAMISU | HY13: JASRYH | HZ13: JAFSCK | IA13: JAVMMS | IB13: JAVMP1 | IC13: JAVMP2 | ID13: JAVMP3 | IE13: JAFKK | IF13: JASC11 | IG13: JASC12 | IH13: JASC13 | II13: JASC14 | IJ13: JASC15 | IK13: JAF220
A14: 1 | B14: 活動区分 | C14: JAKATU | D14: NUMERIC | E14: Yes | F14: 0 | G14: 0:ｶﾂﾄﾞｳﾃﾞｰﾀ 1:ｻｸｼﾞｮﾃﾞｰﾀ | I14: 0 | J14: 21080678 | K14: 0 | L14: 1 | M14: 5110 | N14: 5120 | O14: 1 | P14: 11 | Q14: 20180903 | R14: 20180906 | S14: 0 | T14: 50695 | U14: 518661 | V14: E/FC5XC5 813X660 | X14: 831-21-1-1 | Y14: E | Z14: C5 | AA14: 0000 | AB14: 00 | AC14: 160 | AD14: 4 | AE14: 4 | AF14: 92 | AI14: 0001 | AJ14: 0000 | AK14: 00 | AL14: 115 | AM14: 4 | AN14: 4 | AO14: 98 | AR14: C5 | AS14: 0000 | AT14: 00 | AU14: 160 | AV14: 4 | AW14: 4 | AX14: 92 | BA14: 0 | BB14: 0 | BC14: 0 | BD14: 0 | BE14: 0 | BF14: 0 | BG14: 0 | BH14: 850 | BI14: 660 | BJ14: 755 | BK14: 813 | BL14: 660 | BM14: 755 | BN14: 0 | BO14: 0 | BP14: 0 | BQ14: 0 | BR14: 813 | BS14: 660 | BT14: 755 | BU14: 2 | BV14: 3 | BW14: 1 | BX14: 0 | BY14: ｱｵﾔﾏｻﾏﾌﾞﾝ | BZ14: 必ず反転 | CA14: 9/5ﾋﾙﾂﾐ6 ｻﾞﾂﾊﾟﾚｯﾄﾗｯﾌﾟﾏｷ | CB14: 42 | CC14: 1 | CD14: 0 | CE14: 0 | CF14: 4123 | CG14: NW65 | CH14: 20180903 | CI14: 62924 | CJ14: 20180903 | CK14: 63045 | CL14: 1 | CM14: 1 | CN14: 5064 | CO14: 424 | CP14: 17808 | CQ14: 7451.69 | CR14: 14332 | CS14: 0 | CT14: 1 | CW14: 0 | CX14: 0 | CY14: 31.34 | CZ14: 0 | DA14: 0 | DB14: 0 | DC14: 0 | DE14: 20180906 | DF14: 20180905 | DG14: 0 | DH14: 0 | DI14: 0 | DJ14: 0 | DK14: 0 | DL14: 0 | DM14: 0 | DN14: 0 | DR14: 0 | DS14: 0 | DT14: 0 | DU14: 1 | DV14: 20180904 | DW14: 20180904 | DX14: 762 | DY14: 4 | DZ14: 20180904 | EA14: 762 | EB14: 4 | EC14: 1 | ED14: 20180904 | EE14: 90325 | EF14: 1 | EG14: 0 | EH14: 0 | EI14: 20180906 | EJ14: 755 | EK14: 755 | EL14: 1 | EM14: 20180906 | EN14: 1 | EO14: 42 | EP14: 850 | EQ14: 660 | ER14: 813 | ES14: 755 | ET14: 755 | EU14: 17789 | EV14: 17789 | EW14: 0 | EX14: 0 | EY14: 0 | EZ14: 0 | FA14: 0 | FB14: 0 | FC14: 0 | FD14: 0 | FE14: 0 | FF14: 1 | FG14: 1 | FH14: 2 | FI14: 0 | FJ14: 762 | FK14: 0 | FL14: 0 | FM14: 0 | FN14: 0 | FO14: 0 | FP14: 0 | FQ14: 0 | FR14: 0 | FS14: 0 | FT14: 0 | FU14: 0 | FV14: 0 | FX14: 1 | FY14: 0 | GA14: 0 | GB14: 0 | GC14: 0 | GD14: 0 | GE14: 0 | GF14: 0 | GG14: 0 | GH14: 0 | GI14: 0 | GL14: 0 | GM14: 0 | GN14: 0 | GO14: 0 | GP14: 2143 | GQ14: 0 | GR14: 0 | GS14: 0 | GT14: 0 | GV14: 0 | GW14: 0 | GX14: 0 | GY14: 0 | GZ14: 0 | HC14: 0 | HD14: 0 | HE14: 0 | HF14: 0 | HG14: 50058 | HH14: 1 | HI14: 0 | HJ14: 0 | HK14: 0 | HM14: 0 | HN14: 0 | HO14: 0 | HP14: 0 | HR14: 0 | HT14: 0 | HU14: 0 | HV14: 0 | HX14: 0 | HY14: 0 | HZ14: 0 | IA14: 5120 | IB14: 0 | IC14: 0 | ID14: 0 | IE14: 4 | IF14: 0 | IG14: 0 | IH14: 0 | II14: 0 | IJ14: 0 | IK14: 0
