Workbook
Name Rev.: 表紙!$U$22
Name Ver.: 表紙!$AE$26
Name ご確認者: 表紙!$AG$40
Name ご確認日: 表紙!$AG$42
Name サブシステム名: 表紙!$U$28
Name システム名: 表紙!$U$26
Name プロジェクト名: 表紙!$U$18
Name 開発区分: 表紙!$U$36
Name 機能ＩＤ: 表紙!$U$32
Name 機能区分: 表紙!$U$34
Name 機能名称: 表紙!$U$30
Name 顧客名: 表紙!$U$16
Name 最終更新者: 表紙!$AB$40
Name 最終更新日: 表紙!$AB$42
Name 作成者: 表紙!$W$40
Name 作成日: 表紙!$W$42
Name 章: 表紙!$M$10
Name 文書名: 表紙!$M$10

Sheet 目次
A1: アドオン設計書作成ガイド
C3: ■アドオン設計と成果物について
D4: ・システム設計フェーズとソフトウェア設計フェーズでアドオンの処理仕様を定義する
D5: ・システム設計フェーズとソフトウェア設計フェーズの成果物がアドオン設計書であり、ソフトウェア製作フェーズのインプットとなる
C7: ■各設計フェーズ毎のアドオン設計書作成範囲
D8: ・システム設計フェーズ：他機能との関連を定義するとともに、画面や帳票、ファイル入出力を中心とした外部入出力の設計を行う
D9: ・ソフトウェア設計フェーズ：内部処理を中心とした設計を行う
U11: ◎ | W11: … | X11: システム設計フェーズで作成
U12: ○ | W12: … | X12: システム設計フェーズで基本仕様を定義して、ソフトウェア設計フェーズで詳細化する
U13: △ | W13: … | X13: 必要に応じて（例えば標準仕様から変更がない場合は不要）
U14: ‐ | W14: … | X14: 不要
W15: … | X15: ソフトウェア設計フェーズで作成
D17: 各設計書と作成対象シートのマトリックス | S17: ※カスタマイズ：標準機能に機能を追加する アドオン：新規で機能を開発する
D18: EXCELシート | N18: 画面設計書 | W18: バッチ設計書 | AF18: 帳票設計書 | AO18: ＢＩ設計書 | AT18: .Net設計書 | BB18: EXCELシート | BL18: WebDB設計書 | BR18: 帳票設計書 | BX18: 汎用申請設計書
N19: カスタマイズ | S19: アドオン | W19: カスタマイズ | AB19: アドオン | AF19: カスタマイズ | AK19: アドオン | AO19: アドオン | AT19: アドオン | BL19: アドオン | BR19: アドオン | BX19: アドオン
D20: 概要 | N20: ◎ | O20: ※1 | S20: ◎ | W20: ◎ | X20: ※1 | AB20: ◎ | AF20: ◎ | AG20: ※1 | AK20: ◎ | AO20: ◎ | AT20: ◎ | BB20: 機能概要 | BL20: ◎ | BR20: ◎ | BX20: ◎
D21: レイアウト | N21: ◎ | O21: ※2 | S21: ◎ | W21: ‐ | AB21: ‐ | AF21: ◎ | AG21: ※2 | AK21: ◎ | AO21: ◎ | AT21: ◎ | BB21: アプリケーションフロー | BL21: ◎ | BR21: ー | BX21: ◎
D22: 項目説明 | N22: △ | S22: ○ | W22: ‐ | AB22: ‐ | AF22: △ | AK22: ○ | AO22: ○ | AT22: ○ | BB22: データベース設定 | BL22: ◎ | BR22: ー | BX22: ◎
D23: 引数説明 | N23: ‐ | S23: ‐ | W23: △ | AB23: ◎ | AF23: ‐ | AK23: ‐ | AO23: ‐ | AT23: ◎ | BB23: フィールド設定 | BL23: ◎ | BR23: ー | BX23: ◎
D24: 処理概要 | N24: ◎ | S24: ◎ | W24: ◎ | AB24: ◎ | AF24: ◎ | AK24: ◎ | AO24: ◎ | AT24: ◎ | BB24: 一覧表示画面設定 | BL24: ◎ | BR24: ー | BX24: ◎
D25: 処理詳細 | BB25: 表示編集画面設定 | BL25: ◎ | BR25: ー | BX25: ◎
D26: 処理・サービス関連図 | N26: △ | S26: ◎ | W26: △ | AB26: ◎ | AF26: ‐ | AK26: ‐ | AO26: ‐ | AT26: ◎ | BB26: 明細画面設定 | BL26: △ | BN26: ※3 | BR26: ー | BX26: △ | BZ26: ※3
D27: 検索入出力仕様 | N27: △ | S27: ○ | W27: △ | AB27: ○ | AF27: ‐ | AK27: ‐ | AO27: ‐ | AT27: ○ | BB27: 集計表示設定 | BL27: △ | BN27: ※4 | BR27: ー | BX27: △ | BZ27: ※4
D28: 更新入出力仕様 | N28: △ | S28: ○ | W28: △ | AB28: ○ | AF28: ‐ | AK28: ‐ | AO28: ‐ | AT28: ○ | BB28: 絞り込み条件設定 | BL28: △ | BN28: ※5 | BR28: ー | BX28: △ | BZ28: ※5
D29: ファイル入出力仕様 | N29: △ | S29: △ | W29: ‐ | AB29: ‐ | AF29: ‐ | AK29: ‐ | AO29: ‐ | AT29: △ | BB29: その他設定 | BR29: ー
D30: 画面遷移 | N30: △ | S30: ◎ | W30: ‐ | AB30: ‐ | AF30: ‐ | AK30: ‐ | AO30: ‐ | AT30: ◎ | BB30: 帳票イメージ | BL30: ー | BR30: ◎ | BX30: ー
D31: メッセージ一覧 | N31: △ | S31: △ | W31: △ | AB31: △ | AF31: ‐ | AK31: ‐ | AO31: ‐ | AT31: △ | BB31: 項目設計 | BL31: ー | BR31: ◎ | BX31: ー
D32: 補足説明 | N32: △ | S32: △ | W32: △ | AB32: △ | AF32: △ | AK32: △ | AO32: △ | AT32: △ | BB32: 補足説明 | BL32: △ | BR32: △ | BX32: △
D33: サービス呼出編集仕様 | N33: - | S33: - | W33: - | AB33: - | AF33: - | AK33: - | AO33: - | AT33: - | BB33: 補足説明(詳細)
D35: ※1 | G35: 別シートでカスタマイズ内容を記載する | BB35: ※3 | BE35: 単票画面は記載しない
D36: ※2 | G36: 吹き出しでカスタマイズ内容を記載する | BB36: ※4 | BE36: 集計・グラフ機能を使用する場合に記載する
BB37: ※5 | BE37: 共通設定のみ記載する(個別設定は、記載しない)

Sheet 表紙
AW2: サブモジュール
AW3: MA_マスタ管理
AW4: MB_業務共通
AW5: MG_原価管理
AW6: MSBA_需給管理
M7: 基本設計 | AW7: MSBB_販売管理
AW8: MSBC_生産管理
AW9: MSBD_購買管理
M10: アドオン設計書 | AW10: MSBE_在庫物流管理
AW11: MSBF_品質管理
AW12: MSBG_債権管理
AW13: MSBH_債務管理
AW14: MSBI_締処理
AW15: MSUA_リスト・入力補助
M16: 顧客 | U16: 株式会社クラウン・パッケージ | AW16: PF_ESBアダプタ
M18: プロジェクト名 | U18: 基幹システム刷新PJ | AW18: 機能区分
AW19: 画面
M20: 文書番号 | AW20: 帳票
AW21: バッチ
M22: Ｒｅｖ． | U22: {=MAX(_xlfn.NUMBERVALUE(改訂!A7:E44))} -> 1 | AW22: マスタ
M24: 機密性区分 | U24: 取扱注意（Ｃ） | AW24: 開発区分
AW25: カスタマイズ
M26: システム名 | U26: Webシステム | AC26: Ver. | AE26: 7.0.2 | AW26: アドオン
AW27: －
M28: サブモジュール | U28: MSBB_販売管理
M30: 機能名 | U30: =M50 -> 受注伝票
M32: 機能ID | U32: =G50 -> MSBBRA050
M34: 機能区分 | U34: 帳票
M36: 開発区分 | U36: アドオン
W39: 作成 | AB39: 最終更新 | AG39: ご確認
W40: MDSOL
W42: 44837
A48: 文書番号 | G48: 画面ID | M48: 画面名 | V48: Version | AB48: Revision
A50: M7-US-1140 | G50: MSBBRA050 | M50: 受注伝票 | V50: 1.0.0 | AB50: r01.00
A53: 共通（元データ）
A54: Webシステム | K54: 文書名 | U54: モジュールID | Z54: MS | AE54: モジュール名 | AJ54: Webシステム | AS54: 文書番号 | AZ54: Version | BF54: Rev.
K55: 画面説明書 | U55: ｻﾌﾞﾓｼﾞｭｰﾙID | Z55: MSBB | AE55: ｻﾌﾞﾓｼﾞｭｰﾙ名 | AJ55: 販売Webシステム | AS55: 972501-0-0001 | AZ55: 1.0.0 | BF55: r00.00
K56: 表紙 | U56: 表題 | Z56: MSBBRA050 | AE56: 受注伝票
A57: 共通（リンク用）
A58: =A54 -> Webシステム | K58: 文書名 | U58: モジュールID | Z58: =Z54 -> MS | AE58: モジュール名 | AJ58: =AJ54 -> Webシステム | AS58: 文書番号 | AZ58: Version | BF58: Rev.
K59: =文書名 -> アドオン設計書 | U59: ｻﾌﾞﾓｼﾞｭｰﾙID | Z59: =Z55 -> MSBB | AE59: ｻﾌﾞﾓｼﾞｭｰﾙ名 | AJ59: =AJ55 -> 販売Webシステム | AS59: =AS55 -> 972501-0-0001 | AZ59: =AZ55 -> 1.0.0 | BF59: =BF55 -> r00.00
K60: =RIGHT(CELL("filename",$A$1),LEN(CELL("filename",$A$1))-FIND("]",CELL("filename",$A$1))) -> 表紙 | U60: 表題 | Z60: =Z56 -> MSBBRA050 | AE60: =AE56 -> 受注伝票
A62: 概要シート用
A63: =A58 -> Webシステム | O63: 文書名 | AC63: モジュールID | AJ63: =Z58 -> MS | AQ63: モジュール名 | AX63: =AJ58 -> Webシステム | BL63: 文書番号 | BU63: Version | CB63: Rev.
O64: =K59 -> アドオン設計書 | AC64: サブモジュールID | AJ64: =Z59 -> MSBB | AQ64: サブモジュール名 | AX64: =AJ59 -> 販売Webシステム | BL64: =AS59 -> 972501-0-0001 | BU64: 7.0.2 | CB64: {=MAX(_xlfn.NUMBERVALUE(改訂!A7:E44))} -> 1
O65: =RIGHT(CELL("filename",$A$1),LEN(CELL("filename",$A$1))-FIND("]",CELL("filename",$A$1))) -> 表紙 | AC65: 表題 | AJ65: =Z60 -> MSBBRA050 | AQ65: =AE60 -> 受注伝票

Sheet 改訂
A1: 第7章 | K1: 改訂 | AU1: 作成者 | AZ1: MDSOL | BE1: 作成日 | BJ1: =表紙!W42 -> 44837 | BP1: Rev.
AU2: 修正者 | BE2: 改訂日 | BP2: =表紙!CB64 -> 1
A5: Rev. | F5: 改定内容 | BC5: 頁 | BM5: 変更日 変更者 | BR5: 確認日 確認者
A7: 1 | F7: 新規作成

Sheet 概要
A1: =表紙!A54 -> Webシステム | O1: 文書名 | AC1: モジュールID | AJ1: =表紙!AJ63 -> MS | AQ1: モジュール名 | AX1: =表紙!AX63 -> Webシステム | BL1: 文書番号 | BU1: Version | CB1: Rev.
O2: =表紙!O64 -> アドオン設計書 | AC2: サブモジュールID | AJ2: =表紙!AJ64 -> MSBB | AQ2: サブモジュール名 | AX2: =表紙!AX64 -> 販売Webシステム | BL2: =表紙!BL64 -> 972501-0-0001 | BU2: =表紙!BU64 -> 7.0.2 | CB2: =表紙!CB64 -> 1
O3: =RIGHT(CELL("filename",$A$1),LEN(CELL("filename",$A$1))-FIND("]",CELL("filename",$A$1))) -> 概要 | AC3: 表題 | AJ3: =表紙!AJ65 -> MSBBRA050 | AQ3: =表紙!AQ65 -> 受注伝票
AO5: 概要
C7: 【業務要件】
D8: カスタマイズ | H8: 内容
D9: No.
D10: 80 | H10: 受注伝票を追加する
C13: 【機能概要】
D14: 1. | E14: 受注・製品マスタから情報を受注伝票を発行する
C16: 【前提条件】
D17: 1. | E17: PrintPro：帳票フォームはCP様設計とする
D18: 2. | E18: 単票形式とする
C20: 【説明】
D21: ・ | E21: 受注情報と工程情報を出力し、生産予定組後の受注納期を関係者へ回覧する
C23: 【帳票分類】
D24: ・ | E24: 社内帳票
C26: 【帳票ツール】
D27: ・ | E27: PrintProを利用した仕組み(CSVをログインユーザー単位にサーの所定フォルダへ出力する)
C29: 【帳票出力条件】
D30: ・ | E30: 受注入力で登録されたデータを出力対象データとする
C32: 【再発行時の印刷データ利用】
D33: ・ | E33: なし
D34: ※発行時のデータを保存しない
C36: 【改頁条件】
D37: ・ | E37: 手配NO
D38: ・ | E38: 部材が3件以上
C40: 【データのソート順】
D41: ・ | E41: 手配NO、製品CD
C43: 【自由記述】
D44: ・ | E44: なし

Sheet 帳票イメージ
A1: =表紙!A54 -> Webシステム | K1: 文書名 | U1: モジュールID | Z1: =表紙!$AJ$63 -> MS | AE1: モジュール名 | AJ1: =表紙!$AX$63 -> Webシステム | AS1: 文書番号 | AZ1: Version | BF1: Rev.
K2: =表紙!O64 -> アドオン設計書 | U2: ｻﾌﾞﾓｼﾞｭｰﾙID | Z2: =表紙!$AJ$64 -> MSBB | AE2: ｻﾌﾞﾓｼﾞｭｰﾙ名 | AJ2: =表紙!$AX$64 -> 販売Webシステム | AS2: =表紙!$BL$64 -> 972501-0-0001 | AZ2: =表紙!$BU$64 -> 7.0.2 | BF2: =表紙!$CB$64 -> 1
K3: =RIGHT(CELL("filename",$A$1),LEN(CELL("filename",$A$1))-FIND("]",CELL("filename",$A$1))) -> 帳票イメージ | U3: 表題 | Z3: =表紙!$AJ$65 -> MSBBRA050 | AE3: =表紙!$AQ$65 -> 受注伝票
A5: 帳票イメージ
BG8: 青枠はヘッダー・フッター情報
BG9: ピンク枠は明細情報
BG10: 黄緑枠は固定情報
BN24: 廃棄返却 版型マスタ
BN25: 上単価→売上単価
BN26: シート数、ショート過剰
BN27: 原紙使用ｍ

Sheet 項目説明 
A1: =表紙!A54 -> Webシステム | K1: 文書名 | U1: モジュールID | Z1: =表紙!$AJ$63 -> MS | AE1: モジュール名 | AJ1: =表紙!$AX$63 -> Webシステム | AS1: 文書番号 | AZ1: Version | BF1: Rev.
K2: =表紙!O64 -> アドオン設計書 | U2: ｻﾌﾞﾓｼﾞｭｰﾙID | Z2: =表紙!$AJ$64 -> MSBB | AE2: ｻﾌﾞﾓｼﾞｭｰﾙ名 | AJ2: =表紙!$AX$64 -> 販売Webシステム | AS2: =表紙!$BL$64 -> 972501-0-0001 | AZ2: =表紙!$BU$64 -> 7.0.2 | BF2: =表紙!$CB$64 -> 1
K3: =RIGHT(CELL("filename",$A$1),LEN(CELL("filename",$A$1))-FIND("]",CELL("filename",$A$1))) -> 項目説明 | U3: 表題 | Z3: =表紙!$AJ$65 -> MSBBRA050 | AE3: =表紙!$AQ$65 -> 受注伝票
C5: 共通項目エリア | N5: 表示 | R5: 最大 | T5: 出力仕様 | BK5: O
T6: テーブル名 | AB6: 項目名 | AJ6: 備考
A7: 参照テーブル
T8: 受注
T9: 受注明細
T10: 受注加工工程
T11: 担当者マスタ
T12: 受注(過去) | AJ12: 製品CDで受注・受注明細を検索し、受注日降順で抽出し、最初に一致したデータ
T13: 受注明細(過去)
A15: 上部
A16: 1 | C16: 機密事項 | T16: 製品マスタ | AB16: 機密情報区分
A17: 2 | C17: 受注日 | T17: 受注 | AB17: 受注日
A18: 3 | C18: 納期 | T18: 受注 | AB18: 客先納期
A19: 4 | C19: 得意先CD | T19: 受注 | AB19: 得意先CD
A20: 5 | C20: 得意先名 | T20: 取引先マスタ | AB20: 取引先名
A21: 6 | C21: 納入先CD | T21: 受注 | AB21: 納入先CD
A22: 7 | C22: 納入先名 | T22: 取引先マスタ | AB22: 取引先名
A23: 8 | C23: 品名 | T23: 受注明細 | AB23: CP品名１
A24: 9 | C24: FSC | T24: 受注明細 | AB24: FSC認証
A25: 10 | C25: 注文NO | T25: 受注 | AB25: 注文NO
A26: 11 | C26: 営業担当CD | T26: 受注 | AB26: 営業担当CD
A27: 12 | C27: 営業担当名 | T27: 担当者マスタ | AB27: 担当者名
... A32: 17 | C32: 売価区分 | T32: 受注明細 | AB32: 売価区分
A33: 18 | C33: 前項あり | AJ33: 受注明細数で設定
A34: 19 | C34: 食品安全 | T34: 受注明細 | AB34: 食品安全
A35: 中部
A36: 1 | C36: 番号 | T36: 受注明細 | AB36: 明細番号
A37: 2 | C37: 部材名 | T37: 受注明細 | AB37: CP品名2
A38: 3 | C38: 製品CD | T38: 受注明細 | AB38: 製品CD
A39: 4 | C39: 客品番 | T39: 受注明細 | AB39: 客品番
A40: 5 | C40: 手配NO | T40: 受注明細 | AB40: 手配NO
A41: 6 | C41: 工程１ | T41: 受注加工工程 | AB41: 工程CD | AJ41: 先頭行から順番に設定していく
A42: 7 | C42: 工程２ | T42: 受注加工工程 | AB42: 工程CD | AJ42: 先頭行から順番に設定していく
A43: 8 | C43: 工程３ | T43: 受注加工工程 | AB43: 工程CD | AJ43: 先頭行から順番に設定していく
A44: 9 | C44: 工程４ | T44: 受注加工工程 | AB44: 工程CD | AJ44: 先頭行から順番に設定していく
A45: 10 | C45: 工程５ | T45: 受注加工工程 | AB45: 工程CD | AJ45: 先頭行から順番に設定していく
A46: 11 | C46: 工程６ | T46: 受注加工工程 | AB46: 工程CD | AJ46: 先頭行から順番に設定していく
A47: 12 | C47: 工程７ | T47: 受注加工工程 | AB47: 工程CD | AJ47: 先頭行から順番に設定していく
A48: 13 | C48: 工程８ | T48: 受注加工工程 | AB48: 工程CD | AJ48: 先頭行から順番に設定していく
A49: 14 | C49: 受注数 | T49: 受注明細 | AB49: 受注数
A50: 15 | C50: 単価 | T50: 受注明細 | AB50: 単価
A51: 16 | C51: セット比率 | T51: 受注明細 | AB51: セット比率
A52: 17 | C52: 見積ロット | T52: 製品マスタ | AB52: ロット数
A53: 18 | C53: 両 | AJ53: 受注加工工程のコルゲータが片面か両面かで設定
A54: 19 | C54: G | T54: 受注明細 | AB54: 段
A55: 20 | C55: 使用M
A56: 21 | C56: T/TH-0610 | T56: 受注加工工程 | AB56: 版NO
A57: 22 | C57: 丁 | T57: 受注加工工程 | AB57: 工程仕様１ | AJ57: トムソンの丁付けを取得
A58: 23 | C58: 表原紙コード | T58: 受注明細 | AB58: 表原紙コード
A59: 24 | C59: 表印刷コード | T59: 受注明細 | AB59: 表印刷コード
A60: 25 | C60: 表エンボス | T60: 受注明細 | AB60: 表エンボス
A61: 26 | C61: 表原紙名 | T61: 受注明細 | AB61: 表原紙名
A62: 27 | C62: 中原紙コード | T62: 受注明細 | AB62: 中原紙コード
A63: 28 | C63: 中印刷コード | T63: 受注明細 | AB63: 中印刷コード
A64: 29 | C64: 中エンボス | T64: 受注明細 | AB64: 中エンボス
A65: 30 | C65: 中原紙名 | T65: 受注明細 | AB65: 中原紙名
A66: 31 | C66: 裏原紙コード | T66: 受注明細 | AB66: 裏原紙コード
A67: 32 | C67: 裏印刷コード | T67: 受注明細 | AB67: 裏印刷コード
A68: 33 | C68: 裏エンボス | T68: 受注明細 | AB68: 裏エンボス
A69: 34 | C69: 裏原紙名 | T69: 受注明細 | AB69: 裏原紙名
... A78: 43 | C78: 伝票備考 | T78: 受注明細 | AB78: 伝票備考
A79: 下部
A80: 1 | C80: 新版 | AJ80: 手書き項目とする
A81: 2 | C81: 先方版 | AJ81: 手書き項目とする
A82: 3 | C82: 新型 | AJ82: 手書き項目とする
A83: 4 | C83: 先方型 | AJ83: 手書き項目とする
A84: 5 | C84: サンプル要不要 | AJ84: 受注明細.サンプル数が0より大きい場合あり、0はなし
A85: 6 | C85: サンプル数 | T85: 受注明細 | AB85: サンプル数
C86: (デザイン分含む)
A87: 7 | C87: 刷本入荷・引取り出荷NO | AJ87: 手書き項目とする
A88: 8 | C88: 刷本入荷・引取り数 | AJ88: 手書き項目とする
A89: 9 | C89: 刷本寸法 | AJ89: 手書き項目とする
A90: 10 | C90: 片面・構成 | AJ90: 手書き項目とする
A91: 11 | C91: 中芯 | AJ91: 手書き項目とする
A92: 12 | C92: 片面・寸法 巾 | AJ92: 手書き項目とする
A93: 13 | C93: 片面・寸法 流れ | AJ93: 手書き項目とする
A94: 14 | C94: 納入予備 要不要 | AJ94: 受注明細.納入予備数が0より大きい場合あり、0はなし
A95: 15 | C95: 納入予備数 | T95: 受注明細 | AB95: 納入予備数
A96: 16 | C96: 前回受注年月日 | T96: 受注(過去) | AB96: 受注日
A97: 17 | C97: 前回手配NO | T97: 受注明細(過去) | AB97: 手配NO | AJ97: 受注回数なのでは
A98: 18 | C98: 前回シート数 | T98: 受注明細(過去)
A99: 19 | C99: ショート過剰
A100: 20 | C100: ※続きあり | AJ100: ３部材以上の場合で最終ページ(手配NOでグループ)でない場合に表示

Sheet 処理概要
A1: =表紙!A54 -> Webシステム | K1: 文書名 | U1: モジュールID | Z1: =表紙!$AJ$63 -> MS | AE1: モジュール名 | AJ1: =表紙!$AX$63 -> Webシステム | AS1: 文書番号 | AZ1: Version | BF1: Rev.
K2: =表紙!O64 -> アドオン設計書 | U2: ｻﾌﾞﾓｼﾞｭｰﾙID | Z2: =表紙!$AJ$64 -> MSBB | AE2: ｻﾌﾞﾓｼﾞｭｰﾙ名 | AJ2: =表紙!$AX$64 -> 販売Webシステム | AS2: =表紙!$BL$64 -> 972501-0-0001 | AZ2: =表紙!$BU$64 -> 7.0.2 | BF2: =表紙!$CB$64 -> 1
K3: =RIGHT(CELL("filename",$A$1),LEN(CELL("filename",$A$1))-FIND("]",CELL("filename",$A$1))) -> 処理概要 | U3: 表題 | Z3: =表紙!$AJ$65 -> MSBBRA050 | AE3: =表紙!$AQ$65 -> 受注伝票
A5: No | B5: 入力 | J5: 処理 | BD5: 出力
A6: 1 | B6: ヘッダー・明細・フッター | J6: 入力
C8: Web受注入力 | K8: 売上ヘッダテーブル他から出力対象のデータを読み込む。
C9: Web受注一覧照会
A19: ２ | B19: 出力する | J19: 出力する
C21: Web受注入力 | K21: 読み込んだデータに対して、受注伝票を出力する。 | BD21: 受注伝票
C22: Web受注一覧照会
K23: 明細3セットで改頁する。
K25: 手配NO単位で改頁する。

Sheet 処理詳細
A1: =表紙!A54 -> Webシステム | K1: 文書名 | U1: モジュールID | Z1: =表紙!$AJ$63 -> MS | AE1: モジュール名 | AJ1: =表紙!$AX$63 -> Webシステム | AS1: 文書番号 | AZ1: Version | BF1: Rev.
K2: =表紙!O64 -> アドオン設計書 | U2: ｻﾌﾞﾓｼﾞｭｰﾙID | Z2: =表紙!$AJ$64 -> MSBB | AE2: ｻﾌﾞﾓｼﾞｭｰﾙ名 | AJ2: =表紙!$AX$64 -> 販売Webシステム | AS2: =表紙!$BL$64 -> 972501-0-0001 | AZ2: =表紙!$BU$64 -> 7.0.2 | BF2: =表紙!$CB$64 -> 1
K3: =RIGHT(CELL("filename",$A$1),LEN(CELL("filename",$A$1))-FIND("]",CELL("filename",$A$1))) -> 処理詳細 | U3: 表題 | Z3: =表紙!$AJ$65 -> MSBBRA050 | AE3: =表紙!$AQ$65 -> 受注伝票
A5: No | B5: 入力 | J5: 処理 | BD5: 出力
A6: 1 | B6: 対象データの抽出
J7: 1．帳票上部項目抽出
K8: 下記の条件に従い、対象テーブルからデータを検索する。
K10: ・WEB受注をもとに検索する
K11: 帳票項目 | W11: テーブル | AE11: 項目名 | AM11: 取得条件、編集仕様
K12: 機密事項 | W12: WEB製品基本マスタ | AE12: 機密情報区分
K13: 受注日 | W13: WEB受注 | AE13: 受注日
K14: 納期 | W14: WEB受注 | AE14: 客先納期
K15: 得意先CD | W15: WEB受注 | AE15: 得意先CD
K16: 得意先名 | W16: WEB取引先マスタ | AE16: 取引先名
K17: 納入先CD | W17: WEB受注明細 | AE17: 納品先CD
K18: 納入先名 | W18: WEB取引先マスタ | AE18: 取引先名
K19: 品名 | W19: WEB受注明細 | AE19: CP品名１
K20: FSC | W20: WEB受注明細 | AE20: FSC認証
K21: 注文NO | W21: WEB受注 | AE21: 注文NO
K22: 営業担当CD | W22: WEB受注 | AE22: 営業担当CD
K23: 営業担当名 | W23: 担当者マスタ | AE23: 担当者名
... K29: 食品安全 | W29: WEB受注明細 | AE29: 食品安全
K31: 【結合条件】
O32: WEB受注 | U32: Web受注NO | AA32: = | AD32: WEB受注明細 | AM32: Web受注NO
M33: AND | O33: WEB受注明細 | U33: 製品コード | AA33: = | AD33: WEB製品基本マスタ | AM33: 製品コード
M34: AND | O34: WEB受注 | U34: 得意先ＣＤ | AA34: = | AD34: WEB取引先マスタ ※得意先 | AM34: 取引先ＣＤ
M35: AND | O35: WEB取引先マスタ | U35: 得意先ＦＬＧ | AA35: = | AD35: '1'
M36: AND | O36: WEB取引先マスタ | U36: 論理削除ＦＬＧ | AA36: = | AD36: '0'
M37: AND | O37: WEB受注 | U37: 納入先CD | AA37: = | AD37: WEB取引先マスタ ※納品先 | AM37: 取引先ＣＤ
M38: AND | O38: WEB取引先マスタ | U38: 納品先ＦＬＧ | AA38: = | AD38: '1'
M39: AND | O39: WEB取引先マスタ | U39: 論理削除ＦＬＧ | AA39: = | AD39: '0'
M40: AND | O40: WEB受注 | U40: 営業担当CD | AA40: = | AD40: 担当者マスタ | AM40: 担当者CD
M41: AND | O41: 担当者マスタ | U41: 論理削除ＦＬＧ | AA41: = | AD41: '0'
M42: AND | O42: WEB取引先マスタ | U42: 業務担当CD | AA42: = | AD42: 担当者マスタ | AM42: 担当者CD | AR42: (得意先)
M43: AND | O43: 担当者マスタ | U43: 論理削除ＦＬＧ | AA43: = | AD43: '0'
J45: 2．帳票中部項目抽出
K46: 下記の条件に従い、対象テーブルからデータを検索する。
K48: ・WEB受注明細をもとに検索する
K49: 帳票項目 | W49: テーブル | AE49: 項目名 | AM49: 取得条件、編集仕様
K50: 番号 | W50: WEB受注明細 | AE50: 明細番号
K51: 部材名 | W51: WEB受注明細 | AE51: CP品名2
K52: 製品CD | W52: WEB受注明細 | AE52: 製品CD
K53: 客品番 | W53: WEB受注明細 | AE53: 客品番
K54: 手配NO | W54: WEB受注明細 | AE54: 手配NO
K55: 工程１ | W55: WEB受注加工工程 | AE55: 工程CD | AM55: 先頭行から順番に設定していく
K56: 工程２ | W56: WEB受注加工工程 | AE56: 工程CD | AM56: 先頭行から順番に設定していく
K57: 工程３ | W57: WEB受注加工工程 | AE57: 工程CD | AM57: 先頭行から順番に設定していく
K58: 工程４ | W58: WEB受注加工工程 | AE58: 工程CD | AM58: 先頭行から順番に設定していく
K59: 工程５ | W59: WEB受注加工工程 | AE59: 工程CD | AM59: 先頭行から順番に設定していく
K60: 工程６ | W60: WEB受注加工工程 | AE60: 工程CD | AM60: 先頭行から順番に設定していく
K61: 工程７ | W61: WEB受注加工工程 | AE61: 工程CD | AM61: 先頭行から順番に設定していく
K62: 工程８ | W62: WEB受注加工工程 | AE62: 工程CD | AM62: 先頭行から順番に設定していく
K63: 受注数 | W63: WEB受注明細 | AE63: 受注数
K64: 単価 | W64: WEB受注明細 | AE64: 単価
K65: セット比率 | W65: WEB受注明細 | AE65: セット比率
K66: 見積ロット | W66: WEB製品基本マスタ | AE66: ロット数
K67: 両 | AM67: 受注加工工程のコルゲータが片面か両面かで設定
K68: G | W68: WEB受注明細 | AE68: 段
K69: 使用M | AM69: 受注加工工程に工程ＣＤ＝"0050"(原紙巻取り)の仕様1 ※原紙の巻M
K70: T/TH-0610 | W70: WEB受注加工工程 | AE70: 版NO
K71: 丁 | W71: WEB受注加工工程 | AE71: 工程仕様１ | AM71: トムソン工程の丁付けを取得
K72: 表原紙コード | W72: WEB受注明細 | AE72: 表原紙コード
K73: 表印刷コード | W73: WEB受注明細 | AE73: 表印刷コード
K74: 表エンボス | W74: WEB受注明細 | AE74: 表エンボス
K75: 表原紙名 | W75: WEB受注明細 | AE75: 表原紙名
K76: 中原紙コード | W76: WEB受注明細 | AE76: 中原紙コード
K77: 中印刷コード | W77: WEB受注明細 | AE77: 中印刷コード
K78: 中エンボス | W78: WEB受注明細 | AE78: 中エンボス
K79: 中原紙名 | W79: WEB受注明細 | AE79: 中原紙名
K80: 裏原紙コード | W80: WEB受注明細 | AE80: 裏原紙コード
K81: 裏印刷コード | W81: WEB受注明細 | AE81: 裏印刷コード
K82: 裏エンボス | W82: WEB受注明細 | AE82: 裏エンボス
K83: 裏原紙名 | W83: WEB受注明細 | AE83: 裏原紙名
... K92: 伝票備考 | W92: WEB受注明細 | AE92: 伝票備考
K94: 【結合条件】
O95: WEB受注 | U95: Web受注NO | AA95: = | AD95: WEB受注明細 | AM95: Web受注NO
M96: AND | O96: WEB受注明細 | U96: Web受注NO | AA96: = | AD96: WEB受注加工工程 | AM96: Web受注NO
M97: AND | O97: WEB受注明細 | U97: Web受注明細ＮＯ | AA97: = | AD97: WEB受注加工工程 | AM97: Web受注明細ＮＯ
M98: AND | O98: WEB受注明細 | U98: 製品コード | AA98: = | AD98: WEB受注加工工程 | AM98: 製品コード
M99: AND | O99: WEB受注明細 | U99: 製品コード | AA99: = | AD99: WEB製品基本マスタ | AM99: 製品コード
J102: 3．帳票下部項目抽出
K103: 下記の条件に従い、対象テーブルからデータを検索する。
K105: ・WEB受注明細をもとに検索する
K106: 帳票項目 | W106: テーブル | AE106: 項目名 | AM106: 取得条件、編集仕様
K107: サンプル数 | W107: 受注明細 | AE107: サンプル数
K108: 納入予備数 | W108: 受注明細 | AE108: 納入予備数
K109: 前回受注年月日 | W109: 受注(過去) | AE109: 受注日
K110: 前回手配NO | W110: 受注明細(過去) | AE110: 手配NO
K111: 前回シート数 | W111: 受注明細(過去) | AE111: 数量
K112: ショート過剰 | AM112: 出来高実績（過去）の出来高数（取引単位数量の合計）を検索する。 検索条件： 品目CD＝受注明細(過去).品目ＣＤ 枝番１＝受注明細(過去).枝番１ 枝番２＝受注明細(過去).枝番２ 枝番３＝受注明細(過去).枝番３ 手配NO1＝受注明細(過去).手配NO1 手配NO２＝受注明細(過去).手配NO２ 手配NO３＝受注明細(過去).手配NO３ 手配NO４＝受注明細(過去).手配NO４ ・出来高数＞受注明細（過去）.数量の場合、”過剰”とする。 ・出来高数＜受注明細（過去）.数量の場合、”ショート”とする。
K114: 【結合条件】
O115: WEB受注 | U115: Web受注NO | AA115: = | AD115: WEB受注明細 | AK115: Web受注NO
M116: AND | O116: WEB受注 | U116: Web受注NO | AA116: = | AD116: 受注(過去) | AK116: Web受注NO | AO116: (+)
M117: AND | O117: WEB受注明細 | U117: Web受注明細ＮＯ | AA117: = | AD117: 受注明細(過去) | AK117: Web受注明細ＮＯ | AQ117: (+)
M118: AND | O118: 受注(過去) | U118: Web受注NO | AA118: = | AD118: 受注明細(過去) | AK118: Web受注NO | AO118: (+)
M121: ※ | O121: WEB受注(過去)
O122: WEB受注明細(過去)
O123: 製品CD、得意先ＣＤを条件に前回の受注・受注明細を検索する。※受注日降順で抽出し、最初に一致したデータ
A126: ２ | B126: 出力する
J128: 1．検索結果を下記の項目順でソートする。 | X128: ※フォームにて設定される場合、当処理は不要。
...

Sheet 出力元画面
A1: =表紙!A54 -> Webシステム | K1: 文書名 | U1: モジュールID | Z1: =表紙!$AJ$63 -> MS | AE1: モジュール名 | AJ1: =表紙!$AX$63 -> Webシステム | AS1: 文書番号 | AZ1: Version | BF1: Rev.
K2: =表紙!O64 -> アドオン設計書 | U2: ｻﾌﾞﾓｼﾞｭｰﾙID | Z2: =表紙!$AJ$64 -> MSBB | AE2: ｻﾌﾞﾓｼﾞｭｰﾙ名 | AJ2: =表紙!$AX$64 -> 販売Webシステム | AS2: =表紙!$BL$64 -> 972501-0-0001 | AZ2: =表紙!$BU$64 -> 7.0.2 | BF2: =表紙!$CB$64 -> 1
K3: =RIGHT(CELL("filename",$A$1),LEN(CELL("filename",$A$1))-FIND("]",CELL("filename",$A$1))) -> 出力元画面 | U3: 表題 | Z3: =表紙!$AJ$65 -> MSBBRA050 | AE3: =表紙!$AQ$65 -> 受注伝票
AD5: 出力元画面
B7: 画面ＩＤ | I7: 画面名 | Y7: 備考
B8: MSBBPA070 | I8: Web受注入力
B9: MSBBPA080 | I9: Web受注一覧照会
