Workbook
Name Rev.: 表紙!$U$22
Name Revision: [2]表紙!$AP$5
Name Ver.: 表紙!$AE$26
Name Version: [2]表紙!$AJ$5
Name ご確認者: 表紙!$AG$40
Name ご確認日: 表紙!$AG$42
Name サブシステム名: 表紙!$U$28
Name システム名: 表紙!$U$26
Name プロジェクト名: 表紙!$U$18
Name 開発区分: 表紙!$U$36
Name 機能ＩＤ: 表紙!$U$32
Name 機能区分: 表紙!$U$34
Name 機能名称: 表紙!$U$30
Name 顧客名: 表紙!$U$16
Name 最終更新者: 表紙!$AB$40
Name 最終更新日: 表紙!$AB$42
Name 作成者: 表紙!$W$40
Name 作成日: 表紙!$W$42
Name 章: 表紙!$M$10
Name 文書番号: [2]表紙!$O$5
Name 文書名: 表紙!$M$10
Name 文書名: [2]表紙!$M$15

Sheet 目次
A1: アドオン設計書作成ガイド
C3: ■アドオン設計と成果物について
D4: ・システム設計フェーズとソフトウェア設計フェーズでアドオンの処理仕様を定義する
D5: ・システム設計フェーズとソフトウェア設計フェーズの成果物がアドオン設計書であり、ソフトウェア製作フェーズのインプットとなる
C7: ■各設計フェーズ毎のアドオン設計書作成範囲
D8: ・システム設計フェーズ：他機能との関連を定義するとともに、画面や帳票、ファイル入出力を中心とした外部入出力の設計を行う
D9: ・ソフトウェア設計フェーズ：内部処理を中心とした設計を行う
U11: ◎ | W11: … | X11: システム設計フェーズで作成
U12: ○ | W12: … | X12: システム設計フェーズで基本仕様を定義して、ソフトウェア設計フェーズで詳細化する
U13: △ | W13: … | X13: 必要に応じて（例えば標準仕様から変更がない場合は不要）
U14: ‐ | W14: … | X14: 不要
W15: … | X15: ソフトウェア設計フェーズで作成
D17: 各設計書と作成対象シートのマトリックス | S17: ※カスタマイズ：標準機能に機能を追加する アドオン：新規で機能を開発する
D18: EXCELシート | N18: 画面設計書 | W18: バッチ設計書 | AF18: 帳票設計書 | AO18: ＢＩ設計書 | AT18: .Net設計書 | BB18: EXCELシート | BL18: WebDB設計書 | BR18: 帳票設計書 | BX18: 汎用申請設計書
N19: カスタマイズ | S19: アドオン | W19: カスタマイズ | AB19: アドオン | AF19: カスタマイズ | AK19: アドオン | AO19: アドオン | AT19: アドオン | BL19: アドオン | BR19: アドオン | BX19: アドオン
D20: 概要 | N20: ◎ | O20: ※1 | S20: ◎ | W20: ◎ | X20: ※1 | AB20: ◎ | AF20: ◎ | AG20: ※1 | AK20: ◎ | AO20: ◎ | AT20: ◎ | BB20: 機能概要 | BL20: ◎ | BR20: ◎ | BX20: ◎
D21: レイアウト | N21: ◎ | O21: ※2 | S21: ◎ | W21: ‐ | AB21: ‐ | AF21: ◎ | AG21: ※2 | AK21: ◎ | AO21: ◎ | AT21: ◎ | BB21: アプリケーションフロー | BL21: ◎ | BR21: ー | BX21: ◎
D22: 項目説明 | N22: △ | S22: ○ | W22: ‐ | AB22: ‐ | AF22: △ | AK22: ○ | AO22: ○ | AT22: ○ | BB22: データベース設定 | BL22: ◎ | BR22: ー | BX22: ◎
D23: 引数説明 | N23: ‐ | S23: ‐ | W23: △ | AB23: ◎ | AF23: ‐ | AK23: ‐ | AO23: ‐ | AT23: ◎ | BB23: フィールド設定 | BL23: ◎ | BR23: ー | BX23: ◎
D24: 処理概要 | N24: ◎ | S24: ◎ | W24: ◎ | AB24: ◎ | AF24: ◎ | AK24: ◎ | AO24: ◎ | AT24: ◎ | BB24: 一覧表示画面設定 | BL24: ◎ | BR24: ー | BX24: ◎
D25: 処理詳細 | BB25: 表示編集画面設定 | BL25: ◎ | BR25: ー | BX25: ◎
D26: 処理・サービス関連図 | N26: △ | S26: ◎ | W26: △ | AB26: ◎ | AF26: ‐ | AK26: ‐ | AO26: ‐ | AT26: ◎ | BB26: 明細画面設定 | BL26: △ | BN26: ※3 | BR26: ー | BX26: △ | BZ26: ※3
D27: 検索入出力仕様 | N27: △ | S27: ○ | W27: △ | AB27: ○ | AF27: ‐ | AK27: ‐ | AO27: ‐ | AT27: ○ | BB27: 集計表示設定 | BL27: △ | BN27: ※4 | BR27: ー | BX27: △ | BZ27: ※4
D28: 更新入出力仕様 | N28: △ | S28: ○ | W28: △ | AB28: ○ | AF28: ‐ | AK28: ‐ | AO28: ‐ | AT28: ○ | BB28: 絞り込み条件設定 | BL28: △ | BN28: ※5 | BR28: ー | BX28: △ | BZ28: ※5
D29: ファイル入出力仕様 | N29: △ | S29: △ | W29: ‐ | AB29: ‐ | AF29: ‐ | AK29: ‐ | AO29: ‐ | AT29: △ | BB29: その他設定 | BR29: ー
D30: 画面遷移 | N30: △ | S30: ◎ | W30: ‐ | AB30: ‐ | AF30: ‐ | AK30: ‐ | AO30: ‐ | AT30: ◎ | BB30: 帳票イメージ | BL30: ー | BR30: ◎ | BX30: ー
D31: メッセージ一覧 | N31: △ | S31: △ | W31: △ | AB31: △ | AF31: ‐ | AK31: ‐ | AO31: ‐ | AT31: △ | BB31: 項目設計 | BL31: ー | BR31: ◎ | BX31: ー
D32: 補足説明 | N32: △ | S32: △ | W32: △ | AB32: △ | AF32: △ | AK32: △ | AO32: △ | AT32: △ | BB32: 補足説明 | BL32: △ | BR32: △ | BX32: △
D33: サービス呼出編集仕様 | N33: - | S33: - | W33: - | AB33: - | AF33: - | AK33: - | AO33: - | AT33: - | BB33: 補足説明(詳細)
D35: ※1 | G35: 別シートでカスタマイズ内容を記載する | BB35: ※3 | BE35: 単票画面は記載しない
D36: ※2 | G36: 吹き出しでカスタマイズ内容を記載する | BB36: ※4 | BE36: 集計・グラフ機能を使用する場合に記載する
BB37: ※5 | BE37: 共通設定のみ記載する(個別設定は、記載しない)

Sheet 表紙
AW2: サブモジュール
AW3: MA_マスタ管理
AW4: MB_業務共通
AW5: MG_原価管理
AW6: MSBA_需給管理
M7: 基本設計 | AW7: MSBB_販売管理
AW8: MSBC_生産管理
AW9: MSBD_購買管理
M10: アドオン設計書 | AW10: MSBE_在庫物流管理
AW11: MSBF_品質管理
AW12: MSBG_債権管理
AW13: MSBH_債務管理
AW14: MSBI_締処理
AW15: MSUA_リスト・入力補助
M16: 顧客 | U16: 株式会社クラウン・パッケージ | AW16: PF_ESBアダプタ
M18: プロジェクト名 | U18: 基幹システム刷新PJ | AW18: 機能区分
AW19: 画面
M20: 文書番号 | AW20: 帳票
AW21: バッチ
M22: Ｒｅｖ． | U22: {=MAX(_xlfn.NUMBERVALUE(改訂!A7:E44))} -> 1 | AW22: マスタ
M24: 機密性区分 | U24: 取扱注意（Ｃ） | AW24: 開発区分
AW25: カスタマイズ
M26: システム名 | U26: Webシステム | AC26: Ver. | AE26: 7.0.2 | AW26: アドオン
AW27: －
M28: サブモジュール | U28: MSBB_販売管理
M30: 機能名 | U30: =M50 -> Web見積計算書入力
M32: 機能ID | U32: =G50 -> MSBBPA010
M34: 機能区分 | U34: 画面
M36: 開発区分 | U36: アドオン
W39: 作成 | AB39: 最終更新 | AG39: ご確認
W40: MDSOL
W42: 44824
A48: 文書番号 | G48: 画面ID | M48: 画面名 | V48: Version | AB48: Revision
A50: M7-US-1140 | G50: MSBBPA010 | M50: Web見積計算書入力 | V50: 1.0.0 | AB50: r01.00
A53: 共通（元データ）
A54: Webシステム | K54: 文書名 | U54: モジュールID | Z54: MS | AE54: モジュール名 | AJ54: 見積管理 | AS54: 文書番号 | AZ54: Version | BF54: Rev.
K55: 画面説明書 | U55: ｻﾌﾞﾓｼﾞｭｰﾙID | Z55: MSBB | AE55: ｻﾌﾞﾓｼﾞｭｰﾙ名 | AJ55: Webシステム | AS55: M7-US-1140 | AZ55: 1.0.0 | BF55: r00.00
K56: 表紙 | U56: 表題 | Z56: MSBBPA010 | AE56: Web見積計算書入力
A57: 共通（リンク用）
A58: =A54 -> Webシステム | K58: 文書名 | U58: モジュールID | Z58: =Z54 -> MS | AE58: モジュール名 | AJ58: =AJ54 -> 見積管理 | AS58: 文書番号 | AZ58: Version | BF58: Rev.
K59: =文書名 -> アドオン設計書 | U59: ｻﾌﾞﾓｼﾞｭｰﾙID | Z59: =Z55 -> MSBB | AE59: ｻﾌﾞﾓｼﾞｭｰﾙ名 | AJ59: =AJ55 -> Webシステム | AS59: =AS55 -> M7-US-1140 | AZ59: =AZ55 -> 1.0.0 | BF59: =BF55 -> r00.00
K60: =RIGHT(CELL("filename",$A$1),LEN(CELL("filename",$A$1))-FIND("]",CELL("filename",$A$1))) -> #VALUE! | U60: 表題 | Z60: =Z56 -> MSBBPA010 | AE60: =AE56 -> Web見積計算書入力
A62: 概要シート用
A63: =A58 -> Webシステム | O63: 文書名 | AC63: モジュールID | AJ63: =Z58 -> MS | AQ63: モジュール名 | AX63: =AJ58 -> 見積管理 | BL63: 文書番号 | BU63: Version | CB63: Rev.
O64: =K59 -> アドオン設計書 | AC64: サブモジュールID | AJ64: =Z59 -> MSBB | AQ64: サブモジュール名 | AX64: =AJ59 -> Webシステム | BL64: =AS59 -> M7-US-1140 | BU64: 7.0.2 | CB64: {=MAX(_xlfn.NUMBERVALUE(改訂!A7:E44))} -> 1
O65: =RIGHT(CELL("filename",$A$1),LEN(CELL("filename",$A$1))-FIND("]",CELL("filename",$A$1))) -> #VALUE! | AC65: 表題 | AJ65: =Z60 -> MSBBPA010 | AQ65: =AE60 -> Web見積計算書入力

Sheet 改訂
A1: 第7章 | K1: 改訂 | AU1: 作成者 | AZ1: MDSOL | BE1: 作成日 | BJ1: =表紙!W42 -> 44824 | BP1: Rev.
AU2: 修正者 | BE2: 改訂日 | BP2: =表紙!CB64 -> 1
A5: Rev. | F5: 改定内容 | BC5: 頁 | BM5: 変更日 変更者 | BR5: 確認日 確認者
A7: 1 | F7: 新規作成

Sheet 概要
A1: =表紙!A54 -> Webシステム | O1: 文書名 | AC1: モジュールID | AJ1: =表紙!AJ63 -> MS | AQ1: モジュール名 | AX1: =表紙!AX63 -> 見積管理 | BL1: 文書番号 | BU1: Version | CB1: Rev.
O2: =表紙!O64 -> アドオン設計書 | AC2: サブモジュールID | AJ2: =表紙!AJ64 -> MSBB | AQ2: サブモジュール名 | AX2: =表紙!AX64 -> Webシステム | BL2: =表紙!BL64 -> M7-US-1140 | BU2: =表紙!BU64 -> 7.0.2 | CB2: =表紙!CB64 -> 1
O3: =RIGHT(CELL("filename",$A$1),LEN(CELL("filename",$A$1))-FIND("]",CELL("filename",$A$1))) -> #VALUE! | AC3: 表題 | AJ3: =表紙!AJ65 -> MSBBPA010 | AQ3: =表紙!AQ65 -> Web見積計算書入力
AO5: 概要
B7: 【業務要件】
C8: カスタマイズ | G8: 内容
C9: No. | G9: アドオン件名 | Y9: アドオン機能
C10: 3 | G10: 見積管理：見積入力画面 | Y10: ■定型の見積もりフォームに数量と単価などを入力し、見積もりを行う | AT10: システム設計フェーズ変更点
Y11: ■見積結果は蓄積され、再活用できること | AU11: 見積計算書(価格印字無※見積計算書とレイアウトは同じ)の出力帳票を追加
Y12: ・定型見積フォーム入力
Y13: ・見積計算書の発行
Y14: ■見積マスターを用いて、見積額を算出する
Y15: ■製品仕様ごとの原価・粗利を見れるようにする
Y16: ■標準LTが分かるようにする（将来課題）
C17: 4 | G17: 見積Webシステム | Y17: 見積Webシステム：主要機能
C18: 146 | H18: 見積業務は、機能要求レベルが高く、 | Y18: ①見積(見積計算書)入力・発行②御見積書入力・発行③見積確定④受注入力⑤受注一覧(単価訂正)⑥製品マスタ⑦得意先マスタ⑧シート単価マスタ
H19: UIに機能制限があるPOWER EGGでの実現が難しく、 | Y19: ※詳細機能は、「機能要件一覧」に記載
H20: 見積Webシステム(スクラッチ開発)を新規に構築する。 | Z20: システム設計フェーズ変更点
AA21: ④受注入力(TOP画面、基本情報、工程情報)
AB22: 当初想定は、1画面で明細形式での画面構成を想定していたが、製品マスタと同等のテーブル構造を持ち、
AB23: 受注入力でも工程仕様画面を表示(仕様の変更可はシート受注のみ)するように変更
B25: 【機能概要】
C26: ・顧客要求より、製品の仕様を登録し、見積計算処理を行う。
B28: 【前提条件】
C29: ・WEB見積計算書入力、見積計算は、WEBシステムの機能とする。(WEBシステムに機能構築する。)
B31: 【説明】
C32: ・見積計算書の登録(新規登録・訂正登録・削除)及び参照を行う画面、見積計算書を発行する
B34: 【目的】
C35: ・見積計算書を登録・訂正する。
C36: ・見積計算書を発行する。
C37: ・見積計算書の決定入力する。（見積提出後、決定した場合、補足情報を追加入力する。）
B39: 【処理関連図/サービス関連図】
C40: ※処理・サービス関連図シートに詳細記載
B42: 【オペレーション一覧】
C43: ID | L43: 処理名 | Y43: 処理概要
C44: Srch01 | L44: 検索 | Y44: 見積計算書の検索処理を行う。
C45: Upd01 | L45: 登録 | Y45: 見積計算書の登録処理を行う。
C46: Del01 | L46: 削除 | Y46: 見積計算書の削除処理を行う。
B48: 【SQLID一覧】
C49: なし
B51: 【ソート順】
C52: なし
B54: 【データアクセスコントロール】
C55: ・拠点による制御
C56: ※詳細は、【MSBBPA000】_共通設計書_アドオン(Webシステム共通仕様)にて定義
B58: 【自由記述】
C59: なし

Sheet レイアウト
A1: =表紙!A54 -> Webシステム | K1: 文書名 | U1: モジュールID | Z1: =表紙!$AJ$63 -> MS | AE1: モジュール名 | AJ1: =表紙!$AX$63 -> 見積管理 | AS1: 文書番号 | AZ1: Version | BF1: Rev.
K2: =表紙!O64 -> アドオン設計書 | U2: ｻﾌﾞﾓｼﾞｭｰﾙID | Z2: =表紙!$AJ$64 -> MSBB | AE2: ｻﾌﾞﾓｼﾞｭｰﾙ名 | AJ2: =表紙!$AX$64 -> Webシステム | AS2: =表紙!$BL$64 -> M7-US-1140 | AZ2: =表紙!$BU$64 -> 7.0.2 | BF2: =表紙!$CB$64 -> 1
K3: =RIGHT(CELL("filename",$A$1),LEN(CELL("filename",$A$1))-FIND("]",CELL("filename",$A$1))) -> #VALUE! | U3: 表題 | Z3: =表紙!$AJ$65 -> MSBBPA010 | AE3: =表紙!$AQ$65 -> Web見積計算書入力
A5: 画面イメージ
B7: ≫凡例
Q8: ・・・ | S8: ボタン | AH8: 参照情報
C9: 見積計算書NO | Q9: ・・・ | S9: 検索項目(検索画面表示選択)
C10: 品名 | Q10: ・・・ | S10: 入力項目 | AH10: 担当者
C11: 得意先 | Q11: ・・・ | S11: 表示項目(得意先名称、原紙名等)
C12: 操作種別 | I12: ●登録 | M12: ○訂正 | Q12: ・・・ | S12: 選択項目(一つのみ選択可能)
C13: 受注区分 | Q13: ・・・ | S13: 選択項目(一つのみ選択可能)
C14: 作業順 | I14: ☑AAA | M14: ☑BBB | Q14: ・・・ | S14: 選択項目(複数選択可能)
AF15: CP指摘 2022/10/18 本多 見積計算書№からと同様にして、製品マスタからの参照入力も可能でしょうか？ | BM15: MDSOL 野村 2022/10/28 現想定では、過去見積やテンプレート見積からの参照を想定しています。追加必要でしょうか。
C18: 1ページ目：基本情報画面 | BO18: ポップアップ | BS18: ※モーダレス表示
D20: 操作種別 | J20: ●登録 | N20: ○訂正 | R20: ○削除 | V20: ○参照 | Z20: ○コピー
N22: 見積計算書NO
BQ24: 注意メッセージ
D25: 見積計算書NO | J25: 自動採番
D26: 見積拠点 | W26: 受注拠点 | AP26: 担当者 | BS26: 82 | BU26: ・フレキソ印刷有り + 表ライナーの濃い色は裏移り注意
BU27: <<改善方法>> 裏ライナーにフレ輪、ニス引き
D29: 基本情報 | BS29: 83 | BU29: ・両面で、中芯エフカラー黒の使用は、貼合不可の拠点も有ります。要確認
D30: 得意先 | AC30: 案件No | AI30: (件名:オートフィルタ) | AP30: (案件No親/子、サンプル依頼ID) | BS30: 84 | BU30: ・表面加工、PP、マットPPは、グルアが可能か要確認
D31: 受注区分 | J31: 製品 | P31: 製品区分(大) | BS31: 85 | BU31: ・グルアのある表面加工PPは、S648を指示する(東京製造)
BS32: 86 | BU32: ・グルアのある表面加工マットPPは、YMS1を指示する。
D33: 顧客品名 | J33: 48byte7890XXXXXXXXX2XXXXXXXXX3XXXXXXXXX4XXXXXXX8 | AI33: 20byte7890XXXXXXXXX2 | BS33: 87 | BU33: ・Gプリ両面印刷P5仕様は、どちらかをOPニス、どちらかを水性ニスにする。
D34: 受注総数 | O34: 受注年月 | T34: YYYY/MM | AB34: 親子区分 | AO34: FSC認証区分 | BA34: FSC材質区分 | BS34: 88 | BU34: ・ベース原紙ヤシに印刷工程が有ります。製造備考に(改良品)の文言を挿入します。
BS35: 89 | BU35: ・UVクリア版は印刷 +1.5ﾐﾘのﾇﾘﾀｼが必要。⇒樹脂版作成時に版発注者へ連絡してください。
D36: 構成情報 | BS36: 90 | BU36: ・顔料系の箔を使用するとプレスマークが目立つ可能性あり。⇒仕上がりを事前確認してください。
D37: シート 段 | J37: E | O37: 原紙 | X37: 印刷 | AI37: エンボス | AT37: メーカ | BE37: G7で印刷 | BS37: 91 | BU37: ・Gプリ印刷は、クラフト３層でK判以上は印刷不可、シート構成の変更を検討。
F38: 表 | BE38: 柄数 | BS38: 92 | BU38: ・裏にグラビア・フレマル・オフセット・フレキソ等、印刷有の"抜きまでの製品で"梱包のみ"は、荷崩れの可能
F39: 中 | BU39: 性大、包装工程追加を検討
F40: 裏 | BE40: 柄数
D41: 枚葉印刷 | J41: オフセット
D42: 刃渡り（mm) | J42: 巾 | P42: 流れ | V42: 咥え | Z42: 前後 | AF42: 左右 | BQ42: 改善形状メッセージ
D43: シート寸法 | J43: 巾 | P43: 流れ | U43: ※(抜き無し見積もり：刃渡り寸法が無いので、シート寸法を入力する。) | BS43: ※基本情報の形状で、003 041 120 160 をしていした場合
D44: 最終機械工程 | J44: グルア
D46: 製品形状 | X46: 物流区分 | AI46: 容リ支払 | AU46: 識別表示 | BQ46: 難作業メッセージ
BS47: 81 | BU47: ・難作業!! 包装は、"胴巻" 又は"カートン入れ"を推奨 | CO47: 完全包装をしていした場合
D48: AD（形状） | BS48: 82 | BU48: ・難作業!! カートンのテープ貼りは、"I貼り" を推奨 | CO48: H貼りを指定した場合
D49: 戦略商品区分 | J49: □ | K49: FSC | N49: □ | O49: TKP | R49: □ | S49: スマパピ | V49: □ | W49: バリット | Z49: □ | AA49: マイクロ | AD49: □ | AE49: カラフルウィッシュ
D51: 備考
D52: 印刷備考 | J52: FSC管理NO・1614 | AD52: 製造備考 | AJ52: ｹﾞ7ｺｰﾄﾞ（文昌堂）支給 ｼｮｳﾜﾄﾞｳﾍ/4
D53: 伝票備考 | J53: FSC.1614 オ＝ト | AD53: 納入備考 | AJ53: ｼｮｳﾜﾄﾞｳ/7 ﾓﾁｺﾐ ｶｰﾄﾝ/11
D54: 出荷備考１ | J54: XXXXXXXXX1XXXXXXXXX2XXXXXXXXX3XX | AD54: 出荷備考２ | AJ54: 32byte
AX55: 提案ロット1 | BC55: 提案ロット2 | BH55: 単位 | BQ55: 金額にかかわる仕様が変更されています。再計算されます。
D56: 見積り数 | J56: 1,000 | O56: 2,000 | T56: 3,000
D57: (決定予想) | J57: ○ | O57: ○ | T57: ◎ | Y57: ○ | AD57: ○ | AI57: ○ | AN57: ○ | AS57: ○ | AX57: ○ | BC57: ○
D58: パレット数 | J58: 999.9 | O58: 999.9 | T58: 999.9 | Y58: 999.9 | AD58: 999.9 | AI58: 999.9 | AN58: 999.9 | AS58: 999.9
BI62: ※ボタン押下時、チェック後表示
BJ63: 修正必須がある場合は、次画面へ遷移しない
C65: 溶リ判定
C67: A.「特定容器包装(紙製品)」 | AC67: B.「段ボール容器」 | BD67: C.「商品(購買品)」
C68: 紙の重量が重い | AC68: 段ボール原紙の重量が重い | BD68: 受注区分が商品
D72: 特定容器包装チェックリスト：製品 | AD72: プラ素材使用チェック | BE72: 特定容器包装チェックリスト：製品
D73: □ | E73: 「容器」又は「包装」に該当しない | AD73: □ | AE73: 容易に分離可能なプラスチック素材が接着されている | BE73: ☑ | BF73: 段ボール製の製品
E74: 例) 看板/POP/フィルムの芯/ラベル/ステッカー | AE74: 例) 窓貼り、ビタッと台紙等 | BE74: □ | BF74: 紙製容器包装 | BR74: 使用量 | BY74: g
D75: □ | E75: 商品の容器、及び包装に該当しない | AD75: □ | AE75: 容易に分離不可能なプラスチック素材が接着されている | BE75: □ | BF75: プラスチック製容器包装 | BR75: 使用量 | BY75: g
E76: 例) 販促品・景品、DM等の容器包装/クラフトグッズ/ファイルボックス等 | AE76: 例) | AG76: PETラミ、PBTラミ、ウォータータフ、SUT等プラ系加工紙等箱を分解 | BE76: □ | BF76: ガラス製容器 | BR76: 使用量 | BY76: g
D77: □ | E77: 商品が費消され、又は当該商品と分離された場合に不要にならない | AG77: しないと分離できない構造の窓貼り等も含む | BE77: □ | BF77: PETボトル | BR77: 使用量 | BY77: g
E78: 例) カレンダー台紙/保管用ケース等※おもちゃ空き箱は容器包装 | BE78: ※使用量は特定容器包装に該当する場合のみ入力する
D79: □ | E79: 一般消費者で費消しない | AD79: ※店頭販売品の個別包装(容リ法対象)がある場合、使用量を入力 | BE79: ※紙製容器包装に分離可能なプラスチックが取り付けられている場合は
E80: 例) B to B向け外装・中装箱/海外で費消する製品の容器包装 | AD80: 紙使用量 | AL80: g | BF80: 紙/プラ両方の使用量を入力する
AD81: プラ使用量 | AL81: g | BE81: ※段ボールに分離可能なプラスチックが取り付けられている場合は、段
D82: □ | E82: 特定包装に該当する | BF82: ボールとプラにチェックして、プラスチェックに使用量を入力する
E83: 例) シート状かつ商品全体を含む為の最低面積が1/2を超えている
D84: □ | E84: 容易に分離可能なプラスチック素材が接着されている | BE84: ※店頭販売品の個別包装(容リ法対象)がある場合、使用量を入力
E85: 例) 窓貼り、ビタッと台紙等 | BE85: 紙使用量 | BM85: g
BE86: プラ使用量 | BM86: g
D87: ※店頭販売品の個別包装(容リ法対象)がある場合、使用量を入力
D88: 紙使用量 | L88: g
D89: プラ使用量 | L89: g
C95: 2ページ目：工程情報画面
D96: 見積計算書NO | I96: 99999999 | M96: - | N96: 01 | P96: 得意先 | T96: 999999 | W96: XXXXXXXXX1XXXXXXXXX2 | AG96: 案件NO | AK96: 99999999 | AO96: XXXXXXXXX1XXXXX6
D97: 顧客品名 | I97: 48byte7890XXXXXXXXX2XXXXXXXXX3XXXXXXXXX4XXXXXXX8 | AH97: 20byte7890XXXXXXXXX2
D98: 工程CD | G98: 工程名 | M98: 作業 | T98: WG | V98: 製造場所 | AC98: 仕様／工程備考
V99: （拠点・外注） | AC99: 仕様1 | AG99: 仕様2 | AK99: 仕様3 | AO99: 仕様4 | AS99: 仕様5 | AW99: 仕様6 | BA99: 仕様7 | BE99: 版NO | BJ99: ■工程の初期表示パターン
AC100: 工程備考１ | AS100: 工程備考２ | BK100: 印刷CDあり | BR100: 印刷マスタのインキ＝油性なら | CC100: 「輪転グラビア工程」 追加
D101: 0110 | G101: 片面コルゲータ | M101: 01101 | O101: 貼合 | T101: 15 | V101: 東京 | AC101: 両/片 | AG101: 全判巾 | AK101: 全判流れ | BR101: 印刷マスタのインキ＝水性なら | CC101: 「輪転フレマル工程」 追加
AC102: 片面
BK103: ｴﾝﾎﾞｽCDあり | BR103: 「エンボス工程」
D104: 0110 | G104: コルゲータ | M104: 01102 | O104: コルスリ | T104: 15 | V104: 東京 | AC104: 表巾 | AG104: ｽﾘｯﾀｰ1巾 | AK104: ｽﾘｯﾀｰ1流れ | AO104: ｽﾘｯﾀｰ2巾 | AS104: ｽﾘｯﾀｰ2流れ | AW104: ｺﾙｽﾘ | BA104: 付け数
BK105: コルゲータ | BR105: 表原紙がなく、中裏が巻き原紙 | CC105: 「片面コルゲータ」 追加
BR106: 表がコートボールで中・裏が巻き原紙 | CC106: 「片面コルゲータ」 追加
D107: 0200 | G107: ｺｰﾄﾎﾞｰﾙ手配 | M107: 02001 | O107: コートボール手配 | T107: 30 | V107: 森紙販売 | AC107: 表中裏 | AG107: 巾 | AK107: 流れ | AO107: 目なり | AS107: 連量 | AW107: 単価 | BA107: 得スキ | BR107: 表中裏がコートボール | CC107: コルゲータなし
AC108: 表 | BR108: 表中裏とも原紙なし | CC108: コルゲータなし
BR109: 上記以外 | CC109: 「両面コルゲータ」 追加
M110: 02002 | O110: コートボール断裁 | T110: 30 | V110: 森紙販売 | AC110: 表中裏 | AG110: 巾 | AK110: 流れ | AO110: 裁ち数
AC111: 表 | BK111: 枚葉印刷 | BR111: フレキソなら「紙粉除去」「フレキソ工程」 追加
BR112: オフセットなら「コートボール手配」「コートボール断裁」「刷版手配」「紙粉除去」「オフセット工程」「合紙」 追加
D113: 0440 | G113: 刷版手配 | M113: 04401 | O113: 刷版手配 | T113: 30 | V113: SANYO | AC113: 寸法 | AG113: 版作成 | AK113: 面付数 | AO113: 版数 | AS113: 抜きｽﾞﾚ | AW113: 面付番号 | BA113: 混入防止
BK114: 最終機械工程 | BR114: 輪転～オフセットまでは上記のとおり
BR115: 合紙 | BU115: 上記条件で合紙なければ追加
D116: 0450 | G116: オフセット印刷 | M116: 04502 | O116: オフセット印刷 | T116: 30 | V116: 名古屋 | AC116: 色数 | AG116: 色数割増 | AK116: インキ区分 | AO116: 針先 | BR116: トムソン | BU116: 「トムソン工程」 追加
BK117: 最終機械工程 | BR117: 輪転～オフセットまでは上記のとおり
BR118: 合紙 | BU118: 上記条件で合紙なければ追加
M119: 04503 | O119: ニス | T119: 30 | V119: 名古屋 | AC119: 壺ニス | AG119: コーターニス | AK119: スポット | BR119: トムソン | BU119: 「トムソン工程」 追加
BR120: 箔押 | BU120: 「トムソン」「箔押」 追加
BR121: グルア | BU121: 「トムソン」「グルア工程」 追加
D122: 0550 | G122: 合紙 | M122: 05501 | O122: 合紙 | T122: 30 | V122: 名古屋 | AC122: 合紙 | AG122: 合紙糊 | BR122: テーパー | BU122: 「テーパー工程」 追加
BK124: カートン手配 | BR124: 常に固定セット
...

Sheet 旧レイアウトイメージ
A1: =表紙!A54 -> Webシステム | K1: 文書名 | U1: モジュールID | Z1: =表紙!$AJ$63 -> MS | AE1: モジュール名 | AJ1: =表紙!$AX$63 -> 見積管理 | AS1: 文書番号 | AZ1: Version | BF1: Rev.
K2: =表紙!O64 -> アドオン設計書 | U2: ｻﾌﾞﾓｼﾞｭｰﾙID | Z2: =表紙!$AJ$64 -> MSBB | AE2: ｻﾌﾞﾓｼﾞｭｰﾙ名 | AJ2: =表紙!$AX$64 -> Webシステム | AS2: =表紙!$BL$64 -> M7-US-1140 | AZ2: =表紙!$BU$64 -> 7.0.2 | BF2: =表紙!$CB$64 -> 1
K3: =RIGHT(CELL("filename",$A$1),LEN(CELL("filename",$A$1))-FIND("]",CELL("filename",$A$1))) -> #VALUE! | U3: 表題 | Z3: =表紙!$AJ$65 -> MSBBPA010 | AE3: =表紙!$AQ$65 -> Web見積計算書入力
A5: 画面イメージ
B7: ≫凡例 | AG7: 全体画面構成
Q8: ・・・ | S8: ボタン | AG8: ボタン | AP8: … | AQ8: ボタン処理
C9: 見積計算書№ | Q9: ・・・ | S9: 検索項目(検索画面表示選択) | AG9: 見積ヘッダー情報
C10: 品名 | Q10: ・・・ | S10: 入力項目
C11: 得意先 | Q11: ・・・ | S11: 表示項目(得意先名称、原紙名等)
C12: 操作種別 | I12: ●登録 | M12: ○訂正 | Q12: ・・・ | S12: 選択項目(一つのみ選択可能) | AG12: 決定見積情報 | AP12: … | AQ12: 見積区分「決定」時、表示
C13: 受注区分 | Q13: ・・・ | S13: 選択項目(一つのみ選択可能) | AG13: 工程選択ボタン
C14: 作業順 | I14: ☑AAA | M14: ☑BBB | Q14: ・・・ | S14: 選択項目(複数選択可能) | AG14: 工程仕様
C32: １ページ目
D37: 操作種別 | J37: ●登録 | N37: ○訂正 | R37: ○削除 | V37: ○参照
D39: 見積区分 | J39: ●通常 | N39: ○決定
D40: 見積計算書№ | AB40: 参照見積計算書№
D41: 案件№
D42: 得意先
D44: トムソン工程 | J44: ○抜有 | N44: ○抜無
D46: 品名 | J46: 100文字 | AD46: FSC認証製品 | AQ46: 受注年月 | AU46: YYMM
D47: 受注区分 | R47: 製品区分 | AD47: アイテム | AI47: 1:親、2:子
D48: 製品形状 | R48: 物流区分 | AD48: 容リ支払 | AQ48: 識別表示
D50: シート 段 | V50: メーカー | AD50: G7で印刷 | AQ50: 受注総数
D51: 構成 | F51: 表 | AD51: 柄数
F52: 中
F53: 裏 | AD53: 柄数
D54: シート寸法 | N54: × | S54: ※(抜き無し見積もり：刃渡り寸法が無いので、シート寸法を入力する。)
D56: 印刷備考 | AD56: 製造備考
D57: 横持備考 | AD57: 納入備考
D58: 配車備考 | AD58: 伝票備考
AX60: 単位
D61: 見積り数
D62: (決定予想) | J62: ○ | O62: ○ | T62: ○ | Y62: ○ | AD62: ○ | AI62: ○ | AN62: ○ | AS62: ○
D64: 工程パターン | P64: (選択補助機能)
D65: 最低工賃
N71: □ | O71: ----- | T71: □ | U71: ----- | Z71: □ | AA71: ----- | AF71: □ | AG71: -----
N72: □ | O72: ----- | T72: □ | U72: ----- | Z72: □ | AA72: ----- | AF72: □ | AG72: -----
N73: ☑ | O73: フレキソ印刷 | T73: □ | U73: ----- | Z73: □ | AA73: ----- | AF73: □ | AG73: -----
N74: □ | O74: ----- | T74: □ | U74: ----- | Z74: □ | AA74: ----- | AF74: □ | AG74: -----
N75: □ | O75: ----- | T75: □ | U75: ----- | Z75: ☑ | AA75: トムソン | AF75: ☑ | AG75: 穴あけ
N76: □ | O76: ----- | T76: □ | U76: ----- | Z76: □ | AA76: ----- | AF76: □ | AG76: -----
N77: □ | O77: ----- | T77: □ | U77: ----- | Z77: □ | AA77: ----- | AF77: □ | AG77: -----
N78: ☑ | O78: グルア(1) | T78: ☑ | U78: グルア(2) | Z78: □ | AA78: ----- | AF78: □ | AG78: -----
N79: □ | O79: ----- | T79: □ | U79: ----- | Z79: □ | AA79: ----- | AF79: □ | AG79: -----
N80: □ | O80: ----- | T80: □ | U80: ----- | Z80: □ | AA80: ----- | AF80: □ | AG80: -----
D82: ポップアップ画面で選択した作業順の仕様が一覧表示されます。
D84: № | F84: 作業順 | O84: 仕様 | AQ84: 備考
BD85: マスタ項目案
D87: 1 | G87: 0300：フレキソ印刷 | P87: (1) | R87: 表色数 | AC87: 9999% | AR87: 備考1 | BD87: 作業順CD | BI87: 項目制御
P88: (2) | R88: ベタ金銀割増 | AC88: 0:無、1:ニス、2:撥水、3:シックトーン | AR88: 備考2 | BD88: 仕様№ | BI88: (M/W仕様確認)
P89: (3) | R89: ニス | AR89: 版№ | BD89: 仕様
P90: (4) | R90: 抗菌抗ウイルスニス | BD90: 注意書き
P91: (7) | R91: ヌリタシ | AC91: 1:有 | BD91: 使用区分
D94: 2 | G94: 0600：トムソン | P94: (1) | AR94: 備考1
P95: (2) | AR95: 備考2
P96: (3) | AR96: 版№
P97: (4)
P98: (5)
P99: (6)
C107: 見積区分：「●決定」選択時、決定情報を入力します。決定情報入力欄が表示されます。
D112: 操作種別 | J112: ●登録 | N112: ○訂正 | R112: ○削除 | V112: ○参照
D114: 見積区分 | J114: ○通常 | N114: ●決定
D118: 工程パターン | P118: (選択補助機能)
D119: 最低工賃
E122: 決定見積情報 | BQ122: 見積区分 | BW122: ○通常 | CA122: ●決定
F123: 決定見積情報1 | AF123: 決定見積情報2
F124: 決定見積情報3 | AF124: 決定見積情報4 | BQ124: 見積区分=決定時に表示される。
F125: 決定見積情報5 | AF125: 決定見積情報6
C137: A.「特定容器包装(紙製品)」 | W137: B.「段ボール容器」 | AQ137: C.「商品(購買品)」
C138: 紙の重量が重い | W138: 段ボール原紙の重量が重い | AQ138: 受注区分が商品
D142: 特定容器包装チェックリスト：製品 | X142: プラ素材使用チェック | AR142: 特定容器包装チェックリスト：製品
D143: □ | E143: 「容器」又は「包装」に該当しない | X143: □ | Y143: ----- | AR143: ☑ | AS143: 段ボール製の製品
D144: □ | E144: ----- | X144: □ | Y144: ----- | AR144: □ | AS144: ----- | BA144: 使用量 | BH144: g
D145: □ | E145: ----- | AR145: □ | AS145: ----- | BA145: 使用量 | BH145: g
D146: □ | E146: ----- | AR146: □ | AS146: ----- | BA146: 使用量 | BH146: g
AR147: □ | AS147: ----- | BA147: 使用量 | BH147: g
D148: ※店頭販売品の個別包装(容リ法対象)がある場合、 | X148: ※店頭販売品の個別包装(容リ法対象)がある場合、 | AR148: ※店頭販売品の個別包装(容リ法対象)がある場合、
D149: 使用量を入力 | X149: 使用量を入力 | AR149: 使用量を入力
D150: 紙使用量 | L150: g | X150: 紙使用量 | AF150: g | AR150: 紙使用量 | AZ150: g
D151: プラ使用量 | L151: g | X151: プラ使用量 | AF151: g | AR151: プラ使用量 | AZ151: g
D161: 製品形状 | R161: 物流区分 | AD161: 容リ支払 | AI161: 該当 | AQ161: 識別表示 | AU161: 紙マーク相当
C169: OK 登録を続ける：1ページ目の入力チェックされます。 | U169: エラー時は、ここにエラーメッセージが表示されます。
C173: ２ページ目（初期登録時、再計算が必要な場合のみ表示することも可能。）
E178: 注意メッセージ
G180: 82 | I180: ・フレキソ印刷有り + 表ライナーの濃い色は裏移り注意
I181: <<改善方法>> 裏ライナーにフレ輪、ニス引き
G182: 83 | I182: ・両面で、中芯エフカラー黒の使用は、貼合不可の拠点も有ります。要確認
G183: 84 | I183: ・表面加工、PP、マットPPは、グルアが可能か要確認
G184: 85 | I184: ・グルアのある表面加工PPは、S648を指示する(東京製造)
G185: 86 | I185: ・グルアのある表面加工マットPPは、YMS1を指示する。
G186: 87 | I186: ・Gプリ両面印刷P5仕様は、どちらかをOPニス、どちらかを水性ニスにする。
G187: 88 | I187: ・ベース原紙ヤシに印刷工程が有ります。製造備考に(改良品)の文言を挿入します。
G188: 89 | I188: ・UVクリア版は印刷 +1.5ﾐﾘのﾇﾘﾀｼが必要。⇒樹脂版作成時に版発注者へ連絡してください。
G189: 90 | I189: ・顔料系の箔を使用するとプレスマークが目立つ可能性あり。⇒仕上がりを事前確認してください。
G190: 91 | I190: ・Gプリ印刷は、クラフト３層でK判以上は印刷不可、シート構成の変更を検討。
G191: 92 | I191: ・裏にグラビア・フレマル・オフセット・フレキソ等、印刷有の"抜きまでの製品で"梱包のみ"は、荷崩れの可能
I192: 性大、包装工程追加を検討
E195: 改善形状メッセージ
G196: ※基本情報の形状で、003 041 120 160 をしていした場合
E201: 難作業メッセージ
...

Sheet 項目説明
A1: =表紙!A54 -> Webシステム | K1: 文書名 | U1: モジュールID | Z1: =表紙!$AJ$63 -> MS | AE1: モジュール名 | AJ1: =表紙!$AX$63 -> 見積管理 | AS1: 文書番号 | AZ1: Version | BF1: Rev. | BM1: =表紙!BM54 -> 0 | BW1: 文書名 | CG1: モジュールID | CL1: =表紙!$AJ$63 -> MS | CQ1: モジュール名 | CV1: =表紙!$AX$63 -> 見積管理 | DE1: 文書番号 | DL1: Version | DR1: Rev.
K2: =表紙!O64 -> アドオン設計書 | U2: ｻﾌﾞﾓｼﾞｭｰﾙID | Z2: =表紙!$AJ$64 -> MSBB | AE2: ｻﾌﾞﾓｼﾞｭｰﾙ名 | AJ2: =表紙!$AX$64 -> Webシステム | AS2: =表紙!$BL$64 -> M7-US-1140 | AZ2: =表紙!$BU$64 -> 7.0.2 | BF2: =表紙!$CB$64 -> 1 | BW2: =表紙!CA64 -> 0 | CG2: ｻﾌﾞﾓｼﾞｭｰﾙID | CL2: =表紙!$AJ$64 -> MSBB | CQ2: ｻﾌﾞﾓｼﾞｭｰﾙ名 | CV2: =表紙!$AX$64 -> Webシステム | DE2: =表紙!$BL$64 -> M7-US-1140 | DL2: =表紙!$BU$64 -> 7.0.2 | DR2: =表紙!$CB$64 -> 1
K3: =RIGHT(CELL("filename",$A$1),LEN(CELL("filename",$A$1))-FIND("]",CELL("filename",$A$1))) -> #VALUE! | U3: 表題 | Z3: =表紙!$AJ$65 -> MSBBPA010 | AE3: =表紙!$AQ$65 -> Web見積計算書入力 | BW3: =RIGHT(CELL("filename",$A$1),LEN(CELL("filename",$A$1))-FIND("]",CELL("filename",$A$1))) -> #VALUE! | CG3: 表題 | CL3: =表紙!$AJ$65 -> MSBBPA010 | CQ3: =表紙!$AQ$65 -> Web見積計算書入力
A5: 第1画面(基本情報画面) | BM5: 第1画面(基本情報画面)
B6: 操作種別 | N6: 説明 | BE6: Ｗ | BF6: 型 | BG6: 参 | BH6: 必 | BI6: 入 | BJ6: 非 | BK6: 検 | BN6: 操作種別 | BY6: 最大入力文字数 | CK6: DB文字数 | CS6: mcframe項目名 | DB6: mcframeDB文字数
A7: ● | B7: 登録 | M7: 【MSBBPA000】_共通設計書_アドオン(Webシステム共通仕様)にて定義 | BE7: R | BN7: 登録
A8: ● | B8: 訂正 | M8: 【MSBBPA000】_共通設計書_アドオン(Webシステム共通仕様)にて定義 | BE8: R | BN8: 訂正
A9: ● | B9: 削除 | M9: 【MSBBPA000】_共通設計書_アドオン(Webシステム共通仕様)にて定義 | BE9: R | BN9: 削除
A10: ● | B10: 参照 | M10: 【MSBBPA000】_共通設計書_アドオン(Webシステム共通仕様)にて定義 | BE10: R | BN10: 参照
A11: ● | B11: コピー | M11: 【MSBBPA000】_共通設計書_アドオン(Webシステム共通仕様)にて定義 | BE11: R | BN11: コピー
B12: 検索 | N12: 説明 | BE12: Ｗ | BF12: 型 | BG12: 参 | BH12: 必 | BI12: 入 | BJ12: 非 | BK12: 検 | BN12: 検索
A13: ○ | B13: 見積計算書NO | M13: 【MSBBPACOM】_共通設計書_アドオン(共通ロジック)にて定義 | BE13: A | BF13: S | BK13: 検 | BN13: 見積計算書NO | BY13: 10文字 | CK13: 10文字 | DY13: CP指摘 2022/10/18 本多 製品コードから参照入力を可能とするのであれば、製品コードのフィールドが必要と思われます。
B14: 基本情報 | N14: 説明 | BE14: Ｗ | BF14: 型 | BG14: 参 | BH14: 必 | BI14: 入 | BJ14: 非 | BK14: 検 | BN14: 基本情報 | DZ14: MDSOL 野村 2022/10/28 現想定では、過去見積やテンプレート見積からの参照を想定しています。追加必要でしょうか。
B15: 見積計算書NO | M15: 自動採番項目(登録時は、空白)、訂正・削除・参照時に見積計算書NOを表示する | BE15: T | BF15: S | BH15: 必 | BN15: 見積計算書NO | BY15: 10文字 | CK15: 10文字
A16: ● | B16: 見積拠点 | M16: 【MSBBPACOM】_共通設計書_アドオン(共通ロジック)にて定義 | BE16: C | BF16: S | BH16: 必 | BN16: 見積拠点
A17: ● | B17: 受注拠点 | M17: 【MSBBPACOM】_共通設計書_アドオン(共通ロジック)にて定義 | BE17: C | BF17: S | BH17: 必 | BN17: 受注拠点
A18: ● | B18: 担当者 | M18: 【MSBBPACOM】_共通設計書_アドオン(共通ロジック)にて定義 | BE18: C | BF18: S | BH18: 必 | BN18: 担当者
A19: ● | B19: 得意先 | M19: 【MSBBPACOM】_共通設計書_アドオン(共通ロジック)にて定義 | BE19: A | BF19: S | BG19: 参 | BN19: 得意先
A20: ● | B20: 案件No | M20: 入力・表示形式は、[9999999-999] ※案件№（親）＋’－’＋案件№（子）でセットする(親7桁、子3桁) | BE20: A | BF20: S | BG20: 参 | BK20: 検 | BN20: 案件No | BY20: 11文字 | CK20: 15文字 | CS20: 手配NO3 | DB20: 15文字
M21: 【MSBBPACOM】_共通設計書_アドオン(共通ロジック)にて定義
A22: ● | B22: 受注区分 | M22: 【MSBBPACOM】_共通設計書_アドオン(共通ロジック)にて定義 | BE22: C | BF22: S | BG22: 参 | BN22: 受注区分
A23: ● | B23: 製品区分(大) | M23: 【MSBBPACOM】_共通設計書_アドオン(共通ロジック)にて定義 | BE23: C | BF23: S | BG23: 参 | BH23: 必 | BN23: 製品区分(大)
A24: ● | B24: 顧客品名1 | M24: 顧客品名1を入力する | BE24: T | BF24: S | BG24: 参 | BN24: 顧客品名 | BY24: 32文字 | CK24: 100文字 | CS24: 品目マスタ.品目別名３ | DB24: 100文字
A25: ● | B25: 顧客品名2 | M25: 顧客品名2を入力する | BE25: T | BF25: S | BG25: 参 | BY25: 12文字 | CK25: 100文字 | CS25: 品目マスタ.品目別名4 | DB25: 100文字
A26: ● | B26: 受注総数 | M26: 受注総数を入力する | BE26: T | BF26: N | BG26: 参 | BH26: 必 | BN26: 受注総数 | BY26: 10,2 | CK26: 10,2
A27: ● | B27: 受注年月 | M27: 入力・表示形式は、[YYYY/MM] | BE27: T | BF27: D | BH27: 必 | BN27: 受注年月
A28: ● | B28: 親子区分 | M28: 【MSBBPACOM】_共通設計書_アドオン(共通ロジック)にて定義 | BE28: C | BF28: S | BG28: 参 | BN28: 親子区分
A29: ● | B29: FSC認証区分 | M29: 【MSBBPACOM】_共通設計書_アドオン(共通ロジック)にて定義 | BE29: C | BF29: S | BG29: 参 | BN29: FSC認証区分
B30: FSC材質区分 | M30: 【MSBBPACOM】_共通設計書_アドオン(共通ロジック)にて定義 | BE30: C | BF30: S | BG30: 参 | BN30: FSC材質区分
B31: 構成情報 | N31: 説明 | BE31: Ｗ | BF31: 型 | BG31: 参 | BH31: 必 | BI31: 入 | BJ31: 非 | BK31: 検 | BN31: 構成情報
A32: ● | B32: シート段 | M32: 【MSBBPACOM】_共通設計書_アドオン(共通ロジック)にて定義 | BE32: C | BF32: S | BG32: 参 | BK32: 検 | BN32: シート段
A33: ● | B33: 原紙CD(表) | M33: 【MSBBPACOM】_共通設計書_アドオン(共通ロジック)にて定義 | BE33: A | BF33: S | BG33: 参 | BK33: 検 | BN33: 原紙CD(表)
A34: ● | B34: 印刷CD(表) | M34: 【MSBBPACOM】_共通設計書_アドオン(共通ロジック)にて定義 | BE34: A | BF34: S | BG34: 参 | BK34: 検 | BN34: 印刷CD(表)
A35: ● | B35: エンボスCD(表) | M35: 【MSBBPACOM】_共通設計書_アドオン(共通ロジック)にて定義 | BE35: A | BF35: S | BG35: 参 | BK35: 検 | BN35: エンボスCD(表)
A36: ● | B36: メーカCD(表) | M36: 【MSBBPACOM】_共通設計書_アドオン(共通ロジック)にて定義 | BE36: A | BF36: S | BG36: 参 | BK36: 検 | BN36: メーカCD(表)
A37: ● | B37: 柄数(表) | M37: 柄数(表)を入力する | BE37: T | BF37: S | BG37: 参 | BN37: 柄数(表) | BY37: 10,2 | CK37: 10,2
A38: ● | B38: 原紙CD(中) | M38: 【MSBBPACOM】_共通設計書_アドオン(共通ロジック)にて定義 | BE38: A | BF38: S | BG38: 参 | BK38: 検 | BN38: 原紙CD(中)
A39: ● | B39: 印刷CD(中) | M39: 【MSBBPACOM】_共通設計書_アドオン(共通ロジック)にて定義 | BE39: A | BF39: S | BG39: 参 | BK39: 検 | BN39: 印刷CD(中)
A40: ● | B40: エンボスCD(中) | M40: 【MSBBPACOM】_共通設計書_アドオン(共通ロジック)にて定義 | BE40: A | BF40: S | BG40: 参 | BK40: 検 | BN40: エンボスCD(中)
A41: ● | B41: メーカCD(中) | M41: 【MSBBPACOM】_共通設計書_アドオン(共通ロジック)にて定義 | BE41: A | BF41: S | BG41: 参 | BK41: 検 | BN41: メーカCD(中)
A42: ● | B42: 原紙CD(裏) | M42: 【MSBBPACOM】_共通設計書_アドオン(共通ロジック)にて定義 | BE42: A | BF42: S | BG42: 参 | BK42: 検 | BN42: 原紙CD(裏)
A43: ● | B43: 印刷CD(裏) | M43: 【MSBBPACOM】_共通設計書_アドオン(共通ロジック)にて定義 | BE43: A | BF43: S | BG43: 参 | BK43: 検 | BN43: 印刷CD(裏)
A44: ● | B44: エンボスCD(裏) | M44: 【MSBBPACOM】_共通設計書_アドオン(共通ロジック)にて定義 | BE44: A | BF44: S | BG44: 参 | BK44: 検 | BN44: エンボスCD(裏)
A45: ● | B45: メーカCD(裏) | M45: 【MSBBPACOM】_共通設計書_アドオン(共通ロジック)にて定義 | BE45: A | BF45: S | BG45: 参 | BK45: 検 | BN45: メーカCD(裏)
A46: ● | B46: 柄数(裏) | M46: 柄数(裏)を入力する | BE46: T | BF46: S | BG46: 参 | BN46: 柄数(裏) | BY46: 10,2 | CK46: 10,2
A47: ● | B47: 枚葉印刷 | M47: 【MSBBPACOM】_共通設計書_アドオン(共通ロジック)にて定義 | BE47: C | BF47: S | BG47: 参 | BN47: 枚葉印刷
A48: ● | B48: 刃渡り_巾 | M48: 刃渡り_巾を入力する | U48: テキスト変更後の処理として、[シート寸法_巾]が空白時に[シート寸法_巾]を計算する | BE48: T | BF48: N | BG48: 参 | BN48: 刃渡り_巾 | BY48: 10,2 | CK48: 10,2
A49: ● | B49: 刃渡り_流れ | M49: 刃渡り_流れを入力する | U49: テキスト変更後の処理として、[シート寸法_流れ]が空白時に[シート寸法_流れ]を計算する | BE49: T | BF49: N | BG49: 参 | BN49: 刃渡り_流れ | BY49: 10,2 | CK49: 10,2
B50: 咥え_前後 | M50: 咥え_前後を表示する | BE50: T | BF50: N | BN50: 咥え_前後 | BY50: 10,2 | CK50: 10,2
B51: 咥え_左右 | M51: 咥え_左右を表示する | BE51: T | BF51: N | BN51: 咥え_左右 | BY51: 10,2 | CK51: 10,2
A52: ● | B52: シート寸法_巾 | M52: シート寸法_巾 | S52: = | T52: 刃渡り_巾 + 咥え_前後 | BE52: T | BF52: N | BH52: 必 | BN52: シート寸法_巾 | BY52: 10,2 | CK52: 10,2
A53: ● | B53: シート寸法_流れ | M53: シート寸法_流れ | S53: = | T53: 刃渡り_流れ + 咥え_左右 | BE53: T | BF53: N | BH53: 必 | BN53: シート寸法_流れ | BY53: 10,2 | CK53: 10,2
A54: ● | B54: 最終機械工程 | M54: 【MSBBPACOM】_共通設計書_アドオン(共通ロジック)にて定義 | BE54: C | BF54: S | BG54: 参 | BN54: 最終機械工程
A55: ● | B55: 製品形状 | M55: 【MSBBPACOM】_共通設計書_アドオン(共通ロジック)にて定義(計上分類、計上区分) | BE55: C | BF55: S | BG55: 参 | BN55: 製品形状
A56: ● | B56: 物流区分 | M56: 【MSBBPACOM】_共通設計書_アドオン(共通ロジック)にて定義 | BE56: C | BF56: S | BG56: 参 | BN56: 物流区分
B57: 容リ支払 | M57: 【MSBBPACOM】_共通設計書_アドオン(共通ロジック)にて定義 | AE57: 0：非該当 1：該当 | BE57: C | BF57: S | BN57: 容リ支払 | DX57: CP指摘 2022/10/18 本多 容リ支払区分 0：非該当 1：該当 | ET57: MDSOL 野村 2022/10/25 追記しました。
B58: 識別表示 | M58: 【MSBBPACOM】_共通設計書_アドオン(共通ロジック)にて定義 | AE58: 容器リサイクル法に関しての「識別表示」 0: 非表示 1: 段 ﾎﾞｰﾙﾏｰｸ 相当 2 : 紙 ﾏｰｸ 相当 3:ﾌﾟﾗﾏーク | BE58: C | BF58: S | BN58: 識別表示 | DX58: 指摘CP 2022/09/27 玉置 容器リサイクル法に関しての「識別表示」と説明 0: 非表示 1: 段 ﾎﾞｰﾙﾏｰｸ 相当 2 : 紙 ﾏｰｸ 相当 3:ﾌﾟﾗﾏーク | EU58: 定数一覧は、【MSBBPACOM】_共通設計書_アドオン(Web共通ロジック)で管理しております。
A59: ● | B59: AD（形状） | M59: 【MSBBPACOM】_共通設計書_アドオン(共通ロジック)にて定義 | BE59: C | BF59: S | BN59: AD（形状） | EU59: 容リ支払、識別表示の処理に関しては、処理概要(チェック仕様)-溶リ判定ポップアップに定義しております。
A60: ● | B60: 戦略商品区分_01 | M60: FSC | BE60: チ | BF60: F | BN60: 戦略商品区分_01
A61: ● | B61: 戦略商品区分_02 | M61: TKP | BE61: チ | BF61: F | BN61: 戦略商品区分_02
A62: ● | B62: 戦略商品区分_03 | M62: スマパピ | BE62: チ | BF62: F | BN62: 戦略商品区分_03
A63: ● | B63: 戦略商品区分_04 | M63: バリット | BE63: チ | BF63: F | BN63: 戦略商品区分_04
A64: ● | B64: 戦略商品区分_05 | M64: マイクロ | BE64: チ | BF64: F | BN64: 戦略商品区分_05
A65: ● | B65: 戦略商品区分_06 | M65: カラフルウィッシュ | BE65: チ | BF65: F | BN65: 戦略商品区分_06
A66: ● | B66: 戦略商品区分_07 | M66: 空き項目:マスタ値により、不可視設定 | BE66: チ | BF66: F | BN66: 戦略商品区分_07
A67: ● | B67: 戦略商品区分_08 | M67: 空き項目:マスタ値により、不可視設定 | BE67: チ | BF67: F | BN67: 戦略商品区分_08
A68: ● | B68: 戦略商品区分_09 | M68: 空き項目:マスタ値により、不可視設定 | BE68: チ | BF68: F | BN68: 戦略商品区分_09
A69: ● | B69: 戦略商品区分_10 | M69: 空き項目:マスタ値により、不可視設定 | BE69: チ | BF69: F | BN69: 戦略商品区分_10
B70: 備考 | N70: 説明 | BE70: Ｗ | BF70: 型 | BG70: 参 | BH70: 必 | BI70: 入 | BJ70: 非 | BK70: 検 | BN70: 備考
A71: ● | B71: 印刷備考 | M71: 印刷備考を入力する | BE71: T | BF71: S | BG71: 参 | BN71: 印刷備考 | BY71: 32文字 | CK71: 32文字 | CS71: 受注明細.印刷備考 | DB71: 32文字
A72: ● | B72: 製造備考 | M72: 製造備考を入力する | BE72: T | BF72: S | BG72: 参 | BN72: 製造備考 | BY72: 32文字 | CK72: 32文字 | CS72: 受注明細.製造備考 | DB72: 32文字
A73: ● | B73: 伝票備考 | M73: 伝票備考を入力する | BE73: T | BF73: S | BG73: 参 | BN73: 伝票備考 | BY73: 32文字 | CK73: 32文字 | CS73: 受注明細.伝票備考 | DB73: 32文字
A74: ● | B74: 納入備考 | M74: 納入備考を入力する | BE74: T | BF74: S | BG74: 参 | BN74: 納入備考 | BY74: 32文字 | CK74: 32文字 | CS74: 受注明細.納入備考 | DB74: 32文字
A75: ● | B75: 出荷備考１ | M75: 出荷備考１を入力する | BE75: T | BF75: S | BG75: 参 | BN75: 出荷備考１ | BY75: 32文字 | CK75: 32文字 | CS75: 出荷予定.出荷備考１ | DB75: 32文字
A76: ● | B76: 出荷備考２ | M76: 出荷備考２を入力する | BE76: T | BF76: S | BG76: 参 | BN76: 出荷備考２ | BY76: 32文字 | CK76: 32文字 | CS76: 出荷予定.出荷備考２ | DB76: 32文字
B77: 見積り数 | N77: 説明 | BE77: Ｗ | BF77: 型 | BG77: 参 | BH77: 必 | BI77: 入 | BJ77: 非 | BK77: 検 | BN77: 見積り数
A78: ● | B78: 見積り数01 | M78: 見積り数01を入力する | BE78: T | BF78: N | BG78: 参 | BH78: 必 | BN78: 見積り数01 | BY78: 10,2 | CK78: 10,2
A79: ● | B79: 見積り数02 | M79: 見積り数02を入力する | BE79: T | BF79: N | BG79: 参 | BN79: 見積り数02 | BY79: 10,2 | CK79: 10,2
A80: ● | B80: 見積り数03 | M80: 見積り数03を入力する | BE80: T | BF80: N | BG80: 参 | BN80: 見積り数03 | BY80: 10,2 | CK80: 10,2
A81: ● | B81: 見積り数04 | M81: 見積り数04を入力する | BE81: T | BF81: N | BG81: 参 | BN81: 見積り数04 | BY81: 10,2 | CK81: 10,2
A82: ● | B82: 見積り数05 | M82: 見積り数05を入力する | BE82: T | BF82: N | BG82: 参 | BN82: 見積り数05 | BY82: 10,2 | CK82: 10,2
A83: ● | B83: 見積り数06 | M83: 見積り数06を入力する | BE83: T | BF83: N | BG83: 参 | BN83: 見積り数06 | BY83: 10,2 | CK83: 10,2
A84: ● | B84: 見積り数07 | M84: 見積り数07を入力する | BE84: T | BF84: N | BG84: 参 | BN84: 見積り数07 | BY84: 10,2 | CK84: 10,2
A85: ● | B85: 見積り数08 | M85: 見積り数08を入力する | BE85: T | BF85: N | BG85: 参 | BN85: 見積り数08 | BY85: 10,2 | CK85: 10,2
B86: 提案ロット1 | M86: 決定予想のラジオボタンで選択したタイミングで「提案ロット数」を計算する | BE86: T | BF86: N | BN86: 提案ロット1 | BY86: 10,2 | CK86: 10,2
B87: 提案ロット2 | N87: 〃 | BE87: T | BF87: N | BN87: 提案ロット2 | BY87: 10,2 | CK87: 10,2
A88: ● | B88: 単位 | M88: 【MSBBPACOM】_共通設計書_アドオン(共通ロジック)にて定義 | BE88: T | BF88: S | BG88: 参 | BN88: 単位
A89: ● | B89: 決定予想見積り数 | M89: 決定予想チェック時に提案ロット数をセットする | BE89: R | BN89: 決定予想見積り数
B90: パレット数01 | M90: 見積り数からフォーカスを抜けたタイミングで、出荷の容積計算を流用し、見積り数もとにパレット数を算出する | BE90: T | BF90: N | BN90: パレット数01 | BY90: 10,2 | CK90: 10,2
B91: パレット数02 | N91: 〃 | BE91: T | BF91: N | BN91: パレット数02 | BY91: 10,2 | CK91: 10,2
B92: パレット数03 | N92: 〃 | BE92: T | BF92: N | BN92: パレット数03 | BY92: 10,2 | CK92: 10,2
B93: パレット数04 | N93: 〃 | BE93: T | BF93: N | BN93: パレット数04 | BY93: 10,2 | CK93: 10,2
B94: パレット数05 | N94: 〃 | BE94: T | BF94: N | BN94: パレット数05 | BY94: 10,2 | CK94: 10,2
B95: パレット数06 | N95: 〃 | BE95: T | BF95: N | BN95: パレット数06 | BY95: 10,2 | CK95: 10,2
B96: パレット数07 | N96: 〃 | BE96: T | BF96: N | BN96: パレット数07 | BY96: 10,2 | CK96: 10,2
B97: パレット数08 | N97: 〃 | BE97: T | BF97: N | BN97: パレット数08 | BY97: 10,2 | CK97: 10,2
B98: フッター | N98: 説明 | BE98: Ｗ | BF98: 型 | BG98: 参 | BH98: 必 | BI98: 入 | BJ98: 非 | BK98: 検 | BN98: フッター
B99: クリア | M99: 画面を初期化する | BE99: B | BN99: クリア
B100: 次画面 | M100: 第1画面のチェックを行い、エラーが無ければ溶リ判定画面へ遷移する | BE100: B | BN100: 次画面
A102: 溶リ判定画面※溶リ判定(溶リ判定A・B・Cで該当する画面を表示する)を行い、溶リ判定画面を表示
...

Sheet 引数説明
A1: =表紙!A54 -> Webシステム | K1: 文書名 | U1: モジュールID | Z1: =表紙!$AJ$63 -> MS | AE1: モジュール名 | AJ1: =表紙!$AX$63 -> 見積管理 | AS1: 文書番号 | AZ1: Version | BF1: Rev.
K2: =表紙!O64 -> アドオン設計書 | U2: ｻﾌﾞﾓｼﾞｭｰﾙID | Z2: =表紙!$AJ$64 -> MSBB | AE2: ｻﾌﾞﾓｼﾞｭｰﾙ名 | AJ2: =表紙!$AX$64 -> Webシステム | AS2: =表紙!$BL$64 -> M7-US-1140 | AZ2: =表紙!$BU$64 -> 7.0.2 | BF2: =表紙!$CB$64 -> 1
K3: =RIGHT(CELL("filename",$A$1),LEN(CELL("filename",$A$1))-FIND("]",CELL("filename",$A$1))) -> #VALUE! | U3: 表題 | Z3: =表紙!$AJ$65 -> MSBBPA010 | AE3: =表紙!$AQ$65 -> Web見積計算書入力
B5: オペレーションＩＤ/名称：SloRecvIfImp_Upd01/取込
A6: 必 | B6: 項目名 | N6: 説明 | AS6: 未設定時の振る舞い

Sheet 項目説明 (入力値)
A1: =表紙!A54 -> Webシステム | K1: 文書名 | U1: モジュールID | Z1: =表紙!$AJ$63 -> MS | AE1: モジュール名 | AJ1: =表紙!$AX$63 -> 見積管理 | AS1: 文書番号 | AZ1: Version | BF1: Rev.
K2: =表紙!O64 -> アドオン設計書 | U2: ｻﾌﾞﾓｼﾞｭｰﾙID | Z2: =表紙!$AJ$64 -> MSBB | AE2: ｻﾌﾞﾓｼﾞｭｰﾙ名 | AJ2: =表紙!$AX$64 -> Webシステム | AS2: =表紙!$BL$64 -> M7-US-1140 | AZ2: =表紙!$BU$64 -> 7.0.2 | BF2: =表紙!$CB$64 -> 1
K3: =RIGHT(CELL("filename",$A$1),LEN(CELL("filename",$A$1))-FIND("]",CELL("filename",$A$1))) -> #VALUE! | U3: 表題 | Z3: =表紙!$AJ$65 -> MSBBPA010 | AE3: =表紙!$AQ$65 -> Web見積計算書入力
A5: 第1画面(基本情報画面)
B6: 操作種別 | M6: 最大入力文字数 | Y6: DB文字数 | AG6: mcframe項目名 | AP6: mcframeDB文字数 | BE6: リ | BF6: 型 | BG6: 参 | BH6: コ | BI6: 入 | BJ6: 非 | BK6: Ｏ
A7: ● | B7: 登録する | BF7: R
A8: ● | B8: 訂正する | BF8: R
A9: ● | B9: 取り消す | BF9: R
A10: ● | B10: 参照する | BF10: R
A11: ● | B11: コピー | BF11: R
B12: 検索 | BE12: リ | BF12: 型 | BG12: 参 | BH12: コ | BI12: 入 | BJ12: 非 | BK12: Ｏ
A13: ○ | B13: 見積計算書No | M13: 10文字 | Y13: 10文字 | BF13: S
B14: 基本情報 | BE14: リ | BF14: 型 | BG14: 参 | BH14: コ | BI14: 入 | BJ14: 非 | BK14: Ｏ
A15: ● | B15: 見積計算書No | M15: 10文字 | Y15: 10文字 | BF15: S
A16: ● | B16: 拠点 | BF16: S
A17: ● | B17: 担当者 | BF17: S
A18: ● | B18: 得意先 | BE18: C | BF18: S | BG18: 参
A19: ● | B19: 案件No | M19: 7文字 | Y19: 15文字 | AG19: 手配NO3 | AP19: 15文字 | BE19: C | BF19: S | BG19: 参
A20: ● | B20: 顧客品名 | M20: 32文字 | Y20: 100文字 | AG20: 品目マスタ.品目別名３ | AP20: 100文字 | BF20: S | BG20: 参
M21: 12文字 | Y21: 100文字 | AG21: 品目マスタ.品目別名4 | AP21: 100文字
A22: ● | B22: 受注総数 | M22: 10,2 | Y22: 10,2 | BF22: N | BG22: 参
A23: ● | B23: 受注年月 | BF23: D
A24: ● | B24: 親子区分 | BE24: CI | BF24: S | BG24: 参
A25: ● | B25: FSC認証区分 | BE25: C | BF25: S | BG25: 参
A26: ● | B26: FSC材質区分 | BE26: C | BF26: S | BG26: 参
B27: 構成情報 | BE27: リ | BF27: 型 | BG27: 参 | BH27: コ | BI27: 入 | BJ27: 非 | BK27: Ｏ
A28: ● | B28: 受注区分 | BE28: CI | BF28: S | BG28: 参
A29: ● | B29: シート段 | BE29: CI | BF29: S | BG29: 参
A30: ● | B30: 原紙コード(表) | BE30: C | BF30: S | BG30: 参
A31: ● | B31: 印刷コード(表) | BE31: C | BF31: S | BG31: 参
A32: ● | B32: エンボスコード(表) | BE32: C | BF32: S | BG32: 参
A33: ● | B33: 柄数(表) | M33: 10,2 | Y33: 10,2 | BE33: C | BF33: S | BG33: 参
A34: ● | B34: 原紙コード(中) | BE34: C | BF34: S | BG34: 参
A35: ● | B35: 印刷コード(中) | BE35: C | BF35: S | BG35: 参
A36: ● | B36: エンボスコード(中) | BE36: C | BF36: S | BG36: 参
A37: ● | B37: 原紙コード(裏) | BE37: C | BF37: S | BG37: 参
A38: ● | B38: 印刷コード(裏) | BE38: C | BF38: S | BG38: 参
A39: ● | B39: エンボスコード(裏) | BE39: C | BF39: S | BG39: 参
A40: ● | B40: 柄数(裏) | M40: 10,2 | Y40: 10,2 | BE40: C | BF40: S | BG40: 参
A41: ● | B41: 枚葉印刷 | BE41: C | BF41: S | BG41: 参
A42: ● | B42: 刃渡り_巾 | M42: 10,2 | Y42: 10,2 | BF42: N | BG42: 参
A43: ● | B43: 刃渡り_流れ | M43: 10,2 | Y43: 10,2 | BF43: N | BG43: 参
A44: ● | B44: 咥え_前後 | M44: 10,2 | Y44: 10,2 | BF44: N | BG44: 参
A45: ● | B45: 咥え_左右 | M45: 10,2 | Y45: 10,2 | BF45: N | BG45: 参
A46: ● | B46: シート寸法_巾 | M46: 10,2 | Y46: 10,2 | BF46: N | BG46: 参
A47: ● | B47: シート寸法_流れ | M47: 10,2 | Y47: 10,2 | BF47: N | BG47: 参
A48: ● | B48: 最終機械工程 | BE48: C | BF48: S | BG48: 参
A49: ● | B49: 製品形状 | BE49: C | BF49: S | BG49: 参
A50: ● | B50: 物流区分 | BE50: C | BF50: S | BG50: 参
B51: 容リ支払 | BF51: S
B52: 識別表示 | BF52: S
B53: 備考 | BE53: リ | BF53: 型 | BG53: 参 | BH53: コ | BI53: 入 | BJ53: 非 | BK53: Ｏ
A54: ● | B54: 印刷備考 | M54: 32文字 | Y54: 32文字 | AG54: 受注明細.印刷備考 | AP54: 32文字 | BF54: S | BG54: 参
A55: ● | B55: 製造備考 | M55: 32文字 | Y55: 32文字 | AG55: 受注明細.製造備考 | AP55: 32文字 | BF55: S | BG55: 参
A56: ● | B56: 伝票備考 | M56: 32文字 | Y56: 32文字 | AG56: 受注明細.伝票備考 | AP56: 32文字 | BF56: S | BG56: 参
A57: ● | B57: 納入備考 | M57: 32文字 | Y57: 32文字 | AG57: 受注明細.納入備考 | AP57: 32文字 | BF57: S | BG57: 参
A58: ● | B58: 出荷備考１ | M58: 32文字 | Y58: 32文字 | AG58: 出荷予定.出荷備考１ | AP58: 32文字 | BF58: S | BG58: 参
A59: ● | B59: 出荷備考２ | M59: 32文字 | Y59: 32文字 | AG59: 出荷予定.出荷備考２ | AP59: 32文字 | BF59: S | BG59: 参
B60: 見積り数 | BE60: リ | BF60: 型 | BG60: 参 | BH60: コ | BI60: 入 | BJ60: 非 | BK60: Ｏ
A61: ● | B61: 見積り数01 | M61: 10,2 | Y61: 10,2 | BF61: N
A62: ● | B62: 見積り数02 | M62: 10,2 | Y62: 10,2 | BF62: N
A63: ● | B63: 見積り数03 | M63: 10,2 | Y63: 10,2 | BF63: N
A64: ● | B64: 見積り数04 | M64: 10,2 | Y64: 10,2 | BF64: N
A65: ● | B65: 見積り数05 | M65: 10,2 | Y65: 10,2 | BF65: N
A66: ● | B66: 見積り数06 | M66: 10,2 | Y66: 10,2 | BF66: N
A67: ● | B67: 見積り数07 | M67: 10,2 | Y67: 10,2 | BF67: N
A68: ● | B68: 見積り数08 | M68: 10,2 | Y68: 10,2 | BF68: N
B69: パレット数01 | M69: 10,2 | Y69: 10,2 | BF69: N
B70: パレット数02 | M70: 10,2 | Y70: 10,2 | BF70: N
B71: パレット数03 | M71: 10,2 | Y71: 10,2 | BF71: N
B72: パレット数04 | M72: 10,2 | Y72: 10,2 | BF72: N
B73: パレット数05 | M73: 10,2 | Y73: 10,2 | BF73: N
B74: パレット数06 | M74: 10,2 | Y74: 10,2 | BF74: N
B75: パレット数07 | M75: 10,2 | Y75: 10,2 | BF75: N
B76: パレット数08 | M76: 10,2 | Y76: 10,2 | BF76: N
B77: 提案ロット1 | M77: 10,2 | Y77: 10,2 | BF77: N
B78: 提案ロット2 | M78: 10,2 | Y78: 10,2 | BF78: N
A79: ● | B79: 決定予想見積り数 | BF79: R
B80: フッター | BE80: リ | BF80: 型 | BG80: 参 | BH80: コ | BI80: 入 | BJ80: 非 | BK80: Ｏ
B81: クリア | BF81: B
B82: 溶リ判定 | BF82: B
B83: 次画面 | BF83: B
A85: 第2画面(工程情報画面)
B86: ヘッダー | BE86: リ | BF86: 型 | BG86: 参 | BH86: コ | BI86: 入 | BJ86: 非 | BK86: Ｏ
B87: 見積計算書No | M87: 10文字 | BF87: S
B88: 得意先 | BF88: S
B89: 案件No | M89: 7文字 | Y89: 7文字 | AG89: 手配NO3 | AP89: 15文字 | BF89: S
B90: 顧客品名 | BF90: S
B91: 工程情報 | BE91: リ | BF91: 型 | BG91: 参 | BH91: コ | BI91: 入 | BJ91: 非 | BK91: Ｏ
A92: ● | B92: 工程 | BE92: C | BF92: S | BG92: 参
B93: 工程名 | BF93: S
A94: ● | B94: 作業 | BE94: C | BF94: S | BG94: 参
B95: 作業名 | BF95: S
A96: ● | B96: WG | BE96: C | BF96: S | BG96: 参
A97: ● | B97: 製造場所 | BE97: C | BF97: S | BG97: 参
B98: 仕様１名称 | BF98: N
A99: ● | B99: 仕様１値 | BF99: N | BG99: 参
B100: 仕様２名称 | BF100: N
A101: ● | B101: 仕様２値 | BF101: N | BG101: 参
B102: 仕様３名称 | BF102: N
...

Sheet 処理概要
A1: =表紙!A54 -> Webシステム | K1: 文書名 | U1: モジュールID | Z1: =表紙!$AJ$63 -> MS | AE1: モジュール名 | AJ1: =表紙!$AX$63 -> 見積管理 | AS1: 文書番号 | AZ1: Version | BF1: Rev.
K2: =表紙!O64 -> アドオン設計書 | U2: ｻﾌﾞﾓｼﾞｭｰﾙID | Z2: =表紙!$AJ$64 -> MSBB | AE2: ｻﾌﾞﾓｼﾞｭｰﾙ名 | AJ2: =表紙!$AX$64 -> Webシステム | AS2: =表紙!$BL$64 -> M7-US-1140 | AZ2: =表紙!$BU$64 -> 7.0.2 | BF2: =表紙!$CB$64 -> 1
K3: =RIGHT(CELL("filename",$A$1),LEN(CELL("filename",$A$1))-FIND("]",CELL("filename",$A$1))) -> #VALUE! | U3: 表題 | Z3: =表紙!$AJ$65 -> MSBBPA010 | AE3: =表紙!$AQ$65 -> Web見積計算書入力
A5: 第1画面(基本情報画面)
A6: No | B6: 入力 | J6: 処理 | BD6: 出力
A7: 1 | B7: 初期表示
J8: 1.処理概要
K9: 初期表示
L10: 見積拠点 | P10: ： | Q10: ログインに紐づく拠点CDを表示する | AD10: ※ | AE10: 見積拠点：管理者・岐阜事業所が変更可能(見積計算の拠点となる) | BM10: CP指摘 2022/09/28 木﨑 シート[レイアウト]では「拠点に紐づく担当者を表示」と記載があります。こちらが正でしょうか？
L11: 受注拠点 | P11: ： | Q11: ログインに紐づく拠点CDを表示する | AD11: ※ | AE11: 受注拠点：管理者のみ変更可能 | BN11: MDSOL 野村 2022/10/28 左記は初期表示の仕様となります。
L12: 担当者 | P12: ： | Q12: ログイン担当者CDを表示する | BO12: 拠点に紐づく担当者を表示は、選択値のことになります。
BO13: 受注拠点が変更になった場合に、担当者の選択値が「拠点に紐づく担当者」になることを指します。
A14: 2 | B14: 画面操作
J15: 1.処理概要
K16: 操作種別
L17: 登録 | U17: ・・・ | X17: 検索.見積計算書NO 入力不可
X18: 構成情報：枚葉印刷～最終機械工程の表示
L19: 訂正、削除、参照 | U19: ・・・ | X19: 検索.見積計算書NO 入力可
L20: コピー | X20: 構成情報：枚葉印刷～最終機械工程の非表示
K22: 見積計算書NO
L23: 訂正、削除、参照 | U23: ・・・ | X23: 更新入出力仕様を参考に各項目に値をセットする | BD23: 検索入出力仕様.検索No1
L24: コピー | X24: 検索入出力仕様(見積計算書NO)の仕様に沿い、各項目に値をセットする
K26: 案件 | U26: ・・・ | X26: 検索入出力仕様(案件)の仕様に沿い、各項目に値をセットする | BD26: 検索入出力仕様.検索No2
K28: ボタン処理
L29: クリアボタン押下 | U29: ・・・ | X29: 画面を初期化する
L30: 溶リ判定押下 | U30: ・・・ | X30: 溶リ判定画面を表示する
A32: 3 | B32: 次画面処理
J33: 1.処理概要
K34: チェック処理 | BD34: 処理概要(チェック仕様)
L35: 処理概要(チェック仕様)のチェック処理を行う | BD35: 第1画面(基本情報画面)
L36: ※チェック処理でエラーメッセージがある場合は、後続処理をキャンセルし、エラーポップアップ表示する
K37: 容リ法対象ポップアップ表示
L38: 得意先マスタ：容リ法対象=1:該当時、容リ法対象ポップアップ表示する、容リ法対象≠1時は、第2画面へ遷移する
L40: 容器包装リサイクル法判定を行い、ポップアップA、B、Cに遷移する | BM40: (設計書添付資料：【MSBBPA010_添付資料】見積計算仕様__20220719_V01.xlsx)
M41: 遷移画面 | AD41: 判定条件
M42: A.特定容器包装(紙製品) | AA42: ・・・ | AD42: 紙の重量が重い
M43: B.ダンボール容器 | AA43: ・・・ | AD43: 段ボール原紙の重量が重い
M44: C.商品(購買品) | AA44: ・・・ | AD44: 受注区分が商品
M46: 概要
M47: ①原紙は、段ボール原紙、ダンボール原紙以外(以後 : 紙)で区分されている。
M48: ②原紙 3層の重量を段ボール原紙と紙に分けて集計して、大きい方に分類される。そのチェック画面を表示する。
N49: ※中芯は、段性率を乗じる
N50: A.特定容器包装(紙製品)
N51: B.ダンボール容器
N52: C.商品(購買品)
M53: ③チェックリストの内容から、 「容リ支払い対象」、 「表示マーク」 を判断する。 ・・・・判定基準フローを参照
N54: 容リ支払い | Q54: 該当 非該当
N55: 識別表示 | Q55: 段ボールマーク相当
Q56: 紙マーク相当
Q57: プラマーク相当
Q58: 段ボール/プラマーク相当
Q59: 紙マーク/プラマーク相当
Q60: PETマーク相当
L61: ≫紙と段ボールの判定方法
N62: 表／中／裏 原紙コード より 原紙マスタの各坪量 を 段原紙区分 の 有無 で 集計
N63: 段原紙区分：１ ＝ 段ボール原紙、 これ以外紙扱い原紙
N64: 中芯は汎用マスタ 段成率（容リ法）より 段成率を乗じる | AN64: ※汎用マスタ(M067:段成率(容リ法))
N66: 坪量比較 | Q66: 段原紙区分あり | W66: ＞ | X66: 段原紙区分なし | AE66: … | AG66: 段ﾎﾞｰﾙ扱い
Q67: 段原紙区分あり | W67: ＜ | X67: 段原紙区分なし | AE67: … | AG67: 紙扱い
Q68: 段原紙区分あり | W68: ＝ | X68: 段原紙区分なし | AE68: … | AG68: 段ﾎﾞｰﾙ扱い
X69: コートボール | AE69: … | AG69: 紙扱い
L71: ※製品重量の算出方法
M72: トムソンあり | Q72: … | R72: 刃渡り寸法㎡ × （坪量 ： 表＋中＋裏） × ０．８ （20％をヤレ率として80％を製品重量とする為）
M73: トムソンなし | Q73: … | R73: スリッタ／シート寸法㎡ × （坪量 ： 表＋中＋裏） × ０．８ （20％をヤレ率として80％を製品重量とする為）
R74: どちらも中芯は汎用マスタ 段成率（容リ法）より 段成率を乗じる | AN74: ※汎用マスタ(M067:段成率(容リ法))
L76: ※購買品重量の算出方法
M77: 特定容器包装チェックリスト：商品 ポップアップウィンドウ で 各項目別に手入力
L79: ※店頭販売品の個別包装（容リ法対象）使用量
M80: 店頭販売品で容リ法対象となる個別包装が別途ある場合、製品または商品とは別に使用量を入力する
M81: 例）自社内にて製品または商品を個別に紙またはプラ包装してから出荷する製品など
M82: 注）店頭販売時の観点なので、消費者が廃棄するであろう素材についてであり、輸送のための紙・ﾗｯﾌﾟ巻き包装は含まない
A85: 第2画面(工程情報画面)
A86: No | B86: 入力 | J86: 処理 | BD86: 出力
A87: 1 | B87: 初期表示
J88: 1.処理概要
K89: 初期表示
L90: 見積計算書NO | Q90: ： | R90: 操作種別：新規時=空白、それ以外=第一画面の見積計算書NOを表示する
L91: 得意先 | Q91: ： | R91: 第一画面の得意先名を表示する
L92: 案件No | Q92: ： | R92: 第一画面の案件名を表示する
L93: 顧客品名 | Q93: ： | R93: 第一画面の顧客品名を表示する
K95: 初期工程登録セット(操作種別：新規登録時) | BN95: ※補足：工程選択ポップアップの画面の動き
L96: 工程初期表示パターンに伴い、工程をセットする
A98: 2 | B98: 画面操作
J99: 1.処理概要
K100: 項目処理
L101: ワーキンググループCD | U101: ・・・ | X101: ワーキンググループCD セット時、
X102: 製造場所のリストをクリアし、
X103: 製造場所のリストに対してワーキンググループCDを条件とする
K104: ボタン処理
L105: 前画面ボタン押下 | U105: ・・・ | X105: 前画面(第1画面(基本情報画面))に戻る
L107: 工程選択ボタン押下 | U107: ・・・ | X107: 工程選択ポップアップを表示する
K109: 工程選択ポップアップ
L110: ポップアップ起動時処理 | U110: ・・・ | X110: 工程・作業一覧を表示し、呼出元の工程・作業にチェックする | BN110: ↓ | BO110: 工程選択ポップアップの呼び出し | CS110: 刷版手配を追加チェック
L111: 工程反映ボタン押下 | U111: ・・・ | X111: 工程情報画面にチェック結果を反映させる
CQ115: →
CS120: ↓ | CU120: 第2画面(工程情報画面)へ反映
A125: 3 | B125: 次画面処理
J126: 1.処理概要
K127: チェック処理
L128: 処理概要(チェック仕様)のチェック処理を行う | BD128: 処理概要(チェック仕様)
...

Sheet 処理詳細
A1: =表紙!A54 -> Webシステム | K1: 文書名 | U1: モジュールID | Z1: =表紙!$AJ$63 -> MS | AE1: モジュール名 | AJ1: =表紙!$AX$63 -> 見積管理 | AS1: 文書番号 | AZ1: Version | BF1: Rev.
K2: =表紙!O64 -> アドオン設計書 | U2: ｻﾌﾞﾓｼﾞｭｰﾙID | Z2: =表紙!$AJ$64 -> MSBB | AE2: ｻﾌﾞﾓｼﾞｭｰﾙ名 | AJ2: =表紙!$AX$64 -> Webシステム | AS2: =表紙!$BL$64 -> M7-US-1140 | AZ2: =表紙!$BU$64 -> 7.0.2 | BF2: =表紙!$CB$64 -> 1
K3: =RIGHT(CELL("filename",$A$1),LEN(CELL("filename",$A$1))-FIND("]",CELL("filename",$A$1))) -> #VALUE! | U3: 表題 | Z3: =表紙!$AJ$65 -> MSBBPA010 | AE3: =表紙!$AQ$65 -> Web見積計算書入力
A5: No | B5: 入力 | J5: 処理 | BD5: 出力
A6: 1 | B6: 初期表示
A12: 2 | B12: 画面操作
A18: 3 | B18: 検索【F1】

Sheet 処理概要(チェック仕様)
A1: =表紙!A54 -> Webシステム | K1: 文書名 | U1: モジュールID | Z1: =表紙!$AJ$63 -> MS | AE1: モジュール名 | AJ1: =表紙!$AX$63 -> 見積管理 | AS1: 文書番号 | AZ1: Version | BF1: Rev.
K2: =表紙!O64 -> アドオン設計書 | U2: ｻﾌﾞﾓｼﾞｭｰﾙID | Z2: =表紙!$AJ$64 -> MSBB | AE2: ｻﾌﾞﾓｼﾞｭｰﾙ名 | AJ2: =表紙!$AX$64 -> Webシステム | AS2: =表紙!$BL$64 -> M7-US-1140 | AZ2: =表紙!$BU$64 -> 7.0.2 | BF2: =表紙!$CB$64 -> 1
K3: =RIGHT(CELL("filename",$A$1),LEN(CELL("filename",$A$1))-FIND("]",CELL("filename",$A$1))) -> #VALUE! | U3: 表題 | Z3: =表紙!$AJ$65 -> MSBBPA010 | AE3: =表紙!$AQ$65 -> Web見積計算書入力
A5: 第1画面(基本情報画面)
A6: No | B6: 入力 | J6: 1ページ目：基本情報画面 | BD6: 出力
A7: 1 | B7: ヘッダー見積計算書 | J7: 見積計算書NO選択/検索
J8: 1.処理概要
K9: チェック処理
L10: 見積計算書NO
N11: 必須チェック | U11: 「見積計算書NOが未入力です。」 | BD11: メッセージID.101
N12: ＤＢチェック | U12: 「見積計算書NOが未登録です。」 | BD12: メッセージID.102
A14: 2 | B14: 次へチェック | J14: 次へチェック処理
J15: 1.処理概要
K16: チェック処理
L17: 見積拠点CD
N18: 必須チェック | U18: 「見積拠点CDが未入力です。」 | BD18: メッセージID.111
L19: 受注拠点CD
N20: 必須チェック | U20: 「受注拠点CDが未入力です。」 | BD20: メッセージID.112
L21: 担当者CD
N22: 必須チェック | U22: 「担当者CDが未入力です。」 | BD22: メッセージID.113
L23: 得意先
N24: 必須チェック | U24: 「得意先が未入力です。」 | BD24: メッセージID.114
L25: 案件NO
N26: 必須チェック | U26: 「案件NOが未入力です。」 | BD26: メッセージID.115
L27: 顧客品名
N28: 必須チェック | U28: 「顧客品名が未入力です。」 | BD28: メッセージID.116
L29: 受注総数
N30: 必須チェック | U30: 「受注総数が未入力です。」 | BD30: メッセージID.117
L31: 受注年月
N32: 必須チェック | U32: 「受注年月が未入力です。」 | BD32: メッセージID.118
L33: 親子区分
N34: 必須チェック | U34: 「親子区分が未入力です。」 | BD34: メッセージID.119
L35: FSC認証区分
N36: FSC認証製品>=1以上、 | BN36: CP指摘 2022/10/18 本多 製品区分 入力必須チェック 「製品区分が未入力です」 表示されますか？
N37: 原紙CDから原紙マスタを参照し、FSC区分が「0:非認証」の場合、「原紙が非認証です。」 | BD37: メッセージID.120
L38: 受注区分
N39: 必須チェック | U39: 「受注区分が未入力です。」 | BD39: メッセージID.121
L40: 製品区分_大
N41: 必須チェック | U41: 「製品区分が未入力です。」 | BD41: メッセージID.129 | BN41: MDSOL 野村 2022/10/28 製品区分を必須に変更し、チェック追加しました。
L42: シート 段
N43: 必須チェック | U43: 「シート 段が未入力です。」 | BD43: メッセージID.122
L44: シート寸法巾・流れ
N45: 必須チェック | U45: 「シート寸法(巾)が未入力です。」 | BD45: メッセージID.123
N46: 必須チェック | U46: 「シート寸法(流れ)が未入力です。」 | BD46: メッセージID.124
L47: G7で印刷(柄数)
N48: 柄数に入力があり、受注総数に入力が無い場合、下記メッセージを表示
U49: 「柄数入力時、受注総数の入力が必要になります。」 | BD49: メッセージID.125
L50: 製品形状
N51: 製品形状マスタ取得
N52: 効率化形状が存在する場合、メッセージ表示 （メッセージ： 効率改善形状に該当！） | BD52: メッセージID.126
L53: 見積り数01
N54: 必須チェック | U54: 「見積り数が未入力です。」 | BD54: メッセージID.127
L55: 決定予想
N56: 整合性チェック | U56: 見積り数の入力が無い項目に決定予想がチェックされている場合、
U57: 「決定予想の選択が不正です。」 | BD57: メッセージID.128
A59: 溶リ判定ポップアップ
A60: No | B60: 入力 | J60: A.「特定容器包装(紙製品)」 | BD60: 出力
A61: 1 | B61: 確定 | J61: 確定処理
J62: 1.処理概要
K63: チェック処理
L64: 溶リ判定区分A_05チェック時
M65: 下記の何れかにチェックが付いている場合、エラー | BD65: メッセージID.P11
M66: 溶リ判定区分A_01
M67: 溶リ判定区分A_02
M68: 溶リ判定区分A_03
M69: 溶リ判定区分A_04
L70: 溶リ判定区分A_06チェック時
M71: 下記の何れかにチェックが付いている場合、エラー | BD71: メッセージID.P12
M72: 溶リ判定区分A_01
M73: 溶リ判定区分A_02
M74: 溶リ判定区分A_03
M75: 溶リ判定区分A_04
L77: 判定条件 | AF77: 容リ支払 | AL77: 識別表示 | BD77: 容リ支払
L78: 溶リ判定区分A_01～04 どれかに１つ以上チェック有 | AF78: 非該当 | AL78: 非表示 | BD78: 識別表示
L79: 溶リ判定区分A_01～04 すべてチェック無 | AF79: 該当 | AL79: 紙マーク相当
L80: 溶リ判定区分A_01～04 すべてチェック無＋Fチェック有 | AF80: 該当 | AL80: 紙ﾏｰｸ/ﾌﾟﾗﾏｰｸ相当
L81: 溶リ判定区分A_05 のみチェック有り | AF81: 非該当 | AL81: 紙マーク相当
L82: 溶リ判定区分A_05&05 チェック有り | AF82: 非該当 | AL82: 紙ﾏｰｸ/ﾌﾟﾗﾏｰｸ相当
K84: 確定処理
L85: ポップアップの登録内容を記憶し、次画面へ遷移する
A87: No | B87: 入力 | J87: B.「段ボール容器」 | BD87: 出力
A88: 2 | B88: 確定 | J88: 確定処理
J89: 1.処理概要
K90: チェック処理
L91: 無し
L93: 判定条件 | AF93: 容リ支払 | AL93: 識別表示 | BD93: 容リ支払
L94: 溶リ判定区分B_01 のみチェック有り | AF94: 該当 | AL94: 段ﾎﾞｰﾙ/ﾌﾟﾗﾏｰｸ相当 | BD94: 識別表示
L95: 溶リ判定区分B_02 のみチェック有り | AF95: 非該当 | AL95: 非表示
L96: 溶リ判定区分B_01 & 溶リ判定区分B_02 チェック有り | AF96: 該当 | AL96: ﾌﾟﾗﾏｰｸ相当
L97: どちらにもチェック無 | AF97: 非該当 | AL97: 段ﾎﾞｰﾙﾏｰｸ相当
K99: 確定処理
L100: ポップアップの登録内容を記憶し、次画面へ遷移する
A102: No | B102: 入力 | J102: C.「商品(購買品)」 | BD102: 出力
A103: 3 | B103: 確定 | J103: 確定処理
J104: 1.処理概要
K105: チェック処理
L106: 溶リ判定区分C_01 & 溶リ判定区分C_02チェック時、エラー | BD106: メッセージID.P35 | BN106: CP指摘 2022/10/18 本多 溶リ判定区分C_01 & 溶リ判定区分C_02チェック時、エラー
L107: 溶リ判定区分C_01 & 溶リ判定区分C_03チェック時、エラー | BD107: メッセージID.P31 | BN107: MDSOL 野村 2022/10/28 上記チェック追加しました。
L108: 溶リ判定区分C_04チェック時
M109: 下記の何れかにチェックが付いている場合、エラー | BD109: メッセージID.P32
...

Sheet 処理・サービス関連図
A1: =表紙!A54 -> Webシステム | K1: 文書名 | U1: モジュールID | Z1: =表紙!$AJ$63 -> MS | AE1: モジュール名 | AJ1: =表紙!$AX$63 -> 見積管理 | AS1: 文書番号 | AZ1: Version | BF1: Rev.
K2: =表紙!O64 -> アドオン設計書 | U2: ｻﾌﾞﾓｼﾞｭｰﾙID | Z2: =表紙!$AJ$64 -> MSBB | AE2: ｻﾌﾞﾓｼﾞｭｰﾙ名 | AJ2: =表紙!$AX$64 -> Webシステム | AS2: =表紙!$BL$64 -> M7-US-1140 | AZ2: =表紙!$BU$64 -> 7.0.2 | BF2: =表紙!$CB$64 -> 1
K3: =RIGHT(CELL("filename",$A$1),LEN(CELL("filename",$A$1))-FIND("]",CELL("filename",$A$1))) -> #VALUE! | U3: 表題 | Z3: =表紙!$AJ$65 -> MSBBPA010 | AE3: =表紙!$AQ$65 -> Web見積計算書入力
C7: 検索処理
C19: 更新処理

Sheet 検索入出力仕様
A1: =表紙!A54 -> Webシステム | K1: 文書名 | U1: モジュールID | Z1: =表紙!$AJ$63 -> MS | AE1: モジュール名 | AJ1: =表紙!$AX$63 -> 見積管理 | AS1: 文書番号 | AZ1: Version | BF1: Rev.
K2: =表紙!O64 -> アドオン設計書 | U2: ｻﾌﾞﾓｼﾞｭｰﾙID | Z2: =表紙!$AJ$64 -> MSBB | AE2: ｻﾌﾞﾓｼﾞｭｰﾙ名 | AJ2: =表紙!$AX$64 -> Webシステム | AS2: =表紙!$BL$64 -> M7-US-1140 | AZ2: =表紙!$BU$64 -> 7.0.2 | BF2: =表紙!$CB$64 -> 1
K3: =RIGHT(CELL("filename",$A$1),LEN(CELL("filename",$A$1))-FIND("]",CELL("filename",$A$1))) -> #VALUE! | U3: 表題 | Z3: =表紙!$AJ$65 -> MSBBPA010 | AE3: =表紙!$AQ$65 -> Web見積計算書入力
A5: No | G5: 1 | S5: ボタン | Z5: 見積計算書NO | AH5: 備考 | AK5: 見積計算書NOからのコピー登録
A6: 処理分類 | E6: 検索 | S6: ソート順
A7: No | C7: 転送先 | V7: 転送元 | AQ7: 説明
C8: 種 | D8: オブジェクト | K8: 項目名 | V8: 種 | W8: オブジェクト | AF8: 項目名
A9: 1 | C9: 画 | D9: 第1画面(基本情報画面) | K9: 得意先 | V9: T | W9: 見積計算書 | AF9: 得意先
A10: 2 | C10: 画 | D10: 第1画面(基本情報画面) | K10: 案件No | V10: T | W10: 見積計算書 | AF10: 案件No
A11: 3 | C11: 画 | D11: 第1画面(基本情報画面) | K11: 案件名 | V11: T | W11: ヒアリングシート | AF11: 案件名
A12: 4 | C12: 画 | D12: 第1画面(基本情報画面) | K12: 受注区分 | V12: T | W12: 見積計算書 | AF12: 受注区分
A13: 5 | C13: 画 | D13: 第1画面(基本情報画面) | K13: 製品区分(大) | V13: T | W13: 見積計算書 | AF13: 製品区分_大
A14: 6 | C14: 画 | D14: 第1画面(基本情報画面) | K14: 顧客品名 | V14: T | W14: 見積計算書 | AF14: 顧客品名
A15: 7 | C15: 画 | D15: 第1画面(基本情報画面) | K15: 受注総数 | V15: T | W15: 見積計算書 | AF15: 受注総数
A16: 8 | C16: 画 | D16: 第1画面(基本情報画面) | K16: 受注年月 | V16: T | W16: 見積計算書 | AF16: 受注年月
A17: 9 | C17: 画 | D17: 第1画面(基本情報画面) | K17: 親子区分 | V17: T | W17: 見積計算書 | AF17: 親子区分
A18: 10 | C18: 画 | D18: 第1画面(基本情報画面) | K18: FSC認証区分 | V18: T | W18: 見積計算書 | AF18: FSC認証区分
A19: 11 | C19: 画 | D19: 第1画面(基本情報画面) | K19: FSC材質区分 | V19: T | W19: 見積計算書 | AF19: FSC材質区分
A20: 12 | C20: 画 | D20: 第1画面(基本情報画面) | K20: シート段 | V20: T | W20: 見積計算書 | AF20: シート段
... A45: 37 | C45: 画 | D45: 第1画面(基本情報画面) | K45: AD（形状） | V45: T | W45: 見積計算書 | AF45: AD（形状）
A46: 38 | C46: 画 | D46: 第1画面(基本情報画面) | K46: 戦略商品区分_01 | V46: T | W46: 見積計算書 | AF46: 戦略商品区分_01 | AQ46: FSC
A47: 39 | C47: 画 | D47: 第1画面(基本情報画面) | K47: 戦略商品区分_02 | V47: T | W47: 見積計算書 | AF47: 戦略商品区分_02 | AQ47: TKP
A48: 40 | C48: 画 | D48: 第1画面(基本情報画面) | K48: 戦略商品区分_03 | V48: T | W48: 見積計算書 | AF48: 戦略商品区分_03 | AQ48: スマパピ
A49: 41 | C49: 画 | D49: 第1画面(基本情報画面) | K49: 戦略商品区分_04 | V49: T | W49: 見積計算書 | AF49: 戦略商品区分_04 | AQ49: バリット
A50: 42 | C50: 画 | D50: 第1画面(基本情報画面) | K50: 戦略商品区分_05 | V50: T | W50: 見積計算書 | AF50: 戦略商品区分_05 | AQ50: マイクロ
A51: 43 | C51: 画 | D51: 第1画面(基本情報画面) | K51: 戦略商品区分_06 | V51: T | W51: 見積計算書 | AF51: 戦略商品区分_06 | AQ51: カラフルウィッシュ
A52: 44 | C52: 画 | D52: 第1画面(基本情報画面) | V52: T | W52: 見積計算書 | AF52: 戦略商品区分_07 | AQ52: 空き項目:マスタ値により、不可視設定
A53: 45 | C53: 画 | D53: 第1画面(基本情報画面) | V53: T | W53: 見積計算書 | AF53: 戦略商品区分_08 | AQ53: 空き項目:マスタ値により、不可視設定
A54: 46 | C54: 画 | D54: 第1画面(基本情報画面) | V54: T | W54: 見積計算書 | AF54: 戦略商品区分_09 | AQ54: 空き項目:マスタ値により、不可視設定
A55: 47 | C55: 画 | D55: 第1画面(基本情報画面) | V55: T | W55: 見積計算書 | AF55: 戦略商品区分_10 | AQ55: 空き項目:マスタ値により、不可視設定
A56: 48 | C56: 画 | D56: 第1画面(基本情報画面) | K56: 印刷備考 | V56: T | W56: 見積計算書 | AF56: 印刷備考
A57: 49 | C57: 画 | D57: 第1画面(基本情報画面) | K57: 製造備考 | V57: T | W57: 見積計算書 | AF57: 製造備考
A58: 50 | C58: 画 | D58: 第1画面(基本情報画面) | K58: 伝票備考 | V58: T | W58: 見積計算書 | AF58: 伝票備考
A59: 51 | C59: 画 | D59: 第1画面(基本情報画面) | K59: 納入備考 | V59: T | W59: 見積計算書 | AF59: 納入備考
A60: 52 | C60: 画 | D60: 第1画面(基本情報画面) | K60: 出荷備考１ | V60: T | W60: 見積計算書 | AF60: 出荷備考１
A61: 53 | C61: 画 | D61: 第1画面(基本情報画面) | K61: 出荷備考２ | V61: T | W61: 見積計算書 | AF61: 出荷備考２
A62: 54 | C62: 画 | D62: 第1画面(基本情報画面) | K62: 見積り数01 | V62: T | W62: 見積計算書 | AF62: 見積数 | AQ62: 見積書計算書の枝番データ分、01～08にデータセットする
A63: 55 | C63: 画 | D63: 第1画面(基本情報画面) | K63: 見積り数02 | V63: T | W63: 見積計算書 | AF63: 見積数
A64: 56 | C64: 画 | D64: 第1画面(基本情報画面) | K64: 見積り数03 | V64: T | W64: 見積計算書 | AF64: 見積数
A65: 57 | C65: 画 | D65: 第1画面(基本情報画面) | K65: 見積り数04 | V65: T | W65: 見積計算書 | AF65: 見積数
A66: 58 | C66: 画 | D66: 第1画面(基本情報画面) | K66: 見積り数05 | V66: T | W66: 見積計算書 | AF66: 見積数
A67: 59 | C67: 画 | D67: 第1画面(基本情報画面) | K67: 見積り数06 | V67: T | W67: 見積計算書 | AF67: 見積数
A68: 60 | C68: 画 | D68: 第1画面(基本情報画面) | K68: 見積り数07 | V68: T | W68: 見積計算書 | AF68: 見積数
A69: 61 | C69: 画 | D69: 第1画面(基本情報画面) | K69: 見積り数08 | V69: T | W69: 見積計算書 | AF69: 見積数
A70: 62 | C70: 画 | D70: 第1画面(基本情報画面) | K70: 提案ロット1 | V70: T | W70: 見積計算書 | AF70: 提案ロット1
A71: 63 | C71: 画 | D71: 第1画面(基本情報画面) | K71: 提案ロット2 | V71: T | W71: 見積計算書 | AF71: 提案ロット2
A72: 64 | C72: 画 | D72: 第1画面(基本情報画面) | K72: 単位 | V72: T | W72: 見積計算書 | AF72: 単位
A73: 65 | C73: 画 | D73: 第1画面(基本情報画面) | K73: 決定予想見積り数 | V73: T | W73: 見積計算書 | AF73: 決定予想見積り数
A74: 66 | C74: 画 | D74: 第1画面(基本情報画面) | K74: パレット数01 | V74: T | W74: 見積計算書 | AF74: パレット数 | AQ74: 見積書計算書の枝番データ分、01～08にデータセットする
A75: 67 | C75: 画 | D75: 第1画面(基本情報画面) | K75: パレット数02 | V75: T | W75: 見積計算書 | AF75: パレット数
A76: 68 | C76: 画 | D76: 第1画面(基本情報画面) | K76: パレット数03 | V76: T | W76: 見積計算書 | AF76: パレット数
A77: 69 | C77: 画 | D77: 第1画面(基本情報画面) | K77: パレット数04 | V77: T | W77: 見積計算書 | AF77: パレット数
A78: 70 | C78: 画 | D78: 第1画面(基本情報画面) | K78: パレット数05 | V78: T | W78: 見積計算書 | AF78: パレット数
A79: 71 | C79: 画 | D79: 第1画面(基本情報画面) | K79: パレット数06 | V79: T | W79: 見積計算書 | AF79: パレット数
A80: 72 | C80: 画 | D80: 第1画面(基本情報画面) | K80: パレット数07 | V80: T | W80: 見積計算書 | AF80: パレット数
A81: 73 | C81: 画 | D81: 第1画面(基本情報画面) | K81: パレット数08 | V81: T | W81: 見積計算書 | AF81: パレット数
A82: 74 | C82: 画 | D82: 第2画面(工程情報画面) | K82: 工程 | V82: T | W82: 見積加工工程 | AF82: 工程
A83: 75 | C83: 画 | D83: 第2画面(工程情報画面) | K83: 作業 | V83: T | W83: 見積加工工程 | AF83: 作業
A84: 76 | C84: 画 | D84: 第2画面(工程情報画面) | K84: WG | V84: T | W84: 見積加工工程 | AF84: WG
A85: 77 | C85: 画 | D85: 第2画面(工程情報画面) | K85: 製造場所 | V85: T | W85: 見積加工工程 | AF85: 製造場所
A86: 78 | C86: 画 | D86: 第2画面(工程情報画面) | K86: 仕様１値 | V86: T | W86: 見積加工工程 | AF86: 仕様１値
... A130: 122 | C130: 画 | D130: 決定見積製品補足 | K130: 定数出荷 | V130: T | W130: 見積計算書 | AF130: 定数出荷
A133: No | G133: 2 | S133: ボタン | Z133: ヒアリングシート・案件 | AH133: 備考 | AK133: ヒアリングシート・案件からの連携
A134: 処理分類 | E134: 検索 | S134: ソート順
A135: No | C135: 転送先 | V135: 転送元 | AQ135: 説明
C136: 種 | D136: オブジェクト | K136: 項目名 | V136: 種 | W136: オブジェクト | AF136: 項目名
A137: 1 | C137: 画 | D137: 第1画面(基本情報画面) | K137: 案件No | V137: T | W137: ヒアリングシート | AF137: 案件No
A138: 2 | C138: 画 | D138: 第1画面(基本情報画面) | K138: 案件名 | V138: T | W138: ヒアリングシート | AF138: 案件名
A139: 3 | C139: 画 | D139: 第1画面(基本情報画面) | K139: 受注年月 | V139: T | W139: ヒアリングシート | AF139: 受注予測年月
A140: 4 | C140: 画 | D140: 第1画面(基本情報画面) | K140: シート段 | V140: T | W140: ヒアリングシート | AF140: 段
A141: 5 | C141: 画 | D141: 第1画面(基本情報画面) | K141: 原紙CD(表) | V141: T | W141: ヒアリングシート | AF141: 原紙・表
A142: 6 | C142: 画 | D142: 第1画面(基本情報画面) | K142: 原紙CD(中) | V142: T | W142: ヒアリングシート | AF142: 原紙・中
A143: 7 | C143: 画 | D143: 第1画面(基本情報画面) | K143: 原紙CD(裏) | V143: T | W143: ヒアリングシート | AF143: 原紙・裏
A144: 8 | C144: 画 | D144: 第1画面(基本情報画面) | K144: 印刷CD(裏) | V144: T | W144: ヒアリングシート | AF144: 印刷CD(裏)
A145: 9 | C145: 画 | D145: 第1画面(基本情報画面) | K145: 刃渡り_巾 | V145: T | W145: ヒアリングシート | AF145: 刃渡り_巾
A146: 10 | C146: 画 | D146: 第1画面(基本情報画面) | K146: 刃渡り_流れ | V146: T | W146: ヒアリングシート | AF146: 刃渡り_流れ
A147: 11 | C147: 画 | D147: 第1画面(基本情報画面) | K147: シート寸法_巾 | V147: T | W147: ヒアリングシート | AF147: 刃渡り・巾
A148: 12 | C148: 画 | D148: 第1画面(基本情報画面) | K148: シート寸法_流れ | V148: T | W148: ヒアリングシート | AF148: 刃渡り・流れ
... A161: 25 | C161: 画 | D161: 第1画面(基本情報画面) | K161: デザイン提案NO | V161: T | W161: ヒアリングシート | AF161: デザイン提案NO

Sheet 更新入出力仕様
A1: =表紙!A54 -> Webシステム | K1: 文書名 | U1: モジュールID | Z1: =表紙!$AJ$63 -> MS | AE1: モジュール名 | AJ1: =表紙!$AX$63 -> 見積管理 | AS1: 文書番号 | AZ1: Version | BF1: Rev.
K2: =表紙!O64 -> アドオン設計書 | U2: ｻﾌﾞﾓｼﾞｭｰﾙID | Z2: =表紙!$AJ$64 -> MSBB | AE2: ｻﾌﾞﾓｼﾞｭｰﾙ名 | AJ2: =表紙!$AX$64 -> Webシステム | AS2: =表紙!$BL$64 -> M7-US-1140 | AZ2: =表紙!$BU$64 -> 7.0.2 | BF2: =表紙!$CB$64 -> 1
K3: =RIGHT(CELL("filename",$A$1),LEN(CELL("filename",$A$1))-FIND("]",CELL("filename",$A$1))) -> #VALUE! | U3: 表題 | Z3: =表紙!$AJ$65 -> MSBBPA010 | AE3: =表紙!$AQ$65 -> Web見積計算書入力
A5: No | G5: 1 | S5: ロジック名称 | Z5: 見積計算書 | AH5: 備考
A6: 処理分類 | E6: 更新
A7: No | C7: 転送先 | V7: 転送元 | AQ7: 説明
C8: 種 | D8: オブジェクト | K8: 項目名 | V8: 種 | W8: オブジェクト | AF8: 項目名
A9: 1 | C9: T | D9: 見積計算書 | K9: 見積計算書NO | V9: 画 | W9: 第1画面(基本情報画面) | AF9: 見積計算書NO | BN9: CP指摘 2022/10/18 本多 製品コードから参照入力を可能とするのであれば、製品コードのフィールドが必要と思われます。
A10: 2 | C10: T | D10: 見積計算書 | K10: 参照元_見積計算書NO | V10: 画 | W10: 第1画面(基本情報画面) | AF10: 参照元_見積計算書NO | BO10: MDSOL 野村 2022/10/28 現想定では、過去見積やテンプレート見積からの参照を想定しています。追加必要でしょうか。
A11: 3 | C11: T | D11: 見積計算書 | K11: 見積日 | AQ11: 登録日
A12: 4 | C12: T | D12: 見積計算書 | K12: 見積拠点CD | V12: 画 | W12: 第1画面(基本情報画面) | AF12: 見積拠点CD
A13: 5 | C13: T | D13: 見積計算書 | K13: 受注拠点CD | V13: 画 | W13: 第1画面(基本情報画面) | AF13: 受注拠点CD
A14: 6 | C14: T | D14: 見積計算書 | K14: 担当者CD | V14: 画 | W14: 第1画面(基本情報画面) | AF14: 担当者CD
A15: 7 | C15: T | D15: 見積計算書 | K15: 得意先CD | V15: 画 | W15: 第1画面(基本情報画面) | AF15: 得意先CD
A16: 8 | C16: T | D16: 見積計算書 | K16: 案件No | V16: 画 | W16: 第1画面(基本情報画面) | AF16: 案件No
A17: 9 | C17: T | D17: 見積計算書 | K17: 案件No(親・子) | V17: 画 | W17: 第1画面(基本情報画面) | AF17: 案件No(親・子)
A18: 10 | C18: T | D18: 見積計算書 | K18: 案件No(子) | V18: 画 | W18: 第1画面(基本情報画面) | AF18: 案件No(子)
A19: 11 | C19: T | D19: 見積計算書 | K19: サンプル依頼ID | V19: 画 | W19: 第1画面(基本情報画面) | AF19: サンプル依頼ID
A20: 12 | C20: T | D20: 見積計算書 | K20: 受注区分 | V20: 画 | W20: 第1画面(基本情報画面) | AF20: 受注区分
A21: 13 | C21: T | D21: 見積計算書 | K21: 顧客品名 | V21: 画 | W21: 第1画面(基本情報画面) | AF21: 顧客品名
A22: 14 | C22: T | D22: 見積計算書 | K22: 受注総数 | V22: 画 | W22: 第1画面(基本情報画面) | AF22: 受注総数
A23: 15 | C23: T | D23: 見積計算書 | K23: 受注年月 | V23: 画 | W23: 第1画面(基本情報画面) | AF23: 受注年月
... A52: 44 | C52: T | D52: 見積計算書 | K52: AD（形状） | V52: 画 | W52: 第1画面(基本情報画面) | AF52: AD（形状）
A53: 45 | C53: T | D53: 見積計算書 | K53: 戦略商品区分_01 | V53: 画 | W53: 第1画面(基本情報画面) | AF53: 戦略商品区分_01 | AQ53: FSC
A54: 46 | C54: T | D54: 見積計算書 | K54: 戦略商品区分_02 | V54: 画 | W54: 第1画面(基本情報画面) | AF54: 戦略商品区分_02 | AQ54: TKP
A55: 47 | C55: T | D55: 見積計算書 | K55: 戦略商品区分_03 | V55: 画 | W55: 第1画面(基本情報画面) | AF55: 戦略商品区分_03 | AQ55: スマパピ
A56: 48 | C56: T | D56: 見積計算書 | K56: 戦略商品区分_04 | V56: 画 | W56: 第1画面(基本情報画面) | AF56: 戦略商品区分_04 | AQ56: バリット
A57: 49 | C57: T | D57: 見積計算書 | K57: 戦略商品区分_05 | V57: 画 | W57: 第1画面(基本情報画面) | AF57: 戦略商品区分_05 | AQ57: マイクロ
A58: 50 | C58: T | D58: 見積計算書 | K58: 戦略商品区分_06 | V58: 画 | W58: 第1画面(基本情報画面) | AF58: 戦略商品区分_06 | AQ58: カラフルウィッシュ
A59: 51 | C59: T | D59: 見積計算書 | K59: 戦略商品区分_07 | V59: 画 | W59: 第1画面(基本情報画面) | AQ59: 空き項目:マスタ値により、不可視設定
A60: 52 | C60: T | D60: 見積計算書 | K60: 戦略商品区分_08 | V60: 画 | W60: 第1画面(基本情報画面) | AQ60: 空き項目:マスタ値により、不可視設定
A61: 53 | C61: T | D61: 見積計算書 | K61: 戦略商品区分_09 | V61: 画 | W61: 第1画面(基本情報画面) | AQ61: 空き項目:マスタ値により、不可視設定
A62: 54 | C62: T | D62: 見積計算書 | K62: 戦略商品区分_10 | V62: 画 | W62: 第1画面(基本情報画面) | AQ62: 空き項目:マスタ値により、不可視設定
A63: 55 | C63: T | D63: 見積計算書 | K63: 印刷備考 | V63: 画 | W63: 第1画面(基本情報画面) | AF63: 印刷備考
A64: 56 | C64: T | D64: 見積計算書 | K64: 製造備考 | V64: 画 | W64: 第1画面(基本情報画面) | AF64: 製造備考
A65: 57 | C65: T | D65: 見積計算書 | K65: 伝票備考 | V65: 画 | W65: 第1画面(基本情報画面) | AF65: 伝票備考
A66: 58 | C66: T | D66: 見積計算書 | K66: 納入備考 | V66: 画 | W66: 第1画面(基本情報画面) | AF66: 納入備考
A67: 59 | C67: T | D67: 見積計算書 | K67: 出荷備考１ | V67: 画 | W67: 第1画面(基本情報画面) | AF67: 出荷備考１
A68: 60 | C68: T | D68: 見積計算書 | K68: 出荷備考２ | V68: 画 | W68: 第1画面(基本情報画面) | AF68: 出荷備考２
A69: 61 | C69: T | D69: 見積計算書 | K69: 見積数 | V69: 画 | W69: 第1画面(基本情報画面) | AF69: 見積り数01 | AQ69: 見積り数01～08分の枝番として、見積書計算書のデータを生成する
A70: 62 | C70: T | D70: 見積計算書 | K70: 見積数 | V70: 画 | W70: 第1画面(基本情報画面) | AF70: 見積り数02
A71: 63 | C71: T | D71: 見積計算書 | K71: 見積数 | V71: 画 | W71: 第1画面(基本情報画面) | AF71: 見積り数03
A72: 64 | C72: T | D72: 見積計算書 | K72: 見積数 | V72: 画 | W72: 第1画面(基本情報画面) | AF72: 見積り数04
A73: 65 | C73: T | D73: 見積計算書 | K73: 見積数 | V73: 画 | W73: 第1画面(基本情報画面) | AF73: 見積り数05
A74: 66 | C74: T | D74: 見積計算書 | K74: 見積数 | V74: 画 | W74: 第1画面(基本情報画面) | AF74: 見積り数06
A75: 67 | C75: T | D75: 見積計算書 | K75: 見積数 | V75: 画 | W75: 第1画面(基本情報画面) | AF75: 見積り数07
A76: 68 | C76: T | D76: 見積計算書 | K76: 見積数 | V76: 画 | W76: 第1画面(基本情報画面) | AF76: 見積り数08
A77: 69 | C77: T | D77: 見積計算書 | K77: 提案ロット1 | V77: 画 | W77: 第1画面(基本情報画面) | AF77: 提案ロット1
A78: 70 | C78: T | D78: 見積計算書 | K78: 提案ロット2 | V78: 画 | W78: 第1画面(基本情報画面) | AF78: 提案ロット2
A79: 71 | C79: T | D79: 見積計算書 | K79: 単位 | V79: 画 | W79: 第1画面(基本情報画面) | AF79: 単位
A80: 72 | C80: T | D80: 見積計算書 | K80: 決定予想見積り数 | V80: 画 | W80: 第1画面(基本情報画面) | AF80: 決定予想見積り数
A81: 73 | C81: T | D81: 見積計算書 | K81: パレット数 | V81: 画 | W81: 第1画面(基本情報画面) | AF81: パレット数01 | AQ81: 見積り数01～08分の枝番として、見積書計算書のデータを生成する
A82: 74 | C82: T | D82: 見積計算書 | K82: パレット数 | V82: 画 | W82: 第1画面(基本情報画面) | AF82: パレット数02
A83: 75 | C83: T | D83: 見積計算書 | K83: パレット数 | V83: 画 | W83: 第1画面(基本情報画面) | AF83: パレット数03
A84: 76 | C84: T | D84: 見積計算書 | K84: パレット数 | V84: 画 | W84: 第1画面(基本情報画面) | AF84: パレット数04
A85: 77 | C85: T | D85: 見積計算書 | K85: パレット数 | V85: 画 | W85: 第1画面(基本情報画面) | AF85: パレット数05
A86: 78 | C86: T | D86: 見積計算書 | K86: パレット数 | V86: 画 | W86: 第1画面(基本情報画面) | AF86: パレット数06
A87: 79 | C87: T | D87: 見積計算書 | K87: パレット数 | V87: 画 | W87: 第1画面(基本情報画面) | AF87: パレット数07
A88: 80 | C88: T | D88: 見積計算書 | K88: パレット数 | V88: 画 | W88: 第1画面(基本情報画面) | AF88: パレット数08
A89: 81 | C89: T | D89: 見積計算書 | K89: 溶リ判定区分A_01 | V89: 画 | W89: 溶リ判定画面 | AF89: 溶リ判定区分A_01
A90: 82 | C90: T | D90: 見積計算書 | K90: 溶リ判定区分A_02 | V90: 画 | W90: 溶リ判定画面 | AF90: 溶リ判定区分A_02
A91: 83 | C91: T | D91: 見積計算書 | K91: 溶リ判定区分A_03 | V91: 画 | W91: 溶リ判定画面 | AF91: 溶リ判定区分A_03
A92: 84 | C92: T | D92: 見積計算書 | K92: 溶リ判定区分A_04 | V92: 画 | W92: 溶リ判定画面 | AF92: 溶リ判定区分A_04
A93: 85 | C93: T | D93: 見積計算書 | K93: 溶リ判定区分A_05 | V93: 画 | W93: 溶リ判定画面 | AF93: 溶リ判定区分A_05
... A175: 167 | C175: T | D175: 見積計算書 | K175: 決定金額 | V175: 画 | W175: 第3画面(その他金額情報) | AF175: 決定金額
A176: 168 | C176: T | D176: 見積計算書 | K176: デザイン提案NO | AQ176: ヒアリングシートからの連携を想定
A180: No | G180: 2 | S180: ロジック名称 | Z180: 見積加工工程 | AH180: 備考
A181: 処理分類 | E181: 更新
A182: No | C182: 転送先 | V182: 転送元 | AQ182: 説明
C183: 種 | D183: オブジェクト | K183: 項目名 | V183: 種 | W183: オブジェクト | AF183: 項目名
A184: 1 | C184: T | D184: 見積加工工程 | K184: 見積計算書NO | V184: 画
A185: 2 | C185: T | D185: 見積加工工程 | K185: 作業CD | V185: 画 | W185: 第2画面(工程情報画面)
A186: 3 | C186: T | D186: 見積加工工程 | K186: 工程CD | V186: 画 | W186: 第2画面(工程情報画面)
A187: 4 | C187: T | D187: 見積加工工程 | K187: 作業順 | V187: 画 | W187: 第2画面(工程情報画面)
A188: 5 | C188: T | D188: 見積加工工程 | K188: ワーキンググループＣＤ | V188: 画 | W188: 第2画面(工程情報画面)
A189: 6 | C189: T | D189: 見積加工工程 | K189: 製造場所 | V189: 画 | W189: 第2画面(工程情報画面)
A190: 7 | C190: T | D190: 見積加工工程 | K190: 工程仕様01 | V190: 画 | W190: 第2画面(工程情報画面)
A191: 8 | C191: T | D191: 見積加工工程 | K191: 工程仕様02 | V191: 画 | W191: 第2画面(工程情報画面)
A192: 9 | C192: T | D192: 見積加工工程 | K192: 工程仕様03 | V192: 画 | W192: 第2画面(工程情報画面)
A193: 10 | C193: T | D193: 見積加工工程 | K193: 工程仕様04 | V193: 画 | W193: 第2画面(工程情報画面)
A194: 11 | C194: T | D194: 見積加工工程 | K194: 工程仕様05 | V194: 画 | W194: 第2画面(工程情報画面)
A195: 12 | C195: T | D195: 見積加工工程 | K195: 工程仕様06 | V195: 画 | W195: 第2画面(工程情報画面)
A196: 13 | C196: T | D196: 見積加工工程 | K196: 工程仕様07 | V196: 画 | W196: 第2画面(工程情報画面)
A197: 14 | C197: T | D197: 見積加工工程 | K197: 工程仕様08 | AQ197: 拡張用
A198: 15 | C198: T | D198: 見積加工工程 | K198: 工程仕様09 | AQ198: 拡張用
A199: 16 | C199: T | D199: 見積加工工程 | K199: 工程仕様10 | AQ199: 拡張用
A200: 17 | C200: T | D200: 見積加工工程 | K200: 版NO | V200: 画 | W200: 第2画面(工程情報画面)
A201: 18 | C201: T | D201: 見積加工工程 | K201: 工程備考１ | V201: 画 | W201: 第2画面(工程情報画面)
A202: 19 | C202: T | D202: 見積加工工程 | K202: 工程備考２ | V202: 画 | W202: 第2画面(工程情報画面)
A203: 20 | C203: T | D203: 見積加工工程 | K203: 指示数 | V203: 画 | W203: 第3画面(計算結果画面)
A204: 21 | C204: T | D204: 見積加工工程 | K204: 見積単価 | V204: 画 | W204: 第3画面(計算結果画面)
A205: 22 | C205: T | D205: 見積加工工程 | K205: 見積工賃 | V205: 画 | W205: 第3画面(計算結果画面)
A206: 23 | C206: T | D206: 見積加工工程 | K206: 外注単価 | V206: 画 | W206: 第3画面(計算結果画面)
A207: 24 | C207: T | D207: 見積加工工程 | K207: 外注金額 | V207: 画 | W207: 第3画面(計算結果画面)
A208: 25 | C208: T | D208: 見積加工工程 | K208: 版型仕入 | V208: 画 | W208: 第3画面(計算結果画面)
A209: 26 | C209: T | D209: 見積加工工程 | K209: 版型金額 | V209: 画 | W209: 第3画面(計算結果画面)
A210: 27 | C210: T | D210: 見積加工工程 | K210: 並び順 | AQ210: 画面の並び順、システム自動採番

Sheet ファイル入出力仕様
A1: =表紙!A54 -> Webシステム | K1: 文書名 | U1: モジュールID | Z1: =表紙!$AJ$63 -> MS | AE1: モジュール名 | AJ1: =表紙!$AX$63 -> 見積管理 | AS1: 文書番号 | AZ1: Version | BF1: Rev.
K2: =表紙!O64 -> アドオン設計書 | U2: ｻﾌﾞﾓｼﾞｭｰﾙID | Z2: =表紙!$AJ$64 -> MSBB | AE2: ｻﾌﾞﾓｼﾞｭｰﾙ名 | AJ2: =表紙!$AX$64 -> Webシステム | AS2: =表紙!$BL$64 -> M7-US-1140 | AZ2: =表紙!$BU$64 -> 7.0.2 | BF2: =表紙!$CB$64 -> 1
K3: =RIGHT(CELL("filename",$A$1),LEN(CELL("filename",$A$1))-FIND("]",CELL("filename",$A$1))) -> #VALUE! | U3: 表題 | Z3: =表紙!$AJ$65 -> MSBBPA010 | AE3: =表紙!$AQ$65 -> Web見積計算書入力
A5: No | G5: 1 | S5: ロジック名称 | AH5: 備考
A6: 処理分類 | E6: 更新
A7: No | C7: 転送先 | V7: 転送元 | AQ7: 説明
C8: 種 | D8: オブジェクト | K8: 項目名 | V8: 種 | W8: オブジェクト | AF8: 項目名

Sheet 画面遷移
A1: =表紙!A54 -> Webシステム | K1: 文書名 | U1: モジュールID | Z1: =表紙!$AJ$63 -> MS | AE1: モジュール名 | AJ1: =表紙!$AX$63 -> 見積管理 | AS1: 文書番号 | AZ1: Version | BF1: Rev.
K2: =表紙!O64 -> アドオン設計書 | U2: ｻﾌﾞﾓｼﾞｭｰﾙID | Z2: =表紙!$AJ$64 -> MSBB | AE2: ｻﾌﾞﾓｼﾞｭｰﾙ名 | AJ2: =表紙!$AX$64 -> Webシステム | AS2: =表紙!$BL$64 -> M7-US-1140 | AZ2: =表紙!$BU$64 -> 7.0.2 | BF2: =表紙!$CB$64 -> 1
K3: =RIGHT(CELL("filename",$A$1),LEN(CELL("filename",$A$1))-FIND("]",CELL("filename",$A$1))) -> #VALUE! | U3: 表題 | Z3: =表紙!$AJ$65 -> MSBBPA010 | AE3: =表紙!$AQ$65 -> Web見積計算書入力
A5: 画面遷移フロー図
C7: 前提条件
D8: 見積計算書・製品マスタ・受注入力画面は、複数画面を遷移して項目を選択・入力し、登録する画面となる
J10: 次画面 | U10: 最初・最終画面以外は、基本「次画面・前画面」のボタンが用意されている
V11: 次画面：現在のページを記憶する
V12: 前画面：前のページに戻る、次画面を押した時に情報をセットし前画面を呼び出す
V13: ※次画面を押した時と同じ情報となる(次画面で途中まで入力して、前画面をクリックすると入力キャンセル扱いとなる)
J14: 前画面
A17: ＩＤ | C17: S01 | E17: 見積計算書機能の画面遷移
C19: ≫操作種別：登録、訂正、コピー
D20: 1ページ目：基本情報画面 | O20: 2ページ目：工程情報画面 | AH20: 3ページ目：計算結果画面
J21: 次画面 | U21: 次画面
J23: 戻る | U23: 戻る
D25: 溶リ判定必要時
D26: (取引先.容器リ法対象=該当)
E27: 戻る
I30: 溶リ判定ポップアップ | R30: 工程選択ポップアップ
I31: ※得意先マスタ：容リ法対象=1:該当時
C33: ≫操作種別：削除、参照
D34: 1ページ目：基本情報画面 | O34: 3ページ目：計算結果画面
J37: 戻る | V37: ※削除時
C43: ≫コピー登録
D44: 3ページ目：計算結果画面 | U44: 3ページ目：計算結果画面
A51: ＩＤ | C51: S02 | E51: 見積計算書、他画面の画面遷移
D53: NO1 | AG53: ※Web御見積書登録・発行側で記述
D54: Web見積計算書一覧照会(検索モード) | AG54: Web御見積書登録・発行
K60: Web見積計算書入力 | V60: Web見積計算書入力 | AG60: Web見積計算書入力
K61: 1ページ目：基本情報画面 | V61: 2ページ目：工程情報画面 | AG61: 3ページ目：計算結果画面
Q62: 次画面 | AB62: 次画面
Q64: 戻る | AB64: 戻る
D67: NO2 | Q67: NO4
D68: 簡易検索 | I68: NO3 | Q68: 簡易検索
D69: ヒアリングシート | I69: Web取引先一覧照会 | Q69: その他
A74: ID | D74: 処理名
A75: S02 | D75: 見積計算書から他画面の画面遷移
B77: NO | D77: 遷移元ＩＤ | H77: 遷移元画面名 | P77: 遷移先ＩＤ | U77: 遷移先画面名 | AC77: 目的 | AH77: 引継項目 | AQ77: 遷移後のアクション(遷移先) | BA77: 戻り値 | BJ77: 戻り値取得後のアクション(遷移元) | BT77: 備考
B78: 1 | D78: MSBBPA010 | H78: Web見積計算書入力(基本) | P78: MSBBPA020 | U78: Web見積計算書一覧照会 | AC78: 検索結果取得 | AQ78: 検索 | BA78: 見積計算書選択データ(1行) | BJ78: 検索入出力仕様.NO1
B79: 2 | D79: MSBBPA010 | H79: Web見積計算書入力(基本) | P79: MSBBPA900 | U79: Web汎用検索(共通検索) | AC79: 検索結果取得 | AQ79: 検索 | BA79: ヒアリングシート選択データ(1行) | BJ79: 検索入出力仕様.NO2
B80: 3 | D80: MSBBPA010 | H80: Web見積計算書入力(基本) | P80: MSBBPA120 | U80: Web取引先一覧照会 | AC80: 検索結果取得 | AQ80: 検索 | BA80: 取引先選択データ(1行) | BJ80: 対象データに値セット | BT80: 得意先CD、得意先名に値セット
B81: 4 | D81: MSBBPA010 | H81: Web見積計算書入力(基本) | P81: MSBBPA900 | U81: Web汎用検索(共通検索) | AC81: 検索結果取得 | AQ81: 検索 | BA81: 各種検索画面の選択データ(1行) | BJ81: 対象データに値セット | BT81: CD、名称に値セット
B82: 5
B83: 6
B84: 7
B85: 8

Sheet メッセージ一覧
A1: =表紙!A54 -> Webシステム | K1: 文書名 | U1: モジュールID | Z1: =表紙!$AJ$63 -> MS | AE1: モジュール名 | AJ1: =表紙!$AX$63 -> 見積管理 | AS1: 文書番号 | AZ1: Version | BF1: Rev.
K2: =表紙!O64 -> アドオン設計書 | U2: ｻﾌﾞﾓｼﾞｭｰﾙID | Z2: =表紙!$AJ$64 -> MSBB | AE2: ｻﾌﾞﾓｼﾞｭｰﾙ名 | AJ2: =表紙!$AX$64 -> Webシステム | AS2: =表紙!$BL$64 -> M7-US-1140 | AZ2: =表紙!$BU$64 -> 7.0.2 | BF2: =表紙!$CB$64 -> 1
K3: =RIGHT(CELL("filename",$A$1),LEN(CELL("filename",$A$1))-FIND("]",CELL("filename",$A$1))) -> #VALUE! | U3: 表題 | Z3: =表紙!$AJ$65 -> MSBBPA010 | AE3: =表紙!$AQ$65 -> Web見積計算書入力
C4: ↓アドオン画面のため、基本全て[新]
A5: No | C5: 新/変 | E5: 種別 | G5: メッセージ内容 | AQ5: 備考（パラメータ等） | BG5: メッセージID
A6: 1 | C6: 新 | E6: W | G6: 「見積計算書NOが未入力です。」 | BG6: メッセージID.101
A7: 2 | C7: 新 | E7: W | G7: 「見積計算書NOが未登録です。」 | BG7: メッセージID.102
A8: 3 | C8: 新 | E8: W | G8: 「見積拠点CDが未入力です。」 | BG8: メッセージID.111
A9: 4 | C9: 新 | E9: W | G9: 「受注拠点CDが未入力です。」 | BG9: メッセージID.112
A10: 5 | C10: 新 | E10: W | G10: 「担当者CDが未入力です。」 | BG10: メッセージID.113
A11: 6 | C11: 新 | E11: W | G11: 「得意先が未入力です。」 | BG11: メッセージID.114
A12: 7 | C12: 新 | E12: W | G12: 「案件NOが未入力です。」 | BG12: メッセージID.115
A13: 8 | C13: 新 | E13: W | G13: 「顧客品名が未入力です。」 | BG13: メッセージID.116
A14: 9 | C14: 新 | E14: W | G14: 「受注総数が未入力です。」 | BG14: メッセージID.117
A15: 10 | C15: 新 | E15: W | G15: 「受注年月が未入力です。」 | BG15: メッセージID.118
A16: 11 | C16: 新 | E16: W | G16: 「親子区分が未入力です。」 | BG16: メッセージID.119
A17: 12 | C17: 新 | E17: W | G17: 「原紙が非認証です。」 | BG17: メッセージID.120
... A91: 86 | C91: 新 | E91: W | G91: 「シート単価を入力」 | BG91: メッセージID.310

Sheet テーブル項目_見積計算書
A1: =表紙!A54 -> Webシステム | K1: 文書名 | U1: モジュールID | Z1: =表紙!$AJ$63 -> MS | AE1: モジュール名 | AJ1: =表紙!$AX$63 -> 見積管理 | AS1: 文書番号 | AZ1: Version | BF1: Rev.
K2: =表紙!O64 -> アドオン設計書 | U2: ｻﾌﾞﾓｼﾞｭｰﾙID | Z2: =表紙!$AJ$64 -> MSBB | AE2: ｻﾌﾞﾓｼﾞｭｰﾙ名 | AJ2: =表紙!$AX$64 -> Webシステム | AS2: =表紙!$BL$64 -> M7-US-1140 | AZ2: =表紙!$BU$64 -> 7.0.2 | BF2: =表紙!$CB$64 -> 1
K3: =RIGHT(CELL("filename",$A$1),LEN(CELL("filename",$A$1))-FIND("]",CELL("filename",$A$1))) -> #VALUE! | U3: 表題 | Z3: =表紙!$AJ$65 -> MSBBPA010 | AE3: =表紙!$AQ$65 -> Web見積計算書入力
A5: テーブル名 | O5: 日本語名 | AE5: 種別
O6: 見積計算書 | AE6: アドオン(新規) | BP6: CP指摘 2022/10/18 本多 現状、見積から製品コードが作成された場合、見積テーブルへ製品コードを記録しています。これにより見積決定率の算出等をしております。
BQ7: MDSOL 野村 2022/10/28 製品CD追加しました。
A8: 主キー | D8: 項目名 | O8: 日本語名 | AE8: 型 | AG8: 桁 | AI8: Null | AK8: 説明 | BL8: 値の制限 | BM8: 設定仕様 | BN8: 未設定時の振る舞い | BO8: 見積計算書 画面
A9: 〇 | O9: 見積計算書NO | AE9: C | AI9: N | AK9: 枝番含む | BO9: 第1画面(基本情報画面) | BP9: CP指摘 2022/09/30 三宅 見積計算書№は「枝番を含む」となっているので「123456」と「1」のように持つのではなく「123456-1」のように一つのカラムで持つのでしょうか？分けずに持つその場合、参照時にロット別表示やロット別見積一覧の箇所は「ハイフン区切りの前の部分が一致するレコード」として取得しないといけないので効率が悪く処理も遅くならないでしょうか？
D10: QTN_CALC_NO_M | O10: 見積計算書NO_主番 | AE10: N | AI10: N | AK10: 見積計算書NOの内訳(99999999-01) 99999999部分 | BO10: 第1画面(基本情報画面) | BQ10: MDSOL 野村 2022/10/28 内訳項目として追加しました。
D11: QTN_CALC_NO_B | O11: 見積計算書NO_枝番 | AE11: N | AI11: N | AK11: 見積計算書NOの内訳(99999999-01) 1部分 | BO11: 第1画面(基本情報画面)
O12: 参照元_見積計算書NO | AE12: C | AI12: Y | AK12: 操作種別：コピー時、保存 | BL12: 見積計算書トラン | BO12: 第1画面(基本情報画面)
D13: PRO_CD | O13: 製品コード | AE13: C | AI13: N | AK13: 品目コード+枝番
O14: 見積日 | AE14: D | AI14: N | AK14: 見積作成日
O15: 見積拠点CD | AE15: C | AI15: N | BL15: 拠点マスタ | BO15: 第1画面(基本情報画面)
O16: 受注拠点CD | AE16: C | AI16: N | BL16: 拠点マスタ | BO16: 第1画面(基本情報画面)
O17: 担当者CD | AE17: C | AI17: N | BL17: 担当者マスタ | BO17: 第1画面(基本情報画面)
O18: 得意先CD | AE18: C | AI18: N | BL18: 得意先マスタ | BO18: 第1画面(基本情報画面)
O19: 案件No | AE19: C | AI19: N | AK19: 案件No(親) | BL19: ヒアリングシート | BO19: 第1画面(基本情報画面)
O20: サンプル依頼ID | AE20: C | AI20: N | BL20: ヒアリングシート | BO20: 第1画面(基本情報画面)
O21: 受注区分 | AE21: C | AI21: N | BO21: 第1画面(基本情報画面)
O22: 顧客品名 | AE22: C | AI22: N | BO22: 第1画面(基本情報画面)
O23: 受注総数 | AE23: N | AI23: N | BO23: 第1画面(基本情報画面)
O24: 受注年月 | AE24: C | AI24: N | BO24: 第1画面(基本情報画面)
O25: 親子区分 | AE25: C | AI25: N | BO25: 第1画面(基本情報画面)
O26: FSC認証区分 | AE26: C | AI26: N | BO26: 第1画面(基本情報画面)
O27: FSC材質区分 | AE27: C | AI27: N | BO27: 第1画面(基本情報画面)
O28: シート段 | AE28: C | AI28: N | BO28: 第1画面(基本情報画面)
O29: 原紙CD(表) | AE29: C | AI29: N | BL29: 原紙マスタ | BO29: 第1画面(基本情報画面)
O30: 印刷CD(表) | AE30: C | AI30: N | BL30: 汎用マスタ(印刷マスタ) | BO30: 第1画面(基本情報画面)
O31: エンボスCD(表) | AE31: C | AI31: N | BL31: 汎用マスタ(エンボスマスタ) | BO31: 第1画面(基本情報画面)
O32: 柄数(表) | AE32: C | AI32: N | BO32: 第1画面(基本情報画面)
O33: 原紙CD(中) | AE33: C | AI33: N | BL33: 原紙マスタ | BO33: 第1画面(基本情報画面)
O34: 印刷CD(中) | AE34: C | AI34: N | BL34: 汎用マスタ(印刷マスタ) | BO34: 第1画面(基本情報画面)
O35: エンボスCD(中) | AE35: C | AI35: N | BL35: 汎用マスタ(エンボスマスタ) | BO35: 第1画面(基本情報画面)
O36: 原紙CD(裏) | AE36: C | AI36: N | BL36: 原紙マスタ | BO36: 第1画面(基本情報画面)
O37: 印刷CD(裏) | AE37: C | AI37: N | BL37: 汎用マスタ(印刷マスタ) | BO37: 第1画面(基本情報画面)
O38: エンボスCD(裏) | AE38: C | AI38: N | BL38: 汎用マスタ(エンボスマスタ) | BO38: 第1画面(基本情報画面)
O39: 柄数(裏) | AE39: C | AI39: N | BO39: 第1画面(基本情報画面)
O40: 枚葉印刷 | AE40: C | AI40: N | BO40: 第1画面(基本情報画面)
O41: 刃渡り_巾 | AE41: N | AI41: N | BO41: 第1画面(基本情報画面)
O42: 刃渡り_流れ | AE42: N | AI42: N | BO42: 第1画面(基本情報画面)
O43: 咥え_前後 | AE43: N | AI43: N | BO43: 第1画面(基本情報画面)
O44: 咥え_左右 | AE44: N | AI44: N | BO44: 第1画面(基本情報画面)
O45: シート寸法_巾 | AE45: N | AI45: N | BO45: 第1画面(基本情報画面)
O46: シート寸法_流れ | AE46: N | AI46: N | BO46: 第1画面(基本情報画面)
O47: 最終機械工程 | AE47: C | AI47: N | BO47: 第1画面(基本情報画面)
O48: 製品形状1=計上分類 | AE48: C | AI48: N | AK48: 選択項目は、汎用マスタで管理 | BO48: 第1画面(基本情報画面)
O49: 製品形状2=計上区分 | AE49: C | AI49: N | AL49: 〃 | BO49: 第1画面(基本情報画面)
O50: 物流区分 | AE50: C | AI50: N | AL50: 〃 | BO50: 第1画面(基本情報画面)
O51: 容リ支払 | AE51: C | AI51: N | BO51: 第1画面(基本情報画面)
O52: 識別表示 | AE52: C | AI52: N | BO52: 第1画面(基本情報画面)
O53: AD（形状） | AE53: C | AI53: N | BO53: 第1画面(基本情報画面)
O54: 戦略商品区分_01 | AE54: N | AI54: N | AK54: FSC | BL54: 1：はい、0：いいえ | BO54: 第1画面(基本情報画面)
O55: 戦略商品区分_02 | AE55: N | AI55: N | AK55: TKP | BL55: 1：はい、0：いいえ | BO55: 第1画面(基本情報画面)
O56: 戦略商品区分_03 | AE56: N | AI56: N | AK56: スマパピ | BL56: 1：はい、0：いいえ | BO56: 第1画面(基本情報画面)
O57: 戦略商品区分_04 | AE57: N | AI57: N | AK57: バリット | BL57: 1：はい、0：いいえ | BO57: 第1画面(基本情報画面)
O58: 戦略商品区分_05 | AE58: N | AI58: N | AK58: マイクロ | BL58: 1：はい、0：いいえ | BO58: 第1画面(基本情報画面)
O59: 戦略商品区分_06 | AE59: N | AI59: N | AK59: カラフルウィッシュ | BL59: 1：はい、0：いいえ | BO59: 第1画面(基本情報画面)
O60: 戦略商品区分_07 | AE60: N | AI60: N | AK60: 空き項目:マスタ値により、不可視設定 | BL60: 1：はい、0：いいえ | BO60: 第1画面(基本情報画面)
O61: 戦略商品区分_08 | AE61: N | AI61: N | AK61: 空き項目:マスタ値により、不可視設定 | BL61: 1：はい、0：いいえ | BO61: 第1画面(基本情報画面)
O62: 戦略商品区分_09 | AE62: N | AI62: N | AK62: 空き項目:マスタ値により、不可視設定 | BL62: 1：はい、0：いいえ | BO62: 第1画面(基本情報画面)
O63: 戦略商品区分_10 | AE63: N | AI63: N | AK63: 空き項目:マスタ値により、不可視設定 | BL63: 1：はい、0：いいえ | BO63: 第1画面(基本情報画面)
O64: 印刷備考 | AE64: C | AI64: N | BL64: 1：はい、0：いいえ | BO64: 第1画面(基本情報画面)
O65: 製造備考 | AE65: C | AI65: N | BO65: 第1画面(基本情報画面)
O66: 伝票備考 | AE66: C | AI66: N | BO66: 第1画面(基本情報画面)
O67: 納入備考 | AE67: C | AI67: N | BO67: 第1画面(基本情報画面)
O68: 出荷備考１ | AE68: C | AI68: N | BO68: 第1画面(基本情報画面) | BP68: CP指摘 2022/09/30 三宅 見積計算書№は「枝番を含む」となっているので「123456」と「1」のように持つのではなく「123456-1」のように一つのカラムで持つのでしょうか？分けずに持つその場合、参照時にロット別表示やロット別見積一覧の箇所は「ハイフン区切りの前の部分が一致するレコード」として取得しないといけないので効率が悪く処理も遅くならないでしょうか？
O69: 出荷備考２ | AE69: C | AI69: N | BO69: 第1画面(基本情報画面) | BQ69: MDSOL 野村 2022/10/28 内訳項目として追加しました。
O70: 見積り数 | AE70: N | AI70: N | BO70: 第1画面(基本情報画面)
O71: 見積り数02 | AE71: N | AI71: N | BO71: 第1画面(基本情報画面)
O72: 見積り数03 | AE72: N | AI72: N | BO72: 第1画面(基本情報画面)
O73: 見積り数04 | AE73: N | AI73: N | BO73: 第1画面(基本情報画面)
O74: 見積り数05 | AE74: N | AI74: N | BO74: 第1画面(基本情報画面)
O75: 見積り数06 | AE75: N | AI75: N | BO75: 第1画面(基本情報画面)
O76: 見積り数07 | AE76: N | AI76: N | BO76: 第1画面(基本情報画面)
O77: 見積り数08 | AE77: N | AI77: N | BO77: 第1画面(基本情報画面)
O78: 提案ロット1 | AE78: N | AI78: N | BO78: 第1画面(基本情報画面)
O79: 提案ロット2 | AE79: N | AI79: N | BO79: 第1画面(基本情報画面)
O80: 単位 | AE80: N | AI80: N | BO80: 第1画面(基本情報画面)
O81: 決定予想見積り数 | AE81: N | AI81: N | BO81: 第1画面(基本情報画面)
O82: パレット数 | AE82: N | AI82: N | AK82: 画面.パレット数01～パレット数08は、枝番データを指す | BO82: 第1画面(基本情報画面) | BR82: MDSOL 野村 2022/10/28 内訳項目として追加しました。
O83: パレット数02 | AE83: N | AI83: N | BO83: 第1画面(基本情報画面)
O84: パレット数03 | AE84: N | AI84: N | BO84: 第1画面(基本情報画面)
O85: パレット数04 | AE85: N | AI85: N | BO85: 第1画面(基本情報画面)
O86: パレット数05 | AE86: N | AI86: N | BO86: 第1画面(基本情報画面)
O87: パレット数06 | AE87: N | AI87: N | BO87: 第1画面(基本情報画面)
O88: パレット数07 | AE88: N | AI88: N | BO88: 第1画面(基本情報画面)
O89: パレット数08 | AE89: N | AI89: N | BO89: 第1画面(基本情報画面)
O90: 溶リ判定区分A_01 | AE90: C | AI90: N | BO90: 溶リ判定画面
O91: 溶リ判定区分A_02 | AE91: C | AI91: N | BO91: 溶リ判定画面
O92: 溶リ判定区分A_03 | AE92: C | AI92: N | BO92: 溶リ判定画面
O93: 溶リ判定区分A_04 | AE93: C | AI93: N | BO93: 溶リ判定画面 | BR93: MDSOL 野村 2022/10/28 画面用に項目として保持しようと考えましたが、ご指摘のとおり枝番で管理します。
O94: 溶リ判定区分A_05 | AE94: C | AI94: N | BO94: 溶リ判定画面 | CA94: パレットは項目として追加済みです。
O95: 溶リ判定区分A_06 | AE95: C | AI95: N | BO95: 溶リ判定画面
O96: 溶リ判定_紙使用量 | AE96: N | AI96: N | BO96: 溶リ判定画面
O97: 溶リ判定_プラ使用量 | AE97: N | AI97: N | BO97: 溶リ判定画面
O98: 溶リ判定区分B_01 | AE98: C | AI98: N | BO98: 溶リ判定画面
O99: 溶リ判定区分B_02 | AE99: C | AI99: N | BO99: 溶リ判定画面
O100: 溶リ判定区分C_01 | AE100: C | AI100: N | BO100: 溶リ判定画面
O101: 溶リ判定区分C_02 | AE101: C | AI101: N | BO101: 溶リ判定画面
...

Sheet テーブル項目_見積加工工程
A1: =表紙!A54 -> Webシステム | K1: 文書名 | U1: モジュールID | Z1: =表紙!$AJ$63 -> MS | AE1: モジュール名 | AJ1: =表紙!$AX$63 -> 見積管理 | AS1: 文書番号 | AZ1: Version | BF1: Rev.
K2: =表紙!O64 -> アドオン設計書 | U2: ｻﾌﾞﾓｼﾞｭｰﾙID | Z2: =表紙!$AJ$64 -> MSBB | AE2: ｻﾌﾞﾓｼﾞｭｰﾙ名 | AJ2: =表紙!$AX$64 -> Webシステム | AS2: =表紙!$BL$64 -> M7-US-1140 | AZ2: =表紙!$BU$64 -> 7.0.2 | BF2: =表紙!$CB$64 -> 1
K3: =RIGHT(CELL("filename",$A$1),LEN(CELL("filename",$A$1))-FIND("]",CELL("filename",$A$1))) -> #VALUE! | U3: 表題 | Z3: =表紙!$AJ$65 -> MSBBPA010 | AE3: =表紙!$AQ$65 -> Web見積計算書入力
A5: テーブル名 | O5: 日本語名 | AE5: 種別
O6: 見積加工工程 | AE6: アドオン(新規)
A8: 主キー | D8: 項目名 | O8: 日本語名 | AE8: 型 | AG8: 桁 | AI8: Null | AK8: 説明 | BL8: 値の制限 | BM8: 設定仕様 | BN8: 未設定時の振る舞い | BO8: 見積計算書 画面
A9: 〇 | O9: 見積計算書NO | AE9: C | AI9: N | AK9: 枝番含む | BO9: 1ページ目：メンテ対象選択画面
A10: 〇 | O10: 作業CD | AE10: C | AI10: N | BL10: 作業マスタ(条件=作業CD) | BO10: 第2画面(工程情報画面)
O11: 工程CD | AE11: C | AI11: N | BL11: 工程マスタ | BO11: 第2画面(工程情報画面)
O12: 作業順 | AE12: N | AI12: N | AK12: 工程毎の作業順、システム自動採番 | BO12: 第2画面(工程情報画面)
O13: ワーキンググループＣＤ | AE13: C | AG13: 10 | AI13: Y | AK13: 製造場所に紐づくワーキンググループCD | BO13: 第2画面(工程情報画面)
O14: 製造場所 | AE14: C | AI14: Y | BL14: 汎用マスタ(拠点・外注) | BO14: 第2画面(工程情報画面)
O15: 工程仕様01 | AE15: N | AI15: Y | BL15: 汎用マスタ(工程仕様) | BO15: 第2画面(工程情報画面)
O16: 工程仕様02 | AE16: N | AI16: Y | BL16: 汎用マスタ(工程仕様) | BO16: 第2画面(工程情報画面)
O17: 工程仕様03 | AE17: N | AI17: Y | BL17: 汎用マスタ(工程仕様) | BO17: 第2画面(工程情報画面)
O18: 工程仕様04 | AE18: N | AI18: Y | BL18: 汎用マスタ(工程仕様) | BO18: 第2画面(工程情報画面)
O19: 工程仕様05 | AE19: N | AI19: Y | BL19: 汎用マスタ(工程仕様) | BO19: 第2画面(工程情報画面)
O20: 工程仕様06 | AE20: N | AI20: Y | BL20: 汎用マスタ(工程仕様) | BO20: 第2画面(工程情報画面)
O21: 工程仕様07 | AE21: N | AI21: Y | BL21: 汎用マスタ(工程仕様) | BO21: 第2画面(工程情報画面)
O22: 工程仕様08 | AE22: N | AI22: Y | BL22: 汎用マスタ(工程仕様)
O23: 工程仕様09 | AE23: N | AI23: Y | BL23: 汎用マスタ(工程仕様)
O24: 工程仕様10 | AE24: N | AI24: Y | BL24: 汎用マスタ(工程仕様)
O25: 版NO | AE25: C | AI25: Y | BO25: 第2画面(工程情報画面)
O26: 工程備考１ | AE26: C | AI26: Y | BO26: 第2画面(工程情報画面)
O27: 工程備考２ | AE27: C | AI27: Y | BO27: 第2画面(工程情報画面)
O28: 指示数 | AE28: N | BO28: 第3画面(計算結果画面)
O29: 見積単価 | AE29: N | BO29: 第3画面(計算結果画面)
O30: 見積工賃 | AE30: N | BO30: 第3画面(計算結果画面)
O31: 外注単価 | AE31: N | BO31: 第3画面(計算結果画面)
O32: 外注金額 | AE32: N | BO32: 第3画面(計算結果画面)
O33: 版型仕入 | AE33: N | BO33: 第3画面(計算結果画面)
O34: 版型金額 | AE34: N | BO34: 第3画面(計算結果画面)
O35: 並び順 | AE35: N | AI35: N | AK35: 画面の並び順、システム自動採番
D36: MEMO1 | O36: メモ１ | AE36: C | AG36: 100 | AI36: Y
D37: MEMO2 | O37: メモ２ | AE37: C | AG37: 100 | AI37: Y
D38: MEMO3 | O38: メモ３ | AE38: C | AG38: 100 | AI38: Y
D39: DEL_FLG | O39: 論理削除ＦＬＧ | AE39: F | AI39: N | AK39: 論理削除を示すフラグ
D40: DEL_USR_ID | O40: 論理削除ユーザＩＤ | AE40: C | AG40: 500 | AI40: Y
D41: DEL_USR_NM | O41: 論理削除ユーザ名 | AE41: C | AG41: 100 | AI41: Y
D42: DEL_TS | O42: 論理削除日時 | AE42: TS | AG42: 0 | AI42: Y
D43: INS_USR_ID | O43: 登録ユーザＩＤ | AE43: C | AG43: 500 | AI43: Y
D44: INS_USR_NM | O44: 登録ユーザ名 | AE44: C | AG44: 100 | AI44: Y
D45: INS_TS | O45: 登録日時 | AE45: TS | AG45: 0 | AI45: Y
D46: INS_FUNC_ID | O46: 登録機能ＩＤ | AE46: C | AG46: 50 | AI46: Y
D47: UPD_CNTR | O47: 更新カウンタ | AE47: N | AG47: 9,0 | AI47: Y
D48: UPD_USR_ID | O48: 更新ユーザＩＤ | AE48: C | AG48: 500 | AI48: Y
D49: UPD_USR_NM | O49: 更新ユーザ名 | AE49: C | AG49: 100 | AI49: Y
D50: UPD_TS | O50: 更新日時 | AE50: TS | AG50: 0 | AI50: Y
D51: UPD_FUNC_ID | O51: 更新機能ＩＤ | AE51: C | AG51: 50 | AI51: Y
D52: UPD_SRV_REQ_NO | O52: 更新リクエストＮＯ | AE52: C | AG52: 50 | AI52: Y

Sheet |→補足シート

Sheet 現行画面
A1: =表紙!A54 -> Webシステム | K1: 文書名 | U1: モジュールID | Z1: =表紙!$AJ$63 -> MS | AE1: モジュール名 | AJ1: =表紙!$AX$63 -> 見積管理 | AS1: 文書番号 | AY1: Version | BE1: Rev.
K2: =表紙!O64 -> アドオン設計書 | U2: ｻﾌﾞﾓｼﾞｭｰﾙID | Z2: =表紙!$AJ$64 -> MSBB | AE2: ｻﾌﾞﾓｼﾞｭｰﾙ名 | AJ2: =表紙!$AX$64 -> Webシステム | AS2: =表紙!$BL$64 -> M7-US-1140 | AY2: =表紙!$BU$64 -> 7.0.2 | BE2: =表紙!$CB$64 -> 1
K3: =RIGHT(CELL("filename",$A$1),LEN(CELL("filename",$A$1))-FIND("]",CELL("filename",$A$1))) -> #VALUE! | U3: 表題 | Z3: =表紙!$AJ$65 -> MSBBPA010 | AE3: =表紙!$AQ$65 -> Web見積計算書入力
A5: 画面イメージ
C7: 第1画面
C46: 第2画面 | AZ46: 第3画面
C82: 第4画面
C118: 第5画面
