Workbook
Name Rev.: [2]表紙!$U$22
Name Rev.: 表紙!$U$22
Name Revision: #REF!
Name Ver.: #REF!
Name Ver.: 表紙!$AE$26
Name Version: #REF!
Name ご確認者: #REF!
Name ご確認者: 表紙!$AG$40
Name ご確認日: #REF!
Name ご確認日: 表紙!$AG$42
Name サブシステム名: #REF!
Name サブシステム名: 表紙!$U$28
Name システム名: #REF!
Name システム名: 表紙!$U$26
Name プロジェクト名: #REF!
Name プロジェクト名: 表紙!$U$18
Name 開発区分: #REF!
Name 開発区分: 表紙!$U$36
Name 機能ＩＤ: #REF!
Name 機能ＩＤ: 表紙!$U$32
Name 機能区分: #REF!
Name 機能区分: 表紙!$U$34
Name 機能名称: #REF!
Name 機能名称: 表紙!$U$30
Name 顧客名: #REF!
Name 顧客名: 表紙!$U$16
Name 最終更新者: #REF!
Name 最終更新者: 表紙!$AB$40
Name 最終更新日: #REF!
Name 最終更新日: 表紙!$AB$42
Name 作成者: #REF!
Name 作成者: 表紙!$W$40
Name 作成日: #REF!
Name 作成日: 表紙!$W$42
Name 章: #REF!
Name 章: 表紙!$M$10
Name 発行日: #REF!
Name 文書番号: #REF!
Name 文書名: 表紙!$M$10
Name 文書名: #REF!

Sheet 目次
A1: アドオン設計書作成ガイド
C3: ■アドオン設計と成果物について
D4: ・システム設計フェーズとソフトウェア設計フェーズでアドオンの処理仕様を定義する
D5: ・システム設計フェーズとソフトウェア設計フェーズの成果物がアドオン設計書であり、ソフトウェア製作フェーズのインプットとなる
C7: ■各設計フェーズ毎のアドオン設計書作成範囲
D8: ・システム設計フェーズ：他機能との関連を定義するとともに、画面や帳票、ファイル入出力を中心とした外部入出力の設計を行う
D9: ・ソフトウェア設計フェーズ：内部処理を中心とした設計を行う
U11: ◎ | W11: … | X11: システム設計フェーズで作成
U12: ○ | W12: … | X12: システム設計フェーズで基本仕様を定義して、ソフトウェア設計フェーズで詳細化する
U13: △ | W13: … | X13: 必要に応じて（例えば標準仕様から変更がない場合は不要）
U14: ‐ | W14: … | X14: 不要
W15: … | X15: ソフトウェア設計フェーズで作成
D17: 各設計書と作成対象シートのマトリックス | S17: ※カスタマイズ：標準機能に機能を追加する アドオン：新規で機能を開発する
D18: EXCELシート | N18: 画面設計書 | W18: バッチ設計書 | AF18: 帳票設計書 | AO18: ＢＩ設計書 | AT18: .Net設計書 | BB18: EXCELシート | BL18: WebDB設計書 | BR18: 帳票設計書 | BX18: 汎用申請設計書
N19: カスタマイズ | S19: アドオン | W19: カスタマイズ | AB19: アドオン | AF19: カスタマイズ | AK19: アドオン | AO19: アドオン | AT19: アドオン | BL19: アドオン | BR19: アドオン | BX19: アドオン
D20: 概要 | N20: ◎ | O20: ※1 | S20: ◎ | W20: ◎ | X20: ※1 | AB20: ◎ | AF20: ◎ | AG20: ※1 | AK20: ◎ | AO20: ◎ | AT20: ◎ | BB20: 機能概要 | BL20: ◎ | BR20: ◎ | BX20: ◎
D21: レイアウト | N21: ◎ | O21: ※2 | S21: ◎ | W21: ‐ | AB21: ‐ | AF21: ◎ | AG21: ※2 | AK21: ◎ | AO21: ◎ | AT21: ◎ | BB21: アプリケーションフロー | BL21: ◎ | BR21: ー | BX21: ◎
D22: 項目説明 | N22: △ | S22: ○ | W22: ‐ | AB22: ‐ | AF22: △ | AK22: ○ | AO22: ○ | AT22: ○ | BB22: データベース設定 | BL22: ◎ | BR22: ー | BX22: ◎
D23: 引数説明 | N23: ‐ | S23: ‐ | W23: △ | AB23: ◎ | AF23: ‐ | AK23: ‐ | AO23: ‐ | AT23: ◎ | BB23: フィールド設定 | BL23: ◎ | BR23: ー | BX23: ◎
D24: 処理概要 | N24: ◎ | S24: ◎ | W24: ◎ | AB24: ◎ | AF24: ◎ | AK24: ◎ | AO24: ◎ | AT24: ◎ | BB24: 一覧表示画面設定 | BL24: ◎ | BR24: ー | BX24: ◎
D25: 処理詳細 | BB25: 表示編集画面設定 | BL25: ◎ | BR25: ー | BX25: ◎
D26: 処理・サービス関連図 | N26: △ | S26: ◎ | W26: △ | AB26: ◎ | AF26: ‐ | AK26: ‐ | AO26: ‐ | AT26: ◎ | BB26: 明細画面設定 | BL26: △ | BN26: ※3 | BR26: ー | BX26: △ | BZ26: ※3
D27: 検索入出力仕様 | N27: △ | S27: ○ | W27: △ | AB27: ○ | AF27: ‐ | AK27: ‐ | AO27: ‐ | AT27: ○ | BB27: 集計表示設定 | BL27: △ | BN27: ※4 | BR27: ー | BX27: △ | BZ27: ※4
D28: 更新入出力仕様 | N28: △ | S28: ○ | W28: △ | AB28: ○ | AF28: ‐ | AK28: ‐ | AO28: ‐ | AT28: ○ | BB28: 絞り込み条件設定 | BL28: △ | BN28: ※5 | BR28: ー | BX28: △ | BZ28: ※5
D29: ファイル入出力仕様 | N29: △ | S29: △ | W29: ‐ | AB29: ‐ | AF29: ‐ | AK29: ‐ | AO29: ‐ | AT29: △ | BB29: その他設定 | BR29: ー
D30: 画面遷移 | N30: △ | S30: ◎ | W30: ‐ | AB30: ‐ | AF30: ‐ | AK30: ‐ | AO30: ‐ | AT30: ◎ | BB30: 帳票イメージ | BL30: ー | BR30: ◎ | BX30: ー
D31: メッセージ一覧 | N31: △ | S31: △ | W31: △ | AB31: △ | AF31: ‐ | AK31: ‐ | AO31: ‐ | AT31: △ | BB31: 項目設計 | BL31: ー | BR31: ◎ | BX31: ー
D32: 補足説明 | N32: △ | S32: △ | W32: △ | AB32: △ | AF32: △ | AK32: △ | AO32: △ | AT32: △ | BB32: 補足説明 | BL32: △ | BR32: △ | BX32: △
D33: サービス呼出編集仕様 | N33: - | S33: - | W33: - | AB33: - | AF33: - | AK33: - | AO33: - | AT33: - | BB33: 補足説明(詳細)
D35: ※1 | G35: 別シートでカスタマイズ内容を記載する | BB35: ※3 | BE35: 単票画面は記載しない
D36: ※2 | G36: 吹き出しでカスタマイズ内容を記載する | BB36: ※4 | BE36: 集計・グラフ機能を使用する場合に記載する
BB37: ※5 | BE37: 共通設定のみ記載する(個別設定は、記載しない)

Sheet 表紙
AW2: サブモジュール
AW3: MA_マスタ管理
AW4: MB_業務共通
AW5: MG_原価管理
AW6: MSBA_需給管理
M7: 基本設計 | AW7: MSBB_販売管理
AW8: MSBC_生産管理
AW9: MSBD_購買管理
M10: アドオン設計書 | AW10: MSBE_在庫物流管理
AW11: MSBF_品質管理
AW12: MSBG_債権管理
AW13: MSBH_債務管理
AW14: MSBI_締処理
AW15: MSUA_リスト・入力補助
M16: 顧客 | U16: 株式会社クラウン・パッケージ | AW16: PF_ESBアダプタ
M18: プロジェクト名 | U18: 基幹システム刷新PJ | AW18: 機能区分
AW19: 画面
M20: 文書番号 | AW20: 帳票
AW21: バッチ
M22: Ｒｅｖ． | U22: {=MAX(_xlfn.NUMBERVALUE(改訂!A7:E48))} -> 1 | AW22: マスタ
M24: 機密性区分 | U24: 取扱注意（Ｃ） | AW24: 開発区分
AW25: カスタマイズ
M26: システム名 | U26: mcframe7 | AC26: Ver. | AE26: 7.0.2 | AW26: アドオン
AW27: －
M28: サブモジュール | U28: MSBB_販売管理
M30: 機能名 | U30: =M50 -> Web取引先マスタ
M32: 機能ID | U32: =G50 -> MSBBPA110
M34: 機能区分 | U34: 画面
M36: 開発区分 | U36: アドオン
W39: 作成 | AB39: 最終更新 | AG39: ご確認
W40: MDSOL
W42: 44824
A48: 文書番号 | G48: 画面ID | M48: 画面名 | V48: Version | AB48: Revision
A50: M7-US-1140 | G50: MSBBPA110 | M50: Web取引先マスタ | V50: 1.0.0 | AB50: r01.00
A53: 共通（元データ）
A54: Webシステム | K54: 文書名 | U54: モジュールID | Z54: MS | AE54: モジュール名 | AJ54: Webシステム | AS54: 文書番号 | AZ54: Version | BF54: Rev.
K55: 画面説明書 | U55: ｻﾌﾞﾓｼﾞｭｰﾙID | Z55: MSBB | AE55: ｻﾌﾞﾓｼﾞｭｰﾙ名 | AJ55: 販売Webシステム | AS55: M7-US-1140 | AZ55: 1.0.0 | BF55: r00.00
K56: 表紙 | U56: 表題 | Z56: MSBBPA110 | AE56: Web取引先マスタ
A57: 共通（リンク用）
A58: =A54 -> Webシステム | K58: 文書名 | U58: モジュールID | Z58: =Z54 -> MS | AE58: モジュール名 | AJ58: =AJ54 -> Webシステム | AS58: 文書番号 | AZ58: Version | BF58: Rev.
K59: =文書名 -> アドオン設計書 | U59: ｻﾌﾞﾓｼﾞｭｰﾙID | Z59: =Z55 -> MSBB | AE59: ｻﾌﾞﾓｼﾞｭｰﾙ名 | AJ59: =AJ55 -> 販売Webシステム | AS59: =AS55 -> M7-US-1140 | AZ59: =AZ55 -> 1.0.0 | BF59: =BF55 -> r00.00
K60: =RIGHT(CELL("filename",$A$1),LEN(CELL("filename",$A$1))-FIND("]",CELL("filename",$A$1))) -> 表紙 | U60: 表題 | Z60: =Z56 -> MSBBPA110 | AE60: =AE56 -> Web取引先マスタ
A62: 概要シート用
A63: =A58 -> Webシステム | O63: 文書名 | AC63: モジュールID | AJ63: =Z58 -> MS | AQ63: モジュール名 | AX63: =AJ58 -> Webシステム | BL63: 文書番号 | BU63: Version | CB63: Rev.
O64: =K59 -> アドオン設計書 | AC64: サブモジュールID | AJ64: =Z59 -> MSBB | AQ64: サブモジュール名 | AX64: =AJ59 -> 販売Webシステム | BL64: =AS59 -> M7-US-1140 | BU64: 7.0.2 | CB64: {=MAX(_xlfn.NUMBERVALUE(改訂!A7:E48))} -> 1
O65: =RIGHT(CELL("filename",$A$1),LEN(CELL("filename",$A$1))-FIND("]",CELL("filename",$A$1))) -> 表紙 | AC65: 表題 | AJ65: =Z60 -> MSBBPA110 | AQ65: =AE60 -> Web取引先マスタ

Sheet 改訂
A1: 第7章 | K1: 改訂 | AU1: 作成者 | AZ1: MDSOL | BE1: 作成日 | BJ1: =表紙!W42 -> 44824 | BP1: Rev.
AU2: 修正者 | BE2: 改訂日 | BP2: =表紙!CB64 -> 1
A5: Rev. | F5: 改定内容 | BC5: 頁 | BM5: 変更日 変更者 | BR5: 確認日 確認者
A7: 1 | F7: 新規作成

Sheet 概要
A1: =表紙!A54 -> Webシステム | O1: 文書名 | AC1: モジュールID | AJ1: =表紙!AJ63 -> MS | AQ1: モジュール名 | AX1: =表紙!AX63 -> Webシステム | BL1: 文書番号 | BU1: Version | CB1: Rev.
O2: =表紙!O64 -> アドオン設計書 | AC2: サブモジュールID | AJ2: =表紙!AJ64 -> MSBB | AQ2: サブモジュール名 | AX2: =表紙!AX64 -> 販売Webシステム | BL2: =表紙!BL64 -> M7-US-1140 | BU2: =表紙!BU64 -> 7.0.2 | CB2: =表紙!CB64 -> 1
O3: =RIGHT(CELL("filename",$A$1),LEN(CELL("filename",$A$1))-FIND("]",CELL("filename",$A$1))) -> 概要 | AC3: 表題 | AJ3: =表紙!AJ65 -> MSBBPA110 | AQ3: =表紙!AQ65 -> Web取引先マスタ
AO5: 概要
B7: 【業務要件】
C8: カスタマイズ | G8: 内容
C9: No.
C10: 4 | G10: 見積Webシステムを構築する
H11: 主要機能
H12: ⑦得意先マスタ | M12: ・・・＞ | O12: システム設計フェーズ変更点：得意先→取引先
C14: 35 | G14: 消込条件追加
H15: ①取引先の口座を管理する(得意先マスタ項目追加:得意先マスタのアドオンに含む)
C17: 75 | G17: 取引先マスタのmcframeへの連携
H18: Webにて取引先マスタ(得意先マスタ)を実装する
C20: 40 | G20: 発注一覧登録、発注登録 共通帳票印刷共通ロジック
H21: 発注先のFSC認証番号(取引先マスタ 発注先タブのメモ３)の取得、出力 | AD21: ・・・＞mcframe7 メモ3に連携する
B24: 【機能概要】
C25: Web取引先の情報のメンテ画面
B27: 【前提条件】
C28: Web取引先とmcframe7取引先のデータ転送は、Web→mcframe7への一方通行とする
C29: 得意先は総務、加工先は業務での画面入力となるが、ログイン(担当者)よる各項目の入力使用可否は制御しない→運用ルールを規定し対応する
C30: mcframe7の取引先マスタと連携するため、mcframe7の制限事項に反する登録は不可とする
D31: →下記項目の変更時、エラーとする
B51: 【説明】
C52: Web取引先の情報を登録する画面
B54: 【目的】
C55: Web取引先に関する情報を登録・訂正する
B57: 【処理関連図/サービス関連図】
C58: ※処理・サービス関連図シートに詳細記載
B60: 【オペレーション一覧】
C61: 操作種別による制御(事前申請、登録、訂正、削除、参照)
B63: 【SQLID一覧】
C64: なし
B66: 【ソート順】
C67: なし
B69: 【データアクセスコントロール】
C70: 拠点による制御となる、ただし本機能は変更可能とする
C71: ※詳細は、【MSBBPA000】_共通設計書_アドオン(Webシステム共通仕様)にて定義
B73: 【自由記述】
C74: なし

Sheet 画面イメージ
A1: =表紙!A54 -> Webシステム | K1: 文書名 | U1: モジュールID | Z1: =表紙!$AJ$63 -> MS | AE1: モジュール名 | AJ1: =表紙!$AX$63 -> Webシステム | AS1: 文書番号 | AZ1: Version | BF1: Rev.
K2: =表紙!O64 -> アドオン設計書 | U2: ｻﾌﾞﾓｼﾞｭｰﾙID | Z2: =表紙!$AJ$64 -> MSBB | AE2: ｻﾌﾞﾓｼﾞｭｰﾙ名 | AJ2: =表紙!$AX$64 -> 販売Webシステム | AS2: =表紙!$BL$64 -> M7-US-1140 | AZ2: =表紙!$BU$64 -> 7.0.2 | BF2: =表紙!$CB$64 -> 1
K3: =RIGHT(CELL("filename",$A$1),LEN(CELL("filename",$A$1))-FIND("]",CELL("filename",$A$1))) -> 画面イメージ | U3: 表題 | Z3: =表紙!$AJ$65 -> MSBBPA110 | AE3: =表紙!$AQ$65 -> Web取引先マスタ
A5: 画面イメージ
B7: ≫凡例
Q8: ・・・ | S8: ボタン
C9: 見積計算書№ | Q9: ・・・ | S9: 検索項目(検索画面表示選択)
C10: 品名 | Q10: ・・・ | S10: 入力項目
C11: 取引先 | Q11: ・・・ | S11: 表示項目(取引先名称、原紙名等)
C12: 操作種別 | I12: ●登録 | M12: ○訂正 | Q12: ・・・ | S12: 選択項目(一つのみ選択可能)
C13: 受注区分 | Q13: ・・・ | S13: 選択項目(一つのみ選択可能)
C14: 作業順 | I14: ☑AAA | M14: ☑BBB | Q14: ・・・ | S14: 選択項目(複数選択可能)
C18: 取引先マスタ | V18: システム管理者のみ
V19: ↓
D20: 操作種別 | J20: ●事前申請 | N20: ○登録 | R20: ○訂正 | V20: ○削除 | Z20: ○参照 | BP20: 操作種別 | BV20: ●登録 | BZ20: ○訂正 | CD20: ○削除 | CH20: ○参照
AQ21: ＸＸＸＸＸＸＸＸＸ１ＸＸＸＸＸＸＸＸＸ２ＸＸＸＸ
N22: 取引先CD | AQ22: 1234567890123456789012345678901234567890 | BZ22: 取引先
D25: ステータス | J25: 事前登録・本登録
D27: 基本情報 | J27: 取引分類 | BP27: 基本情報 | BV27: 取引先分類 | GA27: MDSOL 野村 2022/10/25 訂正は、得意先担当マスタで実施する想定です。
D28: 取引先名 | J28: 48バイト | X28: 取引先略称 | AD28: 24バイト | AQ28: 文字数に関して：現行34バイト | BP28: 取引先分類1 | BV28: 管轄WG | CJ28: 取引先分類2 | CP28: 得意先区分 | GI28: 人事異動等で必要となる一覧での変更が可能です。
D29: 拠点CD | X29: 標準企業コード | AD29: 20文字 | AQ29: 48バイト、24バイトとする。 | BP29: 取引先分類3 | BV29: ユーザ・コンバータ | CJ29: 取引先分類4 | CP29: 業種 | GI29: 日付(FROM～TO)の一括設定機能も持ちます。
D30: 法人番号 | J30: 13文字 | X30: 法人番号区分 | AD30: 0:法人,1:個人 | BP30: 取引先分類5 | BV30: 顧客ランク | CJ30: 取引先分類6 | CP30: 債権区分 | GI30: ※簡易的な手順は、【MSBBBA020】_バッチ設計書_アドオン(取引先マスタ連携)に記載しています。
D31: 地方公共団体CD | J31: 5文字 | X31: でんさい利用者番号 | AD31: (メモ2連携) | AJ31: ←請求利用者番号(9桁のコード) | BP31: 取引先分類7 | BV31: 締め日 | CJ31: 取引先分類8
BP32: 取引先分類9 | CJ32: 取引先分類10 | GA32: CP指摘 2022/10/27 落合 売上担当者の項目の右側に、「変更はMcFrame7 得意先担当マスタにて」と、注記をつけてください
D33: 郵便番号 | J33: 10文字 | GB33: MDSOL 野村 2022/10/31 追記しました。 | GP33: 2022/11/01 落合 問題なし
D34: 都道府県 | J34: 40文字 | X34: 市区町村 | AD34: 40文字 | BP34: 販売分析 | EC34: MDSOL 野村 2022/10/25 法人番号区分(0:法人,1:個人)を追加しました。
D35: 町域・番地 | J35: 40文字 | X35: 建物など | AD35: 40文字 | BP35: 販売分析１
D36: ＴＥＬ | J36: 30文字 | X36: ＦＡＸ | AD36: 30文字 | BP36: 販売分析２
D37: 地域CD | BP37: 販売分析３
FU38: MDSOL 野村 2022/10/25 | GK38: CP指摘 2022/10/29 落合 不要になっている項目はセッションの中で不要と判断された項目でしょうか？
D39: 営業担当 | V39: ※変更はMcFrame7 得意先担当マスタにて | FV39: 内容確認し必要部分を追加しました、確認願います | GL39: MDSOL 野村 2022/10/31 はい。Backlogとセッションで現行得意先とのマッピングを実施し要否確認した認識です。→必要ならご連絡ください。
D40: 業務担当
BP41: ■得意先 | BV41: ■売掛先 | CB41: ■請求先 | CH41: ■入金先 | CN41: ■納品先 | FV41: 回覧区分 | GD41: … | GF41: 追加済
FV42: 納品計算書種類 | GD42: …
D43: ■得意先 | H43: ■売掛先 | L43: ■請求先 | P43: ■入金先 | T43: □納品先 | BP43: 請求先 | FV43: 納品計算書様式 | GD43: … | GF43: 不要と判断 | GK43: 様式は1種を想定
D44: □発注先 | H44: □買掛先 | L44: □支払予定管理先 | T44: □支払先 | FV44: 計算書明細順 | GD44: … | GF44: 不要と判断 | GK44: 納品計算書の並びは、得意先ＣＤ、納入日、受注NO、受注明細NO、売上実績NOを想定
FV45: 計算書発行区分 | GD45: … | GF45: 追加済 | GK45: 以前要望で追加した「納品計算出力区分」と重複か。
FV46: 計算書寸法表示 | GD46: … | GF46: 追加済 | GK46: 納品計算書出力区分「加工品構成印字」として追加。
D47: ■得意先 | J47: ■売掛先 | P47: ■請求先 | V47: ■入金先 | AB47: □納品先 | BP47: ■得意先 | BV47: ■売掛先 | CB47: ■請求先 | CH47: ■入金先 | CN47: ■納品先 | GK47: 以前、提供いただいた納品計算書の仕様に構成印字等は有りませんでしたが、帳票にどのように影響するでしょうか。
D48: □発注先 | J48: □買掛先 | P48: □支払予定管理先 | V48: □支払先 | FV48: 計算書出力日区分 | GD48: … | GF48: 不要と判断 | GK48: 新基幹システムでは、ユーザー判断で出力を想定
BP49: 入金先 | CQ49: 債権与信管理先
D50: 得意先CD(親) | AD50: ﾕｰｻﾞｰ・ｺﾝﾊﾞｰﾀ区分 | AJ50: (0：コンバーター １：ユーザー ２：準ユーザー) | BP50: 請求締日1 | FV50: 袋システム用は不要と判断
D51: 売掛先 | AD51: □与信管理先
BP52: 請求書印刷区分 | BV52: (0:する 1:しない) | CJ52: 請求書封緘区分 | CP52: (0:する 1:しない) | CX52: 電子請求 請求書 | DD52: (0:する1:しない)
D53: 得意先部署 | X53: 得意先担当者 | AR53: 得意先担当者敬称 | FV53: 領収書発行区分 | GD53: … | GF53: 追加済 | GK53: 0:する 1:しない | GQ53: 切り分けする・しないは、必要か。※レイアウトが2枚組から1帳票となった。
D54: 容器リ法対象 | J54: (0:非該当1:該当) | BP54: 請求書宛先 | CJ54: 請求書送付担当者 | FV54: 受注明細出力区分 | GD54: … | GF54: 不要と判断 | GK54: 該当帳票無し
BP55: 請求書郵便番号 | FV55: 売上明細出力区分 | GD55: … | GF55: 不要と判断 | GK55: 該当帳票無し
BP56: 請求書都道府県 | CJ56: 請求書市区町村 | FV56: 在庫保管期間 | GD56: … | GF56: 不要と判断 | GK56: 備考はフリー入力
D57: 売上計算 | BP57: 請求書町域・番地 | CJ57: 請求書建物など | FV57: 製品明細区分 | GD57: … | GF57: 不要と判断 | GK57: 要件未確認
D58: 売上計上区分 | J58: (0:設定なし、2:枚) | Q58: ※シート売りで㎡を枚単価に変換 | AB58: ｼｰﾄ枚売上時の計算方法
D59: 売上計算区分(㎡) | Q59: (主にシート売上に使用) | AB59: 売上計算区分(枚) | AP59: (主に加工品、数量単位と単価単位が同じ場合) | FV59: 請求書印刷 | GD59: … | GF59: 追加済 | GK59: 0:する 1:しない | GQ59: 電子請求 請求書は区分となった。
D60: 端数計算処理区分 | AB60: 全判売区分 | AJ60: (1:シート売上寸法、数量を全判で表示) | FV60: 請求書郵送 | GD60: … | GF60: 追加要否判断
D61: スリッター請求区分 | J61: (0:取れない、1:幅のみ、2:流れのみ、3:幅流れとも) | BP61: ■得意先 | BV61: ■売掛先 | CB61: ■請求先 | CH61: ■入金先 | CN61: ■納品先 | FV61: 請求書FAX | GD61: … | GF61: 追加要否判断
D62: スリッター請求単価 | R62: スリッター最大流 | AA62: (入力された値より小さい時) | FV62: 請求書封緘区分 | GD62: … | GF62: 追加済 | GK62: ひげ情報の印字に使用する
D63: 印刷最低請求 | J63: (0:不可、1:可) | W63: 未満 | AA63: (1:㎡、8:m) | BP63: 振込人名 | CD63: 銀行 | CQ63: 銀行支店 | DD63: 振込元口座 | FV63: 請求通知/営業 | GD63: … | GF63: 不要と判断 | GK63: 新基幹システムでの該当機能無し(PE汎用申請の判断材料になるか)
D64: 貼合最低請求 | J64: (0:不可、1:可) | W64: 未満 | AA64: (1:㎡、8:m) | AF64: 増@ | BP64: 仮口座区分 | BV64: 0:本口座 1:仮口座 | CD64: 本口座登録日 | FV64: 請求通知/総務 | GD64: … | GF64: 不要と判断 | GK64: 新基幹システムでの該当機能無し(PE汎用申請の判断材料になるか)
D65: 貼合増請求表示 | J65: (0:別途請求、1:シート単価に上乗せ) | W65: ※大阪のみ
D66: 加工見積最低 | J66: (0:別途請求、1:加工単価に上乗せ) | W66: ※名古屋のみ | AB66: 新シート単価適用基準 | BP66: 集金区分 | BV66: １：集金 | CD66: 集金予定日 | CQ66: 振出人 | DD66: 手形回り区分 | DJ66: (0:ｼﾞｺ 1:ﾏﾜﾘ)
D68: 納品書 | AR68: 見積計算書(提出用) | BP68: 領収書発行区分 | BV68: (0:ｽﾙ 1:ｼﾅｲ) | FV68: 下記、項目追加しました
D69: 納品書出力区分 | J69: (0:ｶｺｳﾋﾝ ｺｳｾｲ,ｽﾝﾎﾟｳ ﾅｼ 1:ｱﾘ) | AR69: 寸法印字区分 | FW69: 仮口座区分
D70: 納品書発行区分 | J70: (0:ｽﾙ 1:ｼﾅｲ 2:ﾊｯｿｳﾌﾖｳﾄｲﾝｼﾞ) | BP70: 領収書宛先 | CJ70: 領収書送付担当者 | FW70: 本口座登録日
D71: 特伝区分 | J71: (0:ﾂｳｼﾞｮｳ 1:ﾄｸﾃﾞﾝ 2:ｺｸﾖ) | X71: 夜積区分 | AE71: (0:ｲｶﾞｲ 1:ﾖﾂﾞﾐ) | BP71: 領収書郵便番号 | FW71: 親得意先CD
BP72: 領収書都道府県 | CJ72: 領収書市区町村 | FW72: 納品計算書発行区分
D73: 納品計算書 | BP73: 領収書町域・番地 | CJ73: 領収書建物など
D74: 納品計算出力区分 | J74: 電子/FAX/郵送/特電/営業回覧/本支店用 | X74: 納品計算書発行区分 | AR74: 納品計算出力区分 | AY74: 1:加工品構成印字
BP75: 回収備考
D76: 宛先 | X76: 送付担当者
D77: 郵便番号
D78: 都道府県 | X78: 市区町村 | BP78: ■得意先 | BV78: ■売掛先 | CB78: ■請求先 | CH78: ■入金先 | CN78: ■納品先
D79: 町域・番地 | X79: 建物など
BP80: 物流グループCD
D81: 回覧区分 | J81: 1:回覧(営業に回覧) | X81: 電子請求納品計算書 | AE81: (0:する1:しない) | BP81: 納品先部署 | CJ81: 納品先担当者
CJ82: 納品先担当者敬称
BP83: トラック長制限 | BV83: 数値2桁 | DD83: CP指摘 2022/09/23 落合 項目追加：出荷予定時間初期値
BP84: 納入時間制限 | BV84: 数値2桁 | BY84: ～ | BZ84: 数値2桁
BP85: (FROM～TO) | CJ85: 出荷予定時間 | DE85: MDSOL 野村 2022/10/25
DF86: 項目追加しました
DG87: 中身は出荷条件となります。
DG88: 受注入力で納品先を選択後の初期値に連携されます
DE89: 2022/11/01 落合 問題なし
C102: 発注先設定
D104: ■得意先 | J104: ■売掛先 | P104: ■請求先 | V104: ■入金先 | AB104: □納品先
D105: ■発注先 | J105: ■買掛先 | P105: ■支払予定管理先 | V105: ■支払先
D107: 発注先パターン | Q107: □メーカ | U107: □FSC認証先区分
D109: 買掛先
D110: 発注先部署 | X110: 発注先担当者 | AR110: 発注先担当者敬称
D111: 仕入先FSC認許No | J111: (メモ3連携) | X111: FSC加工先 | AD111: (1:該当)
D113: □購買単価変更許可FLG | N113: □下請対象FLG | Z113: □有償支給先FLG | AL113: □買戻義務FLG
D114: □納期回答確認FLG | N114: □配送要否FLG | CB114: MDSOL回答 2022/11/11(内部指摘事項対応)
CC115: 発注先に配送要否ＦＬＧ | CI115: 追加
D116: 仕入税CD | Q116: □仕入税優先FLG | X116: 仕入金額端数処理区分 | AR116: 仕入税額端数処理区分
D117: 支給積送管理区分 | X117: 仕入ロット明細分割区分
D118: 仕入計上区分 | X118: 外注単価区分 | AR118: 支給計上区分
D119: 支給税CD | Q119: □支給税優先FLG | X119: 仕入金額端数処理区分 | AR119: 仕入税額端数処理区分
D122: ■得意先 | J122: ■売掛先 | P122: ■請求先 | V122: ■入金先 | AB122: □納品先
D123: ■発注先 | J123: ■買掛先 | P123: ■支払予定管理先 | V123: ■支払先
D125: 支払予定管理先 | AE125: 債務部門CD
D128: ■得意先 | J128: ■売掛先 | P128: ■請求先 | V128: ■入金先 | AB128: □納品先
D129: ■発注先 | J129: ■買掛先 | P129: ■支払予定管理先 | V129: ■支払先
D131: 支払先 | AE131: 支払予定管理先担当部門CD
...

Sheet レイアウト(旧)
A1: =表紙!A54 -> Webシステム | K1: 文書名 | U1: モジュールID | Z1: =表紙!$AJ$63 -> MS | AE1: モジュール名 | AJ1: =表紙!$AX$63 -> Webシステム | AS1: 文書番号 | AZ1: Version | BF1: Rev.
K2: =表紙!O64 -> アドオン設計書 | U2: ｻﾌﾞﾓｼﾞｭｰﾙID | Z2: =表紙!$AJ$64 -> MSBB | AE2: ｻﾌﾞﾓｼﾞｭｰﾙ名 | AJ2: =表紙!$AX$64 -> 販売Webシステム | AS2: =表紙!$BL$64 -> M7-US-1140 | AZ2: =表紙!$BU$64 -> 7.0.2 | BF2: =表紙!$CB$64 -> 1
K3: =RIGHT(CELL("filename",$A$1),LEN(CELL("filename",$A$1))-FIND("]",CELL("filename",$A$1))) -> レイアウト(旧) | U3: 表題 | Z3: =表紙!$AJ$65 -> MSBBPA110 | AE3: =表紙!$AQ$65 -> Web取引先マスタ
A5: 画面イメージ
B7: ≫凡例
Q8: ・・・ | S8: ボタン
C9: 見積計算書№ | Q9: ・・・ | S9: 検索項目(検索画面表示選択)
C10: 品名 | Q10: ・・・ | S10: 入力項目
C11: 得意先 | Q11: ・・・ | S11: 表示項目(得意先名称、原紙名等)
C12: 操作種別 | I12: ●登録 | M12: ○訂正 | Q12: ・・・ | S12: 選択項目(一つのみ選択可能)
C13: 受注区分 | Q13: ・・・ | S13: 選択項目(一つのみ選択可能)
C14: 作業順 | I14: ☑AAA | M14: ☑BBB | Q14: ・・・ | S14: 選択項目(複数選択可能)
C16: １ページ目
D20: 操作種別 | J20: ●登録 | N20: ○訂正 | R20: ○削除 | V20: ○参照
D22: 得意先 | J22: (得意先名:オートフィルタ)
D27: ステータス | X27: 得意先マスタ登録票
D29: 基本情報
E30: 基本情報 | K30: 取引先分類
D32: 得意先名 | J32: 100文字
D34: 得意先別名１ | J34: 100文字 | X34: 得意先別名２ | AD34: 100文字
D35: 得意先別名３ | J35: 100文字 | X35: 得意先別名４ | AD35: 100文字
D37: 法人番号 | J37: 13文字 | X37: 標準企業コード | AD37: 20文字
D39: 郵便番号 | J39: 10文字
D40: 住所１ | J40: 40文字 | X40: 住所２ | AD40: 40文字
D41: 住所３ | J41: 40文字 | X41: 住所４ | AD41: 40文字
D42: ＴＥＬ | J42: 30文字 | X42: ＦＡＸ | AD42: 30文字
D44: 得意先区分 | X44: 地域CD
D46: 詳細情報
D47: ■ | E47: 得意先 | V47: □ | W47: 売掛先 | AB47: □ | AC47: 請求先 | AH47: □ | AI47: 入金先 | AN47: □ | AO47: 納品先
E48: 得意先 | K48: 売上計算 | Q48: 得意先情報
D50: 営業担当
D51: 業務担当
D72: 納品計算出力区分
J73: 電子
J74: FAX
J75: 郵送 | P75: <補足>
J76: 特電 | P76: 電子の場合はPDFへ出力後ナビエクスプレスへアップロードを行う。
J77: 営業回覧 | P77: ナビエクスプレス側でPDFを得意先ごとに振り分けメールで送信している。
J78: 本支店用
D87: 詳細情報
D88: ■ | E88: 得意先 | V88: □ | W88: 売掛先 | AB88: □ | AC88: 請求先 | AH88: □ | AI88: 入金先 | AN88: □ | AO88: 納品先
E89: 得意先 | K89: 売上計算 | Q89: 得意先情報
D91: スリッター請求区分 | N91: (0:取れない、1:幅のみ、2:流れのみ、3:幅流れとも)
D92: スリッター請求単価 | N92: スリッター最大流 | W92: (入力された値より小さい時)
D94: 印刷最低請求 | N94: (0:不可、1:可) | W94: 未満 | AA94: (1:㎡、8:m)
D95: 貼合最低請求 | N95: (0:不可、1:可) | W95: 未満 | AA95: (1:㎡、8:m) | AF95: 増@
D96: 貼合増請求表示 | N96: (0:別途請求、1:シート単価に上乗せ)
D97: 加工見積最低 | N97: (0:別途請求、1:加工単価に上乗せ)
D138: 詳細情報
D139: ■ | E139: 得意先 | V139: □ | W139: 売掛先 | AB139: □ | AC139: 請求先 | AH139: □ | AI139: 入金先 | AN139: □ | AO139: 納品先
E140: 得意先 | K140: 売上計算 | Q140: 得意先情報

Sheet 項目説明
A1: =表紙!A54 -> Webシステム | K1: 文書名 | U1: モジュールID | Z1: =表紙!$AJ$63 -> MS | AE1: モジュール名 | AJ1: =表紙!$AX$63 -> Webシステム | AS1: 文書番号 | AZ1: Version | BF1: Rev.
K2: =表紙!O64 -> アドオン設計書 | U2: ｻﾌﾞﾓｼﾞｭｰﾙID | Z2: =表紙!$AJ$64 -> MSBB | AE2: ｻﾌﾞﾓｼﾞｭｰﾙ名 | AJ2: =表紙!$AX$64 -> 販売Webシステム | AS2: =表紙!$BL$64 -> M7-US-1140 | AZ2: =表紙!$BU$64 -> 7.0.2 | BF2: =表紙!$CB$64 -> 1
K3: =RIGHT(CELL("filename",$A$1),LEN(CELL("filename",$A$1))-FIND("]",CELL("filename",$A$1))) -> 項目説明 | U3: 表題 | Z3: =表紙!$AJ$65 -> MSBBPA110 | AE3: =表紙!$AQ$65 -> Web取引先マスタ
B5: 操作種別 | N5: 説明 | BE5: Ｗ | BF5: 型 | BG5: 参 | BH5: 必 | BI5: 入 | BJ5: 非 | BK5: 検 | BM5: 指摘ＣＰ 2022/10/20 玉置 項目の追加が必要 取引先区分が「メーカ」の場合、ＦＳＣ認証先で有るか無いかの区分が必要です。
A6: ● | B6: 事前登録 | M6: 登録と同様の処理となる ステータスのみ事前登録で更新する | BE6: R | BN6: MDSOL 野村 2022/10/25
A7: ● | B7: 登録 | M7: 【MSBBPA000】_共通設計書_アドオン(Webシステム共通仕様)にて定義 | BE7: R | BO7: FSC加工先 項目とは別で必要でしょうか。
A8: ● | B8: 訂正 | M8: 【MSBBPA000】_共通設計書_アドオン(Webシステム共通仕様)にて定義 | BE8: R | BO8: 現行は属性情報としての項目と認識しています。
A9: ● | B9: 削除 | M9: 【MSBBPA000】_共通設計書_アドオン(Webシステム共通仕様)にて定義 | BE9: R
A10: ● | B10: 参照 | M10: 【MSBBPA000】_共通設計書_アドオン(Webシステム共通仕様)にて定義 | BE10: R
B12: 検索項目 | N12: 説明 | BE12: Ｗ | BF12: 型 | BG12: 参 | BH12: 必 | BI12: 入 | BJ12: 非 | BK12: 検
A13: 〇 | B13: 取引先CD | M13: 【MSBBPACOM】_共通設計書_アドオン(共通ロジック)にて定義 | BE13: A | BF13: S | BK13: 検
B14: 取引先名 | M14: 取引先CDに対する取引先名を表示する | BE14: T | BF14: S
B16: 共通項目 | N16: 説明 | BE16: Ｗ | BF16: 型 | BG16: 参 | BH16: 必 | BI16: 入 | BJ16: 非 | BK16: 検
A17: ● | B17: 取引先ステータス | M17: ステータスが表示される(0:事前登録、1:本登録) | AS17: 操作種別:訂正時、変更可能とする | BE17: C | BF17: S
M18: ※操作種別:事前登録時は事前登録固定、登録時は、登録固定
B20: タブ１ | N20: 説明 | BE20: Ｗ | BF20: 型 | BG20: 参 | BH20: 必 | BI20: 入 | BJ20: 非 | BK20: 検
B21: 基本情報 | M21: 基本情報タブ、タブ選択で各タブに設定された内容を表示する | BE21: tab
B22: 取引分類 | M22: 取引分類タブ、タブ選択で各タブに設定された内容を表示する | BE22: tab
B24: 取引先基本情報 | N24: 説明 | BE24: Ｗ | BF24: 型 | BG24: 参 | BH24: 必 | BI24: 入 | BJ24: 非 | BK24: 検
A25: ● | B25: 取引先名 | M25: 取引先名を入力する | BE25: T | BF25: S | BG25: 参 | BH25: 必
A26: ● | B26: 取引先略称 | M26: 取引先略称を入力する | AS26: ※mcframe7：取引先別名１ | BE26: T | BF26: S | BG26: 参
A27: ● | B27: 拠点CD | M27: 【MSBBPACOM】_共通設計書_アドオン(共通ロジック)にて定義 | AJ27: 初期値：ログイン拠点をセットする | BE27: C | BF27: S | BG27: 参 | BH27: 必
B28: 拠点名 | M28: 拠点コードに対する拠点名を表示する | BE28: T | BF28: S
A29: ● | B29: 標準企業コード | M29: 標準企業コードを入力する | BE29: T | BF29: S | BG29: 参
A30: ● | B30: 法人番号 | M30: 法人番号を入力する | BE30: T | BF30: S | BG30: 参
A31: ● | B31: 法人番号区分 | M31: 【MSBBPACOM】_共通設計書_アドオン(共通ロジック)にて定義 | BE31: T | BF31: S | BG31: 参
A32: ● | B32: 地方公共団体CD | M32: 地方公共団体CDを入力する | BE32: T | BF32: S | BG32: 参
A33: ● | B33: でんさい利用者番号 | M33: でんさい利用者番号を入力する | AS33: ※mcframe7：メモ２ | BE33: T | BF33: S | BG33: 参
A34: ● | B34: 郵便番号 | M34: 郵便番号を入力する | BE34: T | BF34: S | BG34: 参
A35: ● | B35: 都道府県 | M35: 都道府県を入力する | AS35: ※mcframe7：住所１ | BE35: T | BF35: S | BG35: 参
A36: ● | B36: 市区町村 | M36: 市区町村を入力する | AS36: ※mcframe7：住所２ | BE36: T | BF36: S | BG36: 参
A37: ● | B37: 町域・番地 | M37: 町域・番地を入力する | AS37: ※mcframe7：住所３ | BE37: T | BF37: S | BG37: 参
A38: ● | B38: 建物など | M38: 建物などを入力する | AS38: ※mcframe7：住所４ | BE38: T | BF38: S | BG38: 参
A39: ● | B39: ＴＥＬ | M39: ＴＥＬを入力する | BE39: T | BF39: S | BG39: 参
A40: ● | B40: ＦＡＸ | M40: ＦＡＸを入力する | BE40: T | BF40: S | BG40: 参
A41: ● | B41: 地域CD | M41: 【MSBBPACOM】_共通設計書_アドオン(共通ロジック)にて定義 | BE41: C | BF41: S | BG41: 参
A42: ● | B42: 営業担当 | M42: 【MSBBPACOM】_共通設計書_アドオン(共通ロジック)にて定義 | AS42: 得意先FLG=ON時、必須 | BE42: T | BF42: S | BG42: 参 | BH42: 条 | BK42: 検 | BM42: CP指摘 2022/09/23 落合 新規・訂正とも営業担当者を入力できる必要あり
B43: 営業担当名 | M43: 営業担当選択後に営業担当名がセットされる | BE43: T | BF43: S
B44: 営業担当名注記 | M44: 「※変更はMcFrame7 得意先担当マスタにて」と表記 | BE44: T | BF44: S
A45: ● | B45: 業務担当 | M45: 【MSBBPACOM】_共通設計書_アドオン(共通ロジック)にて定義 | AS45: 得意先FLG=ON時、必須 | BE45: T | BF45: S | BG45: 参 | BH45: 条 | BK45: 検 | BM45: CP指摘 2022/09/23 落合 新規・訂正とも業務担当者を入力できる必要あり
B46: 業務担当名 | M46: 業務担当選択後に業務担当名がセットされる | BE46: T | BF46: S
A47: ● | B47: 得意先FLG | M47: 得意先タブのFLG、☑でチェックタブを有効とする | AJ47: 取引先が[得意先]の属性を持つ場合にチェックします | BE47: チ | BF47: F | BG47: 参 | BN47: MDSOL 野村 2022/10/25 訂正は、得意先担当マスタで実施する想定です。
A48: ● | B48: 売掛先FLG | M48: 売掛先タブのFLG、☑でチェックタブを有効とする | AJ48: 取引先が[売掛先]の属性を持つ場合にチェックします | BE48: チ | BF48: F | BG48: 参 | BN48: ※詳細は、画面イメージに記載
A49: ● | B49: 請求先FLG | M49: 請求先タブのFLG、☑でチェックタブを有効とする | AJ49: 取引先が[請求先]の属性を持つ場合にチェックします | BE49: チ | BF49: F | BG49: 参
A50: ● | B50: 入金先FLG | M50: 入金先タブのFLG、☑でチェックタブを有効とする | AJ50: 取引先が[入金先]の属性を持つ場合にチェックします | BE50: チ | BF50: F | BG50: 参
A51: ● | B51: 納品先FLG | M51: 納品先タブのFLG、☑でチェックタブを有効とする | AJ51: 取引先が[納品先]の属性を持つ場合にチェックします | BE51: チ | BF51: F | BG51: 参
A52: ● | B52: 発注先FLG | M52: 発注先タブのFLG、☑でチェックタブを有効とする | AJ52: 取引先が[発注先]の属性を持つ場合にチェックします | BE52: チ | BF52: F | BG52: 参
A53: ● | B53: 買掛先FLG | M53: 買掛先タブのFLG、☑でチェックタブを有効とする | AJ53: 取引先が[買掛先]の属性を持つ場合にチェックします | BE53: チ | BF53: F | BG53: 参
A54: ● | B54: 支払予定管理先FLG | M54: 支払予定管理先タブのFLG、☑でチェックタブを有効とする | AJ54: 取引先が[支払予定管理先]の属性を持つ場合にチェックします | BE54: チ | BF54: F | BG54: 参
A55: ● | B55: 支払先FLG | M55: 支払先タブのFLG、☑でチェックタブを有効とする | AJ55: 取引先が[支払先]の属性を持つ場合にチェックします | BE55: チ | BF55: F | BG55: 参
B57: 取引先分類 | N57: 説明 | BE57: Ｗ | BF57: 型 | BG57: 参 | BH57: 必 | BI57: 入 | BJ57: 非 | BK57: 検
A58: ● | B58: 取引先分類1 | M58: 【MSBBPACOM】_共通設計書_アドオン(共通ロジック)にて定義 | BE58: C | BF58: S | BG58: 参
B59: 取引先分類名1 | M59: 取引先分類1選択後に取引先分類名1がセットされる | BE59: T | BF59: S
A60: ● | B60: 取引先分類2 | M60: 【MSBBPACOM】_共通設計書_アドオン(共通ロジック)にて定義 | BE60: C | BF60: S | BG60: 参
B61: 取引先分類名2 | M61: 取引先分類2選択後に取引先分類名2がセットされる | BE61: T | BF61: S
A62: ● | B62: 取引先分類3 | M62: 【MSBBPACOM】_共通設計書_アドオン(共通ロジック)にて定義 | BE62: C | BF62: S | BG62: 参
B63: 取引先分類名3 | M63: 取引先分類3選択後に取引先分類名3がセットされる | BE63: T | BF63: S
A64: ● | B64: 取引先分類4 | M64: 【MSBBPACOM】_共通設計書_アドオン(共通ロジック)にて定義 | BE64: C | BF64: S | BG64: 参
B65: 取引先分類名4 | M65: 取引先分類4選択後に取引先分類名4がセットされる | BE65: T | BF65: S
A66: ● | B66: 取引先分類5 | M66: 【MSBBPACOM】_共通設計書_アドオン(共通ロジック)にて定義 | BE66: C | BF66: S | BG66: 参
B67: 取引先分類名5 | M67: 取引先分類5選択後に取引先分類名5がセットされる | BE67: T | BF67: S
A68: ● | B68: 取引先分類6 | M68: 【MSBBPACOM】_共通設計書_アドオン(共通ロジック)にて定義 | BE68: C | BF68: S | BG68: 参
B69: 取引先分類名6 | M69: 取引先分類6選択後に取引先分類名6がセットされる | BE69: T | BF69: S
A70: ● | B70: 取引先分類7 | M70: 【MSBBPACOM】_共通設計書_アドオン(共通ロジック)にて定義 | BE70: C | BF70: S | BG70: 参
B71: 取引先分類名7 | M71: 取引先分類7選択後に取引先分類名7がセットされる | BE71: T | BF71: S
A72: ● | B72: 取引先分類8 | M72: 【MSBBPACOM】_共通設計書_アドオン(共通ロジック)にて定義 | BE72: C | BF72: S | BG72: 参
B73: 取引先分類名8 | M73: 取引先分類8選択後に取引先分類名8がセットされる | BE73: T | BF73: S
A74: ● | B74: 取引先分類9 | M74: 【MSBBPACOM】_共通設計書_アドオン(共通ロジック)にて定義 | BE74: C | BF74: S | BG74: 参
B75: 取引先分類名9 | M75: 取引先分類9選択後に取引先分類名9がセットされる | BE75: T | BF75: S
A76: ● | B76: 取引先分類10 | M76: 【MSBBPACOM】_共通設計書_アドオン(共通ロジック)にて定義 | BE76: C | BF76: S | BG76: 参
B77: 取引先分類名10 | M77: 取引先分類10選択後に取引先分類名10がセットされる | BE77: T | BF77: S
A78: ● | B78: 販売分析１ | M78: 【MSBBPACOM】_共通設計書_アドオン(共通ロジック)にて定義 | BE78: C | BF78: S | BG78: 参
B79: 販売分析名１ | M79: 販売分析１選択後に販売分析名１がセットされる | BE79: T | BF79: S
A80: ● | B80: 販売分析２ | M80: 【MSBBPACOM】_共通設計書_アドオン(共通ロジック)にて定義 | BE80: C | BF80: S | BG80: 参
B81: 販売分析名2 | M81: 販売分析２選択後に販売分析名２がセットされる | BE81: T | BF81: S
A82: ● | B82: 販売分析３ | M82: 【MSBBPACOM】_共通設計書_アドオン(共通ロジック)にて定義 | BE82: C | BF82: S | BG82: 参
B83: 販売分析名3 | M83: 販売分析３選択後に販売分析名３がセットされる | BE83: T | BF83: S
B85: タブ２ | N85: 説明 | BE85: Ｗ | BF85: 型 | BG85: 参 | BH85: 必 | BI85: 入 | BJ85: 非 | BK85: 検
B86: 得意先タブ | M86: 得意先タブ、タブ選択で各タブに設定された内容を表示する | BE86: tab | BG86: 参
B87: 売掛先タブ | M87: 売掛先タブ、タブ選択で各タブに設定された内容を表示する | BE87: tab | BG87: 参
B88: 請求先タブ | M88: 請求先タブ、タブ選択で各タブに設定された内容を表示する | BE88: tab | BG88: 参
B89: 入金先タブ | M89: 入金先タブ、タブ選択で各タブに設定された内容を表示する | BE89: tab | BG89: 参
B90: 納品先タブ | M90: 納品先タブ、タブ選択で各タブに設定された内容を表示する | BE90: tab | BG90: 参
B91: 発注先タブ | M91: 発注先タブ、タブ選択で各タブに設定された内容を表示する | BE91: tab | BG91: 参
B92: 買掛先タブ | M92: 買掛先タブ、タブ選択で各タブに設定された内容を表示する | BE92: tab | BG92: 参
B93: 支払予定管理先タブ | M93: 支払予定管理先タブ、タブ選択で各タブに設定された内容を表示する | BE93: tab | BG93: 参
B94: 支払先タブ | M94: 支払先タブ、タブ選択で各タブに設定された内容を表示する | BE94: tab | BG94: 参
B96: 得意先 | N96: 説明 | BE96: Ｗ | BF96: 型 | BG96: 参 | BH96: 必 | BI96: 入 | BJ96: 非 | BK96: 検
A97: ● | B97: 得意先CD(親) | M97: 【MSBBPACOM】_共通設計書_アドオン(共通ロジック)にて定義 | BE97: A | BF97: S | BG97: 参
B98: 得意先CD(親)名 | M98: 得意先CD(親)選択後に得意先CD(親)名がセットされる | BE98: T | BF98: S
A99: ● | B99: ユーザー・コンバーター区分 | M99: 【MSBBPACOM】_共通設計書_アドオン(共通ロジック)にて定義 | BE99: C | BF99: S | BG99: 参
A100: ● | B100: 売掛先 | M100: 【MSBBPACOM】_共通設計書_アドオン(共通ロジック)にて定義 | BE100: A | BF100: S | BG100: 参 | BH100: 条
B101: 売掛先名 | M101: 売掛先選択後に売掛先がセットされる | BE101: T | BF101: S
A102: ● | B102: 与信管理先 | M102: 取引先が[与信管理先]の属性を持つ場合にチェックします | BE102: チ | BF102: F | BG102: 参
A103: ● | B103: 得意先部署 | M103: 得意先部署を入力する | BE103: T | BF103: S | BG103: 参
A104: ● | B104: 得意先担当者 | M104: 得意先担当者を入力する | BE104: T | BF104: S | BG104: 参
A105: ● | B105: 得意先担当者敬称 | M105: 得意先担当者敬称を入力する | BE105: T | BF105: S | BG105: 参
A106: ● | B106: 容器リ法対象 | M106: 【MSBBPACOM】_共通設計書_アドオン(共通ロジック)にて定義 | BE106: C | BF106: S | BG106: 参
B107: 得意先(売上計算) | N107: 説明 | BE107: Ｗ | BF107: 型 | BG107: 参 | BH107: 必 | BI107: 入 | BJ107: 非 | BK107: 検
A108: ● | B108: 売上計上区分 | M108: 【MSBBPACOM】_共通設計書_アドオン(共通ロジック)にて定義 | BE108: C | BF108: S | BG108: 参
...

Sheet 引数説明
A1: =表紙!A54 -> Webシステム | K1: 文書名 | U1: モジュールID | Z1: =表紙!$AJ$63 -> MS | AE1: モジュール名 | AJ1: =表紙!$AX$63 -> Webシステム | AS1: 文書番号 | AZ1: Version | BF1: Rev.
K2: =表紙!O64 -> アドオン設計書 | U2: ｻﾌﾞﾓｼﾞｭｰﾙID | Z2: =表紙!$AJ$64 -> MSBB | AE2: ｻﾌﾞﾓｼﾞｭｰﾙ名 | AJ2: =表紙!$AX$64 -> 販売Webシステム | AS2: =表紙!$BL$64 -> M7-US-1140 | AZ2: =表紙!$BU$64 -> 7.0.2 | BF2: =表紙!$CB$64 -> 1
K3: =RIGHT(CELL("filename",$A$1),LEN(CELL("filename",$A$1))-FIND("]",CELL("filename",$A$1))) -> 引数説明 | U3: 表題 | Z3: =表紙!$AJ$65 -> MSBBPA110 | AE3: =表紙!$AQ$65 -> Web取引先マスタ
B5: オペレーションＩＤ/名称：SloRecvIfImp_Upd01/取込
A6: 必 | B6: 項目名 | N6: 説明 | AS6: 未設定時の振る舞い
B7: 得意先ＣＤ | M7: 受注受信ＩＦの検索条件

Sheet 処理概要
A1: =表紙!A54 -> Webシステム | K1: 文書名 | U1: モジュールID | Z1: =表紙!$AJ$63 -> MS | AE1: モジュール名 | AJ1: =表紙!$AX$63 -> Webシステム | AS1: 文書番号 | AZ1: Version | BF1: Rev.
K2: =表紙!O64 -> アドオン設計書 | U2: ｻﾌﾞﾓｼﾞｭｰﾙID | Z2: =表紙!$AJ$64 -> MSBB | AE2: ｻﾌﾞﾓｼﾞｭｰﾙ名 | AJ2: =表紙!$AX$64 -> 販売Webシステム | AS2: =表紙!$BL$64 -> M7-US-1140 | AZ2: =表紙!$BU$64 -> 7.0.2 | BF2: =表紙!$CB$64 -> 1
K3: =RIGHT(CELL("filename",$A$1),LEN(CELL("filename",$A$1))-FIND("]",CELL("filename",$A$1))) -> 処理概要 | U3: 表題 | Z3: =表紙!$AJ$65 -> MSBBPA110 | AE3: =表紙!$AQ$65 -> Web取引先マスタ
A5: No | B5: 入力 | J5: 処理 | BD5: 出力
A6: 1 | B6: 初期表示
J7: １．初期処理
K8: 初期表示
L9: 各項目のクリア処理と初期値設定を行う
A11: 2 | B11: タブ選択
J12: １．タブ選択処理
K13: 各チェックボックス(得意先、売掛先、請求先、入金先、納品先、発注先、買掛先、支払予定管理先、支払先)のチェックON=各TAB使用可
K14: 各チェックボックス(得意先、売掛先、請求先、入金先、納品先、発注先、買掛先、支払予定管理先、支払先)のチェックOFF=各TAB使用不可
A16: 3 | B16: 取引先CD検索処理
J17: １．取引先CD検索処理
K18: 検索条件：取引先CDを指定後、以下の検索処理を実行する | BD18: 検索入出力仕様.NO1
A20: 4 | B20: 発注先パターン選択処理
J21: １．発注先パターン選択処理
K22: 「発注先(原材料、資材、副資材、購買品、他)関連」時
M23: 下請対象ＦＬＧ、有償支給先ＦＬＧ、買戻義務ＦＬＧ … □チェック無し固定
L24: 初期値設定
M25: 納期回答確認ＦＬＧ:☑チェック有り
M26: 仕入金額端数処理区分:3=四捨五入
M27: 仕入税額端数処理区分:3=四捨五入
M28: 仕入税:P010、仕入税優先ＦＬＧ:□チェック無し
M29: 発注先カレンダ:CAL01
M30: 支給積送管理区分:1=着荷登録不要
M31: 仕入ロット明細分割区分:1=分割しない
M32: 仕入計上区分:2=検収基準
L33: 使用不可
M34: 外注単価区分
M35: 支給計上区分
M36: 支給単価変更許可ＦＬＧ
M37: 支給税
M38: 支給税優先
M39: 支給金額端数処理区分
M40: 支給税計算区分
M41: 支給税額端数処理区分
K42: 「発注先(外注品)関連」時
M43: 支給計上区分:2着荷基準 … 固定
L44: 初期値設定
M45: 納期回答確認ＦＬＧ:☑チェック有り
M46: 仕入金額端数処理区分:3=四捨五入
M47: 仕入税額端数処理区分:3=四捨五入
M48: 仕入税:P010、仕入税優先ＦＬＧ:□チェック無し
M49: 発注先カレンダ:CAL01
M50: 支給積送管理区分:1=着荷登録不要
M51: 仕入ロット明細分割区分:1=分割しない
M52: 仕入計上区分:2=検収基準
M53: 外注単価区分:1=加工単価+有償支給単価
M54: 支給単価変更許可ＦＬＧ:☑チェック有り
K55: ※発注先パターンに関しては、マスタ定義書_取引先マスタを参照
A57: 5 | B57: 登録ボタン押下処理
J58: １．登録ボタン押下処理
K59: 登録ボタン押下(チェック処理) | U59: ： | V59: チェック処理にてエラーとなった場合、後続処理をキャンセルする
L60: 必須チェック | Q60: 項目：取引先名、拠点CD
Q61: エラーメッセージ：「必須項目に値が指定されていません。項目名：パラメータ」 | BD61: メッセージID.001
Q62: エラーメッセージ：「いずれかを選択してください。」 | BD62: メッセージID.002
Q63: ※得意先、売掛先、請求先、入金先、納品先、発注先、買掛先、支払予定管理先、支払先…いずれかにチェックが無い場合
Q64: 項目：売掛先(&売掛先FLG=OFFの場合)、営業担当、業務担当
Q65: エラーメッセージ：「必須項目に値が指定されていません。(得意先選択時) 項目名：パラメータ」 | BD65: メッセージID.003
Q66: 項目：請求先(&請求先FLG=OFFの場合)
Q67: エラーメッセージ：「必須項目に値が指定されていません。(売掛先選択時) 項目名：パラメータ」 | BD67: メッセージID.004
Q68: 項目：入金先(&入金先FLG=OFFの場合)
Q69: エラーメッセージ：「必須項目に値が指定されていません。(請求先選択時) 項目名：パラメータ」 | BD69: メッセージID.005
Q70: 項目：物流グループCD
Q71: エラーメッセージ：「必須項目に値が指定されていません。(納品先選択時) 項目名：パラメータ」 | BD71: メッセージID.006
Q72: 項目：発注先パターン、買掛先(&買掛先FLG=OFFの場合)、仕入金額端数処理区分
Q73: 仕入税額端数処理区分、支給積送管理区分、仕入ロット明細分割区分
Q74: エラーメッセージ：「必須項目に値が指定されていません。(発注先選択時) 項目名：パラメータ」 | BD74: メッセージID.007
Q75: 項目：支給金額端数処理区分、支給税額端数処理区分、支給税計算区分
Q76: エラーメッセージ：「必須項目に値が指定されていません。(発注先選択時、有償支給先ＦＬＧ=ON) 項目名：パラメータ」 | BD76: メッセージID.008
Q77: 項目：支給税ＣＤ
Q78: エラーメッセージ：「必須項目に値が指定されていません。 | BD78: メッセージID.009
W79: (発注先選択時、有償支給先ＦＬＧ=ON、買戻義務ＦＬＧ=ON) 項目名：パラメータ」
Q80: 項目：支払予定管理先(&支払予定管理先FLG=OFFの場合)
Q81: エラーメッセージ：「必須項目に値が指定されていません。(買掛先選択時) 項目名：パラメータ」 | BD81: メッセージID.010
Q82: 項目：支払先(&支払先FLG=OFFの場合)、支払予定管理先担当部門ＣＤ
Q83: エラーメッセージ：「必須項目に値が指定されていません。(支払予定管理先選択時)」 | BD83: メッセージID.011
Q84: 項目：支払締日１
Q85: エラーメッセージ：「必須項目に値が指定されていません。(支払予定管理先選択時、都度支払ＦＬＧ=OFF)」 | BD85: メッセージID.012
Q86: 項目：支払税額端数処理区分
Q87: エラーメッセージ：「必須項目に値が指定されていません。(支払予定管理先選択時、支払税計算ＦＬＧ=ON)」 | BD87: メッセージID.013
Q88: 項目：支払予定締遅延日数
Q89: エラーメッセージ：「必須項目に値が指定されていません。(支払予定管理先選択時、バッチ支払予定締ＦＬＧ=ON)」 | BD89: メッセージID.014
L91: 入力チェック | Q91: 半角大文字アルファベット、半角数字、半角スペース、「-」以外の入力
Q92: 項目：郵便番号、納品計算書_郵便番号、請求書郵便番号、領収書郵便番号
L93: (入力形式) | R93: エラーメッセージ：「文字列がパターンに一致しません。」 | BD93: メッセージID.015
Q94: 「+」、「-」、半角スペース、「(」、「)」、半角数字以外の入力
Q95: 項目：ＴＥＬ、ＦＡＸ
R96: エラーメッセージ：「文字列がパターンに一致しません。」 | BD96: メッセージID.016
Q97: 「1」～「31」、「99」以外の入力
Q98: 項目：請求締日1、支払締日1、集金予定日
R99: エラーメッセージ：「1～31, 99」の数値を指定してください。 項目名：パラメータ」 | BD99: メッセージID.017
R100: ※入力コンポーネントで制御可能な場合はチェック不要
L102: 操作種別：訂正時のFLG変更
M103: 変更不可の項目変更時、エラーメッセージを表示する
Q104: エラーメッセージ：「変更が許可されていません。 項目名：パラメータ」 | BD104: メッセージID.018
K106: 画面の内容を元に以下の登録処理を実行する
K107: １）WEB取引先マスタ登録処理
L108: WEB取引先マスタに画面入力値を登録する | BD108: 更新入出力仕様.NO1
...

Sheet 処理詳細
A1: =表紙!A54 -> Webシステム | K1: 文書名 | U1: モジュールID | Z1: =表紙!$AJ$63 -> MS | AE1: モジュール名 | AJ1: =表紙!$AX$63 -> Webシステム | AS1: 文書番号 | AZ1: Version | BF1: Rev.
K2: =表紙!O64 -> アドオン設計書 | U2: ｻﾌﾞﾓｼﾞｭｰﾙID | Z2: =表紙!$AJ$64 -> MSBB | AE2: ｻﾌﾞﾓｼﾞｭｰﾙ名 | AJ2: =表紙!$AX$64 -> 販売Webシステム | AS2: =表紙!$BL$64 -> M7-US-1140 | AZ2: =表紙!$BU$64 -> 7.0.2 | BF2: =表紙!$CB$64 -> 1
K3: =RIGHT(CELL("filename",$A$1),LEN(CELL("filename",$A$1))-FIND("]",CELL("filename",$A$1))) -> 処理詳細 | U3: 表題 | Z3: =表紙!$AJ$65 -> MSBBPA110 | AE3: =表紙!$AQ$65 -> Web取引先マスタ
A5: No | B5: 入力 | J5: 処理 | BD5: 出力
A6: 1 | B6: 初期表示
A12: 2 | B12: 画面操作
A18: 3 | B18: 検索【F1】

Sheet 処理・サービス関連図
A1: =表紙!A54 -> Webシステム | K1: 文書名 | U1: モジュールID | Z1: =表紙!$AJ$63 -> MS | AE1: モジュール名 | AJ1: =表紙!$AX$63 -> Webシステム | AS1: 文書番号 | AZ1: Version | BF1: Rev.
K2: =表紙!O64 -> アドオン設計書 | U2: ｻﾌﾞﾓｼﾞｭｰﾙID | Z2: =表紙!$AJ$64 -> MSBB | AE2: ｻﾌﾞﾓｼﾞｭｰﾙ名 | AJ2: =表紙!$AX$64 -> 販売Webシステム | AS2: =表紙!$BL$64 -> M7-US-1140 | AZ2: =表紙!$BU$64 -> 7.0.2 | BF2: =表紙!$CB$64 -> 1
K3: =RIGHT(CELL("filename",$A$1),LEN(CELL("filename",$A$1))-FIND("]",CELL("filename",$A$1))) -> 処理・サービス関連図 | U3: 表題 | Z3: =表紙!$AJ$65 -> MSBBPA110 | AE3: =表紙!$AQ$65 -> Web取引先マスタ
C7: 検索処理
C19: 更新処理
C28: ※取引先マスタ連携仕様は、【MSBBBA020】_バッチ設計書_アドオン(取引先マスタ連携)にて定義
C29: mcframe7転送

Sheet 検索入出力仕様
A1: =表紙!A54 -> Webシステム | K1: 文書名 | U1: モジュールID | Z1: =表紙!$AJ$63 -> MS | AE1: モジュール名 | AJ1: =表紙!$AX$63 -> Webシステム | AS1: 文書番号 | AZ1: Version | BF1: Rev.
K2: =表紙!O64 -> アドオン設計書 | U2: ｻﾌﾞﾓｼﾞｭｰﾙID | Z2: =表紙!$AJ$64 -> MSBB | AE2: ｻﾌﾞﾓｼﾞｭｰﾙ名 | AJ2: =表紙!$AX$64 -> 販売Webシステム | AS2: =表紙!$BL$64 -> M7-US-1140 | AZ2: =表紙!$BU$64 -> 7.0.2 | BF2: =表紙!$CB$64 -> 1
K3: =RIGHT(CELL("filename",$A$1),LEN(CELL("filename",$A$1))-FIND("]",CELL("filename",$A$1))) -> 検索入出力仕様 | U3: 表題 | Z3: =表紙!$AJ$65 -> MSBBPA110 | AE3: =表紙!$AQ$65 -> Web取引先マスタ
A5: No | G5: 1 | S5: ボタン | AH5: 備考
A6: 処理分類 | E6: 検索 | S6: ソート順
A7: No | C7: 転送先 | Z7: 転送元 | AU7: 説明
C8: 種 | D8: オブジェクト | N8: 項目名 | Z8: 種 | AA8: オブジェクト | AJ8: 項目名
A9: 1 | C9: 画 | D9: 基本情報 | N9: 取引先CD | Z9: T | AA9: WEB取引先(マスタ)VIEW | AJ9: 取引先CD
A10: 2 | C10: 画 | D10: 基本情報 | N10: ステータス | Z10: T | AA10: WEB取引先(マスタ)VIEW | AJ10: ステータス
A11: 3 | C11: 画 | D11: 基本情報 | N11: 取引先名 | Z11: T | AA11: WEB取引先(マスタ)VIEW | AJ11: 取引先名
A12: 4 | C12: 画 | D12: 基本情報 | N12: 取引先略称 | Z12: T | AA12: WEB取引先(マスタ)VIEW | AJ12: 取引先略称
A13: 5 | C13: 画 | D13: 基本情報 | N13: 拠点CD | Z13: T | AA13: WEB取引先(マスタ)VIEW | AJ13: 拠点CD
A14: 6 | C14: 画 | D14: 基本情報 | N14: 拠点名 | Z14: T | AA14: WEB取引先(マスタ)VIEW | AJ14: 拠点名
A15: 7 | C15: 画 | D15: 基本情報 | N15: 標準企業コード | Z15: T | AA15: WEB取引先(マスタ)VIEW | AJ15: 標準企業コード
A16: 8 | C16: 画 | D16: 基本情報 | N16: 法人番号 | Z16: T | AA16: WEB取引先(マスタ)VIEW | AJ16: 法人番号
A17: 9 | C17: 画 | D17: 基本情報 | N17: 法人番号区分 | Z17: T | AA17: WEB取引先(マスタ)VIEW | AJ17: 法人番号区分
A18: 10 | C18: 画 | D18: 基本情報 | N18: 地方公共団体CD | Z18: T | AA18: WEB取引先(マスタ)VIEW | AJ18: 地方公共団体CD
A19: 11 | C19: 画 | D19: 基本情報 | N19: でんさい利用者番号 | Z19: T | AA19: WEB取引先(マスタ)VIEW | AJ19: でんさい利用者番号
A20: 12 | C20: 画 | D20: 基本情報 | N20: 郵便番号 | Z20: T | AA20: WEB取引先(マスタ)VIEW | AJ20: 郵便番号
... A208: 200 | C208: 画 | D208: 支払先 | N208: 支払部門名 | Z208: T | AA208: WEB取引先(マスタ)VIEW | AJ208: 支払部門名

Sheet 更新入出力仕様
A1: =表紙!A54 -> Webシステム | K1: 文書名 | U1: モジュールID | Z1: =表紙!$AJ$63 -> MS | AE1: モジュール名 | AJ1: =表紙!$AX$63 -> Webシステム | AS1: 文書番号 | AZ1: Version | BF1: Rev.
K2: =表紙!O64 -> アドオン設計書 | U2: ｻﾌﾞﾓｼﾞｭｰﾙID | Z2: =表紙!$AJ$64 -> MSBB | AE2: ｻﾌﾞﾓｼﾞｭｰﾙ名 | AJ2: =表紙!$AX$64 -> 販売Webシステム | AS2: =表紙!$BL$64 -> M7-US-1140 | AZ2: =表紙!$BU$64 -> 7.0.2 | BF2: =表紙!$CB$64 -> 1
K3: =RIGHT(CELL("filename",$A$1),LEN(CELL("filename",$A$1))-FIND("]",CELL("filename",$A$1))) -> 更新入出力仕様 | U3: 表題 | Z3: =表紙!$AJ$65 -> MSBBPA110 | AE3: =表紙!$AQ$65 -> Web取引先マスタ
A5: No | G5: 1 | S5: ロジック名称 | Z5: 登録ボタン | AH5: 備考
A6: 処理分類 | E6: 登録、更新
A7: No | C7: 転送先 | Z7: 転送元 | AU7: 説明
C8: 種 | D8: オブジェクト | N8: 項目名 | Z8: 種 | AA8: オブジェクト | AJ8: 項目名
A9: 1 | C9: T | D9: WEB取引先マスタ | N9: 取引先CD | Z9: 画 | AA9: 基本情報 | AJ9: 取引先CD
A10: 2 | C10: T | D10: WEB取引先マスタ | N10: ステータス | Z10: 画 | AA10: 基本情報 | AJ10: ステータス
A11: 3 | C11: T | D11: WEB取引先マスタ | N11: 取引先名 | Z11: 画 | AA11: 基本情報 | AJ11: 取引先名
A12: 4 | C12: T | D12: WEB取引先マスタ | N12: 取引先略称 | Z12: 画 | AA12: 基本情報 | AJ12: 取引先略称
A13: 5 | C13: T | D13: WEB取引先マスタ | N13: 拠点CD | Z13: 画 | AA13: 基本情報 | AJ13: 拠点CD
A14: 6 | C14: T | D14: WEB取引先マスタ | N14: 標準企業コード | Z14: 画 | AA14: 基本情報 | AJ14: 標準企業コード
A15: 7 | C15: T | D15: WEB取引先マスタ | N15: 法人番号 | Z15: 画 | AA15: 基本情報 | AJ15: 法人番号
A16: 8 | C16: T | D16: WEB取引先マスタ | N16: 法人番号区分 | Z16: 画 | AA16: 基本情報 | AJ16: 法人番号区分
A17: 9 | C17: T | D17: WEB取引先マスタ | N17: 地方公共団体CD | Z17: 画 | AA17: 基本情報 | AJ17: 地方公共団体CD
A18: 10 | C18: T | D18: WEB取引先マスタ | N18: でんさい利用者番号 | Z18: 画 | AA18: 基本情報 | AJ18: でんさい利用者番号
A19: 11 | C19: T | D19: WEB取引先マスタ | N19: 郵便番号 | Z19: 画 | AA19: 基本情報 | AJ19: 郵便番号
A20: 12 | C20: T | D20: WEB取引先マスタ | N20: 都道府県 | Z20: 画 | AA20: 基本情報 | AJ20: 都道府県
... A179: 171 | C179: T | D179: WEB取引先マスタ | N179: 支払部門CD | Z179: 画 | AA179: 支払先 | AJ179: 支払部門CD
A180: 172 | C180: T | D180: WEB取引先マスタ | N180: mcframe7転送FLG | AJ180: 0
A181: 173 | C181: T | D181: WEB取引先マスタ | N181: mcframe7転送日時 | AJ181: [DBNull]
A184: No | G184: 2 | S184: ロジック名称 | Z184: 岐阜IF連携 | AH184: 備考
A185: 処理分類 | E185: 更新
A186: No | C186: 転送先 | Z186: 転送元 | AU186: 説明
C187: 種 | D187: オブジェクト | N187: 項目名 | Z187: 種 | AA187: オブジェクト | AJ187: 項目名
A188: 1 | C188: T | D188: WEB取引先マスタ | N188: 岐阜IF連携FLG | AJ188: 0
A189: 2 | C189: T | D189: WEB取引先マスタ | N189: 岐阜IF連携最終更新日 | AJ189: [DBNull]
A191: 更新条件
A192: 1 | C192: T | D192: WEB取引先マスタ | N192: 取引先CD | Z192: 画 | AA192: 基本情報 | AJ192: 取引先CD
A193: 2 | C193: 画 | D193: 基本情報 | N193: 得意先FLG | AJ193: ON(チェック時)
A194: 3 | C194: 画 | D194: 基本情報 | N194: 納品先FLG | AJ194: ON(チェック時)
D195: 2,3は、OR条件となる
E196: 得意先FLG、納品先FLGのどちらかが、チェックされていた場合に更新処理を実施する

Sheet 画面遷移
A1: =表紙!A54 -> Webシステム | K1: 文書名 | U1: モジュールID | Z1: =表紙!$AJ$63 -> MS | AE1: モジュール名 | AJ1: =表紙!$AX$63 -> Webシステム | AS1: 文書番号 | AZ1: Version | BF1: Rev.
K2: =表紙!O64 -> アドオン設計書 | U2: ｻﾌﾞﾓｼﾞｭｰﾙID | Z2: =表紙!$AJ$64 -> MSBB | AE2: ｻﾌﾞﾓｼﾞｭｰﾙ名 | AJ2: =表紙!$AX$64 -> 販売Webシステム | AS2: =表紙!$BL$64 -> M7-US-1140 | AZ2: =表紙!$BU$64 -> 7.0.2 | BF2: =表紙!$CB$64 -> 1
K3: =RIGHT(CELL("filename",$A$1),LEN(CELL("filename",$A$1))-FIND("]",CELL("filename",$A$1))) -> 画面遷移 | U3: 表題 | Z3: =表紙!$AJ$65 -> MSBBPA110 | AE3: =表紙!$AQ$65 -> Web取引先マスタ
A5: 画面遷移フロー図
A6: ＩＤ | C6: S01 | E6: Web取引先マスタから他画面の画面遷移
D8: NO1
D9: Web取引先マスタ一覧照会 | R9: Web取引先マスタ
D14: NO2
D15: Web汎用検索(共通検索)
A20: ID | D20: 処理名
A21: S01 | D21: Web取引先マスタから他画面の画面遷移
B23: NO | D23: 遷移元ＩＤ | H23: 遷移元画面名 | Q23: 遷移先ＩＤ | V23: 遷移先画面名 | AE23: 目的 | AJ23: 引継項目 | AS23: 遷移後のアクション(遷移先) | BC23: 戻り値 | BL23: 戻り値取得後のアクション(遷移元) | BV23: 備考
B24: 1 | D24: MSBBPA110 | H24: Web取引先マスタ | Q24: MSBBPA120 | V24: Web取引先マスタ一覧照会 | AE24: 検索結果取得 | AS24: 検索 | BC24: 各種検索画面の選択データ(1行) | BL24: 対象データに値セット | BV24: CD、名称に値セット
B25: 2 | D25: MSBBPA110 | H25: Web取引先マスタ | Q25: MSBBPA900 | V25: Web汎用検索(共通検索) | AE25: 検索結果取得 | AS25: 検索 | BC25: 各種検索画面の選択データ(1行) | BL25: 対象データに値セット | BV25: CD、名称に値セット
B26: 3
B27: 4
B28: 5
B29: 6
B30: 7
B31: 8

Sheet メッセージ一覧
A1: =表紙!A54 -> Webシステム | K1: 文書名 | U1: モジュールID | Z1: =表紙!$AJ$63 -> MS | AE1: モジュール名 | AJ1: =表紙!$AX$63 -> Webシステム | AS1: 文書番号 | AZ1: Version | BF1: Rev.
K2: =表紙!O64 -> アドオン設計書 | U2: ｻﾌﾞﾓｼﾞｭｰﾙID | Z2: =表紙!$AJ$64 -> MSBB | AE2: ｻﾌﾞﾓｼﾞｭｰﾙ名 | AJ2: =表紙!$AX$64 -> 販売Webシステム | AS2: =表紙!$BL$64 -> M7-US-1140 | AZ2: =表紙!$BU$64 -> 7.0.2 | BF2: =表紙!$CB$64 -> 1
K3: =RIGHT(CELL("filename",$A$1),LEN(CELL("filename",$A$1))-FIND("]",CELL("filename",$A$1))) -> メッセージ一覧 | U3: 表題 | Z3: =表紙!$AJ$65 -> MSBBPA110 | AE3: =表紙!$AQ$65 -> Web取引先マスタ
C4: ↓アドオン画面のため、基本全て[新]
A5: No | C5: 新/変 | E5: 種別 | G5: メッセージ内容 | AQ5: 備考（パラメータ等） | BG5: メッセージID
A6: 1 | C6: 新 | E6: W | G6: 「必須項目に値が指定されていません。」 | AQ6: 取引先名、拠点CD | BG6: メッセージID.001
A8: 2 | C8: 新 | E8: W | G8: 「いずれかを選択してください。」 | AQ8: 得意先、売掛先、請求先、入金先、納品先 | BG8: メッセージID.002
G9: ※得意先、売掛先、請求先、入金先、納品先、発注先、買掛先、支払予定管理先、支払先…いずれかにチェックが無い場合 | AQ9: 発注先、買掛先、支払予定管理先、支払先
A11: 3 | C11: 新 | E11: W | G11: 「必須項目に値が指定されていません。(得意先選択時)」 | AQ11: 売掛先(&売掛先FLG=OFFの場合) | BG11: メッセージID.003
AQ12: 営業担当、業務担当
A14: 4 | C14: 新 | E14: W | G14: 「必須項目に値が指定されていません。(売掛先選択時)」 | AQ14: 請求先(&請求先FLG=OFFの場合) | BG14: メッセージID.004
A16: 5 | C16: 新 | E16: W | G16: 「必須項目に値が指定されていません。(請求先選択時)」 | AQ16: 入金先(&入金先FLG=OFFの場合) | BG16: メッセージID.005
A18: 6 | C18: 新 | E18: W | G18: 「必須項目に値が指定されていません。(納品先選択時)」 | AQ18: 物流グループCD | BG18: メッセージID.006
A20: 7 | C20: 新 | E20: W | G20: 「必須項目に値が指定されていません。(発注先選択時)」 | AQ20: 発注先パターン、買掛先(&買掛先FLG=OFFの場合) | BG20: メッセージID.007
AQ21: 仕入金額端数処理区分、仕入税額端数処理区分
AQ22: 支給積送管理区分、仕入ロット明細分割区分
A23: 8 | C23: 新 | E23: W | G23: 「必須項目に値が指定されていません。(発注先選択時、有償支給先ＦＬＧ=ON)」 | AQ23: 支給金額端数処理区分、支給税額端数処理区分 | BG23: メッセージID.008
AQ24: 支給税計算区分
A26: 9 | C26: 新 | E26: W | G26: 「必須項目に値が指定されていません。(発注先選択時、有償支給先ＦＬＧ=ON、買戻義務ＦＬＧ=ON)」 | AQ26: 支給税ＣＤ | BG26: メッセージID.009
A28: 10 | C28: 新 | E28: W | G28: 「必須項目に値が指定されていません。(買掛先選択時)」 | AQ28: 支払予定管理先(&支払予定管理先FLG=OFFの場合) | BG28: メッセージID.010
A30: 11 | C30: 新 | E30: W | G30: 「必須項目に値が指定されていません。(支払予定管理先選択時)」 | AQ30: 支払先(&支払先FLG=OFFの場合) | BG30: メッセージID.011
AQ31: 支払予定管理先担当部門ＣＤ
A32: 12 | C32: 新 | E32: W | G32: 「必須項目に値が指定されていません。(支払予定管理先選択時、都度支払ＦＬＧ=OFF)」 | AQ32: 支払締日１ | BG32: メッセージID.012
A34: 13 | C34: 新 | E34: W | G34: 「必須項目に値が指定されていません。(支払予定管理先選択時、支払税計算ＦＬＧ=ON)」 | AQ34: 支払税額端数処理区分 | BG34: メッセージID.013
A36: 14 | C36: 新 | E36: W | G36: 「必須項目に値が指定されていません。(支払予定管理先選択時、バッチ支払予定締ＦＬＧ=ON)」 | AQ36: 支払予定締遅延日数 | BG36: メッセージID.014
A38: 15 | C38: 新 | E38: W | G38: 「文字列がパターンに一致しません。項目名：パラメータ1、パターン：パラメータ2」 | AQ38: 郵便番号、納品計算書_郵便番号 | BG38: メッセージID.015
AQ39: 請求書郵便番号、領収書郵便番号
AQ40: パラメータ2:郵便番号（半角大文字アルファベット、半角数字、半角スペース、「-」から成り立つ文字列）
A42: 16 | C42: 新 | E42: W | G42: 「文字列がパターンに一致しません。項目名：パラメータ1、パターン：パラメータ2」 | AQ42: ＴＥＬ、ＦＡＸ | BG42: メッセージID.016
AQ44: パラメータ2:電話番号（「+」、「-」、半角スペース、「(」、「)」、半角数字から成り立つ文字列）
A46: 17 | C46: 新 | E46: W | G46: 「「1～31, 99」の数値を指定してください。 項目名：パラメータ」 | AQ46: 請求締日1、支払締日1、集金予定日 | BG46: メッセージID.017
A48: 18 | C48: 新 | E48: W | G48: 「変更が許可されていません。 項目名：パラメータ」 | AQ48: 得意先FLG、売掛先FLG、請求先FLG、入金先FLG | BG48: メッセージID.018
AQ49: 発注先FLG、買掛先FLG、支払予定管理先FLG
AQ50: 支払先FLG、与信管理先FLG、納品先FLG、メーカFLG
AQ51: 有償支給先FLG、支給積送管理区分
AQ52: 外注単価区分、買戻義務FLG

Sheet ファイル入出力仕様
A1: =表紙!A54 -> Webシステム | K1: 文書名 | U1: モジュールID | Z1: =表紙!$AJ$63 -> MS | AE1: モジュール名 | AJ1: =表紙!$AX$63 -> Webシステム | AS1: 文書番号 | AZ1: Version | BF1: Rev.
K2: =表紙!O64 -> アドオン設計書 | U2: ｻﾌﾞﾓｼﾞｭｰﾙID | Z2: =表紙!$AJ$64 -> MSBB | AE2: ｻﾌﾞﾓｼﾞｭｰﾙ名 | AJ2: =表紙!$AX$64 -> 販売Webシステム | AS2: =表紙!$BL$64 -> M7-US-1140 | AZ2: =表紙!$BU$64 -> 7.0.2 | BF2: =表紙!$CB$64 -> 1
K3: =RIGHT(CELL("filename",$A$1),LEN(CELL("filename",$A$1))-FIND("]",CELL("filename",$A$1))) -> ファイル入出力仕様 | U3: 表題 | Z3: =表紙!$AJ$65 -> MSBBPA110 | AE3: =表紙!$AQ$65 -> Web取引先マスタ
A5: No | G5: 1 | S5: ロジック名称 | AH5: 備考
A6: 処理分類 | E6: 更新
A7: No | C7: 転送先 | V7: 転送元 | AQ7: 説明
C8: 種 | D8: オブジェクト | K8: 項目名 | V8: 種 | W8: オブジェクト | AF8: 項目名

Sheet テーブル項目_WEB取引先マスタ
A1: =表紙!A54 -> Webシステム | K1: 文書名 | U1: モジュールID | Z1: =表紙!$AJ$63 -> MS | AE1: モジュール名 | AJ1: =表紙!$AX$63 -> Webシステム | AS1: 文書番号 | AZ1: Version | BF1: Rev.
K2: =表紙!O64 -> アドオン設計書 | U2: ｻﾌﾞﾓｼﾞｭｰﾙID | Z2: =表紙!$AJ$64 -> MSBB | AE2: ｻﾌﾞﾓｼﾞｭｰﾙ名 | AJ2: =表紙!$AX$64 -> 販売Webシステム | AS2: =表紙!$BL$64 -> M7-US-1140 | AZ2: =表紙!$BU$64 -> 7.0.2 | BF2: =表紙!$CB$64 -> 1
K3: =RIGHT(CELL("filename",$A$1),LEN(CELL("filename",$A$1))-FIND("]",CELL("filename",$A$1))) -> テーブル項目_WEB取引先マスタ | U3: 表題 | Z3: =表紙!$AJ$65 -> MSBBPA110 | AE3: =表紙!$AQ$65 -> Web取引先マスタ
A5: テーブル名 | O5: 日本語名 | AE5: 種別
O6: WEB取引先マスタ | AE6: アドオン(新規)
A8: 主キー | D8: 項目名 | O8: 日本語名 | AE8: 型 | AG8: 桁 | AI8: Null | AK8: 説明 | BL8: 値の制限 | BM8: 設定仕様 | BN8: 未設定時の振る舞い | BO8: 画面
A9: 〇 | D9: BP_CD | O9: 取引先CD | AE9: C | AG9: 20 | AI9: N
D10: BP_STATUS | O10: ステータス | AE10: C | AG10: 2 | AI10: N
D11: BP_ALT_NM1 | O11: 取引先名 | AE11: C | AG11: 100 | AI11: Y
D12: BP_NM | O12: 取引先略称 | AE12: C | AG12: 10 | AI12: Y
D13: BASE_CD | O13: 拠点CD | AE13: C | AG13: 10 | AI13: Y
D14: STD_CO_CD | O14: 標準企業コード | AE14: C | AG14: 20 | AI14: Y
D15: EIN | O15: 法人番号 | AE15: C | AG15: 13 | AI15: Y
D16: EIN_TYP | O16: 法人番号区分 | AE16: C | AG16: 2 | AI16: Y
D17: LOCAL_PUBLIC_CD | O17: 地方公共団体CD | AE17: C | AG17: 5 | AI17: Y
D18: DENZAI_NO | O18: でんさい利用者番号 | AE18: C | AG18: 9 | AI18: Y
D19: ZIP_CD | O19: 郵便番号 | AE19: C | AG19: 10 | AI19: Y
D20: ADDR1 | O20: 都道府県 | AE20: C | AG20: 40 | AI20: Y
D21: ADDR2 | O21: 市区町村 | AE21: C | AG21: 40 | AI21: Y
... D28: BUS_USR_CD | O28: 業務担当CD | AE28: C | AG28: 500 | AI28: Y
D29: CST_FLG | O29: 得意先FLG | AE29: F | AI29: N
D30: ACST_FLG | O30: 売掛先FLG | AE30: F | AI30: N
D31: BCST_FLG | O31: 請求先FLG | AE31: F | AI31: N
D32: RCST_FLG | O32: 入金先FLG | AE32: F | AI32: N
D33: DLV_FLG | O33: 納品先FLG | AE33: F | AI33: N
D34: SPPL_FLG | O34: 発注先FLG | AE34: F | AI34: N
D35: ASPPL_FLG | O35: 買掛先FLG | AE35: F | AI35: N
D36: BSPPL_FLG | O36: 支払予定管理先FLG | AE36: F | AI36: N
D37: PSPPL_FLG | O37: 支払先FLG | AE37: F | AI37: N
D38: BP_GRP_CD1 | O38: 取引先分類1 | AE38: C | AG38: 10 | AI38: Y
D39: BP_GRP_CD2 | O39: 取引先分類2 | AE39: C | AG39: 10 | AI39: Y
D40: BP_GRP_CD3 | O40: 取引先分類3 | AE40: C | AG40: 10 | AI40: Y
D41: BP_GRP_CD4 | O41: 取引先分類4 | AE41: C | AG41: 10 | AI41: Y
D42: BP_GRP_CD5 | O42: 取引先分類5 | AE42: C | AG42: 10 | AI42: Y
D43: BP_GRP_CD6 | O43: 取引先分類6 | AE43: C | AG43: 10 | AI43: Y
D44: BP_GRP_CD7 | O44: 取引先分類7 | AE44: C | AG44: 10 | AI44: Y
D45: BP_GRP_CD8 | O45: 取引先分類8 | AE45: C | AG45: 10 | AI45: Y
D46: BP_GRP_CD9 | O46: 取引先分類9 | AE46: C | AG46: 10 | AI46: Y
D47: BP_GRP_CD10 | O47: 取引先分類10 | AE47: C | AG47: 10 | AI47: Y
D48: SLS_ANLY_CD01 | O48: 販売分析１ | AE48: C | AG48: 10 | AI48: Y
D49: SLS_ANLY_CD02 | O49: 販売分析２ | AE49: C | AG49: 10 | AI49: Y
... D53: ACST_CD | O53: 売掛先CD | AE53: C | AG53: 20 | AI53: Y
D54: CRED_FLG | O54: 与信管理先FLG | AE54: F | AI54: N
D55: CST_CNTCT_DPT | O55: 得意先部署 | AE55: C | AG55: 100 | AI55: Y
D56: CST_CNTCT_PSN | O56: 得意先担当者 | AE56: C | AG56: 100 | AI56: Y
D57: CST_CNTCT_PSN_TITLE | O57: 得意先担当者敬称 | AE57: C | AG57: 10 | AI57: Y
D58: CPRL_TYP | O58: 容器リ法対象 | AE58: C | AG58: 2 | AI58: Y
D59: SLS_BASIS_TYP | O59: 売上計上区分 | AE59: C | AG59: 2 | AI59: Y
D60: SLS_SHEET_CALC_TYP | O60: シート枚売上時の計算方法 | AE60: C | AG60: 2 | AI60: Y
D61: SLS_BASIS_TYP_M | O61: 売上計算区分(㎡) | AE61: C | AG61: 2 | AI61: Y
D62: SLS_BASIS_TYP_S | O62: 売上計算区分(枚) | AE62: C | AG62: 2 | AI62: Y
D63: SLS_RND_TYP | O63: 端数計算処理区分 | AE63: C | AG63: 2 | AI63: Y
D64: SLS_ZENPAN_TYP | O64: 全判売区分 | AE64: C | AG64: 2 | AI64: Y
D65: SLITTER_BILL_TYP | O65: スリッター請求区分 | AE65: C | AG65: 2 | AI65: Y
D66: SLITTER_BILL_PRICE | O66: スリッター請求単価 | AE66: N | AI66: Y
D67: SLITTER_MAX_LENG | O67: スリッター最大流 | AE67: N | AI67: Y
D68: PRINT_MIN_BILL_TYP | O68: 印刷最低請求 | AE68: C | AG68: 2 | AI68: Y
D69: PRINT_MIN_BILL_LESS | O69: 印刷最低請求未満 | AE69: N | AI69: Y
D70: PRINT_MIN_BILL_UNIT | O70: 印刷最低請求単位 | AE70: C | AG70: 2 | AI70: Y
D71: BOND_MIN_BILL_TYP | O71: 貼合最低請求 | AE71: C | AG71: 2 | AI71: Y
D72: BOND_MIN_BILL_LESS | O72: 貼合最低請求未満 | AE72: N | AI72: Y
D73: BOND_MIN_BILL_UNIT | O73: 貼合最低請求単位 | AE73: C | AG73: 2 | AI73: Y
D74: BOND_ADD_COST | O74: 貼合増@ | AE74: N | AI74: Y
D75: BOND_ADD_BILL | O75: 貼合増請求表示 | AE75: C | AG75: 2 | AI75: Y
D76: PROCESS_ESTIMATE_LOWEST | O76: 加工見積最低 | AE76: C | AG76: 2 | AI76: Y
D77: DLV_SLIP_OUTPUT_TYP | O77: 納品書出力区分 | AE77: C | AG77: 2 | AI77: Y
D78: DLV_SLIP_PRINT_TYP | O78: 納品書発行区分 | AE78: C | AG78: 2 | AI78: Y
D79: TOKUDEN_TYP | O79: 特伝区分 | AE79: C | AG79: 2 | AI79: Y
D80: YOZUMI_TYP | O80: 夜積区分 | AE80: C | AG80: 2 | AI80: Y
D81: SIZE_PURINT_TYP | O81: 寸法印字区分 | AE81: C | AG81: 2 | AI81: Y
D82: DLVCALC_OUTPUT_TYP | O82: 納品計算出力区分 | AE82: C | AG82: 2 | AI82: Y
D83: DLVCALC_PRINT_TYP | O83: 納品計算書発行区分 | AE83: C | AG83: 2 | AI83: Y
D84: DLVCALC_OUTPUT_TYP2 | O84: 納品計算出力区分2 | AE84: C | AG84: 2 | AI84: Y
D85: DLVCALC_BCST_NM | O85: 納品計算_宛先 | AE85: C | AG85: 100 | AI85: Y
D86: DLVCALC_BCST_PSN | O86: 納品計算_送付担当者 | AE86: C | AG86: 100 | AI86: Y
... D94: AR_CRED_CD | O94: 債権与信管理先CD | AE94: C | AG94: 20 | AI94: Y
D95: BILL_CL_DAY1 | O95: 請求締日1 | AE95: N | AG95: 2,0 | AI95: Y
D96: BILL_PRINT_TYP | O96: 請求書印刷区分 | AE96: C | AG96: 2 | AI96: Y
D97: BILL_SEAL_TYP | O97: 請求書封緘区分 | AE97: C | AG97: 2 | AI97: Y
D98: BILL_ELEC_TYP | O98: 電子請求請求書 | AE98: C | AG98: 2 | AI98: Y
D99: BILL_BCST_NM | O99: 請求書_宛先 | AE99: C | AG99: 100 | AI99: Y
D100: BILL_BCST_PSN | O100: 請求書_送付担当者 | AE100: C | AG100: 100 | AI100: Y
D101: BILL_ZIP_CD | O101: 請求書_郵便番号 | AE101: C | AG101: 10 | AI101: Y
D102: BILL_ADDR1 | O102: 請求書_都道府県 | AE102: C | AG102: 40 | AI102: Y
D103: BILL_ADDR2 | O103: 請求書_市区町村 | AE103: C | AG103: 40 | AI103: Y
D104: BILL_ADDR3 | O104: 請求書_町域・番地 | AE104: C | AG104: 40 | AI104: Y
D105: BILL_ADDR4 | O105: 請求書_建物など | AE105: C | AG105: 40 | AI105: Y
D106: XFR_PSN | O106: 振込人名 | AE106: C | AG106: 100 | AI106: Y
D107: RCST_BANK_CD | O107: 銀行(入金先) | AE107: C | AG107: 15 | AI107: Y
... D110: BANK_AC_TYP | O110: 仮口座区分 | AE110: C | AG110: 2 | AI110: Y
D111: BANK_AC_DT | O111: 本口座登録日 | AE111: D | AI111: Y
D112: DRAWER | O112: 振出人 | AE112: C | AG112: 100 | AI112: Y
D113: COLLECT_TYP | O113: 集金区分 | AE113: C | AG113: 2 | AI113: Y
D114: COLLECT_TOBE_DAY | O114: 集金予定日 | AE114: N | AG114: 2,0 | AI114: Y
D115: BILL_NOTE_TYP | O115: 手形回り区分 | AE115: C | AG115: 2 | AI115: Y
D116: RECEIPT_BCST_NM | O116: 領収書_宛先 | AE116: C | AG116: 100 | AI116: Y
D117: RECEIPT_BCST_PSN | O117: 領収書_送付担当者 | AE117: C | AG117: 100 | AI117: Y
D118: RECEIPT_ZIP_CD | O118: 領収書_郵便番号 | AE118: C | AG118: 10 | AI118: Y
D119: RECEIPT_ADDR1 | O119: 領収書_都道府県 | AE119: C | AG119: 40 | AI119: Y
D120: RECEIPT_ADDR2 | O120: 領収書_市区町村 | AE120: C | AG120: 40 | AI120: Y
...

Sheet |→補足シート

Sheet mcf取引先
AS7: 【運用後の変更に注意が必要な項目】
AS8: 項目名 | AT8: 変更不可理由
AS9: 得意先FLG | AT9: オンからオフへの変更は不可
AS10: 売掛先FLG | AT10: オンからオフへの変更は不可
AS11: 請求先FLG | AT11: オンからオフへの変更は不可
AS12: 入金先FLG | AT12: オンからオフへの変更は不可
AS13: 発注先FLG | AT13: オンからオフへの変更は不可
AS14: 買掛先FLG | AT14: オンからオフへの変更は不可
AS15: 支払予定管理先FLG | AT15: オンからオフへの変更は不可
AS16: 支払先FLG | AT16: オンからオフへの変更は不可
AS17: 与信管理先FLG | AT17: オンからオフへの変更は不可
AS18: 納品先FLG | AT18: オンからオフへの変更は不可
AS19: メーカFLG | AT19: オンからオフへの変更は不可
... AS27: 買戻義務FLG | AT27: 途中で変更すると有償支給在庫の資産管理区分、外注仕入の有償支給税額に影響するため
AS31: 【運用後の変更に注意が必要な項目】
AS32: 項目名 | AT32: 変更不可理由
AS33: 得意先FLG | AT33: オンからオフへの変更は不可
AS34: 売掛先FLG | AT34: オンからオフへの変更は不可
AS35: 請求先FLG | AT35: オンからオフへの変更は不可
AS36: 入金先FLG | AT36: オンからオフへの変更は不可
AS37: 発注先FLG | AT37: オンからオフへの変更は不可
AS38: 買掛先FLG | AT38: オンからオフへの変更は不可
AS39: 支払予定管理先FLG | AT39: オンからオフへの変更は不可
AS40: 支払先FLG | AT40: オンからオフへの変更は不可
AS41: 与信管理先FLG | AT41: オンからオフへの変更は不可
AS42: 納品先FLG | AT42: オンからオフへの変更は不可
AS43: メーカFLG | AT43: オンからオフへの変更は不可
... AS47: 買戻義務FLG | AT47: 途中で変更すると有償支給在庫の資産管理区分、外注仕入の有償支給税額に影響するため

Sheet 補足説明資料
A1: =表紙!A54 -> Webシステム | O1: 文書名 | AC1: モジュールID | AJ1: =表紙!AJ64 -> MSBB | AQ1: モジュール名 | AX1: =表紙!AX64 -> 販売Webシステム | BL1: 文書番号 | BU1: Version | CB1: Rev.
O2: =表紙!O65 -> 表紙 | AC2: サブモジュールID | AJ2: =表紙!AJ65 -> MSBBPA110 | AQ2: サブモジュール名 | AX2: =表紙!AX65 -> 0 | BL2: =表紙!BL65 -> 0 | BU2: =表紙!BU65 -> 0 | CB2: =表紙!CB65 -> 0
O3: =RIGHT(CELL("filename",$A$1),LEN(CELL("filename",$A$1))-FIND("]",CELL("filename",$A$1))) -> 補足説明資料 | AC3: 表題 | AJ3: =表紙!AJ66 -> 0 | AQ3: =表紙!AQ66 -> 0
AO5: 補足説明
