Workbook
Name Rev.: 表紙!$U$22
Name Revision: 表紙!$AP$5
Name Ver.: 表紙!$AE$26
Name ご確認者: 表紙!$AG$40
Name ご確認日: 表紙!$AG$42
Name サブシステム名: 表紙!$U$28
Name システム名: 表紙!$U$26
Name プロジェクト名: 表紙!$U$18
Name 開発区分: 表紙!$U$36
Name 機能ＩＤ: 表紙!$U$32
Name 機能区分: 表紙!$U$34
Name 機能名称: 表紙!$U$30
Name 顧客名: 表紙!$U$16
Name 最終更新者: 表紙!$AB$40
Name 最終更新日: 表紙!$AB$42
Name 作成者: 表紙!$W$40
Name 作成日: 表紙!$W$42
Name 章: 表紙!$M$10
Name 発行日: 表紙!$W$42
Name 文書番号: 表紙!$O$5
Name 文書名: 表紙!$M$10

Sheet 表紙
AW2: サブモジュール
AW3: MA_マスタ管理
AW4: MB_業務共通
AW5: MG_原価管理
AW6: MSBA_需給管理
M7: 基本設計 | AW7: MSBB_販売管理
AW8: MSBC_生産管理
AW9: MSBD_購買管理
M10: 画面機能 | AW10: MSBE_在庫物流管理
AW11: MSBF_品質管理
AW12: MSBG_債権管理
AW13: MSBH_債務管理
AW14: MSBI_締処理
AW15: MSUA_リスト・入力補助
M16: 顧客 | U16: 株式会社クラウン・パッケージ | AW16: PF_ESBアダプタ
M18: プロジェクト名 | U18: 新基幹システム導入 | AW18: 機能区分
AW19: 画面
M20: 文書番号 | U20: =A50 -> M7-US-1140 | AW20: 帳票
AW21: バッチ
M22: Ｒｅｖ． | U22: {=MAX(_xlfn.NUMBERVALUE(改訂!A7:E46))} -> 3 | AW22: マスタ
M24: 機密性区分 | U24: 取扱注意（Ｃ） | AW24: 開発区分
AW25: カスタマイズ
M26: システム名 | U26: Webシステム | AC26: Ver. | AE26: 7.0.2 | AW26: アドオン
AW27: －
M28: サブモジュール | U28: MSBB_販売管理
M30: 機能名 | U30: =M50 -> Web版型・木型マスタ
M32: 機能ID | U32: =G50 -> MSBBPA140
M34: 機能区分 | U34: 画面
M36: 開発区分 | U36: アドオン
W39: 作成 | AB39: 最終更新 | AG39: ご確認
W40: MDSOL
W42: 44643
A48: 文書番号 | G48: 画面ID | M48: 画面名 | V48: Version | AB48: Revision
A50: M7-US-1140 | G50: MSBBPA140 | M50: Web版型・木型マスタ | V50: 1.0.0 | AB50: r01.00
A53: 共通（元データ）
A54: Webシステム | K54: 文書名 | U54: モジュールID | Z54: MS | AE54: モジュール名 | AJ54: 見積管理 | AS54: 文書番号 | AZ54: Version | BF54: Rev.
K55: 画面説明書 | U55: ｻﾌﾞﾓｼﾞｭｰﾙID | Z55: MSBB | AE55: ｻﾌﾞﾓｼﾞｭｰﾙ名 | AJ55: Webシステム | AS55: M7-US-1140 | AZ55: 1.0.0 | BF55: r00.00
K56: 表紙 | U56: 表題 | Z56: アドオン画面 | AE56: Web版型・木型マスタ
A57: 共通（リンク用）
A58: =A54 -> Webシステム | K58: 文書名 | U58: モジュールID | Z58: =IF(Z54="","",Z54) -> MS | AE58: モジュール名 | AJ58: =IF(AJ54="","",AJ54) -> 見積管理 | AS58: 文書番号 | AZ58: Version | BF58: Rev.
K59: =文書名 -> 画面機能 | U59: ｻﾌﾞﾓｼﾞｭｰﾙID | Z59: =IF(Z55="","",Z55) -> MSBB | AE59: ｻﾌﾞﾓｼﾞｭｰﾙ名 | AJ59: =IF(AJ55="","",AJ55) -> Webシステム | AS59: =AS55 -> M7-US-1140 | AZ59: =AZ55 -> 1.0.0 | BF59: =BF55 -> r00.00
K60: =RIGHT(CELL("filename",$A$1),LEN(CELL("filename",$A$1))-FIND("]",CELL("filename",$A$1))) -> 表紙 | U60: 表題 | Z60: =IF(Z56="","",Z56) -> アドオン画面 | AE60: =AE56 -> Web版型・木型マスタ
A62: 概要シート用
A63: =A58 -> Webシステム | O63: 文書名 | AC63: モジュールID | AJ63: =Z58 -> MS | AQ63: モジュール名 | AX63: =AJ58 -> 見積管理 | BL63: 文書番号 | BU63: Version | CB63: Rev.
O64: =K59 -> 画面機能 | AC64: サブモジュールID | AJ64: =Z59 -> MSBB | AQ64: サブモジュール名 | AX64: =AJ59 -> Webシステム | BL64: =AS59 -> M7-US-1140 | BU64: =AZ55 -> 1.0.0 | CB64: {=MAX(_xlfn.NUMBERVALUE(改訂!A7:E46))} -> 3
O65: =RIGHT(CELL("filename",$A$1),LEN(CELL("filename",$A$1))-FIND("]",CELL("filename",$A$1))) -> 表紙 | AC65: 表題 | AJ65: =Z60 -> アドオン画面 | AQ65: =AE60 -> Web版型・木型マスタ

Sheet 改訂
K1: 改訂 | AU1: 作成者 | AZ1: MDSOL | BE1: 作成日 | BJ1: =表紙!W42 -> 44643 | BP1: Rev.
AU2: 修正者 | AZ2: MDSOL | BE2: 改訂日 | BJ2: 44894 | BP2: =表紙!CB64 -> 3
A5: Rev. | F5: 改定内容 | BC5: 頁 | BM5: 変更日 変更者 | BR5: 確認日 確認者
A7: 1 | F7: 新規作成 | BM7: 44865
BM8: MDSOL
A9: 2 | F9: 処理関連図/サービス関連図 ・・・ 実績テーブルを追加、詳細記述 検索入出力仕様 ・・・ 転送元のテーブル名不正を訂正(通し数の実績テーブルの名称不正の訂正) | BC9: 概要、検索入出力仕様 処理・サービス関連図 | BM9: 44894
BM10: MDSOL
A11: 2 | F11: 案件NOをDBの項目は、案件NO(親)＋案件NO(子)＋案件NO(部材)に分割する ※画面項目は、1つとする | BC11: 検索入出力仕様 | BM11: 44894
BM12: MDSOL
A13: 3 | F13: 詳細設計の追加 | BC13: 画面遷移 処理詳細 | BM13: 44896
BM14: TBK華
A15: 3 | F15: メッセージIDの採番 | BC15: メッセージ一覧 | BM15: 44931
BM16: TBK華

Sheet 概要
A1: =表紙!A54 -> Webシステム | O1: 文書名 | AC1: モジュールID | AJ1: =表紙!$AJ$63 -> MS | AQ1: モジュール名 | AX1: =表紙!$AX$63 -> 見積管理 | BL1: 文書番号 | BU1: Version | CB1: Rev.
O2: =表紙!O64 -> 画面機能 | AC2: サブモジュールID | AJ2: =表紙!$AJ$64 -> MSBB | AQ2: サブモジュール名 | AX2: =表紙!$AX$64 -> Webシステム | BL2: =表紙!$BL$64 -> M7-US-1140 | BU2: =表紙!$BU$64 -> 1.0.0 | CB2: =表紙!$CB$64 -> 3
O3: =RIGHT(CELL("filename",$A$1),LEN(CELL("filename",$A$1))-FIND("]",CELL("filename",$A$1))) -> 概要 | AC3: 表題 | AJ3: =表紙!$AJ$65 -> アドオン画面 | AQ3: =表紙!$AQ$65 -> Web版型・木型マスタ
AO5: 概要
B8: 【業務要件】
C9: カスタマイズ | G9: 内容
C10: No.
C11: 98 | G11: 管理している木型・版型のマスタをメンテナンスする画面
G12: 製造時に使用した木型、版型の通し数の管理が必要
G13: →通し数のカウントアップは、通し数集計バッチにて実施する
B16: 【機能概要】
C17: 1. | D17: 見積確定WFを確認し、木型・版型の情報を登録する、新規登録時は決定見積NOを入力し初期情報を表示する
D18: 木型・版型Noや品目で検索を行い、木型・版型の情報を参照する
C19: 2. | D19: 木型・版型管理マスタの情報についてメンテナンスを行う
D20: 廃棄予定日や適用期間の調整、使用不可(論理削除)の設定を行う
B23: 【前提条件】
C24: 1. | D24: 場所・棚ライン、通し数に関しては画面より変更しない、発注先・加工予定先は本画面のみに使用する情報となる。(発注登録等に連携はしない。)
C25: 2. | D25: ファイル取込によるデータ更新は行わない
B27: 【説明】
C28: 木型・版型情報のメンテナンス及び参照を行う画面
B30: 【目的】
C32: 目的（レベル１） | Q32: 目的（レベル２） | AT32: 利用シーン/補足 | BV32: 操作種別/検索モード
C33: 木型・版型管理マスタを | BV33: 登録
C34: 登録する。
C35: 木型・版型管理マスタを | BV35: 改定
C36: 改定する。
C37: 木型・版型管理マスタを | BV37: 訂正
C38: 訂正する。
C39: 木型・版型管理マスタを | BV39: 削除
C40: 削除する（管理者のみ）。
C41: 木型・版型管理マスタを | BV41: 参照
C42: 参照する。
B45: 【処理関連図/サービス関連図】
C46: ■訂正する
C47: 検索処理
CK48: Rev2.0 記述追加
C57: 更新処理
B64: 【オペレーション一覧】
C66: ID | L66: 処理名 | Y66: 処理概要
C67: Srch01 | L67: 検索 | Y67: 木型・版型管理マスタの検索処理を行う。
C68: Upd01 | L68: 登録 | Y68: 木型・版型管理マスタの登録処理を行う。
C69: Del01 | L69: 削除 | Y69: 木型・版型管理マスタの削除処理を行う。
B72: 【SQLID一覧】
C73: なし
B75: 【ソート順】
C77: オペレーションID | J77: 一覧名 | Q77: ソート順 | BA77: 条件
J78: 一覧 | Q78: 木型・版型No、Rev
B80: 【データアクセスコントロール】
C82: ボタン名 | J82: データアクセスコントロール対象項目 | Z82: 条件
J83: なし
B85: 【自由記述】
C86: なし

Sheet Webレイアウト(登録)
A1: =表紙!A54 -> Webシステム | K1: 文書名 | U1: モジュールID | Z1: =表紙!$AJ$63 -> MS | AE1: モジュール名 | AJ1: =表紙!$AX$63 -> 見積管理 | AS1: 文書番号 | AZ1: Version | BF1: Rev.
K2: =表紙!O64 -> 画面機能 | U2: ｻﾌﾞﾓｼﾞｭｰﾙID | Z2: =表紙!$AJ$64 -> MSBB | AE2: ｻﾌﾞﾓｼﾞｭｰﾙ名 | AJ2: =表紙!$AX$64 -> Webシステム | AS2: =表紙!$BL$64 -> M7-US-1140 | AZ2: =表紙!$BU$64 -> 1.0.0 | BF2: =表紙!$CB$64 -> 3
K3: =RIGHT(CELL("filename",$A$1),LEN(CELL("filename",$A$1))-FIND("]",CELL("filename",$A$1))) -> Webレイアウト(登録) | U3: 表題 | Z3: =表紙!$AJ$65 -> アドオン画面 | AE3: =表紙!$AQ$65 -> Web版型・木型マスタ
A5: 画面イメージ
B7: ≫凡例
Q8: ・・・ | S8: ボタン
C9: 見積計算書№ | Q9: ・・・ | S9: 検索項目(検索画面表示選択)
C10: 品名 | Q10: ・・・ | S10: 入力項目
C11: 得意先 | Q11: ・・・ | S11: 表示項目(得意先名称、原紙名等)
C12: 操作種別 | I12: ●登録 | M12: ○訂正 | Q12: ・・・ | S12: 選択項目(一つのみ選択可能)
C13: 受注区分 | Q13: ・・・ | S13: 選択項目(一つのみ選択可能)
C14: 作業順 | I14: ☑AAA | M14: ☑BBB | Q14: ・・・ | S14: 選択項目(複数選択可能)
BM17: CP指摘 2022/11/09 落合 版型発注書はPOWEREGGから手動で発行でしたでしょうか？ | CO17: MDSOL回答 2022/11/10 石田 手動で発行となります。POWEREGGへのリンクボタンをつけました。
BM18: CP指摘 2022/11/09 落合 売上可否区分＝売上可の時のみ、版型受注を作成して欲しいです | CO18: MDSOL回答 2022/11/10 石田 会議にて売上可以外も受注を作成するとなりました。
BM21: CP指摘 2022/09/21 土屋 版型No1つで一意となるのであれば、版型名称とRevが表示項目かと思われます | CP21: MDSOL回答 2022/10/31 石田 検索欄について版型名に関しては表示項目になります。REVに関しては過去のデータを参照することもあるため入力としています。入力欄については、当画面で版型名を編集するため入力欄でREVは自動採番のため表示項目です。 | FI21: 2022/11/01 落合 問題なし
D22: 操作種別 | J22: ●登録 | N22: ○改定 | R22: ○訂正 | V22: ○削除 | Z22: ○参照 | BM22: CP指摘 2022/09/21 土屋 改定の入力方法の説明がツールチップあると良いと思います | CP22: MDSOL回答 2022/10/31 石田 マニュアルで対応願います。 | DI22: 2022/11/01 落合 問題なし
N24: 版型No | AN24: Rev
BM26: CP指摘 2022/09/21 土屋 添付ファイルを確認したくなる為、案件Noが表示されるていると良いお思います | CP26: MDSOL回答 2022/10/31 石田 案件NO項目を追加しました。見積計算書NOに紐づく案件NOを表示します。 | DV26: 2022/11/01 落合 問題なし
D27: 拠点
D29: 基本情報
D30: 決定見積NO | J30: X/999999 | W30: 案件NO | BM30: CP指摘 2022/09/22 三宅 | CA30: MDSOL回答 2022/10/31 石田 mcframeに操作感を合わせラジオボタンで切替になります。初期は登録になります。 | DI30: 2022/11/01 落合 問題なし
D31: 版型名 | W31: 売上可否区分 | AC31: (売上可否区分) | AI31: 手配NO | BN31: 操作種別 ○登録 ○訂正 ○削除 ○参照
D32: 版型No | J32: (自動採番) | W32: Rev | AI32: 適用開始日 | BN32: ラジオボタンで切替？初期値は登録？
D33: 得意先
D34: 代表製品CD | AI34: 新版区分 | BN34: 一般的なWebシステムのような、URL別に
BN35: /patterns 一覧 詳細表示へ
D36: 工程 | AI36: 版型分類 | BN36: /patterns/create 登録 完了したら詳細表示へ
D37: 最終加工場所 | AI37: 実績日(最終使用日) | BN37: /patterns/1234567 現行詳細表示 編集・削除へ
BN38: /patterns/1234567/1 詳細表示 Rev
BN39: /patterns/1234567/edit 編集 完了したら詳細表示へ
D40: 構成情報 | BN40: で
D41: シート 段 | J41: E | O41: 原紙 | X41: 印刷 | AI41: エンボス | AT41: メーカ | BN41: 新規登録画面で「登録」、登録後は「参照」画面に遷移
F42: 表 | BN42: 「参照」で開いて「訂正」「削除」に切替可能
F43: 中 | BN43: というような動線ではなくて、mcframeやオフコンの画面をそのまま再現したような
F44: 裏 | BN44: /patterns 一画面に全部詰め込むようなイメージ?
BN45: mcframeと似たような操作性にしたいという想定と考えられるので反対はしないが
D46: 抜方向 | J46: リスト選択 | R46: 面付け | Y46: ~ | AD46: 複版 | AI46: リスト選択 | BN46: 適切に切り分けて開発していただきたい
D47: シート寸法 | M47: ×
D48: 刃渡り寸法 | M48: × | R48: 付数 | AD48: 個数 | AO48: 色数 | AW48: 本数
D49: フレキソ版厚 | R49: シリンダーサイズ
D51: 発注先 | AD51: 加工予定先
D52: 納期 | R52: 入荷実績日
D53: 見積価格 | R53: 売上決定価格 | AD53: 仕入予定金額 | AQ53: 売上日
AD54: 売上可否区分 | AI54: リスト選択 | AQ54: 売上備考
D56: 落丁型 | R56: 置き版 | W56: リスト選択 | AD56: ハンマー | AI56: リスト選択 | AQ56: 見落とし型 | AW56: リスト選択
D57: 場所 | AD57: 棚・ライン
D59: 通し数 | R59: 限界通し数 | BM59: CP指摘 2022/09/21 土屋 廃棄の実績日は不要でしょうか | CE59: MDSOL回答 2022/10/31 石田 実績日を追加致しました | CW59: 2022/11/01 落合 問題なし
D62: 廃棄予定日 | R62: 廃棄実績日
D64: 返却予定日 | R64: 返却日 | AD64: 返却理由
D66: 備考 | BM66: CP指摘 2022/09/22 三宅 添付情報や必要物は今後これ以上増えることは無いのでしょうか テーブル設計も版型マスターに決め打ちで直接持たせているので増える場合は改修コストが高そう
BM67: (そもそも元々は無かった項目なのでそこまで対応必須の追加自体が無いかも)
D68: 添付情報
E69: □表図面 □裏図面 □現物 □版下 □ポジ □ネガ □MO □FD | BM69: MDSOL回答 2022/10/31 石田 現状は現行の版型発注書に合わせ、固定になります。 | CN69: 2022/11/01 落合 問題なし
D71: 必要物
D72: タタキ | R72: マイラー | AI72: ゲラ刷り | AW72: 校正
D73: 青焼 | R73: カンプ | AI73: 印刷設計書 | AW73: その他名称
AW74: その他
D77: 過去履歴
D79: № | F79: 適用開始日 | K79: 適用終了日 | P79: Rev | R79: 発注先 | U79: 発注先名 | Y79: 通し数 | AC79: 廃棄予定日 | AH79: 返却予定日 | AM79: 返却日 | AR79: 返却理由
D81: 1 | F81: 2022/07/01 | K81: 2022/07/01 | P81: 1 | R81: 12345 | U81: XXXXXXX8 | Y81: 1000 | AC81: 2022/07/01 | AH81: 2022/07/01 | AM81: 2022/07/01 | AR81: XXXXXXX8XXXXXXX8
D82: 2 | F82: 2022/07/01 | K82: 2022/07/01 | P82: 2 | R82: 12345 | U82: XXXXXXX8 | Y82: 1000 | AC82: 2022/07/01 | AH82: 2022/07/01 | AM82: 2022/07/01 | AR82: XXXXXXX8XXXXXXX8
D83: 3 | F83: 2022/07/01 | K83: 2022/07/01 | P83: 3 | R83: 12345 | U83: XXXXXXX8 | Y83: 1000 | AC83: 2022/07/01 | AH83: 2022/07/01 | AM83: 2022/07/01 | AR83: XXXXXXX8XXXXXXX8
D84: 4 | F84: 2022/07/01 | K84: 2022/07/01 | P84: 4 | R84: 12345 | U84: XXXXXXX8 | Y84: 2000 | AC84: 2022/07/01 | AH84: 2022/07/01 | AM84: 2022/07/01 | AR84: XXXXXXX8XXXXXXX8
D85: 5 | F85: 2022/07/01 | K85: 2022/07/01 | P85: 5 | R85: 12345 | U85: XXXXXXX8 | Y85: 2000 | AC85: 2022/07/01 | AH85: 2022/07/01 | AM85: 2022/07/01 | AR85: XXXXXXX8XXXXXXX8
D86: 6 | F86: 2022/07/01 | K86: 2022/07/01 | P86: 6 | R86: 12345 | U86: XXXXXXX8 | Y86: 2000 | AC86: 2022/07/01 | AH86: 2022/07/01 | AM86: 2022/07/01 | AR86: XXXXXXX8XXXXXXX8
D87: 7 | F87: 2022/07/01 | K87: 2022/07/01 | P87: 7 | R87: 12345 | U87: XXXXXXX8 | Y87: 3000 | AC87: 2022/07/01 | AH87: 2022/07/01 | AM87: 2022/07/01 | AR87: XXXXXXX8XXXXXXX8 | BM87: CP指摘 2022/09/21 土屋 ラベル発行ボタンは、表示している版型Noのみ発行と認識しましたが、複数ラベル発行は可能なのでしょうか
D88: 8 | F88: 2022/07/01 | K88: 2022/07/01 | P88: 8 | R88: 12345 | U88: XXXXXXX8 | Y88: 3000 | AC88: 2022/07/01 | AH88: 2022/07/01 | AM88: 2022/07/01 | AR88: XXXXXXX8XXXXXXX8 | BM88: MDSOL回答 2022/10/31 石田 一覧機能により発行可能になります。 | CJ88: 2022/11/01 落合 問題なし

Sheet mcf画面イメージ
A1: mcframe 7 | K1: 文書名 | U1: モジュールID | Z1: =表紙!$AJ$63 -> MS | AE1: モジュール名 | AJ1: =表紙!$AX$63 -> 見積管理 | AS1: 文書番号 | AZ1: Version | BF1: Rev.
K2: =表紙!O64 -> 画面機能 | U2: ｻﾌﾞﾓｼﾞｭｰﾙID | Z2: =表紙!$AJ$64 -> MSBB | AE2: ｻﾌﾞﾓｼﾞｭｰﾙ名 | AJ2: =表紙!$AX$64 -> Webシステム | AS2: =表紙!$BL$64 -> M7-US-1140 | AZ2: =表紙!$BU$64 -> 1.0.0 | BF2: =表紙!$CB$64 -> 3
K3: =RIGHT(CELL("filename",$A$1),LEN(CELL("filename",$A$1))-FIND("]",CELL("filename",$A$1))) -> mcf画面イメージ | U3: 表題 | Z3: =表紙!$AJ$65 -> アドオン画面 | AE3: =表紙!$AQ$65 -> Web版型・木型マスタ
A5: 画面イメージ

Sheet 検索画面
D2: 〇参照
D4: 版型№ | J4: コード | O4: 名称 | AE4: Rev | AJ4: Rev番号 | AQ4: 適用開始日 | AW4: 44756
D5: 版型分類
D6: 得意先 | J6: コード | O6: 名称 | AE6: 新版区分
D7: 製品品目 | J7: コード | O7: 品名１ | AD7: 品名２
D9: 工程 | J9: コード | O9: 名称 | AE9: 通し数 | AQ9: 以上
D10: 発注先 | J10: コード | O10: 名称
D11: 入荷日 | O11: ～
D13: 棚・ライン | J13: コード | O13: 名称
D14: 廃棄予定日 | J14: 44756 | P14: 返却予定日 | U14: 44756 | AA14: 返却日 | AD14: 44756
BI15: 検索
D17: 版型№ | I17: 名称 | Y17: Rev番号 | AE17: 版型分類 | AJ17: 製品品目 | AO17: 名称 | BH17: 通し数 | BL17: 入荷日 | BR17: 返却予定日 | BX17: 返却日 | CD17: 工程 | CG17: 棚 | CI17: 最終加工先 | CN17: 新版区分 | CS17: 刃渡り | CV17: 色数 | CY17: ・・・・・ | DB17: その他登録されている項目
D18: コード | I18: 名称 | Y18: Rev番号 | AE18: 木型 | AJ18: コード | AO18: 品名１＋品名２ | BL18: 44756 | BR18: 44756 | BX18: 44756
D19: コード | I19: 名称 | Y19: Rev番号 | AE19: 木型 | AJ19: コード | AO19: 品名１＋品名２ | BL19: 44756 | BR19: 44756 | BX19: 44756
D20: コード | I20: 名称 | Y20: Rev番号 | AE20: 木型 | AJ20: コード | AO20: 品名１＋品名２ | BL20: 44756 | BR20: 44756 | BX20: 44756
D21: コード | I21: 名称 | Y21: Rev番号 | AE21: 木型 | AJ21: コード | AO21: 品名１＋品名２ | BL21: 44756 | BR21: 44756 | BX21: 44756
D22: コード | I22: 名称 | Y22: Rev番号 | AE22: ゴム版 | AJ22: コード | AO22: 品名１＋品名２ | BL22: 44756 | BR22: 44756 | BX22: 44756
D23: コード | I23: 名称 | Y23: Rev番号 | AE23: オフ版 | AJ23: コード | AO23: 品名１＋品名２ | BL23: 44756 | BR23: 44756 | BX23: 44756
D24: コード | I24: 名称 | Y24: Rev番号 | AE24: オフ版 | AJ24: コード | AO24: 品名１＋品名２ | BL24: 44756 | BR24: 44756 | BX24: 44756
D25: コード | I25: 名称 | Y25: Rev番号 | AE25: ゴム版 | AJ25: コード | AO25: 品名１＋品名２ | BL25: 44756 | BR25: 44756 | BX25: 44756
D26: コード | I26: 名称 | Y26: Rev番号 | AE26: オフ版 | AJ26: コード | AO26: 品名１＋品名２ | BL26: 44756 | BR26: 44756 | BX26: 44756
D27: コード | I27: 名称 | Y27: Rev番号 | AE27: 見落とし | AJ27: コード | AO27: 品名１＋品名２ | BL27: 44756 | BR27: 44756 | BX27: 44756
D28: コード | I28: 名称 | Y28: Rev番号 | AE28: 窓開け | AJ28: コード | AO28: 品名１＋品名２ | BL28: 44756 | BR28: 44756 | BX28: 44756
D29: コード | I29: 名称 | Y29: Rev番号 | AE29: 箔版 | AJ29: コード | AO29: 品名１＋品名２ | BL29: 44756 | BR29: 44756 | BX29: 44756
D30: コード | I30: 名称 | Y30: Rev番号 | AJ30: コード | AO30: 品名１＋品名２ | BL30: 44756 | BR30: 44756 | BX30: 44756
D31: コード | I31: 名称 | Y31: Rev番号 | AJ31: コード | AO31: 品名１＋品名２ | BL31: 44756 | BR31: 44756 | BX31: 44756
D32: コード | I32: 名称 | Y32: Rev番号 | AJ32: コード | AO32: 品名１＋品名２ | BL32: 44756 | BR32: 44756 | BX32: 44756
D33: コード | I33: 名称 | Y33: Rev番号 | AJ33: コード | AO33: 品名１＋品名２ | BL33: 44756 | BR33: 44756 | BX33: 44756
D36: 版型メンテ

Sheet 登録画面
D2: ◎登録 | I2: 〇訂正 | N2: 〇削除
D4: 版型№ | J4: コード | O4: 名称 | AE4: 適用開始日 | AK4: 44756
E5: Rev | J5: Rev番号
D6: 得意先 | J6: コード | O6: 名称 | AE6: 新版区分
D7: 製品品目 | J7: コード | O7: 品名１ | AD7: 品名２
D9: 工程 | J9: コード | O9: 名称 | AE9: 版型分類
D10: 最終加工場所 | J10: コード | O10: 名称 | AE10: 実績日 | AJ10: 44756
D12: 刃渡り寸法 | J12: コード | O12: × | P12: コード | Z12: 付数 | AG12: 個数 | AN12: 色数
D13: 落丁型 | P13: 置き版 | T13: リスト選択 | Z13: ハンマー | AD13: リスト選択 | AJ13: 見落とし型 | AO13: リスト選択
D15: 備考
D17: 発注先 | J17: コード | O17: 名称 | AE17: 入荷実績日 | AK17: 44756 | AR17: 金額
D19: 棚・ライン | J19: コード | O19: 名称
D20: 廃棄予定日 | J20: 44756 | P20: 返却予定日 | U20: 44756 | AA20: 返却日 | AD20: 44756 | AJ20: 返却理由
D23: ■過去履歴
D25: 適用開始日 | J25: Rev | M25: 発注先 | AH25: 通し数 | AO25: 廃棄予定日 | AU25: 返却予定日 | BA25: 返却日 | BG25: 返却理由
D26: 40404 | J26: 1 | M26: コード | R26: 名称 | AO26: 44756 | AU26: 44756 | BA26: 44756
D27: 41348 | J27: 2 | M27: コード | R27: 名称 | AO27: 44756 | AU27: 44756 | BA27: 44756
D28: 42445 | J28: 3 | M28: コード | R28: 名称 | AO28: 44756 | AU28: 44756 | BA28: 44756
D29: 43175 | J29: 4 | M29: コード | R29: 名称 | AO29: 44756 | AU29: 44756 | BA29: 44756
D30: 44271 | J30: 5 | M30: コード | R30: 名称 | AO30: 44756 | AU30: 44756 | BA30: 44756

Sheet 項目説明
A1: =表紙!A54 -> Webシステム | K1: 文書名 | U1: モジュールID | Z1: =表紙!$AJ$63 -> MS | AE1: モジュール名 | AJ1: =表紙!$AX$63 -> 見積管理 | AS1: 文書番号 | AZ1: Version | BF1: Rev.
K2: =表紙!O64 -> 画面機能 | U2: ｻﾌﾞﾓｼﾞｭｰﾙID | Z2: =表紙!$AJ$64 -> MSBB | AE2: ｻﾌﾞﾓｼﾞｭｰﾙ名 | AJ2: =表紙!$AX$64 -> Webシステム | AS2: =表紙!$BL$64 -> M7-US-1140 | AZ2: =表紙!$BU$64 -> 1.0.0 | BF2: =表紙!$CB$64 -> 3
K3: =RIGHT(CELL("filename",$A$1),LEN(CELL("filename",$A$1))-FIND("]",CELL("filename",$A$1))) -> 項目説明 | U3: 表題 | Z3: =表紙!$AJ$65 -> アドオン画面 | AE3: =表紙!$AQ$65 -> Web版型・木型マスタ
B5: 操作種別 | N5: 説明 | BE5: Ｗ | BF5: 型 | BG5: 参 | BH5: 必 | BI5: 入 | BJ5: 非 | BK5: 検 | BM5: CP指摘 2022/09/22 三宅 | CM5: MDSOL回答 2022/10/31 石田 WEB画面説明書（共通）.xlsxの挿絵_画面説明書の見方に記載致しました
A6: ● | B6: 登録 | M6: 登録モード 初期選択 | BE6: R | BM6: 左端の● 〇 や [リ 型 参 コ 入 非 Ｏ] | CZ6: 2022/11/01 落合 問題なし
A7: ● | B7: 改定 | M7: 改定モード 改定は最大REV＋１にREVが更新される | BE7: R | BM7: リのCB などと見ても各項目の内容が分からないのですが凡例はどこかに無いのでしょうか
A8: ● | B8: 訂正 | M8: 訂正モード 訂正はREVそのまま | BE8: R | BM8: 読み解いた範囲では「型」がデータ型とUIの種類がごちゃまぜになっているようで意味不明です
A9: ● | B9: 削除 | M9: 削除モード | BE9: R | BM9: Bは boolean ではなく button のようですが Sは stirng? のようで textarea と input type="text" の違いとかは考慮されていない様子です
A10: ● | B10: 参照 | M10: 参照モード | BE10: R | BM10: (ただしこの表を詳細に埋める必要性は感じないのでわざわざ変える必要はないと考えます)
B12: 検索項目 | N12: 説明 | BE12: Ｗ | BF12: 型 | BG12: 参 | BH12: 必 | BI12: 入 | BJ12: 非 | BK12: 検
A13: 〇 | B13: 版型No | M13: 入力後(Selected)、検索処理を行う。 | Z13: ※操作種別が登録以外の場合、入力可能 | BE13: A | BF13: S | BG13: 参 | BK13: 検
B14: Rev | Z14: ※操作種別が改定・参照時、入力可能(訂正・削除時は、版型No毎の最大値を表示) | BE14: T | BF14: S | BG14: 参
B16: 登録項目 | N16: 説明 | BE16: Ｗ | BF16: 型 | BG16: 参 | BH16: 必 | BI16: 入 | BJ16: 非 | BK16: 検
A17: ● | B17: 拠点 | M17: 事業所 | BE17: C | BF17: S | BG17: 参 | BH17: 必
B19: 登録項目 - 基本情報 | N19: 説明 | BE19: Ｗ | BF19: 型 | BG19: 参 | BH19: 必 | BI19: 入 | BJ19: 非 | BK19: 検
A20: ● | B20: 決定見積NO | M20: 見積計算書の決定見積NO | BE20: A | BF20: S | BH20: 必 | BK20: 検
B21: 案件NO | M21: 見積計算書NOに対応する案件NO | BE21: T | BF21: S | BG21: 参
A22: ● | B22: 版型名 | M22: 版型名称 | BE22: T | BF22: S | BH22: 必
B23: 売上可否区分 | M23: 売上できるかどうかの区分 | BE23: C | BF23: S | BG23: 参
B24: 手配NO | M24: 手配NO1 | BE24: T | BF24: S | BG24: 参
B25: 版型No | M25: 版型の番号 | BE25: T | BF25: S | BG25: 参
B26: Rev | M26: Rev＝最大Rev＋１ 検索後の表示時、自動設定。※操作種別が改定の場合、登録レコードの最大REVデータを表示する。 | BE26: T | BF26: S
A27: ● | B27: 適用開始日 | M27: マスタの適用開始日 | BE27: カ | BF27: D | BH27: 必
A28: ● | B28: 得意先 | M28: 決定見積NOから得意先を表示する。 | BE28: A | BF28: S | BG28: 参 | BH28: 必 | BK28: 検
A29: ● | B29: 代表製品CD | M29: 版型NOを最初に設定した製品CDを製品マスタから設定する。 | BE29: A | BF29: S | BG29: 参 | BH29: 必 | BK29: 検
B30: 新版区分 | M30: 操作種別=新規時は、「新版」をセット、改定時は「再販」をセットする | BE30: C | BF30: S | BG30: 参
A31: ● | B31: 工程 | M31: 入力後※操作種別が登録の場合 工程:300フレキソの時、ゴム型 工程:450オフセットの時、オフ型 工程:600トムソンの時、木型 工程:650箔押の時、箔版 版型分類を初期値セット | BE31: A | BF31: S
A32: ● | B32: 版型分類 | M32: 版型の分類 | BE32: C | BF32: S
A33: ● | B33: 最終加工場所 | M33: 最終の加工場所 | BE33: C | BF33: S
B34: 実績日（最終使用日） | M34: 最終使用日を表示する | BE34: カ | BF34: D | BG34: 参
BM35: CP指摘 2022/09/21 土屋 複版：1：有、0：無し は不要でしたでしょうか | CO35: MDSOL回答 2022/10/31 石田 追加致しました。 | DK35: 2022/11/01 落合 問題なし
B36: 登録項目 - 構成情報 | N36: 説明 | BE36: Ｗ | BF36: 型 | BG36: 参 | BH36: 必 | BI36: 入 | BJ36: 非 | BK36: 検
B37: シート段 | M37: 段を表示する | BE37: T | BF37: S | BG37: 参
B38: 原紙コード(表) | M38: 原紙コード(表)を表示する | BE38: T | BF38: S | BG38: 参
B39: 印刷コード(表) | M39: 印刷コード(表)を表示する | BE39: T | BF39: S | BG39: 参
B40: エンボスコード(表) | M40: エンボスコード(表)を表示する | BE40: T | BF40: S | BG40: 参
B41: メーカ(表) | M41: メーカ(表)を表示する | BE41: T | BF41: S | BG41: 参
B42: 原紙コード(中) | M42: 原紙コード(中)を表示する | BE42: T | BF42: S | BG42: 参
B43: 印刷コード(中) | M43: 印刷コード(中)を表示する | BE43: T | BF43: S | BG43: 参
B44: エンボスコード(中) | M44: エンボスコード(中)を表示する | BE44: T | BF44: S | BG44: 参
B45: メーカ(中) | M45: メーカ(中)を表示する | BE45: T | BF45: S | BG45: 参
B46: 原紙コード(裏) | M46: 原紙コード(裏)を表示する | BE46: T | BF46: S | BG46: 参
B47: 印刷コード(裏) | M47: 印刷コード(裏)を表示する | BE47: T | BF47: S | BG47: 参
B48: エンボスコード(裏) | M48: エンボスコード(裏)を表示する | BE48: T | BF48: S | BG48: 参
B49: メーカ(裏) | M49: メーカ(裏)を表示する | BE49: T | BF49: S | BG49: 参
A50: ● | B50: 抜方向 | M50: 抜き方向を設定する | BE50: C | BF50: S
A51: ● | B51: 面付け(From) | M51: 面付け(From)を設定する | BE51: T | BF51: N
A52: ● | B52: 面付け(To) | M52: 面付け(To)を設定する | BE52: T | BF52: N
A53: ● | B53: 複版 | M53: 複版を設定する。1：有、0：無し | BE53: C | BF53: S
A54: ● | B54: シート寸法(巾) | M54: シート寸法(巾)を設定する | BE54: T | BF54: N
A55: ● | B55: シート寸法(流れ) | M55: シート寸法(流れ)を設定する | BE55: T | BF55: N
A56: ● | B56: 刃渡り寸法(巾) | M56: 刃渡り寸法(巾)を設定する | BE56: T | BF56: N
A57: ● | B57: 刃渡り寸法(流れ) | M57: 刃渡り寸法(流れ)を設定する | BE57: T | BF57: N
A58: ● | B58: 付数 | M58: 付数を設定する | BE58: T | BF58: N
A59: ● | B59: 個数 | M59: 個数を設定する | BE59: T | BF59: N
A60: ● | B60: 色数 | M60: 色数を設定する | BE60: T | BF60: N
A61: ● | B61: 本数 | M61: 本数を設定する | BE61: T | BF61: N
... A63: ● | B63: シリンダーサイズ | M63: シリンダーサイズを設定する | BE63: T | BF63: N
A64: ● | B64: 発注先 | M64: 発注先を設定する | BE64: A | BF64: S | BG64: 参 | BH64: 必 | BK64: 検
A65: ● | B65: 加工予定先 | M65: 加工予定先を設定する | BE65: A | BF65: S | BG65: 参 | BH65: 必 | BK65: 検
A66: ● | B66: 納期 | M66: 納期を設定する | BE66: カ | BF66: D
A67: ● | B67: 入荷実績日 | M67: 入荷実績日を設定する | BE67: カ | BF67: D | BH67: 必
A68: ● | B68: 見積価格 | M68: 見積価格を設定する | BE68: T | BF68: N
A69: ● | B69: 売上決定価格 | M69: 売上決定価格を設定する | BE69: T | BF69: N
A70: ● | B70: 仕入予定金額 | M70: 仕入予定金額を設定する | BE70: T | BF70: N
A71: ● | B71: 売上日 | M71: 売上日を設定する | BE71: カ | BF71: D
A72: ● | B72: 売上可否区分 | M72: 1:可,2:不可,3:商品込,4:社内処理,5:後報 | BE72: C | BF72: S
A73: ● | B73: 売上備考 | M73: 売上備考を設定する | BE73: T | BF73: D
A74: ● | B74: 落丁型 | M74: 落丁型を設定する | BE74: C | BF74: S
A75: ● | B75: 置き版 | M75: 置き版を設定する | BE75: C | BF75: S
A76: ● | B76: ハンマー | M76: ハンマーを設定する | BE76: C | BF76: S
A77: ● | B77: 見落とし型 | M77: 見落とし型を設定する | BE77: C | BF77: S
B78: 場所 | M78: 在庫場所を表示する | BE78: A | BF78: S | BG78: 参
B79: 棚・ライン | M79: 在庫場所の棚番を表示する | BE79: A | BF79: S | BG79: 参
B80: 通し数 | M80: 通し数を表示する。 | BE80: T | BF80: N | BG80: 参
A81: ● | B81: 限界通し数 | M81: 限界通し数を設定する | BE81: T | BF81: N
A82: ● | B82: 廃棄予定日 | M82: 廃棄予定日を設定する | BE82: カ | BF82: D
A83: ● | B83: 廃棄実績日 | M83: 廃棄実績日を設定する | BE83: カ | BF83: D
A84: ● | B84: 返却予定日 | M84: 返却予定日を設定する | BE84: カ | BF84: D
A85: ● | B85: 返却日 | M85: 返却日を設定する | BE85: カ | BF85: D
A86: ● | B86: 返却理由 | M86: 返却理由を設定する | BE86: T | BF86: S
A87: ● | B87: 備考 | M87: 備考を設定する | BE87: T | BF87: S
B89: 登録項目 - 添付情報 | N89: 説明 | BE89: Ｗ | BF89: 型 | BG89: 参 | BH89: 必 | BI89: 入 | BJ89: 非 | BK89: 検
A90: ● | B90: 表図面 | M90: 添付書類 表図面 | BE90: チ | BF90: S
A91: ● | B91: 裏図面 | M91: 添付書類 裏図面 | BE91: チ | BF91: S
A92: ● | B92: 現物 | M92: 添付書類 現物 | BE92: チ | BF92: S
A93: ● | B93: 版下 | M93: 添付書類 版下 | BE93: チ | BF93: S
A94: ● | B94: ポジ | M94: 添付書類 ポジ | BE94: チ | BF94: S
A95: ● | B95: ネガ | M95: 添付書類 ネガ | BE95: チ | BF95: S
A96: ● | B96: MO | M96: 添付書類 MO | BE96: チ | BF96: S
A97: ● | B97: FD | M97: 添付書類 FD | BE97: チ | BF97: S
B99: 登録項目 - 必要物 | N99: 説明 | BE99: Ｗ | BF99: 型 | BG99: 参 | BH99: 必 | BI99: 入 | BJ99: 非 | BK99: 検
A100: ● | B100: タタキ | M100: タタキを設定する | BE100: T | BF100: S
A101: ● | B101: マイラー | M101: マイラーを設定する | BE101: T | BF101: S
A102: ● | B102: ゲラ刷り | M102: ゲラ刷りを設定する | BE102: T | BF102: S
A103: ● | B103: 校正 | M103: 校正を設定する | BE103: T | BF103: S
A104: ● | B104: 青焼 | M104: 青焼を設定する | BE104: T | BF104: S
A105: ● | B105: カンプ | M105: カンプを設定する | BE105: T | BF105: S
A106: ● | B106: 印刷設計書 | M106: 印刷設計書を設定する | BE106: T | BF106: S
A107: ● | B107: その他名称 | M107: その他名称を設定する | BE107: T | BF107: S
...

Sheet 画面遷移
A1: =表紙!A54 -> Webシステム | K1: 文書名 | U1: モジュールID | Z1: =表紙!$AJ$63 -> MS | AE1: モジュール名 | AJ1: =表紙!$AX$63 -> 見積管理 | AS1: 文書番号 | AZ1: Version | BF1: Rev.
K2: =表紙!O64 -> 画面機能 | U2: ｻﾌﾞﾓｼﾞｭｰﾙID | Z2: =表紙!$AJ$64 -> MSBB | AE2: ｻﾌﾞﾓｼﾞｭｰﾙ名 | AJ2: =表紙!$AX$64 -> Webシステム | AS2: =表紙!$BL$64 -> M7-US-1140 | AZ2: =表紙!$BU$64 -> 1.0.0 | BF2: =表紙!$CB$64 -> 3
K3: =RIGHT(CELL("filename",$A$1),LEN(CELL("filename",$A$1))-FIND("]",CELL("filename",$A$1))) -> 画面遷移 | U3: 表題 | Z3: =表紙!$AJ$65 -> アドオン画面 | AE3: =表紙!$AQ$65 -> Web版型・木型マスタ
A5: ID | D5: 処理名 | Y5: ダブルクリック対象 | AH5: ダブルクリック処理条件
A6: S01 | D6: なし
BL7: CP指摘 2022/09/21 土屋 版型Noの検索画面など虫眼鏡が付いている検索画面への記載が必要かと思います | BU7: MDSOL回答 2022/10/31 石田 検索に関しては、【MSBBPA000】_共通設計書_アドオン(Webシステム共通仕様)にて定義しております。
B8: 遷移処理 | BU8: 2022/11/01 落合 問題なし
B9: 遷移元画面ＩＤ | I9: MSBBPA150
B10: 遷移元画面名 | I10: Web版型・木型マスタ一覧照会
B11: 遷移先画面ＩＤ | I11: MSBBPA140
B12: 遷移先画面名 | I12: Web版型・木型マスタ
B13: 遷移条件 | I13: Web版型・木型マスタ一覧照会画面の一覧表示部データから一つのみ選択の後、選択ボタンをクリックします
B14: 引継項目・種別 | I14: 遷移元画面項目 | AJ14: 遷移先画面項目
I15: 版号Rev | AJ15: 版号Rev
I16: 版型NO | AJ16: 版型NO
B18: 遷移後のアクション | I18: 操作種別が「参照」をします
A20: ID | D20: 処理名 | Y20: ダブルクリック対象 | AH20: ダブルクリック処理条件
A21: S02 | D21: なし
B23: 遷移処理
B24: 遷移元画面ＩＤ | I24: なし
B25: 遷移元画面名 | I25: メニュー
B26: 遷移先画面ＩＤ | I26: MSBBPA140
B27: 遷移先画面名 | I27: Web版型・木型マスタ
B28: 遷移条件 | I28: なし
B29: 引継項目・種別 | I29: 遷移元画面項目 | AJ29: 遷移先画面項目
I30: メンニュー一覧のkey | AJ30: なし
B32: 遷移後のアクション | I32: 画面を初期化して、操作種別が「登録」をします

Sheet 処理概要
A1: =表紙!A54 -> Webシステム | K1: 文書名 | U1: モジュールID | Z1: =表紙!$AJ$63 -> MS | AE1: モジュール名 | AJ1: =表紙!$AX$63 -> 見積管理 | AS1: 文書番号 | AZ1: Version | BF1: Rev.
K2: =表紙!O64 -> 画面機能 | U2: ｻﾌﾞﾓｼﾞｭｰﾙID | Z2: =表紙!$AJ$64 -> MSBB | AE2: ｻﾌﾞﾓｼﾞｭｰﾙ名 | AJ2: =表紙!$AX$64 -> Webシステム | AS2: =表紙!$BL$64 -> M7-US-1140 | AZ2: =表紙!$BU$64 -> 1.0.0 | BF2: =表紙!$CB$64 -> 3
K3: =RIGHT(CELL("filename",$A$1),LEN(CELL("filename",$A$1))-FIND("]",CELL("filename",$A$1))) -> 処理概要 | U3: 表題 | Z3: =表紙!$AJ$65 -> アドオン画面 | AE3: =表紙!$AQ$65 -> Web版型・木型マスタ
A5: No | B5: 入力 | J5: 処理 | BD5: 出力
A6: 1 | B6: 検索 | J6: 木型・版型管理マスタを検索する | BN6: CP指摘 2022/09/21 三宅 | CT6: MDSOL回答 2022/10/31 石田 検索に関しては、【MSBBPA000】_共通設計書_アドオン(Webシステム共通仕様)にて定義しております。遷移ではないので表現を変更しました。
C7: 操作種別=登録 | J7: 1. | K7: 決定見積NOを検索する | BO7: モーダルウインドウではなく「遷移」なのでしょうか
K8: 見積計算書一覧照会を表示する | BO8: 別ページに遷移して取得データを保持して元ページに戻ってくる制御は問題無く可能なのでしょうか
K9: →見積計算書一覧照会の選択後、結果を返す | BD9: 検索入出力仕様.No1 | BO9: 「画面遷移」シートは空のようです
A12: 2 | B12: 検索 | J12: 木型・版型管理マスタを検索する
C13: 操作種別 | J13: 1. | K13: 木型・版型管理マスタを検索する | BD13: 検索入出力仕様.No2 | BN13: CP指摘 2022/09/21 土屋 入力された検索条件とは何をさしていますでしょうか？この画面は他の版型検索画面があって、そこで版型Noが一意に特定された後に表示されるものではないのでしょうか | DY13: MDSOL回答 2022/10/31 石田 登録は、この画面からスタートになります。入力された検索条件とは版型Noを指します。 | FP13: 2022/11/04 土屋 問題なし(版型Noのみ検索対象であれば一意になる為問題なし。版型名が入力候補となると複数ヒットする可能性がある為NGの認識です)
D14: 改定・訂正・削除 | K14: 入力された検索条件で木型・版型管理マスタを検索し、画面に表示する
K15: 検索結果が0件の場合、メッセージを表示する | BD15: メッセージNo.1
J17: 2. | K17: 木型・版型管理の格納されている場所を検索する
K18: 取得した木型・版型の品目CDを用いて、現状在庫を検索し、格納されている場所を取得する
J20: 3. | K20: 製品CDを検索する
K21: 木型・版型Noを用いて製品マスタを検索し製品CD、および製品名１・２を取得する
A24: 3 | B24: 登録 | J24: 木型・版型管理マスタを登録する
B25: 登録前チェック | J25: 1. | K25: 必須項目のチェックを行う
K26: 必須項目に入力されているかチェックを行う | BN26: CP指摘 2022/09/21 三宅 「処理を終了する」とは？ メッセージを出して登録を確定させないだけでは？ | CW26: MDSOL回答 2022/10/31 石田 後続処理を終了することを指します。
K27: エラーの場合メッセージを表示し、処理を終了する | BD27: メッセージNo.3
BN28: CP指摘 2022/09/22 三宅 売上可でないのに見積価格 決定価格 が入っている、フレキソ工程でないのにフレキソ版厚の値を持っている、等は許容するか否か要検討 | DO28: MDSOL回答 2022/10/31 石田 現仕様では、フリーです。チェック要望があれば追記します。
J29: 2 | K29: 適用開始日と適用終了日の前後関係のチェックを行う
K30: 適用終了日が適用開始日より前になっていないかチェックを行う
K31: エラーの場合メッセージを表示し、処理を終了する | BD31: メッセージNo.4
J33: 3 | K33: 適用開始日と廃棄予定日の前後関係のチェックを行う
K34: 廃棄予定日が適用開始日より前になっていないかチェックを行う
K35: エラーの場合メッセージを表示し、処理を終了する | BD35: メッセージNo.5
J37: 4 | K37: 適用終了日と廃棄予定日の前後関係のチェックを行う
K38: 廃棄予定日が適用終了日より前になっていないかチェックを行う
K39: エラーの場合メッセージを表示し、処理を終了する | BD39: メッセージNo.6
B41: 登録処理 | J41: 5 | K41: 対象データを登録する
L42: 詳細は、処理概要(登録)参照
A45: 3 | B45: 改定 | J45: 木型・版型管理マスタを登録する
B46: 登録前チェック | J46: 1 | K46: 必須項目のチェックを行う
K47: 必須項目に入力されているかチェックを行う | BD47: メッセージNo.3
K48: エラーの場合メッセージを表示し、処理を終了する | BN48: CP指摘 2022/09/22 三宅 新Revの適用開始日が前Revの適用終了日の翌日かどうかのチェックが必要だと思います(入力ミスで重複期間や適用されない期間が存在しないように) あるいは改定時は開始日は自動でセットされ変更不可にするなど | EN48: MDSOL回答 2022/10/31 石田 適用終了日を自動セットとなります。適用開始日をセットし、追加で(現在日～適用開始日)のデータをセットすると動きが不正となるため。未来日程を１つしか入れれない制御を追加します。+以前の日付はセットできないようにします。
J50: 2 | K50: 適用開始日と適用終了日の前後関係のチェックを行う
K51: 適用開始日を元に前REVの適用終了日をー1日で自動設定する。
K52: 未来日は一つしか入れれないように既存版
K53: エラーの場合メッセージを表示し、処理を終了する | BD53: メッセージNo.4
J55: 3 | K55: 適用開始日と廃棄予定日の前後関係のチェックを行う
K56: 廃棄予定日が適用開始日より前になっていないかチェックを行う
K57: エラーの場合メッセージを表示し、処理を終了する | BD57: メッセージNo.5
J59: 4 | K59: 適用終了日と廃棄予定日の前後関係のチェックを行う
K60: 廃棄予定日が適用終了日より前になっていないかチェックを行う
K61: エラーの場合メッセージを表示し、処理を終了する | BD61: メッセージNo.6
B63: 登録処理 | J63: 5 | K63: 対象データを登録する
L64: 詳細は、処理概要(登録)参照
A67: 4 | B67: 訂正 | J67: 木型・版型管理マスタを更新する | BM67: CP指摘 2022/09/22 三宅 排他チェックとは？悲観ロックとか？ | CK67: MDSOL回答 2022/10/31 石田 楽観排他になります。 | DG67: 2022/11/01 落合 問題なし
B68: 更新前チェック | J68: 1 | K68: 排他チェックを行う
K69: エラーの場合メッセージを表示し、処理を終了する | BD69: メッセージNo.2 | BM69: CP指摘 2022/09/22 三宅 過去Revを遡って修正可にするかどうか要検討 | CK69: MDSOL回答 2022/10/31 石田 現仕様では最新のみ修正となります。 | DM69: 2022/11/01 落合 問題なし
J71: 2 | K71: 必須項目のチェックを行う
K72: 必須項目に入力されているかチェックを行う
K73: エラーの場合メッセージを表示し、処理を終了する | BD73: メッセージNo.3
J75: 3 | K75: 適用開始日と適用終了日の前後関係のチェックを行う
K76: 適用終了日が適用開始日より前になっていないかチェックを行う
K77: エラーの場合メッセージを表示し、処理を終了する | BD77: メッセージNo.4
J79: 4 | K79: 適用開始日と廃棄予定日の前後関係のチェックを行う
K80: 廃棄予定日が適用開始日より前になっていないかチェックを行う
K81: エラーの場合メッセージを表示し、処理を終了する | BD81: メッセージNo.5
J83: 5 | K83: 適用終了日と廃棄予定日の前後関係のチェックを行う
K84: 廃棄予定日が適用終了日より前になっていないかチェックを行う
K85: エラーの場合メッセージを表示し、処理を終了する | BD85: メッセージNo.6
B87: 更新処理 | J87: 6 | K87: 対象データを更新する
L88: 詳細は、処理概要(登録)参照
A91: 5 | B91: 削除 | J91: 削除処理を行う。
B92: 削除チェック | J92: 1. | K92: 排他チェックを行う
K93: エラーの場合メッセージを表示し、処理を終了する | BD93: メッセージNo.2 | BM93: CP指摘 2022/09/22 三宅 現在も使用されている版でないか実績を参照して確認するチェックは必要か | DA93: MDSOL回答 2022/10/31 石田 現仕様ではなし。使われているかどうか判断できない。 | EG93: 2022/11/01 落合 問題なし
BM94: CP指摘 2022/09/22 三宅 論理削除されたデータの復活画面は必要か(画面無しでも復活手順を作っておくことは必要) | DA94: MDSOL回答 2022/10/31 石田 共通仕様に記載します。取引先マスタ・製品マスタ・版型/木型マスタが該当。削除登録で削除flg=on 一覧照会画面：抽出条件に削除flg☑を追加する デフォルトon 登録画面、操作種別：登録・更新時は、db参照項目は、削除flg□(off)を条件とする 操作種別：参照時は、削除flgを加味しない。削除登録でデータを呼び出し、削除データを呼び出した場合、削除取消とする 削除flg☑とする | FC94: 2022/11/01 落合 問題なし
B95: 削除処理 | J95: 2. | K95: 対象データを削除する
K96: 論理削除とする
K97: 詳細は、処理概要(登録)参照
A99: 6 | B99: ラベル発行 | J99: 対象データのラベル発行用CSVファイルを出力する | BN99: CP指摘 2022/09/21 三宅 ラベル発行ボタンクリックのみで即発行なのか 発行時に各種追加設定必要では(枚数や種類等) | DC99: MDSOL回答 2022/10/31 石田 ポップアップ確認後、発行されます。 | EC99: 2022/11/01 落合 問題なし
BN100: CP指摘 2022/09/21 三宅 「ダイアログ無し所定のフォルダ」とはローカルのフォルダを想定しているのでしょうか？新しいPrintProのWeb版はローカルのファイルにはアクセスできないのでサーバー内にcsvを作成して、そのファイルにURLでアクセスできることが必要
K101: ラベル発行用のCSVファイルを出力する(ダイアログ無し、所定のフォルダへ) | BD101: ファイル入出力仕様.NO1 | BP101: なおファイル名が同じ場合は同時にユーザーが同時に処理するとトラブルが起きるのでランダム文字なりUUIDなりでユニークなファイル名で動的に作成してそのファイル名を含んだURLをopenする必要あり(生成されたcsvが溜まるのでフォルダ内の一定期間以上古いファイルを削除する処理を挟む)
BP102: 処理イメージ
K103: ※設定情報は、web.configファイルにて管理する | BP103: ボタンをクリックしたらJavaScriptで処理
BP104: patterns/createcsv (仮) へパラメータを投げる
A105: 7 | B105: クリア | J105: 画面初期状態を行う | BP105: アクセス先のエンドポイントに対応したプログラムではランダム生成した重複しない名前でcsvを作成し、作成完了したらファイル名を { filename: 'b400aaef-9089-4e7e-8231-c8b1e57eadee' } のように返す
BP106: (csv作成に失敗したらエラーが返るのでメッセージを出してそこで終了)
K107: 初期表示に戻す | BP107: ※作成先のフォルダは csv/{ファイル名} (仮)のようなURLでアクセスできるようにしておく
L108: 拠点 | Q108: ： | R108: ログインに紐づく拠点CDを表示する | BP108: それを受け取って
L109: 他の項目 | Q109: ： | R109: 空白 | BP109: window.open("./printpro/pattern/?file=b400aaef-9089-4e7e-8231-c8b1e57eadee", "_blank");
L110: 操作種別 | Q110: ： | R110: 処理無し | BP110: のようにPrintPro発行ページを開く
BP111: PrintPro発行ページはファイル名を受け取って./csv/b400aaef-9089-4e7e-8231-c8b1e57eadee.csv からデータを取得して印刷処理をする
A112: 8 | B112: 版型発注書 | J112: 版型発注書画面へ遷移する
J114: 遷移URLがない場合（登録・更新モードの更新ボタン押下後）
J115: １．版型NOよりPE木型・版型管理マスタを参照しキー項目を取得する。
J116: ２．PE木型・版型管理マスタURLと1.のキー項目からPE版型発注書遷移URLを作成する。
J117: ３．２のPE版型発注書遷移URLから遷移する。
J118: それ以外の場合（参照モードなど）
J119: １．PE版型発注書遷移URLから遷移する

Sheet 処理詳細
A1: Webシステム | K1: 文書名 | U1: モジュールID | Z1: MS | AE1: モジュール名 | AJ1: 見積管理 | AS1: 文書番号 | AZ1: Version | BF1: Rev.
K2: 画面機能 | U2: ｻﾌﾞﾓｼﾞｭｰﾙID | Z2: MSBB | AE2: ｻﾌﾞﾓｼﾞｭｰﾙ名 | AJ2: Webシステム | AS2: M7-US-1140 | AZ2: 1.0.0 | BF2: 1
K3: =RIGHT(CELL("filename",$A$1),LEN(CELL("filename",$A$1))-FIND("]",CELL("filename",$A$1))) -> 処理詳細 | U3: 表題 | Z3: アドオン画面 | AE3: Web版型・木型マスタ
A5: No | B5: 入力 | J5: 処理 | BD5: 出力
A6: 1 | B6: 初期表示
J7: 1.1 | L7: 遷移元メニューから
L8: 操作種別 | P8: ： | Q8: 「登録」を設定する
L9: 版型No | P9: ： | Q9: 版型NoとRev、変更不可とする 、Revが「１」を設定
L10: その他 | P10: ： | Q10: 活性とする、各項目のクリア処理と初期値設定を行う
J12: 1.2 | L12: 遷移元【MSBBPA150】_木型マスタ一覧照会から
L13: 操作種別 | P13: ： | Q13: 「参照」を設定する
L14: 全画面が非活性とする
A16: 2 | B16: 画面操作
J17: 2.1 | L17: 操作種別ボタンの制御処理
K18: 2.1.1 | N18: [操作種別]ラジオが「改定」の場合、
N19: 版型名は編集不可、または 版型発注書、ラベル発行ボタンが非活性。その他、編集可、ボタンが活性。
K20: 2.1.2 | N20: [操作種別]が「訂正」の場合、
N21: 「改定」と同じ
K22: 2.1.3 | N22: [操作種別]が「削除」の場合、
N23: 版型No検索ボタンと登録ボタンが活性
K24: 2.1.4 | N24: [操作種別]が「参照」の場合、
N25: 全画面が非活性とする
N27: ※操作種別切り替え処理は、以下の通りです。
A39: 3 | B39: 検索
J40: 3.1 | L40: 版型Noの検索ボタン処理
L41: 版型No検索のポップアップ画面へを遷移して、抽出条件をもとに結果を表示したところ、
L42: 選択結果(1行)を遷移元画面（WEB版型・木型情報）に返す
L44: 版型No検索_SQLリソースの検索仕様
L45: 【MSBBPACOM】_共通設計書_アドオン(Web共通ロジック)の「処理詳細(共通検索)」シート」を参照する。
J47: 3.2 | L47: 決定見積NOの検索ボタン処理
L48: 決定見積No検索のポップアップ画面へを遷移して、抽出条件をもとに結果を表示したところ、
L49: 選択結果(1行)を遷移元画面（本画面の基本情報と構成情報を設定）に返す
L51: 決定見積NO検索_SQLリソースの検索仕様
L52: 【MSBBPACOM】_共通設計書_アドオン(Web共通ロジック)の「処理詳細(共通検索)」シート」を参照する。
J54: 3.3 | L54: 得意先の検索ボタン処理
L55: 取引先マスタ検索のポップアップ画面へを遷移して、抽出条件＜取引先コード＞あるいは、＜取引先名＞をもとに結果を表示したところ、
L56: 選択結果(1行)を遷移元画面（本画面の得意先コード、得意先名を設定）に返す
L58: 取引先マスタ検索_SQLリソースの検索仕様
L59: 【MSBBPACOM】_共通設計書_アドオン(Web共通ロジック)の「処理詳細(共通検索)」シート」を参照する。
L61: 製品コードの検索ボタン処理
J62: 3.4 | L62: 製品検索のポップアップ画面へを遷移して、抽出条件をもとに結果を表示したところ、
L63: 選択結果(1行)を遷移元画面（本画面の製品コード、製品名を設定）に返す
L64: 木型・版型Noを用いて製品マスタを検索し製品コード、および製品名１・２を取得する
L66: 製品マスタ検索_SQLリソースの検索仕様
L67: 【MSBBPACOM】_共通設計書_アドオン(Web共通ロジック)の「処理詳細(共通検索)」シート」を参照する。
J69: 3.5 | L69: 加工予定先コードの検索ボタン処理
L70: 加工予定先検索のポップアップ画面へを遷移して、抽出条件をもとに結果を表示したところ、
L71: 選択結果(1行)を遷移元画面（本画面の加工予定先コード、加工予定先名を設定）に返す
L73: 取引先マスタ検索_SQLリソースの検索仕様
L74: 【MSBBPACOM】_共通設計書_アドオン(Web共通ロジック)の「処理詳細(共通検索)」シート」を参照する。
J76: 3.6 | L76: 発注先の検索ボタン処理
L77: 発注先検索のポップアップ画面へを遷移して、抽出条件をもとに結果を表示したところ、
L78: 選択結果(1行)を遷移元画面（本画面の発注先コード、発注先名を設定）に返す
L80: 取引先マスタ検索_SQLリソースの検索仕様
L81: 【MSBBPACOM】_共通設計書_アドオン(Web共通ロジック)の「処理詳細(共通検索)」シート」を参照する。
J83: 3.7 | L83: 見積計算書マスタを検索する（[操作種別] = 「登録」）
L84: 再検索結果が0件の場合、メッセージを表示する | BD84: メッセージNo.1
L85: 再検索結果が0件の以外の場合、
L87: 見積計算書検索_SQLリソースの検索仕様 | BD87: 検索入出力仕様.No1
N88: 【対象テーブル】
O89: ・ | P89: 【見積計算書マスタ】
O90: ・ | P90: 【取引先マスタ】
O91: ・ | P91: 【原紙マスタ】
O92: ・ | P92: 【印刷マスタ】
O93: ・ | P93: 【エンボスマスタ】
N95: 【結合条件】
O96: AND 見積計算書マスタ．得意先コード = 取引先マスタ.得意先コード(+)
O97: AND 見積計算書マスタ．原紙コード(表) = 原紙マスタ.原紙コード(表)(+)
O98: AND 見積計算書マスタ．印刷コード(表) = 印刷マスタ.印刷コード(表)(+)
O99: AND 見積計算書マスタ．エンボスコード(表) = エンボスマスタ.エンボスコード(表)(+)
O100: AND 見積計算書マスタ．メーカ(表) = 取引先マスタ.メーカ(表)(+)
O101: AND 見積計算書マスタ．原紙コード(中) = 原紙マスタ.原紙コード(中)(+)
O102: AND 見積計算書マスタ．印刷コード(中) = 印刷マスタ.印刷コード(中)(+)
O103: AND 見積計算書マスタ．エンボスコード(中) = エンボスマスタ.エンボスコード(中)(+)
O104: AND 見積計算書マスタ．メーカ(中) = 取引先マスタ.メーカ(中)(+)
O105: AND 見積計算書マスタ．原紙コード(裏) = 原紙マスタ.原紙コード(裏)(+)
O106: AND 見積計算書マスタ．印刷コード(裏) = 印刷マスタ.印刷コード(裏)(+)
O107: AND 見積計算書マスタ．エンボスコード(裏) = エンボスマスタ.エンボスコード(裏)(+)
O108: AND 見積計算書マスタ．メーカ(裏) = 取引先マスタ.メーカ(裏)(+)
N110: 【抽出条件】
O111: AND 見積計算書マスタ.見積計算書NO = 画面.決定見積NO
N113: 【ソート条件】
O114: なし
J116: 3.8 | L116: 木型・版型管理マスタを検索する（[操作種別] = 「改定」・「訂正」・「削除」・「参照」）
L117: 再検索結果が0件の場合、メッセージを表示する | BD117: メッセージNo.1
L118: 再検索結果が0件の以外の場合、
L119: 画面データを表示する （Rev＝最大Rev＋１ ※[操作種別]が「改定」のみの場合 検索後の表示時、自動設定）
L121: 版型・木型検索_SQLリソースの検索仕様 | BD121: 検索入出力仕様.No2
N122: 【対象テーブル】
O123: ・ | P123: 【版型・木型マスタ】
O124: ・ | P124: 【拠点マスタ】
O125: ・ | P125: 【得意先マスタ】
O126: ・ | P126: 【製品マスタ】
O127: ・ | P127: 【木型・版型実績】
O128: ・ | P128: 【原紙マスタ】
O129: ・ | P129: 【印刷マスタ】
O130: ・ | P130: 【エンボスマスタ】
O131: ・ | P131: 【発注先マスタ】
O132: ・ | P132: 【現状在庫】
O133: ・ | P133: 【場所マスタ】
...

Sheet 処理概要(登録)
A1: =表紙!A54 -> Webシステム | K1: 文書名 | U1: モジュールID | Z1: =表紙!$AJ$63 -> MS | AE1: モジュール名 | AJ1: =表紙!$AX$63 -> 見積管理 | AS1: 文書番号 | AZ1: Version | BF1: Rev.
K2: =表紙!O64 -> 画面機能 | U2: ｻﾌﾞﾓｼﾞｭｰﾙID | Z2: =表紙!$AJ$64 -> MSBB | AE2: ｻﾌﾞﾓｼﾞｭｰﾙ名 | AJ2: =表紙!$AX$64 -> Webシステム | AS2: =表紙!$BL$64 -> M7-US-1140 | AZ2: =表紙!$BU$64 -> 1.0.0 | BF2: =表紙!$CB$64 -> 3
K3: =RIGHT(CELL("filename",$A$1),LEN(CELL("filename",$A$1))-FIND("]",CELL("filename",$A$1))) -> 処理概要(登録) | U3: 表題 | Z3: =表紙!$AJ$65 -> アドオン画面 | AE3: =表紙!$AQ$65 -> Web版型・木型マスタ
A5: No | B5: 入力 | J5: 処理 | BD5: 出力
A6: 1 | B6: 登録 | J6: 木型・版型管理マスタを登録する
K8: 登録処理に関して、以下の処理を実施する
K9: 登録・改定・訂正・削除処理フロー
BM13: CP指摘 2022/09/22 三宅 これを見ると版型マスタ以外も更新がかかるようですが概要の関連図や処理・サービス関連図は版型マスタ単独にしか影響しないような記述です | DP13: MDSOL回答 2022/10/31 石田 品目マスタ連携、受注連携の更新内容についてはそれぞれの機能で記載しております。PEについては当機能で行うため更新入出力仕様（PE）に記載しております。
DQ14: 2022/11/01 落合 問題なし
L36: No | N36: 操作種別 | R36: 版型マスタ登録 | X36: 品目マスタ連携 | AD36: 受注連携 | AJ36: PE API連携
L37: 1 | N37: 登録 | R37: 新規 | X37: 新規 | AD37: 新規 | AJ37: 新規
L38: 2 | N38: 改定 | R38: 改定 | X38: 新規 | AD38: 新規 | AJ38: 新規 | BM38: CP指摘 2022/09/21 版型マスタ登録の操作種別が改定時について、データの作り上を詳しく記載して下さい | CY38: MDSOL回答 2022/10/31 石田 更新入出力仕様（改定）で記載しております。
L39: 3 | N39: 訂正 | R39: 更新 | X39: 更新 | AD39: 更新 | AJ39: 更新 | BM39: CP指摘 2022/09/21 版型マスタ登録の操作種別が訂正時の訂正は更新ではないでしょうか | CY39: MDSOL回答 2022/10/31 石田 訂正致しました。
L40: 4 | N40: 削除 | R40: 更新(論理削除) | X40: 更新(論理削除) | AD40: 更新(論理削除) | AJ40: 削除
R41: ※更新入出力仕様

Sheet 処理・サービス関連図
A1: =表紙!A54 -> Webシステム | K1: 文書名 | U1: モジュールID | Z1: =表紙!$AJ$63 -> MS | AE1: モジュール名 | AJ1: =表紙!$AX$63 -> 見積管理 | AS1: 文書番号 | AZ1: Version | BF1: Rev.
K2: =表紙!O64 -> 画面機能 | U2: ｻﾌﾞﾓｼﾞｭｰﾙID | Z2: =表紙!$AJ$64 -> MSBB | AE2: ｻﾌﾞﾓｼﾞｭｰﾙ名 | AJ2: =表紙!$AX$64 -> Webシステム | AS2: =表紙!$BL$64 -> M7-US-1140 | AZ2: =表紙!$BU$64 -> 1.0.0 | BF2: =表紙!$CB$64 -> 3
K3: =RIGHT(CELL("filename",$A$1),LEN(CELL("filename",$A$1))-FIND("]",CELL("filename",$A$1))) -> 処理・サービス関連図 | U3: 表題 | Z3: =表紙!$AJ$65 -> アドオン画面 | AE3: =表紙!$AQ$65 -> Web版型・木型マスタ
AT6: 凡例 | BN6: CP指摘 2022/09/22 POWEREGG連携は概要シートでは版型データ参照は取り消し線で消され、見積ワークフローを参照するとなっている「木型・版型発注」は古い記述では？ | DQ6: MDSOL回答 2022/10/31 石田 停止絵致しました。
BE7: 画面
AX9: 外部システムサービス | BE9: サービス
AX11: アドオンテーブル | BE11: テーブル
BE13: サービス・テーブルのグループ
BE15: ファイル
BE17: 帳票
AV24: 木型・版型管理情報
AV25: 通し数、最終使用実績日を参照 | BN25: CP指摘 2022/09/22 三宅 「現状在庫」から「通し数集計バッチ」のようななんらかの処理を挟んだ「木型・版型管理マスタ」への矢印が必要ではないでしょうか(版マスタに在庫情報持たせるなら) | DU25: MDSOL回答 2022/10/31 石田 停止絵致しました。
BN27: Rev2.0 記述訂正

Sheet 検索入出力仕様
A1: =表紙!A54 -> Webシステム | K1: 文書名 | U1: モジュールID | Z1: =表紙!$AJ$63 -> MS | AE1: モジュール名 | AJ1: =表紙!$AX$63 -> 見積管理 | AS1: 文書番号 | AZ1: Version | BF1: Rev.
K2: =表紙!O64 -> 画面機能 | U2: ｻﾌﾞﾓｼﾞｭｰﾙID | Z2: =表紙!$AJ$64 -> MSBB | AE2: ｻﾌﾞﾓｼﾞｭｰﾙ名 | AJ2: =表紙!$AX$64 -> Webシステム | AS2: =表紙!$BL$64 -> M7-US-1140 | AZ2: =表紙!$BU$64 -> 1.0.0 | BF2: =表紙!$CB$64 -> 3
K3: =RIGHT(CELL("filename",$A$1),LEN(CELL("filename",$A$1))-FIND("]",CELL("filename",$A$1))) -> 検索入出力仕様 | U3: 表題 | Z3: =表紙!$AJ$65 -> アドオン画面 | AE3: =表紙!$AQ$65 -> Web版型・木型マスタ
A5: No | G5: 1 | H5: ボタン | L5: 検索 | S5: ロジック名称 | AH5: 備考 | AK5: 木型・版型管理マスタの検索
A6: 処理分類 | E6: 検索 | H6: ソート順
A7: No | C7: 転送先 | S7: 転送元 | AK7: 説明
C8: 種 | D8: オブジェクト | H8: 項目名 | S8: 種 | T8: オブジェクト | Z8: 項目名
A9: 1 | C9: 画 | D9: 基本情報 | H9: 決定見積NO | S9: T | T9: 見積計算書 | Z9: 見積計算書NO
A10: 2 | C10: 画 | D10: 基本情報 | H10: 案件NO | S10: T | T10: 見積計算書 | Z10: 案件NO(親)、(子)、(部材) | AK10: 表示形式：案件NO(親)+ '-' + 案件NO(子)+ '-' + 案件NO(部材) | BM10: Rev2.0 変更
A11: 3 | C11: 画 | D11: 基本情報 | H11: 版型名 | S11: T | T11: 見積計算書 | Z11: 顧客品名 | BM11: CP指摘 2022/09/21 土屋 顧客品名＋版型分類名にするとわかりやすいと思います | CP11: MDSOL回答 2022/10/31 石田 見積参照時には、分類はセットされておりません。 | DR11: 2022/11/04 土屋 問題なし(当該ページNo1は見積参照時の検索される記載内容と認識しました。No1とNo2の違いがヘッダーの備考に書かれているとわかりやすいかと思いました)
A12: 4 | C12: 画 | D12: 基本情報 | H12: 得意先 | S12: T | T12: 見積計算書 | Z12: 得意先
A13: 5 | C13: 画 | D13: 基本情報 | H13: 得意先名 | S13: T | T13: 取引先 | Z13: 得意先名
A14: 6 | C14: 画 | D14: 構成情報 | H14: シート段 | S14: T | T14: 見積計算書 | Z14: シート段
A15: 7 | C15: 画 | D15: 構成情報 | H15: 原紙コード(表) | S15: T | T15: 見積計算書 | Z15: 原紙コード(表)
A16: 8 | C16: 画 | D16: 構成情報 | H16: 原紙コード(表)名 | S16: T | T16: 原紙 | Z16: 原紙コード(表)名
A17: 9 | C17: 画 | D17: 構成情報 | H17: 印刷コード(表) | S17: T | T17: 見積計算書 | Z17: 印刷コード(表)
A18: 10 | C18: 画 | D18: 構成情報 | H18: 印刷コード(表)名 | S18: T | T18: 印刷 | Z18: 印刷コード(表)名
A19: 11 | C19: 画 | D19: 構成情報 | H19: エンボスコード(表) | S19: T | T19: 見積計算書 | Z19: エンボスコード(表)
A20: 12 | C20: 画 | D20: 構成情報 | H20: エンボスコード(表)名 | S20: T | T20: エンボス | Z20: エンボスコード(表)名
A21: 13 | C21: 画 | D21: 構成情報 | H21: メーカ(表) | S21: T | T21: 見積計算書 | Z21: メーカ(表)
A22: 14 | C22: 画 | D22: 構成情報 | H22: メーカ(表)名 | S22: T | T22: 取引先 | Z22: メーカ(表)名
A23: 15 | C23: 画 | D23: 構成情報 | H23: 原紙コード(中) | S23: T | T23: 見積計算書 | Z23: 原紙コード(中)
... A43: 35 | C43: 画 | D43: 構成情報 | H43: 付数 | S43: T | T43: 見積計算書 | Z43: 付数
A46: No | G46: 2 | H46: ボタン | L46: 検索 | S46: ロジック名称 | AH46: 備考 | AK46: 木型・版型管理マスタの検索
A47: 処理分類 | E47: 検索 | H47: ソート順
A48: No | C48: 転送先 | S48: 転送元 | AK48: 説明
C49: 種 | D49: オブジェクト | H49: 項目名 | S49: 種 | T49: オブジェクト | Z49: 項目名
A50: 1 | C50: 画 | H50: 拠点 | S50: T | T50: 木型・版型管理マスタ | Z50: 拠点
A51: 2 | C51: 画 | H51: 拠点名 | S51: T | T51: 拠点マスタ | Z51: 拠点名
A52: 3 | C52: 画 | D52: 基本情報 | H52: 決定見積NO | S52: T | T52: 木型・版型管理マスタ | Z52: 決定見積NO
A53: 3 | C53: 画 | D53: 基本情報 | H53: 案件NO | S53: T | T53: 見積計算書 | Z53: 案件NO(親)、(子)、(部材) | AK53: 表示形式：案件NO(親)+ '-' + 案件NO(子)+ '-' + 案件NO(部材) | BM53: Rev2.0 変更
A54: 4 | C54: 画 | D54: 基本情報 | H54: 版型名 | S54: T | T54: 木型・版型管理マスタ | Z54: 版型名
A55: 5 | C55: 画 | D55: 基本情報 | H55: 売上可否区分 | S55: T | T55: 木型・版型管理マスタ | Z55: 売上可否区分
A56: 6 | C56: 画 | D56: 基本情報 | H56: 手配NO | S56: T | T56: 木型・版型管理マスタ | Z56: 手配NO | AK56: 受注連携後の後処理で手配NOを更新する
A57: 7 | C57: 画 | D57: 基本情報 | H57: 版型No | S57: T | T57: 木型・版型管理マスタ | Z57: 木型・版型No
A58: 8 | C58: 画 | D58: 基本情報 | H58: Rev | S58: T | T58: 木型・版型管理マスタ | Z58: Rev
A59: 9 | C59: 画 | D59: 基本情報 | H59: 適用開始日 | S59: T | T59: 木型・版型管理マスタ | Z59: 適用開始日
A60: 10 | C60: 画 | D60: 基本情報 | H60: 得意先 | S60: T | T60: 木型・版型管理マスタ | Z60: 得意先CD
A61: 11 | C61: 画 | D61: 基本情報 | H61: 得意先名 | S61: T | T61: 得意先マスタ | Z61: 得意先名
A62: 12 | C62: 画 | D62: 基本情報 | H62: 代表製品CD | S62: T | T62: 木型・版型管理マスタ | Z62: 製品CD
A63: 13 | C63: 画 | D63: 基本情報 | H63: 代表製品名1 | S63: T | T63: 製品マスタ | Z63: 品名１ | AK63: 製品の品名１
A64: 14 | C64: 画 | D64: 基本情報 | H64: 代表製品名2 | S64: T | T64: 製品マスタ | Z64: 品名２ | AK64: 製品の品名２
A65: 15 | C65: 画 | D65: 基本情報 | H65: 新版区分 | S65: T | T65: 木型・版型管理マスタ | Z65: 新版区分
A66: 16 | C66: 画 | D66: 基本情報 | H66: 工程 | S66: T | T66: 木型・版型管理マスタ | Z66: 工程
A67: 17 | C67: 画 | D67: 基本情報 | H67: 版型分類 | S67: T | T67: 木型・版型管理マスタ | Z67: 版型分類
A68: 18 | C68: 画 | D68: 基本情報 | H68: 最終加工場所 | S68: T | T68: 木型・版型管理マスタ | Z68: 最終加工場所
A69: 19 | C69: 画 | D69: 基本情報 | H69: 実績日 | S69: T | T69: 木型・版型管理情報 | Z69: 実績日 | AK69: 実績テーブルを参照する | BN69: Rev2.0 記述変更(木型・版型実績→木型・版型管理情報)
A70: 20 | C70: 画 | D70: 構成情報 | H70: シート段 | S70: T | T70: 木型・版型管理マスタ | Z70: シート段
A71: 21 | C71: 画 | D71: 構成情報 | H71: 原紙コード(表) | S71: T | T71: 木型・版型管理マスタ | Z71: 原紙コード(表)
A72: 22 | C72: 画 | D72: 構成情報 | H72: 原紙コード(表)名 | S72: T | T72: 原紙マスタ | Z72: 原紙コード名
A73: 23 | C73: 画 | D73: 構成情報 | H73: 印刷コード(表) | S73: T | T73: 木型・版型管理マスタ | Z73: 印刷コード(表)
A74: 24 | C74: 画 | D74: 構成情報 | H74: 印刷コード(表)名 | S74: T | T74: 印刷マスタ | Z74: 印刷コード名
A75: 25 | C75: 画 | D75: 構成情報 | H75: エンボスコード(表) | S75: T | T75: 木型・版型管理マスタ | Z75: エンボスコード(表)
A76: 26 | C76: 画 | D76: 構成情報 | H76: エンボスコード(表)名 | S76: T | T76: エンボスマスタ | Z76: エンボスコード名
A77: 27 | C77: 画 | D77: 構成情報 | H77: メーカ(表) | S77: T | T77: 木型・版型管理マスタ | Z77: メーカ(表)
A78: 28 | C78: 画 | D78: 構成情報 | H78: メーカ(表)名 | S78: T | T78: メーカマスタ | Z78: メーカ名
A79: 29 | C79: 画 | D79: 構成情報 | H79: 原紙コード(中) | S79: T | T79: 木型・版型管理マスタ | Z79: 原紙コード(中)
A80: 30 | C80: 画 | D80: 構成情報 | H80: 原紙コード(中)名 | S80: T | T80: 原紙マスタ | Z80: 原紙コード名
A81: 31 | C81: 画 | D81: 構成情報 | H81: 印刷コード(中) | S81: T | T81: 木型・版型管理マスタ | Z81: 印刷コード(中)
... A125: 75 | C125: 画 | D125: 構成情報 | H125: 棚・ライン名 | S125: T | T125: 場所マスタ | Z125: 棚・ライン名
A126: 76 | C126: 画 | D126: 構成情報 | H126: 通し数 | S126: T | T126: 木型・版型管理情報 | Z126: 通し数 | AK126: 実績テーブルを参照する | BN126: Rev2.0 記述変更(木型・版型実績→木型・版型管理情報)
A127: 77 | C127: 画 | D127: 構成情報 | H127: 限界通し数 | S127: T | T127: 木型・版型管理マスタ | Z127: 限界通し数
A128: 78 | C128: 画 | D128: 構成情報 | H128: 廃棄予定日 | S128: T | T128: 木型・版型管理マスタ | Z128: 廃棄予定日
A129: 79 | C129: 画 | D129: 構成情報 | H129: 返却予定日 | S129: T | T129: 木型・版型管理マスタ | Z129: 返却予定日
A130: 80 | C130: 画 | D130: 構成情報 | H130: 返却日 | S130: T | T130: 木型・版型管理マスタ | Z130: 返却日
A131: 81 | C131: 画 | D131: 構成情報 | H131: 返却理由 | S131: T | T131: 木型・版型管理マスタ | Z131: 返却理由
A132: 82 | C132: 画 | D132: 構成情報 | H132: 備考 | S132: T | T132: 木型・版型管理マスタ | Z132: 備考
A133: 83 | C133: 画 | D133: 添付情報 | H133: 表図面 | S133: T | T133: 木型・版型管理マスタ | Z133: 添付情報_表図面
A134: 84 | C134: 画 | D134: 添付情報 | H134: 裏図面 | S134: T | T134: 木型・版型管理マスタ | Z134: 添付情報_裏図面
A135: 85 | C135: 画 | D135: 添付情報 | H135: 現物 | S135: T | T135: 木型・版型管理マスタ | Z135: 添付情報_現物
A136: 86 | C136: 画 | D136: 添付情報 | H136: 版下 | S136: T | T136: 木型・版型管理マスタ | Z136: 添付情報_版下
A137: 87 | C137: 画 | D137: 添付情報 | H137: ポジ | S137: T | T137: 木型・版型管理マスタ | Z137: 添付情報_ポジ
A138: 88 | C138: 画 | D138: 添付情報 | H138: ネガ | S138: T | T138: 木型・版型管理マスタ | Z138: 添付情報_ネガ
... A149: 99 | C149: 画 | D149: 必要物 | H149: その他 | S149: T | T149: 木型・版型管理マスタ | Z149: 必要物_その他
A150: 100 | C150: 画 | D150: 過去履歴 | H150: № | Z150: 行番
A151: 101 | C151: 画 | D151: 過去履歴 | H151: 適用開始日 | S151: T | T151: 木型・版型管理マスタ | Z151: 適用開始日
A152: 102 | C152: 画 | D152: 過去履歴 | H152: 適用終了日 | S152: T | T152: 木型・版型管理マスタ | Z152: 適用終了日
A153: 103 | C153: 画 | D153: 過去履歴 | H153: Rev | S153: T | T153: 木型・版型管理マスタ | Z153: Rev
A154: 104 | C154: 画 | D154: 過去履歴 | H154: 発注先 | S154: T | T154: 木型・版型管理マスタ | Z154: 発注先
A155: 105 | C155: 画 | D155: 過去履歴 | H155: 発注先名 | S155: T | T155: 発注先マスタ | Z155: 発注先名
A156: 106 | C156: 画 | D156: 過去履歴 | H156: 通し数 | S156: T | T156: 木型・版型管理マスタ | Z156: 通し数
A157: 107 | C157: 画 | D157: 過去履歴 | H157: 廃棄予定日 | S157: T | T157: 木型・版型管理マスタ | Z157: 廃棄予定日
A158: 108 | C158: 画 | D158: 過去履歴 | H158: 返却予定日 | S158: T | T158: 木型・版型管理マスタ | Z158: 返却予定日
A159: 109 | C159: 画 | D159: 過去履歴 | H159: 返却日 | S159: T | T159: 木型・版型管理マスタ | Z159: 返却日
A160: 110 | C160: 画 | D160: 過去履歴 | H160: 返却理由 | S160: T | T160: 木型・版型管理マスタ | Z160: 返却理由
A161: 111 | C161: 画 | D161: ボタン | H161: 版型発注書 | S161: T | AK161: 版型発注書URL＋&KEY＝ PE木型・版型管理マスタ.NO

Sheet 更新入出力仕様
A1: =表紙!A54 -> Webシステム | K1: 文書名 | U1: モジュールID | Z1: =表紙!$AJ$63 -> MS | AE1: モジュール名 | AJ1: =表紙!$AX$63 -> 見積管理 | AS1: 文書番号 | AZ1: Version | BF1: Rev.
K2: =表紙!O64 -> 画面機能 | U2: ｻﾌﾞﾓｼﾞｭｰﾙID | Z2: =表紙!$AJ$64 -> MSBB | AE2: ｻﾌﾞﾓｼﾞｭｰﾙ名 | AJ2: =表紙!$AX$64 -> Webシステム | AS2: =表紙!$BL$64 -> M7-US-1140 | AZ2: =表紙!$BU$64 -> 1.0.0 | BF2: =表紙!$CB$64 -> 3
K3: =RIGHT(CELL("filename",$A$1),LEN(CELL("filename",$A$1))-FIND("]",CELL("filename",$A$1))) -> 更新入出力仕様 | U3: 表題 | Z3: =表紙!$AJ$65 -> アドオン画面 | AE3: =表紙!$AQ$65 -> Web版型・木型マスタ
A5: No | G5: 1 | H5: ボタン | L5: 登録する | S5: ロジック名称 | AH5: 備考 | AK5: 木型・版型管理マスタの登録
A6: 処理分類 | E6: 登録 | H6: ソート順
A7: No | C7: 転送先 | S7: 転送元 | AK7: 説明
C8: 種 | D8: オブジェクト | H8: 項目名 | S8: 種 | T8: オブジェクト | Z8: 項目名
A9: 1 | C9: T | D9: 木型・版型管理マスタ | H9: 拠点 | S9: 画 | T9: 版型マスタメンテ | Z9: 拠点
A10: 2 | C10: T | D10: 木型・版型管理マスタ | H10: 決定見積NO | S10: 画 | T10: 版型マスタメンテ | Z10: 決定見積NO
A11: 3 | C11: T | D11: 木型・版型管理マスタ | H11: 品目CD | S11: 画 | T11: 版型マスタメンテ | Z11: 品名
A12: 4 | C12: T | D12: 木型・版型管理マスタ | H12: 売上可否区分 | S12: 画 | T12: 版型マスタメンテ | Z12: 売上可否区分
A13: 5 | C13: T | D13: 木型・版型管理マスタ | H13: 手配NO | S13: 画 | T13: 版型マスタメンテ | Z13: 手配NO
A14: 6 | C14: T | D14: 木型・版型管理マスタ | H14: 版型No | S14: 画 | T14: 版型マスタメンテ | Z14: 版型No
A15: 7 | C15: T | D15: 木型・版型管理マスタ | H15: Rev | S15: 画 | T15: 版型マスタメンテ | Z15: Rev
A16: 8 | C16: T | D16: 木型・版型管理マスタ | H16: 適用開始日 | S16: 画 | T16: 版型マスタメンテ | Z16: 適用開始日
A17: 9 | C17: T | D17: 木型・版型管理マスタ | H17: 得意先 | S17: 画 | T17: 版型マスタメンテ | Z17: 得意先
A18: 10 | C18: T | D18: 木型・版型管理マスタ | H18: 代表製品CD | S18: 画 | T18: 版型マスタメンテ | Z18: 代表製品CD
A19: 11 | C19: T | D19: 木型・版型管理マスタ | H19: 新版区分 | S19: 画 | T19: 版型マスタメンテ | Z19: 新版区分
A20: 12 | C20: T | D20: 木型・版型管理マスタ | H20: 工程 | S20: 画 | T20: 版型マスタメンテ | Z20: 工程
... A70: 62 | C70: T | D70: 木型・版型管理マスタ | H70: 備考 | S70: 画 | T70: 版型マスタメンテ | Z70: 備考
A71: 63 | C71: T | D71: 木型・版型管理マスタ | H71: 論理削除ＦＬＧ | Z71: システム自動処理 | AK71: 0
A72: 64 | C72: T | D72: 木型・版型管理マスタ | H72: 登録ユーザＩＤ | Z72: システム自動処理
A73: 65 | C73: T | D73: 木型・版型管理マスタ | H73: 登録ユーザ名 | Z73: システム自動処理
A74: 66 | C74: T | D74: 木型・版型管理マスタ | H74: 登録日時 | Z74: システム自動処理
A75: 67 | C75: T | D75: 木型・版型管理マスタ | H75: 登録機能ＩＤ | Z75: システム自動処理
A76: 68 | C76: T | D76: 木型・版型管理マスタ | H76: 登録機能名 | Z76: システム自動処理
A77: 69 | C77: T | D77: 木型・版型管理マスタ | H77: 更新ユーザＩＤ | Z77: システム自動処理
A78: 70 | C78: T | D78: 木型・版型管理マスタ | H78: 更新ユーザ名 | Z78: システム自動処理
A79: 71 | C79: T | D79: 木型・版型管理マスタ | H79: 更新日時 | Z79: システム自動処理
A80: 72 | C80: T | D80: 木型・版型管理マスタ | H80: 更新機能ＩＤ | Z80: システム自動処理
A81: 73 | C81: T | D81: 木型・版型管理マスタ | H81: 更新機能名 | Z81: システム自動処理
A82: 74 | C82: T | D82: 木型・版型管理マスタ | H82: 更新リクエストＮＯ | Z82: システム自動処理
A83: 75 | C83: T | D83: 木型・版型管理マスタ | H83: 論理削除ユーザＩＤ | Z83: システム自動処理
... A85: 77 | C85: T | D85: 木型・版型管理マスタ | H85: 論理削除日時 | Z85: システム自動処理
A86: No | G86: 2 | H86: ボタン | L86: 改定する | S86: ロジック名称 | AH86: 備考 | AK86: 木型・版型管理マスタの登録
A87: 処理分類 | E87: 改定 | H87: ソート順
A88: No | C88: 転送先 | S88: 転送元 | AK88: 説明
C89: 種 | D89: オブジェクト | H89: 項目名 | S89: 種 | T89: オブジェクト | Z89: 項目名
A90: 1 | C90: T | D90: 木型・版型管理マスタ | H90: 拠点 | S90: 画 | T90: 版型マスタメンテ | Z90: 拠点
A91: 2 | C91: T | D91: 木型・版型管理マスタ | H91: 決定見積NO | S91: 画 | T91: 版型マスタメンテ | Z91: 決定見積NO
A92: 3 | C92: T | D92: 木型・版型管理マスタ | H92: 品目CD | S92: 画 | T92: 版型マスタメンテ | Z92: 品名
A93: 4 | C93: T | D93: 木型・版型管理マスタ | H93: 売上可否区分 | S93: 画 | T93: 版型マスタメンテ | Z93: 売上可否区分
A94: 5 | C94: T | D94: 木型・版型管理マスタ | H94: 手配NO | S94: 画 | T94: 版型マスタメンテ | Z94: 手配NO
A95: 6 | C95: T | D95: 木型・版型管理マスタ | H95: 版型No | S95: 画 | T95: 版型マスタメンテ | Z95: 版型No
A96: 7 | C96: T | D96: 木型・版型管理マスタ | H96: Rev | S96: 画 | T96: 版型マスタメンテ | Z96: Rev | AK96: ※改定はRev＝最大Rev＋１ 画面表示時、自動設定
A97: 8 | C97: T | D97: 木型・版型管理マスタ | H97: 適用開始日 | S97: 画 | T97: 版型マスタメンテ | Z97: 適用開始日
A98: 9 | C98: T | D98: 木型・版型管理マスタ | H98: 得意先 | S98: 画 | T98: 版型マスタメンテ | Z98: 得意先
A99: 10 | C99: T | D99: 木型・版型管理マスタ | H99: 代表製品CD | S99: 画 | T99: 版型マスタメンテ | Z99: 代表製品CD
A100: 11 | C100: T | D100: 木型・版型管理マスタ | H100: 新版区分 | S100: 画 | T100: 版型マスタメンテ | Z100: 新版区分
A101: 12 | C101: T | D101: 木型・版型管理マスタ | H101: 工程 | S101: 画 | T101: 版型マスタメンテ | Z101: 工程
A102: 13 | C102: T | D102: 木型・版型管理マスタ | H102: 版型分類 | S102: 画 | T102: 版型マスタメンテ | Z102: 版型分類
A103: 14 | C103: T | D103: 木型・版型管理マスタ | H103: 最終加工場所 | S103: 画 | T103: 版型マスタメンテ | Z103: 最終加工場所
A104: 15 | C104: T | D104: 木型・版型管理マスタ | H104: 実績日 | S104: 画 | T104: 版型マスタメンテ | Z104: 実績日
A105: 16 | C105: T | D105: 木型・版型管理マスタ | H105: シート段 | S105: 画 | T105: 版型マスタメンテ | Z105: シート段
A106: 17 | C106: T | D106: 木型・版型管理マスタ | H106: 原紙コード(表) | S106: 画 | T106: 版型マスタメンテ | Z106: 原紙コード(表)
A107: 18 | C107: T | D107: 木型・版型管理マスタ | H107: 印刷コード(表) | S107: 画 | T107: 版型マスタメンテ | Z107: 印刷コード(表)
A108: 19 | C108: T | D108: 木型・版型管理マスタ | H108: エンボスコード(表) | S108: 画 | T108: 版型マスタメンテ | Z108: エンボスコード(表)
... A151: 62 | C151: T | D151: 木型・版型管理マスタ | H151: 備考 | S151: 画 | T151: 版型マスタメンテ | Z151: 備考
A152: 63 | C152: T | D152: 木型・版型管理マスタ | H152: 論理削除ＦＬＧ | Z152: システム自動処理
A153: 64 | C153: T | D153: 木型・版型管理マスタ | H153: 登録ユーザＩＤ | Z153: システム自動処理
A154: 65 | C154: T | D154: 木型・版型管理マスタ | H154: 登録ユーザ名 | Z154: システム自動処理
A155: 66 | C155: T | D155: 木型・版型管理マスタ | H155: 登録日時 | Z155: システム自動処理
A156: 67 | C156: T | D156: 木型・版型管理マスタ | H156: 登録機能ＩＤ | Z156: システム自動処理
A157: 68 | C157: T | D157: 木型・版型管理マスタ | H157: 登録機能名 | Z157: システム自動処理
A158: 69 | C158: T | D158: 木型・版型管理マスタ | H158: 更新ユーザＩＤ | Z158: システム自動処理
A159: 70 | C159: T | D159: 木型・版型管理マスタ | H159: 更新ユーザ名 | Z159: システム自動処理
A160: 71 | C160: T | D160: 木型・版型管理マスタ | H160: 更新日時 | Z160: システム自動処理
A161: 72 | C161: T | D161: 木型・版型管理マスタ | H161: 更新機能ＩＤ | Z161: システム自動処理
A162: 73 | C162: T | D162: 木型・版型管理マスタ | H162: 更新機能名 | Z162: システム自動処理
A163: 74 | C163: T | D163: 木型・版型管理マスタ | H163: 更新リクエストＮＯ | Z163: システム自動処理
... A166: 77 | C166: T | D166: 木型・版型管理マスタ | H166: 論理削除日時 | Z166: システム自動処理
A167: No | G167: 3 | H167: ボタン | L167: 訂正する | S167: ロジック名称 | AH167: 備考 | AK167: 木型・版型管理マスタの更新
A168: 処理分類 | E168: 更新 | H168: ソート順
A169: No | C169: 転送先 | S169: 転送元 | AK169: 説明
C170: 種 | D170: オブジェクト | H170: 項目名 | S170: 種 | T170: オブジェクト | Z170: 項目名
A171: 1 | C171: T | D171: 木型・版型管理マスタ | H171: 拠点 | S171: 画 | T171: 版型マスタメンテ | Z171: 拠点
A172: 2 | C172: T | D172: 木型・版型管理マスタ | H172: 決定見積NO | S172: 画 | T172: 版型マスタメンテ | Z172: 決定見積NO
A173: 3 | C173: T | D173: 木型・版型管理マスタ | H173: 品目CD | S173: 画 | T173: 版型マスタメンテ | Z173: 品名
A174: 4 | C174: T | D174: 木型・版型管理マスタ | H174: 売上可否区分 | S174: 画 | T174: 版型マスタメンテ | Z174: 売上可否区分 | AK174: ※更新しない
A175: 5 | C175: T | D175: 木型・版型管理マスタ | H175: 手配NO | S175: 画 | T175: 版型マスタメンテ | Z175: 手配NO | AK175: ※更新しない
A176: 6 | C176: T | D176: 木型・版型管理マスタ | H176: 版型No | S176: 画 | T176: 版型マスタメンテ | Z176: 版型No | AK176: 更新用KEY※更新しない
A177: 7 | C177: T | D177: 木型・版型管理マスタ | H177: Rev | S177: 画 | T177: 版型マスタメンテ | Z177: Rev | AK177: 更新用KEY※更新しない
A178: 8 | C178: T | D178: 木型・版型管理マスタ | H178: 適用開始日 | S178: 画 | T178: 版型マスタメンテ | Z178: 適用開始日
A179: 9 | C179: T | D179: 木型・版型管理マスタ | H179: 得意先 | S179: 画 | T179: 版型マスタメンテ | Z179: 得意先
A180: 10 | C180: T | D180: 木型・版型管理マスタ | H180: 代表製品CD | S180: 画 | T180: 版型マスタメンテ | Z180: 代表製品CD
A181: 11 | C181: T | D181: 木型・版型管理マスタ | H181: 新版区分 | S181: 画 | T181: 版型マスタメンテ | Z181: 新版区分 | AK181: ※更新しない
A182: 12 | C182: T | D182: 木型・版型管理マスタ | H182: 工程 | S182: 画 | T182: 版型マスタメンテ | Z182: 工程
A183: 13 | C183: T | D183: 木型・版型管理マスタ | H183: 版型分類 | S183: 画 | T183: 版型マスタメンテ | Z183: 版型分類
A184: 14 | C184: T | D184: 木型・版型管理マスタ | H184: 最終加工場所 | S184: 画 | T184: 版型マスタメンテ | Z184: 最終加工場所
A185: 15 | C185: T | D185: 木型・版型管理マスタ | H185: 実績日 | S185: 画 | T185: 版型マスタメンテ | Z185: 実績日 | AK185: ※更新しない
A186: 16 | C186: T | D186: 木型・版型管理マスタ | H186: シート段 | S186: 画 | T186: 版型マスタメンテ | Z186: シート段
A187: 17 | C187: T | D187: 木型・版型管理マスタ | H187: 原紙コード(表) | S187: 画 | T187: 版型マスタメンテ | Z187: 原紙コード(表)
A188: 18 | C188: T | D188: 木型・版型管理マスタ | H188: 印刷コード(表) | S188: 画 | T188: 版型マスタメンテ | Z188: 印刷コード(表)
A189: 19 | C189: T | D189: 木型・版型管理マスタ | H189: エンボスコード(表) | S189: 画 | T189: 版型マスタメンテ | Z189: エンボスコード(表)
A190: 20 | C190: T | D190: 木型・版型管理マスタ | H190: メーカ(表) | S190: 画 | T190: 版型マスタメンテ | Z190: メーカ(表)
A191: 21 | C191: T | D191: 木型・版型管理マスタ | H191: 原紙コード(中) | S191: 画 | T191: 版型マスタメンテ | Z191: 原紙コード(中)
A192: 22 | C192: T | D192: 木型・版型管理マスタ | H192: 印刷コード(中) | S192: 画 | T192: 版型マスタメンテ | Z192: 印刷コード(中)
A193: 23 | C193: T | D193: 木型・版型管理マスタ | H193: エンボスコード(中) | S193: 画 | T193: 版型マスタメンテ | Z193: エンボスコード(中)
A194: 24 | C194: T | D194: 木型・版型管理マスタ | H194: メーカ(中) | S194: 画 | T194: 版型マスタメンテ | Z194: メーカ(中)
A195: 25 | C195: T | D195: 木型・版型管理マスタ | H195: 原紙コード(裏) | S195: 画 | T195: 版型マスタメンテ | Z195: 原紙コード(裏)
...

Sheet 更新入出力仕様(PE)
A1: =表紙!A54 -> Webシステム | K1: 文書名 | U1: モジュールID | Z1: =表紙!$AJ$63 -> MS | AE1: モジュール名 | AJ1: =表紙!$AX$63 -> 見積管理 | AS1: 文書番号 | AZ1: Version | BF1: Rev.
K2: =表紙!O64 -> 画面機能 | U2: ｻﾌﾞﾓｼﾞｭｰﾙID | Z2: =表紙!$AJ$64 -> MSBB | AE2: ｻﾌﾞﾓｼﾞｭｰﾙ名 | AJ2: =表紙!$AX$64 -> Webシステム | AS2: =表紙!$BL$64 -> M7-US-1140 | AZ2: =表紙!$BU$64 -> 1.0.0 | BF2: =表紙!$CB$64 -> 3
K3: =RIGHT(CELL("filename",$A$1),LEN(CELL("filename",$A$1))-FIND("]",CELL("filename",$A$1))) -> 更新入出力仕様(PE) | U3: 表題 | Z3: =表紙!$AJ$65 -> アドオン画面 | AE3: =表紙!$AQ$65 -> Web版型・木型マスタ
A5: No | G5: 1 | H5: ボタン | L5: PE API連携 | S5: ロジック名称 | AH5: 備考 | AK5: PE API連携
A6: 処理分類 | E6: 登録/更新 | H6: ソート順
A7: No | C7: 転送先 | S7: 転送元 | AK7: 説明 | CU7: CP指摘 2022/10/20 本多 起票者は営業担当者ではなく、出力操作時の社員で出力されますでしょうか？ | ED7: MDSOL回答 2022/10/31 石田 営業担当者になります。
C8: 種 | D8: オブジェクト | H8: 項目名 | S8: 種 | T8: オブジェクト | Z8: 項目名 | EE8: 2022/11/01 落合 出力したユーザーで印字して下さい
A9: 1 | C9: T | D9: PE木型・版型管理マスタ | H9: 拠点 | S9: T | T9: 木型・版型管理マスタ | Z9: 拠点 | EF9: MDSOL回答 2022/11/02 野村 出力したユーザーで印字します。PE標準機能で対応可能です。
A10: 2 | C10: T | D10: PE木型・版型管理マスタ | H10: 部門CD | S10: T | T10: 木型・版型管理マスタ | Z10: 部門CD | EF10: 2022/11/04 落合 問題なし
A11: 3 | C11: T | D11: PE木型・版型管理マスタ | H11: 営業担当CD | S11: T | T11: 木型・版型管理マスタ | Z11: 営業担当CD
A12: 4 | C12: T | D12: PE木型・版型管理マスタ | H12: 営業担当名 | S12: T | T12: 木型・版型管理マスタ | Z12: 営業担当名
A13: 5 | C13: T | D13: PE木型・版型管理マスタ | H13: 得意先CD | S13: T | T13: 木型・版型管理マスタ | Z13: 得意先CD
A14: 6 | C14: T | D14: PE木型・版型管理マスタ | H14: 得意先名 | S14: T | T14: 木型・版型管理マスタ | Z14: 得意先名
A15: 7 | C15: T | D15: PE木型・版型管理マスタ | H15: 発注先CD | S15: T | T15: 木型・版型管理マスタ | Z15: 発注先CD
A16: 8 | C16: T | D16: PE木型・版型管理マスタ | H16: 発注先名 | S16: T | T16: 木型・版型管理マスタ | Z16: 発注先名
A17: 9 | C17: T | D17: PE木型・版型管理マスタ | H17: 納期 | S17: T | T17: 木型・版型管理マスタ | Z17: 納期
A18: 10 | C18: T | D18: PE木型・版型管理マスタ | H18: 発注品目 | S18: T | T18: 木型・版型管理マスタ | Z18: 版型分類
A19: 11 | C19: T | D19: PE木型・版型管理マスタ | H19: 発注品目_その他 | S19: T | T19: 木型・版型管理マスタ | Z19: 版型分類
A20: 12 | C20: T | D20: PE木型・版型管理マスタ | H20: 発注内容 | S20: T | T20: 木型・版型管理マスタ | Z20: 新版区分
A21: 13 | C21: T | D21: PE木型・版型管理マスタ | H21: 発注内容_その他 | S21: T | T21: 木型・版型管理マスタ | Z21: 新版区分
A22: 14 | C22: T | D22: PE木型・版型管理マスタ | H22: 加工予定先 | S22: T | T22: 木型・版型管理マスタ | Z22: 加工予定先
... A61: 53 | C61: T | D61: PE木型・版型管理マスタ | H61: 備考欄_注意事項 | S61: T | T61: 木型・版型管理マスタ | Z61: 備考

Sheet ファイル入出力仕様
A1: =表紙!A54 -> Webシステム | K1: 文書名 | U1: モジュールID | Z1: =表紙!$AJ$63 -> MS | AE1: モジュール名 | AJ1: =表紙!$AX$63 -> 見積管理 | AS1: 文書番号 | AZ1: Version | BF1: Rev.
K2: =表紙!O64 -> 画面機能 | U2: ｻﾌﾞﾓｼﾞｭｰﾙID | Z2: =表紙!$AJ$64 -> MSBB | AE2: ｻﾌﾞﾓｼﾞｭｰﾙ名 | AJ2: =表紙!$AX$64 -> Webシステム | AS2: =表紙!$BL$64 -> M7-US-1140 | AZ2: =表紙!$BU$64 -> 1.0.0 | BF2: =表紙!$CB$64 -> 3
K3: =RIGHT(CELL("filename",$A$1),LEN(CELL("filename",$A$1))-FIND("]",CELL("filename",$A$1))) -> ファイル入出力仕様 | U3: 表題 | Z3: =表紙!$AJ$65 -> アドオン画面 | AE3: =表紙!$AQ$65 -> Web版型・木型マスタ
A5: No | G5: 1 | H5: ボタン | L5: ラベル発行 | S5: ロジック名称 | Z5: Prnt01 | AH5: 備考 | AK5: 版・型管理ラベル発行用のCSVファイルの出力
A6: 処理分類 | E6: 出力 | H6: ソート順
A7: No | C7: 転送先 | S7: 転送元 | AK7: 説明
C8: 種 | D8: オブジェクト | H8: 項目名 | S8: 種 | T8: オブジェクト | Z8: 項目名
A9: 1 | C9: フ | D9: 版・型管理ラベル出力用CSVファイル | H9: 版型No | S9: T | T9: 木型・版型管理マスタ | Z9: 版型No
A10: 2 | C10: フ | D10: 版・型管理ラベル出力用CSVファイル | H10: 版型名 | S10: T | T10: 木型・版型管理マスタ | Z10: 版型名
A11: 3 | C11: フ | D11: 版・型管理ラベル出力用CSVファイル | H11: Rev | S11: T | T11: 木型・版型管理マスタ | Z11: Rev
A12: 4 | C12: フ | D12: 版・型管理ラベル出力用CSVファイル | H12: 版型分類 | S12: T | T12: 木型・版型管理マスタ | Z12: 版型分類
A13: 5 | C13: フ | D13: 版・型管理ラベル出力用CSVファイル | H13: 得意先 | S13: T | T13: 木型・版型管理マスタ | Z13: 得意先
A14: 6 | C14: フ | D14: 版・型管理ラベル出力用CSVファイル | H14: 得意先名 | S14: T | T14: 取引先 | Z14: 得意先名
A15: 7 | C15: フ | D15: 版・型管理ラベル出力用CSVファイル | H15: 製品コード | S15: T | T15: 木型・版型管理マスタ | Z15: 製品コード
A16: 8 | C16: フ | D16: 版・型管理ラベル出力用CSVファイル | H16: 製品名 | S16: T | T16: 木型・版型管理マスタ | Z16: 製品名
A17: 9 | C17: フ | D17: 版・型管理ラベル出力用CSVファイル | H17: 通し数 | S17: T | T17: 木型・版型管理マスタ | Z17: 通し数
A18: 10 | C18: フ | D18: 版・型管理ラベル出力用CSVファイル | H18: 限界通し数 | S18: T | T18: 木型・版型管理マスタ | Z18: 限界通し数
A19: 11 | C19: フ | D19: 版・型管理ラベル出力用CSVファイル | H19: 発注先 | S19: T | T19: 木型・版型管理マスタ | Z19: 発注先
A20: 12 | C20: フ | D20: 版・型管理ラベル出力用CSVファイル | H20: 発注先名 | S20: T | T20: 木型・版型管理マスタ | Z20: 発注先名
... A44: 36 | C44: フ | D44: 版・型管理ラベル出力用CSVファイル | H44: 備考 | S44: T | T44: 木型・版型管理マスタ | Z44: 備考
A45: 37 | C45: フ | D45: 版・型管理ラベル出力用CSVファイル | H45: 手配NO | S45: T | T45: 木型・版型管理マスタ | Z45: 手配NO | AK45: 手配NO追加

Sheet メッセージ一覧
A1: =表紙!A54 -> Webシステム | K1: 文書名 | U1: モジュールID | Z1: =表紙!$AJ$63 -> MS | AE1: モジュール名 | AJ1: =表紙!$AX$63 -> 見積管理 | AS1: 文書番号 | AZ1: Version | BF1: Rev.
K2: =表紙!O64 -> 画面機能 | U2: ｻﾌﾞﾓｼﾞｭｰﾙID | Z2: =表紙!$AJ$64 -> MSBB | AE2: ｻﾌﾞﾓｼﾞｭｰﾙ名 | AJ2: =表紙!$AX$64 -> Webシステム | AS2: =表紙!$BL$64 -> M7-US-1140 | AZ2: =表紙!$BU$64 -> 1.0.0 | BF2: =表紙!$CB$64 -> 3
K3: =RIGHT(CELL("filename",$A$1),LEN(CELL("filename",$A$1))-FIND("]",CELL("filename",$A$1))) -> メッセージ一覧 | U3: 表題 | Z3: =表紙!$AJ$65 -> アドオン画面 | AE3: =表紙!$AQ$65 -> Web版型・木型マスタ
A5: No | C5: 新/変 | E5: 種別 | G5: メッセージ内容 | AQ5: 備考（パラメータ等） | BG5: メッセージID
A6: 1 | E6: I | G6: 検索結果がありません。 | BG6: E10008
A7: 2 | C7: 新 | E7: W | G7: すでに更新済みです。再検索してください。 木型・版型No：{1}、Rev：{2} | AQ7: {1}：対象明細行の木型・版型No {2}：対象明細行のRev | BG7: E10023
A8: 3 | E8: W | G8: 必須項目に値が指定されていません。行：{1} 列名：{2} | AQ8: {1}：対象明細行番号 {2}：対象明細行の項目名 | BG8: E10021
A9: 4 | C9: 新 | E9: W | G9: 適用開始日と適用終了日の前後関係が不正です。 行：{1} 適用開始日：{2}、適用終了日：{3} | AQ9: {1}：対象明細行番号 {2}：対象明細行の適用開始日 {3}：対象明細行の適用終了日 | BG9: E10024
A10: 5 | C10: 新 | E10: W | G10: 適用開始日と廃棄予定日の前後関係が不正です。 行：{1} 適用開始日：{2}、廃棄予定日：{3} | AQ10: {1}：対象明細行番号 {2}：対象明細行の適用開始日 {3}：対象明細行の廃棄予定日 | BG10: E10025
A11: 6 | C11: 新 | E11: W | G11: 適用終了日と廃棄予定日の前後関係が不正です。 行：{1} 適用終了日：{2}、廃棄予定日：{3} | AQ11: {1}：対象明細行番号 {2}：対象明細行の適用終了日 {3}：対象明細行の廃棄予定日 | BG11: E10026
A12: 7 | C12: 新 | E12: W | G12: 「発行対象がありません。」 | BG12: E10010
A13: 8 | C13: 新 | E13: W | G13: 「入力形式」、「桁数」と「型」に誤りがあります｡ 項目名：{1} | AQ13: {1}：項目名 | BG13: E00001
A14: 9 | C14: 新 | E14: W | G14: 必須項目に値が指定されていません。項目名：{1} | AQ14: {1}：項目名 | BG14: E10022

Sheet テーブル説明
A1: =表紙!A54 -> Webシステム | O1: 文書名 | AC1: モジュールID | AJ1: =表紙!$AJ$63 -> MS | AQ1: モジュール名 | AX1: =表紙!$AX$63 -> 見積管理 | BL1: 文書番号 | BU1: Version | CB1: Rev.
O2: =表紙!O64 -> 画面機能 | AC2: サブモジュールID | AJ2: =表紙!$AJ$64 -> MSBB | AQ2: サブモジュール名 | AX2: =表紙!$AX$64 -> Webシステム | BL2: =表紙!$BL$64 -> M7-US-1140 | BU2: =表紙!$BU$64 -> 1.0.0 | CB2: =表紙!$CB$64 -> 3
O3: =RIGHT(CELL("filename",$A$1),LEN(CELL("filename",$A$1))-FIND("]",CELL("filename",$A$1))) -> テーブル説明 | AC3: 表題 | AJ3: =表紙!$AJ$65 -> アドオン画面 | AQ3: =表紙!$AQ$65 -> Web版型・木型マスタ
A5: テーブル名 | O5: 日本語名
A6: MAM_ | O6: 木型・版型管理マスタ
A8: 主キー | D8: 項目名 | O8: 日本語名 | AE8: 型 | AG8: 桁 | AI8: Null | AK8: 説明 | BL8: 値の制限 | CF8: 設定仕様 | CZ8: 未設定時の振る舞い
A9: ○ | D9: WD_PTN_NO | O9: 木型・版型No | AE9: C | AG9: 40 | AI9: N | AK9: 木型・版型を特定するNo | CF9: 自動採番
A10: ○ | D10: WD_REV | O10: Rev | AE10: N | AG10: 10 | AI10: N | AK10: 木型・版型Noに対する連番 | BL10: 「0」以上の整数 | CF10: ※改定はRev＝最大Rev＋１ 画面表示時、自動設定
D11: POSITION_CD | O11: 拠点 | AE11: C | AG11: 20 | AI11: N
D12: DECISION_ESTIMATE_NO | O12: 決定見積NO | AE12: C | AG12: 20 | AI12: N
D13: VRSN_NAME | O13: 版型名 | AE13: C | AG13: 100 | AI13: N
D14: EARNINGS_CD | O14: 売上可否区分 | AE14: C | AG14: 20 | AI14: Y | AK14: 1:可,2:不可,3:商品込,4:社内処理,5:後報
D15: ARRANGE_NO | O15: 手配NO | AE15: C | AG15: 20 | AI15: Y
D16: ST_DT | O16: 適用開始日 | AE16: D | AI16: N | AK16: 当該レコードを有効にする日 | BL16: 適用開始日≦適用終了日 適用開始日以外のキー項目が同一となる場合に、期間が重なるようなデータは登録できない
D17: END_DT | O17: 適用終了日 | AE17: D | AI17: N | AK17: 当該レコードが有効となる最終日 | BL17: 適用開始日≦適用終了日 適用開始日以外のキー項目が同一となる場合に、期間が重なるようなデータは登録できない
D18: CST_CD | O18: 得意先CD | AE18: C | AG18: 20 | AI18: N | AK18: 得意先を表す取引先CD | BL18: 取引先マスタで得意先ＦＬＧが設定されている取引先ＣＤ
D19: PRODUCT_CD | O19: 代表製品CD | AE19: C | AG19: 20 | AI19: N
D20: NEW_VER_CD | O20: 新版区分 | AE20: C | AG20: 20 | AI20: Y
D21: PROCESS_CD | O21: 工程 | AE21: C | AG21: 20 | AI21: Y
D22: TYPE_CLASS | O22: 版型分類 | AE22: C | AG22: 20 | AI22: Y
D23: END_PLACE_CD | O23: 最終加工場所 | AE23: C | AG23: 20 | AI23: Y
D24: ACHIEVE_DT | O24: 実績日 | AE24: D | AI24: Y
D25: SHEET_CD | O25: シート段 | AE25: C | AG25: 20 | AI25: N
D26: PAPER_CD_OUT | O26: 原紙コード(表) | AE26: C | AG26: 20 | AI26: Y
D27: PRINT_CD_OUT | O27: 印刷コード(表) | AE27: C | AG27: 20 | AI27: Y
D28: EMBOSS_CD_OUT | O28: エンボスコード(表) | AE28: C | AG28: 20 | AI28: Y
D29: MAKER_CD_OUT | O29: メーカ(表) | AE29: C | AG29: 20 | AI29: Y
D30: PAPER_CD_MID | O30: 原紙コード(中) | AE30: C | AG30: 20 | AI30: Y
D31: PRINT_CD_MID | O31: 印刷コード(中) | AE31: C | AG31: 20 | AI31: Y
D32: EMBOSS_CD_MID | O32: エンボスコード(中) | AE32: C | AG32: 20 | AI32: Y
D33: MAKER_CD_MID | O33: メーカ(中) | AE33: C | AG33: 20 | AI33: Y
D34: PAPER_CD_IN | O34: 原紙コード(裏) | AE34: C | AG34: 20 | AI34: Y
D35: PRINT_CD_IN | O35: 印刷コード(裏) | AE35: C | AG35: 20 | AI35: Y
D36: EMBOSS_CD_IN | O36: エンボスコード(裏) | AE36: C | AG36: 20 | AI36: Y
... D38: EXTRACTION_DIRECT | O38: 抜方向 | AE38: C | AG38: 20 | AI38: Y
D39: IMPOSITION_FROM | O39: 面付け(From) | AE39: N | AG39: 9,0 | AI39: N
D40: IMPOSITION_TO | O40: 面付け(To) | AE40: N | AG40: 9,0 | AI40: N
D41: SHEET_WIDTH | O41: シート寸法(巾) | AE41: N | AG41: 9,0 | AI41: N
D42: SHEET_FLOW | O42: シート寸法(流れ) | AE42: N | AG42: 9,0 | AI42: N
D43: BLADE_WIDTH | O43: 刃渡り寸法(巾) | AE43: N | AG43: 9,0 | AI43: N
D44: BLADE_FLOW | O44: 刃渡り寸法(流れ) | AE44: N | AG44: 9,0 | AI44: N
D45: COM_QTY | O45: 付数 | AE45: N | AG45: 9,0 | AI45: N
D46: MFG_QTY | O46: 個数 | AE46: N | AG46: 3,0 | AI46: N | AK46: 一つの木型・版型から製造できる個数 | BL46: 「1」以上の整数
D47: COLOR_QTY | O47: 色数 | AE47: N | AG47: 9,0 | AI47: N
D48: BOOK_QTY | O48: 本数 | AE48: N | AG48: 9,0 | AI48: N
D49: FLEXO_THICK | O49: フレキソ版厚 | AE49: N | AG49: 9,0 | AI49: N
D50: CYLINDER_SIZE | O50: シリンダーサイズ | AE50: N | AG50: 9,0 | AI50: N
D51: SPPL_CD | O51: 発注先CD | AE51: C | AG51: 20 | AI51: N | AK51: 発注先を表す取引先CD | BL51: 取引先マスタで発注先ＦＬＧが設定されている取引先ＣＤ
D52: PROCESS_DESTINATION | O52: 加工予定先 | AE52: C | AG52: 20 | AI52: Y
D53: DELIVERY_DT | O53: 納期 | AE53: D | AI53: Y
D54: ARR_ACT_TM | O54: 入荷実績日 | AE54: D | AI54: Y | AK54: 木型・版型の入荷実績日
D55: ESTIMATE_AMOUNT | O55: 見積価格 | AE55: N | AG55: 9,3 | AI55: N
D56: DECISION_AMOUNT | O56: 決定価格 | AE56: N | AG56: 9,3 | AI56: N
D57: PURCHASE_AMOUNT | O57: 仕入金額 | AE57: N | AG57: 9,3 | AI57: N
D58: SALES_DT | O58: 売上日 | AE58: D | AI58: Y
D59: STRIPPING_CD | O59: 落丁型 | AE59: C | AG59: 20 | AI59: Y
D60: STANDING_CD | O60: 置き版 | AE60: C | AG60: 20 | AI60: Y
D61: HAMMER_CD | O61: ハンマー | AE61: C | AG61: 20 | AI61: Y
D62: OVERSIGHT_CD | O62: 見落とし型 | AE62: C | AG62: 20 | AI62: Y
D63: PLACE_CD | O63: 場所 | AE63: C | AG63: 20 | AI63: Y
D64: SHELF_LINE_CD | O64: 棚・ライン | AE64: C | AG64: 20 | AI64: Y
D65: WD_QTY | O65: 通し数 | AE65: N | AG65: 9,0 | AI65: N | AK65: 木型・版型を使用した数 | BL65: 「0」以上の整数
D66: LMT_WD_QTY | O66: 限界通し数 | AE66: N | AG66: 9,0 | AI66: N | AK66: 木型・版型の使用可能回数 | BL66: 「0」以上の整数
D67: DISP_SCHD_TM | O67: 廃棄予定日 | AE67: D | AI67: Y | AK67: 木型・版型の廃棄予定日 | BL67: 適用開始日≦廃棄予定日
D68: RETURN_SCHD_TM | O68: 返却予定日 | AE68: D | AI68: Y
D69: RETURN_TM | O69: 返却日 | AE69: D | AI69: Y
D70: RETURN_REASON | O70: 返却理由 | AE70: C | AG70: 300 | AI70: Y
D71: MEMO | O71: 備考 | AE71: C | AG71: 300 | AI71: Y
D72: ATACH_INFO_SHEET_FRONT | O72: 添付情報_表図面 | AE72: F | AI72: N
D73: ATACH_INFO_SHEET_BACK | O73: 添付情報_裏図面 | AE73: F | AI73: N
D74: ATACH_INFO_ACT | O74: 添付情報_現物 | AE74: F | AI74: N
D75: ATACH_INFO_ARTWK | O75: 添付情報_版下 | AE75: F | AI75: N
D76: ATACH_INFO_POSI | O76: 添付情報_ポジ | AE76: F | AI76: N
D77: ATACH_INFO_NEGA | O77: 添付情報_ネガ | AE77: F | AI77: N
D78: ATACH_INFO_MO | O78: 添付情報_MO | AE78: F | AI78: N
D79: ATACH_INFO_FD | O79: 添付情報_FD | AE79: F | AI79: N
D80: NEED_DRAFT | O80: 必要物_タタキ | AE80: N | AG80: 9,0 | AI80: N
D81: NEED_MYLAR | O81: 必要物_マイラー | AE81: N | AG81: 9,0 | AI81: N
D82: NEED_GALLE | O82: 必要物_ゲラ刷り | AE82: N | AG82: 9,0 | AI82: N
D83: NEED_PROOF | O83: 必要物_校正 | AE83: N | AG83: 9,0 | AI83: N
D84: NEED_BLUE | O84: 必要物_青焼 | AE84: N | AG84: 9,0 | AI84: N
D85: NEED_COMP | O85: 必要物_カンプ | AE85: N | AG85: 9,0 | AI85: N
D86: NEED_DOCU_PRINT | O86: 必要物_印刷設計書 | AE86: N | AG86: 9,0 | AI86: N
D87: NEED_OTHER_NAME | O87: 必要物_その他名称 | AE87: C | AG87: 20 | AI87: N
D88: NEED_OTHER | O88: 必要物_その他 | AE88: N | AG88: 9,0 | AI88: N
D89: SLO_NO | O89: 受注ＮＯ | AK89: mcframe7側の連携キー
D90: SLO_D_NO | O90: 受注明細ＮＯ | AK90: mcframe7側の連携キー
D91: STTS | O91: ステータス | AE91: N | AI91: N | AK91: 0:未転送、9:mcframe7転送済
D92: MCF7_TRANS_FLG | O92: mcframe7転送FLG | AE92: F | AI92: N | AK92: mcframe7転送を示すフラグ
D93: DEL_FLG | O93: 論理削除ＦＬＧ | AE93: F | AI93: N | AK93: 論理削除を示すフラグ
D94: DEL_USR_ID | O94: 論理削除ユーザＩＤ | AE94: C | AG94: 500 | AI94: Y
D95: DEL_USR_NM | O95: 論理削除ユーザ名 | AE95: C | AG95: 100 | AI95: Y
D96: DEL_TS | O96: 論理削除日時 | AE96: TS | AG96: 0 | AI96: Y
D97: INS_USR_ID | O97: 登録ユーザＩＤ | AE97: C | AG97: 500 | AI97: Y
D98: INS_USR_NM | O98: 登録ユーザ名 | AE98: C | AG98: 100 | AI98: Y
D99: INS_TS | O99: 登録日時 | AE99: TS | AG99: 0 | AI99: Y
D100: INS_FUNC_ID | O100: 登録機能ＩＤ | AE100: C | AG100: 50 | AI100: Y
D101: UPD_CNTR | O101: 更新カウンタ | AE101: N | AG101: 9,0 | AI101: Y
D102: UPD_USR_ID | O102: 更新ユーザＩＤ | AE102: C | AG102: 500 | AI102: Y
D103: UPD_USR_NM | O103: 更新ユーザ名 | AE103: C | AG103: 100 | AI103: Y
...

Sheet 補足資料
A1: =表紙!A54 -> Webシステム | O1: 文書名 | AC1: モジュールID | AJ1: =表紙!$AJ$63 -> MS | AQ1: モジュール名 | AX1: =表紙!$AX$63 -> 見積管理 | BL1: 文書番号 | BU1: Version | CB1: Rev.
O2: =表紙!O64 -> 画面機能 | AC2: サブモジュールID | AJ2: =表紙!$AJ$64 -> MSBB | AQ2: サブモジュール名 | AX2: =表紙!$AX$64 -> Webシステム | BL2: =表紙!$BL$64 -> M7-US-1140 | BU2: =表紙!$BU$64 -> 1.0.0 | CB2: =表紙!$CB$64 -> 3
O3: =RIGHT(CELL("filename",$A$1),LEN(CELL("filename",$A$1))-FIND("]",CELL("filename",$A$1))) -> 補足資料 | AC3: 表題 | AJ3: =表紙!$AJ$65 -> アドオン画面 | AQ3: =表紙!$AQ$65 -> Web版型・木型マスタ
AO5: 概要
C7: マスタの位置づけ
C8: 品目系マスタ
B48: 【説明】
C49: 木型・版型の情報を管理するマスタ
C50: 夜間に一度製造実績の通し数を集計し更新する
